Workbook
Name PaiementsParAn: 'Water Sewer'!$F$6
Name PaiementsParAn: 'INS RET'!$G$6
Name pmtType: 'INS RET'!$F$20
Name pmtType: 'Water Sewer'!$E$16
Name rate: 'INS RET'!$J$6
Name rate: 'Water Sewer'!$I$6
Name roundOpt: 'INS RET'!$F$24
Name roundOpt: 'Water Sewer'!$E$18
Name TauxIntérêt: 'Water Sewer'!$F$3
Name TauxIntérêt: 'INS RET'!$G$3

Sheet Cover Sheet
A1: ='JV III Consolidated'!J1 -> Operating Budget
A2: ='JV III Consolidated'!J2 -> Lincoln JV III
A3: ='JV III Consolidated'!Q1 -> 46023

Sheet Source and Use of Cash
A1: LINCOLN SUB JOINT VENTURE III
A2: Use of Cash Resources for 2026 Budget Defecit
B7: CASH FLOW AFTER INTEREST ON DEBT SERVICE Year 2026 | E7: =+'JV III Consolidated'!Q131 -> 79039.968
B9: ADD: Operating Cash projected 01/01/2026 | E9: =+'JV III Consolidated'!D139 -> 140840.01
B11: LESS: Monthly Contributions to TI Escrow | E11: 0 | F11: Request discontinuence TI contributions starting 1 January 2026
A13: {A} | B13: ADD BACK: TI Improvements and LC Costs | E13: =+'JV III Consolidated'!Q117+'JV III Consolidated'!Q120 -> 33135.755 | F13: To be paid by TI Reserve
C15: Preliminary Cash Defecit | E15: =SUM(E7:E13) -> 253015.73
A17: {B} | C17: Investor Capital Contributions | E17: 250000
C18: Projected Cash Balance, 31 December 2026 | E18: =SUM(E15:E17) -> 503015.73
B22: Summary of TI Allowance Escrow:
C24: 46022 | D24: Projected Balance, | E24: =+'JV III Consolidated'!D148 -> 117089
A25: {A} | B25: LESS: TI Improvements and Lease Costs year 2026 | E25: =-E13 -> -33135.755
C27: Remaining Balance, TI Escrow | E27: =+E24+E25 -> 83953.245
A28: {B} | C28: Request transfer to cover defecit 2026 | F28: Request funds to be used to cover defecit
C29: Balance of TI Escrow 31 Dec 2026 | E29: =+E27+E28 -> 83953.245
B32: Other Options:
B33: 1 | C33: Discuss lower interest rate
C34: May result in some element of Cash Management as previously proposed by Liberty.
C35: (This was LIK Management, Inc determining what excess cash was available to remit to Bank - not
C36: the normal Bank Cash Management). May require more complexities in structuring
C37: at this time.
B39: 2 | C39: Partners' Capital Call
C40: A possible alternative, subject to approval by Investors.
B42: 3 | C42: Potential sale or re-purpose of the Interplex.
B44: 4 | C44: Further Base Rents Reductions
C45: Base Rents for 2027 are further reduced from 2026 by 3 months Solary $36,075 and 9 months
C46: SEOM $118,318 Total of $155K. Reimbursements for CAM and RETax basd on 2024 would
C47: be about $3,300.

Sheet Assumptions
B1: Budget Assumptions | E1: 46023
B2: ='JV III Consolidated'!J2 -> Lincoln JV III
B4: Account Code | C4: Description | D4: Assumption / Notes
B5: Revenues
B6: ='JV III Consolidated'!A10 -> 4230-8501 | C6: =VLOOKUP($B6,'JV III Consolidated'!$A$10:$U$148,3,FALSE) -> Rental Income - In Place | D6: =IFERROR(VLOOKUP($B6,'JV III Consolidated'!$A$10:$U$148,21,FALSE),"") -> Performed Analysis of Rent Roll
B7: ='JV III Consolidated'!A11 -> 4230-8501 | C7: ='JV III Consolidated'!C11 -> Rental Income - New & Renewal | D7: ='JV III Consolidated'!U11 -> As projected by Leasing Manager
B8: ='JV III Consolidated'!A12 -> 4240-8501 | C8: =VLOOKUP($B8,'JV III Consolidated'!$A$10:$U$148,3,FALSE) -> Percentage Rents | D8: =IFERROR(VLOOKUP($B8,'JV III Consolidated'!$A$10:$U$148,21,FALSE),"") -> 0
B9: ='JV III Consolidated'!A13 -> 4990-8501 | C9: =VLOOKUP($B9,'JV III Consolidated'!$A$10:$U$148,3,FALSE) -> Miscellaneous | D9: =IFERROR(VLOOKUP($B9,'JV III Consolidated'!$A$10:$U$148,21,FALSE),"") -> N/A
B10: ='JV III Consolidated'!A14 -> 9190-8501 | C10: =VLOOKUP($B10,'JV III Consolidated'!$A$10:$U$148,3,FALSE) -> Interest Income | D10: =IFERROR(VLOOKUP($B10,'JV III Consolidated'!$A$10:$U$148,21,FALSE),"") -> N/A
B11: Reimbursements | D11: =IFERROR(VLOOKUP($B11,'JV III Consolidated'!$A$10:$U$148,21,FALSE),"")
B12: ='JV III Consolidated'!A18 -> 4710-8502 | C12: =VLOOKUP($B12,'JV III Consolidated'!$A$10:$U$148,3,FALSE) -> Electric | D12: =IFERROR(VLOOKUP($B12,'JV III Consolidated'!$A$10:$U$148,21,FALSE),"") -> Set to occupancy
B13: ='JV III Consolidated'!A19 -> 4910-8502 | C13: =VLOOKUP($B13,'JV III Consolidated'!$A$10:$U$148,3,FALSE) -> Common Area Maintenance | D13: =IFERROR(VLOOKUP($B13,'JV III Consolidated'!$A$10:$U$148,21,FALSE),"") -> By tenant, based on expenses and tenant base year
B14: ='JV III Consolidated'!A20 -> 4920-8502 | C14: =VLOOKUP($B14,'JV III Consolidated'!$A$10:$U$148,3,FALSE) -> Real Estate Taxes | D14: =IFERROR(VLOOKUP($B14,'JV III Consolidated'!$A$10:$U$148,21,FALSE),"") -> By tenant, based on expenses and tenant base year
B15: ='JV III Consolidated'!A21 -> 4930-8502 | C15: =VLOOKUP($B15,'JV III Consolidated'!$A$10:$U$148,3,FALSE) -> Insurance | D15: =IFERROR(VLOOKUP($B15,'JV III Consolidated'!$A$10:$U$148,21,FALSE),"") -> Included in CAM line item
B16: Reimbursable Expenses | D16: =IFERROR(VLOOKUP($B16,'JV III Consolidated'!$A$10:$U$148,21,FALSE),"")
B17: ='JV III Consolidated'!A27 -> 6030-8502 | C17: =VLOOKUP($B17,'JV III Consolidated'!$A$10:$U$148,3,FALSE) -> Maintenance Salaries | D17: =IFERROR(VLOOKUP($B17,'JV III Consolidated'!$A$10:$U$148,21,FALSE),"") -> Based on 2026 Payroll Budget
B18: ='JV III Consolidated'!A29 -> 6120-8502 | C18: =VLOOKUP($B18,'JV III Consolidated'!$A$10:$U$148,3,FALSE) -> Electric | D18: =IFERROR(VLOOKUP($B18,'JV III Consolidated'!$A$10:$U$148,21,FALSE),"") -> 2026 budget as provided by Electric Supplier
B19: ='JV III Consolidated'!A31 -> 6130-8502 | C19: =VLOOKUP($B19,'JV III Consolidated'!$A$10:$U$148,3,FALSE) -> Water & Sewer | D19: =IFERROR(VLOOKUP($B19,'JV III Consolidated'!$A$10:$U$148,21,FALSE),"") -> 2025 Business Plan grown 3%
B20: ='JV III Consolidated'!A36 -> 6220-8502 | C20: =VLOOKUP($B20,'JV III Consolidated'!$A$10:$U$148,3,FALSE) -> Building Maintenance | D20: ='JV III Consolidated'!U35 -> Includes Split systems & Zone lines
B21: ='JV III Consolidated'!A38 -> 6330-8502 | C21: =VLOOKUP($B21,'JV III Consolidated'!$A$10:$U$148,3,FALSE) -> Parking Lot Cleaning | D21: =IFERROR(VLOOKUP($B21,'JV III Consolidated'!$A$10:$U$148,21,FALSE),"") -> Covered by Condo Fee
B22: ='JV III Consolidated'!A43 -> 6360-8502 | C22: =VLOOKUP($B22,'JV III Consolidated'!$A$10:$U$148,3,FALSE) -> Parking Lot Maintenance | D22: =IFERROR(VLOOKUP($B22,'JV III Consolidated'!$A$10:$U$148,21,FALSE),"") -> Covered by Condo Fee
B23: ='JV III Consolidated'!A45 -> 6370-8502 | C23: =VLOOKUP($B23,'JV III Consolidated'!$A$10:$U$148,3,FALSE) -> Snow Removal | D23: =IFERROR(VLOOKUP($B23,'JV III Consolidated'!$A$10:$U$148,21,FALSE),"") -> Covered by Condo Fee
B24: ='JV III Consolidated'!A50 -> 6380-8502 | C24: =VLOOKUP($B24,'JV III Consolidated'!$A$10:$U$148,3,FALSE) -> Landscaping | D24: =IFERROR(VLOOKUP($B24,'JV III Consolidated'!$A$10:$U$148,21,FALSE),"") -> Covered by Condo Fee
B25: ='JV III Consolidated'!A52 -> 6350-8502 | C25: =VLOOKUP($B25,'JV III Consolidated'!$A$10:$U$148,3,FALSE) -> Security | D25: =IFERROR(VLOOKUP($B25,'JV III Consolidated'!$A$10:$U$148,21,FALSE),"") -> Covered by Condo Fee
B26: ='JV III Consolidated'!A54 -> 6610-8502 | C26: =VLOOKUP($B26,'JV III Consolidated'!$A$10:$U$148,3,FALSE) -> Management Fee | D26: =IFERROR(VLOOKUP($B26,'JV III Consolidated'!$A$10:$U$148,21,FALSE),"") -> 4% of projected revenue
B27: ='JV III Consolidated'!A56 -> 6270-8502 | C27: =VLOOKUP($B27,'JV III Consolidated'!$A$10:$U$148,3,FALSE) -> Trash Removal | D27: =IFERROR(VLOOKUP($B27,'JV III Consolidated'!$A$10:$U$148,21,FALSE),"") -> Covered by Condo Fee
B28: ='JV III Consolidated'!A58 -> 6410-8502 | C28: =VLOOKUP($B28,'JV III Consolidated'!$A$10:$U$148,3,FALSE) -> Real Estate Taxes | D28: =IFERROR(VLOOKUP($B28,'JV III Consolidated'!$A$10:$U$148,21,FALSE),"") -> Per assessments and estimated increases
B29: ='JV III Consolidated'!A63 -> 6510-8502 | C29: =VLOOKUP($B29,'JV III Consolidated'!$A$10:$U$148,3,FALSE) -> Insurance | D29: =IFERROR(VLOOKUP($B29,'JV III Consolidated'!$A$10:$U$148,21,FALSE),"") -> 2025 Business Plan grown 3%
B30: ='JV III Consolidated'!A67 -> 6250-8502 | C30: =VLOOKUP($B30,'JV III Consolidated'!$A$10:$U$148,3,FALSE) -> Cleaning & Supplies | D30: =IFERROR(VLOOKUP($B30,'JV III Consolidated'!$A$10:$U$148,21,FALSE),"") -> As per detail above
B31: Non-Reimbursable Expenses | D31: =IFERROR(VLOOKUP($B31,'JV III Consolidated'!$A$10:$U$148,21,FALSE),"")
B32: ='JV III Consolidated'!A75 -> 5210-8501 | C32: =VLOOKUP($B32,'JV III Consolidated'!$A$10:$U$148,3,FALSE) -> Bad Debt | D32: =IFERROR(VLOOKUP($B32,'JV III Consolidated'!$A$10:$U$148,21,FALSE),"") -> 0
B33: ='JV III Consolidated'!A77 -> 6010-8501 | C33: =VLOOKUP($B33,'JV III Consolidated'!$A$10:$U$148,4,FALSE) -> Salaries & Wages | D33: =IFERROR(VLOOKUP($B33,'JV III Consolidated'!$A$10:$U$148,21,FALSE),"") -> Based on 2026 Payroll Budget
B34: ='JV III Consolidated'!A78 -> 6620-8501 | C34: =VLOOKUP($B34,'JV III Consolidated'!$A$10:$U$148,4,FALSE) -> Commissions-Internal Broker | D34: =IFERROR(VLOOKUP($B34,'JV III Consolidated'!$A$10:$U$148,21,FALSE),"") -> Based on projected leasing assumptions
B35: ='JV III Consolidated'!A81 -> 6110-8501 | C35: =VLOOKUP($B35,'JV III Consolidated'!$A$10:$U$148,4,FALSE) -> Gas | D35: =IFERROR(VLOOKUP($B35,'JV III Consolidated'!$A$10:$U$148,21,FALSE),"") -> 0
B36: ='JV III Consolidated'!A82 -> 6120-8501 | C36: =VLOOKUP($B36,'JV III Consolidated'!$A$10:$U$148,4,FALSE) -> Electric | D36: =IFERROR(VLOOKUP($B36,'JV III Consolidated'!$A$10:$U$148,21,FALSE),"") -> 0
B37: ='JV III Consolidated'!A83 -> 6130-8501 | C37: =VLOOKUP($B37,'JV III Consolidated'!$A$10:$U$148,4,FALSE) -> Water & Sewer | D37: =IFERROR(VLOOKUP($B37,'JV III Consolidated'!$A$10:$U$148,21,FALSE),"") -> 0
B38: ='JV III Consolidated'!A88 -> 6220-8501 | C38: =VLOOKUP($B38,'JV III Consolidated'!$A$10:$U$148,3,FALSE) -> Building Maintenance | D38: =IFERROR(VLOOKUP($B38,'JV III Consolidated'!$A$10:$U$148,21,FALSE),"") -> 2025 Business Plan grown 3%
B39: ='JV III Consolidated'!A90 -> 6610-8501 | C39: =VLOOKUP($B39,'JV III Consolidated'!$A$10:$U$148,3,FALSE) -> Management fee | D39: =IFERROR(VLOOKUP($B39,'JV III Consolidated'!$A$10:$U$148,21,FALSE),"") -> 0
B40: ='JV III Consolidated'!A92 -> 7110-8501 | C40: =VLOOKUP($B40,'JV III Consolidated'!$A$10:$U$148,3,FALSE) -> Marketing | D40: =IFERROR(VLOOKUP($B40,'JV III Consolidated'!$A$10:$U$148,21,FALSE),"") -> 2025 Business Plan grown 3%
B41: ='JV III Consolidated'!A94 -> 8210-8501 | C41: =VLOOKUP($B41,'JV III Consolidated'!$A$10:$U$148,3,FALSE) -> Business Taxes | D41: =IFERROR(VLOOKUP($B41,'JV III Consolidated'!$A$10:$U$148,21,FALSE),"") -> Based on tax rate and revenues
B42: ='JV III Consolidated'!A96 -> 8310-8501 | C42: =VLOOKUP($B42,'JV III Consolidated'!$A$10:$U$148,3,FALSE) -> Legal & Accounting | D42: =IFERROR(VLOOKUP($B42,'JV III Consolidated'!$A$10:$U$148,21,FALSE),"") -> 0
B43: ='JV III Consolidated'!A98 -> 8190-8501 | C43: =VLOOKUP($B43,'JV III Consolidated'!$A$10:$U$148,4,FALSE) -> Bank Fees | D43: =IFERROR(VLOOKUP($B43,'JV III Consolidated'!$A$10:$U$148,21,FALSE),"") -> 2025 Business Plan grown 3%
B44: ='JV III Consolidated'!A99 -> 8930-8501 | C44: =VLOOKUP($B44,'JV III Consolidated'!$A$10:$U$148,4,FALSE) -> Office Supplies | D44: =IFERROR(VLOOKUP($B44,'JV III Consolidated'!$A$10:$U$148,21,FALSE),"") -> 0
B45: ='JV III Consolidated'!A100 -> 8950-8501 | C45: =VLOOKUP($B45,'JV III Consolidated'!$A$10:$U$148,4,FALSE) -> Postage | D45: =IFERROR(VLOOKUP($B45,'JV III Consolidated'!$A$10:$U$148,21,FALSE),"") -> 0
B46: ='JV III Consolidated'!A101 -> 8990-8501 | C46: =VLOOKUP($B46,'JV III Consolidated'!$A$10:$U$148,4,FALSE) -> Other G&A Expense | D46: =IFERROR(VLOOKUP($B46,'JV III Consolidated'!$A$10:$U$148,21,FALSE),"") -> 2025 Business Plan grown 3%
B47: ='JV III Consolidated'!A102 -> 8990-9800 | C47: =VLOOKUP($B47,'JV III Consolidated'!$A$10:$U$148,4,FALSE) -> Other G&A-allocated from LIK | D47: =IFERROR(VLOOKUP($B47,'JV III Consolidated'!$A$10:$U$148,21,FALSE),"") -> 2025 Business Plan grown 3%
D48: =IFERROR(VLOOKUP($B48,'JV III Consolidated'!$A$10:$U$148,21,FALSE),"")
B49: ='JV III Consolidated'!A111 -> 1420-0000 | C49: =VLOOKUP($B49,'JV III Consolidated'!$A$10:$U$148,4,FALSE) -> Land Improvements | D49: =IFERROR(VLOOKUP($B49,'JV III Consolidated'!$A$10:$U$148,21,FALSE),"") -> 0
B50: ='JV III Consolidated'!A112 -> 1430-0000 | C50: =VLOOKUP($B50,'JV III Consolidated'!$A$10:$U$148,4,FALSE) -> Buildings | D50: =IFERROR(VLOOKUP($B50,'JV III Consolidated'!$A$10:$U$148,21,FALSE),"") -> 0
B51: ='JV III Consolidated'!A113 -> 1450-0000 | C51: =VLOOKUP($B51,'JV III Consolidated'!$A$10:$U$148,4,FALSE) -> Equipment | D51: =IFERROR(VLOOKUP($B51,'JV III Consolidated'!$A$10:$U$148,21,FALSE),"") -> 0
B52: ='JV III Consolidated'!A114 -> 1980-8501 | C52: =VLOOKUP($B52,'JV III Consolidated'!$A$10:$U$148,4,FALSE) -> Capital Improvements | D52: =IFERROR(VLOOKUP($B52,'JV III Consolidated'!$A$10:$U$148,21,FALSE),"") -> 0
B53: ='JV III Consolidated'!A117 -> 1440-0000 | C53: =VLOOKUP($B53,'JV III Consolidated'!$A$10:$U$148,3,FALSE) -> Tenant Improvements | D53: =IFERROR(VLOOKUP($B53,'JV III Consolidated'!$A$10:$U$148,21,FALSE),"") -> Based on projected leasing assumptions
B54: ='JV III Consolidated'!A119 -> 1940-8501 | C54: =VLOOKUP($B54,'JV III Consolidated'!$A$10:$U$148,4,FALSE) -> Deferred Marketing | D54: =IFERROR(VLOOKUP($B54,'JV III Consolidated'!$A$10:$U$148,21,FALSE),"") -> 0
B55: ='JV III Consolidated'!A120 -> 1940-8501 | C55: =VLOOKUP($B55,'JV III Consolidated'!$A$10:$U$148,4,FALSE) -> Deferred Marketing | D55: =IFERROR(VLOOKUP($B55,'JV III Consolidated'!$A$10:$U$148,21,FALSE),"") -> 0
B56: ='JV III Consolidated'!A126 -> 9210-8501 | C56: =VLOOKUP($B56,'JV III Consolidated'!$A$10:$U$148,3,FALSE) -> Interest | D56: =IFERROR(VLOOKUP($B56,'JV III Consolidated'!$A$10:$U$148,21,FALSE),"") -> 0
B57: ='JV III Consolidated'!A127 -> 2740-8501 | C57: =VLOOKUP($B57,'JV III Consolidated'!$A$10:$U$148,3,FALSE) -> Mortgage Amortization | D57: =IFERROR(VLOOKUP($B57,'JV III Consolidated'!$A$10:$U$148,21,FALSE),"") -> 0
B58: ='JV III Consolidated'!A128 -> 2740-0000 | C58: =VLOOKUP($B58,'JV III Consolidated'!$A$10:$U$148,3,FALSE) -> Loan Proceeds | D58: =IFERROR(VLOOKUP($B58,'JV III Consolidated'!$A$10:$U$148,21,FALSE),"") -> 0

Sheet JV III Consolidated
B1: Consolidated - 1, 2, 4 | J1: Operating Budget | Q1: =DATE(2026,1,1) -> 46023
J2: Lincoln JV III
Q3: =Q1 -> 46023 | R3: 7/2025 Reprojections
B4: ='Renew & Vac - Rent, TI, LC'!A6+'Renew & Vac - Rent, TI, LC'!A28+'Renew & Vac - Rent, TI, LC'!A50 -> 139635 | E4: Jan | F4: Feb | G4: Mar | H4: Apr | I4: May | J4: Jun | K4: Jul | L4: Aug | M4: Sep | N4: Oct | O4: Nov | P4: Dec | Q4: Total | R4: Total | S4: Var. | T4: Input | U4: Notes
D6: Occupancy % | E6: =SUM('361'!E7,'362'!E7,'364'!E7)/$B$4 -> 0.61410146 | F6: =SUM('361'!F7,'362'!F7,'364'!F7)/$B$4 -> 0.61410146 | G6: =SUM('361'!G7,'362'!G7,'364'!G7)/$B$4 -> 0.61410146 | H6: =SUM('361'!H7,'362'!H7,'364'!H7)/$B$4 -> 0.56112642 | I6: =SUM('361'!I7,'362'!I7,'364'!I7)/$B$4 -> 0.56112642 | J6: =SUM('361'!J7,'362'!J7,'364'!J7)/$B$4 -> 0.56112642 | K6: =SUM('361'!K7,'362'!K7,'364'!K7)/$B$4 -> 0.56112642 | L6: =SUM('361'!L7,'362'!L7,'364'!L7)/$B$4 -> 0.56112642 | ... P6: =SUM('361'!P7,'362'!P7,'364'!P7)/$B$4 -> 0.4757651
B8: Revenues
A10: 4230-8501 | C10: Rental Income - In Place | E10: =+'361'!E10+'362'!E10+'364'!E10 -> 117311.49 | F10: =+'361'!F10+'362'!F10+'364'!F10 -> 113108.16 | G10: =+'361'!G10+'362'!G10+'364'!G10 -> 108595.99 | H10: =+'361'!H10+'362'!H10+'364'!H10 -> 90365.9 | I10: =+'361'!I10+'362'!I10+'364'!I10 -> 86891.73 | J10: =+'361'!J10+'362'!J10+'364'!J10 -> 78990.23 | K10: =+'361'!K10+'362'!K10+'364'!K10 -> 67639.43 | L10: =+'361'!L10+'362'!L10+'364'!L10 -> 71744.97 | ... P10: =+'361'!P10+'362'!P10+'364'!P10 -> 60494.86 | Q10: =SUM(E10:P10) -> 979211.43 | R10: 1503977.4 | S10: =(Q10+Q11)/R10-1 -> -0.054095379 | U10: Performed Analysis of Rent Roll
A11: 4230-8501 | C11: Rental Income - New & Renewal | E11: =+'361'!E11+'362'!E11+'364'!E11 -> 16352.295 | F11: =+'361'!F11+'362'!F11+'364'!F11 -> 20555.628 | G11: =+'361'!G11+'362'!G11+'364'!G11 -> 25067.795 | H11: =+'361'!H11+'362'!H11+'364'!H11 -> 29164.495 | I11: =+'361'!I11+'362'!I11+'364'!I11 -> 32720.328 | J11: =+'361'!J11+'362'!J11+'364'!J11 -> 40695.287 | K11: =+'361'!K11+'362'!K11+'364'!K11 -> 44994.287 | L11: =+'361'!L11+'362'!L11+'364'!L11 -> 46245.287 | ... P11: =+'361'!P11+'362'!P11+'364'!P11 -> 47170.917 | Q11: =SUM(E11:P11) -> 443407.77 | U11: As projected by Leasing Manager
A12: 4240-8501 | C12: Percentage Rents | E12: =+'361'!E12+'362'!E12+'364'!E12 -> 0 | F12: =+'361'!F12+'362'!F12+'364'!F12 -> 0 | G12: =+'361'!G12+'362'!G12+'364'!G12 -> 0 | H12: =+'361'!H12+'362'!H12+'364'!H12 -> 0 | I12: =+'361'!I12+'362'!I12+'364'!I12 -> 0 | J12: =+'361'!J12+'362'!J12+'364'!J12 -> 0 | K12: =+'361'!K12+'362'!K12+'364'!K12 -> 0 | L12: =+'361'!L12+'362'!L12+'364'!L12 -> 0 | ... P12: =+'361'!P12+'362'!P12+'364'!P12 -> 0 | Q12: =SUM(E12:P12) -> 0 | S12: =Q12/R12-1 -> #DIV/0!
A13: 4990-8501 | C13: Miscellaneous | E13: =+'361'!E13+'362'!E13+'364'!E13 -> 0 | F13: =+'361'!F13+'362'!F13+'364'!F13 -> 0 | G13: =+'361'!G13+'362'!G13+'364'!G13 -> 0 | H13: =+'361'!H13+'362'!H13+'364'!H13 -> 0 | I13: =+'361'!I13+'362'!I13+'364'!I13 -> 0 | J13: =+'361'!J13+'362'!J13+'364'!J13 -> 0 | K13: =+'361'!K13+'362'!K13+'364'!K13 -> 0 | L13: =+'361'!L13+'362'!L13+'364'!L13 -> 0 | ... P13: =+'361'!P13+'362'!P13+'364'!P13 -> 0 | Q13: =SUM(E13:P13) -> 0 | R13: 0 | S13: =IFERROR(Q13/R13-1,"") | U13: N/A
A14: 9190-8501 | C14: Interest Income | E14: =+'361'!E14+'362'!E14+'364'!E14 -> 0 | F14: =+'361'!F14+'362'!F14+'364'!F14 -> 0 | G14: =+'361'!G14+'362'!G14+'364'!G14 -> 0 | H14: =+'361'!H14+'362'!H14+'364'!H14 -> 0 | I14: =+'361'!I14+'362'!I14+'364'!I14 -> 0 | J14: =+'361'!J14+'362'!J14+'364'!J14 -> 0 | K14: =+'361'!K14+'362'!K14+'364'!K14 -> 0 | L14: =+'361'!L14+'362'!L14+'364'!L14 -> 0 | ... P14: =+'361'!P14+'362'!P14+'364'!P14 -> 0 | Q14: =SUM(E14:P14) -> 0 | R14: 0 | U14: N/A
D15: Total Rental and Other: | E15: =SUM(E10:E14) -> 133663.78 | F15: =SUM(F10:F14) -> 133663.79 | G15: =SUM(G10:G14) -> 133663.78 | H15: =SUM(H10:H14) -> 119530.39 | I15: =SUM(I10:I14) -> 119612.06 | J15: =SUM(J10:J14) -> 119685.52 | K15: =SUM(K10:K14) -> 112633.72 | L15: =SUM(L10:L14) -> 117990.26 | ... R15: =SUM(R10:R14) -> 1503977.4 | S15: =Q15/R15-1 -> -0.054095379
B17: Reimbursements
A18: 4710-8502 | C18: Electric | E18: =+'361'!E18+'362'!E18+'364'!E18 -> 10302.184 | F18: =+'361'!F18+'362'!F18+'364'!F18 -> 9109.9855 | G18: =+'361'!G18+'362'!G18+'364'!G18 -> 7359.7405 | H18: =+'361'!H18+'362'!H18+'364'!H18 -> 4562.5296 | I18: =+'361'!I18+'362'!I18+'364'!I18 -> 4057.6656 | J18: =+'361'!J18+'362'!J18+'364'!J18 -> 4394.6565 | K18: =+'361'!K18+'362'!K18+'364'!K18 -> 5202.816 | L18: =+'361'!L18+'362'!L18+'364'!L18 -> 5187.1248 | ... P18: =+'361'!P18+'362'!P18+'364'!P18 -> 7747.5708 | Q18: =SUM(E18:P18) -> 70761.162 | R18: 82857.27 | S18: =Q18/R18-1 -> -0.14598728 | U18: Set to occupancy
A19: 4910-8502 | C19: Common Area Maintenance | E19: =+'361'!E19+'362'!E19+'364'!E19 -> 5070 | F19: =+'361'!F19+'362'!F19+'364'!F19 -> 5070 | G19: =+'361'!G19+'362'!G19+'364'!G19 -> 5070 | H19: =+'361'!H19+'362'!H19+'364'!H19 -> 5070 | I19: =+'361'!I19+'362'!I19+'364'!I19 -> 5070 | J19: =+'361'!J19+'362'!J19+'364'!J19 -> 5070 | K19: =+'361'!K19+'362'!K19+'364'!K19 -> 5070 | L19: =+'361'!L19+'362'!L19+'364'!L19 -> 5070 | ... P19: =+'361'!P19+'362'!P19+'364'!P19 -> 5070 | Q19: =SUM(E19:P19) -> 60840 | R19: 54578 | S19: =Q19/R19-1 -> 0.11473487 | U19: By tenant, based on expenses and tenant base year
A20: 4920-8502 | C20: Real Estate Taxes | E20: =+'361'!E20+'362'!E20+'364'!E20 -> 560 | F20: =+'361'!F20+'362'!F20+'364'!F20 -> 560 | G20: =+'361'!G20+'362'!G20+'364'!G20 -> 560 | H20: =+'361'!H20+'362'!H20+'364'!H20 -> 560 | I20: =+'361'!I20+'362'!I20+'364'!I20 -> 560 | J20: =+'361'!J20+'362'!J20+'364'!J20 -> 560 | K20: =+'361'!K20+'362'!K20+'364'!K20 -> 560 | L20: =+'361'!L20+'362'!L20+'364'!L20 -> 560 | ... P20: =+'361'!P20+'362'!P20+'364'!P20 -> 560 | Q20: =SUM(E20:P20) -> 6720 | R20: 11186 | S20: =Q20/R20-1 -> -0.39924906 | U20: By tenant, based on expenses and tenant base year
A21: 4930-8502 | C21: Insurance | E21: =+'361'!E21+'362'!E21+'364'!E21 -> 0 | F21: =+'361'!F21+'362'!F21+'364'!F21 -> 0 | G21: =+'361'!G21+'362'!G21+'364'!G21 -> 0 | H21: =+'361'!H21+'362'!H21+'364'!H21 -> 0 | I21: =+'361'!I21+'362'!I21+'364'!I21 -> 0 | J21: =+'361'!J21+'362'!J21+'364'!J21 -> 0 | K21: =+'361'!K21+'362'!K21+'364'!K21 -> 0 | L21: =+'361'!L21+'362'!L21+'364'!L21 -> 0 | ... P21: =+'361'!P21+'362'!P21+'364'!P21 -> 0 | Q21: =SUM(E21:P21) -> 0 | R21: 0 | S21: =IFERROR(Q21/R21-1,"") | U21: Included in CAM line item
D22: Total Reimbursements: | E22: =SUM(E18:E21) -> 15932.184 | F22: =SUM(F18:F21) -> 14739.985 | G22: =SUM(G18:G21) -> 12989.74 | H22: =SUM(H18:H21) -> 10192.53 | I22: =SUM(I18:I21) -> 9687.6656 | J22: =SUM(J18:J21) -> 10024.656 | K22: =SUM(K18:K21) -> 10832.816 | L22: =SUM(L18:L21) -> 10817.125 | ... R22: =SUM(R18:R21) -> 148621.27 | S22: =Q22/R22-1 -> -0.069304399
B24: TOTAL REVENUES | E24: =+E15+E22 -> 149595.97 | F24: =+F15+F22 -> 148403.77 | G24: =+G15+G22 -> 146653.53 | H24: =+H15+H22 -> 129722.92 | I24: =+I15+I22 -> 129299.72 | J24: =+J15+J22 -> 129710.17 | K24: =+K15+K22 -> 123466.53 | L24: =+L15+L22 -> 128807.38 | ... R24: =+R15+R22 -> 1652598.7 | S24: =Q24/R24-1 -> -0.055463154
Q25: =+'361'!Q24+'362'!Q24+'364'!Q24 -> 1560940.4
B26: Reimbursable Expenses
A27: 6030-8502 | C27: Maintenance Salaries | E27: =+'361'!E27+'362'!E27+'364'!E27 -> 3931.6667 | F27: =+'361'!F27+'362'!F27+'364'!F27 -> 3931.6667 | G27: =+'361'!G27+'362'!G27+'364'!G27 -> 3931.6667 | H27: =+'361'!H27+'362'!H27+'364'!H27 -> 3931.6667 | I27: =+'361'!I27+'362'!I27+'364'!I27 -> 3931.6667 | J27: =+'361'!J27+'362'!J27+'364'!J27 -> 3931.6667 | K27: =+'361'!K27+'362'!K27+'364'!K27 -> 3931.6667 | L27: =+'361'!L27+'362'!L27+'364'!L27 -> 3931.6667 | ... P27: =+'361'!P27+'362'!P27+'364'!P27 -> 3931.6667 | Q27: =SUM(E27:P27) -> 47180 | R27: 30778.77 | S27: =Q27/R27-1 -> 0.53287477 | U27: Based on 2026 Payroll Budget
A29: 6120-8502 | C29: Electric | E29: =+'361'!E29+'362'!E29+'364'!E29 -> 17256 | F29: =+'361'!F29+'362'!F29+'364'!F29 -> 15367 | G29: =+'361'!G29+'362'!G29+'364'!G29 -> 12325 | H29: =+'361'!H29+'362'!H29+'364'!H29 -> 8167 | I29: =+'361'!I29+'362'!I29+'364'!I29 -> 7297 | J29: =+'361'!J29+'362'!J29+'364'!J29 -> 7928 | K29: =+'361'!K29+'362'!K29+'364'!K29 -> 9433 | L29: =+'361'!L29+'362'!L29+'364'!L29 -> 9482 | ... P29: =+'361'!P29+'362'!P29+'364'!P29 -> 15544 | Q29: =SUM(E29:P29) -> 127883 | R29: 125357.78 | S29: =Q29/R29-1 -> 0.020144103 | U29: 2026 budget as provided by Electric Supplier
A31: 6130-8502 | C31: Water & Sewer | E31: =+'361'!E31+'362'!E31+'364'!E31 -> 4165.48 | F31: =+'361'!F31+'362'!F31+'364'!F31 -> 4018.19 | G31: =+'361'!G31+'362'!G31+'364'!G31 -> 4425.04 | H31: =+'361'!H31+'362'!H31+'364'!H31 -> 2943.9 | I31: =+'361'!I31+'362'!I31+'364'!I31 -> 3179.77 | J31: =+'361'!J31+'362'!J31+'364'!J31 -> 3185.95 | K31: =+'361'!K31+'362'!K31+'364'!K31 -> 3448.6 | L31: =+'361'!L31+'362'!L31+'364'!L31 -> 3597.95 | ... P31: =+'361'!P31+'362'!P31+'364'!P31 -> 4417.83 | Q31: =SUM(E31:P31) -> 44542.21 | R31: 43939.16 | S31: =Q31/R31-1 -> 0.013724659 | U31: 2025 Business Plan grown 3%
D33: Building Maint.-Contractual | E33: =+'361'!E33+'362'!E33+'364'!E33 -> 5657 | F33: =+'361'!F33+'362'!F33+'364'!F33 -> 4982 | G33: =+'361'!G33+'362'!G33+'364'!G33 -> 3642 | H33: =+'361'!H33+'362'!H33+'364'!H33 -> 8029 | I33: =+'361'!I33+'362'!I33+'364'!I33 -> 4332 | J33: =+'361'!J33+'362'!J33+'364'!J33 -> 2832 | K33: =+'361'!K33+'362'!K33+'364'!K33 -> 6307 | L33: =+'361'!L33+'362'!L33+'364'!L33 -> 4332 | ... P33: =+'361'!P33+'362'!P33+'364'!P33 -> 2832 | Q33: =SUM(E33:P33) -> 58948
D34: Building Maint.-Recurring | E34: =+'361'!E34+'362'!E34+'364'!E34 -> 6345 | F34: =+'361'!F34+'362'!F34+'364'!F34 -> 6270 | G34: =+'361'!G34+'362'!G34+'364'!G34 -> 5445 | H34: =+'361'!H34+'362'!H34+'364'!H34 -> 6645 | I34: =+'361'!I34+'362'!I34+'364'!I34 -> 15480 | J34: =+'361'!J34+'362'!J34+'364'!J34 -> 5345 | K34: =+'361'!K34+'362'!K34+'364'!K34 -> 6890 | L34: =+'361'!L34+'362'!L34+'364'!L34 -> 5070 | ... P34: =+'361'!P34+'362'!P34+'364'!P34 -> 5170 | Q34: =SUM(E34:P34) -> 85200
D35: Building Maint.-Big Projects | E35: =+'361'!E35+'362'!E35+'364'!E35 -> 0 | F35: =+'361'!F35+'362'!F35+'364'!F35 -> 4635 | G35: =+'361'!G35+'362'!G35+'364'!G35 -> 0 | H35: =+'361'!H35+'362'!H35+'364'!H35 -> 0 | I35: =+'361'!I35+'362'!I35+'364'!I35 -> 0 | J35: =+'361'!J35+'362'!J35+'364'!J35 -> 46350 | K35: =+'361'!K35+'362'!K35+'364'!K35 -> 0 | L35: =+'361'!L35+'362'!L35+'364'!L35 -> 0 | ... P35: =+'361'!P35+'362'!P35+'364'!P35 -> 0 | Q35: =SUM(E35:P35) -> 55620 | U35: Includes Split systems & Zone lines
A36: 6220-8502 | C36: Building Maintenance | E36: =SUM(E33:E35) -> 12002 | F36: =SUM(F33:F35) -> 15887 | G36: =SUM(G33:G35) -> 9087 | H36: =SUM(H33:H35) -> 14674 | I36: =SUM(I33:I35) -> 19812 | J36: =SUM(J33:J35) -> 54527 | K36: =SUM(K33:K35) -> 13197 | L36: =SUM(L33:L35) -> 9402 | ... Q36: =SUM(Q33:Q35) -> 199768 | R36: 124189.81 | S36: =Q36/R36-1 -> 0.60856998
A38: 6330-8502 | B38: (SC) | C38: Parking Lot Cleaning | E38: =+'361'!E38+'362'!E38+'364'!E38 -> 0 | F38: =+'361'!F38+'362'!F38+'364'!F38 -> 0 | G38: =+'361'!G38+'362'!G38+'364'!G38 -> 0 | H38: =+'361'!H38+'362'!H38+'364'!H38 -> 0 | I38: =+'361'!I38+'362'!I38+'364'!I38 -> 0 | J38: =+'361'!J38+'362'!J38+'364'!J38 -> 0 | K38: =+'361'!K38+'362'!K38+'364'!K38 -> 0 | L38: =+'361'!L38+'362'!L38+'364'!L38 -> 0 | ... P38: =+'361'!P38+'362'!P38+'364'!P38 -> 0 | Q38: =SUM(E38:P38) -> 0 | U38: Covered by Condo Fee
D40: Parking Lot Maint.-Contractual | E40: =+'361'!E40+'362'!E40+'364'!E40 -> 0 | F40: =+'361'!F40+'362'!F40+'364'!F40 -> 0 | G40: =+'361'!G40+'362'!G40+'364'!G40 -> 0 | H40: =+'361'!H40+'362'!H40+'364'!H40 -> 0 | I40: =+'361'!I40+'362'!I40+'364'!I40 -> 0 | J40: =+'361'!J40+'362'!J40+'364'!J40 -> 0 | K40: =+'361'!K40+'362'!K40+'364'!K40 -> 0 | L40: =+'361'!L40+'362'!L40+'364'!L40 -> 0 | ... P40: =+'361'!P40+'362'!P40+'364'!P40 -> 0 | Q40: =SUM(E40:P40) -> 0
D41: Parking Lot Maint.-Recurring | E41: =+'361'!E41+'362'!E41+'364'!E41 -> 0 | F41: =+'361'!F41+'362'!F41+'364'!F41 -> 0 | G41: =+'361'!G41+'362'!G41+'364'!G41 -> 0 | H41: =+'361'!H41+'362'!H41+'364'!H41 -> 0 | I41: =+'361'!I41+'362'!I41+'364'!I41 -> 0 | J41: =+'361'!J41+'362'!J41+'364'!J41 -> 0 | K41: =+'361'!K41+'362'!K41+'364'!K41 -> 0 | L41: =+'361'!L41+'362'!L41+'364'!L41 -> 0 | ... P41: =+'361'!P41+'362'!P41+'364'!P41 -> 0 | Q41: =SUM(E41:P41) -> 0
D42: Parking Lot Maint.-Big Projects | E42: =+'361'!E42+'362'!E42+'364'!E42 -> 0 | F42: =+'361'!F42+'362'!F42+'364'!F42 -> 0 | G42: =+'361'!G42+'362'!G42+'364'!G42 -> 0 | H42: =+'361'!H42+'362'!H42+'364'!H42 -> 0 | I42: =+'361'!I42+'362'!I42+'364'!I42 -> 0 | J42: =+'361'!J42+'362'!J42+'364'!J42 -> 0 | K42: =+'361'!K42+'362'!K42+'364'!K42 -> 0 | L42: =+'361'!L42+'362'!L42+'364'!L42 -> 0 | ... P42: =+'361'!P42+'362'!P42+'364'!P42 -> 0 | Q42: =SUM(E42:P42) -> 0
A43: 6360-8502 | C43: Parking Lot Maintenance | E43: =SUM(E40:E42) -> 0 | F43: =SUM(F40:F42) -> 0 | G43: =SUM(G40:G42) -> 0 | H43: =SUM(H40:H42) -> 0 | I43: =SUM(I40:I42) -> 0 | J43: =SUM(J40:J42) -> 0 | K43: =SUM(K40:K42) -> 0 | L43: =SUM(L40:L42) -> 0 | ... Q43: =SUM(Q40:Q42) -> 0 | R43: 646.79 | S43: =Q43/R43-1 -> -1 | U43: Covered by Condo Fee
A45: 6370-8502 | C45: Snow Removal | E45: =+'361'!E45+'362'!E45+'364'!E45 -> 0 | F45: =+'361'!F45+'362'!F45+'364'!F45 -> 0 | G45: =+'361'!G45+'362'!G45+'364'!G45 -> 0 | H45: =+'361'!H45+'362'!H45+'364'!H45 -> 0 | I45: =+'361'!I45+'362'!I45+'364'!I45 -> 0 | J45: =+'361'!J45+'362'!J45+'364'!J45 -> 0 | K45: =+'361'!K45+'362'!K45+'364'!K45 -> 0 | L45: =+'361'!L45+'362'!L45+'364'!L45 -> 0 | ... P45: =+'361'!P45+'362'!P45+'364'!P45 -> 0 | Q45: =SUM(E45:P45) -> 0 | R45: 0 | S45: =Q45/R45-1 -> #DIV/0! | U45: Covered by Condo Fee
D47: Landscaping-Contractual | E47: =+'361'!E47+'362'!E47+'364'!E47 -> 0 | F47: =+'361'!F47+'362'!F47+'364'!F47 -> 0 | G47: =+'361'!G47+'362'!G47+'364'!G47 -> 0 | H47: =+'361'!H47+'362'!H47+'364'!H47 -> 0 | I47: =+'361'!I47+'362'!I47+'364'!I47 -> 0 | J47: =+'361'!J47+'362'!J47+'364'!J47 -> 0 | K47: =+'361'!K47+'362'!K47+'364'!K47 -> 0 | L47: =+'361'!L47+'362'!L47+'364'!L47 -> 0 | ... P47: =+'361'!P47+'362'!P47+'364'!P47 -> 0 | Q47: =SUM(E47:P47) -> 0
D48: Landscaping-Recurring | E48: =+'361'!E48+'362'!E48+'364'!E48 -> 0 | F48: =+'361'!F48+'362'!F48+'364'!F48 -> 0 | G48: =+'361'!G48+'362'!G48+'364'!G48 -> 0 | H48: =+'361'!H48+'362'!H48+'364'!H48 -> 0 | I48: =+'361'!I48+'362'!I48+'364'!I48 -> 0 | J48: =+'361'!J48+'362'!J48+'364'!J48 -> 0 | K48: =+'361'!K48+'362'!K48+'364'!K48 -> 0 | L48: =+'361'!L48+'362'!L48+'364'!L48 -> 0 | ... P48: =+'361'!P48+'362'!P48+'364'!P48 -> 0 | Q48: =SUM(E48:P48) -> 0
D49: Landscaping-Big Projects | E49: =+'361'!E49+'362'!E49+'364'!E49 -> 0 | F49: =+'361'!F49+'362'!F49+'364'!F49 -> 0 | G49: =+'361'!G49+'362'!G49+'364'!G49 -> 0 | H49: =+'361'!H49+'362'!H49+'364'!H49 -> 0 | I49: =+'361'!I49+'362'!I49+'364'!I49 -> 0 | J49: =+'361'!J49+'362'!J49+'364'!J49 -> 0 | K49: =+'361'!K49+'362'!K49+'364'!K49 -> 0 | L49: =+'361'!L49+'362'!L49+'364'!L49 -> 0 | ... P49: =+'361'!P49+'362'!P49+'364'!P49 -> 0 | Q49: =SUM(E49:P49) -> 0
A50: 6380-8502 | C50: Landscaping | E50: =SUM(E47:E49) -> 0 | F50: =SUM(F47:F49) -> 0 | G50: =SUM(G47:G49) -> 0 | H50: =SUM(H47:H49) -> 0 | I50: =SUM(I47:I49) -> 0 | J50: =SUM(J47:J49) -> 0 | K50: =SUM(K47:K49) -> 0 | L50: =SUM(L47:L49) -> 0 | ... Q50: =SUM(Q47:Q49) -> 0 | R50: 450 | S50: =Q50/R50-1 -> -1 | U50: Covered by Condo Fee
A52: 6350-8502 | C52: Security | E52: =+'361'!E52+'362'!E52+'364'!E52 -> 0 | F52: =+'361'!F52+'362'!F52+'364'!F52 -> 0 | G52: =+'361'!G52+'362'!G52+'364'!G52 -> 0 | H52: =+'361'!H52+'362'!H52+'364'!H52 -> 0 | I52: =+'361'!I52+'362'!I52+'364'!I52 -> 0 | J52: =+'361'!J52+'362'!J52+'364'!J52 -> 0 | K52: =+'361'!K52+'362'!K52+'364'!K52 -> 0 | L52: =+'361'!L52+'362'!L52+'364'!L52 -> 0 | ... P52: =+'361'!P52+'362'!P52+'364'!P52 -> 0 | Q52: =SUM(E52:P52) -> 0 | S52: =Q52/R52-1 -> #DIV/0! | U52: Covered by Condo Fee
A54: 6610-8502 | B54: (BP) | C54: Management Fee | E54: =+'361'!E54+'362'!E54+'364'!E54 -> 5984 | F54: =+'361'!F54+'362'!F54+'364'!F54 -> 5936 | G54: =+'361'!G54+'362'!G54+'364'!G54 -> 5866 | H54: =+'361'!H54+'362'!H54+'364'!H54 -> 5188 | I54: =+'361'!I54+'362'!I54+'364'!I54 -> 5172 | J54: =+'361'!J54+'362'!J54+'364'!J54 -> 5188 | K54: =+'361'!K54+'362'!K54+'364'!K54 -> 4939 | L54: =+'361'!L54+'362'!L54+'364'!L54 -> 5153 | ... P54: =+'361'!P54+'362'!P54+'364'!P54 -> 4842 | Q54: =SUM(E54:P54) -> 62436 | R54: 66207.36 | S54: =Q54/R54-1 -> -0.056962851 | U54: 4% of projected revenue
A56: 6270-8502 | C56: Trash Removal | E56: =+'361'!E56+'362'!E56+'364'!E56 -> 0 | F56: =+'361'!F56+'362'!F56+'364'!F56 -> 0 | G56: =+'361'!G56+'362'!G56+'364'!G56 -> 0 | H56: =+'361'!H56+'362'!H56+'364'!H56 -> 0 | I56: =+'361'!I56+'362'!I56+'364'!I56 -> 0 | J56: =+'361'!J56+'362'!J56+'364'!J56 -> 0 | K56: =+'361'!K56+'362'!K56+'364'!K56 -> 0 | L56: =+'361'!L56+'362'!L56+'364'!L56 -> 0 | ... P56: =+'361'!P56+'362'!P56+'364'!P56 -> 0 | Q56: =SUM(E56:P56) -> 0 | R56: 497 | S56: =Q56/R56-1 -> -1 | U56: Covered by Condo Fee
A58: 6410-8502 | C58: Real Estate Taxes | E58: =+'361'!E58+'362'!E58+'364'!E58 -> 11425.059 | F58: =+'361'!F58+'362'!F58+'364'!F58 -> 11425.059 | G58: =+'361'!G58+'362'!G58+'364'!G58 -> 11425.059 | H58: =+'361'!H58+'362'!H58+'364'!H58 -> 11425.059 | I58: =+'361'!I58+'362'!I58+'364'!I58 -> 11425.059 | J58: =+'361'!J58+'362'!J58+'364'!J58 -> 11425.059 | K58: =+'361'!K58+'362'!K58+'364'!K58 -> 11425.059 | L58: =+'361'!L58+'362'!L58+'364'!L58 -> 11425.059 | ... P58: =+'361'!P58+'362'!P58+'364'!P58 -> 11425.059 | Q58: =SUM(E58:P58) -> 137100.7 | R58: 337165.74 | S58: =Q58/R58-1 -> -0.59337297 | U58: Per assessments and estimated increases
D60: Insurance-Liability | E60: =+'361'!E60+'362'!E60+'364'!E60 -> 3800 | F60: =+'361'!F60+'362'!F60+'364'!F60 -> 3800 | G60: =+'361'!G60+'362'!G60+'364'!G60 -> 3800 | H60: =+'361'!H60+'362'!H60+'364'!H60 -> 3800 | I60: =+'361'!I60+'362'!I60+'364'!I60 -> 3800 | J60: =+'361'!J60+'362'!J60+'364'!J60 -> 3800 | K60: =+'361'!K60+'362'!K60+'364'!K60 -> 3800 | L60: =+'361'!L60+'362'!L60+'364'!L60 -> 3800 | ... P60: =+'361'!P60+'362'!P60+'364'!P60 -> 3876 | Q60: =SUM(E60:P60) -> 45752
D61: Insurabce-Property | E61: =+'361'!E61+'362'!E61+'364'!E61 -> 1167 | F61: =+'361'!F61+'362'!F61+'364'!F61 -> 1167 | G61: =+'361'!G61+'362'!G61+'364'!G61 -> 1167 | H61: =+'361'!H61+'362'!H61+'364'!H61 -> 1167 | I61: =+'361'!I61+'362'!I61+'364'!I61 -> 1167 | J61: =+'361'!J61+'362'!J61+'364'!J61 -> 1167 | K61: =+'361'!K61+'362'!K61+'364'!K61 -> 1167 | L61: =+'361'!L61+'362'!L61+'364'!L61 -> 1167 | ... P61: =+'361'!P61+'362'!P61+'364'!P61 -> 1190.34 | Q61: =SUM(E61:P61) -> 14050.68
D62: Insurance-Other | E62: =+'361'!E62+'362'!E62+'364'!E62 -> 0 | F62: =+'361'!F62+'362'!F62+'364'!F62 -> 0 | G62: =+'361'!G62+'362'!G62+'364'!G62 -> 0 | H62: =+'361'!H62+'362'!H62+'364'!H62 -> 0 | I62: =+'361'!I62+'362'!I62+'364'!I62 -> 0 | J62: =+'361'!J62+'362'!J62+'364'!J62 -> 0 | K62: =+'361'!K62+'362'!K62+'364'!K62 -> 0 | L62: =+'361'!L62+'362'!L62+'364'!L62 -> 0 | ... P62: =+'361'!P62+'362'!P62+'364'!P62 -> 0 | Q62: =SUM(E62:P62) -> 0
A63: 6510-8502 | C63: Insurance | E63: =SUM(E60:E62) -> 4967 | F63: =SUM(F60:F62) -> 4967 | G63: =SUM(G60:G62) -> 4967 | H63: =SUM(H60:H62) -> 4967 | I63: =SUM(I60:I62) -> 4967 | J63: =SUM(J60:J62) -> 4967 | K63: =SUM(K60:K62) -> 4967 | L63: =SUM(L60:L62) -> 4967 | ... Q63: =SUM(Q60:Q62) -> 59802.68 | R63: 58120 | S63: =Q63/R63-1 -> 0.028951824 | U63: 2025 Business Plan grown 3%
D65: Cleaning & Supplies | E65: =+'361'!E65+'362'!E65+'364'!E65 -> 12052.297 | F65: =+'361'!F65+'362'!F65+'364'!F65 -> 12052.297 | G65: =+'361'!G65+'362'!G65+'364'!G65 -> 12052.297 | H65: =+'361'!H65+'362'!H65+'364'!H65 -> 11029.816 | I65: =+'361'!I65+'362'!I65+'364'!I65 -> 11029.816 | J65: =+'361'!J65+'362'!J65+'364'!J65 -> 11029.816 | K65: =+'361'!K65+'362'!K65+'364'!K65 -> 11029.816 | L65: =+'361'!L65+'362'!L65+'364'!L65 -> 11029.816 | ... P65: =+'361'!P65+'362'!P65+'364'!P65 -> 9381.2725 | Q65: =SUM(E65:P65) -> 130717.34 | U65: Based on occupancy. ( cleaning, supplies, and porter)
D66: Cleaning & Supplies-Vacancies | E66: =+'361'!E66+'362'!E66+'364'!E66 -> 416.26118 | F66: =+'361'!F66+'362'!F66+'364'!F66 -> 416.26118 | G66: =+'361'!G66+'362'!G66+'364'!G66 -> 416.26118 | H66: =+'361'!H66+'362'!H66+'364'!H66 -> 473.40432 | I66: =+'361'!I66+'362'!I66+'364'!I66 -> 473.40432 | J66: =+'361'!J66+'362'!J66+'364'!J66 -> 473.40432 | K66: =+'361'!K66+'362'!K66+'364'!K66 -> 473.40432 | L66: =+'361'!L66+'362'!L66+'364'!L66 -> 473.40432 | ... P66: =+'361'!P66+'362'!P66+'364'!P66 -> 565.48189 | Q66: =SUM(E66:P66) -> 5772.4771 | U66: Based on occupancy.
A67: 6250-8502 | B67: (BP) | C67: Cleaning & Supplies | E67: =SUM(E65:E66) -> 12468.558 | F67: =SUM(F65:F66) -> 12468.558 | G67: =SUM(G65:G66) -> 12468.558 | H67: =SUM(H65:H66) -> 11503.22 | I67: =SUM(I65:I66) -> 11503.22 | J67: =SUM(J65:J66) -> 11503.22 | K67: =SUM(K65:K66) -> 11503.22 | L67: =SUM(L65:L66) -> 11503.22 | ... Q67: =SUM(Q65:Q66) -> 136489.81 | R67: 138915.13 | S67: =Q67/R67-1 -> -0.017458975 | U67: As per detail above
C69: Other - Condo Fee | E69: =+'361'!E69+'362'!E69+'364'!E69 -> 41180 | F69: =+'361'!F69+'362'!F69+'364'!F69 -> 0 | G69: =+'361'!G69+'362'!G69+'364'!G69 -> 0 | H69: =+'361'!H69+'362'!H69+'364'!H69 -> 41180 | I69: =+'361'!I69+'362'!I69+'364'!I69 -> 0 | J69: =+'361'!J69+'362'!J69+'364'!J69 -> 0 | K69: =+'361'!K69+'362'!K69+'364'!K69 -> 41180 | L69: =+'361'!L69+'362'!L69+'364'!L69 -> 0 | ... P69: =+'361'!P69+'362'!P69+'364'!P69 -> 0 | Q69: =SUM(E69:P69) -> 164720 | R69: 199212 | S69: =Q69/R69-1 -> -0.17314218 | U69: Condo budget same as 2025
C71: Total Reimbursable Expenses | E71: =+E27+E29+E31+E36+E38+E43+E45+E50+E52+E54+E56+E58+E63+E67+E69 -> 113379.76 | F71: =+F27+F29+F31+F36+F38+F43+F45+F50+F52+F54+F56+F58+F63+F67+F69 -> 74000.473 | G71: =+G27+G29+G31+G36+G38+G43+G45+G50+G52+G54+G56+G58+G63+G67+G69 -> 64495.323 | H71: =+H27+H29+H31+H36+H38+H43+H45+H50+H52+H54+H56+H58+H63+H67+H69 -> 103979.85 | I71: =+I27+I29+I31+I36+I38+I43+I45+I50+I52+I54+I56+I58+I63+I67+I69 -> 67287.715 | J71: =+J27+J29+J31+J36+J38+J43+J45+J50+J52+J54+J56+J58+J63+J67+J69 -> 102655.9 | K71: =+K27+K29+K31+K36+K38+K43+K45+K50+K52+K54+K56+K58+K63+K67+K69 -> 104024.55 | L71: =+L27+L29+L31+L36+L38+L43+L45+L50+L52+L54+L56+L58+L63+L67+L69 -> 59461.895 | ... R71: =+R27+R29+R31+R36+R38+R43+R45+R50+R52+R54+R56+R58+R63+R67+R69 -> 1125479.5 | S71: =Q71/R71-1 -> -0.12932899
Q72: ='361'!Q71+'362'!Q71+'364'!Q71 -> 979922.41
B73: Non-Reimbursable Expenses
A75: 5210-8501 | C75: Bad Debt | E75: =+'361'!E75+'362'!E75+'364'!E75 -> 0 | F75: =+'361'!F75+'362'!F75+'364'!F75 -> 0 | G75: =+'361'!G75+'362'!G75+'364'!G75 -> 0 | H75: =+'361'!H75+'362'!H75+'364'!H75 -> 0 | I75: =+'361'!I75+'362'!I75+'364'!I75 -> 0 | J75: =+'361'!J75+'362'!J75+'364'!J75 -> 0 | K75: =+'361'!K75+'362'!K75+'364'!K75 -> 0 | L75: =+'361'!L75+'362'!L75+'364'!L75 -> 0 | ... P75: =+'361'!P75+'362'!P75+'364'!P75 -> 0 | Q75: =SUM(E75:P75) -> 0
A77: 6010-8501 | D77: Salaries & Wages | E77: =+'361'!E77+'362'!E77+'364'!E77 -> 4870.9167 | F77: =+'361'!F77+'362'!F77+'364'!F77 -> 4870.9167 | G77: =+'361'!G77+'362'!G77+'364'!G77 -> 4870.9167 | H77: =+'361'!H77+'362'!H77+'364'!H77 -> 4870.9167 | I77: =+'361'!I77+'362'!I77+'364'!I77 -> 4870.9167 | J77: =+'361'!J77+'362'!J77+'364'!J77 -> 4870.9167 | K77: =+'361'!K77+'362'!K77+'364'!K77 -> 4870.9167 | L77: =+'361'!L77+'362'!L77+'364'!L77 -> 4870.9167 | ... P77: =+'361'!P77+'362'!P77+'364'!P77 -> 4870.9167 | Q77: =SUM(E77:P77) -> 58451 | U77: Based on 2026 Payroll Budget
A78: 6620-8501 | D78: Commissions-Internal Broker | E78: =+'361'!E78+'362'!E78+'364'!E78 -> 1622.25 | F78: =+'361'!F78+'362'!F78+'364'!F78 -> 0 | G78: =+'361'!G78+'362'!G78+'364'!G78 -> 0 | H78: =+'361'!H78+'362'!H78+'364'!H78 -> 1622.25 | I78: =+'361'!I78+'362'!I78+'364'!I78 -> 0 | J78: =+'361'!J78+'362'!J78+'364'!J78 -> 0 | K78: =+'361'!K78+'362'!K78+'364'!K78 -> 1622.25 | L78: =+'361'!L78+'362'!L78+'364'!L78 -> 0 | ... P78: =+'361'!P78+'362'!P78+'364'!P78 -> 0 | Q78: =SUM(E78:P78) -> 6489 | U78: Based on projected leasing assumptions
C79: Leasing Salaries and Commissions | E79: =SUM(E77:E78) -> 6493.1667 | F79: =SUM(F77:F78) -> 4870.9167 | G79: =SUM(G77:G78) -> 4870.9167 | H79: =SUM(H77:H78) -> 6493.1667 | I79: =SUM(I77:I78) -> 4870.9167 | J79: =SUM(J77:J78) -> 4870.9167 | K79: =SUM(K77:K78) -> 6493.1667 | L79: =SUM(L77:L78) -> 4870.9167 | ... Q79: =SUM(Q77:Q78) -> 64940 | R79: 61030.27 | S79: =Q79/R79-1 -> 0.064062145
A81: 6110-8501 | D81: Gas | E81: =+'361'!E81+'362'!E81+'364'!E81 -> 0 | F81: =+'361'!F81+'362'!F81+'364'!F81 -> 0 | G81: =+'361'!G81+'362'!G81+'364'!G81 -> 0 | H81: =+'361'!H81+'362'!H81+'364'!H81 -> 0 | I81: =+'361'!I81+'362'!I81+'364'!I81 -> 0 | J81: =+'361'!J81+'362'!J81+'364'!J81 -> 0 | K81: =+'361'!K81+'362'!K81+'364'!K81 -> 0 | L81: =+'361'!L81+'362'!L81+'364'!L81 -> 0 | ... P81: =+'361'!P81+'362'!P81+'364'!P81 -> 0 | Q81: =SUM(E81:P81) -> 0
A82: 6120-8501 | D82: Electric | E82: =+'361'!E82+'362'!E82+'364'!E82 -> 0 | F82: =+'361'!F82+'362'!F82+'364'!F82 -> 0 | G82: =+'361'!G82+'362'!G82+'364'!G82 -> 0 | H82: =+'361'!H82+'362'!H82+'364'!H82 -> 0 | I82: =+'361'!I82+'362'!I82+'364'!I82 -> 0 | J82: =+'361'!J82+'362'!J82+'364'!J82 -> 0 | K82: =+'361'!K82+'362'!K82+'364'!K82 -> 0 | L82: =+'361'!L82+'362'!L82+'364'!L82 -> 0 | ... P82: =+'361'!P82+'362'!P82+'364'!P82 -> 0 | Q82: =SUM(E82:P82) -> 0
A83: 6130-8501 | D83: Water & Sewer | E83: =+'361'!E83+'362'!E83+'364'!E83 -> 0 | F83: =+'361'!F83+'362'!F83+'364'!F83 -> 0 | G83: =+'361'!G83+'362'!G83+'364'!G83 -> 0 | H83: =+'361'!H83+'362'!H83+'364'!H83 -> 0 | I83: =+'361'!I83+'362'!I83+'364'!I83 -> 0 | J83: =+'361'!J83+'362'!J83+'364'!J83 -> 0 | K83: =+'361'!K83+'362'!K83+'364'!K83 -> 0 | L83: =+'361'!L83+'362'!L83+'364'!L83 -> 0 | ... P83: =+'361'!P83+'362'!P83+'364'!P83 -> 0 | Q83: =SUM(E83:P83) -> 0
C84: Utilities | E84: =SUM(E81:E83) -> 0 | F84: =SUM(F81:F83) -> 0 | G84: =SUM(G81:G83) -> 0 | H84: =SUM(H81:H83) -> 0 | I84: =SUM(I81:I83) -> 0 | J84: =SUM(J81:J83) -> 0 | K84: =SUM(K81:K83) -> 0 | L84: =SUM(L81:L83) -> 0 | ... Q84: =SUM(Q81:Q83) -> 0 | R84: 164.23 | S84: =Q84/R84-1 -> -1
D86: Building Maint.-Recurring | E86: =+'361'!E86+'362'!E86+'364'!E86 -> 2817.05 | F86: =+'361'!F86+'362'!F86+'364'!F86 -> 2817.05 | G86: =+'361'!G86+'362'!G86+'364'!G86 -> 2817.05 | H86: =+'361'!H86+'362'!H86+'364'!H86 -> 2817.05 | I86: =+'361'!I86+'362'!I86+'364'!I86 -> 2817.05 | J86: =+'361'!J86+'362'!J86+'364'!J86 -> 2817.05 | K86: =+'361'!K86+'362'!K86+'364'!K86 -> 2817.05 | L86: =+'361'!L86+'362'!L86+'364'!L86 -> 2817.05 | ... P86: =+'361'!P86+'362'!P86+'364'!P86 -> 2817.05 | Q86: =SUM(E86:P86) -> 33804.6
D87: Building Maint.-Big Projects | E87: =+'361'!E87+'362'!E87+'364'!E87 -> 0 | F87: =+'361'!F87+'362'!F87+'364'!F87 -> 0 | G87: =+'361'!G87+'362'!G87+'364'!G87 -> 0 | H87: =+'361'!H87+'362'!H87+'364'!H87 -> 0 | I87: =+'361'!I87+'362'!I87+'364'!I87 -> 0 | J87: =+'361'!J87+'362'!J87+'364'!J87 -> 0 | K87: =+'361'!K87+'362'!K87+'364'!K87 -> 0 | L87: =+'361'!L87+'362'!L87+'364'!L87 -> 0 | ... P87: =+'361'!P87+'362'!P87+'364'!P87 -> 0 | Q87: =SUM(E87:P87) -> 0
A88: 6220-8501 | C88: Building Maintenance | E88: =SUM(E86:E87) -> 2817.05 | F88: =SUM(F86:F87) -> 2817.05 | G88: =SUM(G86:G87) -> 2817.05 | H88: =SUM(H86:H87) -> 2817.05 | I88: =SUM(I86:I87) -> 2817.05 | J88: =SUM(J86:J87) -> 2817.05 | K88: =SUM(K86:K87) -> 2817.05 | L88: =SUM(L86:L87) -> 2817.05 | ... Q88: =SUM(Q86:Q87) -> 33804.6 | R88: 29353.9 | S88: =Q88/R88-1 -> 0.1516221 | U88: 2025 Business Plan grown 3%
A90: 6610-8501 | B90: (SC) | C90: Management fee | E90: ='361'!E90+'362'!E90+'364'!E90 -> 0 | F90: ='361'!F90+'362'!F90+'364'!F90 -> 0 | G90: ='361'!G90+'362'!G90+'364'!G90 -> 0 | H90: ='361'!H90+'362'!H90+'364'!H90 -> 0 | I90: ='361'!I90+'362'!I90+'364'!I90 -> 0 | J90: ='361'!J90+'362'!J90+'364'!J90 -> 0 | K90: ='361'!K90+'362'!K90+'364'!K90 -> 0 | L90: ='361'!L90+'362'!L90+'364'!L90 -> 0 | ... P90: ='361'!P90+'362'!P90+'364'!P90 -> 0 | Q90: =SUM(E90:P90) -> 0 | S90: =Q90/R90-1 -> #DIV/0!
S91: =Q91/R91-1 -> #DIV/0!
A92: 7110-8501 | C92: Marketing | E92: =+'361'!E92+'362'!E92+'364'!E92 -> 1250 | F92: =+'361'!F92+'362'!F92+'364'!F92 -> 1250 | G92: =+'361'!G92+'362'!G92+'364'!G92 -> 1250 | H92: =+'361'!H92+'362'!H92+'364'!H92 -> 1250 | I92: =+'361'!I92+'362'!I92+'364'!I92 -> 1250 | J92: =+'361'!J92+'362'!J92+'364'!J92 -> 1250 | K92: =+'361'!K92+'362'!K92+'364'!K92 -> 1250 | L92: =+'361'!L92+'362'!L92+'364'!L92 -> 1250 | ... P92: =+'361'!P92+'362'!P92+'364'!P92 -> 1250 | Q92: =SUM(E92:P92) -> 15000 | R92: 17558.14 | S92: =Q92/R92-1 -> -0.14569539 | U92: 2025 Business Plan grown 3%
A94: 8210-8501 | C94: Business Taxes | E94: =+'361'!E94+'362'!E94+'364'!E94 -> 0 | F94: =+'361'!F94+'362'!F94+'364'!F94 -> 0 | G94: =+'361'!G94+'362'!G94+'364'!G94 -> 0 | H94: =+'361'!H94+'362'!H94+'364'!H94 -> 3268.2316 | I94: =+'361'!I94+'362'!I94+'364'!I94 -> 0 | J94: =+'361'!J94+'362'!J94+'364'!J94 -> 0 | K94: =+'361'!K94+'362'!K94+'364'!K94 -> 0 | L94: =+'361'!L94+'362'!L94+'364'!L94 -> 0 | ... P94: =+'361'!P94+'362'!P94+'364'!P94 -> 0 | Q94: =SUM(E94:P94) -> 3268.2316 | R94: 2989 | S94: =Q94/R94-1 -> 0.09341975 | U94: Based on tax rate and revenues
A96: 8310-8501 | C96: Legal & Accounting | E96: =+'361'!E96+'362'!E96+'364'!E96 -> 2573.6667 | F96: =+'361'!F96+'362'!F96+'364'!F96 -> 2573.6667 | G96: =+'361'!G96+'362'!G96+'364'!G96 -> 2573.6667 | H96: =+'361'!H96+'362'!H96+'364'!H96 -> 2573.6667 | I96: =+'361'!I96+'362'!I96+'364'!I96 -> 2573.6667 | J96: =+'361'!J96+'362'!J96+'364'!J96 -> 2573.6667 | K96: =+'361'!K96+'362'!K96+'364'!K96 -> 2573.6667 | L96: =+'361'!L96+'362'!L96+'364'!L96 -> 2573.6667 | ... P96: =+'361'!P96+'362'!P96+'364'!P96 -> 2573.6667 | Q96: =SUM(E96:P96) -> 30884 | R96: 28370.8 | S96: =Q96/R96-1 -> 0.088584037
A98: 8190-8501 | D98: Bank Fees | E98: =+'361'!E98+'362'!E98+'364'!E98 -> 159.65 | F98: =+'361'!F98+'362'!F98+'364'!F98 -> 159.65 | G98: =+'361'!G98+'362'!G98+'364'!G98 -> 159.65 | H98: =+'361'!H98+'362'!H98+'364'!H98 -> 159.65 | I98: =+'361'!I98+'362'!I98+'364'!I98 -> 159.65 | J98: =+'361'!J98+'362'!J98+'364'!J98 -> 159.65 | K98: =+'361'!K98+'362'!K98+'364'!K98 -> 159.65 | L98: =+'361'!L98+'362'!L98+'364'!L98 -> 159.65 | ... P98: =+'361'!P98+'362'!P98+'364'!P98 -> 159.65 | Q98: =SUM(E98:P98) -> 1915.8 | U98: 2025 Business Plan grown 3%
A99: 8930-8501 | D99: Office Supplies | E99: =+'361'!E99+'362'!E99+'364'!E99 -> 0 | F99: =+'361'!F99+'362'!F99+'364'!F99 -> 0 | G99: =+'361'!G99+'362'!G99+'364'!G99 -> 0 | H99: =+'361'!H99+'362'!H99+'364'!H99 -> 0 | I99: =+'361'!I99+'362'!I99+'364'!I99 -> 0 | J99: =+'361'!J99+'362'!J99+'364'!J99 -> 0 | K99: =+'361'!K99+'362'!K99+'364'!K99 -> 0 | L99: =+'361'!L99+'362'!L99+'364'!L99 -> 0 | ... P99: =+'361'!P99+'362'!P99+'364'!P99 -> 0 | Q99: =SUM(E99:P99) -> 0
A100: 8950-8501 | D100: Postage | E100: =+'361'!E100+'362'!E100+'364'!E100 -> 0 | F100: =+'361'!F100+'362'!F100+'364'!F100 -> 0 | G100: =+'361'!G100+'362'!G100+'364'!G100 -> 0 | H100: =+'361'!H100+'362'!H100+'364'!H100 -> 0 | I100: =+'361'!I100+'362'!I100+'364'!I100 -> 0 | J100: =+'361'!J100+'362'!J100+'364'!J100 -> 0 | K100: =+'361'!K100+'362'!K100+'364'!K100 -> 0 | L100: =+'361'!L100+'362'!L100+'364'!L100 -> 0 | ... P100: =+'361'!P100+'362'!P100+'364'!P100 -> 0 | Q100: =SUM(E100:P100) -> 0
A101: 8990-8501 | D101: Other G&A Expense | E101: =+'361'!E101+'362'!E101+'364'!E101 -> 20.6 | F101: =+'361'!F101+'362'!F101+'364'!F101 -> 20.6 | G101: =+'361'!G101+'362'!G101+'364'!G101 -> 20.6 | H101: =+'361'!H101+'362'!H101+'364'!H101 -> 20.6 | I101: =+'361'!I101+'362'!I101+'364'!I101 -> 20.6 | J101: =+'361'!J101+'362'!J101+'364'!J101 -> 20.6 | K101: =+'361'!K101+'362'!K101+'364'!K101 -> 20.6 | L101: =+'361'!L101+'362'!L101+'364'!L101 -> 20.6 | ... P101: =+'361'!P101+'362'!P101+'364'!P101 -> 20.6 | Q101: =SUM(E101:P101) -> 247.2 | U101: 2025 Business Plan grown 3%
A102: 8990-9800 | D102: Other G&A-allocated from LIK | E102: =+'361'!E102+'362'!E102+'364'!E102 -> 3543.2 | F102: =+'361'!F102+'362'!F102+'364'!F102 -> 3543.2 | G102: =+'361'!G102+'362'!G102+'364'!G102 -> 3543.2 | H102: =+'361'!H102+'362'!H102+'364'!H102 -> 3543.2 | I102: =+'361'!I102+'362'!I102+'364'!I102 -> 3543.2 | J102: =+'361'!J102+'362'!J102+'364'!J102 -> 3543.2 | K102: =+'361'!K102+'362'!K102+'364'!K102 -> 3543.2 | L102: =+'361'!L102+'362'!L102+'364'!L102 -> 3543.2 | ... P102: =+'361'!P102+'362'!P102+'364'!P102 -> 3543.2 | Q102: =SUM(E102:P102) -> 42518.4 | U102: 2025 Business Plan grown 3%
C103: General & Administrative | E103: =SUM(E98:E102) -> 3723.45 | F103: =SUM(F98:F102) -> 3723.45 | G103: =SUM(G98:G102) -> 3723.45 | H103: =SUM(H98:H102) -> 3723.45 | I103: =SUM(I98:I102) -> 3723.45 | J103: =SUM(J98:J102) -> 3723.45 | K103: =SUM(K98:K102) -> 3723.45 | L103: =SUM(L98:L102) -> 3723.45 | ... Q103: =SUM(Q98:Q102) -> 44681.4 | R103: 45222.9 | S103: =Q103/R103-1 -> -0.011974022
C105: Total Non-Reimbursable Expenses | E105: =+E75+E79+E84+E88+E90+E92+E94+E96+E103 -> 16857.333 | F105: =+F75+F79+F84+F88+F90+F92+F94+F96+F103 -> 15235.083 | G105: =+G75+G79+G84+G88+G90+G92+G94+G96+G103 -> 15235.083 | H105: =+H75+H79+H84+H88+H90+H92+H94+H96+H103 -> 20125.565 | I105: =+I75+I79+I84+I88+I90+I92+I94+I96+I103 -> 15235.083 | J105: =+J75+J79+J84+J88+J90+J92+J94+J96+J103 -> 15235.083 | K105: =+K75+K79+K84+K88+K90+K92+K94+K96+K103 -> 16857.333 | L105: =+L75+L79+L84+L88+L90+L92+L94+L96+L103 -> 15235.083 | ... R105: =+R75+R79+R84+R88+R90+R92+R94+R96+R103 -> 184689.24 | S105: =Q105/R105-1 -> 0.04271495
B107: TOTAL OPERATING EXPENSES | E107: =+E71+E105 -> 130237.1 | F107: =+F71+F105 -> 89235.557 | G107: =+G71+G105 -> 79730.407 | H107: =+H71+H105 -> 124105.41 | I107: =+I71+I105 -> 82522.799 | J107: =+J71+J105 -> 117890.98 | K107: =+K71+K105 -> 120881.88 | L107: =+L71+L105 -> 74696.979 | ... R107: =+R71+R105 -> 1310168.8 | S107: =Q107/R107-1 -> -0.10507665
B109: NET OPERATING INCOME | E109: =+E24-E107 -> 19358.872 | F109: =+F24-F107 -> 59168.217 | G109: =+G24-G107 -> 66923.119 | H109: =+H24-H107 -> 5617.5143 | I109: =+I24-I107 -> 46776.925 | J109: =+J24-J107 -> 11819.195 | K109: =+K24-K107 -> 2584.654 | L109: =+L24-L107 -> 54110.403 | ... R109: =+R24-R107 -> 342429.92 | S109: =Q109/R109-1 -> 0.13436268
A111: 1420-0000 | D111: Land Improvements | E111: =+'361'!E111+'362'!E111+'364'!E111 -> 0 | F111: =+'361'!F111+'362'!F111+'364'!F111 -> 0 | G111: =+'361'!G111+'362'!G111+'364'!G111 -> 0 | H111: =+'361'!H111+'362'!H111+'364'!H111 -> 0 | I111: =+'361'!I111+'362'!I111+'364'!I111 -> 0 | J111: =+'361'!J111+'362'!J111+'364'!J111 -> 0 | K111: =+'361'!K111+'362'!K111+'364'!K111 -> 0 | L111: =+'361'!L111+'362'!L111+'364'!L111 -> 0 | ... P111: =+'361'!P111+'362'!P111+'364'!P111 -> 0 | Q111: =SUM(E111:P111) -> 0
A112: 1430-0000 | D112: Buildings | E112: =+'361'!E112+'362'!E112+'364'!E112 -> 0 | F112: =+'361'!F112+'362'!F112+'364'!F112 -> 0 | G112: =+'361'!G112+'362'!G112+'364'!G112 -> 0 | H112: =+'361'!H112+'362'!H112+'364'!H112 -> 0 | I112: =+'361'!I112+'362'!I112+'364'!I112 -> 0 | J112: =+'361'!J112+'362'!J112+'364'!J112 -> 0 | K112: =+'361'!K112+'362'!K112+'364'!K112 -> 0 | L112: =+'361'!L112+'362'!L112+'364'!L112 -> 0 | ... P112: =+'361'!P112+'362'!P112+'364'!P112 -> 0 | Q112: =SUM(E112:P112) -> 0
A113: 1450-0000 | D113: Equipment | E113: =+'361'!E113+'362'!E113+'364'!E113 -> 0 | F113: =+'361'!F113+'362'!F113+'364'!F113 -> 0 | G113: =+'361'!G113+'362'!G113+'364'!G113 -> 0 | H113: =+'361'!H113+'362'!H113+'364'!H113 -> 0 | I113: =+'361'!I113+'362'!I113+'364'!I113 -> 0 | J113: =+'361'!J113+'362'!J113+'364'!J113 -> 0 | K113: =+'361'!K113+'362'!K113+'364'!K113 -> 0 | L113: =+'361'!L113+'362'!L113+'364'!L113 -> 0 | ... P113: =+'361'!P113+'362'!P113+'364'!P113 -> 0 | Q113: =SUM(E113:P113) -> 0
A114: 1980-8501 | D114: Capital Improvements | E114: =+'361'!E114+'362'!E114+'364'!E114 -> 0 | F114: =+'361'!F114+'362'!F114+'364'!F114 -> 0 | G114: =+'361'!G114+'362'!G114+'364'!G114 -> 0 | H114: =+'361'!H114+'362'!H114+'364'!H114 -> 0 | I114: =+'361'!I114+'362'!I114+'364'!I114 -> 0 | J114: =+'361'!J114+'362'!J114+'364'!J114 -> 0 | K114: =+'361'!K114+'362'!K114+'364'!K114 -> 0 | L114: =+'361'!L114+'362'!L114+'364'!L114 -> 0 | ... P114: =+'361'!P114+'362'!P114+'364'!P114 -> 0 | Q114: =SUM(E114:P114) -> 0
C115: Capital Improvements | E115: =SUM(E111:E114) -> 0 | F115: =SUM(F111:F114) -> 0 | G115: =SUM(G111:G114) -> 0 | H115: =SUM(H111:H114) -> 0 | I115: =SUM(I111:I114) -> 0 | J115: =SUM(J111:J114) -> 0 | K115: =SUM(K111:K114) -> 0 | L115: =SUM(L111:L114) -> 0 | ... Q115: =SUM(Q111:Q114) -> 0 | S115: =Q115/R115-1 -> #DIV/0!
A117: 1440-0000 | C117: Tenant Improvements | E117: =+'361'!E117+'362'!E117+'364'!E117 -> 9576 | F117: =+'361'!F117+'362'!F117+'364'!F117 -> 0 | G117: =+'361'!G117+'362'!G117+'364'!G117 -> 0 | H117: =+'361'!H117+'362'!H117+'364'!H117 -> 0 | I117: =+'361'!I117+'362'!I117+'364'!I117 -> 0 | J117: =+'361'!J117+'362'!J117+'364'!J117 -> 0 | K117: =+'361'!K117+'362'!K117+'364'!K117 -> 2346 | L117: =+'361'!L117+'362'!L117+'364'!L117 -> 0 | ... P117: =+'361'!P117+'362'!P117+'364'!P117 -> 0 | Q117: =SUM(E117:P117) -> 14928 | R117: 12201.74 | S117: =Q117/R117-1 -> 0.22343207 | U117: Based on projected leasing assumptions
A119: 1940-8501 | D119: Deferred Marketing | E119: =+'361'!E119+'362'!E119+'364'!E119 -> 0 | F119: =+'361'!F119+'362'!F119+'364'!F119 -> 0 | G119: =+'361'!G119+'362'!G119+'364'!G119 -> 0 | H119: =+'361'!H119+'362'!H119+'364'!H119 -> 0 | I119: =+'361'!I119+'362'!I119+'364'!I119 -> 0 | J119: =+'361'!J119+'362'!J119+'364'!J119 -> 0 | K119: =+'361'!K119+'362'!K119+'364'!K119 -> 0 | L119: =+'361'!L119+'362'!L119+'364'!L119 -> 0 | ... P119: =+'361'!P119+'362'!P119+'364'!P119 -> 0 | Q119: =SUM(E119:P119) -> 0
A120: 1940-8501 | D120: Outside Leasing Commissions | E120: =+'361'!E120+'362'!E120+'364'!E120 -> 10383.68 | F120: =+'361'!F120+'362'!F120+'364'!F120 -> 4539.6 | G120: =+'361'!G120+'362'!G120+'364'!G120 -> 0 | H120: =+'361'!H120+'362'!H120+'364'!H120 -> 0 | I120: =+'361'!I120+'362'!I120+'364'!I120 -> 0 | J120: =+'361'!J120+'362'!J120+'364'!J120 -> 652.65 | K120: =+'361'!K120+'362'!K120+'364'!K120 -> 648.945 | L120: =+'361'!L120+'362'!L120+'364'!L120 -> 900.72 | ... P120: =+'361'!P120+'362'!P120+'364'!P120 -> 0 | Q120: =SUM(E120:P120) -> 18207.755 | U120: Based on projected leasing assumptions
C121: Outside Leasing Commissions | E121: =SUM(E119:E120) -> 10383.68 | F121: =SUM(F119:F120) -> 4539.6 | G121: =SUM(G119:G120) -> 0 | H121: =SUM(H119:H120) -> 0 | I121: =SUM(I119:I120) -> 0 | J121: =SUM(J119:J120) -> 652.65 | K121: =SUM(K119:K120) -> 648.945 | L121: =SUM(L119:L120) -> 900.72 | ... Q121: =SUM(Q119:Q120) -> 18207.755 | R121: 7060.54 | S121: =Q121/R121-1 -> 1.5788049 | U121: 7/2025 Projections is for Capitalized Lease Costs
B123: CASH FLOW BEFORE DEBT SERVICE | E123: =+E109-E115-E117-E121 -> -600.80758 | F123: =+F109-F115-F117-F121 -> 54628.617 | G123: =+G109-G115-G117-G121 -> 66923.119 | H123: =+H109-H115-H117-H121 -> 5617.5143 | I123: =+I109-I115-I117-I121 -> 46776.925 | J123: =+J109-J115-J117-J121 -> 11166.545 | K123: =+K109-K115-K117-K121 -> -410.29098 | L123: =+L109-L115-L117-L121 -> 53209.683 | ... R123: =+R109-R115-R117-R121 -> 323167.64 | S123: =Q123/R123-1 -> 0.099441664
B125: Debt Service
A126: 9210-8501 | C126: Interest | E126: ='361'!E126+'362'!E126+'364'!E126 -> 23022 | F126: ='361'!F126+'362'!F126+'364'!F126 -> 23022 | G126: ='361'!G126+'362'!G126+'364'!G126 -> 23022 | H126: ='361'!H126+'362'!H126+'364'!H126 -> 23022 | I126: ='361'!I126+'362'!I126+'364'!I126 -> 23022 | J126: ='361'!J126+'362'!J126+'364'!J126 -> 23022 | K126: ='361'!K126+'362'!K126+'364'!K126 -> 23022 | L126: ='361'!L126+'362'!L126+'364'!L126 -> 23022 | ... P126: ='361'!P126+'362'!P126+'364'!P126 -> 23022 | Q126: =SUM(E126:P126) -> 276264 | R126: 279671.63 | S126: =Q126/R126-1 -> -0.012184396
A127: 2740-8501 | C127: Mortgage Amortization | E127: ='361'!E127+'362'!E127+'364'!E127 -> 0 | F127: ='361'!F127+'362'!F127+'364'!F127 -> 0 | G127: ='361'!G127+'362'!G127+'364'!G127 -> 0 | H127: ='361'!H127+'362'!H127+'364'!H127 -> 0 | I127: ='361'!I127+'362'!I127+'364'!I127 -> 0 | J127: ='361'!J127+'362'!J127+'364'!J127 -> 0 | K127: ='361'!K127+'362'!K127+'364'!K127 -> 0 | L127: ='361'!L127+'362'!L127+'364'!L127 -> 0 | ... P127: ='361'!P127+'362'!P127+'364'!P127 -> 0 | Q127: =SUM(E127:P127) -> 0 | R127: 30472.93 | S127: =Q127/R127-1 -> -1
A128: 2740-0000 | C128: Loan Proceeds | Q128: =SUM(E128:P128) -> 0
C129: Total Debt Service | E129: =SUM(E126:E128) -> 23022 | F129: =SUM(F126:F128) -> 23022 | G129: =SUM(G126:G128) -> 23022 | H129: =SUM(H126:H128) -> 23022 | I129: =SUM(I126:I128) -> 23022 | J129: =SUM(J126:J128) -> 23022 | K129: =SUM(K126:K128) -> 23022 | L129: =SUM(L126:L128) -> 23022 | ... R129: =SUM(R126:R128) -> 310144.56 | S129: =Q129/R129-1 -> -0.10924119
B131: CASH FLOW AFTER DEBT SERVICE | E131: =+E123-E129 -> -23622.808 | F131: =+F123-F129 -> 31606.617 | G131: =+G123-G129 -> 43901.119 | H131: =+H123-H129 -> -17404.486 | I131: =+I123-I129 -> 23754.925 | J131: =+J123-J129 -> -11855.455 | K131: =+K123-K129 -> -23432.291 | L131: =+L123-L129 -> 30187.683 | ... R131: =+R123-R129 -> 13023.08 | S131: =Q131/R131-1 -> 5.0692223
B138: Operating Cash 12/31/2025 (Projected using Jun reprojections). Includes $40,065.01 returned to JV III for overages on RET escrows.
D139: =100775+40065.01 -> 140840.01 | Q139: =+D139 -> 140840.01
D140: Monthly TI Escrow Deposit | E140: =IF(T140=TRUE,0,-5000) -> -5000 | F140: =+E140 -> -5000 | G140: =+F140 -> -5000 | H140: =+G140 -> -5000 | I140: =+H140 -> -5000 | J140: =+I140 -> -5000 | K140: =+J140 -> -5000 | L140: =+K140 -> -5000 | M140: =+L140 -> -5000 | ... P140: =+O140 -> -5000 | Q140: =SUM(E140:P140) -> -60000 | T140: FALSE | U140: Toggle Escrow Contributions
E141: =+E131+D139+E140 -> 112217.2 | F141: =+E141+F131+F140 -> 138823.82 | G141: =+F141+G131+G140 -> 177724.94 | H141: =+G141+H131+H140 -> 155320.45 | I141: =+H141+I131+I140 -> 174075.38 | J141: =+I141+J131+J140 -> 157219.92 | K141: =+J141+K131+K140 -> 128787.63 | L141: =+K141+L131+L140 -> 153975.31 | M141: =+L141+M131+M140 -> 178197.06 | ... P141: =+O141+P131+P140 -> 159879.98 | Q141: =+Q131+Q139+Q140 -> 159879.98
D145: Monthly Transfer to TI Escrow | E145: =-E140 -> 5000 | F145: =+E145 -> 5000 | G145: =+F145 -> 5000 | H145: =+G145 -> 5000 | I145: =+H145 -> 5000 | J145: =+I145 -> 5000 | K145: =+J145 -> 5000 | L145: =+K145 -> 5000 | M145: =+L145 -> 5000 | ... P145: =+O145 -> 5000
B147: TI Cash 09/30/2025 (Assumes TI Reserve contributions stop)
...

Sheet 361
B1: 3610 | J1: =+'JV III Consolidated'!J1 -> Operating Budget | Q1: ='JV III Consolidated'!Q1 -> 46023
J2: ='JV III Consolidated'!J2 -> Lincoln JV III
Q3: =Q1 -> 46023 | S3: 7/2025 Reprojections
B4: ='Renew & Vac - Rent, TI, LC'!A6 -> 41821 | E4: Jan | F4: Feb | G4: Mar | H4: Apr | I4: May | J4: Jun | K4: Jul | L4: Aug | M4: Sep | N4: Oct | O4: Nov | P4: Dec | Q4: Total | R4: Total PSF | S4: Total | T4: Var. | U4: Input | V4: Notes
D6: Occupancy % | E6: ='Renew & Vac - Rent, TI, LC'!AH9 -> 0.5898 | F6: ='Renew & Vac - Rent, TI, LC'!AI9 -> 0.5898 | G6: ='Renew & Vac - Rent, TI, LC'!AJ9 -> 0.5898 | H6: ='Renew & Vac - Rent, TI, LC'!AK9 -> 0.5898 | I6: ='Renew & Vac - Rent, TI, LC'!AL9 -> 0.5898 | J6: ='Renew & Vac - Rent, TI, LC'!AM9 -> 0.5898 | K6: ='Renew & Vac - Rent, TI, LC'!AN9 -> 0.5898 | L6: ='Renew & Vac - Rent, TI, LC'!AO9 -> 0.5898 | ... P6: ='Renew & Vac - Rent, TI, LC'!AS9 -> 0.5898
D7: Occupancy SF | E7: =$B$4*E6 -> 24666.026 | F7: =$B$4*F6 -> 24666.026 | G7: =$B$4*G6 -> 24666.026 | H7: =$B$4*H6 -> 24666.026 | I7: =$B$4*I6 -> 24666.026 | J7: =$B$4*J6 -> 24666.026 | K7: =$B$4*K6 -> 24666.026 | L7: =$B$4*L6 -> 24666.026 | ... P7: =$B$4*P6 -> 24666.026
B8: Revenues
A10: 4230-8501 | C10: Rental Income - In Place | E10: =SUMIFS('In Place Revenue'!$G:$G,'In Place Revenue'!$A:$A,$B$1,'In Place Revenue'!$H:$H,1) -> 25265.13 | F10: =SUMIFS('In Place Revenue'!$G:$G,'In Place Revenue'!$A:$A,$B$1,'In Place Revenue'!$H:$H,2) -> 21061.8 | G10: =SUMIFS('In Place Revenue'!$G:$G,'In Place Revenue'!$A:$A,$B$1,'In Place Revenue'!$H:$H,3) -> 19266.3 | H10: =SUMIFS('In Place Revenue'!$G:$G,'In Place Revenue'!$A:$A,$B$1,'In Place Revenue'!$H:$H,4) -> 17241.88 | I10: =SUMIFS('In Place Revenue'!$G:$G,'In Place Revenue'!$A:$A,$B$1,'In Place Revenue'!$H:$H,5) -> 15196.88 | J10: =SUMIFS('In Place Revenue'!$G:$G,'In Place Revenue'!$A:$A,$B$1,'In Place Revenue'!$H:$H,6) -> 9190.63 | K10: =SUMIFS('In Place Revenue'!$G:$G,'In Place Revenue'!$A:$A,$B$1,'In Place Revenue'!$H:$H,7) -> 7388 | L10: =SUMIFS('In Place Revenue'!$G:$G,'In Place Revenue'!$A:$A,$B$1,'In Place Revenue'!$H:$H,8) -> 6171.75 | M10: =SUMIFS('In Place Revenue'!$G:$G,'In Place Revenue'!$A:$A,$B$1,'In Place Revenue'!$H:$H,9) -> 6171.75 | N10: =SUMIFS('In Place Revenue'!$G:$G,'In Place Revenue'!$A:$A,$B$1,'In Place Revenue'!$H:$H,10) -> 4414.25 | O10: =SUMIFS('In Place Revenue'!$G:$G,'In Place Revenue'!$A:$A,$B$1,'In Place Revenue'!$H:$H,11) -> 4414.25 | P10: =SUMIFS('In Place Revenue'!$G:$G,'In Place Revenue'!$A:$A,$B$1,'In Place Revenue'!$H:$H,12) -> 4414.25 | Q10: =SUM(E10:P10) -> 140196.87 | R10: =Q10/$B$4 -> 3.3523079 | S10: 344588.27 | T10: =IFERROR((Q10+Q11)/S10-1,"-") -> 0.16673986 | V10: Inplace reviewed, ok
A11: 4230-8501 | C11: Rental Income - New & Renewal | E11: ='Renew & Vac - Rent, TI, LC'!AH10 -> 9431.875 | F11: ='Renew & Vac - Rent, TI, LC'!AI10 -> 13635.208 | G11: ='Renew & Vac - Rent, TI, LC'!AJ10 -> 15430.708 | H11: ='Renew & Vac - Rent, TI, LC'!AK10 -> 15430.708 | I11: ='Renew & Vac - Rent, TI, LC'!AL10 -> 17475.708 | J11: ='Renew & Vac - Rent, TI, LC'!AM10 -> 23605.292 | K11: ='Renew & Vac - Rent, TI, LC'!AN10 -> 25407.917 | L11: ='Renew & Vac - Rent, TI, LC'!AO10 -> 26658.917 | ... P11: ='Renew & Vac - Rent, TI, LC'!AS10 -> 29871.917 | Q11: =SUM(E11:P11) -> 261848 | R11: =Q11/$B$4 -> 6.2611607 | T11: =IFERROR(Q11/S11-1,"-") -> -
A12: 4240-8501 | C12: Percentage Rents | E12: 0 | F12: 0 | G12: 0 | H12: 0 | I12: 0 | J12: 0 | K12: 0 | L12: 0 | M12: 0 | N12: 0 | O12: 0 | P12: 0 | Q12: =SUM(E12:P12) -> 0 | R12: =Q12/$B$4 -> 0 | T12: =R12/S12-1 -> #DIV/0!
A13: 4990-8501 | C13: Miscellaneous | E13: 0 | F13: 0 | G13: 0 | H13: 0 | I13: 0 | J13: 0 | K13: 0 | L13: 0 | M13: 0 | N13: 0 | O13: 0 | P13: 0 | Q13: =SUM(E13:P13) -> 0 | R13: =Q13/$B$4 -> 0 | T13: =IFERROR(Q13/S13-1,"-") -> -
A14: 9190-8501 | C14: Interest Income | E14: 0 | F14: 0 | G14: 0 | H14: 0 | I14: 0 | J14: 0 | K14: 0 | L14: 0 | M14: 0 | N14: 0 | O14: 0 | P14: 0 | Q14: =SUM(E14:P14) -> 0 | R14: =Q14/$B$4 -> 0 | T14: =IFERROR(Q14/S14-1,"-") -> -
C15: Total Rental and Other | E15: =SUM(E10:E14) -> 34697.005 | F15: =SUM(F10:F14) -> 34697.008 | G15: =SUM(G10:G14) -> 34697.008 | H15: =SUM(H10:H14) -> 32672.588 | I15: =SUM(I10:I14) -> 32672.588 | J15: =SUM(J10:J14) -> 32795.922 | K15: =SUM(K10:K14) -> 32795.917 | L15: =SUM(L10:L14) -> 32830.667 | ... Q15: =SUM(Q10:Q14) -> 402044.87 | R15: =Q15/$B$4 -> 9.6134686 | S15: =SUM(S10:S14) -> 344588.27 | T15: =IFERROR(Q15/S15-1,"-") -> 0.16673986
B17: Reimbursements
A18: 4710-8502 | C18: Electric | E18: =E6*E29 -> 4529.0742 | F18: =F6*F29 -> 3922.7598 | G18: =G6*G29 -> 2932.4856 | H18: =H6*H29 -> 1787.6838 | I18: =I6*I29 -> 1485.1164 | J18: =J6*J29 -> 1739.91 | K18: =K6*K29 -> 2132.127 | L18: =L6*L29 -> 2111.484 | ... P18: =P6*P29 -> 4106.7774 | Q18: =SUM(E18:P18) -> 30423.064 | R18: =Q18/$B$4 -> 0.72745902 | S18: 28439.42 | T18: =IFERROR(Q18/S18-1,"-") -> 0.069749791 | U18: DW | V18: =Q18/Q29*100&"% Set to occupancy" -> 58.98% Set to occupancy
A19: 4910-8502 | C19: Common Area Maintenance | E19: =+'Tenant Recoveries'!F21 -> 1670 | F19: =+E19 -> 1670 | G19: =+F19 -> 1670 | H19: =+G19 -> 1670 | I19: =+H19 -> 1670 | J19: =+I19 -> 1670 | K19: =+J19 -> 1670 | L19: =+K19 -> 1670 | M19: =+L19 -> 1670 | ... P19: =+O19 -> 1670 | Q19: =SUM(E19:P19) -> 20040 | R19: =Q19/$B$4 -> 0.4791851 | S19: 17594 | T19: =IFERROR(Q19/S19-1,"-") -> 0.13902467 | V19: =Q19/(Q71-Q63-Q58-Q29) -> 0.091197906
A20: 4920-8502 | C20: Real Estate Taxes | E20: =+'Tenant Recoveries'!F22 -> 130 | F20: =+E20 -> 130 | G20: =+F20 -> 130 | H20: =+G20 -> 130 | I20: =+H20 -> 130 | J20: =+I20 -> 130 | K20: =+J20 -> 130 | L20: =+K20 -> 130 | M20: =+L20 -> 130 | ... P20: =+O20 -> 130 | Q20: =SUM(E20:P20) -> 1560 | R20: =Q20/$B$4 -> 0.037301834 | S20: 3386 | T20: =IFERROR(Q20/S20-1,"-") -> -0.53927939 | V20: =Q20/Q58 -> 0.038425745
A21: 4930-8502 | C21: Insurance | Q21: =SUM(E21:P21) -> 0 | R21: =Q21/$B$4 -> 0 | T21: =IFERROR(Q21/S21-1,"-") -> -
C22: Total Reimbursements | E22: =SUM(E18:E21) -> 6329.0742 | F22: =SUM(F18:F21) -> 5722.7598 | G22: =SUM(G18:G21) -> 4732.4856 | H22: =SUM(H18:H21) -> 3587.6838 | I22: =SUM(I18:I21) -> 3285.1164 | J22: =SUM(J18:J21) -> 3539.91 | K22: =SUM(K18:K21) -> 3932.127 | L22: =SUM(L18:L21) -> 3911.484 | ... Q22: =SUM(Q18:Q21) -> 52023.064 | R22: =Q22/$B$4 -> 1.243946 | S22: =SUM(S18:S21) -> 49419.42 | T22: =IFERROR(Q22/S22-1,"-") -> 0.052684625
R23: =Q23/$B$4 -> 0
B24: TOTAL REVENUES | E24: =+E15+E22 -> 41026.079 | F24: =+F15+F22 -> 40419.768 | G24: =+G15+G22 -> 39429.494 | H24: =+H15+H22 -> 36260.272 | I24: =+I15+I22 -> 35957.705 | J24: =+J15+J22 -> 36335.832 | K24: =+K15+K22 -> 36728.044 | L24: =+L15+L22 -> 36742.151 | ... Q24: =+Q15+Q22 -> 454067.93 | R24: =Q24/$B$4 -> 10.857415 | S24: =+S15+S22 -> 394007.69 | T24: =IFERROR(Q24/S24-1,"-") -> 0.15243419 | V24: Why is 2026 revenues 17.48% higher
V25: Move out -,1429, 2 new -- 1.838+2.394 | Z25: =1838+2394-1429 -> 2803 | AA25: =+Z25*18.5 -> 51855.5 | AB25: =+Q24-S24 -> 60060.244
B26: Reimbursable Expenses
A27: 6030-8502 | C27: Maintenance Salaries | E27: ='Allocated Expenses'!E4 -> 1179.5 | F27: ='Allocated Expenses'!F4 -> 1179.5 | G27: ='Allocated Expenses'!G4 -> 1179.5 | H27: ='Allocated Expenses'!H4 -> 1179.5 | I27: ='Allocated Expenses'!I4 -> 1179.5 | J27: ='Allocated Expenses'!J4 -> 1179.5 | K27: ='Allocated Expenses'!K4 -> 1179.5 | L27: ='Allocated Expenses'!L4 -> 1179.5 | ... P27: ='Allocated Expenses'!P4 -> 1179.5 | Q27: =SUM(E27:P27) -> 14154 | R27: =Q27/$B$4 -> 0.33844241 | S27: 8881.32 | T27: =IFERROR(Q27/S27-1,"-") -> 0.59368202
A29: 6120-8502 | C29: Electric | E29: 7679 | F29: 6651 | G29: 4972 | H29: 3031 | I29: 2518 | J29: 2950 | K29: 3615 | L29: 3580 | M29: 2717 | N29: 2835 | O29: 4071 | P29: 6963 | Q29: =SUM(E29:P29) -> 51582 | R29: =Q29/$B$4 -> 1.2333995 | S29: 49514.07 | T29: =IFERROR(Q29/S29-1,"-") -> 0.041764492 | U29: DW | V29: Data\Shared\Properties\Business Plans - All Entities\2026\ISG Electric data
A31: 6130-8502 | C31: Water & Sewer | E31: ='Water Sewer'!D9 -> 1965.4 | F31: ='Water Sewer'!E9 -> 1938.62 | G31: ='Water Sewer'!F9 -> 1875.79 | H31: ='Water Sewer'!G9 -> 1798.54 | I31: ='Water Sewer'!H9 -> 1995.27 | J31: ='Water Sewer'!I9 -> 1897.42 | K31: ='Water Sewer'!J9 -> 1907.72 | L31: ='Water Sewer'!K9 -> 1988.06 | ... P31: ='Water Sewer'!O9 -> 2011.75 | Q31: =SUM(E31:P31) -> 23159.41 | R31: =Q31/$B$4 -> 0.55377466 | S31: 23066.28 | T31: =IFERROR(Q31/S31-1,"-") -> 0.0040374954 | U31: AK | V31: 2025 Business Plan grown 3%
D33: Building Maint.-Contractual | E33: ='Building Maint'!C13 -> 1960 | F33: ='Building Maint'!D13 -> 1660 | G33: ='Building Maint'!E13 -> 1820 | H33: ='Building Maint'!F13 -> 2610 | I33: ='Building Maint'!G13 -> 1010 | J33: ='Building Maint'!H13 -> 1010 | K33: ='Building Maint'!I13 -> 2610 | L33: ='Building Maint'!J13 -> 1010 | ... P33: ='Building Maint'!N13 -> 1010 | Q33: =SUM(E33:P33) -> 20140 | R33: =Q33/$B$4 -> 0.48157624
D34: Building Maint.-Recurring | E34: ='Building Maint'!C6 -> 2115 | F34: ='Building Maint'!D6 -> 2040 | G34: ='Building Maint'!E6 -> 1815 | H34: ='Building Maint'!F6 -> 2215 | I34: ='Building Maint'!G6 -> 4290 | J34: ='Building Maint'!H6 -> 1690 | K34: ='Building Maint'!I6 -> 2385 | L34: ='Building Maint'!J6 -> 1690 | ... P34: ='Building Maint'!N6 -> 1690 | Q34: =SUM(E34:P34) -> 28250 | R34: =Q34/$B$4 -> 0.67549796
D35: Building Maint.-Big Projects | F35: =1.03*1500 -> 1545 | J35: =1.03*15000 -> 15450 | N35: =1.03*1500 -> 1545 | Q35: =SUM(E35:P35) -> 18540 | R35: =Q35/$B$4 -> 0.44331795 | V35: Split systems & Zone lines
A36: 6220-8502 | C36: Building Maintenance | E36: =SUM(E33:E35) -> 4075 | F36: =SUM(F33:F35) -> 5245 | G36: =SUM(G33:G35) -> 3635 | H36: =SUM(H33:H35) -> 4825 | I36: =SUM(I33:I35) -> 5300 | J36: =SUM(J33:J35) -> 18150 | K36: =SUM(K33:K35) -> 4995 | L36: =SUM(L33:L35) -> 2700 | ... Q36: =SUM(Q33:Q35) -> 66930 | R36: =Q36/$B$4 -> 1.6003921 | S36: 40295.41 | T36: =IFERROR(Q36/S36-1,"-") -> 0.66098322
A38: 6330-850 | B38: (SC) | C38: Parking Lot Cleaning | Q38: =SUM(E38:P38) -> 0 | R38: =Q38/$B$4 -> 0
D40: Parking Lot Maint.-Contractual | Q40: =SUM(E40:P40) -> 0 | R40: =Q40/$B$4 -> 0
D41: Parking Lot Maint.-Recurring | E41: ='Parking Lot Maint'!C6 -> 0 | F41: ='Parking Lot Maint'!D6 -> 0 | G41: ='Parking Lot Maint'!E6 -> 0 | H41: ='Parking Lot Maint'!F6 -> 0 | I41: ='Parking Lot Maint'!G6 -> 0 | J41: ='Parking Lot Maint'!H6 -> 0 | K41: ='Parking Lot Maint'!I6 -> 0 | L41: ='Parking Lot Maint'!J6 -> 0 | ... P41: ='Parking Lot Maint'!N6 -> 0 | Q41: =SUM(E41:P41) -> 0 | R41: =Q41/$B$4 -> 0
D42: Parking Lot Maint.-Big Projects | Q42: =SUM(E42:P42) -> 0 | R42: =Q42/$B$4 -> 0
A43: 6330-8502 | C43: Parking Lot Maintenance | E43: =SUM(E40:E42) -> 0 | F43: =SUM(F40:F42) -> 0 | G43: =SUM(G40:G42) -> 0 | H43: =SUM(H40:H42) -> 0 | I43: =SUM(I40:I42) -> 0 | J43: =SUM(J40:J42) -> 0 | K43: =SUM(K40:K42) -> 0 | L43: =SUM(L40:L42) -> 0 | ... Q43: =SUM(Q40:Q42) -> 0 | R43: =Q43/$B$4 -> 0 | S43: 114 | T43: =IFERROR(Q43/S43-1,"-") -> -1
A45: 6370-8502 | C45: Snow Removal | Q45: =SUM(E45:P45) -> 0 | R45: =Q45/$B$4 -> 0 | T45: =IFERROR(Q45/S45-1,"-") -> -
D47: Landscaping-Contractual | Q47: =SUM(E47:P47) -> 0 | R47: =Q47/$B$4 -> 0
D48: Landscaping-Recurring | E48: =Landscaping!C6 -> 0 | F48: =Landscaping!D6 -> 0 | G48: =Landscaping!E6 -> 0 | H48: =Landscaping!F6 -> 0 | I48: =Landscaping!G6 -> 0 | J48: =Landscaping!H6 -> 0 | K48: =Landscaping!I6 -> 0 | L48: =Landscaping!J6 -> 0 | ... P48: =Landscaping!N6 -> 0 | Q48: =SUM(E48:P48) -> 0 | R48: =Q48/$B$4 -> 0
D49: Landscaping-Big Projects | Q49: =SUM(G49:P49) -> 0 | R49: =Q49/$B$4 -> 0
A50: 6380-8502 | C50: Landscaping | E50: =SUM(E47:E49) -> 0 | F50: =SUM(F47:F49) -> 0 | G50: =SUM(G47:G49) -> 0 | H50: =SUM(H47:H49) -> 0 | I50: =SUM(I47:I49) -> 0 | J50: =SUM(J47:J49) -> 0 | K50: =SUM(K47:K49) -> 0 | L50: =SUM(L47:L49) -> 0 | ... Q50: =SUM(Q47:Q49) -> 0 | R50: =Q50/$B$4 -> 0 | S50: 135 | T50: =IFERROR(Q50/S50-1,"-") -> -1
A52: 6350-8502 | C52: Security | Q52: =SUM(E52:P52) -> 0 | R52: =Q52/$B$4 -> 0 | T52: =IFERROR(Q52/S52-1,"-") -> -
A54: 6610-8502 | B54: (BP) | C54: Management Fee | E54: =ROUND(E$24*0.04,0) -> 1641 | F54: =ROUND(F$24*0.04,0) -> 1617 | G54: =ROUND(G$24*0.04,0) -> 1577 | H54: =ROUND(H$24*0.04,0) -> 1450 | I54: =ROUND(I$24*0.04,0) -> 1438 | J54: =ROUND(J$24*0.04,0) -> 1453 | K54: =ROUND(K$24*0.04,0) -> 1469 | L54: =ROUND(L$24*0.04,0) -> 1470 | ... P54: =ROUND(P$24*0.04,0) -> 1608 | Q54: =SUM(E54:P54) -> 18161 | R54: =Q54/$B$4 -> 0.43425552 | S54: 16077.88 | T54: =IFERROR(Q54/S54-1,"-") -> 0.12956435
A56: 6270-8502 | C56: Trash Removal | E56: =Trash!C6 -> 0 | F56: =Trash!D6 -> 0 | G56: =Trash!E6 -> 0 | H56: =Trash!F6 -> 0 | I56: =Trash!G6 -> 0 | J56: =Trash!H6 -> 0 | K56: =Trash!I6 -> 0 | L56: =Trash!J6 -> 0 | ... P56: =Trash!N6 -> 0 | Q56: =SUM(E56:P56) -> 0 | R56: =Q56/$B$4 -> 0 | S56: 263 | T56: =IFERROR(Q56/S56-1,"-") -> -1
A58: 6410-8502 | C58: Real Estate Taxes | E58: =+'INS RET'!E32 -> 3383.1484 | F58: =+'INS RET'!F32 -> 3383.1484 | G58: =+'INS RET'!G32 -> 3383.1484 | H58: =+'INS RET'!H32 -> 3383.1484 | I58: =+'INS RET'!I32 -> 3383.1484 | J58: =+'INS RET'!J32 -> 3383.1484 | K58: =+'INS RET'!K32 -> 3383.1484 | L58: =+'INS RET'!L32 -> 3383.1484 | ... P58: =+'INS RET'!P32 -> 3383.1484 | Q58: =SUM(E58:P58) -> 40597.781 | R58: =Q58/$B$4 -> 0.97075109 | S58: 102499.12 | T58: =IFERROR(Q58/S58-1,"-") -> -0.60392068
D60: Insurance-Liability | E60: =+'INS RET'!E6+'INS RET'!E7 -> 1142 | F60: =+'INS RET'!F6+'INS RET'!F7 -> 1142 | G60: =+'INS RET'!G6+'INS RET'!G7 -> 1142 | H60: =+'INS RET'!H6+'INS RET'!H7 -> 1142 | I60: =+'INS RET'!I6+'INS RET'!I7 -> 1142 | J60: =+'INS RET'!J6+'INS RET'!J7 -> 1142 | K60: =+'INS RET'!K6+'INS RET'!K7 -> 1142 | L60: =+'INS RET'!L6+'INS RET'!L7 -> 1142 | ... P60: =+'INS RET'!P6+'INS RET'!P7 -> 1164.84 | Q60: =SUM(E60:P60) -> 13749.68 | R60: =Q60/$B$4 -> 0.32877454
D61: Insurabce-Property | E61: =+'INS RET'!E9 -> 347 | F61: =+'INS RET'!F9 -> 347 | G61: =+'INS RET'!G9 -> 347 | H61: =+'INS RET'!H9 -> 347 | I61: =+'INS RET'!I9 -> 347 | J61: =+'INS RET'!J9 -> 347 | K61: =+'INS RET'!K9 -> 347 | L61: =+'INS RET'!L9 -> 347 | ... P61: =+'INS RET'!P9 -> 353.94 | Q61: =SUM(E61:P61) -> 4177.88 | R61: =Q61/$B$4 -> 0.099899094
D62: Insurance-Other | E62: =+'INS RET'!E10 -> 0 | F62: =+'INS RET'!F10 -> 0 | G62: =+'INS RET'!G10 -> 0 | H62: =+'INS RET'!H10 -> 0 | I62: =+'INS RET'!I10 -> 0 | J62: =+'INS RET'!J10 -> 0 | K62: =+'INS RET'!K10 -> 0 | L62: =+'INS RET'!L10 -> 0 | ... P62: =+'INS RET'!P10 -> 0 | Q62: =SUM(E62:P62) -> 0 | R62: =Q62/$B$4 -> 0
A63: 6510-8502 | C63: Insurance | E63: =SUM(E60:E62) -> 1489 | F63: =SUM(F60:F62) -> 1489 | G63: =SUM(G60:G62) -> 1489 | H63: =SUM(H60:H62) -> 1489 | I63: =SUM(I60:I62) -> 1489 | J63: =SUM(J60:J62) -> 1489 | K63: =SUM(K60:K62) -> 1489 | L63: =SUM(L60:L62) -> 1489 | ... Q63: =SUM(Q60:Q62) -> 17927.56 | R63: =Q63/$B$4 -> 0.42867363 | S63: 17560 | T63: =IFERROR(Q63/S63-1,"-") -> 0.020931663
D65: Cleaning & Supplies | E65: ='Allocated Expenses'!E11+'Allocated Expenses'!E18 -> 3860.9342 | F65: ='Allocated Expenses'!F11+'Allocated Expenses'!F18 -> 3860.9342 | G65: ='Allocated Expenses'!G11+'Allocated Expenses'!G18 -> 3860.9342 | H65: ='Allocated Expenses'!H11+'Allocated Expenses'!H18 -> 3860.9342 | I65: ='Allocated Expenses'!I11+'Allocated Expenses'!I18 -> 3860.9342 | J65: ='Allocated Expenses'!J11+'Allocated Expenses'!J18 -> 3860.9342 | K65: ='Allocated Expenses'!K11+'Allocated Expenses'!K18 -> 3860.9342 | L65: ='Allocated Expenses'!L11+'Allocated Expenses'!L18 -> 3860.9342 | ... P65: ='Allocated Expenses'!P11+'Allocated Expenses'!P18 -> 3860.9342 | Q65: =SUM(E65:P65) -> 46331.211 | R65: =Q65/$B$4 -> 1.1078456 | U65: DW | V65: Based on occupancy. Includes cleaning, supplies, and porter fee.
D66: Cleaning & Supplies-Vacancies | E66: ='Allocated Expenses'!E27 -> 132.52218 | F66: ='Allocated Expenses'!F27 -> 132.52218 | G66: ='Allocated Expenses'!G27 -> 132.52218 | H66: ='Allocated Expenses'!H27 -> 132.52218 | I66: ='Allocated Expenses'!I27 -> 132.52218 | J66: ='Allocated Expenses'!J27 -> 132.52218 | K66: ='Allocated Expenses'!K27 -> 132.52218 | L66: ='Allocated Expenses'!L27 -> 132.52218 | ... P66: ='Allocated Expenses'!P27 -> 132.52218 | Q66: =SUM(E66:P66) -> 1590.2661 | R66: =Q66/$B$4 -> 0.03802554 | U66: DW | V66: Based on occupancy.
A67: 6250-8502 | B67: (BP) | C67: Cleaning & Supplies | E67: =SUM(E65:E66) -> 3993.4564 | F67: =SUM(F65:F66) -> 3993.4564 | G67: =SUM(G65:G66) -> 3993.4564 | H67: =SUM(H65:H66) -> 3993.4564 | I67: =SUM(I65:I66) -> 3993.4564 | J67: =SUM(J65:J66) -> 3993.4564 | K67: =SUM(K65:K66) -> 3993.4564 | L67: =SUM(L65:L66) -> 3993.4564 | ... Q67: =SUM(Q65:Q66) -> 47921.477 | R67: =Q67/$B$4 -> 1.1458711 | S67: 43298.7 | T67: =IFERROR(Q67/S67-1,"-") -> 0.1067648
A69: 6990-8502 | C69: Other - Condo Fee | E69: ='Allocated Expenses'!E34 -> 12354 | F69: ='Allocated Expenses'!F34 -> 0 | G69: ='Allocated Expenses'!G34 -> 0 | H69: ='Allocated Expenses'!H34 -> 12354 | I69: ='Allocated Expenses'!I34 -> 0 | J69: ='Allocated Expenses'!J34 -> 0 | K69: ='Allocated Expenses'!K34 -> 12354 | L69: ='Allocated Expenses'!L34 -> 0 | ... P69: ='Allocated Expenses'!P34 -> 0 | Q69: =SUM(E69:P69) -> 49416 | R69: =Q69/$B$4 -> 1.1816073 | S69: 61044 | T69: =IFERROR(Q69/S69-1,"-") -> -0.19048555
C71: Total Reimbursable Expenses | E71: =+E27+E29+E31+E36+E38+E43+E45+E50+E52+E54+E56+E58+E63+E67+E69 -> 37759.505 | F71: =+F27+F29+F31+F36+F38+F43+F45+F50+F52+F54+F56+F58+F63+F67+F69 -> 25496.725 | G71: =+G27+G29+G31+G36+G38+G43+G45+G50+G52+G54+G56+G58+G63+G67+G69 -> 22104.895 | H71: =+H27+H29+H31+H36+H38+H43+H45+H50+H52+H54+H56+H58+H63+H67+H69 -> 33503.645 | I71: =+I27+I29+I31+I36+I38+I43+I45+I50+I52+I54+I56+I58+I63+I67+I69 -> 21296.375 | J71: =+J27+J29+J31+J36+J38+J43+J45+J50+J52+J54+J56+J58+J63+J67+J69 -> 34495.525 | K71: =+K27+K29+K31+K36+K38+K43+K45+K50+K52+K54+K56+K58+K63+K67+K69 -> 34385.825 | L71: =+L27+L29+L31+L36+L38+L43+L45+L50+L52+L54+L56+L58+L63+L67+L69 -> 19783.165 | ... Q71: =+Q27+Q29+Q31+Q36+Q38+Q43+Q45+Q50+Q52+Q54+Q56+Q58+Q63+Q67+Q69 -> 329849.23 | R71: =Q71/$B$4 -> 7.8871674 | S71: =+S27+S29+S31+S36+S38+S43+S45+S50+S52+S54+S56+S58+S63+S67+S69 -> 362748.78 | T71: =IFERROR(Q71/S71-1,"-") -> -0.09069514 | V71: =Q71-Q29-Q58 -> 237669.45
B73: Non-Reimbursable Expenses
A75: 5210-0000 | C75: Bad Debt | E75: 0 | F75: 0 | G75: 0 | H75: 0 | I75: 0 | J75: 0 | K75: 0 | L75: 0 | M75: 0 | N75: 0 | O75: 0 | P75: 0 | Q75: =SUM(E75:P75) -> 0 | R75: =Q75/$B$4 -> 0 | T75: =IFERROR(Q75/S75-1,"-") -> -
A77: 6010-8501 | D77: Salaries & Wages | E77: ='Allocated Expenses'!E41 -> 1461.275 | F77: ='Allocated Expenses'!F41 -> 1461.275 | G77: ='Allocated Expenses'!G41 -> 1461.275 | H77: ='Allocated Expenses'!H41 -> 1461.275 | I77: ='Allocated Expenses'!I41 -> 1461.275 | J77: ='Allocated Expenses'!J41 -> 1461.275 | K77: ='Allocated Expenses'!K41 -> 1461.275 | L77: ='Allocated Expenses'!L41 -> 1461.275 | ... P77: ='Allocated Expenses'!P41 -> 1461.275 | Q77: =SUM(E77:P77) -> 17535.3 | R77: =Q77/$B$4 -> 0.41929413
A78: 6620-8501 | D78: Commissions-Internal Broker | E78: ='Allocated Expenses'!E48 -> 486.675 | F78: ='Allocated Expenses'!F48 -> 0 | G78: ='Allocated Expenses'!G48 -> 0 | H78: ='Allocated Expenses'!H48 -> 486.675 | I78: ='Allocated Expenses'!I48 -> 0 | J78: ='Allocated Expenses'!J48 -> 0 | K78: ='Allocated Expenses'!K48 -> 486.675 | L78: ='Allocated Expenses'!L48 -> 0 | ... P78: ='Allocated Expenses'!P48 -> 0 | Q78: =SUM(E78:P78) -> 1946.7 | R78: =Q78/$B$4 -> 0.046548385
C79: Leasing Salaries and Commissions | E79: =SUM(E77:E78) -> 1947.95 | F79: =SUM(F77:F78) -> 1461.275 | G79: =SUM(G77:G78) -> 1461.275 | H79: =SUM(H77:H78) -> 1947.95 | I79: =SUM(I77:I78) -> 1461.275 | J79: =SUM(J77:J78) -> 1461.275 | K79: =SUM(K77:K78) -> 1947.95 | L79: =SUM(L77:L78) -> 1461.275 | ... Q79: =SUM(Q77:Q78) -> 19482 | R79: =Q79/$B$4 -> 0.46584252 | S79: 18591.78 | T79: =IFERROR(Q79/S79-1,"-") -> 0.047882451
A81: 6110-8501 | D81: Gas | Q81: =SUM(E81:P81) -> 0 | R81: =Q81/$B$4 -> 0
A82: 6120-8501 | D82: Electric | Q82: =SUM(E82:P82) -> 0 | R82: =Q82/$B$4 -> 0
A83: 6130-8501 | D83: Water & Sewer | Q83: =SUM(E83:P83) -> 0 | R83: =Q83/$B$4 -> 0
C84: Utilities | E84: =SUM(E81:E83) -> 0 | F84: =SUM(F81:F83) -> 0 | G84: =SUM(G81:G83) -> 0 | H84: =SUM(H81:H83) -> 0 | I84: =SUM(I81:I83) -> 0 | J84: =SUM(J81:J83) -> 0 | K84: =SUM(K81:K83) -> 0 | L84: =SUM(L81:L83) -> 0 | ... Q84: =SUM(Q81:Q83) -> 0 | R84: =Q84/$B$4 -> 0 | S84: 72.3 | T84: =IFERROR(Q84/S84-1,"-") -> -1
D86: Building Maint.-Recurring | E86: =1.03*910 -> 937.3 | F86: =1.03*910 -> 937.3 | G86: =1.03*910 -> 937.3 | H86: =1.03*910 -> 937.3 | I86: =1.03*910 -> 937.3 | J86: =1.03*910 -> 937.3 | K86: =1.03*910 -> 937.3 | L86: =1.03*910 -> 937.3 | ... P86: =1.03*910 -> 937.3 | Q86: =SUM(E86:P86) -> 11247.6 | R86: =Q86/$B$4 -> 0.26894622
D87: Building Maint.-Big Projects | Q87: =SUM(E87:P87) -> 0 | R87: =Q87/$B$4 -> 0
A88: 6220-8501 | C88: Building Maintenance | E88: =SUM(E86:E87) -> 937.3 | F88: =SUM(F86:F87) -> 937.3 | G88: =SUM(G86:G87) -> 937.3 | H88: =SUM(H86:H87) -> 937.3 | I88: =SUM(I86:I87) -> 937.3 | J88: =SUM(J86:J87) -> 937.3 | K88: =SUM(K86:K87) -> 937.3 | L88: =SUM(L86:L87) -> 937.3 | ... Q88: =SUM(Q86:Q87) -> 11247.6 | R88: =Q88/$B$4 -> 0.26894622 | S88: 18810.98 | T88: =IFERROR(Q88/S88-1,"-") -> -0.40207262
A90: 6610-8501 | B90: (SC) | C90: Management fee | Q90: =SUM(E90:P90) -> 0 | R90: =Q90/$B$4 -> 0 | T90: =R90/S90-1 -> #DIV/0!
T91: =R91/S91-1 -> #DIV/0!
A92: 7110-8501 | C92: Marketing | E92: ='Allocated Expenses'!E55 -> 375 | F92: ='Allocated Expenses'!F55 -> 375 | G92: ='Allocated Expenses'!G55 -> 375 | H92: ='Allocated Expenses'!H55 -> 375 | I92: ='Allocated Expenses'!I55 -> 375 | J92: ='Allocated Expenses'!J55 -> 375 | K92: ='Allocated Expenses'!K55 -> 375 | L92: ='Allocated Expenses'!L55 -> 375 | ... P92: ='Allocated Expenses'!P55 -> 375 | Q92: =SUM(E92:P92) -> 4500 | R92: =Q92/$B$4 -> 0.10760144 | S92: 7647.6 | T92: =IFERROR(Q92/S92-1,"-") -> -0.4115801
A94: 8210-8501 | C94: Business Taxes | E94: ='Allocated Expenses'!E62 -> 0 | F94: ='Allocated Expenses'!F62 -> 0 | G94: ='Allocated Expenses'!G62 -> 0 | H94: ='Allocated Expenses'!H62 -> 950.70844 | I94: ='Allocated Expenses'!I62 -> 0 | J94: ='Allocated Expenses'!J62 -> 0 | K94: ='Allocated Expenses'!K62 -> 0 | L94: ='Allocated Expenses'!L62 -> 0 | ... P94: ='Allocated Expenses'!P62 -> 0 | Q94: =SUM(E94:P94) -> 950.70844 | R94: =Q94/$B$4 -> 0.0227328 | S94: 996 | T94: =IFERROR(Q94/S94-1,"-") -> -0.045473449
A96: 8310-8501 | C96: Legal & Accounting | E96: ='Allocated Expenses'!E69 -> 772.1 | F96: ='Allocated Expenses'!F69 -> 772.1 | G96: ='Allocated Expenses'!G69 -> 772.1 | H96: ='Allocated Expenses'!H69 -> 772.1 | I96: ='Allocated Expenses'!I69 -> 772.1 | J96: ='Allocated Expenses'!J69 -> 772.1 | K96: ='Allocated Expenses'!K69 -> 772.1 | L96: ='Allocated Expenses'!L69 -> 772.1 | ... P96: ='Allocated Expenses'!P69 -> 772.1 | Q96: =SUM(E96:P96) -> 9265.2 | R96: =Q96/$B$4 -> 0.2215442 | S96: 8453.5 | T96: =IFERROR(Q96/S96-1,"-") -> 0.0960194
A98: 8190-8501 | D98: Bank Fees | E98: ='Allocated Expenses'!E76 -> 47.895 | F98: ='Allocated Expenses'!F76 -> 47.895 | G98: ='Allocated Expenses'!G76 -> 47.895 | H98: ='Allocated Expenses'!H76 -> 47.895 | I98: ='Allocated Expenses'!I76 -> 47.895 | J98: ='Allocated Expenses'!J76 -> 47.895 | K98: ='Allocated Expenses'!K76 -> 47.895 | L98: ='Allocated Expenses'!L76 -> 47.895 | ... P98: ='Allocated Expenses'!P76 -> 47.895 | Q98: =SUM(E98:P98) -> 574.74 | R98: =Q98/$B$4 -> 0.013742856
A99: 8930-8501 | D99: Office Supplies | E99: ='Allocated Expenses'!E83 -> 0 | F99: ='Allocated Expenses'!F83 -> 0 | G99: ='Allocated Expenses'!G83 -> 0 | H99: ='Allocated Expenses'!H83 -> 0 | I99: ='Allocated Expenses'!I83 -> 0 | J99: ='Allocated Expenses'!J83 -> 0 | K99: ='Allocated Expenses'!K83 -> 0 | L99: ='Allocated Expenses'!L83 -> 0 | ... P99: ='Allocated Expenses'!P83 -> 0 | Q99: =SUM(E99:P99) -> 0 | R99: =Q99/$B$4 -> 0
A100: 8950-8501 | D100: Postage | E100: ='Allocated Expenses'!E90 -> 0 | F100: ='Allocated Expenses'!F90 -> 0 | G100: ='Allocated Expenses'!G90 -> 0 | H100: ='Allocated Expenses'!H90 -> 0 | I100: ='Allocated Expenses'!I90 -> 0 | J100: ='Allocated Expenses'!J90 -> 0 | K100: ='Allocated Expenses'!K90 -> 0 | L100: ='Allocated Expenses'!L90 -> 0 | ... P100: ='Allocated Expenses'!P90 -> 0 | Q100: =SUM(E100:P100) -> 0 | R100: =Q100/$B$4 -> 0
A101: 8990-8501 | D101: Other G&A Expense | E101: ='Allocated Expenses'!E97 -> 6.18 | F101: ='Allocated Expenses'!F97 -> 6.18 | G101: ='Allocated Expenses'!G97 -> 6.18 | H101: ='Allocated Expenses'!H97 -> 6.18 | I101: ='Allocated Expenses'!I97 -> 6.18 | J101: ='Allocated Expenses'!J97 -> 6.18 | K101: ='Allocated Expenses'!K97 -> 6.18 | L101: ='Allocated Expenses'!L97 -> 6.18 | ... P101: ='Allocated Expenses'!P97 -> 6.18 | Q101: =SUM(E101:P101) -> 74.16 | R101: =Q101/$B$4 -> 0.0017732718 | V101: Peco (est 20/mo) from JM
A102: 8990-9800 | D102: Other G&A-allocated from LIK | E102: ='Allocated Expenses'!E104 -> 1062.96 | F102: ='Allocated Expenses'!F104 -> 1062.96 | G102: ='Allocated Expenses'!G104 -> 1062.96 | H102: ='Allocated Expenses'!H104 -> 1062.96 | I102: ='Allocated Expenses'!I104 -> 1062.96 | J102: ='Allocated Expenses'!J104 -> 1062.96 | K102: ='Allocated Expenses'!K104 -> 1062.96 | L102: ='Allocated Expenses'!L104 -> 1062.96 | ... P102: ='Allocated Expenses'!P104 -> 1062.96 | Q102: =SUM(E102:P102) -> 12755.52 | R102: =Q102/$B$4 -> 0.30500275
C103: General & Administrative | E103: =SUM(E98:E102) -> 1117.035 | F103: =SUM(F98:F102) -> 1117.035 | G103: =SUM(G98:G102) -> 1117.035 | H103: =SUM(H98:H102) -> 1117.035 | I103: =SUM(I98:I102) -> 1117.035 | J103: =SUM(J98:J102) -> 1117.035 | K103: =SUM(K98:K102) -> 1117.035 | L103: =SUM(L98:L102) -> 1117.035 | ... Q103: =SUM(Q98:Q102) -> 13404.42 | R103: =Q103/$B$4 -> 0.32051888 | S103: 14517.93 | T103: =IFERROR(Q103/S103-1,"-") -> -0.076698951
C105: Total Non-Reimbursable Expenses | E105: =+E75+E79+E84+E88+E90+E92+E94+E96+E103 -> 5149.385 | F105: =+F75+F79+F84+F88+F90+F92+F94+F96+F103 -> 4662.71 | G105: =+G75+G79+G84+G88+G90+G92+G94+G96+G103 -> 4662.71 | H105: =+H75+H79+H84+H88+H90+H92+H94+H96+H103 -> 6100.0934 | I105: =+I75+I79+I84+I88+I90+I92+I94+I96+I103 -> 4662.71 | J105: =+J75+J79+J84+J88+J90+J92+J94+J96+J103 -> 4662.71 | K105: =+K75+K79+K84+K88+K90+K92+K94+K96+K103 -> 5149.385 | L105: =+L75+L79+L84+L88+L90+L92+L94+L96+L103 -> 4662.71 | ... Q105: =+Q75+Q79+Q84+Q88+Q90+Q92+Q94+Q96+Q103 -> 58849.928 | R105: =Q105/$B$4 -> 1.4071861 | S105: =+S75+S79+S84+S88+S90+S92+S94+S96+S103 -> 69090.09 | T105: =IFERROR(Q105/S105-1,"-") -> -0.14821462
B107: TOTAL OPERATING EXPENSES | E107: =+E71+E105 -> 42908.89 | F107: =+F71+F105 -> 30159.435 | G107: =+G71+G105 -> 26767.605 | H107: =+H71+H105 -> 39603.738 | I107: =+I71+I105 -> 25959.085 | J107: =+J71+J105 -> 39158.235 | K107: =+K71+K105 -> 39535.21 | L107: =+L71+L105 -> 24445.875 | ... Q107: =+Q71+Q105 -> 388699.16 | R107: =Q107/$B$4 -> 9.2943535 | S107: =+S71+S105 -> 431838.87 | T107: =IFERROR(Q107/S107-1,"-") -> -0.099897707
B109: NET OPERATING INCOME | E109: =+E24-E107 -> -1882.8107 | F109: =+F24-F107 -> 10260.333 | G109: =+G24-G107 -> 12661.889 | H109: =+H24-H107 -> -3343.4662 | I109: =+I24-I107 -> 9998.6199 | J109: =+J24-J107 -> -2822.4032 | K109: =+K24-K107 -> -2807.1662 | L109: =+L24-L107 -> 12296.276 | ... Q109: =+Q24-Q107 -> 65368.777 | R109: =Q109/$B$4 -> 1.5630611 | S109: =+S24-S107 -> -37831.18 | T109: =IFERROR(Q109/S109-1,"-") -> -2.7279074
A111: 1420-0000 | D111: Land Improvements | Q111: =SUM(E111:P111) -> 0 | R111: =Q111/$B$4 -> 0
A112: 1430-0000 | D112: Buildings | Q112: =SUM(E112:P112) -> 0 | R112: =Q112/$B$4 -> 0
A113: 1450-0000 | D113: Equipment | Q113: =SUM(E113:P113) -> 0 | R113: =Q113/$B$4 -> 0
A114: 1980-0000 | D114: Capital Improvements | Q114: =SUM(E114:P114) -> 0 | R114: =Q114/$B$4 -> 0
C115: Capital Improvements | E115: =SUM(E111:E114) -> 0 | F115: =SUM(F111:F114) -> 0 | G115: =SUM(G111:G114) -> 0 | H115: =SUM(H111:H114) -> 0 | I115: =SUM(I111:I114) -> 0 | J115: =SUM(J111:J114) -> 0 | K115: =SUM(K111:K114) -> 0 | L115: =SUM(L111:L114) -> 0 | ... Q115: =SUM(Q111:Q114) -> 0 | R115: =Q115/$B$4 -> 0 | T115: =IFERROR(Q115/S115-1,"-") -> -
A117: 1440-0000 | C117: Tenant Improvements | E117: ='Renew & Vac - Rent, TI, LC'!AH11 -> 9576 | F117: ='Renew & Vac - Rent, TI, LC'!AI11 -> 0 | G117: ='Renew & Vac - Rent, TI, LC'!AJ11 -> 0 | H117: ='Renew & Vac - Rent, TI, LC'!AK11 -> 0 | I117: ='Renew & Vac - Rent, TI, LC'!AL11 -> 0 | J117: ='Renew & Vac - Rent, TI, LC'!AM11 -> 0 | K117: ='Renew & Vac - Rent, TI, LC'!AN11 -> 0 | L117: ='Renew & Vac - Rent, TI, LC'!AO11 -> 0 | ... P117: ='Renew & Vac - Rent, TI, LC'!AS11 -> 0 | Q117: =SUM(E117:P117) -> 12582 | R117: =Q117/$B$4 -> 0.30085364 | S117: 1633.93 | T117: =IFERROR(Q117/S117-1,"-") -> 6.7004523
D119: Deferred Marketing | Q119: =SUM(E119:P119) -> 0 | R119: =Q119/$B$4 -> 0
D120: Outside Leasing Commissions | E120: ='Renew & Vac - Rent, TI, LC'!AH12 -> 10383.68 | F120: ='Renew & Vac - Rent, TI, LC'!AI12 -> 4539.6 | G120: ='Renew & Vac - Rent, TI, LC'!AJ12 -> 0 | H120: ='Renew & Vac - Rent, TI, LC'!AK12 -> 0 | I120: ='Renew & Vac - Rent, TI, LC'!AL12 -> 0 | J120: ='Renew & Vac - Rent, TI, LC'!AM12 -> 652.65 | K120: ='Renew & Vac - Rent, TI, LC'!AN12 -> 648.945 | L120: ='Renew & Vac - Rent, TI, LC'!AO12 -> 900.72 | ... P120: ='Renew & Vac - Rent, TI, LC'!AS12 -> 0 | Q120: =SUM(E120:P120) -> 18207.755 | R120: =Q120/$B$4 -> 0.4353735
A121: 1940-8501 | C121: Outside Leasing Commissions | E121: =SUM(E119:E120) -> 10383.68 | F121: =SUM(F119:F120) -> 4539.6 | G121: =SUM(G119:G120) -> 0 | H121: =SUM(H119:H120) -> 0 | I121: =SUM(I119:I120) -> 0 | J121: =SUM(J119:J120) -> 652.65 | K121: =SUM(K119:K120) -> 648.945 | L121: =SUM(L119:L120) -> 900.72 | ... Q121: =SUM(Q119:Q120) -> 18207.755 | R121: =Q121/$B$4 -> 0.4353735 | S121: 4645.54 | T121: =IFERROR(Q121/S121-1,"-") -> 2.9194055 | V121: 7/2025 Reprojection is for Capitalized Lease Costs
B123: CASH FLOW BEFORE DEBT SERVICE | E123: =+E109-E115-E117-E121 -> -21842.491 | F123: =+F109-F115-F117-F121 -> 5720.7333 | G123: =+G109-G115-G117-G121 -> 12661.889 | H123: =+H109-H115-H117-H121 -> -3343.4662 | I123: =+I109-I115-I117-I121 -> 9998.6199 | J123: =+J109-J115-J117-J121 -> -3475.0532 | K123: =+K109-K115-K117-K121 -> -3456.1112 | L123: =+L109-L115-L117-L121 -> 11395.556 | ... Q123: =+Q109-Q115-Q117-Q121 -> 34579.022 | R123: =Q123/$B$4 -> 0.82683393 | S123: =+S109-S115-S117-S121 -> -44110.65 | T123: =IFERROR(Q123/S123-1,"-") -> -1.7839155
B125: Debt Service
A126: 9210-8501 | C126: Interest | E126: ='Allocated Expenses'!E112 -> 6906.6 | F126: ='Allocated Expenses'!F112 -> 6906.6 | G126: ='Allocated Expenses'!G112 -> 6906.6 | H126: ='Allocated Expenses'!H112 -> 6906.6 | I126: ='Allocated Expenses'!I112 -> 6906.6 | J126: ='Allocated Expenses'!J112 -> 6906.6 | K126: ='Allocated Expenses'!K112 -> 6906.6 | L126: ='Allocated Expenses'!L112 -> 6906.6 | ... P126: ='Allocated Expenses'!P112 -> 6906.6 | Q126: =SUM(E126:P126) -> 82879.2 | R126: =Q126/$B$4 -> 1.9817604 | S126: 83901 | T126: =IFERROR(Q126/S126-1,"-") -> -0.012178639
A127: 2740-8501 | C127: Mortgage Amortization | E127: =+'Allocated Expenses'!E124 -> 0 | F127: =+'Allocated Expenses'!F124 -> 0 | G127: =+'Allocated Expenses'!G124 -> 0 | H127: =+'Allocated Expenses'!H124 -> 0 | I127: =+'Allocated Expenses'!I124 -> 0 | J127: =+'Allocated Expenses'!J124 -> 0 | K127: =+'Allocated Expenses'!K124 -> 0 | L127: =+'Allocated Expenses'!L124 -> 0 | ... P127: =+'Allocated Expenses'!P124 -> 0 | Q127: =SUM(E127:P127) -> 0 | R127: =Q127/$B$4 -> 0 | S127: 9141.87 | T127: =IFERROR(Q127/S127-1,"-") -> -1
A128: 2740-0000 | C128: Loan Proceeds | Q128: =SUM(E128:P128) -> 0 | R128: =Q128/$B$4 -> 0 | T128: =IFERROR(Q128/S128-1,"-") -> -
C129: Total Debt Service | E129: =SUM(E126:E128) -> 6906.6 | F129: =SUM(F126:F128) -> 6906.6 | G129: =SUM(G126:G128) -> 6906.6 | H129: =SUM(H126:H128) -> 6906.6 | I129: =SUM(I126:I128) -> 6906.6 | J129: =SUM(J126:J128) -> 6906.6 | K129: =SUM(K126:K128) -> 6906.6 | L129: =SUM(L126:L128) -> 6906.6 | ... Q129: =SUM(Q126:Q128) -> 82879.2 | R129: =Q129/$B$4 -> 1.9817604 | S129: =SUM(S126:S128) -> 93042.87 | T129: =IFERROR(Q129/S129-1,"-") -> -0.10923642
B131: CASH FLOW AFTER DEBT SERVICE | E131: =+E123-E129 -> -28749.091 | F131: =+F123-F129 -> -1185.8667 | G131: =+G123-G129 -> 5755.2891 | H131: =+H123-H129 -> -10250.066 | I131: =+I123-I129 -> 3092.0199 | J131: =+J123-J129 -> -10381.653 | K131: =+K123-K129 -> -10362.711 | L131: =+L123-L129 -> 4488.9558 | ... Q131: =+Q123-Q129 -> -48300.178 | R131: =Q131/$B$4 -> -1.1549264 | S131: =+S123-S129 -> -137153.52 | T131: =IFERROR(Q131/S131-1,"-") -> -0.64783858
D135: ="Budget Import - "&B1 -> Budget Import - 3610 | E135: 5 | F135: =E135+1 -> 6 | G135: =F135+1 -> 7 | H135: =G135+1 -> 8 | I135: =H135+1 -> 9 | J135: =I135+1 -> 10 | K135: =J135+1 -> 11 | L135: =K135+1 -> 12 | M135: =L135+1 -> 13 | ... P135: =O135+1 -> 16 | Q135: <- Lookup Column
D136: Account | E136: 1 | F136: 2 | G136: 3 | H136: 4 | I136: 5 | J136: 6 | K136: 7 | L136: 8 | M136: 9 | N136: 10 | O136: 11 | P136: 12 | Q136: Total
A137: =VLOOKUP($D137,$A$10:$D$130,3,FALSE) -> Rental Income - In Place | D137: 4230-8501 | E137: =-(VLOOKUP($D137,$A$10:$P$131,E$135,FALSE)+E11) -> -34697.005 | F137: =-(VLOOKUP($D137,$A$10:$P$131,F$135,FALSE)+F11) -> -34697.008 | G137: =-(VLOOKUP($D137,$A$10:$P$131,G$135,FALSE)+G11) -> -34697.008 | H137: =-(VLOOKUP($D137,$A$10:$P$131,H$135,FALSE)+H11) -> -32672.588 | I137: =-(VLOOKUP($D137,$A$10:$P$131,I$135,FALSE)+I11) -> -32672.588 | J137: =-(VLOOKUP($D137,$A$10:$P$131,J$135,FALSE)+J11) -> -32795.922 | K137: =-(VLOOKUP($D137,$A$10:$P$131,K$135,FALSE)+K11) -> -32795.917 | L137: =-(VLOOKUP($D137,$A$10:$P$131,L$135,FALSE)+L11) -> -32830.667 | ... P137: =-(VLOOKUP($D137,$A$10:$P$131,P$135,FALSE)+P11) -> -34286.167 | Q137: =SUM(E137:P137) -> -402044.87
A138: =VLOOKUP($D138,$A$10:$D$130,3,FALSE) -> Electric | D138: 4710-8502 | E138: =-VLOOKUP($D138,$A$10:$P$131,E$135,FALSE) -> -4529.0742 | F138: =-VLOOKUP($D138,$A$10:$P$131,F$135,FALSE) -> -3922.7598 | G138: =-VLOOKUP($D138,$A$10:$P$131,G$135,FALSE) -> -2932.4856 | H138: =-VLOOKUP($D138,$A$10:$P$131,H$135,FALSE) -> -1787.6838 | I138: =-VLOOKUP($D138,$A$10:$P$131,I$135,FALSE) -> -1485.1164 | J138: =-VLOOKUP($D138,$A$10:$P$131,J$135,FALSE) -> -1739.91 | K138: =-VLOOKUP($D138,$A$10:$P$131,K$135,FALSE) -> -2132.127 | L138: =-VLOOKUP($D138,$A$10:$P$131,L$135,FALSE) -> -2111.484 | ... P138: =-VLOOKUP($D138,$A$10:$P$131,P$135,FALSE) -> -4106.7774 | Q138: =SUM(E138:P138) -> -30423.064
A139: =VLOOKUP($D139,$A$10:$D$130,3,FALSE) -> Common Area Maintenance | D139: 4910-8502 | E139: =-VLOOKUP($D139,$A$10:$P$131,E$135,FALSE) -> -1670 | F139: =-VLOOKUP($D139,$A$10:$P$131,F$135,FALSE) -> -1670 | G139: =-VLOOKUP($D139,$A$10:$P$131,G$135,FALSE) -> -1670 | H139: =-VLOOKUP($D139,$A$10:$P$131,H$135,FALSE) -> -1670 | I139: =-VLOOKUP($D139,$A$10:$P$131,I$135,FALSE) -> -1670 | J139: =-VLOOKUP($D139,$A$10:$P$131,J$135,FALSE) -> -1670 | K139: =-VLOOKUP($D139,$A$10:$P$131,K$135,FALSE) -> -1670 | L139: =-VLOOKUP($D139,$A$10:$P$131,L$135,FALSE) -> -1670 | ... P139: =-VLOOKUP($D139,$A$10:$P$131,P$135,FALSE) -> -1670 | Q139: =SUM(E139:P139) -> -20040
...

Sheet 362
B1: 3620 | J1: =+'JV III Consolidated'!J1 -> Operating Budget | Q1: ='JV III Consolidated'!Q1 -> 46023
J2: =+'JV III Consolidated'!J2 -> Lincoln JV III
Q3: =Q1 -> 46023 | S3: 7/2025 Reprojections
B4: ='Renew & Vac - Rent, TI, LC'!A28 -> 49020 | E4: Jan | F4: Feb | G4: Mar | H4: Apr | I4: May | J4: Jun | K4: Jul | L4: Aug | M4: Sep | N4: Oct | O4: Nov | P4: Dec | Q4: Total | R4: Total PSF | S4: Total | T4: Var. | U4: Input | V4: Notes
D6: Occupancy % | E6: ='Renew & Vac - Rent, TI, LC'!AH31 -> 0.4266 | F6: ='Renew & Vac - Rent, TI, LC'!AI31 -> 0.4266 | G6: ='Renew & Vac - Rent, TI, LC'!AJ31 -> 0.4266 | H6: ='Renew & Vac - Rent, TI, LC'!AK31 -> 0.4266 | I6: ='Renew & Vac - Rent, TI, LC'!AL31 -> 0.4266 | J6: ='Renew & Vac - Rent, TI, LC'!AM31 -> 0.4266 | K6: ='Renew & Vac - Rent, TI, LC'!AN31 -> 0.4266 | L6: ='Renew & Vac - Rent, TI, LC'!AO31 -> 0.4266 | ... P6: ='Renew & Vac - Rent, TI, LC'!AS31 -> 0.4092
D7: Occupancy SF | E7: =$B$4*E6 -> 20911.932 | F7: =$B$4*F6 -> 20911.932 | G7: =$B$4*G6 -> 20911.932 | H7: =$B$4*H6 -> 20911.932 | I7: =$B$4*I6 -> 20911.932 | J7: =$B$4*J6 -> 20911.932 | K7: =$B$4*K6 -> 20911.932 | L7: =$B$4*L6 -> 20911.932 | ... P7: =$B$4*P6 -> 20058.984
B8: Revenues
A10: 4230-8501 | C10: Rental Income - In Place | E10: =SUMIFS('In Place Revenue'!$G:$G,'In Place Revenue'!$A:$A,$B$1,'In Place Revenue'!$H:$H,1) -> 30972.1 | F10: =SUMIFS('In Place Revenue'!$G:$G,'In Place Revenue'!$A:$A,$B$1,'In Place Revenue'!$H:$H,2) -> 30972.1 | G10: =SUMIFS('In Place Revenue'!$G:$G,'In Place Revenue'!$A:$A,$B$1,'In Place Revenue'!$H:$H,3) -> 30972.1 | H10: =SUMIFS('In Place Revenue'!$G:$G,'In Place Revenue'!$A:$A,$B$1,'In Place Revenue'!$H:$H,4) -> 26791.43 | I10: =SUMIFS('In Place Revenue'!$G:$G,'In Place Revenue'!$A:$A,$B$1,'In Place Revenue'!$H:$H,5) -> 25362.26 | J10: =SUMIFS('In Place Revenue'!$G:$G,'In Place Revenue'!$A:$A,$B$1,'In Place Revenue'!$H:$H,6) -> 23467.01 | K10: =SUMIFS('In Place Revenue'!$G:$G,'In Place Revenue'!$A:$A,$B$1,'In Place Revenue'!$H:$H,7) -> 23467.01 | L10: =SUMIFS('In Place Revenue'!$G:$G,'In Place Revenue'!$A:$A,$B$1,'In Place Revenue'!$H:$H,8) -> 23485.55 | M10: =SUMIFS('In Place Revenue'!$G:$G,'In Place Revenue'!$A:$A,$B$1,'In Place Revenue'!$H:$H,9) -> 23772.11 | N10: =SUMIFS('In Place Revenue'!$G:$G,'In Place Revenue'!$A:$A,$B$1,'In Place Revenue'!$H:$H,10) -> 23772.11 | O10: =SUMIFS('In Place Revenue'!$G:$G,'In Place Revenue'!$A:$A,$B$1,'In Place Revenue'!$H:$H,11) -> 23772.11 | P10: =SUMIFS('In Place Revenue'!$G:$G,'In Place Revenue'!$A:$A,$B$1,'In Place Revenue'!$H:$H,12) -> 23772.11 | Q10: =SUM(E10:P10) -> 310578 | R10: =Q10/$B$4 -> 6.3357405 | S10: 403669.53 | T10: =IFERROR((Q10+Q11)/S10-1,"-") -> 0.0072897171 | U10: DW | V10: Home Solutions Realty expected to renew 6/1 but at a reduced rent ($18.50 from $19.00)
A11: 4230-8501 | C11: Rental Income - New & Renewal | E11: ='Renew & Vac - Rent, TI, LC'!AH32 -> 2962.875 | F11: ='Renew & Vac - Rent, TI, LC'!AI32 -> 2962.875 | G11: ='Renew & Vac - Rent, TI, LC'!AJ32 -> 2962.875 | H11: ='Renew & Vac - Rent, TI, LC'!AK32 -> 7058.9583 | I11: ='Renew & Vac - Rent, TI, LC'!AL32 -> 8569.7917 | J11: ='Renew & Vac - Rent, TI, LC'!AM32 -> 10415.167 | K11: ='Renew & Vac - Rent, TI, LC'!AN32 -> 10415.167 | L11: ='Renew & Vac - Rent, TI, LC'!AO32 -> 10415.167 | ... P11: ='Renew & Vac - Rent, TI, LC'!AS32 -> 9025.7917 | Q11: =SUM(E11:P11) -> 96034.167 | R11: =Q11/$B$4 -> 1.9590813 | T11: =IFERROR(Q11/S11-1,"-") -> -
A12: 4240-8501 | C12: Percentage Rent | E12: 0 | F12: 0 | G12: 0 | H12: 0 | I12: 0 | J12: 0 | K12: 0 | L12: 0 | M12: 0 | N12: 0 | O12: 0 | P12: 0 | Q12: =SUM(E12:P12) -> 0 | R12: =Q12/$B$4 -> 0 | T12: =R12/S12-1 -> #DIV/0! | W12: =G12-H12 -> 0
A13: 4990-8501 | C13: Miscellaneous | E13: 0 | F13: 0 | G13: 0 | H13: 0 | I13: 0 | J13: 0 | K13: 0 | L13: 0 | M13: 0 | N13: 0 | O13: 0 | P13: 0 | Q13: =SUM(E13:P13) -> 0 | R13: =Q13/$B$4 -> 0 | T13: =IFERROR(Q13/S13-1,"-") -> -
A14: 9190-8501 | C14: Interest Income | E14: 0 | F14: 0 | G14: 0 | H14: 0 | I14: 0 | J14: 0 | K14: 0 | L14: 0 | M14: 0 | N14: 0 | O14: 0 | P14: 0 | Q14: =SUM(E14:P14) -> 0 | R14: =Q14/$B$4 -> 0 | T14: =IFERROR(Q14/S14-1,"-") -> -
C15: Total Rental and Other | E15: =SUM(E10:E14) -> 33934.975 | F15: =SUM(F10:F14) -> 33934.975 | G15: =SUM(G10:G14) -> 33934.975 | H15: =SUM(H10:H14) -> 33850.388 | I15: =SUM(I10:I14) -> 33932.052 | J15: =SUM(J10:J14) -> 33882.177 | K15: =SUM(K10:K14) -> 33882.177 | L15: =SUM(L10:L14) -> 33900.717 | ... Q15: =SUM(Q10:Q14) -> 406612.17 | R15: =Q15/$B$4 -> 8.2948218 | S15: =SUM(S10:S14) -> 403669.53 | T15: =IFERROR(Q15/S15-1,"-") -> 0.0072897171
B17: Reimbursements
A18: 4710-8502 | C18: Electric | E18: =E6*E29 -> 2270.7918 | F18: =F6*F29 -> 2138.5458 | G18: =G6*G29 -> 1749.06 | H18: =H6*H29 -> 1174.8564 | I18: =I6*I29 -> 1109.5866 | J18: =J6*J29 -> 1199.1726 | K18: =K6*K29 -> 1457.2656 | L18: =L6*L29 -> 1546.8516 | ... P18: =P6*P29 -> 2027.586 | Q18: =SUM(E18:P18) -> 18526.768 | R18: =Q18/$B$4 -> 0.37794304 | S18: 24752.02 | T18: =IFERROR(Q18/S18-1,"-") -> -0.25150482 | U18: DW | V18: =Q18/Q29*100&"% Set to occupancy" -> 42.4623950860627% Set to occupancy
A19: 4910-8502 | C19: Common Area Maintenance | E19: =+'Tenant Recoveries'!G21 -> 1900 | F19: =+E19 -> 1900 | G19: =+F19 -> 1900 | H19: =+G19 -> 1900 | I19: =+H19 -> 1900 | J19: =+I19 -> 1900 | K19: =+J19 -> 1900 | L19: =+K19 -> 1900 | M19: =+L19 -> 1900 | ... P19: =+O19 -> 1900 | Q19: =SUM(E19:P19) -> 22800 | R19: =Q19/$B$4 -> 0.46511628 | S19: 20384 | T19: =IFERROR(Q19/S19-1,"-") -> 0.11852433 | V19: =Q19/(Q71-Q63-Q58-Q29) -> 0.11547064
A20: 4920-8502 | C20: Real Estate Taxes | E20: =+'Tenant Recoveries'!G22 -> 200 | F20: =+E20 -> 200 | G20: =+F20 -> 200 | H20: =+G20 -> 200 | I20: =+H20 -> 200 | J20: =+I20 -> 200 | K20: =+J20 -> 200 | L20: =+K20 -> 200 | M20: =+L20 -> 200 | ... P20: =+O20 -> 200 | Q20: =SUM(E20:P20) -> 2400 | R20: =Q20/$B$4 -> 0.048959608 | S20: 2760 | T20: =IFERROR(Q20/S20-1,"-") -> -0.13043478 | V20: =Q20/Q58 -> 0.056345444
A21: 4930-8502 | C21: Insurance | Q21: =SUM(E21:P21) -> 0 | R21: =Q21/$B$4 -> 0 | T21: =IFERROR(Q21/S21-1,"-") -> -
C22: Total Reimbursements | E22: =SUM(E18:E21) -> 4370.7918 | F22: =SUM(F18:F21) -> 4238.5458 | G22: =SUM(G18:G21) -> 3849.06 | H22: =SUM(H18:H21) -> 3274.8564 | I22: =SUM(I18:I21) -> 3209.5866 | J22: =SUM(J18:J21) -> 3299.1726 | K22: =SUM(K18:K21) -> 3557.2656 | L22: =SUM(L18:L21) -> 3646.8516 | ... Q22: =SUM(Q18:Q21) -> 43726.768 | R22: =Q22/$B$4 -> 0.89201892 | S22: =SUM(S18:S21) -> 47896.02 | T22: =IFERROR(Q22/S22-1,"-") -> -0.087047993
R23: =Q23/$B$4 -> 0
B24: TOTAL REVENUES | E24: =+E15+E22 -> 38305.767 | F24: =+F15+F22 -> 38173.521 | G24: =+G15+G22 -> 37784.035 | H24: =+H15+H22 -> 37125.245 | I24: =+I15+I22 -> 37141.638 | J24: =+J15+J22 -> 37181.349 | K24: =+K15+K22 -> 37439.442 | L24: =+L15+L22 -> 37547.568 | ... Q24: =+Q15+Q22 -> 450338.93 | R24: =Q24/$B$4 -> 9.1868408 | S24: =+S15+S22 -> 451565.55 | T24: =IFERROR(Q24/S24-1,"-") -> -0.0027163625
B26: Reimbursable Expenses
A27: 6030-8502 | C27: Maintenance Salaries | E27: ='Allocated Expenses'!E5 -> 1376.0833 | F27: ='Allocated Expenses'!F5 -> 1376.0833 | G27: ='Allocated Expenses'!G5 -> 1376.0833 | H27: ='Allocated Expenses'!H5 -> 1376.0833 | I27: ='Allocated Expenses'!I5 -> 1376.0833 | J27: ='Allocated Expenses'!J5 -> 1376.0833 | K27: ='Allocated Expenses'!K5 -> 1376.0833 | L27: ='Allocated Expenses'!L5 -> 1376.0833 | ... P27: ='Allocated Expenses'!P5 -> 1376.0833 | Q27: =SUM(E27:P27) -> 16513 | R27: =Q27/$B$4 -> 0.33686251 | S27: 10684.65 | T27: =IFERROR(Q27/S27-1,"-") -> 0.54548815
A29: 6120-8502 | C29: Electric | E29: 5323 | F29: 5013 | G29: 4100 | H29: 2754 | I29: 2601 | J29: 2811 | K29: 3416 | L29: 3626 | M29: 3014 | N29: 2860 | O29: 3158 | P29: 4955 | Q29: =SUM(E29:P29) -> 43631 | R29: =Q29/$B$4 -> 0.89006528 | S29: 41563.41 | T29: =IFERROR(Q29/S29-1,"-") -> 0.049745437 | U29: DW | V29: Data\Shared\Properties\Business Plans - All Entities\2026\ISG Electric data
A31: 6130-8502 | C31: Water & Sewer | E31: ='Water Sewer'!D14 -> 1320.46 | F31: ='Water Sewer'!E14 -> 1207.16 | G31: ='Water Sewer'!F14 -> 1658.3 | H31: ='Water Sewer'!G14 -> 259.56 | I31: ='Water Sewer'!H14 -> 259.56 | J31: ='Water Sewer'!I14 -> 445.99 | K31: ='Water Sewer'!J14 -> 616.97 | L31: ='Water Sewer'!K14 -> 697.31 | ... P31: ='Water Sewer'!O14 -> 1413.16 | Q31: =SUM(E31:P31) -> 10220.69 | R31: =Q31/$B$4 -> 0.20850041 | S31: 9618.34 | T31: =IFERROR(Q31/S31-1,"-") -> 0.062625152 | V31: 2025 Business Plan grown 3%
D33: Building Maint.-Contractual | E33: ='Building Maint'!C14 -> 1931 | F33: ='Building Maint'!D14 -> 1756 | G33: ='Building Maint'!E14 -> 1006 | H33: ='Building Maint'!F14 -> 2792 | I33: ='Building Maint'!G14 -> 1756 | J33: ='Building Maint'!H14 -> 1006 | K33: ='Building Maint'!I14 -> 1931 | L33: ='Building Maint'!J14 -> 1756 | ... P33: ='Building Maint'!N14 -> 1006 | Q33: =SUM(E33:P33) -> 20494 | R33: =Q33/$B$4 -> 0.41807426
D34: Building Maint.-Recurring | E34: ='Building Maint'!C7 -> 2115 | F34: ='Building Maint'!D7 -> 2090 | G34: ='Building Maint'!E7 -> 1815 | H34: ='Building Maint'!F7 -> 2215 | I34: ='Building Maint'!G7 -> 4290 | J34: ='Building Maint'!H7 -> 1965 | K34: ='Building Maint'!I7 -> 2115 | L34: ='Building Maint'!J7 -> 1690 | ... P34: ='Building Maint'!N7 -> 1790 | Q34: =SUM(E34:P34) -> 28185 | R34: =Q34/$B$4 -> 0.5749694
D35: Building Maint.-Big Projects | F35: =1.03*1500 -> 1545 | J35: =1.03*15000 -> 15450 | N35: =1.03*1500 -> 1545 | Q35: =SUM(E35:P35) -> 18540 | R35: =Q35/$B$4 -> 0.37821297
A36: 6220-8502 | C36: Building Maintenance | E36: =SUM(E33:E35) -> 4046 | F36: =SUM(F33:F35) -> 5391 | G36: =SUM(G33:G35) -> 2821 | H36: =SUM(H33:H35) -> 5007 | I36: =SUM(I33:I35) -> 6046 | J36: =SUM(J33:J35) -> 18421 | K36: =SUM(K33:K35) -> 4046 | L36: =SUM(L33:L35) -> 3446 | ... Q36: =SUM(Q33:Q35) -> 67219 | R36: =Q36/$B$4 -> 1.3712566 | S36: 42613.28 | T36: =IFERROR(Q36/S36-1,"-") -> 0.57741906
A38: 6330-850 | B38: (SC) | C38: Parking Lot Cleaning | Q38: =SUM(E38:P38) -> 0 | R38: =Q38/$B$4 -> 0
D40: Parking Lot Maint.-Contractual | Q40: =SUM(E40:P40) -> 0 | R40: =Q40/$B$4 -> 0
D41: Parking Lot Maint.-Recurring | E41: ='Parking Lot Maint'!C7 -> 0 | F41: ='Parking Lot Maint'!D7 -> 0 | G41: ='Parking Lot Maint'!E7 -> 0 | H41: ='Parking Lot Maint'!F7 -> 0 | I41: ='Parking Lot Maint'!G7 -> 0 | J41: ='Parking Lot Maint'!H7 -> 0 | K41: ='Parking Lot Maint'!I7 -> 0 | L41: ='Parking Lot Maint'!J7 -> 0 | ... P41: ='Parking Lot Maint'!N7 -> 0 | Q41: =SUM(E41:P41) -> 0 | R41: =Q41/$B$4 -> 0
D42: Parking Lot Maint.-Big Projects | Q42: =SUM(E42:P42) -> 0 | R42: =Q42/$B$4 -> 0
A43: 6330-8502 | C43: Parking Lot Maintenance | E43: =SUM(E40:E42) -> 0 | F43: =SUM(F40:F42) -> 0 | G43: =SUM(G40:G42) -> 0 | H43: =SUM(H40:H42) -> 0 | I43: =SUM(I40:I42) -> 0 | J43: =SUM(J40:J42) -> 0 | K43: =SUM(K40:K42) -> 0 | L43: =SUM(L40:L42) -> 0 | ... Q43: =SUM(Q40:Q42) -> 0 | R43: =Q43/$B$4 -> 0 | S43: 400 | T43: =IFERROR(Q43/S43-1,"-") -> -1
A45: 6370-8502 | C45: Snow Removal | Q45: =SUM(E45:P45) -> 0 | R45: =Q45/$B$4 -> 0 | T45: =IFERROR(Q45/S45-1,"-") -> -
Q46: =SUM(E46:P46) -> 0
D47: Landscaping-Contractual | Q47: =SUM(E47:P47) -> 0 | R47: =Q47/$B$4 -> 0
D48: Landscaping-Recurring | E48: =Landscaping!C7 -> 0 | F48: =Landscaping!D7 -> 0 | G48: =Landscaping!E7 -> 0 | H48: =Landscaping!F7 -> 0 | I48: =Landscaping!G7 -> 0 | J48: =Landscaping!H7 -> 0 | K48: =Landscaping!I7 -> 0 | L48: =Landscaping!J7 -> 0 | ... P48: =Landscaping!N7 -> 0 | Q48: =SUM(E48:P48) -> 0 | R48: =Q48/$B$4 -> 0
D49: Landscaping-Big Projects | Q49: =SUM(E49:P49) -> 0 | R49: =Q49/$B$4 -> 0
A50: 6380-8502 | C50: Landscaping | E50: =SUM(E47:E49) -> 0 | F50: =SUM(F47:F49) -> 0 | G50: =SUM(G47:G49) -> 0 | H50: =SUM(H47:H49) -> 0 | I50: =SUM(I47:I49) -> 0 | J50: =SUM(J47:J49) -> 0 | K50: =SUM(K47:K49) -> 0 | L50: =SUM(L47:L49) -> 0 | ... Q50: =SUM(Q47:Q49) -> 0 | R50: =Q50/$B$4 -> 0 | S50: 158 | T50: =IFERROR(Q50/S50-1,"-") -> -1
A52: 6350-8502 | C52: Security | Q52: =SUM(E52:P52) -> 0 | R52: =Q52/$B$4 -> 0 | T52: =IFERROR(Q52/S52-1,"-") -> -
A54: 6610-8502 | B54: (BP) | C54: Management Fee | E54: =ROUND(E$24*0.04,0) -> 1532 | F54: =ROUND(F$24*0.04,0) -> 1527 | G54: =ROUND(G$24*0.04,0) -> 1511 | H54: =ROUND(H$24*0.04,0) -> 1485 | I54: =ROUND(I$24*0.04,0) -> 1486 | J54: =ROUND(J$24*0.04,0) -> 1487 | K54: =ROUND(K$24*0.04,0) -> 1498 | L54: =ROUND(L$24*0.04,0) -> 1502 | ... P54: =ROUND(P$24*0.04,0) -> 1477 | Q54: =SUM(E54:P54) -> 18013 | R54: =Q54/$B$4 -> 0.36746226 | S54: 18733.06 | T54: =IFERROR(Q54/S54-1,"-") -> -0.038437948
A56: 6270-8502 | C56: Trash Removal | E56: =Trash!C7 -> 0 | F56: =Trash!D7 -> 0 | G56: =Trash!E7 -> 0 | H56: =Trash!F7 -> 0 | I56: =Trash!G7 -> 0 | J56: =Trash!H7 -> 0 | K56: =Trash!I7 -> 0 | L56: =Trash!J7 -> 0 | ... P56: =Trash!N7 -> 0 | Q56: =SUM(E56:P56) -> 0 | R56: =Q56/$B$4 -> 0 | S56: 43 | T56: =IFERROR(Q56/S56-1,"-") -> -1
A58: 6410-8502 | C58: Real Estate Taxes | E58: =+'INS RET'!E33 -> 3549.5328 | F58: =+'INS RET'!F33 -> 3549.5328 | G58: =+'INS RET'!G33 -> 3549.5328 | H58: =+'INS RET'!H33 -> 3549.5328 | I58: =+'INS RET'!I33 -> 3549.5328 | J58: =+'INS RET'!J33 -> 3549.5328 | K58: =+'INS RET'!K33 -> 3549.5328 | L58: =+'INS RET'!L33 -> 3549.5328 | ... P58: =+'INS RET'!P33 -> 3549.5328 | Q58: =SUM(E58:P58) -> 42594.394 | R58: =Q58/$B$4 -> 0.86891868 | S58: 115339.37 | T58: =IFERROR(Q58/S58-1,"-") -> -0.63070378
D60: Insurance-Liability | E60: =+'INS RET'!E13+'INS RET'!E14 -> 1338 | F60: =+'INS RET'!F13+'INS RET'!F14 -> 1338 | G60: =+'INS RET'!G13+'INS RET'!G14 -> 1338 | H60: =+'INS RET'!H13+'INS RET'!H14 -> 1338 | I60: =+'INS RET'!I13+'INS RET'!I14 -> 1338 | J60: =+'INS RET'!J13+'INS RET'!J14 -> 1338 | K60: =+'INS RET'!K13+'INS RET'!K14 -> 1338 | L60: =+'INS RET'!L13+'INS RET'!L14 -> 1338 | ... P60: =+'INS RET'!P13+'INS RET'!P14 -> 1364.76 | Q60: =SUM(E60:P60) -> 16109.52 | R60: =Q60/$B$4 -> 0.32863158
D61: Insurabce-Property | E61: =+'INS RET'!E16 -> 403 | F61: =+'INS RET'!F16 -> 403 | G61: =+'INS RET'!G16 -> 403 | H61: =+'INS RET'!H16 -> 403 | I61: =+'INS RET'!I16 -> 403 | J61: =+'INS RET'!J16 -> 403 | K61: =+'INS RET'!K16 -> 403 | L61: =+'INS RET'!L16 -> 403 | ... P61: =+'INS RET'!P16 -> 411.06 | Q61: =SUM(E61:P61) -> 4852.12 | R61: =Q61/$B$4 -> 0.098982456
D62: Insurance-Other | E62: =+'INS RET'!E17 -> 0 | F62: =+'INS RET'!F17 -> 0 | G62: =+'INS RET'!G17 -> 0 | H62: =+'INS RET'!H17 -> 0 | I62: =+'INS RET'!I17 -> 0 | J62: =+'INS RET'!J17 -> 0 | K62: =+'INS RET'!K17 -> 0 | L62: =+'INS RET'!L17 -> 0 | ... P62: =+'INS RET'!P17 -> 0 | Q62: =SUM(E62:P62) -> 0 | R62: =Q62/$B$4 -> 0
A63: 6510-8502 | C63: Insurance | E63: =SUM(E60:E62) -> 1741 | F63: =SUM(F60:F62) -> 1741 | G63: =SUM(G60:G62) -> 1741 | H63: =SUM(H60:H62) -> 1741 | I63: =SUM(I60:I62) -> 1741 | J63: =SUM(J60:J62) -> 1741 | K63: =SUM(K60:K62) -> 1741 | L63: =SUM(L60:L62) -> 1741 | ... Q63: =SUM(Q60:Q62) -> 20961.64 | R63: =Q63/$B$4 -> 0.42761404 | S63: 20160 | T63: =IFERROR(Q63/S63-1,"-") -> 0.039763889
D65: Cleaning & Supplies | E65: ='Allocated Expenses'!E12+'Allocated Expenses'!E19 -> 2111.8137 | F65: ='Allocated Expenses'!F12+'Allocated Expenses'!F19 -> 2111.8137 | G65: ='Allocated Expenses'!G12+'Allocated Expenses'!G19 -> 2111.8137 | H65: ='Allocated Expenses'!H12+'Allocated Expenses'!H19 -> 2111.8137 | I65: ='Allocated Expenses'!I12+'Allocated Expenses'!I19 -> 2111.8137 | J65: ='Allocated Expenses'!J12+'Allocated Expenses'!J19 -> 2111.8137 | K65: ='Allocated Expenses'!K12+'Allocated Expenses'!K19 -> 2111.8137 | L65: ='Allocated Expenses'!L12+'Allocated Expenses'!L19 -> 2111.8137 | ... P65: ='Allocated Expenses'!P12+'Allocated Expenses'!P19 -> 1992.9458 | Q65: =SUM(E65:P65) -> 25222.897 | R65: =Q65/$B$4 -> 0.51454298 | U65: DW | V65: Based on occupancy. Includes cleaning, supplies, and porter fee.. Alternate SF for 3620 excludes ISD Renal, who is responsible for cleaning their own space.
D66: Cleaning & Supplies-Vacancies | E66: ='Allocated Expenses'!E28 -> 217.13483 | F66: ='Allocated Expenses'!F28 -> 217.13483 | G66: ='Allocated Expenses'!G28 -> 217.13483 | H66: ='Allocated Expenses'!H28 -> 217.13483 | I66: ='Allocated Expenses'!I28 -> 217.13483 | J66: ='Allocated Expenses'!J28 -> 217.13483 | K66: ='Allocated Expenses'!K28 -> 217.13483 | L66: ='Allocated Expenses'!L28 -> 217.13483 | ... P66: ='Allocated Expenses'!P28 -> 223.72385 | Q66: =SUM(E66:P66) -> 2612.2069 | R66: =Q66/$B$4 -> 0.053288595 | U66: DW | V66: Based on occupancy.
A67: 6250-8502 | B67: (BP) | C67: Cleaning & Supplies | E67: =SUM(E65:E66) -> 2328.9486 | F67: =SUM(F65:F66) -> 2328.9486 | G67: =SUM(G65:G66) -> 2328.9486 | H67: =SUM(H65:H66) -> 2328.9486 | I67: =SUM(I65:I66) -> 2328.9486 | J67: =SUM(J65:J66) -> 2328.9486 | K67: =SUM(K65:K66) -> 2328.9486 | L67: =SUM(L65:L66) -> 2328.9486 | ... Q67: =SUM(Q65:Q66) -> 27835.104 | R67: =Q67/$B$4 -> 0.56783158 | S67: 32620.57 | T67: =IFERROR(Q67/S67-1,"-") -> -0.14670087
A69: 6990-8502 | B69: (SC) | C69: Other - Condo Fee | E69: ='Allocated Expenses'!E35 -> 14413 | F69: ='Allocated Expenses'!F35 -> 0 | G69: ='Allocated Expenses'!G35 -> 0 | H69: ='Allocated Expenses'!H35 -> 14413 | I69: ='Allocated Expenses'!I35 -> 0 | J69: ='Allocated Expenses'!J35 -> 0 | K69: ='Allocated Expenses'!K35 -> 14413 | L69: ='Allocated Expenses'!L35 -> 0 | ... P69: ='Allocated Expenses'!P35 -> 0 | Q69: =SUM(E69:P69) -> 57652 | R69: =Q69/$B$4 -> 1.1760914 | S69: 69084 | T69: =IFERROR(Q69/S69-1,"-") -> -0.16547971
C71: Total Reimbursable Expenses | E71: =+E27+E29+E31+E36+E38+E43+E45+E50+E52+E54+E56+E58+E63+E67+E69 -> 35630.025 | F71: =+F27+F29+F31+F36+F38+F43+F45+F50+F52+F54+F56+F58+F63+F67+F69 -> 22133.725 | G71: =+G27+G29+G31+G36+G38+G43+G45+G50+G52+G54+G56+G58+G63+G67+G69 -> 19085.865 | H71: =+H27+H29+H31+H36+H38+H43+H45+H50+H52+H54+H56+H58+H63+H67+H69 -> 32914.125 | I71: =+I27+I29+I31+I36+I38+I43+I45+I50+I52+I54+I56+I58+I63+I67+I69 -> 19388.125 | J71: =+J27+J29+J31+J36+J38+J43+J45+J50+J52+J54+J56+J58+J63+J67+J69 -> 32160.555 | K71: =+K27+K29+K31+K36+K38+K43+K45+K50+K52+K54+K56+K58+K63+K67+K69 -> 32985.535 | L71: =+L27+L29+L31+L36+L38+L43+L45+L50+L52+L54+L56+L58+L63+L67+L69 -> 18266.875 | ... Q71: =+Q27+Q29+Q31+Q36+Q38+Q43+Q45+Q50+Q52+Q54+Q56+Q58+Q63+Q67+Q69 -> 304639.83 | R71: =Q71/$B$4 -> 6.2146028 | S71: =+S27+S29+S31+S36+S38+S43+S45+S50+S52+S54+S56+S58+S63+S67+S69 -> 361017.68 | T71: =IFERROR(Q71/S71-1,"-") -> -0.15616369 | V71: =Q71-Q29-Q58 -> 218414.43
B73: Non-Reimbursable Expenses | R73: =Q73/$B$4 -> 0
A75: 5210-8501 | C75: Bad Debt | E75: 0 | F75: 0 | G75: 0 | H75: 0 | I75: 0 | J75: 0 | K75: 0 | L75: 0 | M75: 0 | N75: 0 | O75: 0 | P75: 0 | Q75: =SUM(E75:P75) -> 0 | R75: =Q75/$B$4 -> 0 | T75: =IFERROR(Q75/S75-1,"-") -> -
A77: 6010-8501 | D77: Salaries & Wages | E77: ='Allocated Expenses'!E42 -> 1704.8208 | F77: ='Allocated Expenses'!F42 -> 1704.8208 | G77: ='Allocated Expenses'!G42 -> 1704.8208 | H77: ='Allocated Expenses'!H42 -> 1704.8208 | I77: ='Allocated Expenses'!I42 -> 1704.8208 | J77: ='Allocated Expenses'!J42 -> 1704.8208 | K77: ='Allocated Expenses'!K42 -> 1704.8208 | L77: ='Allocated Expenses'!L42 -> 1704.8208 | ... P77: ='Allocated Expenses'!P42 -> 1704.8208 | Q77: =SUM(E77:P77) -> 20457.85 | R77: =Q77/$B$4 -> 0.4173368
A78: 6620-8501 | D78: Commissions-Internal Broker | E78: ='Allocated Expenses'!E49 -> 567.7875 | F78: ='Allocated Expenses'!F49 -> 0 | G78: ='Allocated Expenses'!G49 -> 0 | H78: ='Allocated Expenses'!H49 -> 567.7875 | I78: ='Allocated Expenses'!I49 -> 0 | J78: ='Allocated Expenses'!J49 -> 0 | K78: ='Allocated Expenses'!K49 -> 567.7875 | L78: ='Allocated Expenses'!L49 -> 0 | ... P78: ='Allocated Expenses'!P49 -> 0 | Q78: =SUM(E78:P78) -> 2271.15 | R78: =Q78/$B$4 -> 0.046331089
C79: Leasing Salaries and Commissions | E79: =SUM(E77:E78) -> 2272.6083 | F79: =SUM(F77:F78) -> 1704.8208 | G79: =SUM(G77:G78) -> 1704.8208 | H79: =SUM(H77:H78) -> 2272.6083 | I79: =SUM(I77:I78) -> 1704.8208 | J79: =SUM(J77:J78) -> 1704.8208 | K79: =SUM(K77:K78) -> 2272.6083 | L79: =SUM(L77:L78) -> 1704.8208 | ... Q79: =SUM(Q77:Q78) -> 22729 | R79: =Q79/$B$4 -> 0.46366789 | S79: 19801 | T79: =IFERROR(Q79/S79-1,"-") -> 0.14787132
A81: 6110-8501 | D81: Gas | Q81: =SUM(E81:P81) -> 0 | R81: =Q81/$B$4 -> 0
A82: 6120-8501 | D82: Electric | Q82: =SUM(E82:P82) -> 0 | R82: =Q82/$B$4 -> 0
A83: 6130-8501 | D83: Water & Sewer | Q83: =SUM(E83:P83) -> 0 | R83: =Q83/$B$4 -> 0
C84: Utilities | E84: =SUM(E81:E83) -> 0 | F84: =SUM(F81:F83) -> 0 | G84: =SUM(G81:G83) -> 0 | H84: =SUM(H81:H83) -> 0 | I84: =SUM(I81:I83) -> 0 | J84: =SUM(J81:J83) -> 0 | K84: =SUM(K81:K83) -> 0 | L84: =SUM(L81:L83) -> 0 | ... Q84: =SUM(Q81:Q83) -> 0 | R84: =Q84/$B$4 -> 0 | S84: 52.52 | T84: =IFERROR(Q84/S84-1,"-") -> -1
D86: Building Maint.-Recurring | E86: =1.03*910 -> 937.3 | F86: =1.03*910 -> 937.3 | G86: =1.03*910 -> 937.3 | H86: =1.03*910 -> 937.3 | I86: =1.03*910 -> 937.3 | J86: =1.03*910 -> 937.3 | K86: =1.03*910 -> 937.3 | L86: =1.03*910 -> 937.3 | ... P86: =1.03*910 -> 937.3 | Q86: =SUM(E86:P86) -> 11247.6 | R86: =Q86/$B$4 -> 0.2294492
D87: Building Maint.-Big Projects | Q87: =SUM(E87:P87) -> 0 | R87: =Q87/$B$4 -> 0
A88: 6220-8501 | C88: Building Maintenance | E88: =SUM(E86:E87) -> 937.3 | F88: =SUM(F86:F87) -> 937.3 | G88: =SUM(G86:G87) -> 937.3 | H88: =SUM(H86:H87) -> 937.3 | I88: =SUM(I86:I87) -> 937.3 | J88: =SUM(J86:J87) -> 937.3 | K88: =SUM(K86:K87) -> 937.3 | L88: =SUM(L86:L87) -> 937.3 | ... Q88: =SUM(Q86:Q87) -> 11247.6 | R88: =Q88/$B$4 -> 0.2294492 | S88: 4319 | T88: =IFERROR(Q88/S88-1,"-") -> 1.6042139
A90: 6610-8501 | B90: (SC) | C90: Management fee | Q90: =SUM(E90:P90) -> 0 | R90: =Q90/$B$4 -> 0 | T90: =R90/S90-1 -> #DIV/0!
T91: =R91/S91-1 -> #DIV/0!
A92: 7110-8501 | C92: Marketing | E92: ='Allocated Expenses'!E56 -> 437.5 | F92: ='Allocated Expenses'!F56 -> 437.5 | G92: ='Allocated Expenses'!G56 -> 437.5 | H92: ='Allocated Expenses'!H56 -> 437.5 | I92: ='Allocated Expenses'!I56 -> 437.5 | J92: ='Allocated Expenses'!J56 -> 437.5 | K92: ='Allocated Expenses'!K56 -> 437.5 | L92: ='Allocated Expenses'!L56 -> 437.5 | ... P92: ='Allocated Expenses'!P56 -> 437.5 | Q92: =SUM(E92:P92) -> 5250 | R92: =Q92/$B$4 -> 0.10709914 | S92: 4965.74 | T92: =IFERROR(Q92/S92-1,"-") -> 0.057244238
A94: 8210-8501 | C94: Business Taxes | E94: ='Allocated Expenses'!E63 -> 0 | F94: ='Allocated Expenses'!F63 -> 0 | G94: ='Allocated Expenses'!G63 -> 0 | H94: ='Allocated Expenses'!H63 -> 942.90082 | I94: ='Allocated Expenses'!I63 -> 0 | J94: ='Allocated Expenses'!J63 -> 0 | K94: ='Allocated Expenses'!K63 -> 0 | L94: ='Allocated Expenses'!L63 -> 0 | ... P94: ='Allocated Expenses'!P63 -> 0 | Q94: =SUM(E94:P94) -> 942.90082 | R94: =Q94/$B$4 -> 0.019235023 | S94: 996 | T94: =IFERROR(Q94/S94-1,"-") -> -0.053312428
A96: 8310-8501 | C96: Legal & Accounting | E96: ='Allocated Expenses'!E70 -> 900.78333 | F96: ='Allocated Expenses'!F70 -> 900.78333 | G96: ='Allocated Expenses'!G70 -> 900.78333 | H96: ='Allocated Expenses'!H70 -> 900.78333 | I96: ='Allocated Expenses'!I70 -> 900.78333 | J96: ='Allocated Expenses'!J70 -> 900.78333 | K96: ='Allocated Expenses'!K70 -> 900.78333 | L96: ='Allocated Expenses'!L70 -> 900.78333 | ... P96: ='Allocated Expenses'!P70 -> 900.78333 | Q96: =SUM(E96:P96) -> 10809.4 | R96: =Q96/$B$4 -> 0.22051 | S96: 10082 | T96: =IFERROR(Q96/S96-1,"-") -> 0.072148383
A98: 8190-8501 | D98: Bank Fees | E98: ='Allocated Expenses'!E77 -> 55.8775 | F98: ='Allocated Expenses'!F77 -> 55.8775 | G98: ='Allocated Expenses'!G77 -> 55.8775 | H98: ='Allocated Expenses'!H77 -> 55.8775 | I98: ='Allocated Expenses'!I77 -> 55.8775 | J98: ='Allocated Expenses'!J77 -> 55.8775 | K98: ='Allocated Expenses'!K77 -> 55.8775 | L98: ='Allocated Expenses'!L77 -> 55.8775 | ... P98: ='Allocated Expenses'!P77 -> 55.8775 | Q98: =SUM(E98:P98) -> 670.53 | R98: =Q98/$B$4 -> 0.013678703
A99: 8930-8501 | D99: Office Supplies | E99: ='Allocated Expenses'!E84 -> 0 | F99: ='Allocated Expenses'!F84 -> 0 | G99: ='Allocated Expenses'!G84 -> 0 | H99: ='Allocated Expenses'!H84 -> 0 | I99: ='Allocated Expenses'!I84 -> 0 | J99: ='Allocated Expenses'!J84 -> 0 | K99: ='Allocated Expenses'!K84 -> 0 | L99: ='Allocated Expenses'!L84 -> 0 | ... P99: ='Allocated Expenses'!P84 -> 0 | Q99: =SUM(E99:P99) -> 0 | R99: =Q99/$B$4 -> 0
A100: 8950-8501 | D100: Postage | E100: ='Allocated Expenses'!E91 -> 0 | F100: ='Allocated Expenses'!F91 -> 0 | G100: ='Allocated Expenses'!G91 -> 0 | H100: ='Allocated Expenses'!H91 -> 0 | I100: ='Allocated Expenses'!I91 -> 0 | J100: ='Allocated Expenses'!J91 -> 0 | K100: ='Allocated Expenses'!K91 -> 0 | L100: ='Allocated Expenses'!L91 -> 0 | ... P100: ='Allocated Expenses'!P91 -> 0 | Q100: =SUM(E100:P100) -> 0 | R100: =Q100/$B$4 -> 0
A101: 8990-8501 | D101: Other G&A Expense | E101: ='Allocated Expenses'!E98 -> 7.21 | F101: ='Allocated Expenses'!F98 -> 7.21 | G101: ='Allocated Expenses'!G98 -> 7.21 | H101: ='Allocated Expenses'!H98 -> 7.21 | I101: ='Allocated Expenses'!I98 -> 7.21 | J101: ='Allocated Expenses'!J98 -> 7.21 | K101: ='Allocated Expenses'!K98 -> 7.21 | L101: ='Allocated Expenses'!L98 -> 7.21 | ... P101: ='Allocated Expenses'!P98 -> 7.21 | Q101: =SUM(E101:P101) -> 86.52 | R101: =Q101/$B$4 -> 0.0017649939
A102: 8990-9800 | D102: Other G&A-allocated from LIK | E102: ='Allocated Expenses'!E105 -> 1240.12 | F102: ='Allocated Expenses'!F105 -> 1240.12 | G102: ='Allocated Expenses'!G105 -> 1240.12 | H102: ='Allocated Expenses'!H105 -> 1240.12 | I102: ='Allocated Expenses'!I105 -> 1240.12 | J102: ='Allocated Expenses'!J105 -> 1240.12 | K102: ='Allocated Expenses'!K105 -> 1240.12 | L102: ='Allocated Expenses'!L105 -> 1240.12 | ... P102: ='Allocated Expenses'!P105 -> 1240.12 | Q102: =SUM(E102:P102) -> 14881.44 | R102: =Q102/$B$4 -> 0.30357895
C103: General & Administrative | E103: =SUM(E98:E102) -> 1303.2075 | F103: =SUM(F98:F102) -> 1303.2075 | G103: =SUM(G98:G102) -> 1303.2075 | H103: =SUM(H98:H102) -> 1303.2075 | I103: =SUM(I98:I102) -> 1303.2075 | J103: =SUM(J98:J102) -> 1303.2075 | K103: =SUM(K98:K102) -> 1303.2075 | L103: =SUM(L98:L102) -> 1303.2075 | ... Q103: =SUM(Q98:Q102) -> 15638.49 | R103: =Q103/$B$4 -> 0.31902264 | S103: 13710 | T103: =IFERROR(Q103/S103-1,"-") -> 0.14066302
C105: Total Non-Reimbursable Expenses | E105: =+E75+E79+E84+E88+E90+E92+E94+E96+E103 -> 5851.3992 | F105: =+F75+F79+F84+F88+F90+F92+F94+F96+F103 -> 5283.6117 | G105: =+G75+G79+G84+G88+G90+G92+G94+G96+G103 -> 5283.6117 | H105: =+H75+H79+H84+H88+H90+H92+H94+H96+H103 -> 6794.3 | I105: =+I75+I79+I84+I88+I90+I92+I94+I96+I103 -> 5283.6117 | J105: =+J75+J79+J84+J88+J90+J92+J94+J96+J103 -> 5283.6117 | K105: =+K75+K79+K84+K88+K90+K92+K94+K96+K103 -> 5851.3992 | L105: =+L75+L79+L84+L88+L90+L92+L94+L96+L103 -> 5283.6117 | ... Q105: =+Q75+Q79+Q84+Q88+Q90+Q92+Q94+Q96+Q103 -> 66617.391 | R105: =Q105/$B$4 -> 1.3589839 | S105: =+S75+S79+S84+S88+S90+S92+S94+S96+S103 -> 53926.26 | T105: =IFERROR(Q105/S105-1,"-") -> 0.23534231
B107: TOTAL OPERATING EXPENSES | E107: =+E71+E105 -> 41481.424 | F107: =+F71+F105 -> 27417.336 | G107: =+G71+G105 -> 24369.476 | H107: =+H71+H105 -> 39708.425 | I107: =+I71+I105 -> 24671.736 | J107: =+J71+J105 -> 37444.166 | K107: =+K71+K105 -> 38836.934 | L107: =+L71+L105 -> 23550.486 | ... Q107: =+Q71+Q105 -> 371257.22 | R107: =Q107/$B$4 -> 7.5735867 | S107: =+S71+S105 -> 414943.94 | T107: =IFERROR(Q107/S107-1,"-") -> -0.10528343
B109: NET OPERATING INCOME | E109: =+E24-E107 -> -3175.6571 | F109: =+F24-F107 -> 10756.184 | G109: =+G24-G107 -> 13414.559 | H109: =+H24-H107 -> -2583.18 | I109: =+I24-I107 -> 12469.902 | J109: =+J24-J107 -> -262.8171 | K109: =+K24-K107 -> -1397.4916 | L109: =+L24-L107 -> 13997.082 | ... Q109: =+Q24-Q107 -> 79081.716 | R109: =Q109/$B$4 -> 1.6132541 | S109: =+S24-S107 -> 36621.61 | T109: =IFERROR(Q109/S109-1,"-") -> 1.1594276
A111: 1420-0000 | D111: Land Improvements | Q111: =SUM(E111:P111) -> 0 | R111: =Q111/$B$4 -> 0
A112: 1430-0000 | D112: Buildings | Q112: =SUM(E112:P112) -> 0 | R112: =Q112/$B$4 -> 0
A113: 1450-0000 | D113: Equipment | Q113: =SUM(E113:P113) -> 0 | R113: =Q113/$B$4 -> 0
A114: 1980-8501 | D114: Capital Improvements | Q114: =SUM(E114:P114) -> 0 | R114: =Q114/$B$4 -> 0
C115: Capital Improvements | Q115: =SUM(Q111:Q114) -> 0 | R115: =Q115/$B$4 -> 0 | T115: =IFERROR(Q115/S115-1,"-") -> -
A117: 1440-0000 | C117: Tenant Improvements | E117: ='Renew & Vac - Rent, TI, LC'!AH33 -> 0 | F117: ='Renew & Vac - Rent, TI, LC'!AI33 -> 0 | G117: ='Renew & Vac - Rent, TI, LC'!AJ33 -> 0 | H117: ='Renew & Vac - Rent, TI, LC'!AK33 -> 0 | I117: ='Renew & Vac - Rent, TI, LC'!AL33 -> 0 | J117: ='Renew & Vac - Rent, TI, LC'!AM33 -> 0 | K117: ='Renew & Vac - Rent, TI, LC'!AN33 -> 0 | L117: ='Renew & Vac - Rent, TI, LC'!AO33 -> 0 | ... P117: ='Renew & Vac - Rent, TI, LC'!AS33 -> 0 | Q117: =SUM(E117:P117) -> 0 | R117: =Q117/$B$4 -> 0 | T117: =IFERROR(Q117/S117-1,"-") -> -
A119: 1940-8501 | D119: Deferred Marketing | Q119: =SUM(E119:P119) -> 0 | R119: =Q119/$B$4 -> 0
A120: 1940-8501 | D120: Outside Leasing Commissions | E120: ='Renew & Vac - Rent, TI, LC'!AH34 -> 0 | F120: ='Renew & Vac - Rent, TI, LC'!AI34 -> 0 | G120: ='Renew & Vac - Rent, TI, LC'!AJ34 -> 0 | H120: ='Renew & Vac - Rent, TI, LC'!AK34 -> 0 | I120: ='Renew & Vac - Rent, TI, LC'!AL34 -> 0 | J120: ='Renew & Vac - Rent, TI, LC'!AM34 -> 0 | K120: ='Renew & Vac - Rent, TI, LC'!AN34 -> 0 | L120: ='Renew & Vac - Rent, TI, LC'!AO34 -> 0 | ... P120: ='Renew & Vac - Rent, TI, LC'!AS34 -> 0 | Q120: =SUM(E120:P120) -> 0 | R120: =Q120/$B$4 -> 0
C121: Outside Leasing Commissions | E121: =SUM(E119:E120) -> 0 | F121: =SUM(F119:F120) -> 0 | G121: =SUM(G119:G120) -> 0 | H121: =SUM(H119:H120) -> 0 | I121: =SUM(I119:I120) -> 0 | J121: =SUM(J119:J120) -> 0 | K121: =SUM(K119:K120) -> 0 | L121: =SUM(L119:L120) -> 0 | ... Q121: =SUM(Q119:Q120) -> 0 | R121: =Q121/$B$4 -> 0 | S121: 1050 | T121: =IFERROR(Q121/S121-1,"-") -> -1 | V121: 7/2025 Reprojections is for Capitalized Lease Costs
B123: CASH FLOW BEFORE DEBT SERVICE | E123: =+E109-E115-E117-E121 -> -3175.6571 | F123: =+F109-F115-F117-F121 -> 10756.184 | G123: =+G109-G115-G117-G121 -> 13414.559 | H123: =+H109-H115-H117-H121 -> -2583.18 | I123: =+I109-I115-I117-I121 -> 12469.902 | J123: =+J109-J115-J117-J121 -> -262.8171 | K123: =+K109-K115-K117-K121 -> -1397.4916 | L123: =+L109-L115-L117-L121 -> 13997.082 | ... Q123: =+Q109-Q115-Q117-Q121 -> 79081.716 | R123: =Q123/$B$4 -> 1.6132541 | S123: =+S109-S115-S117-S121 -> 35571.61 | T123: =IFERROR(Q123/S123-1,"-") -> 1.2231695
B125: Debt Service
A126: 9210-8501 | C126: Interest | E126: ='Allocated Expenses'!E113 -> 8057.7 | F126: ='Allocated Expenses'!F113 -> 8057.7 | G126: ='Allocated Expenses'!G113 -> 8057.7 | H126: ='Allocated Expenses'!H113 -> 8057.7 | I126: ='Allocated Expenses'!I113 -> 8057.7 | J126: ='Allocated Expenses'!J113 -> 8057.7 | K126: ='Allocated Expenses'!K113 -> 8057.7 | L126: ='Allocated Expenses'!L113 -> 8057.7 | ... P126: ='Allocated Expenses'!P113 -> 8057.7 | Q126: =SUM(E126:P126) -> 96692.4 | R126: =Q126/$B$4 -> 1.9725092 | S126: 98167 | T126: =IFERROR(Q126/S126-1,"-") -> -0.015021341
A127: 2740-8501 | C127: Mortgage Amortization | E127: =+'Allocated Expenses'!E125 -> 0 | F127: =+'Allocated Expenses'!F125 -> 0 | G127: =+'Allocated Expenses'!G125 -> 0 | H127: =+'Allocated Expenses'!H125 -> 0 | I127: =+'Allocated Expenses'!I125 -> 0 | J127: =+'Allocated Expenses'!J125 -> 0 | K127: =+'Allocated Expenses'!K125 -> 0 | L127: =+'Allocated Expenses'!L125 -> 0 | ... P127: =+'Allocated Expenses'!P125 -> 0 | Q127: =SUM(E127:P127) -> 0 | R127: =Q127/$B$4 -> 0 | S127: 10696.01 | T127: =IFERROR(Q127/S127-1,"-") -> -1
A128: 2740-0000 | C128: Loan Proceeds | Q128: =SUM(E128:P128) -> 0 | R128: =Q128/$B$4 -> 0 | T128: =IFERROR(Q128/S128-1,"-") -> -
C129: Total Debt Service | E129: =SUM(E126:E128) -> 8057.7 | F129: =SUM(F126:F128) -> 8057.7 | G129: =SUM(G126:G128) -> 8057.7 | H129: =SUM(H126:H128) -> 8057.7 | I129: =SUM(I126:I128) -> 8057.7 | J129: =SUM(J126:J128) -> 8057.7 | K129: =SUM(K126:K128) -> 8057.7 | L129: =SUM(L126:L128) -> 8057.7 | ... Q129: =SUM(Q126:Q128) -> 96692.4 | R129: =Q129/$B$4 -> 1.9725092 | S129: =SUM(S126:S128) -> 108863.01 | T129: =IFERROR(Q129/S129-1,"-") -> -0.11179748
B131: CASH FLOW AFTER DEBT SERVICE | E131: =+E123-E129 -> -11233.357 | F131: =+F123-F129 -> 2698.4844 | G131: =+G123-G129 -> 5356.8586 | H131: =+H123-H129 -> -10640.88 | I131: =+I123-I129 -> 4412.2019 | J131: =+J123-J129 -> -8320.5171 | K131: =+K123-K129 -> -9455.1916 | L131: =+L123-L129 -> 5939.3819 | ... Q131: =+Q123-Q129 -> -17610.684 | R131: =Q131/$B$4 -> -0.35925508 | S131: =+S123-S129 -> -73291.4 | T131: =IFERROR(Q131/S131-1,"-") -> -0.75971691
D135: ="Budget Import - "&B1 -> Budget Import - 3620 | E135: 5 | F135: =E135+1 -> 6 | G135: =F135+1 -> 7 | H135: =G135+1 -> 8 | I135: =H135+1 -> 9 | J135: =I135+1 -> 10 | K135: =J135+1 -> 11 | L135: =K135+1 -> 12 | M135: =L135+1 -> 13 | ... P135: =O135+1 -> 16 | Q135: <- Lookup Column
D136: Account | E136: 1 | F136: 2 | G136: 3 | H136: 4 | I136: 5 | J136: 6 | K136: 7 | L136: 8 | M136: 9 | N136: 10 | O136: 11 | P136: 12 | Q136: Total
A137: =VLOOKUP($D137,$A$10:$D$130,3,FALSE) -> Rental Income - In Place | D137: 4230-8501 | E137: =-(VLOOKUP($D137,$A$10:$P$131,E$135,FALSE)+E11) -> -33934.975 | F137: =-(VLOOKUP($D137,$A$10:$P$131,F$135,FALSE)+F11) -> -33934.975 | G137: =-(VLOOKUP($D137,$A$10:$P$131,G$135,FALSE)+G11) -> -33934.975 | H137: =-(VLOOKUP($D137,$A$10:$P$131,H$135,FALSE)+H11) -> -33850.388 | I137: =-(VLOOKUP($D137,$A$10:$P$131,I$135,FALSE)+I11) -> -33932.052 | J137: =-(VLOOKUP($D137,$A$10:$P$131,J$135,FALSE)+J11) -> -33882.177 | K137: =-(VLOOKUP($D137,$A$10:$P$131,K$135,FALSE)+K11) -> -33882.177 | L137: =-(VLOOKUP($D137,$A$10:$P$131,L$135,FALSE)+L11) -> -33900.717 | ... P137: =-(VLOOKUP($D137,$A$10:$P$131,P$135,FALSE)+P11) -> -32797.902 | Q137: =SUM(E137:P137) -> -406612.17
A138: =VLOOKUP($D138,$A$10:$D$130,3,FALSE) -> Electric | D138: 4710-8502 | E138: =-VLOOKUP($D138,$A$10:$P$131,E$135,FALSE) -> -2270.7918 | F138: =-VLOOKUP($D138,$A$10:$P$131,F$135,FALSE) -> -2138.5458 | G138: =-VLOOKUP($D138,$A$10:$P$131,G$135,FALSE) -> -1749.06 | H138: =-VLOOKUP($D138,$A$10:$P$131,H$135,FALSE) -> -1174.8564 | I138: =-VLOOKUP($D138,$A$10:$P$131,I$135,FALSE) -> -1109.5866 | J138: =-VLOOKUP($D138,$A$10:$P$131,J$135,FALSE) -> -1199.1726 | K138: =-VLOOKUP($D138,$A$10:$P$131,K$135,FALSE) -> -1457.2656 | L138: =-VLOOKUP($D138,$A$10:$P$131,L$135,FALSE) -> -1546.8516 | ... P138: =-VLOOKUP($D138,$A$10:$P$131,P$135,FALSE) -> -2027.586 | Q138: =SUM(E138:P138) -> -18526.768
A139: =VLOOKUP($D139,$A$10:$D$130,3,FALSE) -> Common Area Maintenance | D139: 4910-8502 | E139: =-VLOOKUP($D139,$A$10:$P$131,E$135,FALSE) -> -1900 | F139: =-VLOOKUP($D139,$A$10:$P$131,F$135,FALSE) -> -1900 | G139: =-VLOOKUP($D139,$A$10:$P$131,G$135,FALSE) -> -1900 | H139: =-VLOOKUP($D139,$A$10:$P$131,H$135,FALSE) -> -1900 | I139: =-VLOOKUP($D139,$A$10:$P$131,I$135,FALSE) -> -1900 | J139: =-VLOOKUP($D139,$A$10:$P$131,J$135,FALSE) -> -1900 | K139: =-VLOOKUP($D139,$A$10:$P$131,K$135,FALSE) -> -1900 | L139: =-VLOOKUP($D139,$A$10:$P$131,L$135,FALSE) -> -1900 | ... P139: =-VLOOKUP($D139,$A$10:$P$131,P$135,FALSE) -> -1900 | Q139: =SUM(E139:P139) -> -22800
...

Sheet 364
B1: 3640 | J1: =+'362'!J1 -> Operating Budget | Q1: ='JV III Consolidated'!Q1 -> 46023
J2: =+'362'!J2 -> Lincoln JV III
Q3: =Q1 -> 46023 | S3: 7/2025 Reprojections
B4: ='Renew & Vac - Rent, TI, LC'!A50 -> 48794 | E4: Jan | F4: Feb | G4: Mar | H4: Apr | I4: May | J4: Jun | K4: Jul | L4: Aug | M4: Sep | N4: Oct | O4: Nov | P4: Dec | Q4: Total | R4: Total PSF | S4: Total | T4: Var. | U4: Input | V4: Notes
D6: Occupancy % | E6: ='Renew & Vac - Rent, TI, LC'!AH53 -> 0.8233 | F6: ='Renew & Vac - Rent, TI, LC'!AI53 -> 0.8233 | G6: ='Renew & Vac - Rent, TI, LC'!AJ53 -> 0.8233 | H6: ='Renew & Vac - Rent, TI, LC'!AK53 -> 0.6717 | I6: ='Renew & Vac - Rent, TI, LC'!AL53 -> 0.6717 | J6: ='Renew & Vac - Rent, TI, LC'!AM53 -> 0.6717 | K6: ='Renew & Vac - Rent, TI, LC'!AN53 -> 0.6717 | L6: ='Renew & Vac - Rent, TI, LC'!AO53 -> 0.6717 | ... P6: ='Renew & Vac - Rent, TI, LC'!AS53 -> 0.4449
D7: Occupancy SF | E7: =$B$4*E6 -> 40172.1 | F7: =$B$4*F6 -> 40172.1 | G7: =$B$4*G6 -> 40172.1 | H7: =$B$4*H6 -> 32774.93 | I7: =$B$4*I6 -> 32774.93 | J7: =$B$4*J6 -> 32774.93 | K7: =$B$4*K6 -> 32774.93 | L7: =$B$4*L6 -> 32774.93 | ... P7: =$B$4*P6 -> 21708.451
B8: Revenues
A10: 4230-8501 | C10: Rental Income - In Place | E10: =SUMIFS('In Place Revenue'!$G:$G,'In Place Revenue'!$A:$A,$B$1,'In Place Revenue'!$H:$H,1) -> 61074.26 | F10: =SUMIFS('In Place Revenue'!$G:$G,'In Place Revenue'!$A:$A,$B$1,'In Place Revenue'!$H:$H,2) -> 61074.26 | G10: =SUMIFS('In Place Revenue'!$G:$G,'In Place Revenue'!$A:$A,$B$1,'In Place Revenue'!$H:$H,3) -> 58357.59 | H10: =SUMIFS('In Place Revenue'!$G:$G,'In Place Revenue'!$A:$A,$B$1,'In Place Revenue'!$H:$H,4) -> 46332.59 | I10: =SUMIFS('In Place Revenue'!$G:$G,'In Place Revenue'!$A:$A,$B$1,'In Place Revenue'!$H:$H,5) -> 46332.59 | J10: =SUMIFS('In Place Revenue'!$G:$G,'In Place Revenue'!$A:$A,$B$1,'In Place Revenue'!$H:$H,6) -> 46332.59 | K10: =SUMIFS('In Place Revenue'!$G:$G,'In Place Revenue'!$A:$A,$B$1,'In Place Revenue'!$H:$H,7) -> 36784.42 | L10: =SUMIFS('In Place Revenue'!$G:$G,'In Place Revenue'!$A:$A,$B$1,'In Place Revenue'!$H:$H,8) -> 42087.67 | M10: =SUMIFS('In Place Revenue'!$G:$G,'In Place Revenue'!$A:$A,$B$1,'In Place Revenue'!$H:$H,9) -> 42087.67 | N10: =SUMIFS('In Place Revenue'!$G:$G,'In Place Revenue'!$A:$A,$B$1,'In Place Revenue'!$H:$H,10) -> 28542.92 | O10: =SUMIFS('In Place Revenue'!$G:$G,'In Place Revenue'!$A:$A,$B$1,'In Place Revenue'!$H:$H,11) -> 27121.5 | P10: =SUMIFS('In Place Revenue'!$G:$G,'In Place Revenue'!$A:$A,$B$1,'In Place Revenue'!$H:$H,12) -> 32308.5 | Q10: =SUM(E10:P10) -> 528436.56 | R10: =Q10/$B$4 -> 10.82995 | S10: 755719.63 | T10: =IFERROR((Q10+Q11)/S10-1,"-") -> -0.18757944
A11: 4230-8501 | C11: Rental Income - New & Renewal | E11: ='Renew & Vac - Rent, TI, LC'!AH54 -> 3957.5449 | F11: ='Renew & Vac - Rent, TI, LC'!AI54 -> 3957.5449 | G11: ='Renew & Vac - Rent, TI, LC'!AJ54 -> 6674.2116 | H11: ='Renew & Vac - Rent, TI, LC'!AK54 -> 6674.8282 | I11: ='Renew & Vac - Rent, TI, LC'!AL54 -> 6674.8282 | J11: ='Renew & Vac - Rent, TI, LC'!AM54 -> 6674.8282 | K11: ='Renew & Vac - Rent, TI, LC'!AN54 -> 9171.2033 | L11: ='Renew & Vac - Rent, TI, LC'!AO54 -> 9171.2033 | ... P11: ='Renew & Vac - Rent, TI, LC'!AS54 -> 8273.2083 | Q11: =SUM(E11:P11) -> 85525.604 | R11: =Q11/$B$4 -> 1.7527894 | T11: =IFERROR(Q11/S11-1,"-") -> -
A12: 4240-8501 | C12: Percentage Rents | E12: 0 | F12: 0 | G12: 0 | H12: 0 | I12: 0 | J12: 0 | K12: 0 | L12: 0 | M12: 0 | N12: 0 | O12: 0 | P12: 0 | Q12: =SUM(E12:P12) -> 0 | R12: =Q12/$B$4 -> 0 | T12: =R12/S12-1 -> #DIV/0!
A13: 4990-8501 | C13: Miscellaneous | E13: 0 | F13: 0 | G13: 0 | H13: 0 | I13: 0 | J13: 0 | K13: 0 | L13: 0 | M13: 0 | N13: 0 | O13: 0 | P13: 0 | Q13: =SUM(E13:P13) -> 0 | R13: =Q13/$B$4 -> 0 | T13: =IFERROR(Q13/S13-1,"-") -> -
A14: 9190-8501 | C14: Interest Income | E14: 0 | F14: 0 | G14: 0 | H14: 0 | I14: 0 | J14: 0 | K14: 0 | L14: 0 | M14: 0 | N14: 0 | O14: 0 | P14: 0 | Q14: =SUM(E14:P14) -> 0 | R14: =Q14/$B$4 -> 0 | T14: =IFERROR(Q14/S14-1,"-") -> -
C15: Total Rental and Other | E15: =SUM(E10:E14) -> 65031.805 | F15: =SUM(F10:F14) -> 65031.805 | G15: =SUM(G10:G14) -> 65031.802 | H15: =SUM(H10:H14) -> 53007.418 | I15: =SUM(I10:I14) -> 53007.418 | J15: =SUM(J10:J14) -> 53007.418 | K15: =SUM(K10:K14) -> 45955.623 | L15: =SUM(L10:L14) -> 51258.873 | ... Q15: =SUM(Q10:Q14) -> 613962.16 | R15: =Q15/$B$4 -> 12.582739 | S15: =SUM(S10:S14) -> 755719.63 | T15: =IFERROR(Q15/S15-1,"-") -> -0.18757944
B17: Reimbursements
A18: 4710-8502 | C18: Electric | E18: =E6*E29 -> 3502.3182 | F18: =F6*F29 -> 3048.6799 | G18: =G6*G29 -> 2678.1949 | H18: =H6*H29 -> 1599.9894 | I18: =I6*I29 -> 1462.9626 | J18: =J6*J29 -> 1455.5739 | K18: =K6*K29 -> 1613.4234 | L18: =L6*L29 -> 1528.7892 | ... P18: =P6*P29 -> 1613.2074 | Q18: =SUM(E18:P18) -> 21811.331 | R18: =Q18/$B$4 -> 0.44700846 | S18: 29665.83 | T18: =IFERROR(Q18/S18-1,"-") -> -0.26476586 | U18: DW | V18: =Q18/Q29*100&"% Set to occupancy" -> 66.7625681052954% Set to occupancy
A19: 4910-8502 | C19: Common Area Maintenance | E19: =+'Tenant Recoveries'!H21 -> 1500 | F19: =+E19 -> 1500 | G19: =+F19 -> 1500 | H19: =+G19 -> 1500 | I19: =+H19 -> 1500 | J19: =+I19 -> 1500 | K19: =+J19 -> 1500 | L19: =+K19 -> 1500 | M19: =+L19 -> 1500 | ... P19: =+O19 -> 1500 | Q19: =SUM(E19:P19) -> 18000 | R19: =Q19/$B$4 -> 0.36889782 | S19: 16600 | T19: =IFERROR(Q19/S19-1,"-") -> 0.084337349 | V19: =Q19/(Q71-Q63-Q58-Q29) -> 0.075648896
A20: 4920-8502 | C20: Real Estate Taxes | E20: =+'Tenant Recoveries'!H22 -> 230 | F20: =+E20 -> 230 | G20: =+F20 -> 230 | H20: =+G20 -> 230 | I20: =+H20 -> 230 | J20: =+I20 -> 230 | K20: =+J20 -> 230 | L20: =+K20 -> 230 | M20: =+L20 -> 230 | ... P20: =+O20 -> 230 | Q20: =SUM(E20:P20) -> 2760 | R20: =Q20/$B$4 -> 0.056564332 | S20: 5040 | T20: =IFERROR(Q20/S20-1,"-") -> -0.45238095 | V20: =Q20/Q58 -> 0.051197835
A21: 4930-8502 | C21: Insurance | Q21: =SUM(E21:P21) -> 0 | R21: =Q21/$B$4 -> 0 | T21: =IFERROR(Q21/S21-1,"-") -> -
C22: Total Reimbursements | E22: =SUM(E18:E21) -> 5232.3182 | F22: =SUM(F18:F21) -> 4778.6799 | G22: =SUM(G18:G21) -> 4408.1949 | H22: =SUM(H18:H21) -> 3329.9894 | I22: =SUM(I18:I21) -> 3192.9626 | J22: =SUM(J18:J21) -> 3185.5739 | K22: =SUM(K18:K21) -> 3343.4234 | L22: =SUM(L18:L21) -> 3258.7892 | ... Q22: =SUM(Q18:Q21) -> 42571.331 | R22: =Q22/$B$4 -> 0.87247061 | S22: =SUM(S18:S21) -> 51305.83 | T22: =IFERROR(Q22/S22-1,"-") -> -0.17024379
R23: =Q23/$B$4 -> 0
B24: TOTAL REVENUES | E24: =+E15+E22 -> 70264.123 | F24: =+F15+F22 -> 69810.485 | G24: =+G15+G22 -> 69439.996 | H24: =+H15+H22 -> 56337.408 | I24: =+I15+I22 -> 56200.381 | J24: =+J15+J22 -> 56192.992 | K24: =+K15+K22 -> 49299.047 | L24: =+L15+L22 -> 54517.662 | ... Q24: =+Q15+Q22 -> 656533.5 | R24: =Q24/$B$4 -> 13.45521 | S24: =+S15+S22 -> 807025.46 | T24: =IFERROR(Q24/S24-1,"-") -> -0.18647734 | V24: Solaray - $108,225; SEOM - $39,439 | W24: =+S24-Q24 -> 150491.96
V25: $147,664 combined
B26: Reimbursable Expenses
A27: 6030-8502 | C27: Maintenance Salaries | E27: ='Allocated Expenses'!E6 -> 1376.0833 | F27: ='Allocated Expenses'!F6 -> 1376.0833 | G27: ='Allocated Expenses'!G6 -> 1376.0833 | H27: ='Allocated Expenses'!H6 -> 1376.0833 | I27: ='Allocated Expenses'!I6 -> 1376.0833 | J27: ='Allocated Expenses'!J6 -> 1376.0833 | K27: ='Allocated Expenses'!K6 -> 1376.0833 | L27: ='Allocated Expenses'!L6 -> 1376.0833 | ... P27: ='Allocated Expenses'!P6 -> 1376.0833 | Q27: =SUM(E27:P27) -> 16513 | R27: =Q27/$B$4 -> 0.33842276 | S27: 11212.8 | T27: =IFERROR(Q27/S27-1,"-") -> 0.47269192
A29: 6120-8502 | C29: Electric | E29: 4254 | F29: 3703 | G29: 3253 | H29: 2382 | I29: 2178 | J29: 2167 | K29: 2402 | L29: 2276 | M29: 1975 | N29: 1964 | O29: 2490 | P29: 3626 | Q29: =SUM(E29:P29) -> 32670 | R29: =Q29/$B$4 -> 0.66954953 | S29: 34280.3 | T29: =IFERROR(Q29/S29-1,"-") -> -0.046974501 | U29: DW | V29: Data\Shared\Properties\Business Plans - All Entities\2026\ISG Electric data
A31: 6130-8502 | C31: Water & Sewer | E31: ='Water Sewer'!D19 -> 879.62 | F31: ='Water Sewer'!E19 -> 872.41 | G31: ='Water Sewer'!F19 -> 890.95 | H31: ='Water Sewer'!G19 -> 885.8 | I31: ='Water Sewer'!H19 -> 924.94 | J31: ='Water Sewer'!I19 -> 842.54 | K31: ='Water Sewer'!J19 -> 923.91 | L31: ='Water Sewer'!K19 -> 912.58 | ... P31: ='Water Sewer'!O19 -> 992.92 | Q31: =SUM(E31:P31) -> 11162.11 | R31: =Q31/$B$4 -> 0.22875989 | S31: 11254.54 | T31: =IFERROR(Q31/S31-1,"-") -> -0.0082126857 | V31: 2025 Business Plan grown 3%
D33: Building Maint.-Contractual | E33: ='Building Maint'!C15 -> 1766 | F33: ='Building Maint'!D15 -> 1566 | G33: ='Building Maint'!E15 -> 816 | H33: ='Building Maint'!F15 -> 2627 | I33: ='Building Maint'!G15 -> 1566 | J33: ='Building Maint'!H15 -> 816 | K33: ='Building Maint'!I15 -> 1766 | L33: ='Building Maint'!J15 -> 1566 | ... P33: ='Building Maint'!N15 -> 816 | Q33: =SUM(E33:P33) -> 18314 | R33: =Q33/$B$4 -> 0.37533303
D34: Building Maint.-Recurring | E34: ='Building Maint'!C8 -> 2115 | F34: ='Building Maint'!D8 -> 2140 | G34: ='Building Maint'!E8 -> 1815 | H34: ='Building Maint'!F8 -> 2215 | I34: ='Building Maint'!G8 -> 6900 | J34: ='Building Maint'!H8 -> 1690 | K34: ='Building Maint'!I8 -> 2390 | L34: ='Building Maint'!J8 -> 1690 | ... P34: ='Building Maint'!N8 -> 1690 | Q34: =SUM(E34:P34) -> 28765 | R34: =Q34/$B$4 -> 0.5895192
D35: Building Maint.-Big Projects | F35: =1.03*1500 -> 1545 | J35: =1.03*15000 -> 15450 | N35: =1.03*1500 -> 1545 | Q35: =SUM(E35:P35) -> 18540 | R35: =Q35/$B$4 -> 0.37996475
A36: 6220-8502 | C36: Building Maintenance | E36: =SUM(E33:E35) -> 3881 | F36: =SUM(F33:F35) -> 5251 | G36: =SUM(G33:G35) -> 2631 | H36: =SUM(H33:H35) -> 4842 | I36: =SUM(I33:I35) -> 8466 | J36: =SUM(J33:J35) -> 17956 | K36: =SUM(K33:K35) -> 4156 | L36: =SUM(L33:L35) -> 3256 | ... Q36: =SUM(Q33:Q35) -> 65619 | R36: =Q36/$B$4 -> 1.344817 | S36: 41281.12 | T36: =IFERROR(Q36/S36-1,"-") -> 0.58956443
A38: 6330-850 | B38: (SC) | C38: Parking Lot Cleaning | Q38: =SUM(E38:P38) -> 0 | R38: =Q38/$B$4 -> 0
D40: Parking Lot Maint.-Contractual | Q40: =SUM(E40:P40) -> 0 | R40: =Q40/$B$4 -> 0
D41: Parking Lot Maint.-Recurring | E41: ='Parking Lot Maint'!C8 -> 0 | F41: ='Parking Lot Maint'!D8 -> 0 | G41: ='Parking Lot Maint'!E8 -> 0 | H41: ='Parking Lot Maint'!F8 -> 0 | I41: ='Parking Lot Maint'!G8 -> 0 | J41: ='Parking Lot Maint'!H8 -> 0 | K41: ='Parking Lot Maint'!I8 -> 0 | L41: ='Parking Lot Maint'!J8 -> 0 | ... P41: ='Parking Lot Maint'!N8 -> 0 | Q41: =SUM(E41:P41) -> 0 | R41: =Q41/$B$4 -> 0
D42: Parking Lot Maint.-Big Projects | Q42: =SUM(E42:P42) -> 0 | R42: =Q42/$B$4 -> 0
A43: 6330-8502 | C43: Parking Lot Maintenance | E43: =SUM(E40:E42) -> 0 | F43: =SUM(F40:F42) -> 0 | G43: =SUM(G40:G42) -> 0 | H43: =SUM(H40:H42) -> 0 | I43: =SUM(I40:I42) -> 0 | J43: =SUM(J40:J42) -> 0 | K43: =SUM(K40:K42) -> 0 | L43: =SUM(L40:L42) -> 0 | ... Q43: =SUM(Q40:Q42) -> 0 | R43: =Q43/$B$4 -> 0 | S43: 133 | T43: =IFERROR(Q43/S43-1,"-") -> -1
A45: 6370-8502 | C45: Snow Removal | Q45: =SUM(E45:P45) -> 0 | R45: =Q45/$B$4 -> 0 | T45: =IFERROR(Q45/S45-1,"-") -> -
D47: Landscaping-Contractual | Q47: =SUM(E47:P47) -> 0 | R47: =Q47/$B$4 -> 0
D48: Landscaping-Recurring | E48: =Landscaping!C8 -> 0 | F48: =Landscaping!D8 -> 0 | G48: =Landscaping!E8 -> 0 | H48: =Landscaping!F8 -> 0 | I48: =Landscaping!G8 -> 0 | J48: =Landscaping!H8 -> 0 | K48: =Landscaping!I8 -> 0 | L48: =Landscaping!J8 -> 0 | ... P48: =Landscaping!N8 -> 0 | Q48: =SUM(E48:P48) -> 0 | R48: =Q48/$B$4 -> 0
D49: Landscaping-Big Projects | Q49: =SUM(E49:P49) -> 0 | R49: =Q49/$B$4 -> 0
A50: 6380-8502 | C50: Landscaping | E50: =SUM(E47:E49) -> 0 | F50: =SUM(F47:F49) -> 0 | G50: =SUM(G47:G49) -> 0 | H50: =SUM(H47:H49) -> 0 | I50: =SUM(I47:I49) -> 0 | J50: =SUM(J47:J49) -> 0 | K50: =SUM(K47:K49) -> 0 | L50: =SUM(L47:L49) -> 0 | ... Q50: =SUM(Q47:Q49) -> 0 | R50: =Q50/$B$4 -> 0 | S50: 157 | T50: =IFERROR(Q50/S50-1,"-") -> -1
A52: 6350-8502 | C52: Security | Q52: =SUM(E52:P52) -> 0 | R52: =Q52/$B$4 -> 0 | T52: =IFERROR(Q52/S52-1,"-") -> -
A54: 6610-8502 | B54: (BP) | C54: Management Fee | E54: =ROUND(E$24*0.04,0) -> 2811 | F54: =ROUND(F$24*0.04,0) -> 2792 | G54: =ROUND(G$24*0.04,0) -> 2778 | H54: =ROUND(H$24*0.04,0) -> 2253 | I54: =ROUND(I$24*0.04,0) -> 2248 | J54: =ROUND(J$24*0.04,0) -> 2248 | K54: =ROUND(K$24*0.04,0) -> 1972 | L54: =ROUND(L$24*0.04,0) -> 2181 | ... P54: =ROUND(P$24*0.04,0) -> 1757 | Q54: =SUM(E54:P54) -> 26262 | R54: =Q54/$B$4 -> 0.53822191 | S54: 31396.41 | T54: =IFERROR(Q54/S54-1,"-") -> -0.16353494
A56: 6270-8502 | C56: Trash Removal | E56: =Trash!C8 -> 0 | F56: =Trash!D8 -> 0 | G56: =Trash!E8 -> 0 | H56: =Trash!F8 -> 0 | I56: =Trash!G8 -> 0 | J56: =Trash!H8 -> 0 | K56: =Trash!I8 -> 0 | L56: =Trash!J8 -> 0 | ... P56: =Trash!N8 -> 0 | Q56: =SUM(E56:P56) -> 0 | R56: =Q56/$B$4 -> 0 | S56: 191 | T56: =IFERROR(Q56/S56-1,"-") -> -1
A58: 6410-8502 | C58: Real Estate Taxes | E58: =+'INS RET'!E34 -> 4492.3774 | F58: =+'INS RET'!F34 -> 4492.3774 | G58: =+'INS RET'!G34 -> 4492.3774 | H58: =+'INS RET'!H34 -> 4492.3774 | I58: =+'INS RET'!I34 -> 4492.3774 | J58: =+'INS RET'!J34 -> 4492.3774 | K58: =+'INS RET'!K34 -> 4492.3774 | L58: =+'INS RET'!L34 -> 4492.3774 | ... P58: =+'INS RET'!P34 -> 4492.3774 | Q58: =SUM(E58:P58) -> 53908.529 | R58: =Q58/$B$4 -> 1.1048188 | S58: 119327.25 | T58: =IFERROR(Q58/S58-1,"-") -> -0.54822952
D60: Insurance-Liability | E60: =+'INS RET'!E20+'INS RET'!E21 -> 1320 | F60: =+'INS RET'!F20+'INS RET'!F21 -> 1320 | G60: =+'INS RET'!G20+'INS RET'!G21 -> 1320 | H60: =+'INS RET'!H20+'INS RET'!H21 -> 1320 | I60: =+'INS RET'!I20+'INS RET'!I21 -> 1320 | J60: =+'INS RET'!J20+'INS RET'!J21 -> 1320 | K60: =+'INS RET'!K20+'INS RET'!K21 -> 1320 | L60: =+'INS RET'!L20+'INS RET'!L21 -> 1320 | ... P60: =+'INS RET'!P20+'INS RET'!P21 -> 1346.4 | Q60: =SUM(E60:P60) -> 15892.8 | R60: =Q60/$B$4 -> 0.32571218
D61: Insurance-Property | E61: =+'INS RET'!E23 -> 417 | F61: =+'INS RET'!F23 -> 417 | G61: =+'INS RET'!G23 -> 417 | H61: =+'INS RET'!H23 -> 417 | I61: =+'INS RET'!I23 -> 417 | J61: =+'INS RET'!J23 -> 417 | K61: =+'INS RET'!K23 -> 417 | L61: =+'INS RET'!L23 -> 417 | ... P61: =+'INS RET'!P23 -> 425.34 | Q61: =SUM(E61:P61) -> 5020.68 | R61: =Q61/$B$4 -> 0.10289544
D62: Insurance-Other | E62: =+'INS RET'!E24 -> 0 | F62: =+'INS RET'!F24 -> 0 | G62: =+'INS RET'!G24 -> 0 | H62: =+'INS RET'!H24 -> 0 | I62: =+'INS RET'!I24 -> 0 | J62: =+'INS RET'!J24 -> 0 | K62: =+'INS RET'!K24 -> 0 | L62: =+'INS RET'!L24 -> 0 | ... P62: =+'INS RET'!P24 -> 0 | Q62: =SUM(E62:P62) -> 0 | R62: =Q62/$B$4 -> 0
A63: 6510-8502 | C63: Insurance | E63: =SUM(E60:E62) -> 1737 | F63: =SUM(F60:F62) -> 1737 | G63: =SUM(G60:G62) -> 1737 | H63: =SUM(H60:H62) -> 1737 | I63: =SUM(I60:I62) -> 1737 | J63: =SUM(J60:J62) -> 1737 | K63: =SUM(K60:K62) -> 1737 | L63: =SUM(L60:L62) -> 1737 | ... Q63: =SUM(Q60:Q62) -> 20913.48 | R63: =Q63/$B$4 -> 0.42860762 | S63: 20400 | T63: =IFERROR(Q63/S63-1,"-") -> 0.025170588
D65: Cleaning & Supplies | E65: ='Allocated Expenses'!E13+'Allocated Expenses'!E20 -> 6079.5488 | F65: ='Allocated Expenses'!F13+'Allocated Expenses'!F20 -> 6079.5488 | G65: ='Allocated Expenses'!G13+'Allocated Expenses'!G20 -> 6079.5488 | H65: ='Allocated Expenses'!H13+'Allocated Expenses'!H20 -> 5057.0676 | I65: ='Allocated Expenses'!I13+'Allocated Expenses'!I20 -> 5057.0676 | J65: ='Allocated Expenses'!J13+'Allocated Expenses'!J20 -> 5057.0676 | K65: ='Allocated Expenses'!K13+'Allocated Expenses'!K20 -> 5057.0676 | L65: ='Allocated Expenses'!L13+'Allocated Expenses'!L20 -> 5057.0676 | ... P65: ='Allocated Expenses'!P13+'Allocated Expenses'!P20 -> 3527.3924 | Q65: =SUM(E65:P65) -> 59163.229 | R65: =Q65/$B$4 -> 1.2125103 | U65: DW | V65: Based on occupancy. Includes cleaning, supplies, and porter fee.
D66: Cleaning & Supplies-Vacancies | E66: ='Allocated Expenses'!E29 -> 66.604176 | F66: ='Allocated Expenses'!F29 -> 66.604176 | G66: ='Allocated Expenses'!G29 -> 66.604176 | H66: ='Allocated Expenses'!H29 -> 123.74732 | I66: ='Allocated Expenses'!I29 -> 123.74732 | J66: ='Allocated Expenses'!J29 -> 123.74732 | K66: ='Allocated Expenses'!K29 -> 123.74732 | L66: ='Allocated Expenses'!L29 -> 123.74732 | ... P66: ='Allocated Expenses'!P29 -> 209.23587 | Q66: =SUM(E66:P66) -> 1570.004 | R66: =Q66/$B$4 -> 0.03217617 | U66: DW | V66: Based on occupancy.
A67: 6250-8502 | B67: (BP) | C67: Cleaning & Supplies | E67: =SUM(E65:E66) -> 6146.153 | F67: =SUM(F65:F66) -> 6146.153 | G67: =SUM(G65:G66) -> 6146.153 | H67: =SUM(H65:H66) -> 5180.8149 | I67: =SUM(I65:I66) -> 5180.8149 | J67: =SUM(J65:J66) -> 5180.8149 | K67: =SUM(K65:K66) -> 5180.8149 | L67: =SUM(L65:L66) -> 5180.8149 | ... P67: =SUM(P65:P66) -> 3736.6283 | Q67: =SUM(E67:P67) -> 60733.233 | R67: =Q67/$B$4 -> 1.2446865 | S67: 62995.86 | T67: =IFERROR(Q67/S67-1,"-") -> -0.035917072
A69: 6990-8502 | B69: (SC) | C69: Other - Condo Fee | E69: ='Allocated Expenses'!E36 -> 14413 | F69: ='Allocated Expenses'!F36 -> 0 | G69: ='Allocated Expenses'!G36 -> 0 | H69: ='Allocated Expenses'!H36 -> 14413 | I69: ='Allocated Expenses'!I36 -> 0 | J69: ='Allocated Expenses'!J36 -> 0 | K69: ='Allocated Expenses'!K36 -> 14413 | L69: ='Allocated Expenses'!L36 -> 0 | ... P69: ='Allocated Expenses'!P36 -> 0 | Q69: =SUM(E69:P69) -> 57652 | R69: =Q69/$B$4 -> 1.1815387 | S69: 69084 | T69: =IFERROR(Q69/S69-1,"-") -> -0.16547971
C71: Total Reimbursable Expenses | E71: =+E27+E29+E31+E36+E38+E43+E45+E50+E52+E54+E56+E58+E63+E67+E69 -> 39990.234 | F71: =+F27+F29+F31+F36+F38+F43+F45+F50+F52+F54+F56+F58+F63+F67+F69 -> 26370.024 | G71: =+G27+G29+G31+G36+G38+G43+G45+G50+G52+G54+G56+G58+G63+G67+G69 -> 23304.564 | H71: =+H27+H29+H31+H36+H38+H43+H45+H50+H52+H54+H56+H58+H63+H67+H69 -> 37562.076 | I71: =+I27+I29+I31+I36+I38+I43+I45+I50+I52+I54+I56+I58+I63+I67+I69 -> 26603.216 | J71: =+J27+J29+J31+J36+J38+J43+J45+J50+J52+J54+J56+J58+J63+J67+J69 -> 35999.816 | K71: =+K27+K29+K31+K36+K38+K43+K45+K50+K52+K54+K56+K58+K63+K67+K69 -> 36653.186 | L71: =+L27+L29+L31+L36+L38+L43+L45+L50+L52+L54+L56+L58+L63+L67+L69 -> 21411.856 | ... Q71: =+Q27+Q29+Q31+Q36+Q38+Q43+Q45+Q50+Q52+Q54+Q56+Q58+Q63+Q67+Q69 -> 345433.35 | R71: =Q71/$B$4 -> 7.0794227 | S71: =+S27+S29+S31+S36+S38+S43+S45+S50+S52+S54+S56+S58+S63+S67+S69 -> 401713.28 | T71: =IFERROR(Q71/S71-1,"-") -> -0.14009974 | V71: =Q71-Q29-Q58 -> 258854.82
B73: Non-Reimbursable Expenses | R73: =Q73/$B$4 -> 0
A75: 5210-8501 | C75: Bad Debt | E75: 0 | F75: 0 | G75: 0 | H75: 0 | I75: 0 | J75: 0 | K75: 0 | L75: 0 | M75: 0 | N75: 0 | O75: 0 | P75: 0 | Q75: =SUM(E75:P75) -> 0 | R75: =Q75/$B$4 -> 0 | T75: =IFERROR(Q75/S75-1,"-") -> -
A77: 6010-8501 | D77: Salaries & Wages | E77: ='Allocated Expenses'!E43 -> 1704.8208 | F77: ='Allocated Expenses'!F43 -> 1704.8208 | G77: ='Allocated Expenses'!G43 -> 1704.8208 | H77: ='Allocated Expenses'!H43 -> 1704.8208 | I77: ='Allocated Expenses'!I43 -> 1704.8208 | J77: ='Allocated Expenses'!J43 -> 1704.8208 | K77: ='Allocated Expenses'!K43 -> 1704.8208 | L77: ='Allocated Expenses'!L43 -> 1704.8208 | ... P77: ='Allocated Expenses'!P43 -> 1704.8208 | Q77: =SUM(E77:P77) -> 20457.85 | R77: =Q77/$B$4 -> 0.41926979
A78: 6620-8501 | D78: Commissions-Internal Broker | E78: ='Allocated Expenses'!E50 -> 567.7875 | F78: ='Allocated Expenses'!F50 -> 0 | G78: ='Allocated Expenses'!G50 -> 0 | H78: ='Allocated Expenses'!H50 -> 567.7875 | I78: ='Allocated Expenses'!I50 -> 0 | J78: ='Allocated Expenses'!J50 -> 0 | K78: ='Allocated Expenses'!K50 -> 567.7875 | L78: ='Allocated Expenses'!L50 -> 0 | ... P78: ='Allocated Expenses'!P50 -> 0 | Q78: =SUM(E78:P78) -> 2271.15 | R78: =Q78/$B$4 -> 0.046545682
C79: Leasing Salaries and Commissions | E79: =SUM(E77:E78) -> 2272.6083 | F79: =SUM(F77:F78) -> 1704.8208 | G79: =SUM(G77:G78) -> 1704.8208 | H79: =SUM(H77:H78) -> 2272.6083 | I79: =SUM(I77:I78) -> 1704.8208 | J79: =SUM(J77:J78) -> 1704.8208 | K79: =SUM(K77:K78) -> 2272.6083 | L79: =SUM(L77:L78) -> 1704.8208 | ... Q79: =SUM(Q77:Q78) -> 22729 | R79: =Q79/$B$4 -> 0.46581547 | S79: 22637.4 | T79: =IFERROR(Q79/S79-1,"-") -> 0.0040464011
A81: 6110-8501 | D81: Gas | Q81: =SUM(E81:P81) -> 0 | R81: =Q81/$B$4 -> 0
A82: 6120-8501 | D82: Electric | Q82: =SUM(E82:P82) -> 0 | R82: =Q82/$B$4 -> 0
A83: 6130-8501 | D83: Water & Sewer | Q83: =SUM(E83:P83) -> 0 | R83: =Q83/$B$4 -> 0
C84: Utilities | E84: =SUM(E81:E83) -> 0 | F84: =SUM(F81:F83) -> 0 | G84: =SUM(G81:G83) -> 0 | H84: =SUM(H81:H83) -> 0 | I84: =SUM(I81:I83) -> 0 | J84: =SUM(J81:J83) -> 0 | K84: =SUM(K81:K83) -> 0 | L84: =SUM(L81:L83) -> 0 | ... Q84: =SUM(Q81:Q83) -> 0 | R84: =Q84/$B$4 -> 0 | S84: 39.41 | T84: =IFERROR(Q84/S84-1,"-") -> -1
D86: Building Maint.-Recurring | E86: =1.03*915 -> 942.45 | F86: =1.03*915 -> 942.45 | G86: =1.03*915 -> 942.45 | H86: =1.03*915 -> 942.45 | I86: =1.03*915 -> 942.45 | J86: =1.03*915 -> 942.45 | K86: =1.03*915 -> 942.45 | L86: =1.03*915 -> 942.45 | ... P86: =1.03*915 -> 942.45 | Q86: =SUM(E86:P86) -> 11309.4 | R86: =Q86/$B$4 -> 0.2317785
D87: Building Maint.-Big Projects | Q87: =SUM(E87:P87) -> 0 | R87: =Q87/$B$4 -> 0
A88: 6220-8501 | C88: Building Maintenance | E88: =SUM(E86:E87) -> 942.45 | F88: =SUM(F86:F87) -> 942.45 | G88: =SUM(G86:G87) -> 942.45 | H88: =SUM(H86:H87) -> 942.45 | I88: =SUM(I86:I87) -> 942.45 | J88: =SUM(J86:J87) -> 942.45 | K88: =SUM(K86:K87) -> 942.45 | L88: =SUM(L86:L87) -> 942.45 | ... Q88: =SUM(Q86:Q87) -> 11309.4 | R88: =Q88/$B$4 -> 0.2317785 | S88: 6223.61 | T88: =IFERROR(Q88/S88-1,"-") -> 0.81717685
A90: 6610-8501 | B90: (SC) | C90: Management fee | Q90: =SUM(E90:P90) -> 0 | R90: =Q90/$B$4 -> 0 | T90: =R90/S90-1 -> #DIV/0!
T91: =R91/S91-1 -> #DIV/0!
A92: 7110-8501 | C92: Marketing | E92: ='Allocated Expenses'!E57 -> 437.5 | F92: ='Allocated Expenses'!F57 -> 437.5 | G92: ='Allocated Expenses'!G57 -> 437.5 | H92: ='Allocated Expenses'!H57 -> 437.5 | I92: ='Allocated Expenses'!I57 -> 437.5 | J92: ='Allocated Expenses'!J57 -> 437.5 | K92: ='Allocated Expenses'!K57 -> 437.5 | L92: ='Allocated Expenses'!L57 -> 437.5 | ... P92: ='Allocated Expenses'!P57 -> 437.5 | Q92: =SUM(E92:P92) -> 5250 | R92: =Q92/$B$4 -> 0.1075952 | S92: 4944.8 | T92: =IFERROR(Q92/S92-1,"-") -> 0.061721404
A94: 8210-8501 | C94: Business Taxes | E94: ='Allocated Expenses'!E64 -> 0 | F94: ='Allocated Expenses'!F64 -> 0 | G94: ='Allocated Expenses'!G64 -> 0 | H94: ='Allocated Expenses'!H64 -> 1374.6224 | I94: ='Allocated Expenses'!I64 -> 0 | J94: ='Allocated Expenses'!J64 -> 0 | K94: ='Allocated Expenses'!K64 -> 0 | L94: ='Allocated Expenses'!L64 -> 0 | ... P94: ='Allocated Expenses'!P64 -> 0 | Q94: =SUM(E94:P94) -> 1374.6224 | R94: =Q94/$B$4 -> 0.028171955 | S94: 997 | T94: =IFERROR(Q94/S94-1,"-") -> 0.37875864
A96: 8310-8501 | C96: Legal & Accounting | E96: ='Allocated Expenses'!E71 -> 900.78333 | F96: ='Allocated Expenses'!F71 -> 900.78333 | G96: ='Allocated Expenses'!G71 -> 900.78333 | H96: ='Allocated Expenses'!H71 -> 900.78333 | I96: ='Allocated Expenses'!I71 -> 900.78333 | J96: ='Allocated Expenses'!J71 -> 900.78333 | K96: ='Allocated Expenses'!K71 -> 900.78333 | L96: ='Allocated Expenses'!L71 -> 900.78333 | ... P96: ='Allocated Expenses'!P71 -> 900.78333 | Q96: =SUM(E96:P96) -> 10809.4 | R96: =Q96/$B$4 -> 0.22153134 | S96: 9835.03 | T96: =IFERROR(Q96/S96-1,"-") -> 0.099071381
A98: 8190-8501 | D98: Bank Fees | E98: ='Allocated Expenses'!E78 -> 55.8775 | F98: ='Allocated Expenses'!F78 -> 55.8775 | G98: ='Allocated Expenses'!G78 -> 55.8775 | H98: ='Allocated Expenses'!H78 -> 55.8775 | I98: ='Allocated Expenses'!I78 -> 55.8775 | J98: ='Allocated Expenses'!J78 -> 55.8775 | K98: ='Allocated Expenses'!K78 -> 55.8775 | L98: ='Allocated Expenses'!L78 -> 55.8775 | ... P98: ='Allocated Expenses'!P78 -> 55.8775 | Q98: =SUM(E98:P98) -> 670.53 | R98: =Q98/$B$4 -> 0.013742058
A99: 8930-8501 | D99: Office Supplies | E99: ='Allocated Expenses'!E85 -> 0 | F99: ='Allocated Expenses'!F85 -> 0 | G99: ='Allocated Expenses'!G85 -> 0 | H99: ='Allocated Expenses'!H85 -> 0 | I99: ='Allocated Expenses'!I85 -> 0 | J99: ='Allocated Expenses'!J85 -> 0 | K99: ='Allocated Expenses'!K85 -> 0 | L99: ='Allocated Expenses'!L85 -> 0 | ... P99: ='Allocated Expenses'!P85 -> 0 | Q99: =SUM(E99:P99) -> 0 | R99: =Q99/$B$4 -> 0
A100: 8950-8501 | D100: Postage | E100: ='Allocated Expenses'!E92 -> 0 | F100: ='Allocated Expenses'!F92 -> 0 | G100: ='Allocated Expenses'!G92 -> 0 | H100: ='Allocated Expenses'!H92 -> 0 | I100: ='Allocated Expenses'!I92 -> 0 | J100: ='Allocated Expenses'!J92 -> 0 | K100: ='Allocated Expenses'!K92 -> 0 | L100: ='Allocated Expenses'!L92 -> 0 | ... P100: ='Allocated Expenses'!P92 -> 0 | Q100: =SUM(E100:P100) -> 0 | R100: =Q100/$B$4 -> 0
A101: 8990-8501 | D101: Other G&A Expense | E101: ='Allocated Expenses'!E99 -> 7.21 | F101: ='Allocated Expenses'!F99 -> 7.21 | G101: ='Allocated Expenses'!G99 -> 7.21 | H101: ='Allocated Expenses'!H99 -> 7.21 | I101: ='Allocated Expenses'!I99 -> 7.21 | J101: ='Allocated Expenses'!J99 -> 7.21 | K101: ='Allocated Expenses'!K99 -> 7.21 | L101: ='Allocated Expenses'!L99 -> 7.21 | ... P101: ='Allocated Expenses'!P99 -> 7.21 | Q101: =SUM(E101:P101) -> 86.52 | R101: =Q101/$B$4 -> 0.0017731688
A102: 8990-9800 | D102: Other G&A-allocated from LIK | E102: ='Allocated Expenses'!E106 -> 1240.12 | F102: ='Allocated Expenses'!F106 -> 1240.12 | G102: ='Allocated Expenses'!G106 -> 1240.12 | H102: ='Allocated Expenses'!H106 -> 1240.12 | I102: ='Allocated Expenses'!I106 -> 1240.12 | J102: ='Allocated Expenses'!J106 -> 1240.12 | K102: ='Allocated Expenses'!K106 -> 1240.12 | L102: ='Allocated Expenses'!L106 -> 1240.12 | ... P102: ='Allocated Expenses'!P106 -> 1240.12 | Q102: =SUM(E102:P102) -> 14881.44 | R102: =Q102/$B$4 -> 0.30498504
C103: General & Administrative | E103: =SUM(E98:E102) -> 1303.2075 | F103: =SUM(F98:F102) -> 1303.2075 | G103: =SUM(G98:G102) -> 1303.2075 | H103: =SUM(H98:H102) -> 1303.2075 | I103: =SUM(I98:I102) -> 1303.2075 | J103: =SUM(J98:J102) -> 1303.2075 | K103: =SUM(K98:K102) -> 1303.2075 | L103: =SUM(L98:L102) -> 1303.2075 | ... Q103: =SUM(Q98:Q102) -> 15638.49 | R103: =Q103/$B$4 -> 0.32050027 | S103: 15244.65 | T103: =IFERROR(Q103/S103-1,"-") -> 0.025834637
C105: Total Non-Reimbursable Expenses | E105: =+E75+E79+E84+E88+E90+E92+E94+E96+E103 -> 5856.5492 | F105: =+F75+F79+F84+F88+F90+F92+F94+F96+F103 -> 5288.7617 | G105: =+G75+G79+G84+G88+G90+G92+G94+G96+G103 -> 5288.7617 | H105: =+H75+H79+H84+H88+H90+H92+H94+H96+H103 -> 7231.1715 | I105: =+I75+I79+I84+I88+I90+I92+I94+I96+I103 -> 5288.7617 | J105: =+J75+J79+J84+J88+J90+J92+J94+J96+J103 -> 5288.7617 | K105: =+K75+K79+K84+K88+K90+K92+K94+K96+K103 -> 5856.5492 | L105: =+L75+L79+L84+L88+L90+L92+L94+L96+L103 -> 5288.7617 | ... Q105: =+Q75+Q79+Q84+Q88+Q90+Q92+Q94+Q96+Q103 -> 67110.912 | R105: =Q105/$B$4 -> 1.3753927 | S105: =+S75+S79+S84+S88+S90+S92+S94+S96+S103 -> 59921.9 | T105: =IFERROR(Q105/S105-1,"-") -> 0.11997304
B107: TOTAL OPERATING EXPENSES | E107: =+E71+E105 -> 45846.783 | F107: =+F71+F105 -> 31658.785 | G107: =+G71+G105 -> 28593.325 | H107: =+H71+H105 -> 44793.247 | I107: =+I71+I105 -> 31891.977 | J107: =+J71+J105 -> 41288.577 | K107: =+K71+K105 -> 42509.735 | L107: =+L71+L105 -> 26700.617 | ... Q107: =+Q71+Q105 -> 412544.26 | R107: =Q107/$B$4 -> 8.4548154 | S107: =+S71+S105 -> 461635.18 | T107: =IFERROR(Q107/S107-1,"-") -> -0.10634137
B109: NET OPERATING INCOME | E109: =+E24-E107 -> 24417.34 | F109: =+F24-F107 -> 38151.699 | G109: =+G24-G107 -> 40846.671 | H109: =+H24-H107 -> 11544.16 | I109: =+I24-I107 -> 24308.404 | J109: =+J24-J107 -> 14904.415 | K109: =+K24-K107 -> 6789.3118 | L109: =+L24-L107 -> 27817.045 | ... Q109: =+Q24-Q107 -> 243989.23 | R109: =Q109/$B$4 -> 5.0003941 | S109: =+S24-S107 -> 345390.28 | T109: =IFERROR(Q109/S109-1,"-") -> -0.29358397
A111: 1420-0000 | D111: Land Improvements | R111: =Q111/$B$4 -> 0
A112: 1430-0000 | D112: Buildings | Q112: =SUM(E112:P112) -> 0 | R112: =Q112/$B$4 -> 0
A113: 1450-0000 | D113: Equipment | R113: =Q113/$B$4 -> 0
A114: 1980-8501 | D114: Capital Improvements | R114: =Q114/$B$4 -> 0
C115: Capital Improvements | E115: =SUM(E111:E114) -> 0 | F115: =SUM(F111:F114) -> 0 | G115: =SUM(G111:G114) -> 0 | H115: =SUM(H111:H114) -> 0 | I115: =SUM(I111:I114) -> 0 | J115: =SUM(J111:J114) -> 0 | K115: =SUM(K111:K114) -> 0 | L115: =SUM(L111:L114) -> 0 | ... Q115: =SUM(Q111:Q114) -> 0 | R115: =Q115/$B$4 -> 0 | T115: =IFERROR(Q115/S115-1,"-") -> -
A117: 1440-0000 | C117: Tenant Improvements | E117: ='Renew & Vac - Rent, TI, LC'!AH55 -> 0 | F117: ='Renew & Vac - Rent, TI, LC'!AI55 -> 0 | G117: ='Renew & Vac - Rent, TI, LC'!AJ55 -> 0 | H117: ='Renew & Vac - Rent, TI, LC'!AK55 -> 0 | I117: ='Renew & Vac - Rent, TI, LC'!AL55 -> 0 | J117: ='Renew & Vac - Rent, TI, LC'!AM55 -> 0 | K117: ='Renew & Vac - Rent, TI, LC'!AN55 -> 2346 | L117: ='Renew & Vac - Rent, TI, LC'!AO55 -> 0 | ... P117: ='Renew & Vac - Rent, TI, LC'!AS55 -> 0 | Q117: =SUM(E117:P117) -> 2346 | R117: =Q117/$B$4 -> 0.048079682 | S117: 10567.81 | T117: =IFERROR(Q117/S117-1,"-") -> -0.77800509
A119: 1940-8501 | D119: Deferred Marketing | Q119: =SUM(E119:P119) -> 0 | R119: =Q119/$B$4 -> 0
A120: 1940-8501 | D120: Outside Leasing Commissions | E120: ='Renew & Vac - Rent, TI, LC'!AH56 -> 0 | F120: ='Renew & Vac - Rent, TI, LC'!AI56 -> 0 | G120: ='Renew & Vac - Rent, TI, LC'!AJ56 -> 0 | H120: ='Renew & Vac - Rent, TI, LC'!AK56 -> 0 | I120: ='Renew & Vac - Rent, TI, LC'!AL56 -> 0 | J120: ='Renew & Vac - Rent, TI, LC'!AM56 -> 0 | K120: ='Renew & Vac - Rent, TI, LC'!AN56 -> 0 | L120: ='Renew & Vac - Rent, TI, LC'!AO56 -> 0 | ... P120: ='Renew & Vac - Rent, TI, LC'!AS56 -> 0 | Q120: =SUM(E120:P120) -> 0 | R120: =Q120/$B$4 -> 0
C121: Outside Leasing Commissions | E121: =SUM(E119:E120) -> 0 | F121: =SUM(F119:F120) -> 0 | G121: =SUM(G119:G120) -> 0 | H121: =SUM(H119:H120) -> 0 | I121: =SUM(I119:I120) -> 0 | J121: =SUM(J119:J120) -> 0 | K121: =SUM(K119:K120) -> 0 | L121: =SUM(L119:L120) -> 0 | ... Q121: =SUM(Q119:Q120) -> 0 | R121: =Q121/$B$4 -> 0 | S121: 1365 | T121: =IFERROR(Q121/S121-1,"-") -> -1 | V121: 7/2025 Reprojections is for Capitalized Lease Costs
B123: CASH FLOW BEFORE DEBT SERVICE | E123: =+E109-E115-E117-E121 -> 24417.34 | F123: =+F109-F115-F117-F121 -> 38151.699 | G123: =+G109-G115-G117-G121 -> 40846.671 | H123: =+H109-H115-H117-H121 -> 11544.16 | I123: =+I109-I115-I117-I121 -> 24308.404 | J123: =+J109-J115-J117-J121 -> 14904.415 | K123: =+K109-K115-K117-K121 -> 4443.3118 | L123: =+L109-L115-L117-L121 -> 27817.045 | ... Q123: =+Q109-Q115-Q117-Q121 -> 241643.23 | R123: =Q123/$B$4 -> 4.9523144 | S123: =+S109-S115-S117-S121 -> 333457.47 | T123: =IFERROR(Q123/S123-1,"-") -> -0.27534018
B125: Debt Service
A126: 9210-8501 | C126: Interest | E126: ='Allocated Expenses'!E114 -> 8057.7 | F126: ='Allocated Expenses'!F114 -> 8057.7 | G126: ='Allocated Expenses'!G114 -> 8057.7 | H126: ='Allocated Expenses'!H114 -> 8057.7 | I126: ='Allocated Expenses'!I114 -> 8057.7 | J126: ='Allocated Expenses'!J114 -> 8057.7 | K126: ='Allocated Expenses'!K114 -> 8057.7 | L126: ='Allocated Expenses'!L114 -> 8057.7 | ... P126: ='Allocated Expenses'!P114 -> 8057.7 | Q126: =SUM(E126:P126) -> 96692.4 | R126: =Q126/$B$4 -> 1.9816453 | S126: 97604.09 | T126: =IFERROR(Q126/S126-1,"-") -> -0.0093406946
A127: 2740-8501 | C127: Mortgage Amortization | E127: =+'Allocated Expenses'!E126 -> 0 | F127: =+'Allocated Expenses'!F126 -> 0 | G127: =+'Allocated Expenses'!G126 -> 0 | H127: =+'Allocated Expenses'!H126 -> 0 | I127: =+'Allocated Expenses'!I126 -> 0 | J127: =+'Allocated Expenses'!J126 -> 0 | K127: =+'Allocated Expenses'!K126 -> 0 | L127: =+'Allocated Expenses'!L126 -> 0 | ... P127: =+'Allocated Expenses'!P126 -> 0 | Q127: =SUM(E127:P127) -> 0 | R127: =Q127/$B$4 -> 0 | S127: 10635.05 | T127: =IFERROR(Q127/S127-1,"-") -> -1
A128: 2740-0000 | C128: Loan Proceeds | Q128: =SUM(E128:P128) -> 0 | R128: =Q128/$B$4 -> 0 | T128: =IFERROR(Q128/S128-1,"-") -> -
C129: Total Debt Service | E129: =SUM(E126:E128) -> 8057.7 | F129: =SUM(F126:F128) -> 8057.7 | G129: =SUM(G126:G128) -> 8057.7 | H129: =SUM(H126:H128) -> 8057.7 | I129: =SUM(I126:I128) -> 8057.7 | J129: =SUM(J126:J128) -> 8057.7 | K129: =SUM(K126:K128) -> 8057.7 | L129: =SUM(L126:L128) -> 8057.7 | ... Q129: =SUM(Q126:Q128) -> 96692.4 | R129: =Q129/$B$4 -> 1.9816453 | S129: =SUM(S126:S128) -> 108239.14 | T129: =IFERROR(Q129/S129-1,"-") -> -0.10667805
B131: CASH FLOW AFTER DEBT SERVICE | E131: =+E123-E129 -> 16359.64 | F131: =+F123-F129 -> 30093.999 | G131: =+G123-G129 -> 32788.971 | H131: =+H123-H129 -> 3486.4605 | I131: =+I123-I129 -> 16250.704 | J131: =+J123-J129 -> 6846.7148 | K131: =+K123-K129 -> -3614.3882 | L131: =+L123-L129 -> 19759.345 | ... Q131: =+Q123-Q129 -> 144950.83 | R131: =Q131/$B$4 -> 2.9706691 | S131: =+S123-S129 -> 225218.33 | T131: =IFERROR(Q131/S131-1,"-") -> -0.35639861
D135: ="Budget Import - "&B1 -> Budget Import - 3640 | E135: 5 | F135: =E135+1 -> 6 | G135: =F135+1 -> 7 | H135: =G135+1 -> 8 | I135: =H135+1 -> 9 | J135: =I135+1 -> 10 | K135: =J135+1 -> 11 | L135: =K135+1 -> 12 | M135: =L135+1 -> 13 | ... P135: =O135+1 -> 16 | Q135: <- Lookup Column
D136: Account | E136: 1 | F136: 2 | G136: 3 | H136: 4 | I136: 5 | J136: 6 | K136: 7 | L136: 8 | M136: 9 | N136: 10 | O136: 11 | P136: 12 | Q136: Total
A137: =VLOOKUP($D137,$A$10:$D$130,3,FALSE) -> Rental Income - In Place | D137: 4230-8501 | E137: =-(VLOOKUP($D137,$A$10:$P$131,E$135,FALSE)+E11) -> -65031.805 | F137: =-(VLOOKUP($D137,$A$10:$P$131,F$135,FALSE)+F11) -> -65031.805 | G137: =-(VLOOKUP($D137,$A$10:$P$131,G$135,FALSE)+G11) -> -65031.802 | H137: =-(VLOOKUP($D137,$A$10:$P$131,H$135,FALSE)+H11) -> -53007.418 | I137: =-(VLOOKUP($D137,$A$10:$P$131,I$135,FALSE)+I11) -> -53007.418 | J137: =-(VLOOKUP($D137,$A$10:$P$131,J$135,FALSE)+J11) -> -53007.418 | K137: =-(VLOOKUP($D137,$A$10:$P$131,K$135,FALSE)+K11) -> -45955.623 | L137: =-(VLOOKUP($D137,$A$10:$P$131,L$135,FALSE)+L11) -> -51258.873 | ... P137: =-(VLOOKUP($D137,$A$10:$P$131,P$135,FALSE)+P11) -> -40581.708 | Q137: =SUM(E137:P137) -> -613962.16
A138: =VLOOKUP($D138,$A$10:$D$130,3,FALSE) -> Electric | D138: 4710-8502 | E138: =-VLOOKUP($D138,$A$10:$P$131,E$135,FALSE) -> -3502.3182 | F138: =-VLOOKUP($D138,$A$10:$P$131,F$135,FALSE) -> -3048.6799 | G138: =-VLOOKUP($D138,$A$10:$P$131,G$135,FALSE) -> -2678.1949 | H138: =-VLOOKUP($D138,$A$10:$P$131,H$135,FALSE) -> -1599.9894 | I138: =-VLOOKUP($D138,$A$10:$P$131,I$135,FALSE) -> -1462.9626 | J138: =-VLOOKUP($D138,$A$10:$P$131,J$135,FALSE) -> -1455.5739 | K138: =-VLOOKUP($D138,$A$10:$P$131,K$135,FALSE) -> -1613.4234 | L138: =-VLOOKUP($D138,$A$10:$P$131,L$135,FALSE) -> -1528.7892 | ... P138: =-VLOOKUP($D138,$A$10:$P$131,P$135,FALSE) -> -1613.2074 | Q138: =SUM(E138:P138) -> -21811.331
A139: =VLOOKUP($D139,$A$10:$D$130,3,FALSE) -> Common Area Maintenance | D139: 4910-8502 | E139: =-VLOOKUP($D139,$A$10:$P$131,E$135,FALSE) -> -1500 | F139: =-VLOOKUP($D139,$A$10:$P$131,F$135,FALSE) -> -1500 | G139: =-VLOOKUP($D139,$A$10:$P$131,G$135,FALSE) -> -1500 | H139: =-VLOOKUP($D139,$A$10:$P$131,H$135,FALSE) -> -1500 | I139: =-VLOOKUP($D139,$A$10:$P$131,I$135,FALSE) -> -1500 | J139: =-VLOOKUP($D139,$A$10:$P$131,J$135,FALSE) -> -1500 | K139: =-VLOOKUP($D139,$A$10:$P$131,K$135,FALSE) -> -1500 | L139: =-VLOOKUP($D139,$A$10:$P$131,L$135,FALSE) -> -1500 | ... P139: =-VLOOKUP($D139,$A$10:$P$131,P$135,FALSE) -> -1500 | Q139: =SUM(E139:P139) -> -18000
...

Sheet Renew & Vac - Rent, TI, LC
B1: Lease Renewals / Vacancy Rent-Ups | S1: ='JV III Consolidated'!Q1 -> 46023 | CY1: Hidden -->
B2: ='JV III Consolidated'!J2 -> Lincoln JV III
B3: *Based on July-25 RR
A5: 3610
A6: 41821 | B6: =(A6-C24)/A6 -> 0.48863011 | D6: ="Vacancies - "&A5 -> Vacancies - 3610 | N6: ="Renewals - "&A5 -> Renewals - 3610
D7: Leasing Department Assumptions | N7: Leasing Department Assumptions | U7: =A5 -> 3610 | V7: 2025 | AH7: =V7+1 -> 2026 | CZ7: 2025 | DL7: 2026
A8: Suite # | B8: Tenant | C8: Sq Ft | D8: Rent Start Date | E8: Rent Exp. Date | F8: # Years | G8: Per Sq Ft | H8: T.I. /sq ft | I8: Comm | K8: Suite # | L8: Tenant | M8: Sq Ft | N8: Rent Start Date | O8: Rent Exp. Date | P8: # Years | Q8: Per Sq Ft | R8: T.I. /sq ft | S8: Comm | V8: 45658 | W8: 45689 | X8: 45717 | Y8: 45748 | Z8: 45778 | AA8: 45809 | AB8: 45839 | AC8: 45870 | AD8: 45901 | AE8: 45931 | AF8: 45962 | AG8: 45992 | AH8: 46023 | AI8: 46054 | AJ8: 46082 | AK8: 46113 | AL8: 46143 | AM8: 46174 | AN8: 46204 | AO8: 46235 | AP8: 46266 | AQ8: 46296 | AR8: 46327 | AS8: 46357 | AT8: =AH7&" - Totals" -> 2026 - Totals | CZ8: 45658 | DA8: 45689 | DB8: 45717 | DC8: 45748 | DD8: 45778 | DE8: 45809 | DF8: 45839 | DG8: 45870 | DH8: 45901 | DI8: 45931 | DJ8: 45962 | DK8: 45992 | DL8: 46023 | DM8: 46054 | DN8: 46082 | DO8: 46113 | DP8: 46143 | DQ8: 46174 | DR8: 46204 | DS8: 46235 | DT8: 46266 | DU8: 46296 | DV8: 46327 | DW8: 46357
A9: 102 | B9: =IF(A9<>"","VACANT","") -> VACANT | C9: 3370 | F9: =IFERROR(ROUNDUP(((DATEDIF(D9,E9,"d"))/365),1),0) -> 0 | K9: 101 | L9: Altruistic HCA | M9: 1197 | N9: 46082 | O9: 46446 | P9: =IFERROR(ROUNDUP(((DATEDIF(N9,O9,"d"))/365),1),0) -> 1 | Q9: 18 | R9: 0 | S9: 0 | U9: Projected Occ % | V9: {=_xlfn.LET( _xlpm.months, V8:AG8, _xlpm.totalSqft, A6, _xlpm.vacSF, C9:C23, _xlpm.vacStart, D9:D23, _xlpm.vacEnd, E9:E23, _xlpm.renSF, M9:M23, _xlpm.renEnd, O9:O23, _xlfn.MAP(_xlpm.months, _xlfn.LAMBDA(_xlpm.m, _xlfn.LET( _xlpm.vacLoss, SUM( IF( (ISNUMBER(_xlpm.vacSF)) * ( ISBLANK(_xlpm.vacStart) + (_xlpm.m < _xlpm.vacStart) + (ISNUMBER(_xlpm.vacEnd) * (_xlpm.m > _xlpm.vacEnd)) ), _xlpm.vacSF, 0 ) ), _xlpm.renLoss, SUM( IF( (ISNUMBER(_xlpm.renSF)) * (ISNUMBER(_xlpm.renEnd)) * (_xlpm.m > _xlpm.renEnd), _xlpm.renSF, 0 ) ), ROUND((_xlpm.totalSqft - _xlpm.vacLoss - _xlpm.renLoss) / _xlpm.totalSqft, 4) ) )) )} -> 0.4886 | W9: 0.4886 | X9: 0.4886 | Y9: 0.4886 | Z9: 0.4886 | AA9: 0.4886 | AB9: 0.4886 | AC9: 0.4886 | AD9: 0.4886 | AE9: 0.4886 | AF9: 0.4886 | AG9: 0.4886 | AH9: {=_xlfn.LET( _xlpm.months, AH8:AS8, _xlpm.totalSqft, A6, _xlpm.vacSF, C9:C23, _xlpm.vacStart, D9:D23, _xlpm.vacEnd, E9:E23, _xlpm.renSF, M9:M23, _xlpm.renEnd, O9:O23, _xlfn.MAP(_xlpm.months, _xlfn.LAMBDA(_xlpm.m, _xlfn.LET( _xlpm.vacLoss, SUM( IF( (ISNUMBER(_xlpm.vacSF)) * ( ISBLANK(_xlpm.vacStart) + (_xlpm.m < _xlpm.vacStart) + (ISNUMBER(_xlpm.vacEnd) * (_xlpm.m > _xlpm.vacEnd)) ), _xlpm.vacSF, 0 ) ), _xlpm.renLoss, SUM( IF( (ISNUMBER(_xlpm.renSF)) * (ISNUMBER(_xlpm.renEnd)) * (_xlpm.m > _xlpm.renEnd), _xlpm.renSF, 0 ) ), ROUND((_xlpm.totalSqft - _xlpm.vacLoss - _xlpm.renLoss) / _xlpm.totalSqft, 4) ) )) )} -> 0.5898 | AI9: 0.5898 | AJ9: 0.5898 | AK9: 0.5898 | AL9: 0.5898 | AM9: 0.5898 | AN9: 0.5898 | AO9: 0.5898 | AP9: 0.5898 | AQ9: 0.5898 | AR9: 0.5898 | AS9: 0.5898 | CZ9: =IF(AND($D9<=CZ8,$E9>=CZ8),(($G9*$C9)/12),0) -> 0 | DA9: =IF(AND($D9<=DA8,$E9>=DA8),(($G9*$C9)/12),0) -> 0 | DB9: =IF(AND($D9<=DB8,$E9>=DB8),(($G9*$C9)/12),0) -> 0 | DC9: =IF(AND($D9<=DC8,$E9>=DC8),(($G9*$C9)/12),0) -> 0 | DD9: =IF(AND($D9<=DD8,$E9>=DD8),(($G9*$C9)/12),0) -> 0 | DE9: =IF(AND($D9<=DE8,$E9>=DE8),(($G9*$C9)/12),0) -> 0 | DF9: =IF(AND($D9<=DF8,$E9>=DF8),(($G9*$C9)/12),0) -> 0 | DG9: =IF(AND($D9<=DG8,$E9>=DG8),(($G9*$C9)/12),0) -> 0 | ... DW9: =IF(AND($D9<=DW8,$E9>=DW8),(($G9*$C9)/12),0) -> 0
A10: 109 | B10: =IF(A10<>"","VACANT","") -> VACANT | C10: 1759 | F10: =IFERROR(ROUNDUP(((DATEDIF(D10,E10,"d"))/365),1),0) -> 0 | K10: 104 | L10: All Amer Hospice | M10: 2522 | N10: 46054 | O10: 47149 | P10: =IFERROR(ROUNDUP(((DATEDIF(N10,O10,"d"))/365),1),0) -> 3 | Q10: 20 | R10: 0 | S10: 0.03 | U10: Projected Revenue | V10: {=((SUMPRODUCT(($D$9:$D$23<=V$8) * ($E$9:$E$23>=V$8) * ($G$9:$G$23 * $C$9:$C$23)))+(SUMPRODUCT(($N$9:$N$23<=V$8) * ($O$9:$O$23>=V$8) * ($Q$9:$Q$23 * $M$9:$M$23))))/12} -> 0 | W10: {=((SUMPRODUCT(($D$9:$D$23<=W$8) * ($E$9:$E$23>=W$8) * ($G$9:$G$23 * $C$9:$C$23)))+(SUMPRODUCT(($N$9:$N$23<=W$8) * ($O$9:$O$23>=W$8) * ($Q$9:$Q$23 * $M$9:$M$23))))/12} -> 0 | X10: {=((SUMPRODUCT(($D$9:$D$23<=X$8) * ($E$9:$E$23>=X$8) * ($G$9:$G$23 * $C$9:$C$23)))+(SUMPRODUCT(($N$9:$N$23<=X$8) * ($O$9:$O$23>=X$8) * ($Q$9:$Q$23 * $M$9:$M$23))))/12} -> 0 | Y10: {=((SUMPRODUCT(($D$9:$D$23<=Y$8) * ($E$9:$E$23>=Y$8) * ($G$9:$G$23 * $C$9:$C$23)))+(SUMPRODUCT(($N$9:$N$23<=Y$8) * ($O$9:$O$23>=Y$8) * ($Q$9:$Q$23 * $M$9:$M$23))))/12} -> 0 | Z10: {=((SUMPRODUCT(($D$9:$D$23<=Z$8) * ($E$9:$E$23>=Z$8) * ($G$9:$G$23 * $C$9:$C$23)))+(SUMPRODUCT(($N$9:$N$23<=Z$8) * ($O$9:$O$23>=Z$8) * ($Q$9:$Q$23 * $M$9:$M$23))))/12} -> 0 | AA10: {=((SUMPRODUCT(($D$9:$D$23<=AA$8) * ($E$9:$E$23>=AA$8) * ($G$9:$G$23 * $C$9:$C$23)))+(SUMPRODUCT(($N$9:$N$23<=AA$8) * ($O$9:$O$23>=AA$8) * ($Q$9:$Q$23 * $M$9:$M$23))))/12} -> 0 | AB10: {=((SUMPRODUCT(($D$9:$D$23<=AB$8) * ($E$9:$E$23>=AB$8) * ($G$9:$G$23 * $C$9:$C$23)))+(SUMPRODUCT(($N$9:$N$23<=AB$8) * ($O$9:$O$23>=AB$8) * ($Q$9:$Q$23 * $M$9:$M$23))))/12} -> 0 | AC10: {=((SUMPRODUCT(($D$9:$D$23<=AC$8) * ($E$9:$E$23>=AC$8) * ($G$9:$G$23 * $C$9:$C$23)))+(SUMPRODUCT(($N$9:$N$23<=AC$8) * ($O$9:$O$23>=AC$8) * ($Q$9:$Q$23 * $M$9:$M$23))))/12} -> 0 | ... AS10: {=((SUMPRODUCT(($D$9:$D$23<=AS$8) * ($E$9:$E$23>=AS$8) * ($G$9:$G$23 * $C$9:$C$23)))+(SUMPRODUCT(($N$9:$N$23<=AS$8) * ($O$9:$O$23>=AS$8) * ($Q$9:$Q$23 * $M$9:$M$23))))/12} -> 29871.917 | AT10: =SUM(AH10:AS10) -> 261848 | CZ10: =IF(AND($D10<=CZ$8,$E10>=CZ$8),(($G10*$C10)/12),0) -> 0 | DA10: =IF(AND($D10<=DA$8,$E10>=DA$8),(($G10*$C10)/12),0) -> 0 | DB10: =IF(AND($D10<=DB$8,$E10>=DB$8),(($G10*$C10)/12),0) -> 0 | DC10: =IF(AND($D10<=DC$8,$E10>=DC$8),(($G10*$C10)/12),0) -> 0 | DD10: =IF(AND($D10<=DD$8,$E10>=DD$8),(($G10*$C10)/12),0) -> 0 | DE10: =IF(AND($D10<=DE$8,$E10>=DE$8),(($G10*$C10)/12),0) -> 0 | DF10: =IF(AND($D10<=DF$8,$E10>=DF$8),(($G10*$C10)/12),0) -> 0 | DG10: =IF(AND($D10<=DG$8,$E10>=DG$8),(($G10*$C10)/12),0) -> 0 | ... DW10: =IF(AND($D10<=DW$8,$E10>=DW$8),(($G10*$C10)/12),0) -> 0
A11: 206 | B11: =IF(A11<>"","VACANT","") -> VACANT | C11: 1838 | D11: 46023 | E11: 46752 | F11: =IFERROR(ROUNDUP(((DATEDIF(D11,E11,"d"))/365),1),0) -> 2 | G11: 18.5 | H11: 0 | I11: 0.055 | K11: 105 | L11: Julie Meehan | M11: 1140 | N11: 46296 | O11: 46660 | P11: =IFERROR(ROUNDUP(((DATEDIF(N11,O11,"d"))/365),1),0) -> 1 | Q11: 18 | R11: 0 | S11: 0 | U11: Projected TI | V11: {=(SUMPRODUCT((TEXT($N9:$N23,"yyyymm")=TEXT(V$8,"yyyymm")) * ($R9:$R23 * $M9:$M23)))+(SUMPRODUCT((TEXT($D9:$D23,"yyyymm")=TEXT(V$8,"yyyymm")) * ($H9:$H23 * $C9:$C23)))} -> 0 | W11: {=(SUMPRODUCT((TEXT($N9:$N23,"yyyymm")=TEXT(W$8,"yyyymm")) * ($R9:$R23 * $M9:$M23)))+(SUMPRODUCT((TEXT($D9:$D23,"yyyymm")=TEXT(W$8,"yyyymm")) * ($H9:$H23 * $C9:$C23)))} -> 0 | X11: {=(SUMPRODUCT((TEXT($N9:$N23,"yyyymm")=TEXT(X$8,"yyyymm")) * ($R9:$R23 * $M9:$M23)))+(SUMPRODUCT((TEXT($D9:$D23,"yyyymm")=TEXT(X$8,"yyyymm")) * ($H9:$H23 * $C9:$C23)))} -> 0 | Y11: {=(SUMPRODUCT((TEXT($N9:$N23,"yyyymm")=TEXT(Y$8,"yyyymm")) * ($R9:$R23 * $M9:$M23)))+(SUMPRODUCT((TEXT($D9:$D23,"yyyymm")=TEXT(Y$8,"yyyymm")) * ($H9:$H23 * $C9:$C23)))} -> 0 | Z11: {=(SUMPRODUCT((TEXT($N9:$N23,"yyyymm")=TEXT(Z$8,"yyyymm")) * ($R9:$R23 * $M9:$M23)))+(SUMPRODUCT((TEXT($D9:$D23,"yyyymm")=TEXT(Z$8,"yyyymm")) * ($H9:$H23 * $C9:$C23)))} -> 0 | AA11: {=(SUMPRODUCT((TEXT($N9:$N23,"yyyymm")=TEXT(AA$8,"yyyymm")) * ($R9:$R23 * $M9:$M23)))+(SUMPRODUCT((TEXT($D9:$D23,"yyyymm")=TEXT(AA$8,"yyyymm")) * ($H9:$H23 * $C9:$C23)))} -> 0 | AB11: {=(SUMPRODUCT((TEXT($N9:$N23,"yyyymm")=TEXT(AB$8,"yyyymm")) * ($R9:$R23 * $M9:$M23)))+(SUMPRODUCT((TEXT($D9:$D23,"yyyymm")=TEXT(AB$8,"yyyymm")) * ($H9:$H23 * $C9:$C23)))} -> 0 | AC11: {=(SUMPRODUCT((TEXT($N9:$N23,"yyyymm")=TEXT(AC$8,"yyyymm")) * ($R9:$R23 * $M9:$M23)))+(SUMPRODUCT((TEXT($D9:$D23,"yyyymm")=TEXT(AC$8,"yyyymm")) * ($H9:$H23 * $C9:$C23)))} -> 0 | ... AS11: {=(SUMPRODUCT((TEXT($N9:$N23,"yyyymm")=TEXT(AS$8,"yyyymm")) * ($R9:$R23 * $M9:$M23)))+(SUMPRODUCT((TEXT($D9:$D23,"yyyymm")=TEXT(AS$8,"yyyymm")) * ($H9:$H23 * $C9:$C23)))} -> 0 | AT11: =SUM(AH11:AS11) -> 12582 | CZ11: =IF(AND($D11<=CZ$8,$E11>=CZ$8),(($G11*$C11)/12),0) -> 0 | DA11: =IF(AND($D11<=DA$8,$E11>=DA$8),(($G11*$C11)/12),0) -> 0 | DB11: =IF(AND($D11<=DB$8,$E11>=DB$8),(($G11*$C11)/12),0) -> 0 | DC11: =IF(AND($D11<=DC$8,$E11>=DC$8),(($G11*$C11)/12),0) -> 0 | DD11: =IF(AND($D11<=DD$8,$E11>=DD$8),(($G11*$C11)/12),0) -> 0 | DE11: =IF(AND($D11<=DE$8,$E11>=DE$8),(($G11*$C11)/12),0) -> 0 | DF11: =IF(AND($D11<=DF$8,$E11>=DF$8),(($G11*$C11)/12),0) -> 0 | DG11: =IF(AND($D11<=DG$8,$E11>=DG$8),(($G11*$C11)/12),0) -> 0 | ... DW11: =IF(AND($D11<=DW$8,$E11>=DW$8),(($G11*$C11)/12),0) -> 2833.5833
A12: 207 | B12: =IF(A12<>"","VACANT","") -> VACANT | C12: 6959 | F12: =IFERROR(ROUNDUP(((DATEDIF(D12,E12,"d"))/365),1),0) -> 0 | K12: 106 | L12: Patient Bliss | M12: 1002 | N12: 46327 | O12: 47057 | P12: =IFERROR(ROUNDUP(((DATEDIF(N12,O12,"d"))/365),1),0) -> 2 | Q12: 18 | R12: 3 | S12: 0.03 | U12: Procject LC | V12: {=IFERROR((SUMPRODUCT((TEXT($N9:$N23,"yyyymm")=TEXT(V$8,"yyyymm")) * ($S9:$S23 * $M9:$M23*$Q9:$Q23*$P9:$P23)))+(SUMPRODUCT((TEXT($D9:$D23,"yyyymm")=TEXT(V$8,"yyyymm")) * ($I9:$I23 * $C9:$C23*$G9:$G23*$F9:$F23))),0)} -> 0 | W12: {=IFERROR((SUMPRODUCT((TEXT($N9:$N23,"yyyymm")=TEXT(W$8,"yyyymm")) * ($S9:$S23 * $M9:$M23*$Q9:$Q23*$P9:$P23)))+(SUMPRODUCT((TEXT($D9:$D23,"yyyymm")=TEXT(W$8,"yyyymm")) * ($I9:$I23 * $C9:$C23*$G9:$G23*$F9:$F23))),0)} -> 0 | X12: {=IFERROR((SUMPRODUCT((TEXT($N9:$N23,"yyyymm")=TEXT(X$8,"yyyymm")) * ($S9:$S23 * $M9:$M23*$Q9:$Q23*$P9:$P23)))+(SUMPRODUCT((TEXT($D9:$D23,"yyyymm")=TEXT(X$8,"yyyymm")) * ($I9:$I23 * $C9:$C23*$G9:$G23*$F9:$F23))),0)} -> 0 | Y12: {=IFERROR((SUMPRODUCT((TEXT($N9:$N23,"yyyymm")=TEXT(Y$8,"yyyymm")) * ($S9:$S23 * $M9:$M23*$Q9:$Q23*$P9:$P23)))+(SUMPRODUCT((TEXT($D9:$D23,"yyyymm")=TEXT(Y$8,"yyyymm")) * ($I9:$I23 * $C9:$C23*$G9:$G23*$F9:$F23))),0)} -> 0 | Z12: {=IFERROR((SUMPRODUCT((TEXT($N9:$N23,"yyyymm")=TEXT(Z$8,"yyyymm")) * ($S9:$S23 * $M9:$M23*$Q9:$Q23*$P9:$P23)))+(SUMPRODUCT((TEXT($D9:$D23,"yyyymm")=TEXT(Z$8,"yyyymm")) * ($I9:$I23 * $C9:$C23*$G9:$G23*$F9:$F23))),0)} -> 0 | AA12: {=IFERROR((SUMPRODUCT((TEXT($N9:$N23,"yyyymm")=TEXT(AA$8,"yyyymm")) * ($S9:$S23 * $M9:$M23*$Q9:$Q23*$P9:$P23)))+(SUMPRODUCT((TEXT($D9:$D23,"yyyymm")=TEXT(AA$8,"yyyymm")) * ($I9:$I23 * $C9:$C23*$G9:$G23*$F9:$F23))),0)} -> 0 | AB12: {=IFERROR((SUMPRODUCT((TEXT($N9:$N23,"yyyymm")=TEXT(AB$8,"yyyymm")) * ($S9:$S23 * $M9:$M23*$Q9:$Q23*$P9:$P23)))+(SUMPRODUCT((TEXT($D9:$D23,"yyyymm")=TEXT(AB$8,"yyyymm")) * ($I9:$I23 * $C9:$C23*$G9:$G23*$F9:$F23))),0)} -> 0 | AC12: {=IFERROR((SUMPRODUCT((TEXT($N9:$N23,"yyyymm")=TEXT(AC$8,"yyyymm")) * ($S9:$S23 * $M9:$M23*$Q9:$Q23*$P9:$P23)))+(SUMPRODUCT((TEXT($D9:$D23,"yyyymm")=TEXT(AC$8,"yyyymm")) * ($I9:$I23 * $C9:$C23*$G9:$G23*$F9:$F23))),0)} -> 0 | ... AS12: {=IFERROR((SUMPRODUCT((TEXT($N9:$N23,"yyyymm")=TEXT(AS$8,"yyyymm")) * ($S9:$S23 * $M9:$M23*$Q9:$Q23*$P9:$P23)))+(SUMPRODUCT((TEXT($D9:$D23,"yyyymm")=TEXT(AS$8,"yyyymm")) * ($I9:$I23 * $C9:$C23*$G9:$G23*$F9:$F23))),0)} -> 0 | AT12: =SUM(AH12:AS12) -> 18207.755 | CZ12: =IF(AND($D12<=CZ$8,$E12>=CZ$8),(($G12*$C12)/12),0) -> 0 | DA12: =IF(AND($D12<=DA$8,$E12>=DA$8),(($G12*$C12)/12),0) -> 0 | DB12: =IF(AND($D12<=DB$8,$E12>=DB$8),(($G12*$C12)/12),0) -> 0 | DC12: =IF(AND($D12<=DC$8,$E12>=DC$8),(($G12*$C12)/12),0) -> 0 | DD12: =IF(AND($D12<=DD$8,$E12>=DD$8),(($G12*$C12)/12),0) -> 0 | DE12: =IF(AND($D12<=DE$8,$E12>=DE$8),(($G12*$C12)/12),0) -> 0 | DF12: =IF(AND($D12<=DF$8,$E12>=DF$8),(($G12*$C12)/12),0) -> 0 | DG12: =IF(AND($D12<=DG$8,$E12>=DG$8),(($G12*$C12)/12),0) -> 0 | ... DW12: =IF(AND($D12<=DW$8,$E12>=DW$8),(($G12*$C12)/12),0) -> 0
A13: 301 | B13: =IF(A13<>"","VACANT","") -> VACANT | C13: 2394 | D13: 46023 | E13: 47118 | F13: =IFERROR(ROUNDUP(((DATEDIF(D13,E13,"d"))/365),1),0) -> 3 | G13: 18.5 | H13: 4 | I13: 0.05 | K13: 203 | L13: Apollo Acqu | M13: 1311 | N13: 46204 | O13: 46568 | P13: =IFERROR(ROUNDUP(((DATEDIF(N13,O13,"d"))/365),1),0) -> 1 | Q13: 16.5 | R13: 0 | S13: 0.03 | U13: Total: | V13: =SUM(V10:V12) -> 0 | W13: =SUM(W10:W12) -> 0 | X13: =SUM(X10:X12) -> 0 | Y13: =SUM(Y10:Y12) -> 0 | Z13: =SUM(Z10:Z12) -> 0 | AA13: =SUM(AA10:AA12) -> 0 | AB13: =SUM(AB10:AB12) -> 0 | AC13: =SUM(AC10:AC12) -> 0 | ... AT13: =SUM(AT10:AT12) -> 292637.76 | CZ13: =IF(AND($D13<=CZ$8,$E13>=CZ$8),(($G13*$C13)/12),0) -> 0 | DA13: =IF(AND($D13<=DA$8,$E13>=DA$8),(($G13*$C13)/12),0) -> 0 | DB13: =IF(AND($D13<=DB$8,$E13>=DB$8),(($G13*$C13)/12),0) -> 0 | DC13: =IF(AND($D13<=DC$8,$E13>=DC$8),(($G13*$C13)/12),0) -> 0 | DD13: =IF(AND($D13<=DD$8,$E13>=DD$8),(($G13*$C13)/12),0) -> 0 | DE13: =IF(AND($D13<=DE$8,$E13>=DE$8),(($G13*$C13)/12),0) -> 0 | DF13: =IF(AND($D13<=DF$8,$E13>=DF$8),(($G13*$C13)/12),0) -> 0 | DG13: =IF(AND($D13<=DG$8,$E13>=DG$8),(($G13*$C13)/12),0) -> 0 | ... DW13: =IF(AND($D13<=DW$8,$E13>=DW$8),(($G13*$C13)/12),0) -> 3690.75
A14: 304 | B14: =IF(A14<>"","VACANT","") -> VACANT | C14: 2702 | F14: =IFERROR(ROUNDUP(((DATEDIF(D14,E14,"d"))/365),1),0) -> 0 | K14: 205 | L14: Lincoln Medical | M14: 612 | N14: 46143 | O14: 46873 | P14: =IFERROR(ROUNDUP(((DATEDIF(N14,O14,"d"))/365),1),0) -> 2 | Q14: 20 | R14: 0 | S14: 0 | CZ14: =IF(AND($D14<=CZ$8,$E14>=CZ$8),(($G14*$C14)/12),0) -> 0 | DA14: =IF(AND($D14<=DA$8,$E14>=DA$8),(($G14*$C14)/12),0) -> 0 | DB14: =IF(AND($D14<=DB$8,$E14>=DB$8),(($G14*$C14)/12),0) -> 0 | DC14: =IF(AND($D14<=DC$8,$E14>=DC$8),(($G14*$C14)/12),0) -> 0 | DD14: =IF(AND($D14<=DD$8,$E14>=DD$8),(($G14*$C14)/12),0) -> 0 | DE14: =IF(AND($D14<=DE$8,$E14>=DE$8),(($G14*$C14)/12),0) -> 0 | DF14: =IF(AND($D14<=DF$8,$E14>=DF$8),(($G14*$C14)/12),0) -> 0 | DG14: =IF(AND($D14<=DG$8,$E14>=DG$8),(($G14*$C14)/12),0) -> 0 | ... DW14: =IF(AND($D14<=DW$8,$E14>=DW$8),(($G14*$C14)/12),0) -> 0
A15: 206 | B15: =IF(A15<>"","VACANT","") -> VACANT | C15: 2364 | F15: =IFERROR(ROUNDUP(((DATEDIF(D15,E15,"d"))/365),1),0) -> 0 | K15: 209 | L15: West Comm | M15: 600 | N15: 46143 | O15: 46873 | P15: =IFERROR(ROUNDUP(((DATEDIF(N15,O15,"d"))/365),1),0) -> 2 | Q15: 20.5 | R15: 0 | S15: 0 | U15: TI = Sq Ft * T.I /sq ft all paid up front. | CZ15: =IF(AND($D15<=CZ$8,$E15>=CZ$8),(($G15*$C15)/12),0) -> 0 | DA15: =IF(AND($D15<=DA$8,$E15>=DA$8),(($G15*$C15)/12),0) -> 0 | DB15: =IF(AND($D15<=DB$8,$E15>=DB$8),(($G15*$C15)/12),0) -> 0 | DC15: =IF(AND($D15<=DC$8,$E15>=DC$8),(($G15*$C15)/12),0) -> 0 | DD15: =IF(AND($D15<=DD$8,$E15>=DD$8),(($G15*$C15)/12),0) -> 0 | DE15: =IF(AND($D15<=DE$8,$E15>=DE$8),(($G15*$C15)/12),0) -> 0 | DF15: =IF(AND($D15<=DF$8,$E15>=DF$8),(($G15*$C15)/12),0) -> 0 | DG15: =IF(AND($D15<=DG$8,$E15>=DG$8),(($G15*$C15)/12),0) -> 0 | ... DW15: =IF(AND($D15<=DW$8,$E15>=DW$8),(($G15*$C15)/12),0) -> 0
B16: =IF(A16<>"","VACANT","") | F16: =IFERROR(ROUNDUP(((DATEDIF(D16,E16,"d"))/365),1),0) -> 0 | K16: 300 | L16: EELP Inc | M16: 2960 | N16: 46174 | O16: 46538 | P16: =IFERROR(ROUNDUP(((DATEDIF(N16,O16,"d"))/365),1),0) -> 1 | Q16: 17.5 | R16: 0 | S16: 0 | U16: LC = Sq Ft * # Years * Per Sq Ft * Comm all paid up front. | CZ16: =IF(AND($D16<=CZ$8,$E16>=CZ$8),(($G16*$C16)/12),0) -> 0 | DA16: =IF(AND($D16<=DA$8,$E16>=DA$8),(($G16*$C16)/12),0) -> 0 | DB16: =IF(AND($D16<=DB$8,$E16>=DB$8),(($G16*$C16)/12),0) -> 0 | DC16: =IF(AND($D16<=DC$8,$E16>=DC$8),(($G16*$C16)/12),0) -> 0 | DD16: =IF(AND($D16<=DD$8,$E16>=DD$8),(($G16*$C16)/12),0) -> 0 | DE16: =IF(AND($D16<=DE$8,$E16>=DE$8),(($G16*$C16)/12),0) -> 0 | DF16: =IF(AND($D16<=DF$8,$E16>=DF$8),(($G16*$C16)/12),0) -> 0 | DG16: =IF(AND($D16<=DG$8,$E16>=DG$8),(($G16*$C16)/12),0) -> 0 | ... DW16: =IF(AND($D16<=DW$8,$E16>=DW$8),(($G16*$C16)/12),0) -> 0
B17: =IF(A17<>"","VACANT","") | F17: =IFERROR(ROUNDUP(((DATEDIF(D17,E17,"d"))/365),1),0) -> 0 | K17: 302 | L17: Traffic Tech | M17: 834 | N17: 46235 | O17: 46599 | P17: =IFERROR(ROUNDUP(((DATEDIF(N17,O17,"d"))/365),1),0) -> 1 | Q17: 18 | R17: 0 | S17: 0.06 | CZ17: =IF(AND($D17<=CZ$8,$E17>=CZ$8),(($G17*$C17)/12),0) -> 0 | DA17: =IF(AND($D17<=DA$8,$E17>=DA$8),(($G17*$C17)/12),0) -> 0 | DB17: =IF(AND($D17<=DB$8,$E17>=DB$8),(($G17*$C17)/12),0) -> 0 | DC17: =IF(AND($D17<=DC$8,$E17>=DC$8),(($G17*$C17)/12),0) -> 0 | DD17: =IF(AND($D17<=DD$8,$E17>=DD$8),(($G17*$C17)/12),0) -> 0 | DE17: =IF(AND($D17<=DE$8,$E17>=DE$8),(($G17*$C17)/12),0) -> 0 | DF17: =IF(AND($D17<=DF$8,$E17>=DF$8),(($G17*$C17)/12),0) -> 0 | DG17: =IF(AND($D17<=DG$8,$E17>=DG$8),(($G17*$C17)/12),0) -> 0 | ... DW17: =IF(AND($D17<=DW$8,$E17>=DW$8),(($G17*$C17)/12),0) -> 0
B18: =IF(A18<>"","VACANT","") | F18: =IFERROR(ROUNDUP(((DATEDIF(D18,E18,"d"))/365),1),0) -> 0 | K18: 305 | L18: Horizon House | M18: 1145 | N18: 46174 | O18: 46538 | P18: =IFERROR(ROUNDUP(((DATEDIF(N18,O18,"d"))/365),1),0) -> 1 | Q18: 19 | R18: 0 | S18: 0.03 | CZ18: =IF(AND($D18<=CZ$8,$E18>=CZ$8),(($G18*$C18)/12),0) -> 0 | DA18: =IF(AND($D18<=DA$8,$E18>=DA$8),(($G18*$C18)/12),0) -> 0 | DB18: =IF(AND($D18<=DB$8,$E18>=DB$8),(($G18*$C18)/12),0) -> 0 | DC18: =IF(AND($D18<=DC$8,$E18>=DC$8),(($G18*$C18)/12),0) -> 0 | DD18: =IF(AND($D18<=DD$8,$E18>=DD$8),(($G18*$C18)/12),0) -> 0 | DE18: =IF(AND($D18<=DE$8,$E18>=DE$8),(($G18*$C18)/12),0) -> 0 | DF18: =IF(AND($D18<=DF$8,$E18>=DF$8),(($G18*$C18)/12),0) -> 0 | DG18: =IF(AND($D18<=DG$8,$E18>=DG$8),(($G18*$C18)/12),0) -> 0 | ... DW18: =IF(AND($D18<=DW$8,$E18>=DW$8),(($G18*$C18)/12),0) -> 0
B19: =IF(A19<>"","VACANT","") | F19: =IFERROR(ROUNDUP(((DATEDIF(D19,E19,"d"))/365),1),0) -> 0 | K19: 310 | L19: AM Res | M19: 2251 | N19: 45992 | O19: 46721 | P19: =IFERROR(ROUNDUP(((DATEDIF(N19,O19,"d"))/365),1),0) -> 2 | Q19: 15.5 | R19: 0 | S19: 0 | CZ19: =IF(AND($D19<=CZ$8,$E19>=CZ$8),(($G19*$C19)/12),0) -> 0 | DA19: =IF(AND($D19<=DA$8,$E19>=DA$8),(($G19*$C19)/12),0) -> 0 | DB19: =IF(AND($D19<=DB$8,$E19>=DB$8),(($G19*$C19)/12),0) -> 0 | DC19: =IF(AND($D19<=DC$8,$E19>=DC$8),(($G19*$C19)/12),0) -> 0 | DD19: =IF(AND($D19<=DD$8,$E19>=DD$8),(($G19*$C19)/12),0) -> 0 | DE19: =IF(AND($D19<=DE$8,$E19>=DE$8),(($G19*$C19)/12),0) -> 0 | DF19: =IF(AND($D19<=DF$8,$E19>=DF$8),(($G19*$C19)/12),0) -> 0 | DG19: =IF(AND($D19<=DG$8,$E19>=DG$8),(($G19*$C19)/12),0) -> 0 | ... DW19: =IF(AND($D19<=DW$8,$E19>=DW$8),(($G19*$C19)/12),0) -> 0
B20: =IF(A20<>"","VACANT","") | F20: =IFERROR(ROUNDUP(((DATEDIF(D20,E20,"d"))/365),1),0) -> 0 | P20: =IFERROR(ROUNDUP(((DATEDIF(N20,O20,"d"))/365),1),0) -> 0 | CZ20: =IF(AND($D20<=CZ$8,$E20>=CZ$8),(($G20*$C20)/12),0) -> 0 | DA20: =IF(AND($D20<=DA$8,$E20>=DA$8),(($G20*$C20)/12),0) -> 0 | DB20: =IF(AND($D20<=DB$8,$E20>=DB$8),(($G20*$C20)/12),0) -> 0 | DC20: =IF(AND($D20<=DC$8,$E20>=DC$8),(($G20*$C20)/12),0) -> 0 | DD20: =IF(AND($D20<=DD$8,$E20>=DD$8),(($G20*$C20)/12),0) -> 0 | DE20: =IF(AND($D20<=DE$8,$E20>=DE$8),(($G20*$C20)/12),0) -> 0 | DF20: =IF(AND($D20<=DF$8,$E20>=DF$8),(($G20*$C20)/12),0) -> 0 | DG20: =IF(AND($D20<=DG$8,$E20>=DG$8),(($G20*$C20)/12),0) -> 0 | ... DW20: =IF(AND($D20<=DW$8,$E20>=DW$8),(($G20*$C20)/12),0) -> 0
B21: =IF(A21<>"","VACANT","") | F21: =IFERROR(ROUNDUP(((DATEDIF(D21,E21,"d"))/365),1),0) -> 0 | P21: =IFERROR(ROUNDUP(((DATEDIF(N21,O21,"d"))/365),1),0) -> 0 | CZ21: =IF(AND($D21<=CZ$8,$E21>=CZ$8),(($G21*$C21)/12),0) -> 0 | DA21: =IF(AND($D21<=DA$8,$E21>=DA$8),(($G21*$C21)/12),0) -> 0 | DB21: =IF(AND($D21<=DB$8,$E21>=DB$8),(($G21*$C21)/12),0) -> 0 | DC21: =IF(AND($D21<=DC$8,$E21>=DC$8),(($G21*$C21)/12),0) -> 0 | DD21: =IF(AND($D21<=DD$8,$E21>=DD$8),(($G21*$C21)/12),0) -> 0 | DE21: =IF(AND($D21<=DE$8,$E21>=DE$8),(($G21*$C21)/12),0) -> 0 | DF21: =IF(AND($D21<=DF$8,$E21>=DF$8),(($G21*$C21)/12),0) -> 0 | DG21: =IF(AND($D21<=DG$8,$E21>=DG$8),(($G21*$C21)/12),0) -> 0 | ... DW21: =IF(AND($D21<=DW$8,$E21>=DW$8),(($G21*$C21)/12),0) -> 0
B22: =IF(A22<>"","VACANT","") | F22: =IFERROR(ROUNDUP(((DATEDIF(D22,E22,"d"))/365),1),0) -> 0 | P22: =IFERROR(ROUNDUP(((DATEDIF(N22,O22,"d"))/365),1),0) -> 0 | CZ22: =IF(AND($D22<=CZ$8,$E22>=CZ$8),(($G22*$C22)/12),0) -> 0 | DA22: =IF(AND($D22<=DA$8,$E22>=DA$8),(($G22*$C22)/12),0) -> 0 | DB22: =IF(AND($D22<=DB$8,$E22>=DB$8),(($G22*$C22)/12),0) -> 0 | DC22: =IF(AND($D22<=DC$8,$E22>=DC$8),(($G22*$C22)/12),0) -> 0 | DD22: =IF(AND($D22<=DD$8,$E22>=DD$8),(($G22*$C22)/12),0) -> 0 | DE22: =IF(AND($D22<=DE$8,$E22>=DE$8),(($G22*$C22)/12),0) -> 0 | DF22: =IF(AND($D22<=DF$8,$E22>=DF$8),(($G22*$C22)/12),0) -> 0 | DG22: =IF(AND($D22<=DG$8,$E22>=DG$8),(($G22*$C22)/12),0) -> 0 | ... DW22: =IF(AND($D22<=DW$8,$E22>=DW$8),(($G22*$C22)/12),0) -> 0
B23: =IF(A23<>"","VACANT","") | F23: =IFERROR(ROUNDUP(((DATEDIF(D23,E23,"d"))/365),1),0) -> 0 | P23: =IFERROR(ROUNDUP(((DATEDIF(N23,O23,"d"))/365),1),0) -> 0 | CZ23: =IF(AND($D23<=CZ$8,$E23>=CZ$8),(($G23*$C23)/12),0) -> 0 | DA23: =IF(AND($D23<=DA$8,$E23>=DA$8),(($G23*$C23)/12),0) -> 0 | DB23: =IF(AND($D23<=DB$8,$E23>=DB$8),(($G23*$C23)/12),0) -> 0 | DC23: =IF(AND($D23<=DC$8,$E23>=DC$8),(($G23*$C23)/12),0) -> 0 | DD23: =IF(AND($D23<=DD$8,$E23>=DD$8),(($G23*$C23)/12),0) -> 0 | DE23: =IF(AND($D23<=DE$8,$E23>=DE$8),(($G23*$C23)/12),0) -> 0 | DF23: =IF(AND($D23<=DF$8,$E23>=DF$8),(($G23*$C23)/12),0) -> 0 | DG23: =IF(AND($D23<=DG$8,$E23>=DG$8),(($G23*$C23)/12),0) -> 0 | ... DW23: =IF(AND($D23<=DW$8,$E23>=DW$8),(($G23*$C23)/12),0) -> 0
B24: Total Vacant: | C24: =SUM(C9:C23) -> 21386 | L24: Total Renewals: | M24: =SUM(M9:M23) -> 15574 | CZ24: =SUM(CZ9:CZ23) -> 0 | DA24: =SUM(DA9:DA23) -> 0 | DB24: =SUM(DB9:DB23) -> 0 | DC24: =SUM(DC9:DC23) -> 0 | DD24: =SUM(DD9:DD23) -> 0 | DE24: =SUM(DE9:DE23) -> 0 | DF24: =SUM(DF9:DF23) -> 0 | DG24: =SUM(DG9:DG23) -> 0 | ... DW24: =SUM(DW9:DW23) -> 6524.3333
CZ26: =CZ$8 -> 45658 | DA26: =DA$8 -> 45689 | DB26: =DB$8 -> 45717 | DC26: =DC$8 -> 45748 | DD26: =DD$8 -> 45778 | DE26: =DE$8 -> 45809 | DF26: =DF$8 -> 45839 | DG26: =DG$8 -> 45870 | ... DW26: =DW$8 -> 46357
A27: 3620 | CZ27: =IF(AND($N9<=CZ26,$O9>=CZ26),(($Q9*$M9)/12),0) -> 0 | DA27: =IF(AND($N9<=DA26,$O9>=DA26),(($Q9*$M9)/12),0) -> 0 | DB27: =IF(AND($N9<=DB26,$O9>=DB26),(($Q9*$M9)/12),0) -> 0 | DC27: =IF(AND($N9<=DC26,$O9>=DC26),(($Q9*$M9)/12),0) -> 0 | DD27: =IF(AND($N9<=DD26,$O9>=DD26),(($Q9*$M9)/12),0) -> 0 | DE27: =IF(AND($N9<=DE26,$O9>=DE26),(($Q9*$M9)/12),0) -> 0 | DF27: =IF(AND($N9<=DF26,$O9>=DF26),(($Q9*$M9)/12),0) -> 0 | DG27: =IF(AND($N9<=DG26,$O9>=DG26),(($Q9*$M9)/12),0) -> 0 | ... DW27: =IF(AND($N9<=DW26,$O9>=DW26),(($Q9*$M9)/12),0) -> 1795.5
A28: 49020 | B28: =(A28-C46)/A28 -> 0.42662179 | D28: ="Vacancies - "&A27 -> Vacancies - 3620 | N28: ="Renewals - "&A27 -> Renewals - 3620 | CZ28: =IF(AND($N10<=CZ$8,$O10>=CZ$8),(($Q10*$M10)/12),0) -> 0 | DA28: =IF(AND($N10<=DA$8,$O10>=DA$8),(($Q10*$M10)/12),0) -> 0 | DB28: =IF(AND($N10<=DB$8,$O10>=DB$8),(($Q10*$M10)/12),0) -> 0 | DC28: =IF(AND($N10<=DC$8,$O10>=DC$8),(($Q10*$M10)/12),0) -> 0 | DD28: =IF(AND($N10<=DD$8,$O10>=DD$8),(($Q10*$M10)/12),0) -> 0 | DE28: =IF(AND($N10<=DE$8,$O10>=DE$8),(($Q10*$M10)/12),0) -> 0 | DF28: =IF(AND($N10<=DF$8,$O10>=DF$8),(($Q10*$M10)/12),0) -> 0 | DG28: =IF(AND($N10<=DG$8,$O10>=DG$8),(($Q10*$M10)/12),0) -> 0 | ... DW28: =IF(AND($N10<=DW$8,$O10>=DW$8),(($Q10*$M10)/12),0) -> 4203.3333
D29: Leasing Department Assumptions | N29: Leasing Department Assumptions | U29: =A27 -> 3620 | V29: 2025 | AH29: =V29+1 -> 2026 | CZ29: =IF(AND($N11<=CZ$8,$O11>=CZ$8),(($Q11*$M11)/12),0) -> 0 | DA29: =IF(AND($N11<=DA$8,$O11>=DA$8),(($Q11*$M11)/12),0) -> 0 | DB29: =IF(AND($N11<=DB$8,$O11>=DB$8),(($Q11*$M11)/12),0) -> 0 | DC29: =IF(AND($N11<=DC$8,$O11>=DC$8),(($Q11*$M11)/12),0) -> 0 | DD29: =IF(AND($N11<=DD$8,$O11>=DD$8),(($Q11*$M11)/12),0) -> 0 | DE29: =IF(AND($N11<=DE$8,$O11>=DE$8),(($Q11*$M11)/12),0) -> 0 | DF29: =IF(AND($N11<=DF$8,$O11>=DF$8),(($Q11*$M11)/12),0) -> 0 | DG29: =IF(AND($N11<=DG$8,$O11>=DG$8),(($Q11*$M11)/12),0) -> 0 | ... DW29: =IF(AND($N11<=DW$8,$O11>=DW$8),(($Q11*$M11)/12),0) -> 1710
A30: Suite # | B30: Tenant | C30: Sq Ft | D30: Rent Start Date | E30: Rent Exp. Date | F30: # Years | G30: Per Sq Ft | H30: T.I. /sq ft | I30: Comm | K30: Suite # | L30: Tenant | M30: Sq Ft | N30: Rent Start Date | O30: Rent Exp. Date | P30: # Years | Q30: Per Sq Ft | R30: T.I. /sq ft | S30: Comm | V30: 45658 | W30: 45689 | X30: 45717 | Y30: 45748 | Z30: 45778 | AA30: 45809 | AB30: 45839 | AC30: 45870 | AD30: 45901 | AE30: 45931 | AF30: 45962 | AG30: 45992 | AH30: =AH$8 -> 46023 | AI30: =AI$8 -> 46054 | AJ30: =AJ$8 -> 46082 | AK30: =AK$8 -> 46113 | AL30: =AL$8 -> 46143 | AM30: =AM$8 -> 46174 | AN30: =AN$8 -> 46204 | AO30: =AO$8 -> 46235 | ... AS30: =AS$8 -> 46357 | AT30: =AH29&" - Totals" -> 2026 - Totals | CZ30: =IF(AND($N12<=CZ$8,$O12>=CZ$8),(($Q12*$M12)/12),0) -> 0 | DA30: =IF(AND($N12<=DA$8,$O12>=DA$8),(($Q12*$M12)/12),0) -> 0 | DB30: =IF(AND($N12<=DB$8,$O12>=DB$8),(($Q12*$M12)/12),0) -> 0 | DC30: =IF(AND($N12<=DC$8,$O12>=DC$8),(($Q12*$M12)/12),0) -> 0 | DD30: =IF(AND($N12<=DD$8,$O12>=DD$8),(($Q12*$M12)/12),0) -> 0 | DE30: =IF(AND($N12<=DE$8,$O12>=DE$8),(($Q12*$M12)/12),0) -> 0 | DF30: =IF(AND($N12<=DF$8,$O12>=DF$8),(($Q12*$M12)/12),0) -> 0 | DG30: =IF(AND($N12<=DG$8,$O12>=DG$8),(($Q12*$M12)/12),0) -> 0 | ... DW30: =IF(AND($N12<=DW$8,$O12>=DW$8),(($Q12*$M12)/12),0) -> 1503
A31: 201 | B31: =IF(A31<>"","VACANT","") -> VACANT | C31: 7474 | F31: =IFERROR(ROUNDUP(((DATEDIF(D31,E31,"d"))/365),1),0) -> 0 | K31: 102 | L31: Home Solutions | M31: 1197 | N31: 46174 | O31: 46538 | P31: =IFERROR(ROUNDUP(((DATEDIF(N31,O31,"d"))/365),1),0) -> 1 | Q31: 18.5 | R31: 0 | S31: 0 | U31: Projected Occ % | V31: {=_xlfn.LET( _xlpm.months, V30:AG30, _xlpm.totalSqft, A28, _xlpm.vacSF, C31:C45, _xlpm.vacStart, D31:D45, _xlpm.vacEnd, E31:E45, _xlpm.renSF, M31:M45, _xlpm.renEnd, O31:O45, _xlfn.MAP(_xlpm.months, _xlfn.LAMBDA(_xlpm.m, _xlfn.LET( _xlpm.vacLoss, SUM( IF( (ISNUMBER(_xlpm.vacSF)) * ( ISBLANK(_xlpm.vacStart) + (_xlpm.m < _xlpm.vacStart) + (ISNUMBER(_xlpm.vacEnd) * (_xlpm.m > _xlpm.vacEnd)) ), _xlpm.vacSF, 0 ) ), _xlpm.renLoss, SUM( IF( (ISNUMBER(_xlpm.renSF)) * (ISNUMBER(_xlpm.renEnd)) * (_xlpm.m > _xlpm.renEnd), _xlpm.renSF, 0 ) ), ROUND((_xlpm.totalSqft - _xlpm.vacLoss - _xlpm.renLoss) / _xlpm.totalSqft, 4) ) )) )} -> 0.4266 | W31: 0.4266 | X31: 0.4266 | Y31: 0.4266 | Z31: 0.4266 | AA31: 0.4266 | AB31: 0.4266 | AC31: 0.4266 | AD31: 0.4266 | AE31: 0.4266 | AF31: 0.4266 | AG31: 0.4266 | AH31: {=_xlfn.LET( _xlpm.months, AH30:AS30, _xlpm.totalSqft, A28, _xlpm.vacSF, C31:C45, _xlpm.vacStart, D31:D45, _xlpm.vacEnd, E31:E45, _xlpm.renSF, M31:M45, _xlpm.renEnd, O31:O45, _xlfn.MAP(_xlpm.months, _xlfn.LAMBDA(_xlpm.m, _xlfn.LET( _xlpm.vacLoss, SUM( IF( (ISNUMBER(_xlpm.vacSF)) * ( ISBLANK(_xlpm.vacStart) + (_xlpm.m < _xlpm.vacStart) + (ISNUMBER(_xlpm.vacEnd) * (_xlpm.m > _xlpm.vacEnd)) ), _xlpm.vacSF, 0 ) ), _xlpm.renLoss, SUM( IF( (ISNUMBER(_xlpm.renSF)) * (ISNUMBER(_xlpm.renEnd)) * (_xlpm.m > _xlpm.renEnd), _xlpm.renSF, 0 ) ), ROUND((_xlpm.totalSqft - _xlpm.vacLoss - _xlpm.renLoss) / _xlpm.totalSqft, 4) ) )) )} -> 0.4266 | AI31: 0.4266 | AJ31: 0.4266 | AK31: 0.4266 | AL31: 0.4266 | AM31: 0.4266 | AN31: 0.4266 | AO31: 0.4266 | AP31: 0.4266 | AQ31: 0.4266 | AR31: 0.4266 | AS31: 0.4092 | CZ31: =IF(AND($N13<=CZ$8,$O13>=CZ$8),(($Q13*$M13)/12),0) -> 0 | DA31: =IF(AND($N13<=DA$8,$O13>=DA$8),(($Q13*$M13)/12),0) -> 0 | DB31: =IF(AND($N13<=DB$8,$O13>=DB$8),(($Q13*$M13)/12),0) -> 0 | DC31: =IF(AND($N13<=DC$8,$O13>=DC$8),(($Q13*$M13)/12),0) -> 0 | DD31: =IF(AND($N13<=DD$8,$O13>=DD$8),(($Q13*$M13)/12),0) -> 0 | DE31: =IF(AND($N13<=DE$8,$O13>=DE$8),(($Q13*$M13)/12),0) -> 0 | DF31: =IF(AND($N13<=DF$8,$O13>=DF$8),(($Q13*$M13)/12),0) -> 0 | DG31: =IF(AND($N13<=DG$8,$O13>=DG$8),(($Q13*$M13)/12),0) -> 0 | ... DW31: =IF(AND($N13<=DW$8,$O13>=DW$8),(($Q13*$M13)/12),0) -> 1802.625
A32: 203 | B32: =IF(A32<>"","VACANT","") -> VACANT | C32: 2100 | F32: =IFERROR(ROUNDUP(((DATEDIF(D32,E32,"d"))/365),1),0) -> 0 | K32: 108 | L32: J.D. Morrissey | M32: 980 | N32: 46143 | O32: 46387 | P32: =IFERROR(ROUNDUP(((DATEDIF(N32,O32,"d"))/365),1),0) -> 0.7 | Q32: 18.5 | R32: 0 | S32: 0 | U32: Projected Revenue | V32: {=((SUMPRODUCT(($D$31:$D$45<=V$8) * ($E$31:$E$45>=V$8) * ($G$31:$G$45 * $C$31:$C$45)))+(SUMPRODUCT(($N$31:$N$45<=V$8) * ($O$31:$O$45>=V$8) * ($Q$31:$Q$45 * $M$31:$M$45))))/12} -> 0 | W32: {=((SUMPRODUCT(($D$31:$D$45<=W$8) * ($E$31:$E$45>=W$8) * ($G$31:$G$45 * $C$31:$C$45)))+(SUMPRODUCT(($N$31:$N$45<=W$8) * ($O$31:$O$45>=W$8) * ($Q$31:$Q$45 * $M$31:$M$45))))/12} -> 0 | X32: {=((SUMPRODUCT(($D$31:$D$45<=X$8) * ($E$31:$E$45>=X$8) * ($G$31:$G$45 * $C$31:$C$45)))+(SUMPRODUCT(($N$31:$N$45<=X$8) * ($O$31:$O$45>=X$8) * ($Q$31:$Q$45 * $M$31:$M$45))))/12} -> 0 | Y32: {=((SUMPRODUCT(($D$31:$D$45<=Y$8) * ($E$31:$E$45>=Y$8) * ($G$31:$G$45 * $C$31:$C$45)))+(SUMPRODUCT(($N$31:$N$45<=Y$8) * ($O$31:$O$45>=Y$8) * ($Q$31:$Q$45 * $M$31:$M$45))))/12} -> 0 | Z32: {=((SUMPRODUCT(($D$31:$D$45<=Z$8) * ($E$31:$E$45>=Z$8) * ($G$31:$G$45 * $C$31:$C$45)))+(SUMPRODUCT(($N$31:$N$45<=Z$8) * ($O$31:$O$45>=Z$8) * ($Q$31:$Q$45 * $M$31:$M$45))))/12} -> 0 | AA32: {=((SUMPRODUCT(($D$31:$D$45<=AA$8) * ($E$31:$E$45>=AA$8) * ($G$31:$G$45 * $C$31:$C$45)))+(SUMPRODUCT(($N$31:$N$45<=AA$8) * ($O$31:$O$45>=AA$8) * ($Q$31:$Q$45 * $M$31:$M$45))))/12} -> 0 | AB32: {=((SUMPRODUCT(($D$31:$D$45<=AB$8) * ($E$31:$E$45>=AB$8) * ($G$31:$G$45 * $C$31:$C$45)))+(SUMPRODUCT(($N$31:$N$45<=AB$8) * ($O$31:$O$45>=AB$8) * ($Q$31:$Q$45 * $M$31:$M$45))))/12} -> 0 | AC32: {=((SUMPRODUCT(($D$31:$D$45<=AC$8) * ($E$31:$E$45>=AC$8) * ($G$31:$G$45 * $C$31:$C$45)))+(SUMPRODUCT(($N$31:$N$45<=AC$8) * ($O$31:$O$45>=AC$8) * ($Q$31:$Q$45 * $M$31:$M$45))))/12} -> 0 | ... AS32: {=((SUMPRODUCT(($D$31:$D$45<=AS$8) * ($E$31:$E$45>=AS$8) * ($G$31:$G$45 * $C$31:$C$45)))+(SUMPRODUCT(($N$31:$N$45<=AS$8) * ($O$31:$O$45>=AS$8) * ($Q$31:$Q$45 * $M$31:$M$45))))/12} -> 9025.7917 | AT32: =SUM(AH32:AS32) -> 96034.167 | CZ32: =IF(AND($N14<=CZ$8,$O14>=CZ$8),(($Q14*$M14)/12),0) -> 0 | DA32: =IF(AND($N14<=DA$8,$O14>=DA$8),(($Q14*$M14)/12),0) -> 0 | DB32: =IF(AND($N14<=DB$8,$O14>=DB$8),(($Q14*$M14)/12),0) -> 0 | DC32: =IF(AND($N14<=DC$8,$O14>=DC$8),(($Q14*$M14)/12),0) -> 0 | DD32: =IF(AND($N14<=DD$8,$O14>=DD$8),(($Q14*$M14)/12),0) -> 0 | DE32: =IF(AND($N14<=DE$8,$O14>=DE$8),(($Q14*$M14)/12),0) -> 0 | DF32: =IF(AND($N14<=DF$8,$O14>=DF$8),(($Q14*$M14)/12),0) -> 0 | DG32: =IF(AND($N14<=DG$8,$O14>=DG$8),(($Q14*$M14)/12),0) -> 0 | ... DW32: =IF(AND($N14<=DW$8,$O14>=DW$8),(($Q14*$M14)/12),0) -> 1020
A33: 204 | B33: =IF(A33<>"","VACANT","") -> VACANT | C33: 2761 | F33: =IFERROR(ROUNDUP(((DATEDIF(D33,E33,"d"))/365),1),0) -> 0 | K33: 205 | L33: Mason East | M33: 855 | N33: 45992 | O33: 46356 | P33: =IFERROR(ROUNDUP(((DATEDIF(N33,O33,"d"))/365),1),0) -> 1 | Q33: 19.5 | R33: 0 | S33: 0 | U33: Projected TI | V33: {=(SUMPRODUCT((TEXT($N31:$N45,"yyyymm")=TEXT(V$30,"yyyymm")) * ($R31:$R45 * $M31:$M45)))+(SUMPRODUCT((TEXT($D31:$D45,"yyyymm")=TEXT(V$30,"yyyymm")) * ($H31:$H45 * $C31:$C45)))} -> 0 | W33: {=(SUMPRODUCT((TEXT($N31:$N45,"yyyymm")=TEXT(W$30,"yyyymm")) * ($R31:$R45 * $M31:$M45)))+(SUMPRODUCT((TEXT($D31:$D45,"yyyymm")=TEXT(W$30,"yyyymm")) * ($H31:$H45 * $C31:$C45)))} -> 0 | X33: {=(SUMPRODUCT((TEXT($N31:$N45,"yyyymm")=TEXT(X$30,"yyyymm")) * ($R31:$R45 * $M31:$M45)))+(SUMPRODUCT((TEXT($D31:$D45,"yyyymm")=TEXT(X$30,"yyyymm")) * ($H31:$H45 * $C31:$C45)))} -> 0 | Y33: {=(SUMPRODUCT((TEXT($N31:$N45,"yyyymm")=TEXT(Y$30,"yyyymm")) * ($R31:$R45 * $M31:$M45)))+(SUMPRODUCT((TEXT($D31:$D45,"yyyymm")=TEXT(Y$30,"yyyymm")) * ($H31:$H45 * $C31:$C45)))} -> 0 | Z33: {=(SUMPRODUCT((TEXT($N31:$N45,"yyyymm")=TEXT(Z$30,"yyyymm")) * ($R31:$R45 * $M31:$M45)))+(SUMPRODUCT((TEXT($D31:$D45,"yyyymm")=TEXT(Z$30,"yyyymm")) * ($H31:$H45 * $C31:$C45)))} -> 0 | AA33: {=(SUMPRODUCT((TEXT($N31:$N45,"yyyymm")=TEXT(AA$30,"yyyymm")) * ($R31:$R45 * $M31:$M45)))+(SUMPRODUCT((TEXT($D31:$D45,"yyyymm")=TEXT(AA$30,"yyyymm")) * ($H31:$H45 * $C31:$C45)))} -> 0 | AB33: {=(SUMPRODUCT((TEXT($N31:$N45,"yyyymm")=TEXT(AB$30,"yyyymm")) * ($R31:$R45 * $M31:$M45)))+(SUMPRODUCT((TEXT($D31:$D45,"yyyymm")=TEXT(AB$30,"yyyymm")) * ($H31:$H45 * $C31:$C45)))} -> 0 | AC33: {=(SUMPRODUCT((TEXT($N31:$N45,"yyyymm")=TEXT(AC$30,"yyyymm")) * ($R31:$R45 * $M31:$M45)))+(SUMPRODUCT((TEXT($D31:$D45,"yyyymm")=TEXT(AC$30,"yyyymm")) * ($H31:$H45 * $C31:$C45)))} -> 0 | ... AS33: {=(SUMPRODUCT((TEXT($N31:$N45,"yyyymm")=TEXT(AS$30,"yyyymm")) * ($R31:$R45 * $M31:$M45)))+(SUMPRODUCT((TEXT($D31:$D45,"yyyymm")=TEXT(AS$30,"yyyymm")) * ($H31:$H45 * $C31:$C45)))} -> 0 | AT33: =SUM(AH33:AS33) -> 0 | CZ33: =IF(AND($N15<=CZ$8,$O15>=CZ$8),(($Q15*$M15)/12),0) -> 0 | DA33: =IF(AND($N15<=DA$8,$O15>=DA$8),(($Q15*$M15)/12),0) -> 0 | DB33: =IF(AND($N15<=DB$8,$O15>=DB$8),(($Q15*$M15)/12),0) -> 0 | DC33: =IF(AND($N15<=DC$8,$O15>=DC$8),(($Q15*$M15)/12),0) -> 0 | DD33: =IF(AND($N15<=DD$8,$O15>=DD$8),(($Q15*$M15)/12),0) -> 0 | DE33: =IF(AND($N15<=DE$8,$O15>=DE$8),(($Q15*$M15)/12),0) -> 0 | DF33: =IF(AND($N15<=DF$8,$O15>=DF$8),(($Q15*$M15)/12),0) -> 0 | DG33: =IF(AND($N15<=DG$8,$O15>=DG$8),(($Q15*$M15)/12),0) -> 0 | ... DW33: =IF(AND($N15<=DW$8,$O15>=DW$8),(($Q15*$M15)/12),0) -> 1025
A34: 301 | B34: =IF(A34<>"","VACANT","") -> VACANT | C34: 5671 | F34: =IFERROR(ROUNDUP(((DATEDIF(D34,E34,"d"))/365),1),0) -> 0 | K34: 208 | L34: JD Eckman | M34: 2587 | N34: 46113 | O34: 46387 | P34: =IFERROR(ROUNDUP(((DATEDIF(N34,O34,"d"))/365),1),0) -> 0.8 | Q34: 19 | R34: 0 | S34: 0 | U34: Procject LC | V34: {=IFERROR((SUMPRODUCT((TEXT($N31:$N45,"yyyymm")=TEXT(V$30,"yyyymm")) * ($S31:$S45 * $M31:$M45*$Q31:$Q45*$P31:$P45)))+(SUMPRODUCT((TEXT($D31:$D45,"yyyymm")=TEXT(V$30,"yyyymm")) * ($I31:$I45 * $C31:$C45*$G31:$G45*$F31:$F45))),0)} -> 0 | W34: {=IFERROR((SUMPRODUCT((TEXT($N31:$N45,"yyyymm")=TEXT(W$30,"yyyymm")) * ($S31:$S45 * $M31:$M45*$Q31:$Q45*$P31:$P45)))+(SUMPRODUCT((TEXT($D31:$D45,"yyyymm")=TEXT(W$30,"yyyymm")) * ($I31:$I45 * $C31:$C45*$G31:$G45*$F31:$F45))),0)} -> 0 | X34: {=IFERROR((SUMPRODUCT((TEXT($N31:$N45,"yyyymm")=TEXT(X$30,"yyyymm")) * ($S31:$S45 * $M31:$M45*$Q31:$Q45*$P31:$P45)))+(SUMPRODUCT((TEXT($D31:$D45,"yyyymm")=TEXT(X$30,"yyyymm")) * ($I31:$I45 * $C31:$C45*$G31:$G45*$F31:$F45))),0)} -> 0 | Y34: {=IFERROR((SUMPRODUCT((TEXT($N31:$N45,"yyyymm")=TEXT(Y$30,"yyyymm")) * ($S31:$S45 * $M31:$M45*$Q31:$Q45*$P31:$P45)))+(SUMPRODUCT((TEXT($D31:$D45,"yyyymm")=TEXT(Y$30,"yyyymm")) * ($I31:$I45 * $C31:$C45*$G31:$G45*$F31:$F45))),0)} -> 0 | Z34: {=IFERROR((SUMPRODUCT((TEXT($N31:$N45,"yyyymm")=TEXT(Z$30,"yyyymm")) * ($S31:$S45 * $M31:$M45*$Q31:$Q45*$P31:$P45)))+(SUMPRODUCT((TEXT($D31:$D45,"yyyymm")=TEXT(Z$30,"yyyymm")) * ($I31:$I45 * $C31:$C45*$G31:$G45*$F31:$F45))),0)} -> 0 | AA34: {=IFERROR((SUMPRODUCT((TEXT($N31:$N45,"yyyymm")=TEXT(AA$30,"yyyymm")) * ($S31:$S45 * $M31:$M45*$Q31:$Q45*$P31:$P45)))+(SUMPRODUCT((TEXT($D31:$D45,"yyyymm")=TEXT(AA$30,"yyyymm")) * ($I31:$I45 * $C31:$C45*$G31:$G45*$F31:$F45))),0)} -> 0 | AB34: {=IFERROR((SUMPRODUCT((TEXT($N31:$N45,"yyyymm")=TEXT(AB$30,"yyyymm")) * ($S31:$S45 * $M31:$M45*$Q31:$Q45*$P31:$P45)))+(SUMPRODUCT((TEXT($D31:$D45,"yyyymm")=TEXT(AB$30,"yyyymm")) * ($I31:$I45 * $C31:$C45*$G31:$G45*$F31:$F45))),0)} -> 0 | AC34: {=IFERROR((SUMPRODUCT((TEXT($N31:$N45,"yyyymm")=TEXT(AC$30,"yyyymm")) * ($S31:$S45 * $M31:$M45*$Q31:$Q45*$P31:$P45)))+(SUMPRODUCT((TEXT($D31:$D45,"yyyymm")=TEXT(AC$30,"yyyymm")) * ($I31:$I45 * $C31:$C45*$G31:$G45*$F31:$F45))),0)} -> 0 | ... AS34: {=IFERROR((SUMPRODUCT((TEXT($N31:$N45,"yyyymm")=TEXT(AS$30,"yyyymm")) * ($S31:$S45 * $M31:$M45*$Q31:$Q45*$P31:$P45)))+(SUMPRODUCT((TEXT($D31:$D45,"yyyymm")=TEXT(AS$30,"yyyymm")) * ($I31:$I45 * $C31:$C45*$G31:$G45*$F31:$F45))),0)} -> 0 | AT34: =SUM(AH34:AS34) -> 0 | CZ34: =IF(AND($N16<=CZ$8,$O16>=CZ$8),(($Q16*$M16)/12),0) -> 0 | DA34: =IF(AND($N16<=DA$8,$O16>=DA$8),(($Q16*$M16)/12),0) -> 0 | DB34: =IF(AND($N16<=DB$8,$O16>=DB$8),(($Q16*$M16)/12),0) -> 0 | DC34: =IF(AND($N16<=DC$8,$O16>=DC$8),(($Q16*$M16)/12),0) -> 0 | DD34: =IF(AND($N16<=DD$8,$O16>=DD$8),(($Q16*$M16)/12),0) -> 0 | DE34: =IF(AND($N16<=DE$8,$O16>=DE$8),(($Q16*$M16)/12),0) -> 0 | DF34: =IF(AND($N16<=DF$8,$O16>=DF$8),(($Q16*$M16)/12),0) -> 0 | DG34: =IF(AND($N16<=DG$8,$O16>=DG$8),(($Q16*$M16)/12),0) -> 0 | ... DW34: =IF(AND($N16<=DW$8,$O16>=DW$8),(($Q16*$M16)/12),0) -> 4316.6667
A35: 307 | B35: =IF(A35<>"","VACANT","") -> VACANT | C35: 2067 | F35: =IFERROR(ROUNDUP(((DATEDIF(D35,E35,"d"))/365),1),0) -> 0 | K35: 312 | L35: Advenser LLC | M35: 1049 | N35: 46023 | O35: 46752 | P35: =IFERROR(ROUNDUP(((DATEDIF(N35,O35,"d"))/365),1),0) -> 2 | Q35: 18 | R35: 0 | S35: 0 | U35: Total: | V35: =SUM(V32:V34) -> 0 | W35: =SUM(W32:W34) -> 0 | X35: =SUM(X32:X34) -> 0 | Y35: =SUM(Y32:Y34) -> 0 | Z35: =SUM(Z32:Z34) -> 0 | AA35: =SUM(AA32:AA34) -> 0 | AB35: =SUM(AB32:AB34) -> 0 | AC35: =SUM(AC32:AC34) -> 0 | ... AT35: =SUM(AT32:AT34) -> 96034.167 | CZ35: =IF(AND($N17<=CZ$8,$O17>=CZ$8),(($Q17*$M17)/12),0) -> 0 | DA35: =IF(AND($N17<=DA$8,$O17>=DA$8),(($Q17*$M17)/12),0) -> 0 | DB35: =IF(AND($N17<=DB$8,$O17>=DB$8),(($Q17*$M17)/12),0) -> 0 | DC35: =IF(AND($N17<=DC$8,$O17>=DC$8),(($Q17*$M17)/12),0) -> 0 | DD35: =IF(AND($N17<=DD$8,$O17>=DD$8),(($Q17*$M17)/12),0) -> 0 | DE35: =IF(AND($N17<=DE$8,$O17>=DE$8),(($Q17*$M17)/12),0) -> 0 | DF35: =IF(AND($N17<=DF$8,$O17>=DF$8),(($Q17*$M17)/12),0) -> 0 | DG35: =IF(AND($N17<=DG$8,$O17>=DG$8),(($Q17*$M17)/12),0) -> 0 | ... DW35: =IF(AND($N17<=DW$8,$O17>=DW$8),(($Q17*$M17)/12),0) -> 1251
