Workbook
Name PaiementsParAn: 'Water Sewer'!$F$6
Name PaiementsParAn: 'INS RET'!$G$6
Name pmtType: 'INS RET'!$F$20
Name pmtType: 'Water Sewer'!$E$18
Name rate: 'INS RET'!$J$6
Name rate: 'Water Sewer'!$I$6
Name roundOpt: 'INS RET'!$F$24
Name roundOpt: 'Water Sewer'!$E$21
Name TauxIntérêt: 'Water Sewer'!$F$3
Name TauxIntérêt: 'INS RET'!$G$3

Sheet Cover Sheet
A1: ='NI LLC-Consolidated'!J1 -> Operating Budget
A2: ='NI LLC-Consolidated'!J2 -> Neshaminy Interplex LLC
A3: ='NI LLC-Consolidated'!Q1 -> 46023

Sheet Source and Use of Cash
A1: NESHAMINY INTERPELX LLC
A2: Summary Source and Use of Cash for 2026 Budget
B5: CASH FLOW AFTER INTEREST ON DEBT SERVICE | E5: =+'NI LLC-Consolidated'!Q134 -> 297244 | F5: TI costs for 2025 are included in this defecit
B7: ADD: Operating Cash 01/01/2026 | E7: =+'NI LLC-Consolidated'!D139 -> 395118.24 | F7: From 2025 reprojections at end of August
B9: LESS: Monthly Contributions to TI Escrow | E9: 0 | F9: Request no TI contributions for 2026
A11: {A} | B11: ADD: TI Improvements and LC Costs | E11: =+'NI LLC-Consolidated'!Q144+'NI LLC-Consolidated'!Q146 -> 180992.97 | F11: To be funded by balances in TI Reserve
C13: Cash Balance, 31 December 2026 | E13: =SUM(E5:E11) -> 873355.21
A15: {A} | B15: Summary of TI Allowance Escrow:
C17: 46022 | D17: Projected Balance, | E17: =+'NI LLC-Consolidated'!D152 -> 364692
B18: LESS: TI Improvements and Lease Costs year 2026 | E18: =-E11 -> -180992.97
C20: Remaining Balance, TI Escrow | E20: =+E17+E18 -> 183699.03
C22: Balance of TI Escrow 31 Dec 2026 | E22: =+E20+E21 -> 183699.03 | F22: Request funds if needed for any shortfalls
A25: {B} | B25: USE OF DEBT SRVICE ESTROW TRUST FUNDS
C27: 45966 | D27: Per Bank Statement | E27: 2015700
D28: ADD Interest Earnings:
D29: Estimated Interest Nov & Dec 2025 | E29: 12200
D30: Estimated Interest Year 2026 | E30: 73500
D32: Total Available | E32: =SUM(E27:E31) -> 2101400
D33: Initial Escrow Deposit | E33: -1840516
D34: Interest Earnings Available | E34: =+E32+E33 -> 260883.99 | F34: {With permission from Trustees}
C36: FOR INTERNAL DISCUSSION POINTS ONLY
B37: Other Options:
B38: 1 | C38: Discuss lower interest rate
C39: May result in some element of Cash Management as previously proposed by Liberty.
C40: (This was NI LLC determing what excess cash was available to remit to Bank - not
C41: the normal Bank Cash Management). May require more complexities in structuring
C42: at this time.
B44: 2 | C44: Use of Debt Service Escrow
C45: This may be better used for year 2027.
B47: 3 | C47: Potential sale or re-purpose of the Interplex.

Sheet Assumptions
B1: Budget Assumptions | E1: ='NI LLC-Consolidated'!Q1 -> 46023
B2: ='NI LLC-Consolidated'!J2 -> Neshaminy Interplex LLC
B6: Account Code | C6: Description | D6: Assumption / Notes
B7: Revenues
B8: ='NI LLC-Consolidated'!A10 -> 4230-8501 | C8: =IFERROR(VLOOKUP($B8,'NI LLC-Consolidated'!$A$10:$U$155,3,FALSE),"") -> Rental Income - In Place | D8: =IFERROR(VLOOKUP($B8,'NI LLC-Consolidated'!$A$10:$U$155,21,FALSE),"") -> 0
B9: ='NI LLC-Consolidated'!A11 -> 4230-8501 | C9: ='NI LLC-Consolidated'!C11 -> Rental Income - New & Renewal | D9: =IFERROR(VLOOKUP($B9,'NI LLC-Consolidated'!$A$10:$U$155,21,FALSE),"") -> 0
B10: ='NI LLC-Consolidated'!A12 -> 4240-8501 | C10: ='NI LLC-Consolidated'!C12 -> Percentage Rents | D10: =IFERROR(VLOOKUP($B10,'NI LLC-Consolidated'!$A$10:$U$155,21,FALSE),"") -> 0
B11: ='NI LLC-Consolidated'!A13 -> 4990-8501 | C11: =IFERROR(VLOOKUP($B11,'NI LLC-Consolidated'!$A$10:$U$155,3,FALSE),"") -> Miscellaneous | D11: =IFERROR(VLOOKUP($B11,'NI LLC-Consolidated'!$A$10:$U$155,21,FALSE),"") -> Gym Fees and $5K/qtr for Billboard (Applied to 4080)
B12: ='NI LLC-Consolidated'!A14 -> 9190-8501 | C12: =IFERROR(VLOOKUP($B12,'NI LLC-Consolidated'!$A$10:$U$155,3,FALSE),"") -> Interest Income | D12: =IFERROR(VLOOKUP($B12,'NI LLC-Consolidated'!$A$10:$U$155,21,FALSE),"") -> Annualized one month of interest from recent statement (Applied to 4050)
B13: Reimbursements | D13: =IFERROR(VLOOKUP($B13,'NI LLC-Consolidated'!$A$10:$U$155,21,FALSE),"")
B14: ='NI LLC-Consolidated'!A18 -> 4710-8502 | C14: =IFERROR(VLOOKUP($B14,'NI LLC-Consolidated'!$A$10:$U$155,3,FALSE),"") -> Electric | D14: =IFERROR(VLOOKUP($B14,'NI LLC-Consolidated'!$A$10:$U$155,21,FALSE),"") -> Set to occupancy
B15: ='NI LLC-Consolidated'!A19 -> 4910-8502 | C15: =IFERROR(VLOOKUP($B15,'NI LLC-Consolidated'!$A$10:$U$155,3,FALSE),"") -> Common Area Maintenance | D15: =IFERROR(VLOOKUP($B15,'NI LLC-Consolidated'!$A$10:$U$155,21,FALSE),"") -> 0
B16: ='NI LLC-Consolidated'!A20 -> 4920-8502 | C16: =IFERROR(VLOOKUP($B16,'NI LLC-Consolidated'!$A$10:$U$155,3,FALSE),"") -> Real Estate Taxes | D16: =IFERROR(VLOOKUP($B16,'NI LLC-Consolidated'!$A$10:$U$155,21,FALSE),"") -> 0
B17: ='NI LLC-Consolidated'!A21 -> 4930-8502 | C17: =IFERROR(VLOOKUP($B17,'NI LLC-Consolidated'!$A$10:$U$155,3,FALSE),"") -> Insurance | D17: =IFERROR(VLOOKUP($B17,'NI LLC-Consolidated'!$A$10:$U$155,21,FALSE),"") -> 0
B18: Reimbursable Expenses | D18: =IFERROR(VLOOKUP($B18,'NI LLC-Consolidated'!$A$10:$U$155,21,FALSE),"")
B19: ='NI LLC-Consolidated'!A27 -> 6030-8502 | C19: =IFERROR(VLOOKUP($B19,'NI LLC-Consolidated'!$A$10:$U$155,3,FALSE),"") -> Maintenance Salaries | D19: =IFERROR(VLOOKUP($B19,'NI LLC-Consolidated'!$A$10:$U$155,21,FALSE),"") -> Based on 2026 Payroll Budget
B20: ='NI LLC-Consolidated'!A29 -> 6120-8502 | C20: =IFERROR(VLOOKUP($B20,'NI LLC-Consolidated'!$A$10:$U$155,3,FALSE),"") -> Electric | D20: =IFERROR(VLOOKUP($B20,'NI LLC-Consolidated'!$A$10:$U$155,21,FALSE),"") -> Data\Shared\Properties\Business Plans - All Entities\2026\ISG Electric data
B21: ='NI LLC-Consolidated'!A31 -> 6130-8502 | C21: =IFERROR(VLOOKUP($B21,'NI LLC-Consolidated'!$A$10:$U$155,3,FALSE),"") -> Water & Sewer | D21: =IFERROR(VLOOKUP($B21,'NI LLC-Consolidated'!$A$10:$U$155,21,FALSE),"") -> 2025 Business Plan grown 3%
B22: ='NI LLC-Consolidated'!A36 -> 6220-8502 | C22: =IFERROR(VLOOKUP($B22,'NI LLC-Consolidated'!$A$10:$U$155,3,FALSE),"") -> Building Maintenance | D22: =IFERROR(VLOOKUP($B22,'NI LLC-Consolidated'!$A$10:$U$155,21,FALSE),"") -> 0
B23: ='NI LLC-Consolidated'!A38 -> 6330-8502 | C23: =IFERROR(VLOOKUP($B23,'NI LLC-Consolidated'!$A$10:$U$155,3,FALSE),"") -> Parking Lot Cleaning | D23: =IFERROR(VLOOKUP($B23,'NI LLC-Consolidated'!$A$10:$U$155,21,FALSE),"") -> 0
B24: ='NI LLC-Consolidated'!A43 -> 6360-8502 | C24: =IFERROR(VLOOKUP($B24,'NI LLC-Consolidated'!$A$10:$U$155,3,FALSE),"") -> Parking Lot Maintenance | D24: =IFERROR(VLOOKUP($B24,'NI LLC-Consolidated'!$A$10:$U$155,21,FALSE),"") -> 0
B25: ='NI LLC-Consolidated'!A45 -> 6370-8502 | C25: =IFERROR(VLOOKUP($B25,'NI LLC-Consolidated'!$A$10:$U$155,3,FALSE),"") -> Snow Removal | D25: =IFERROR(VLOOKUP($B25,'NI LLC-Consolidated'!$A$10:$U$155,21,FALSE),"") -> 2025 Business Plan grown 3%
B26: ='NI LLC-Consolidated'!A50 -> 6380-8502 | C26: =IFERROR(VLOOKUP($B26,'NI LLC-Consolidated'!$A$10:$U$155,3,FALSE),"") -> Landscaping | D26: =IFERROR(VLOOKUP($B26,'NI LLC-Consolidated'!$A$10:$U$155,21,FALSE),"") -> 0
B27: ='NI LLC-Consolidated'!A52 -> 6350-8502 | C27: =IFERROR(VLOOKUP($B27,'NI LLC-Consolidated'!$A$10:$U$155,3,FALSE),"") -> Security | D27: =IFERROR(VLOOKUP($B27,'NI LLC-Consolidated'!$A$10:$U$155,21,FALSE),"") -> 2025 Business Plan grown 3%
B28: ='NI LLC-Consolidated'!A54 -> 6610-8502 | C28: =IFERROR(VLOOKUP($B28,'NI LLC-Consolidated'!$A$10:$U$155,3,FALSE),"") -> Management Fee | D28: =IFERROR(VLOOKUP($B28,'NI LLC-Consolidated'!$A$10:$U$155,21,FALSE),"") -> 4% EGR for 5-8, 6% EGR for A-C
B29: ='NI LLC-Consolidated'!A56 -> 6270-8502 | C29: =IFERROR(VLOOKUP($B29,'NI LLC-Consolidated'!$A$10:$U$155,3,FALSE),"") -> Trash Removal | D29: =IFERROR(VLOOKUP($B29,'NI LLC-Consolidated'!$A$10:$U$155,21,FALSE),"") -> 2025 Business Plan grown 3%
B30: ='NI LLC-Consolidated'!A58 -> 6410-8502 | C30: =IFERROR(VLOOKUP($B30,'NI LLC-Consolidated'!$A$10:$U$155,3,FALSE),"") -> Real Estate Taxes | D30: =IFERROR(VLOOKUP($B30,'NI LLC-Consolidated'!$A$10:$U$155,21,FALSE),"") -> 0
B31: ='NI LLC-Consolidated'!A63 -> 6510-8502 | C31: =IFERROR(VLOOKUP($B31,'NI LLC-Consolidated'!$A$10:$U$155,3,FALSE),"") -> Insurance | D31: =IFERROR(VLOOKUP($B31,'NI LLC-Consolidated'!$A$10:$U$155,21,FALSE),"") -> 0
B32: ='NI LLC-Consolidated'!A67 -> 6250-8502 | C32: =IFERROR(VLOOKUP($B32,'NI LLC-Consolidated'!$A$10:$U$155,3,FALSE),"") -> Cleaning & Supplies | D32: =IFERROR(VLOOKUP($B32,'NI LLC-Consolidated'!$A$10:$U$155,21,FALSE),"") -> Based on occupancy.
B33: Non-Reimbursable Expenses | D33: =IFERROR(VLOOKUP($B33,'NI LLC-Consolidated'!$A$10:$U$155,21,FALSE),"")
B34: ='NI LLC-Consolidated'!A75 -> 5210-8501 | C34: =IFERROR(VLOOKUP($B34,'NI LLC-Consolidated'!$A$10:$U$155,3,FALSE),"") -> Bad Debt | D34: =IFERROR(VLOOKUP($B34,'NI LLC-Consolidated'!$A$10:$U$155,21,FALSE),"") -> 0
B35: ='NI LLC-Consolidated'!A77 -> 6010-8501 | C35: =IFERROR(VLOOKUP($B35,'NI LLC-Consolidated'!$A$10:$U$155,4,FALSE),"") -> Salaries & Wages | D35: =IFERROR(VLOOKUP($B35,'NI LLC-Consolidated'!$A$10:$U$155,21,FALSE),"") -> Based on 2026 Payroll Budget
B36: ='NI LLC-Consolidated'!A78 -> 6620-8501 | C36: =IFERROR(VLOOKUP($B36,'NI LLC-Consolidated'!$A$10:$U$155,4,FALSE),"") -> Commissions-Internal Broker | D36: =IFERROR(VLOOKUP($B36,'NI LLC-Consolidated'!$A$10:$U$155,21,FALSE),"") -> Based on projected leasing assumptions
B37: ='NI LLC-Consolidated'!A81 -> 6110-8501 | C37: =IFERROR(VLOOKUP($B37,'NI LLC-Consolidated'!$A$10:$U$155,4,FALSE),"") -> Gas | D37: =IFERROR(VLOOKUP($B37,'NI LLC-Consolidated'!$A$10:$U$155,21,FALSE),"") -> 0
B38: ='NI LLC-Consolidated'!A82 -> 6120-8501 | C38: =IFERROR(VLOOKUP($B38,'NI LLC-Consolidated'!$A$10:$U$155,4,FALSE),"") -> Electric | D38: =IFERROR(VLOOKUP($B38,'NI LLC-Consolidated'!$A$10:$U$155,21,FALSE),"") -> 0
B39: ='NI LLC-Consolidated'!A83 -> 6130-8501 | C39: =IFERROR(VLOOKUP($B39,'NI LLC-Consolidated'!$A$10:$U$155,4,FALSE),"") -> Water & Sewer | D39: =IFERROR(VLOOKUP($B39,'NI LLC-Consolidated'!$A$10:$U$155,21,FALSE),"") -> 0
B40: ='NI LLC-Consolidated'!A88 -> 6220-8501 | C40: =IFERROR(VLOOKUP($B40,'NI LLC-Consolidated'!$A$10:$U$155,3,FALSE),"") -> Building Maintenance | D40: =IFERROR(VLOOKUP($B40,'NI LLC-Consolidated'!$A$10:$U$155,21,FALSE),"") -> 2025 Business Plan grown 3%
B41: ='NI LLC-Consolidated'!A90 -> 6610-8501 | C41: =IFERROR(VLOOKUP($B41,'NI LLC-Consolidated'!$A$10:$U$155,3,FALSE),"") -> Management fee | D41: =IFERROR(VLOOKUP($B41,'NI LLC-Consolidated'!$A$10:$U$155,21,FALSE),"") -> 0
B42: ='NI LLC-Consolidated'!A92 -> 7110-8501 | C42: =IFERROR(VLOOKUP($B42,'NI LLC-Consolidated'!$A$10:$U$155,3,FALSE),"") -> Marketing | D42: =IFERROR(VLOOKUP($B42,'NI LLC-Consolidated'!$A$10:$U$155,21,FALSE),"") -> 2025 Business Plan grown 3%
B43: ='NI LLC-Consolidated'!A94 -> 8210-8501 | C43: =IFERROR(VLOOKUP($B43,'NI LLC-Consolidated'!$A$10:$U$155,3,FALSE),"") -> Business Taxes | D43: =IFERROR(VLOOKUP($B43,'NI LLC-Consolidated'!$A$10:$U$155,21,FALSE),"") -> 2025 Business Plan grown 3%
B44: ='NI LLC-Consolidated'!A96 -> 8310-8501 | C44: =IFERROR(VLOOKUP($B44,'NI LLC-Consolidated'!$A$10:$U$155,3,FALSE),"") -> Legal & Accounting | D44: =IFERROR(VLOOKUP($B44,'NI LLC-Consolidated'!$A$10:$U$155,21,FALSE),"") -> 2025 Business Plan grown 3%
B45: ='NI LLC-Consolidated'!A98 -> 8190-8501 | C45: =IFERROR(VLOOKUP($B45,'NI LLC-Consolidated'!$A$10:$U$155,4,FALSE),"") -> Bank Fees | D45: =IFERROR(VLOOKUP($B45,'NI LLC-Consolidated'!$A$10:$U$155,21,FALSE),"") -> 2025 Business Plan grown 3%
B46: ='NI LLC-Consolidated'!A99 -> 8930-8501 | C46: =IFERROR(VLOOKUP($B46,'NI LLC-Consolidated'!$A$10:$U$155,4,FALSE),"") -> Office Supplies | D46: =IFERROR(VLOOKUP($B46,'NI LLC-Consolidated'!$A$10:$U$155,21,FALSE),"") -> 0
B47: ='NI LLC-Consolidated'!A100 -> 8950-8501 | C47: =IFERROR(VLOOKUP($B47,'NI LLC-Consolidated'!$A$10:$U$155,4,FALSE),"") -> Postage | D47: =IFERROR(VLOOKUP($B47,'NI LLC-Consolidated'!$A$10:$U$155,21,FALSE),"") -> 0
B48: ='NI LLC-Consolidated'!A101 -> 8990-8501 | C48: =IFERROR(VLOOKUP($B48,'NI LLC-Consolidated'!$A$10:$U$155,4,FALSE),"") -> Other G&A Expense | D48: =IFERROR(VLOOKUP($B48,'NI LLC-Consolidated'!$A$10:$U$155,21,FALSE),"") -> 2025 Business Plan grown 3%
B49: ='NI LLC-Consolidated'!A102 -> 8990-9800 | C49: =IFERROR(VLOOKUP($B49,'NI LLC-Consolidated'!$A$10:$U$155,4,FALSE),"") -> Other G&A-allocated from LIK | D49: =IFERROR(VLOOKUP($B49,'NI LLC-Consolidated'!$A$10:$U$155,21,FALSE),"") -> 2025 Business Plan grown 3%
D50: =IFERROR(VLOOKUP($B50,'NI LLC-Consolidated'!$A$10:$U$155,21,FALSE),"")
B51: ='NI LLC-Consolidated'!A113 -> 1420-0000 | C51: =IFERROR(VLOOKUP($B51,'NI LLC-Consolidated'!$A$10:$U$155,4,FALSE),"") -> Land Improvements | D51: =IFERROR(VLOOKUP($B51,'NI LLC-Consolidated'!$A$10:$U$155,21,FALSE),"") -> 0
B52: ='NI LLC-Consolidated'!A114 -> 1430-0000 | C52: =IFERROR(VLOOKUP($B52,'NI LLC-Consolidated'!$A$10:$U$155,4,FALSE),"") -> Buildings | D52: =IFERROR(VLOOKUP($B52,'NI LLC-Consolidated'!$A$10:$U$155,21,FALSE),"") -> 0
B53: ='NI LLC-Consolidated'!A115 -> 1450-0000 | C53: =IFERROR(VLOOKUP($B53,'NI LLC-Consolidated'!$A$10:$U$155,4,FALSE),"") -> Equipment | D53: =IFERROR(VLOOKUP($B53,'NI LLC-Consolidated'!$A$10:$U$155,21,FALSE),"") -> 0
B54: ='NI LLC-Consolidated'!A116 -> 1980-8501 | C54: =IFERROR(VLOOKUP($B54,'NI LLC-Consolidated'!$A$10:$U$155,4,FALSE),"") -> Capital Improvements | D54: =IFERROR(VLOOKUP($B54,'NI LLC-Consolidated'!$A$10:$U$155,21,FALSE),"") -> 0
B55: ='NI LLC-Consolidated'!A119 -> 1440-0000 | C55: =IFERROR(VLOOKUP($B55,'NI LLC-Consolidated'!$A$10:$U$155,3,FALSE),"") -> Tenant Improvements | D55: =IFERROR(VLOOKUP($B55,'NI LLC-Consolidated'!$A$10:$U$155,21,FALSE),"") -> Based on projected leasing assumptions
B56: ='NI LLC-Consolidated'!A121 -> 1940-8501 | C56: =IFERROR(VLOOKUP($B56,'NI LLC-Consolidated'!$A$10:$U$155,4,FALSE),"") -> Deferred Marketing | D56: =IFERROR(VLOOKUP($B56,'NI LLC-Consolidated'!$A$10:$U$155,21,FALSE),"") -> 0
B57: ='NI LLC-Consolidated'!A122 -> 1940-8501 | C57: =IFERROR(VLOOKUP($B57,'NI LLC-Consolidated'!$A$10:$U$155,4,FALSE),"") -> Deferred Marketing | D57: =IFERROR(VLOOKUP($B57,'NI LLC-Consolidated'!$A$10:$U$155,21,FALSE),"") -> 0
B58: ='NI LLC-Consolidated'!A128 -> 9210-8501 | C58: =IFERROR(VLOOKUP($B58,'NI LLC-Consolidated'!$A$10:$U$155,4,FALSE),"") -> Interest | D58: =IFERROR(VLOOKUP($B58,'NI LLC-Consolidated'!$A$10:$U$155,21,FALSE),"") -> 0
B59: ='NI LLC-Consolidated'!A129 -> 2740-8501 | C59: =IFERROR(VLOOKUP($B59,'NI LLC-Consolidated'!$A$10:$U$155,4,FALSE),"") -> Mortgage Amortization | D59: =IFERROR(VLOOKUP($B59,'NI LLC-Consolidated'!$A$10:$U$155,21,FALSE),"") -> 0
B60: ='NI LLC-Consolidated'!A130 -> 2740-0000 | C60: =IFERROR(VLOOKUP($B60,'NI LLC-Consolidated'!$A$10:$U$155,4,FALSE),"") -> Loan Proceeds | D60: =IFERROR(VLOOKUP($B60,'NI LLC-Consolidated'!$A$10:$U$155,21,FALSE),"") -> 0

Sheet NI LLC-Consolidated
B1: Consolidated - 5,6,7,8,A,B,C | J1: Operating Budget | Q1: =DATE(2026,1,1) -> 46023
J2: Neshaminy Interplex LLC
Q3: =Q1 -> 46023 | R3: 7/2025 Reprojections
B4: ='Renew & Vac'!A6+'Renew & Vac'!A28+'Renew & Vac'!A50+'Renew & Vac'!A72+'Renew & Vac'!A94+'Renew & Vac'!A116+'Renew & Vac'!A138 -> 397315 | E4: Jan | F4: Feb | G4: Mar | H4: Apr | I4: May | J4: Jun | K4: Jul | L4: Aug | M4: Sep | N4: Oct | O4: Nov | P4: Dec | Q4: Total | R4: Total | S4: Var. | T4: Input | U4: Notes
D6: Occupancy % | E6: =SUM('4050'!E7,'4060'!E7,'4070'!E7,'4080'!E7,'40A0'!E7,'40B0'!E7,'40C0'!E7)/$B$4 -> 0.6669179 | F6: =SUM('4050'!F7,'4060'!F7,'4070'!F7,'4080'!F7,'40A0'!F7,'40B0'!F7,'40C0'!F7)/$B$4 -> 0.6685275 | G6: =SUM('4050'!G7,'4060'!G7,'4070'!G7,'4080'!G7,'40A0'!G7,'40B0'!G7,'40C0'!G7)/$B$4 -> 0.67367598 | H6: =SUM('4050'!H7,'4060'!H7,'4070'!H7,'4080'!H7,'40A0'!H7,'40B0'!H7,'40C0'!H7)/$B$4 -> 0.68748835 | I6: =SUM('4050'!I7,'4060'!I7,'4070'!I7,'4080'!I7,'40A0'!I7,'40B0'!I7,'40C0'!I7)/$B$4 -> 0.68748835 | J6: =SUM('4050'!J7,'4060'!J7,'4070'!J7,'4080'!J7,'40A0'!J7,'40B0'!J7,'40C0'!J7)/$B$4 -> 0.68748835 | K6: =SUM('4050'!K7,'4060'!K7,'4070'!K7,'4080'!K7,'40A0'!K7,'40B0'!K7,'40C0'!K7)/$B$4 -> 0.68375787 | L6: =SUM('4050'!L7,'4060'!L7,'4070'!L7,'4080'!L7,'40A0'!L7,'40B0'!L7,'40C0'!L7)/$B$4 -> 0.68375787 | ... P6: =SUM('4050'!P7,'4060'!P7,'4070'!P7,'4080'!P7,'40A0'!P7,'40B0'!P7,'40C0'!P7)/$B$4 -> 0.66519737
B8: Revenues
A10: 4230-8501 | C10: Rental Income - In Place | E10: =+'4050'!E10+'4060'!E10+'4070'!E10+'4080'!E10+'40A0'!E10+'40B0'!E10+'40C0'!E10+'4000'!E9 -> 293482.04 | F10: =+'4050'!F10+'4060'!F10+'4070'!F10+'4080'!F10+'40A0'!F10+'40B0'!F10+'40C0'!F10+'4000'!F9 -> 291222.19 | G10: =+'4050'!G10+'4060'!G10+'4070'!G10+'4080'!G10+'40A0'!G10+'40B0'!G10+'40C0'!G10+'4000'!G9 -> 291487.24 | H10: =+'4050'!H10+'4060'!H10+'4070'!H10+'4080'!H10+'40A0'!H10+'40B0'!H10+'40C0'!H10+'4000'!H9 -> 279312.18 | I10: =+'4050'!I10+'4060'!I10+'4070'!I10+'4080'!I10+'40A0'!I10+'40B0'!I10+'40C0'!I10+'4000'!I9 -> 280119.76 | J10: =+'4050'!J10+'4060'!J10+'4070'!J10+'4080'!J10+'40A0'!J10+'40B0'!J10+'40C0'!J10+'4000'!J9 -> 280257.6 | K10: =+'4050'!K10+'4060'!K10+'4070'!K10+'4080'!K10+'40A0'!K10+'40B0'!K10+'40C0'!K10+'4000'!K9 -> 220520.85 | L10: =+'4050'!L10+'4060'!L10+'4070'!L10+'4080'!L10+'40A0'!L10+'40B0'!L10+'40C0'!L10+'4000'!L9 -> 219090.56 | ... P10: =+'4050'!P10+'4060'!P10+'4070'!P10+'4080'!P10+'40A0'!P10+'40B0'!P10+'40C0'!P10+'4000'!P9 -> 192534.82 | Q10: =SUM(E10:P10) -> 2953594.6 | R10: 4725706 | S10: =(Q10+Q11)/R10-1 -> -0.047732592
A11: 4230-8501 | C11: Rental Income - New & Renewal | E11: =+'4050'!E11+'4060'!E11+'4070'!E11+'4080'!E11+'40A0'!E11+'40B0'!E11+'40C0'!E11+'4000'!E10 -> 82100.625 | F11: =+'4050'!F11+'4060'!F11+'4070'!F11+'4080'!F11+'40A0'!F11+'40B0'!F11+'40C0'!F11+'4000'!F10 -> 85400.062 | G11: =+'4050'!G11+'4060'!G11+'4070'!G11+'4080'!G11+'40A0'!G11+'40B0'!G11+'40C0'!G11+'4000'!G10 -> 88907.272 | H11: =+'4050'!H11+'4060'!H11+'4070'!H11+'4080'!H11+'40A0'!H11+'40B0'!H11+'40C0'!H11+'4000'!H10 -> 105864.77 | I11: =+'4050'!I11+'4060'!I11+'4070'!I11+'4080'!I11+'40A0'!I11+'40B0'!I11+'40C0'!I11+'4000'!I10 -> 105864.77 | J11: =+'4050'!J11+'4060'!J11+'4070'!J11+'4080'!J11+'40A0'!J11+'40B0'!J11+'40C0'!J11+'4000'!J10 -> 105864.77 | K11: =+'4050'!K11+'4060'!K11+'4070'!K11+'4080'!K11+'40A0'!K11+'40B0'!K11+'40C0'!K11+'4000'!K10 -> 150605.44 | L11: =+'4050'!L11+'4060'!L11+'4070'!L11+'4080'!L11+'40A0'!L11+'40B0'!L11+'40C0'!L11+'4000'!L10 -> 152343.94 | ... P11: =+'4050'!P11+'4060'!P11+'4070'!P11+'4080'!P11+'40A0'!P11+'40B0'!P11+'40C0'!P11+'4000'!P10 -> 167497.23 | Q11: =SUM(E11:P11) -> 1546541.2
A12: 4240-8501 | C12: Percentage Rents | E12: =+'4050'!E12+'4060'!E12+'4070'!E12+'4080'!E12+'40A0'!E12+'40B0'!E12+'40C0'!E12+'4000'!E10 -> 0 | F12: =+'4050'!F12+'4060'!F12+'4070'!F12+'4080'!F12+'40A0'!F12+'40B0'!F12+'40C0'!F12+'4000'!F10 -> 0 | G12: =+'4050'!G12+'4060'!G12+'4070'!G12+'4080'!G12+'40A0'!G12+'40B0'!G12+'40C0'!G12+'4000'!G10 -> 0 | H12: =+'4050'!H12+'4060'!H12+'4070'!H12+'4080'!H12+'40A0'!H12+'40B0'!H12+'40C0'!H12+'4000'!H10 -> 0 | I12: =+'4050'!I12+'4060'!I12+'4070'!I12+'4080'!I12+'40A0'!I12+'40B0'!I12+'40C0'!I12+'4000'!I10 -> 0 | J12: =+'4050'!J12+'4060'!J12+'4070'!J12+'4080'!J12+'40A0'!J12+'40B0'!J12+'40C0'!J12+'4000'!J10 -> 0 | K12: =+'4050'!K12+'4060'!K12+'4070'!K12+'4080'!K12+'40A0'!K12+'40B0'!K12+'40C0'!K12+'4000'!K10 -> 0 | L12: =+'4050'!L12+'4060'!L12+'4070'!L12+'4080'!L12+'40A0'!L12+'40B0'!L12+'40C0'!L12+'4000'!L10 -> 0 | ... P12: =+'4050'!P12+'4060'!P12+'4070'!P12+'4080'!P12+'40A0'!P12+'40B0'!P12+'40C0'!P12+'4000'!P10 -> 0 | Q12: =SUM(E12:P12) -> 0 | S12: =Q12/R12-1 -> #DIV/0!
A13: 4990-8501 | C13: Miscellaneous | E13: =+'4050'!E13+'4060'!E13+'4070'!E13+'4080'!E13+'40A0'!E13+'40B0'!E13+'40C0'!E13+'4000'!E11 -> 200 | F13: =+'4050'!F13+'4060'!F13+'4070'!F13+'4080'!F13+'40A0'!F13+'40B0'!F13+'40C0'!F13+'4000'!F11 -> 200 | G13: =+'4050'!G13+'4060'!G13+'4070'!G13+'4080'!G13+'40A0'!G13+'40B0'!G13+'40C0'!G13+'4000'!G11 -> 5200 | H13: =+'4050'!H13+'4060'!H13+'4070'!H13+'4080'!H13+'40A0'!H13+'40B0'!H13+'40C0'!H13+'4000'!H11 -> 200 | I13: =+'4050'!I13+'4060'!I13+'4070'!I13+'4080'!I13+'40A0'!I13+'40B0'!I13+'40C0'!I13+'4000'!I11 -> 200 | J13: =+'4050'!J13+'4060'!J13+'4070'!J13+'4080'!J13+'40A0'!J13+'40B0'!J13+'40C0'!J13+'4000'!J11 -> 5200 | K13: =+'4050'!K13+'4060'!K13+'4070'!K13+'4080'!K13+'40A0'!K13+'40B0'!K13+'40C0'!K13+'4000'!K11 -> 200 | L13: =+'4050'!L13+'4060'!L13+'4070'!L13+'4080'!L13+'40A0'!L13+'40B0'!L13+'40C0'!L13+'4000'!L11 -> 200 | ... P13: =+'4050'!P13+'4060'!P13+'4070'!P13+'4080'!P13+'40A0'!P13+'40B0'!P13+'40C0'!P13+'4000'!P11 -> 5200 | Q13: =SUM(E13:P13) -> 22400 | S13: =Q13/R13-1 -> #DIV/0! | T13: DW | U13: Gym Fees and $5K/qtr for Billboard (Applied to 4080)
A14: 9190-8501 | C14: Interest Income | E14: =+'4050'!E14+'4060'!E14+'4070'!E14+'4080'!E14+'40A0'!E14+'40B0'!E14+'40C0'!E14+'4000'!E12 -> 207 | F14: =+'4050'!F14+'4060'!F14+'4070'!F14+'4080'!F14+'40A0'!F14+'40B0'!F14+'40C0'!F14+'4000'!F12 -> 207 | G14: =+'4050'!G14+'4060'!G14+'4070'!G14+'4080'!G14+'40A0'!G14+'40B0'!G14+'40C0'!G14+'4000'!G12 -> 207 | H14: =+'4050'!H14+'4060'!H14+'4070'!H14+'4080'!H14+'40A0'!H14+'40B0'!H14+'40C0'!H14+'4000'!H12 -> 207 | I14: =+'4050'!I14+'4060'!I14+'4070'!I14+'4080'!I14+'40A0'!I14+'40B0'!I14+'40C0'!I14+'4000'!I12 -> 207 | J14: =+'4050'!J14+'4060'!J14+'4070'!J14+'4080'!J14+'40A0'!J14+'40B0'!J14+'40C0'!J14+'4000'!J12 -> 207 | K14: =+'4050'!K14+'4060'!K14+'4070'!K14+'4080'!K14+'40A0'!K14+'40B0'!K14+'40C0'!K14+'4000'!K12 -> 207 | L14: =+'4050'!L14+'4060'!L14+'4070'!L14+'4080'!L14+'40A0'!L14+'40B0'!L14+'40C0'!L14+'4000'!L12 -> 207 | ... P14: =+'4050'!P14+'4060'!P14+'4070'!P14+'4080'!P14+'40A0'!P14+'40B0'!P14+'40C0'!P14+'4000'!P12 -> 207 | Q14: =SUM(E14:P14) -> 2484 | R14: 0 | T14: DW | U14: Annualized one month of interest from recent statement (Applied to 4050)
D15: Total Rental and Other: | E15: =SUM(E10:E14) -> 375989.67 | F15: =SUM(F10:F14) -> 377029.25 | G15: =SUM(G10:G14) -> 385801.51 | H15: =SUM(H10:H14) -> 385583.95 | I15: =SUM(I10:I14) -> 386391.53 | J15: =SUM(J10:J14) -> 391529.37 | K15: =SUM(K10:K14) -> 371533.29 | L15: =SUM(L10:L14) -> 371841.5 | ... R15: =SUM(R10:R14) -> 4725706 | S15: =Q15/R15-1 -> -0.042466923
B17: Reimbursements
A18: 4710-8502 | C18: Electric | E18: =+'4050'!E18+'4060'!E18+'4070'!E18+'4080'!E18+'40A0'!E18+'40B0'!E18+'40C0'!E18+'4000'!E16 -> 62057.521 | F18: =+'4050'!F18+'4060'!F18+'4070'!F18+'4080'!F18+'40A0'!F18+'40B0'!F18+'40C0'!F18+'4000'!F16 -> 56555.837 | G18: =+'4050'!G18+'4060'!G18+'4070'!G18+'4080'!G18+'40A0'!G18+'40B0'!G18+'40C0'!G18+'4000'!G16 -> 54115.025 | H18: =+'4050'!H18+'4060'!H18+'4070'!H18+'4080'!H18+'40A0'!H18+'40B0'!H18+'40C0'!H18+'4000'!H16 -> 52905.408 | I18: =+'4050'!I18+'4060'!I18+'4070'!I18+'4080'!I18+'40A0'!I18+'40B0'!I18+'40C0'!I18+'4000'!I16 -> 54964.321 | J18: =+'4050'!J18+'4060'!J18+'4070'!J18+'4080'!J18+'40A0'!J18+'40B0'!J18+'40C0'!J18+'4000'!J16 -> 58906.282 | K18: =+'4050'!K18+'4060'!K18+'4070'!K18+'4080'!K18+'40A0'!K18+'40B0'!K18+'40C0'!K18+'4000'!K16 -> 63811.323 | L18: =+'4050'!L18+'4060'!L18+'4070'!L18+'4080'!L18+'40A0'!L18+'40B0'!L18+'40C0'!L18+'4000'!L16 -> 62006.217 | ... P18: =+'4050'!P18+'4060'!P18+'4070'!P18+'4080'!P18+'40A0'!P18+'40B0'!P18+'40C0'!P18+'4000'!P16 -> 61090.396 | Q18: =SUM(E18:P18) -> 690813.09 | R18: 632018 | S18: =Q18/R18-1 -> 0.093027551 | T18: DW | U18: Set to occupancy
A19: 4910-8502 | C19: Common Area Maintenance | E19: =+'4050'!E19+'4060'!E19+'4070'!E19+'4080'!E19+'40A0'!E19+'40B0'!E19+'40C0'!E19+'4000'!E17 -> 50300 | F19: =+'4050'!F19+'4060'!F19+'4070'!F19+'4080'!F19+'40A0'!F19+'40B0'!F19+'40C0'!F19+'4000'!F17 -> 50300 | G19: =+'4050'!G19+'4060'!G19+'4070'!G19+'4080'!G19+'40A0'!G19+'40B0'!G19+'40C0'!G19+'4000'!G17 -> 50300 | H19: =+'4050'!H19+'4060'!H19+'4070'!H19+'4080'!H19+'40A0'!H19+'40B0'!H19+'40C0'!H19+'4000'!H17 -> 50300 | I19: =+'4050'!I19+'4060'!I19+'4070'!I19+'4080'!I19+'40A0'!I19+'40B0'!I19+'40C0'!I19+'4000'!I17 -> 50300 | J19: =+'4050'!J19+'4060'!J19+'4070'!J19+'4080'!J19+'40A0'!J19+'40B0'!J19+'40C0'!J19+'4000'!J17 -> 50300 | K19: =+'4050'!K19+'4060'!K19+'4070'!K19+'4080'!K19+'40A0'!K19+'40B0'!K19+'40C0'!K19+'4000'!K17 -> 50300 | L19: =+'4050'!L19+'4060'!L19+'4070'!L19+'4080'!L19+'40A0'!L19+'40B0'!L19+'40C0'!L19+'4000'!L17 -> 50300 | ... P19: =+'4050'!P19+'4060'!P19+'4070'!P19+'4080'!P19+'40A0'!P19+'40B0'!P19+'40C0'!P19+'4000'!P17 -> 50300 | Q19: =SUM(E19:P19) -> 603600 | R19: 547773 | S19: =Q19/R19-1 -> 0.1019163
A20: 4920-8502 | C20: Real Estate Taxes | E20: =+'4050'!E20+'4060'!E20+'4070'!E20+'4080'!E20+'40A0'!E20+'40B0'!E20+'40C0'!E20+'4000'!E18 -> 8300 | F20: =+'4050'!F20+'4060'!F20+'4070'!F20+'4080'!F20+'40A0'!F20+'40B0'!F20+'40C0'!F20+'4000'!F18 -> 8300 | G20: =+'4050'!G20+'4060'!G20+'4070'!G20+'4080'!G20+'40A0'!G20+'40B0'!G20+'40C0'!G20+'4000'!G18 -> 8300 | H20: =+'4050'!H20+'4060'!H20+'4070'!H20+'4080'!H20+'40A0'!H20+'40B0'!H20+'40C0'!H20+'4000'!H18 -> 8300 | I20: =+'4050'!I20+'4060'!I20+'4070'!I20+'4080'!I20+'40A0'!I20+'40B0'!I20+'40C0'!I20+'4000'!I18 -> 8300 | J20: =+'4050'!J20+'4060'!J20+'4070'!J20+'4080'!J20+'40A0'!J20+'40B0'!J20+'40C0'!J20+'4000'!J18 -> 8300 | K20: =+'4050'!K20+'4060'!K20+'4070'!K20+'4080'!K20+'40A0'!K20+'40B0'!K20+'40C0'!K20+'4000'!K18 -> 8300 | L20: =+'4050'!L20+'4060'!L20+'4070'!L20+'4080'!L20+'40A0'!L20+'40B0'!L20+'40C0'!L20+'4000'!L18 -> 8300 | ... P20: =+'4050'!P20+'4060'!P20+'4070'!P20+'4080'!P20+'40A0'!P20+'40B0'!P20+'40C0'!P20+'4000'!P18 -> 8300 | Q20: =SUM(E20:P20) -> 99600 | R20: 82162 | S20: =Q20/R20-1 -> 0.21223923
A21: 4930-8502 | C21: Insurance | E21: =+'4050'!E21+'4060'!E21+'4070'!E21+'4080'!E21+'40A0'!E21+'40B0'!E21+'40C0'!E21+'4000'!E19 -> 0 | F21: =+'4050'!F21+'4060'!F21+'4070'!F21+'4080'!F21+'40A0'!F21+'40B0'!F21+'40C0'!F21+'4000'!F19 -> 0 | G21: =+'4050'!G21+'4060'!G21+'4070'!G21+'4080'!G21+'40A0'!G21+'40B0'!G21+'40C0'!G21+'4000'!G19 -> 0 | H21: =+'4050'!H21+'4060'!H21+'4070'!H21+'4080'!H21+'40A0'!H21+'40B0'!H21+'40C0'!H21+'4000'!H19 -> 0 | I21: =+'4050'!I21+'4060'!I21+'4070'!I21+'4080'!I21+'40A0'!I21+'40B0'!I21+'40C0'!I21+'4000'!I19 -> 0 | J21: =+'4050'!J21+'4060'!J21+'4070'!J21+'4080'!J21+'40A0'!J21+'40B0'!J21+'40C0'!J21+'4000'!J19 -> 0 | K21: =+'4050'!K21+'4060'!K21+'4070'!K21+'4080'!K21+'40A0'!K21+'40B0'!K21+'40C0'!K21+'4000'!K19 -> 0 | L21: =+'4050'!L21+'4060'!L21+'4070'!L21+'4080'!L21+'40A0'!L21+'40B0'!L21+'40C0'!L21+'4000'!L19 -> 0 | ... P21: =+'4050'!P21+'4060'!P21+'4070'!P21+'4080'!P21+'40A0'!P21+'40B0'!P21+'40C0'!P21+'4000'!P19 -> 0 | Q21: =SUM(E21:P21) -> 0 | R21: 0 | S21: =Q21/R21-1 -> #DIV/0!
D22: Total Reimbursements: | E22: =SUM(E18:E21) -> 120657.52 | F22: =SUM(F18:F21) -> 115155.84 | G22: =SUM(G18:G21) -> 112715.03 | H22: =SUM(H18:H21) -> 111505.41 | I22: =SUM(I18:I21) -> 113564.32 | J22: =SUM(J18:J21) -> 117506.28 | K22: =SUM(K18:K21) -> 122411.32 | L22: =SUM(L18:L21) -> 120606.22 | ... R22: =SUM(R18:R21) -> 1261953 | S22: =Q22/R22-1 -> 0.10464739
B24: TOTAL REVENUES | E24: =+E15+E22 -> 496647.19 | F24: =+F15+F22 -> 492185.09 | G24: =+G15+G22 -> 498516.54 | H24: =+H15+H22 -> 497089.36 | I24: =+I15+I22 -> 499955.85 | J24: =+J15+J22 -> 509035.65 | K24: =+K15+K22 -> 493944.61 | L24: =+L15+L22 -> 492447.72 | ... R24: =+R15+R22 -> 5987659 | S24: =Q24/R24-1 -> -0.011461258
Q25: =+'4050'!Q24+'4060'!Q24+'4070'!Q24+'4080'!Q24+'40A0'!Q24+'40B0'!Q24+'40C0'!Q24 -> 5919032.9
B26: Reimbursable Expenses
A27: 6030-8502 | C27: Maintenance Salaries | E27: =+'4050'!E27+'4060'!E27+'4070'!E27+'4080'!E27+'40A0'!E27+'40B0'!E27+'40C0'!E27+'4000'!E26 -> 8128.5833 | F27: =+'4050'!F27+'4060'!F27+'4070'!F27+'4080'!F27+'40A0'!F27+'40B0'!F27+'40C0'!F27+'4000'!F26 -> 8128.5833 | G27: =+'4050'!G27+'4060'!G27+'4070'!G27+'4080'!G27+'40A0'!G27+'40B0'!G27+'40C0'!G27+'4000'!G26 -> 8128.5833 | H27: =+'4050'!H27+'4060'!H27+'4070'!H27+'4080'!H27+'40A0'!H27+'40B0'!H27+'40C0'!H27+'4000'!H26 -> 8128.5833 | I27: =+'4050'!I27+'4060'!I27+'4070'!I27+'4080'!I27+'40A0'!I27+'40B0'!I27+'40C0'!I27+'4000'!I26 -> 8128.5833 | J27: =+'4050'!J27+'4060'!J27+'4070'!J27+'4080'!J27+'40A0'!J27+'40B0'!J27+'40C0'!J27+'4000'!J26 -> 8128.5833 | K27: =+'4050'!K27+'4060'!K27+'4070'!K27+'4080'!K27+'40A0'!K27+'40B0'!K27+'40C0'!K27+'4000'!K26 -> 8128.5833 | L27: =+'4050'!L27+'4060'!L27+'4070'!L27+'4080'!L27+'40A0'!L27+'40B0'!L27+'40C0'!L27+'4000'!L26 -> 8128.5833 | ... P27: =+'4050'!P27+'4060'!P27+'4070'!P27+'4080'!P27+'40A0'!P27+'40B0'!P27+'40C0'!P27+'4000'!P26 -> 8128.5833 | Q27: =SUM(E27:P27) -> 97543 | R27: 65400 | S27: =Q27/R27-1 -> 0.49148318 | U27: Based on 2026 Payroll Budget
A29: 6120-8502 | C29: Electric | E29: =+'4050'!E29+'4060'!E29+'4070'!E29+'4080'!E29+'40A0'!E29+'40B0'!E29+'40C0'!E29+'4000'!E28 -> 97164 | F29: =+'4050'!F29+'4060'!F29+'4070'!F29+'4080'!F29+'40A0'!F29+'40B0'!F29+'40C0'!F29+'4000'!F28 -> 88149 | G29: =+'4050'!G29+'4060'!G29+'4070'!G29+'4080'!G29+'40A0'!G29+'40B0'!G29+'40C0'!G29+'4000'!G28 -> 83677 | H29: =+'4050'!H29+'4060'!H29+'4070'!H29+'4080'!H29+'40A0'!H29+'40B0'!H29+'40C0'!H29+'4000'!H28 -> 80724 | I29: =+'4050'!I29+'4060'!I29+'4070'!I29+'4080'!I29+'40A0'!I29+'40B0'!I29+'40C0'!I29+'4000'!I28 -> 84119 | J29: =+'4050'!J29+'4060'!J29+'4070'!J29+'4080'!J29+'40A0'!J29+'40B0'!J29+'40C0'!J29+'4000'!J28 -> 90279 | K29: =+'4050'!K29+'4060'!K29+'4070'!K29+'4080'!K29+'40A0'!K29+'40B0'!K29+'40C0'!K29+'4000'!K28 -> 98568 | L29: =+'4050'!L29+'4060'!L29+'4070'!L29+'4080'!L29+'40A0'!L29+'40B0'!L29+'40C0'!L29+'4000'!L28 -> 95991 | ... P29: =+'4050'!P29+'4060'!P29+'4070'!P29+'4080'!P29+'40A0'!P29+'40B0'!P29+'40C0'!P29+'4000'!P28 -> 96590 | Q29: =SUM(E29:P29) -> 1070652 | R29: 970692 | S29: =Q29/R29-1 -> 0.10297808 | T29: DW | U29: Data\Shared\Properties\Business Plans - All Entities\2026\ISG Electric data
A31: 6130-8502 | C31: Water & Sewer | E31: =+'4050'!E31+'4060'!E31+'4070'!E31+'4080'!E31+'40A0'!E31+'40B0'!E31+'40C0'!E31+'4000'!E30 -> 5481.66 | F31: =+'4050'!F31+'4060'!F31+'4070'!F31+'4080'!F31+'40A0'!F31+'40B0'!F31+'40C0'!F31+'4000'!F30 -> 5746.37 | G31: =+'4050'!G31+'4060'!G31+'4070'!G31+'4080'!G31+'40A0'!G31+'40B0'!G31+'40C0'!G31+'4000'!G30 -> 6181.03 | H31: =+'4050'!H31+'4060'!H31+'4070'!H31+'4080'!H31+'40A0'!H31+'40B0'!H31+'40C0'!H31+'4000'!H30 -> 6196.48 | I31: =+'4050'!I31+'4060'!I31+'4070'!I31+'4080'!I31+'40A0'!I31+'40B0'!I31+'40C0'!I31+'4000'!I30 -> 10136.23 | J31: =+'4050'!J31+'4060'!J31+'4070'!J31+'4080'!J31+'40A0'!J31+'40B0'!J31+'40C0'!J31+'4000'!J30 -> 13574.37 | K31: =+'4050'!K31+'4060'!K31+'4070'!K31+'4080'!K31+'40A0'!K31+'40B0'!K31+'40C0'!K31+'4000'!K30 -> 15153.36 | L31: =+'4050'!L31+'4060'!L31+'4070'!L31+'4080'!L31+'40A0'!L31+'40B0'!L31+'40C0'!L31+'4000'!L30 -> 19042.64 | ... P31: =+'4050'!P31+'4060'!P31+'4070'!P31+'4080'!P31+'40A0'!P31+'40B0'!P31+'40C0'!P31+'4000'!P30 -> 5916.32 | Q31: =SUM(E31:P31) -> 120449.23 | R31: 95262 | S31: =Q31/R31-1 -> 0.26439955 | T31: DW | U31: 2025 Business Plan grown 3%
D33: Building Maint.-Contractual | E33: =+'4050'!E33+'4060'!E33+'4070'!E33+'4080'!E33+'40A0'!E33+'40B0'!E33+'40C0'!E33+'4000'!E32 -> 10827 | F33: =+'4050'!F33+'4060'!F33+'4070'!F33+'4080'!F33+'40A0'!F33+'40B0'!F33+'40C0'!F33+'4000'!F32 -> 9540 | G33: =+'4050'!G33+'4060'!G33+'4070'!G33+'4080'!G33+'40A0'!G33+'40B0'!G33+'40C0'!G33+'4000'!G32 -> 31478 | H33: =+'4050'!H33+'4060'!H33+'4070'!H33+'4080'!H33+'40A0'!H33+'40B0'!H33+'40C0'!H33+'4000'!H32 -> 28878 | I33: =+'4050'!I33+'4060'!I33+'4070'!I33+'4080'!I33+'40A0'!I33+'40B0'!I33+'40C0'!I33+'4000'!I32 -> 9540 | J33: =+'4050'!J33+'4060'!J33+'4070'!J33+'4080'!J33+'40A0'!J33+'40B0'!J33+'40C0'!J33+'4000'!J32 -> 31460 | K33: =+'4050'!K33+'4060'!K33+'4070'!K33+'4080'!K33+'40A0'!K33+'40B0'!K33+'40C0'!K33+'4000'!K32 -> 10827 | L33: =+'4050'!L33+'4060'!L33+'4070'!L33+'4080'!L33+'40A0'!L33+'40B0'!L33+'40C0'!L33+'4000'!L32 -> 9540 | ... P33: =+'4050'!P33+'4060'!P33+'4070'!P33+'4080'!P33+'40A0'!P33+'40B0'!P33+'40C0'!P33+'4000'!P32 -> 24755 | Q33: =SUM(E33:P33) -> 236723 | T33: DW | U33: 2025 Business Plan grown 3%
D34: Building Maint.-Recurring | E34: =+'4050'!E34+'4060'!E34+'4070'!E34+'4080'!E34+'40A0'!E34+'40B0'!E34+'40C0'!E34+'4000'!E33 -> 18455 | F34: =+'4050'!F34+'4060'!F34+'4070'!F34+'4080'!F34+'40A0'!F34+'40B0'!F34+'40C0'!F34+'4000'!F33 -> 11925 | G34: =+'4050'!G34+'4060'!G34+'4070'!G34+'4080'!G34+'40A0'!G34+'40B0'!G34+'40C0'!G34+'4000'!G33 -> 12430 | H34: =+'4050'!H34+'4060'!H34+'4070'!H34+'4080'!H34+'40A0'!H34+'40B0'!H34+'40C0'!H34+'4000'!H33 -> 14425 | I34: =+'4050'!I34+'4060'!I34+'4070'!I34+'4080'!I34+'40A0'!I34+'40B0'!I34+'40C0'!I34+'4000'!I33 -> 24295 | J34: =+'4050'!J34+'4060'!J34+'4070'!J34+'4080'!J34+'40A0'!J34+'40B0'!J34+'40C0'!J34+'4000'!J33 -> 13980 | K34: =+'4050'!K34+'4060'!K34+'4070'!K34+'4080'!K34+'40A0'!K34+'40B0'!K34+'40C0'!K34+'4000'!K33 -> 26380 | L34: =+'4050'!L34+'4060'!L34+'4070'!L34+'4080'!L34+'40A0'!L34+'40B0'!L34+'40C0'!L34+'4000'!L33 -> 12105 | ... P34: =+'4050'!P34+'4060'!P34+'4070'!P34+'4080'!P34+'40A0'!P34+'40B0'!P34+'40C0'!P34+'4000'!P33 -> 12230 | Q34: =SUM(E34:P34) -> 189220 | T34: DW | U34: 2025 Business Plan grown 3%
D35: Building Maint.-Big Projects | E35: =+'4050'!E35+'4060'!E35+'4070'!E35+'4080'!E35+'40A0'!E35+'40B0'!E35+'40C0'!E35+'4000'!E34 -> 0 | F35: =+'4050'!F35+'4060'!F35+'4070'!F35+'4080'!F35+'40A0'!F35+'40B0'!F35+'40C0'!F35+'4000'!F34 -> 20300 | G35: =+'4050'!G35+'4060'!G35+'4070'!G35+'4080'!G35+'40A0'!G35+'40B0'!G35+'40C0'!G35+'4000'!G34 -> 15150 | H35: =+'4050'!H35+'4060'!H35+'4070'!H35+'4080'!H35+'40A0'!H35+'40B0'!H35+'40C0'!H35+'4000'!H34 -> 24205 | I35: =+'4050'!I35+'4060'!I35+'4070'!I35+'4080'!I35+'40A0'!I35+'40B0'!I35+'40C0'!I35+'4000'!I34 -> 10300 | J35: =+'4050'!J35+'4060'!J35+'4070'!J35+'4080'!J35+'40A0'!J35+'40B0'!J35+'40C0'!J35+'4000'!J34 -> 20600 | K35: =+'4050'!K35+'4060'!K35+'4070'!K35+'4080'!K35+'40A0'!K35+'40B0'!K35+'40C0'!K35+'4000'!K34 -> 15450 | L35: =+'4050'!L35+'4060'!L35+'4070'!L35+'4080'!L35+'40A0'!L35+'40B0'!L35+'40C0'!L35+'4000'!L34 -> 10300 | ... P35: =+'4050'!P35+'4060'!P35+'4070'!P35+'4080'!P35+'40A0'!P35+'40B0'!P35+'40C0'!P35+'4000'!P34 -> 0 | Q35: =SUM(E35:P35) -> 151755 | T35: DW | U35: Contingency for repairs including Paint halls/Replace Fire panel/LED lighting/window replacement
A36: 6220-8502 | C36: Building Maintenance | E36: =SUM(E33:E35) -> 29282 | F36: =SUM(F33:F35) -> 41765 | G36: =SUM(G33:G35) -> 59058 | H36: =SUM(H33:H35) -> 67508 | I36: =SUM(I33:I35) -> 44135 | J36: =SUM(J33:J35) -> 66040 | K36: =SUM(K33:K35) -> 52657 | L36: =SUM(L33:L35) -> 31945 | ... Q36: =SUM(Q33:Q35) -> 577698 | R36: 576052 | S36: =Q36/R36-1 -> 0.0028573809
A38: 6330-8502 | B38: (SC) | C38: Parking Lot Cleaning | E38: =+'4050'!E38+'4060'!E38+'4070'!E38+'4080'!E38+'40A0'!E38+'40B0'!E38+'40C0'!E38+'4000'!E37 -> 0 | F38: =+'4050'!F38+'4060'!F38+'4070'!F38+'4080'!F38+'40A0'!F38+'40B0'!F38+'40C0'!F38+'4000'!F37 -> 0 | G38: =+'4050'!G38+'4060'!G38+'4070'!G38+'4080'!G38+'40A0'!G38+'40B0'!G38+'40C0'!G38+'4000'!G37 -> 0 | H38: =+'4050'!H38+'4060'!H38+'4070'!H38+'4080'!H38+'40A0'!H38+'40B0'!H38+'40C0'!H38+'4000'!H37 -> 0 | I38: =+'4050'!I38+'4060'!I38+'4070'!I38+'4080'!I38+'40A0'!I38+'40B0'!I38+'40C0'!I38+'4000'!I37 -> 0 | J38: =+'4050'!J38+'4060'!J38+'4070'!J38+'4080'!J38+'40A0'!J38+'40B0'!J38+'40C0'!J38+'4000'!J37 -> 0 | K38: =+'4050'!K38+'4060'!K38+'4070'!K38+'4080'!K38+'40A0'!K38+'40B0'!K38+'40C0'!K38+'4000'!K37 -> 0 | L38: =+'4050'!L38+'4060'!L38+'4070'!L38+'4080'!L38+'40A0'!L38+'40B0'!L38+'40C0'!L38+'4000'!L37 -> 0 | ... P38: =+'4050'!P38+'4060'!P38+'4070'!P38+'4080'!P38+'40A0'!P38+'40B0'!P38+'40C0'!P38+'4000'!P37 -> 0 | Q38: =SUM(E38:P38) -> 0 | R38: 0
D40: Parking Lot Maint.-Contractual | E40: =+'4050'!E40+'4060'!E40+'4070'!E40+'4080'!E40+'40A0'!E40+'40B0'!E40+'40C0'!E40+'4000'!E39 -> 0 | F40: =+'4050'!F40+'4060'!F40+'4070'!F40+'4080'!F40+'40A0'!F40+'40B0'!F40+'40C0'!F40+'4000'!F39 -> 0 | G40: =+'4050'!G40+'4060'!G40+'4070'!G40+'4080'!G40+'40A0'!G40+'40B0'!G40+'40C0'!G40+'4000'!G39 -> 0 | H40: =+'4050'!H40+'4060'!H40+'4070'!H40+'4080'!H40+'40A0'!H40+'40B0'!H40+'40C0'!H40+'4000'!H39 -> 0 | I40: =+'4050'!I40+'4060'!I40+'4070'!I40+'4080'!I40+'40A0'!I40+'40B0'!I40+'40C0'!I40+'4000'!I39 -> 0 | J40: =+'4050'!J40+'4060'!J40+'4070'!J40+'4080'!J40+'40A0'!J40+'40B0'!J40+'40C0'!J40+'4000'!J39 -> 0 | K40: =+'4050'!K40+'4060'!K40+'4070'!K40+'4080'!K40+'40A0'!K40+'40B0'!K40+'40C0'!K40+'4000'!K39 -> 0 | L40: =+'4050'!L40+'4060'!L40+'4070'!L40+'4080'!L40+'40A0'!L40+'40B0'!L40+'40C0'!L40+'4000'!L39 -> 0 | ... P40: =+'4050'!P40+'4060'!P40+'4070'!P40+'4080'!P40+'40A0'!P40+'40B0'!P40+'40C0'!P40+'4000'!P39 -> 0 | Q40: =SUM(E40:P40) -> 0
D41: Parking Lot Maint.-Recurring | E41: =+'4050'!E41+'4060'!E41+'4070'!E41+'4080'!E41+'40A0'!E41+'40B0'!E41+'40C0'!E41+'4000'!E40 -> 5340.55 | F41: =+'4050'!F41+'4060'!F41+'4070'!F41+'4080'!F41+'40A0'!F41+'40B0'!F41+'40C0'!F41+'4000'!F40 -> 5546.55 | G41: =+'4050'!G41+'4060'!G41+'4070'!G41+'4080'!G41+'40A0'!G41+'40B0'!G41+'40C0'!G41+'4000'!G40 -> 9177.3 | H41: =+'4050'!H41+'4060'!H41+'4070'!H41+'4080'!H41+'40A0'!H41+'40B0'!H41+'40C0'!H41+'4000'!H40 -> 5340.55 | I41: =+'4050'!I41+'4060'!I41+'4070'!I41+'4080'!I41+'40A0'!I41+'40B0'!I41+'40C0'!I41+'4000'!I40 -> 5546.55 | J41: =+'4050'!J41+'4060'!J41+'4070'!J41+'4080'!J41+'40A0'!J41+'40B0'!J41+'40C0'!J41+'4000'!J40 -> 9177.3 | K41: =+'4050'!K41+'4060'!K41+'4070'!K41+'4080'!K41+'40A0'!K41+'40B0'!K41+'40C0'!K41+'4000'!K40 -> 5340.55 | L41: =+'4050'!L41+'4060'!L41+'4070'!L41+'4080'!L41+'40A0'!L41+'40B0'!L41+'40C0'!L41+'4000'!L40 -> 5546.55 | ... P41: =+'4050'!P41+'4060'!P41+'4070'!P41+'4080'!P41+'40A0'!P41+'40B0'!P41+'40C0'!P41+'4000'!P40 -> 9177.3 | Q41: =SUM(E41:P41) -> 80257.6 | T41: DW | U41: 2025 Business Plan grown 3%
D42: Parking Lot Maint.-Big Projects | E42: =+'4050'!E42+'4060'!E42+'4070'!E42+'4080'!E42+'40A0'!E42+'40B0'!E42+'40C0'!E42+'4000'!E41 -> 0 | F42: =+'4050'!F42+'4060'!F42+'4070'!F42+'4080'!F42+'40A0'!F42+'40B0'!F42+'40C0'!F42+'4000'!F41 -> 0 | G42: =+'4050'!G42+'4060'!G42+'4070'!G42+'4080'!G42+'40A0'!G42+'40B0'!G42+'40C0'!G42+'4000'!G41 -> 0 | H42: =+'4050'!H42+'4060'!H42+'4070'!H42+'4080'!H42+'40A0'!H42+'40B0'!H42+'40C0'!H42+'4000'!H41 -> 19905 | I42: =+'4050'!I42+'4060'!I42+'4070'!I42+'4080'!I42+'40A0'!I42+'40B0'!I42+'40C0'!I42+'4000'!I41 -> 20000 | J42: =+'4050'!J42+'4060'!J42+'4070'!J42+'4080'!J42+'40A0'!J42+'40B0'!J42+'40C0'!J42+'4000'!J41 -> 10300 | K42: =+'4050'!K42+'4060'!K42+'4070'!K42+'4080'!K42+'40A0'!K42+'40B0'!K42+'40C0'!K42+'4000'!K41 -> 12360 | L42: =+'4050'!L42+'4060'!L42+'4070'!L42+'4080'!L42+'40A0'!L42+'40B0'!L42+'40C0'!L42+'4000'!L41 -> 12360 | ... P42: =+'4050'!P42+'4060'!P42+'4070'!P42+'4080'!P42+'40A0'!P42+'40B0'!P42+'40C0'!P42+'4000'!P41 -> 0 | Q42: =SUM(E42:P42) -> 114830 | T42: DW | U42: Includes asphalt/pothole repairs and restriping
A43: 6360-8502 | C43: Parking Lot Maintenance | E43: =SUM(E40:E42) -> 5340.55 | F43: =SUM(F40:F42) -> 5546.55 | G43: =SUM(G40:G42) -> 9177.3 | H43: =SUM(H40:H42) -> 25245.55 | I43: =SUM(I40:I42) -> 25546.55 | J43: =SUM(J40:J42) -> 19477.3 | K43: =SUM(K40:K42) -> 17700.55 | L43: =SUM(L40:L42) -> 17906.55 | ... Q43: =SUM(Q40:Q42) -> 195087.6 | R43: 151867 | S43: =Q43/R43-1 -> 0.28459507
A45: 6370-8502 | C45: Snow Removal | E45: =+'4050'!E45+'4060'!E45+'4070'!E45+'4080'!E45+'40A0'!E45+'40B0'!E45+'40C0'!E45+'4000'!E44 -> 26393.75 | F45: =+'4050'!F45+'4060'!F45+'4070'!F45+'4080'!F45+'40A0'!F45+'40B0'!F45+'40C0'!F45+'4000'!F44 -> 26393.75 | G45: =+'4050'!G45+'4060'!G45+'4070'!G45+'4080'!G45+'40A0'!G45+'40B0'!G45+'40C0'!G45+'4000'!G44 -> 25363.75 | H45: =+'4050'!H45+'4060'!H45+'4070'!H45+'4080'!H45+'40A0'!H45+'40B0'!H45+'40C0'!H45+'4000'!H44 -> 0 | I45: =+'4050'!I45+'4060'!I45+'4070'!I45+'4080'!I45+'40A0'!I45+'40B0'!I45+'40C0'!I45+'4000'!I44 -> 0 | J45: =+'4050'!J45+'4060'!J45+'4070'!J45+'4080'!J45+'40A0'!J45+'40B0'!J45+'40C0'!J45+'4000'!J44 -> 0 | K45: =+'4050'!K45+'4060'!K45+'4070'!K45+'4080'!K45+'40A0'!K45+'40B0'!K45+'40C0'!K45+'4000'!K44 -> 0 | L45: =+'4050'!L45+'4060'!L45+'4070'!L45+'4080'!L45+'40A0'!L45+'40B0'!L45+'40C0'!L45+'4000'!L44 -> 0 | ... P45: =+'4050'!P45+'4060'!P45+'4070'!P45+'4080'!P45+'40A0'!P45+'40B0'!P45+'40C0'!P45+'4000'!P44 -> 25878.75 | Q45: =SUM(E45:P45) -> 110210 | R45: 79322 | S45: =Q45/R45-1 -> 0.38940017 | T45: DW | U45: 2025 Business Plan grown 3%
D47: Landscaping-Contractual | E47: =+'4050'!E47+'4060'!E47+'4070'!E47+'4080'!E47+'40A0'!E47+'40B0'!E47+'40C0'!E47+'4000'!E46 -> 0 | F47: =+'4050'!F47+'4060'!F47+'4070'!F47+'4080'!F47+'40A0'!F47+'40B0'!F47+'40C0'!F47+'4000'!F46 -> 0 | G47: =+'4050'!G47+'4060'!G47+'4070'!G47+'4080'!G47+'40A0'!G47+'40B0'!G47+'40C0'!G47+'4000'!G46 -> 10547.803 | H47: =+'4050'!H47+'4060'!H47+'4070'!H47+'4080'!H47+'40A0'!H47+'40B0'!H47+'40C0'!H47+'4000'!H46 -> 10547.803 | I47: =+'4050'!I47+'4060'!I47+'4070'!I47+'4080'!I47+'40A0'!I47+'40B0'!I47+'40C0'!I47+'4000'!I46 -> 10547.803 | J47: =+'4050'!J47+'4060'!J47+'4070'!J47+'4080'!J47+'40A0'!J47+'40B0'!J47+'40C0'!J47+'4000'!J46 -> 10547.803 | K47: =+'4050'!K47+'4060'!K47+'4070'!K47+'4080'!K47+'40A0'!K47+'40B0'!K47+'40C0'!K47+'4000'!K46 -> 10547.803 | L47: =+'4050'!L47+'4060'!L47+'4070'!L47+'4080'!L47+'40A0'!L47+'40B0'!L47+'40C0'!L47+'4000'!L46 -> 10547.803 | ... P47: =+'4050'!P47+'4060'!P47+'4070'!P47+'4080'!P47+'40A0'!P47+'40B0'!P47+'40C0'!P47+'4000'!P46 -> 0 | Q47: =SUM(E47:P47) -> 94930.226 | T47: DW | U47: 2025 Business Plan grown 3%
D48: Landscaping-Recurring | E48: =+'4050'!E48+'4060'!E48+'4070'!E48+'4080'!E48+'40A0'!E48+'40B0'!E48+'40C0'!E48+'4000'!E47 -> 0 | F48: =+'4050'!F48+'4060'!F48+'4070'!F48+'4080'!F48+'40A0'!F48+'40B0'!F48+'40C0'!F48 -> 0 | G48: =+'4050'!G48+'4060'!H48+'4070'!G48+'4080'!G48+'40A0'!G48+'40B0'!G48+'40C0'!G48+'4000'!G47 -> 3476.25 | H48: =+'4050'!H48+'4060'!I48+'4070'!H48+'4080'!H48+'40A0'!H48+'40B0'!H48+'40C0'!H48+'4000'!H47 -> 5330.25 | I48: =+'4050'!I48+'4060'!J48+'4070'!I48+'4080'!I48+'40A0'!I48+'40B0'!I48+'40C0'!I48+'4000'!I47 -> 9244.25 | J48: =+'4050'!J48+'4060'!K48+'4070'!J48+'4080'!J48+'40A0'!J48+'40B0'!J48+'40C0'!J48+'4000'!J47 -> 3476.25 | K48: =+'4050'!K48+'4060'!L48+'4070'!K48+'4080'!K48+'40A0'!K48+'40B0'!K48+'40C0'!K48+'4000'!K47 -> 3476.25 | L48: =+'4050'!L48+'4060'!M48+'4070'!L48+'4080'!L48+'40A0'!L48+'40B0'!L48+'40C0'!L48+'4000'!L47 -> 3476.25 | M48: =+'4050'!M48+'4060'!M48+'4070'!M48+'4080'!M48+'40A0'!M48+'40B0'!M48+'40C0'!M48+'4000'!M47 -> 7081.25 | N48: =+'4050'!N48+'4060'!N48+'4070'!N48+'4080'!N48+'40A0'!N48+'40B0'!N48+'40C0'!N48+'4000'!N47 -> 7493.25 | O48: =+'4050'!O48+'4060'!O48+'4070'!O48+'4080'!O48+'40A0'!O48+'40B0'!O48+'40C0'!O48+'4000'!O47 -> 1287.5 | P48: =+'4050'!P48+'4060'!P48+'4070'!P48+'4080'!P48+'40A0'!P48+'40B0'!P48+'40C0'!P48+'4000'!P47 -> 0 | Q48: =SUM(E48:P48) -> 44341.5 | T48: DW | U48: 2025 Business Plan grown 3%
D49: Landscaping-Big Projects | E49: =+'4050'!E49+'4060'!E49+'4070'!E49+'4080'!E49+'40A0'!E49+'40B0'!E49+'40C0'!E49+'4000'!E48 -> 4166.6667 | F49: =+'4050'!F49+'4060'!F49+'4070'!F49+'4080'!F49+'40A0'!F49+'40B0'!F49+'40C0'!F49+'4000'!F48 -> 4166.6667 | G49: =+'4050'!G49+'4060'!G49+'4070'!G49+'4080'!G49+'40A0'!G49+'40B0'!G49+'40C0'!G49+'4000'!G48 -> 4166.6667 | H49: =+'4050'!H49+'4060'!H49+'4070'!H49+'4080'!H49+'40A0'!H49+'40B0'!H49+'40C0'!H49+'4000'!H48 -> 4166.6667 | I49: =+'4050'!I49+'4060'!I49+'4070'!I49+'4080'!I49+'40A0'!I49+'40B0'!I49+'40C0'!I49+'4000'!I48 -> 4166.6667 | J49: =+'4050'!J49+'4060'!J49+'4070'!J49+'4080'!J49+'40A0'!J49+'40B0'!J49+'40C0'!J49+'4000'!J48 -> 4166.6667 | K49: =+'4050'!K49+'4060'!K49+'4070'!K49+'4080'!K49+'40A0'!K49+'40B0'!K49+'40C0'!K49+'4000'!K48 -> 4166.6667 | L49: =+'4050'!L49+'4060'!L49+'4070'!L49+'4080'!L49+'40A0'!L49+'40B0'!L49+'40C0'!L49+'4000'!L48 -> 4166.6667 | ... P49: =+'4050'!P49+'4060'!P49+'4070'!P49+'4080'!P49+'40A0'!P49+'40B0'!P49+'40C0'!P49+'4000'!P48 -> 4166.6667 | Q49: =SUM(E49:P49) -> 50000 | T49: DW | U49: Fountain repairs
A50: 6380-8502 | C50: Landscaping | E50: =SUM(E47:E49) -> 4166.6667 | F50: =SUM(F47:F49) -> 4166.6667 | G50: =SUM(G47:G49) -> 18190.72 | H50: =SUM(H47:H49) -> 20044.72 | I50: =SUM(I47:I49) -> 23958.72 | J50: =SUM(J47:J49) -> 18190.72 | K50: =SUM(K47:K49) -> 18190.72 | L50: =SUM(L47:L49) -> 18190.72 | ... Q50: =SUM(Q47:Q49) -> 189271.73 | R50: 145803 | S50: =Q50/R50-1 -> 0.29813327
A52: 6350-8502 | C52: Security | E52: =+'4050'!E52+'4060'!E52+'4070'!E52+'4080'!E52+'40A0'!E52+'40B0'!E52+'40C0'!E52+'4000'!E51 -> 2112 | F52: =+'4050'!F52+'4060'!F52+'4070'!F52+'4080'!F52+'40A0'!F52+'40B0'!F52+'40C0'!F52+'4000'!F51 -> 2112 | G52: =+'4050'!G52+'4060'!G52+'4070'!G52+'4080'!G52+'40A0'!G52+'40B0'!G52+'40C0'!G52+'4000'!G51 -> 2112 | H52: =+'4050'!H52+'4060'!H52+'4070'!H52+'4080'!H52+'40A0'!H52+'40B0'!H52+'40C0'!H52+'4000'!H51 -> 2112 | I52: =+'4050'!I52+'4060'!I52+'4070'!I52+'4080'!I52+'40A0'!I52+'40B0'!I52+'40C0'!I52+'4000'!I51 -> 2112 | J52: =+'4050'!J52+'4060'!J52+'4070'!J52+'4080'!J52+'40A0'!J52+'40B0'!J52+'40C0'!J52+'4000'!J51 -> 2112 | K52: =+'4050'!K52+'4060'!K52+'4070'!K52+'4080'!K52+'40A0'!K52+'40B0'!K52+'40C0'!K52+'4000'!K51 -> 2112 | L52: =+'4050'!L52+'4060'!L52+'4070'!L52+'4080'!L52+'40A0'!L52+'40B0'!L52+'40C0'!L52+'4000'!L51 -> 2112 | ... P52: =+'4050'!P52+'4060'!P52+'4070'!P52+'4080'!P52+'40A0'!P52+'40B0'!P52+'40C0'!P52+'4000'!P51 -> 2112 | Q52: =SUM(E52:P52) -> 25344 | R52: 28451 | S52: =Q52/R52-1 -> -0.1092053 | U52: 2025 Business Plan grown 3%
A54: 6610-8502 | B54: (BP) | C54: Management Fee | E54: ='4050'!E54+'4060'!E54+'4070'!E54+'4080'!E54+'40A0'!E54+'40B0'!E54+'40C0'!E54+'4000'!E53 -> 21235 | F54: ='4050'!F54+'4060'!F54+'4070'!F54+'4080'!F54+'40A0'!F54+'40B0'!F54+'40C0'!F54+'4000'!F53 -> 21072 | G54: ='4050'!G54+'4060'!G54+'4070'!G54+'4080'!G54+'40A0'!G54+'40B0'!G54+'40C0'!G54+'4000'!G53 -> 21316 | H54: ='4050'!H54+'4060'!H54+'4070'!H54+'4080'!H54+'40A0'!H54+'40B0'!H54+'40C0'!H54+'4000'!H53 -> 21238 | I54: ='4050'!I54+'4060'!I54+'4070'!I54+'4080'!I54+'40A0'!I54+'40B0'!I54+'40C0'!I54+'4000'!I53 -> 21344 | J54: ='4050'!J54+'4060'!J54+'4070'!J54+'4080'!J54+'40A0'!J54+'40B0'!J54+'40C0'!J54+'4000'!J53 -> 21708 | K54: ='4050'!K54+'4060'!K54+'4070'!K54+'4080'!K54+'40A0'!K54+'40B0'!K54+'40C0'!K54+'4000'!K53 -> 21112 | L54: ='4050'!L54+'4060'!L54+'4070'!L54+'4080'!L54+'40A0'!L54+'40B0'!L54+'40C0'!L54+'4000'!L53 -> 21051 | ... P54: ='4050'!P54+'4060'!P54+'4070'!P54+'4080'!P54+'40A0'!P54+'40B0'!P54+'40C0'!P54+'4000'!P53 -> 20768 | Q54: =SUM(E54:P54) -> 253013 | R54: 255695 | S54: =Q54/R54-1 -> -0.010489059 | U54: 4% EGR for 5-8, 6% EGR for A-C
A56: 6270-8502 | C56: Trash Removal | E56: =+'4050'!E56+'4060'!E56+'4070'!E56+'4080'!E56+'40A0'!E56+'40B0'!E56+'40C0'!E56+'4000'!E55 -> 8538.7 | F56: =+'4050'!F56+'4060'!F56+'4070'!F56+'4080'!F56+'40A0'!F56+'40B0'!F56+'40C0'!F56+'4000'!F55 -> 8538.7 | G56: =+'4050'!G56+'4060'!G56+'4070'!G56+'4080'!G56+'40A0'!G56+'40B0'!G56+'40C0'!G56+'4000'!G55 -> 8538.7 | H56: =+'4050'!H56+'4060'!H56+'4070'!H56+'4080'!H56+'40A0'!H56+'40B0'!H56+'40C0'!H56+'4000'!H55 -> 8590.2 | I56: =+'4050'!I56+'4060'!I56+'4070'!I56+'4080'!I56+'40A0'!I56+'40B0'!I56+'40C0'!I56+'4000'!I55 -> 8538.7 | J56: =+'4050'!J56+'4060'!J56+'4070'!J56+'4080'!J56+'40A0'!J56+'40B0'!J56+'40C0'!J56+'4000'!J55 -> 11638.7 | K56: =+'4050'!K56+'4060'!K56+'4070'!K56+'4080'!K56+'40A0'!K56+'40B0'!K56+'40C0'!K56+'4000'!K55 -> 8538.7 | L56: =+'4050'!L56+'4060'!L56+'4070'!L56+'4080'!L56+'40A0'!L56+'40B0'!L56+'40C0'!L56+'4000'!L55 -> 8538.7 | ... P56: =+'4050'!P56+'4060'!P56+'4070'!P56+'4080'!P56+'40A0'!P56+'40B0'!P56+'40C0'!P56+'4000'!P55 -> 11638.7 | Q56: =SUM(E56:P56) -> 109367.4 | R56: 120560 | S56: =Q56/R56-1 -> -0.092838421 | U56: 2025 Business Plan grown 3%
A58: 6410-8502 | C58: Real Estate Taxes | E58: =+'4050'!E58+'4060'!E58+'4070'!E58+'4080'!E58+'40A0'!E58+'40B0'!E58+'40C0'!E58+'4000'!E57 -> 37458.058 | F58: =+'4050'!F58+'4060'!F58+'4070'!F58+'4080'!F58+'40A0'!F58+'40B0'!F58+'40C0'!F58+'4000'!F57 -> 37458.058 | G58: =+'4050'!G58+'4060'!G58+'4070'!G58+'4080'!G58+'40A0'!G58+'40B0'!G58+'40C0'!G58+'4000'!G57 -> 37458.058 | H58: =+'4050'!H58+'4060'!H58+'4070'!H58+'4080'!H58+'40A0'!H58+'40B0'!H58+'40C0'!H58+'4000'!H57 -> 37458.058 | I58: =+'4050'!I58+'4060'!I58+'4070'!I58+'4080'!I58+'40A0'!I58+'40B0'!I58+'40C0'!I58+'4000'!I57 -> 37458.058 | J58: =+'4050'!J58+'4060'!J58+'4070'!J58+'4080'!J58+'40A0'!J58+'40B0'!J58+'40C0'!J58+'4000'!J57 -> 37458.058 | K58: =+'4050'!K58+'4060'!K58+'4070'!K58+'4080'!K58+'40A0'!K58+'40B0'!K58+'40C0'!K58+'4000'!K57 -> 37458.058 | L58: =+'4050'!L58+'4060'!L58+'4070'!L58+'4080'!L58+'40A0'!L58+'40B0'!L58+'40C0'!L58+'4000'!L57 -> 37458.058 | ... P58: =+'4050'!P58+'4060'!P58+'4070'!P58+'4080'!P58+'40A0'!P58+'40B0'!P58+'40C0'!P58+'4000'!P57 -> 37458.058 | Q58: =SUM(E58:P58) -> 449496.69 | R58: 770524 | S58: =Q58/R58-1 -> -0.41663506
D60: Insurance-Liability | E60: =+'4050'!E60+'4060'!E60+'4070'!E60+'4080'!E60+'40A0'!E60+'40B0'!E60+'40C0'!E60+'4000'!E59 -> 10654 | F60: =+'4050'!F60+'4060'!F60+'4070'!F60+'4080'!F60+'40A0'!F60+'40B0'!F60+'40C0'!F60+'4000'!F59 -> 10654 | G60: =+'4050'!G60+'4060'!G60+'4070'!G60+'4080'!G60+'40A0'!G60+'40B0'!G60+'40C0'!G60+'4000'!G59 -> 10654 | H60: =+'4050'!H60+'4060'!H60+'4070'!H60+'4080'!H60+'40A0'!H60+'40B0'!H60+'40C0'!H60+'4000'!H59 -> 10654 | I60: =+'4050'!I60+'4060'!I60+'4070'!I60+'4080'!I60+'40A0'!I60+'40B0'!I60+'40C0'!I60+'4000'!I59 -> 10654 | J60: =+'4050'!J60+'4060'!J60+'4070'!J60+'4080'!J60+'40A0'!J60+'40B0'!J60+'40C0'!J60+'4000'!J59 -> 10654 | K60: =+'4050'!K60+'4060'!K60+'4070'!K60+'4080'!K60+'40A0'!K60+'40B0'!K60+'40C0'!K60+'4000'!K59 -> 10654 | L60: =+'4050'!L60+'4060'!L60+'4070'!L60+'4080'!L60+'40A0'!L60+'40B0'!L60+'40C0'!L60+'4000'!L59 -> 10654 | ... P60: =+'4050'!P60+'4060'!P60+'4070'!P60+'4080'!P60+'40A0'!P60+'40B0'!P60+'40C0'!P60+'4000'!P59 -> 10867.08 | Q60: =SUM(E60:P60) -> 128274.16
D61: Insurabce-Property | E61: =+'4050'!E61+'4060'!E61+'4070'!E61+'4080'!E61+'40A0'!E61+'40B0'!E61+'40C0'!E61+'4000'!E60 -> 7751 | F61: =+'4050'!F61+'4060'!F61+'4070'!F61+'4080'!F61+'40A0'!F61+'40B0'!F61+'40C0'!F61+'4000'!F60 -> 7751 | G61: =+'4050'!G61+'4060'!G61+'4070'!G61+'4080'!G61+'40A0'!G61+'40B0'!G61+'40C0'!G61+'4000'!G60 -> 7751 | H61: =+'4050'!H61+'4060'!H61+'4070'!H61+'4080'!H61+'40A0'!H61+'40B0'!H61+'40C0'!H61+'4000'!H60 -> 7751 | I61: =+'4050'!I61+'4060'!I61+'4070'!I61+'4080'!I61+'40A0'!I61+'40B0'!I61+'40C0'!I61+'4000'!I60 -> 7751 | J61: =+'4050'!J61+'4060'!J61+'4070'!J61+'4080'!J61+'40A0'!J61+'40B0'!J61+'40C0'!J61+'4000'!J60 -> 7751 | K61: =+'4050'!K61+'4060'!K61+'4070'!K61+'4080'!K61+'40A0'!K61+'40B0'!K61+'40C0'!K61+'4000'!K60 -> 7751 | L61: =+'4050'!L61+'4060'!L61+'4070'!L61+'4080'!L61+'40A0'!L61+'40B0'!L61+'40C0'!L61+'4000'!L60 -> 7751 | ... P61: =+'4050'!P61+'4060'!P61+'4070'!P61+'4080'!P61+'40A0'!P61+'40B0'!P61+'40C0'!P61+'4000'!P60 -> 7906.02 | Q61: =SUM(E61:P61) -> 93322.04
D62: Insurance-Other | E62: =+'4050'!E62+'4060'!E62+'4070'!E62+'4080'!E62+'40A0'!E62+'40B0'!E62+'40C0'!E62+'4000'!E61 -> 324 | F62: =+'4050'!F62+'4060'!F62+'4070'!F62+'4080'!F62+'40A0'!F62+'40B0'!F62+'40C0'!F62+'4000'!F61 -> 324 | G62: =+'4050'!G62+'4060'!G62+'4070'!G62+'4080'!G62+'40A0'!G62+'40B0'!G62+'40C0'!G62+'4000'!G61 -> 324 | H62: =+'4050'!H62+'4060'!H62+'4070'!H62+'4080'!H62+'40A0'!H62+'40B0'!H62+'40C0'!H62+'4000'!H61 -> 324 | I62: =+'4050'!I62+'4060'!I62+'4070'!I62+'4080'!I62+'40A0'!I62+'40B0'!I62+'40C0'!I62+'4000'!I61 -> 324 | J62: =+'4050'!J62+'4060'!J62+'4070'!J62+'4080'!J62+'40A0'!J62+'40B0'!J62+'40C0'!J62+'4000'!J61 -> 324 | K62: =+'4050'!K62+'4060'!K62+'4070'!K62+'4080'!K62+'40A0'!K62+'40B0'!K62+'40C0'!K62+'4000'!K61 -> 324 | L62: =+'4050'!L62+'4060'!L62+'4070'!L62+'4080'!L62+'40A0'!L62+'40B0'!L62+'40C0'!L62+'4000'!L61 -> 324 | ... P62: =+'4050'!P62+'4060'!P62+'4070'!P62+'4080'!P62+'40A0'!P62+'40B0'!P62+'40C0'!P62+'4000'!P61 -> 330.48 | Q62: =SUM(E62:P62) -> 3900.96
A63: 6510-8502 | C63: Insurance | E63: =SUM(E60:E62) -> 18729 | F63: =SUM(F60:F62) -> 18729 | G63: =SUM(G60:G62) -> 18729 | H63: =SUM(H60:H62) -> 18729 | I63: =SUM(I60:I62) -> 18729 | J63: =SUM(J60:J62) -> 18729 | K63: =SUM(K60:K62) -> 18729 | L63: =SUM(L60:L62) -> 18729 | ... Q63: =SUM(Q60:Q62) -> 225497.16 | R63: 225428 | S63: =Q63/R63-1 -> 0.00030679419
D65: Cleaning & Supplies | E65: =+'4050'!E65+'4060'!E65+'4070'!E65+'4080'!E65+'40A0'!E65+'40B0'!E65+'40C0'!E65+'4000'!E64 -> 40618.482 | F65: =+'4050'!F65+'4060'!F65+'4070'!F65+'4080'!F65+'40A0'!F65+'40B0'!F65+'40C0'!F65+'4000'!F64 -> 40706.88 | G65: =+'4050'!G65+'4060'!G65+'4070'!G65+'4080'!G65+'40A0'!G65+'40B0'!G65+'40C0'!G65+'4000'!G64 -> 40989.63 | H65: =+'4050'!H65+'4060'!H65+'4070'!H65+'4080'!H65+'40A0'!H65+'40B0'!H65+'40C0'!H65+'4000'!H64 -> 41748.196 | I65: =+'4050'!I65+'4060'!I65+'4070'!I65+'4080'!I65+'40A0'!I65+'40B0'!I65+'40C0'!I65+'4000'!I64 -> 41748.196 | J65: =+'4050'!J65+'4060'!J65+'4070'!J65+'4080'!J65+'40A0'!J65+'40B0'!J65+'40C0'!J65+'4000'!J64 -> 41748.196 | K65: =+'4050'!K65+'4060'!K65+'4070'!K65+'4080'!K65+'40A0'!K65+'40B0'!K65+'40C0'!K65+'4000'!K64 -> 41543.32 | L65: =+'4050'!L65+'4060'!L65+'4070'!L65+'4080'!L65+'40A0'!L65+'40B0'!L65+'40C0'!L65+'4000'!L64 -> 41543.32 | ... P65: =+'4050'!P65+'4060'!P65+'4070'!P65+'4080'!P65+'40A0'!P65+'40B0'!P65+'40C0'!P65+'4000'!P64 -> 40523.991 | Q65: =SUM(E65:P65) -> 495225.25 | T65: DW | U65: Based on occupancy. Includes cleaning, supplies, and porter fee.
D66: Cleaning & Supplies-Vacancies | E66: =+'4050'!E66+'4060'!E66+'4070'!E66+'4080'!E66+'40A0'!E66+'40B0'!E66+'40C0'!E66+'4000'!E65 -> 1022.315 | F66: =+'4050'!F66+'4060'!F66+'4070'!F66+'4080'!F66+'40A0'!F66+'40B0'!F66+'40C0'!F66+'4000'!F65 -> 1017.3747 | G66: =+'4050'!G66+'4060'!G66+'4070'!G66+'4080'!G66+'40A0'!G66+'40B0'!G66+'40C0'!G66+'4000'!G65 -> 1001.5727 | H66: =+'4050'!H66+'4060'!H66+'4070'!H66+'4080'!H66+'40A0'!H66+'40B0'!H66+'40C0'!H66+'4000'!H65 -> 959.179 | I66: =+'4050'!I66+'4060'!I66+'4070'!I66+'4080'!I66+'40A0'!I66+'40B0'!I66+'40C0'!I66+'4000'!I65 -> 959.179 | J66: =+'4050'!J66+'4060'!J66+'4070'!J66+'4080'!J66+'40A0'!J66+'40B0'!J66+'40C0'!J66+'4000'!J65 -> 959.179 | K66: =+'4050'!K66+'4060'!K66+'4070'!K66+'4080'!K66+'40A0'!K66+'40B0'!K66+'40C0'!K66+'4000'!K65 -> 970.62881 | L66: =+'4050'!L66+'4060'!L66+'4070'!L66+'4080'!L66+'40A0'!L66+'40B0'!L66+'40C0'!L66+'4000'!L65 -> 970.62881 | ... P66: =+'4050'!P66+'4060'!P66+'4070'!P66+'4080'!P66+'40A0'!P66+'40B0'!P66+'40C0'!P66+'4000'!P65 -> 1027.5958 | Q66: =SUM(E66:P66) -> 11831.67 | T66: DW | U66: Based on occupancy.
A67: 6250-8502 | B67: (BP) | C67: Cleaning & Supplies | E67: =SUM(E65:E66) -> 41640.797 | F67: =SUM(F65:F66) -> 41724.254 | G67: =SUM(G65:G66) -> 41991.203 | H67: =SUM(H65:H66) -> 42707.375 | I67: =SUM(I65:I66) -> 42707.375 | J67: =SUM(J65:J66) -> 42707.375 | K67: =SUM(K65:K66) -> 42513.949 | L67: =SUM(L65:L66) -> 42513.949 | ... Q67: =SUM(Q65:Q66) -> 507056.92 | R67: 464386 | S67: =Q67/R67-1 -> 0.091886742 | U67: Based on occupancy.
B69: (SC) | C69: Other | E69: =+'4050'!E69+'4060'!E69+'4070'!E69+'4080'!E69+'40A0'!E69+'40B0'!E69+'40C0'!E69+'4000'!E68 -> 0 | F69: =+'4050'!F69+'4060'!F69+'4070'!F69+'4080'!F69+'40A0'!F69+'40B0'!F69+'40C0'!F69+'4000'!F68 -> 0 | G69: =+'4050'!G69+'4060'!G69+'4070'!G69+'4080'!G69+'40A0'!G69+'40B0'!G69+'40C0'!G69+'4000'!G68 -> 0 | H69: =+'4050'!H69+'4060'!H69+'4070'!H69+'4080'!H69+'40A0'!H69+'40B0'!H69+'40C0'!H69+'4000'!H68 -> 0 | I69: =+'4050'!I69+'4060'!I69+'4070'!I69+'4080'!I69+'40A0'!I69+'40B0'!I69+'40C0'!I69+'4000'!I68 -> 0 | J69: =+'4050'!J69+'4060'!J69+'4070'!J69+'4080'!J69+'40A0'!J69+'40B0'!J69+'40C0'!J69+'4000'!J68 -> 0 | K69: =+'4050'!K69+'4060'!K69+'4070'!K69+'4080'!K69+'40A0'!K69+'40B0'!K69+'40C0'!K69+'4000'!K68 -> 0 | L69: =+'4050'!L69+'4060'!L69+'4070'!L69+'4080'!L69+'40A0'!L69+'40B0'!L69+'40C0'!L69+'4000'!L68 -> 0 | ... P69: =+'4050'!P69+'4060'!P69+'4070'!P69+'4080'!P69+'40A0'!P69+'40B0'!P69+'40C0'!P69+'4000'!P68 -> 0 | Q69: =SUM(E69:P69) -> 0 | R69: 0 | S69: =Q69/R69-1 -> #DIV/0!
C71: Total Reimbursable Expenses | E71: =+E27+E29+E31+E36+E38+E43+E45+E50+E52+E54+E56+E58+E63+E67+E69 -> 305670.76 | F71: =+F27+F29+F31+F36+F38+F43+F45+F50+F52+F54+F56+F58+F63+F67+F69 -> 309529.93 | G71: =+G27+G29+G31+G36+G38+G43+G45+G50+G52+G54+G56+G58+G63+G67+G69 -> 339921.34 | H71: =+H27+H29+H31+H36+H38+H43+H45+H50+H52+H54+H56+H58+H63+H67+H69 -> 338681.97 | I71: =+I27+I29+I31+I36+I38+I43+I45+I50+I52+I54+I56+I58+I63+I67+I69 -> 326913.22 | J71: =+J27+J29+J31+J36+J38+J43+J45+J50+J52+J54+J56+J58+J63+J67+J69 -> 350043.11 | K71: =+K27+K29+K31+K36+K38+K43+K45+K50+K52+K54+K56+K58+K63+K67+K69 -> 340861.92 | L71: =+L27+L29+L31+L36+L38+L43+L45+L50+L52+L54+L56+L58+L63+L67+L69 -> 321607.2 | ... R71: =+R27+R29+R31+R36+R38+R43+R45+R50+R52+R54+R56+R58+R63+R67+R69 -> 3949442 | S71: =Q71/R71-1 -> -0.0047488422
Q72: =+'4000'!Q70+'4050'!Q71+'4060'!Q71+'4070'!Q71+'4080'!Q71+'40A0'!Q71+'40B0'!Q71+'40C0'!Q71 -> 3930686.7
B73: Non-Reimbursable Expenses
A75: 5210-8501 | C75: Bad Debt | E75: =+'4050'!E75+'4060'!E75+'4070'!E75+'4080'!E75+'40A0'!E75+'40B0'!E75+'40C0'!E75+'4000'!E74 -> 0 | F75: =+'4050'!F75+'4060'!F75+'4070'!F75+'4080'!F75+'40A0'!F75+'40B0'!F75+'40C0'!F75+'4000'!F74 -> 0 | G75: =+'4050'!G75+'4060'!G75+'4070'!G75+'4080'!G75+'40A0'!G75+'40B0'!G75+'40C0'!G75+'4000'!G74 -> 0 | H75: =+'4050'!H75+'4060'!H75+'4070'!H75+'4080'!H75+'40A0'!H75+'40B0'!H75+'40C0'!H75+'4000'!H74 -> 0 | I75: =+'4050'!I75+'4060'!I75+'4070'!I75+'4080'!I75+'40A0'!I75+'40B0'!I75+'40C0'!I75+'4000'!I74 -> 0 | J75: =+'4050'!J75+'4060'!J75+'4070'!J75+'4080'!J75+'40A0'!J75+'40B0'!J75+'40C0'!J75+'4000'!J74 -> 0 | K75: =+'4050'!K75+'4060'!K75+'4070'!K75+'4080'!K75+'40A0'!K75+'40B0'!K75+'40C0'!K75+'4000'!K74 -> 0 | L75: =+'4050'!L75+'4060'!L75+'4070'!L75+'4080'!L75+'40A0'!L75+'40B0'!L75+'40C0'!L75+'4000'!L74 -> 0 | ... P75: =+'4050'!P75+'4060'!P75+'4070'!P75+'4080'!P75+'40A0'!P75+'40B0'!P75+'40C0'!P75+'4000'!P74 -> 0 | Q75: =SUM(E75:P75) -> 0 | R75: 0
A77: 6010-8501 | D77: Salaries & Wages | E77: =+'4050'!E77+'4060'!E77+'4070'!E77+'4080'!E77+'40A0'!E77+'40B0'!E77+'40C0'!E77+'4000'!E76 -> 10070.583 | F77: =+'4050'!F77+'4060'!F77+'4070'!F77+'4080'!F77+'40A0'!F77+'40B0'!F77+'40C0'!F77+'4000'!F76 -> 10070.583 | G77: =+'4050'!G77+'4060'!G77+'4070'!G77+'4080'!G77+'40A0'!G77+'40B0'!G77+'40C0'!G77+'4000'!G76 -> 10070.583 | H77: =+'4050'!H77+'4060'!H77+'4070'!H77+'4080'!H77+'40A0'!H77+'40B0'!H77+'40C0'!H77+'4000'!H76 -> 10070.583 | I77: =+'4050'!I77+'4060'!I77+'4070'!I77+'4080'!I77+'40A0'!I77+'40B0'!I77+'40C0'!I77+'4000'!I76 -> 10070.583 | J77: =+'4050'!J77+'4060'!J77+'4070'!J77+'4080'!J77+'40A0'!J77+'40B0'!J77+'40C0'!J77+'4000'!J76 -> 10070.583 | K77: =+'4050'!K77+'4060'!K77+'4070'!K77+'4080'!K77+'40A0'!K77+'40B0'!K77+'40C0'!K77+'4000'!K76 -> 10070.583 | L77: =+'4050'!L77+'4060'!L77+'4070'!L77+'4080'!L77+'40A0'!L77+'40B0'!L77+'40C0'!L77+'4000'!L76 -> 10070.583 | ... P77: =+'4050'!P77+'4060'!P77+'4070'!P77+'4080'!P77+'40A0'!P77+'40B0'!P77+'40C0'!P77+'4000'!P76 -> 10070.583 | Q77: =SUM(E77:P77) -> 120847 | U77: Based on 2026 Payroll Budget
A78: 6620-8501 | D78: Commissions-Internal Broker | E78: =+'4050'!E78+'4060'!E78+'4070'!E78+'4080'!E78+'40A0'!E78+'40B0'!E78+'40C0'!E78+'4000'!E77 -> 6365.4 | F78: =+'4050'!F78+'4060'!F78+'4070'!F78+'4080'!F78+'40A0'!F78+'40B0'!F78+'40C0'!F78+'4000'!F77 -> 0 | G78: =+'4050'!G78+'4060'!G78+'4070'!G78+'4080'!G78+'40A0'!G78+'40B0'!G78+'40C0'!G78+'4000'!G77 -> 0 | H78: =+'4050'!H78+'4060'!H78+'4070'!H78+'4080'!H78+'40A0'!H78+'40B0'!H78+'40C0'!H78+'4000'!H77 -> 6365.4 | I78: =+'4050'!I78+'4060'!I78+'4070'!I78+'4080'!I78+'40A0'!I78+'40B0'!I78+'40C0'!I78+'4000'!I77 -> 0 | J78: =+'4050'!J78+'4060'!J78+'4070'!J78+'4080'!J78+'40A0'!J78+'40B0'!J78+'40C0'!J78+'4000'!J77 -> 0 | K78: =+'4050'!K78+'4060'!K78+'4070'!K78+'4080'!K78+'40A0'!K78+'40B0'!K78+'40C0'!K78+'4000'!K77 -> 6365.4 | L78: =+'4050'!L78+'4060'!L78+'4070'!L78+'4080'!L78+'40A0'!L78+'40B0'!L78+'40C0'!L78+'4000'!L77 -> 0 | ... P78: =+'4050'!P78+'4060'!P78+'4070'!P78+'4080'!P78+'40A0'!P78+'40B0'!P78+'40C0'!P78+'4000'!P77 -> 0 | Q78: =SUM(E78:P78) -> 25461.6 | U78: Based on projected leasing assumptions
C79: Leasing Salaries and Commissions | E79: =SUM(E77:E78) -> 16435.983 | F79: =SUM(F77:F78) -> 10070.583 | G79: =SUM(G77:G78) -> 10070.583 | H79: =SUM(H77:H78) -> 16435.983 | I79: =SUM(I77:I78) -> 10070.583 | J79: =SUM(J77:J78) -> 10070.583 | K79: =SUM(K77:K78) -> 16435.983 | L79: =SUM(L77:L78) -> 10070.583 | ... Q79: =SUM(Q77:Q78) -> 146308.6 | R79: 119664 | S79: =Q79/R79-1 -> 0.22266179
A81: 6110-8501 | D81: Gas | E81: =+'4050'!E81+'4060'!E81+'4070'!E81+'4080'!E81+'40A0'!E81+'40B0'!E81+'40C0'!E81+'4000'!E80 -> 0 | F81: =+'4050'!F81+'4060'!F81+'4070'!F81+'4080'!F81+'40A0'!F81+'40B0'!F81+'40C0'!F81+'4000'!F80 -> 0 | G81: =+'4050'!G81+'4060'!G81+'4070'!G81+'4080'!G81+'40A0'!G81+'40B0'!G81+'40C0'!G81+'4000'!G80 -> 0 | H81: =+'4050'!H81+'4060'!H81+'4070'!H81+'4080'!H81+'40A0'!H81+'40B0'!H81+'40C0'!H81+'4000'!H80 -> 0 | I81: =+'4050'!I81+'4060'!I81+'4070'!I81+'4080'!I81+'40A0'!I81+'40B0'!I81+'40C0'!I81+'4000'!I80 -> 0 | J81: =+'4050'!J81+'4060'!J81+'4070'!J81+'4080'!J81+'40A0'!J81+'40B0'!J81+'40C0'!J81+'4000'!J80 -> 0 | K81: =+'4050'!K81+'4060'!K81+'4070'!K81+'4080'!K81+'40A0'!K81+'40B0'!K81+'40C0'!K81+'4000'!K80 -> 0 | L81: =+'4050'!L81+'4060'!L81+'4070'!L81+'4080'!L81+'40A0'!L81+'40B0'!L81+'40C0'!L81+'4000'!L80 -> 0 | ... P81: =+'4050'!P81+'4060'!P81+'4070'!P81+'4080'!P81+'40A0'!P81+'40B0'!P81+'40C0'!P81+'4000'!P80 -> 0 | Q81: =SUM(E81:P81) -> 0
A82: 6120-8501 | D82: Electric | E82: =+'4050'!E82+'4060'!E82+'4070'!E82+'4080'!E82+'40A0'!E82+'40B0'!E82+'40C0'!E82+'4000'!E81 -> 0 | F82: =+'4050'!F82+'4060'!F82+'4070'!F82+'4080'!F82+'40A0'!F82+'40B0'!F82+'40C0'!F82+'4000'!F81 -> 0 | G82: =+'4050'!G82+'4060'!G82+'4070'!G82+'4080'!G82+'40A0'!G82+'40B0'!G82+'40C0'!G82+'4000'!G81 -> 0 | H82: =+'4050'!H82+'4060'!H82+'4070'!H82+'4080'!H82+'40A0'!H82+'40B0'!H82+'40C0'!H82+'4000'!H81 -> 0 | I82: =+'4050'!I82+'4060'!I82+'4070'!I82+'4080'!I82+'40A0'!I82+'40B0'!I82+'40C0'!I82+'4000'!I81 -> 0 | J82: =+'4050'!J82+'4060'!J82+'4070'!J82+'4080'!J82+'40A0'!J82+'40B0'!J82+'40C0'!J82+'4000'!J81 -> 0 | K82: =+'4050'!K82+'4060'!K82+'4070'!K82+'4080'!K82+'40A0'!K82+'40B0'!K82+'40C0'!K82+'4000'!K81 -> 0 | L82: =+'4050'!L82+'4060'!L82+'4070'!L82+'4080'!L82+'40A0'!L82+'40B0'!L82+'40C0'!L82+'4000'!L81 -> 0 | ... P82: =+'4050'!P82+'4060'!P82+'4070'!P82+'4080'!P82+'40A0'!P82+'40B0'!P82+'40C0'!P82+'4000'!P81 -> 0 | Q82: =SUM(E82:P82) -> 0
A83: 6130-8501 | D83: Water & Sewer | E83: =+'4050'!E83+'4060'!E83+'4070'!E83+'4080'!E83+'40A0'!E83+'40B0'!E83+'40C0'!E83+'4000'!E82 -> 0 | F83: =+'4050'!F83+'4060'!F83+'4070'!F83+'4080'!F83+'40A0'!F83+'40B0'!F83+'40C0'!F83+'4000'!F82 -> 0 | G83: =+'4050'!G83+'4060'!G83+'4070'!G83+'4080'!G83+'40A0'!G83+'40B0'!G83+'40C0'!G83+'4000'!G82 -> 0 | H83: =+'4050'!H83+'4060'!H83+'4070'!H83+'4080'!H83+'40A0'!H83+'40B0'!H83+'40C0'!H83+'4000'!H82 -> 0 | I83: =+'4050'!I83+'4060'!I83+'4070'!I83+'4080'!I83+'40A0'!I83+'40B0'!I83+'40C0'!I83+'4000'!I82 -> 0 | J83: =+'4050'!J83+'4060'!J83+'4070'!J83+'4080'!J83+'40A0'!J83+'40B0'!J83+'40C0'!J83+'4000'!J82 -> 0 | K83: =+'4050'!K83+'4060'!K83+'4070'!K83+'4080'!K83+'40A0'!K83+'40B0'!K83+'40C0'!K83+'4000'!K82 -> 0 | L83: =+'4050'!L83+'4060'!L83+'4070'!L83+'4080'!L83+'40A0'!L83+'40B0'!L83+'40C0'!L83+'4000'!L82 -> 0 | ... P83: =+'4050'!P83+'4060'!P83+'4070'!P83+'4080'!P83+'40A0'!P83+'40B0'!P83+'40C0'!P83+'4000'!P82 -> 0 | Q83: =SUM(E83:P83) -> 0
C84: Utilities | E84: =SUM(E81:E83) -> 0 | F84: =SUM(F81:F83) -> 0 | G84: =SUM(G81:G83) -> 0 | H84: =SUM(H81:H83) -> 0 | I84: =SUM(I81:I83) -> 0 | J84: =SUM(J81:J83) -> 0 | K84: =SUM(K81:K83) -> 0 | L84: =SUM(L81:L83) -> 0 | ... Q84: =SUM(Q81:Q83) -> 0 | R84: 3737 | S84: =Q84/R84-1 -> -1
D86: Building Maint.-Recurring | E86: =+'4050'!E86+'4060'!E86+'4070'!E86+'4080'!E86+'40A0'!E86+'40B0'!E86+'40C0'!E86+'4000'!E85 -> 4269.35 | F86: =+'4050'!F86+'4060'!F86+'4070'!F86+'4080'!F86+'40A0'!F86+'40B0'!F86+'40C0'!F86+'4000'!F85 -> 4269.35 | G86: =+'4050'!G86+'4060'!G86+'4070'!G86+'4080'!G86+'40A0'!G86+'40B0'!G86+'40C0'!G86+'4000'!G85 -> 4269.35 | H86: =+'4050'!H86+'4060'!H86+'4070'!H86+'4080'!H86+'40A0'!H86+'40B0'!H86+'40C0'!H86+'4000'!H85 -> 4269.35 | I86: =+'4050'!I86+'4060'!I86+'4070'!I86+'4080'!I86+'40A0'!I86+'40B0'!I86+'40C0'!I86+'4000'!I85 -> 4423.85 | J86: =+'4050'!J86+'4060'!J86+'4070'!J86+'4080'!J86+'40A0'!J86+'40B0'!J86+'40C0'!J86+'4000'!J85 -> 4269.35 | K86: =+'4050'!K86+'4060'!K86+'4070'!K86+'4080'!K86+'40A0'!K86+'40B0'!K86+'40C0'!K86+'4000'!K85 -> 4269.35 | L86: =+'4050'!L86+'4060'!L86+'4070'!L86+'4080'!L86+'40A0'!L86+'40B0'!L86+'40C0'!L86+'4000'!L85 -> 4269.35 | ... P86: =+'4050'!P86+'4060'!P86+'4070'!P86+'4080'!P86+'40A0'!P86+'40B0'!P86+'40C0'!P86+'4000'!P85 -> 4269.35 | Q86: =SUM(E86:P86) -> 51386.7 | T86: DW
D87: Building Maint.-Big Projects | E87: =+'4050'!E87+'4060'!E87+'4070'!E87+'4080'!E87+'40A0'!E87+'40B0'!E87+'40C0'!E87+'4000'!E86 -> 0 | F87: =+'4050'!F87+'4060'!F87+'4070'!F87+'4080'!F87+'40A0'!F87+'40B0'!F87+'40C0'!F87+'4000'!F86 -> 0 | G87: =+'4050'!G87+'4060'!G87+'4070'!G87+'4080'!G87+'40A0'!G87+'40B0'!G87+'40C0'!G87+'4000'!G86 -> 0 | H87: =+'4050'!H87+'4060'!H87+'4070'!H87+'4080'!H87+'40A0'!H87+'40B0'!H87+'40C0'!H87+'4000'!H86 -> 0 | I87: =+'4050'!I87+'4060'!I87+'4070'!I87+'4080'!I87+'40A0'!I87+'40B0'!I87+'40C0'!I87+'4000'!I86 -> 0 | J87: =+'4050'!J87+'4060'!J87+'4070'!J87+'4080'!J87+'40A0'!J87+'40B0'!J87+'40C0'!J87+'4000'!J86 -> 0 | K87: =+'4050'!K87+'4060'!K87+'4070'!K87+'4080'!K87+'40A0'!K87+'40B0'!K87+'40C0'!K87+'4000'!K86 -> 0 | L87: =+'4050'!L87+'4060'!L87+'4070'!L87+'4080'!L87+'40A0'!L87+'40B0'!L87+'40C0'!L87+'4000'!L86 -> 0 | ... P87: =+'4050'!P87+'4060'!P87+'4070'!P87+'4080'!P87+'40A0'!P87+'40B0'!P87+'40C0'!P87+'4000'!P86 -> 0 | Q87: =SUM(E87:P87) -> 0
A88: 6220-8501 | C88: Building Maintenance | E88: =SUM(E86:E87) -> 4269.35 | F88: =SUM(F86:F87) -> 4269.35 | G88: =SUM(G86:G87) -> 4269.35 | H88: =SUM(H86:H87) -> 4269.35 | I88: =SUM(I86:I87) -> 4423.85 | J88: =SUM(J86:J87) -> 4269.35 | K88: =SUM(K86:K87) -> 4269.35 | L88: =SUM(L86:L87) -> 4269.35 | ... Q88: =SUM(Q86:Q87) -> 51386.7 | R88: 34657 | S88: =Q88/R88-1 -> 0.48272211 | U88: 2025 Business Plan grown 3%
A90: 6610-8501 | B90: (SC) | C90: Management fee | E90: ='4050'!E90+'4060'!E90+'4070'!E90+'4080'!E90+'40A0'!E90+'40B0'!E90+'40C0'!E90+'4000'!E53 -> 0 | F90: ='4050'!F90+'4060'!F90+'4070'!F90+'4080'!F90+'40A0'!F90+'40B0'!F90+'40C0'!F90+'4000'!F53 -> 0 | G90: ='4050'!G90+'4060'!G90+'4070'!G90+'4080'!G90+'40A0'!G90+'40B0'!G90+'40C0'!G90+'4000'!G53 -> 0 | H90: ='4050'!H90+'4060'!H90+'4070'!H90+'4080'!H90+'40A0'!H90+'40B0'!H90+'40C0'!H90+'4000'!H53 -> 0 | I90: ='4050'!I90+'4060'!I90+'4070'!I90+'4080'!I90+'40A0'!I90+'40B0'!I90+'40C0'!I90+'4000'!I53 -> 0 | J90: ='4050'!J90+'4060'!J90+'4070'!J90+'4080'!J90+'40A0'!J90+'40B0'!J90+'40C0'!J90+'4000'!J53 -> 0 | K90: ='4050'!K90+'4060'!K90+'4070'!K90+'4080'!K90+'40A0'!K90+'40B0'!K90+'40C0'!K90+'4000'!K53 -> 0 | L90: ='4050'!L90+'4060'!L90+'4070'!L90+'4080'!L90+'40A0'!L90+'40B0'!L90+'40C0'!L90+'4000'!L53 -> 0 | ... P90: ='4050'!P90+'4060'!P90+'4070'!P90+'4080'!P90+'40A0'!P90+'40B0'!P90+'40C0'!P90+'4000'!P53 -> 0 | Q90: =SUM(E90:P90) -> 0 | S90: =Q90/R90-1 -> #DIV/0!
S91: =Q91/R91-1 -> #DIV/0!
A92: 7110-8501 | C92: Marketing | E92: =+'4050'!E92+'4060'!E92+'4070'!E92+'4080'!E92+'40A0'!E92+'40B0'!E92+'40C0'!E92+'4000'!E91 -> 3863.25 | F92: =+'4050'!F92+'4060'!F92+'4070'!F92+'4080'!F92+'40A0'!F92+'40B0'!F92+'40C0'!F92+'4000'!F91 -> 3863.25 | G92: =+'4050'!G92+'4060'!G92+'4070'!G92+'4080'!G92+'40A0'!G92+'40B0'!G92+'40C0'!G92+'4000'!G91 -> 3863.25 | H92: =+'4050'!H92+'4060'!H92+'4070'!H92+'4080'!H92+'40A0'!H92+'40B0'!H92+'40C0'!H92+'4000'!H91 -> 3863.25 | I92: =+'4050'!I92+'4060'!I92+'4070'!I92+'4080'!I92+'40A0'!I92+'40B0'!I92+'40C0'!I92+'4000'!I91 -> 3863.25 | J92: =+'4050'!J92+'4060'!J92+'4070'!J92+'4080'!J92+'40A0'!J92+'40B0'!J92+'40C0'!J92+'4000'!J91 -> 3863.25 | K92: =+'4050'!K92+'4060'!K92+'4070'!K92+'4080'!K92+'40A0'!K92+'40B0'!K92+'40C0'!K92+'4000'!K91 -> 3863.25 | L92: =+'4050'!L92+'4060'!L92+'4070'!L92+'4080'!L92+'40A0'!L92+'40B0'!L92+'40C0'!L92+'4000'!L91 -> 3863.25 | ... P92: =+'4050'!P92+'4060'!P92+'4070'!P92+'4080'!P92+'40A0'!P92+'40B0'!P92+'40C0'!P92+'4000'!P91 -> 3863.25 | Q92: =SUM(E92:P92) -> 46359 | R92: 48216 | S92: =Q92/R92-1 -> -0.038514186 | U92: 2025 Business Plan grown 3%
A94: 8210-8501 | C94: Business Taxes | E94: =+'4050'!E94+'4060'!E94+'4070'!E94+'4080'!E94+'40A0'!E94+'40B0'!E94+'40C0'!E94+'4000'!E93 -> 0 | F94: =+'4050'!F94+'4060'!F94+'4070'!F94+'4080'!F94+'40A0'!F94+'40B0'!F94+'40C0'!F94+'4000'!F93 -> 0 | G94: =+'4050'!G94+'4060'!G94+'4070'!G94+'4080'!G94+'40A0'!G94+'40B0'!G94+'40C0'!G94+'4000'!G93 -> 0 | H94: =+'4050'!H94+'4060'!H94+'4070'!H94+'4080'!H94+'40A0'!H94+'40B0'!H94+'40C0'!H94+'4000'!H93 -> 13821.101 | I94: =+'4050'!I94+'4060'!I94+'4070'!I94+'4080'!I94+'40A0'!I94+'40B0'!I94+'40C0'!I94+'4000'!I93 -> 0 | J94: =+'4050'!J94+'4060'!J94+'4070'!J94+'4080'!J94+'40A0'!J94+'40B0'!J94+'40C0'!J94+'4000'!J93 -> 0 | K94: =+'4050'!K94+'4060'!K94+'4070'!K94+'4080'!K94+'40A0'!K94+'40B0'!K94+'40C0'!K94+'4000'!K93 -> 0 | L94: =+'4050'!L94+'4060'!L94+'4070'!L94+'4080'!L94+'40A0'!L94+'40B0'!L94+'40C0'!L94+'4000'!L93 -> 0 | ... P94: =+'4050'!P94+'4060'!P94+'4070'!P94+'4080'!P94+'40A0'!P94+'40B0'!P94+'40C0'!P94+'4000'!P93 -> 0 | Q94: =SUM(E94:P94) -> 13821.101 | R94: 0 | S94: =Q94/R94-1 -> #DIV/0! | U94: 2025 Business Plan grown 3%
A96: 8310-8501 | C96: Legal & Accounting | E96: =+'4050'!E96+'4060'!E96+'4070'!E96+'4080'!E96+'40A0'!E96+'40B0'!E96+'40C0'!E96+'4000'!E95 -> 3530.6667 | F96: =+'4050'!F96+'4060'!F96+'4070'!F96+'4080'!F96+'40A0'!F96+'40B0'!F96+'40C0'!F96+'4000'!F95 -> 3530.6667 | G96: =+'4050'!G96+'4060'!G96+'4070'!G96+'4080'!G96+'40A0'!G96+'40B0'!G96+'40C0'!G96+'4000'!G95 -> 3530.6667 | H96: =+'4050'!H96+'4060'!H96+'4070'!H96+'4080'!H96+'40A0'!H96+'40B0'!H96+'40C0'!H96+'4000'!H95 -> 3530.6667 | I96: =+'4050'!I96+'4060'!I96+'4070'!I96+'4080'!I96+'40A0'!I96+'40B0'!I96+'40C0'!I96+'4000'!I95 -> 3530.6667 | J96: =+'4050'!J96+'4060'!J96+'4070'!J96+'4080'!J96+'40A0'!J96+'40B0'!J96+'40C0'!J96+'4000'!J95 -> 3530.6667 | K96: =+'4050'!K96+'4060'!K96+'4070'!K96+'4080'!K96+'40A0'!K96+'40B0'!K96+'40C0'!K96+'4000'!K95 -> 3530.6667 | L96: =+'4050'!L96+'4060'!L96+'4070'!L96+'4080'!L96+'40A0'!L96+'40B0'!L96+'40C0'!L96+'4000'!L95 -> 3530.6667 | ... P96: =+'4050'!P96+'4060'!P96+'4070'!P96+'4080'!P96+'40A0'!P96+'40B0'!P96+'40C0'!P96+'4000'!P95 -> 3530.6667 | Q96: =SUM(E96:P96) -> 42368 | R96: 38233 | S96: =Q96/R96-1 -> 0.10815264 | U96: 2025 Business Plan grown 3%
A98: 8190-8501 | D98: Bank Fees | E98: =+'4000'!E97+'4050'!E98+'4060'!E98+'4070'!E98+'4080'!E98+'40A0'!E98+'40B0'!E98+'40C0'!E98 -> 159.65 | F98: =+'4000'!F97+'4050'!F98+'4060'!F98+'4070'!F98+'4080'!F98+'40A0'!F98+'40B0'!F98+'40C0'!F98 -> 159.65 | G98: =+'4000'!G97+'4050'!G98+'4060'!G98+'4070'!G98+'4080'!G98+'40A0'!G98+'40B0'!G98+'40C0'!G98 -> 159.65 | H98: =+'4000'!H97+'4050'!H98+'4060'!H98+'4070'!H98+'4080'!H98+'40A0'!H98+'40B0'!H98+'40C0'!H98 -> 159.65 | I98: =+'4000'!I97+'4050'!I98+'4060'!I98+'4070'!I98+'4080'!I98+'40A0'!I98+'40B0'!I98+'40C0'!I98 -> 159.65 | J98: =+'4000'!J97+'4050'!J98+'4060'!J98+'4070'!J98+'4080'!J98+'40A0'!J98+'40B0'!J98+'40C0'!J98 -> 159.65 | K98: =+'4000'!K97+'4050'!K98+'4060'!K98+'4070'!K98+'4080'!K98+'40A0'!K98+'40B0'!K98+'40C0'!K98 -> 159.65 | L98: =+'4000'!L97+'4050'!L98+'4060'!L98+'4070'!L98+'4080'!L98+'40A0'!L98+'40B0'!L98+'40C0'!L98 -> 159.65 | ... P98: =+'4000'!P97+'4050'!P98+'4060'!P98+'4070'!P98+'4080'!P98+'40A0'!P98+'40B0'!P98+'40C0'!P98 -> 159.65 | Q98: =SUM(E98:P98) -> 1915.8 | U98: 2025 Business Plan grown 3%
A99: 8930-8501 | D99: Office Supplies | E99: =+'4050'!E99+'4060'!E99+'4070'!E99+'4080'!E99+'40A0'!E99+'40B0'!E99+'40C0'!E99+'4000'!E98 -> 0 | F99: =+'4050'!F99+'4060'!F99+'4070'!F99+'4080'!F99+'40A0'!F99+'40B0'!F99+'40C0'!F99+'4000'!F98 -> 0 | G99: =+'4050'!G99+'4060'!G99+'4070'!G99+'4080'!G99+'40A0'!G99+'40B0'!G99+'40C0'!G99+'4000'!G98 -> 0 | H99: =+'4050'!H99+'4060'!H99+'4070'!H99+'4080'!H99+'40A0'!H99+'40B0'!H99+'40C0'!H99+'4000'!H98 -> 0 | I99: =+'4050'!I99+'4060'!I99+'4070'!I99+'4080'!I99+'40A0'!I99+'40B0'!I99+'40C0'!I99+'4000'!I98 -> 0 | J99: =+'4050'!J99+'4060'!J99+'4070'!J99+'4080'!J99+'40A0'!J99+'40B0'!J99+'40C0'!J99+'4000'!J98 -> 0 | K99: =+'4050'!K99+'4060'!K99+'4070'!K99+'4080'!K99+'40A0'!K99+'40B0'!K99+'40C0'!K99+'4000'!K98 -> 0 | L99: =+'4050'!L99+'4060'!L99+'4070'!L99+'4080'!L99+'40A0'!L99+'40B0'!L99+'40C0'!L99+'4000'!L98 -> 0 | ... P99: =+'4050'!P99+'4060'!P99+'4070'!P99+'4080'!P99+'40A0'!P99+'40B0'!P99+'40C0'!P99+'4000'!P98 -> 0 | Q99: =SUM(E99:P99) -> 0
A100: 8950-8501 | D100: Postage | E100: =+'4050'!E100+'4060'!E100+'4070'!E100+'4080'!E100+'40A0'!E100+'40B0'!E100+'40C0'!E100+'4000'!E99 -> 0 | F100: =+'4050'!F100+'4060'!F100+'4070'!F100+'4080'!F100+'40A0'!F100+'40B0'!F100+'40C0'!F100+'4000'!F99 -> 0 | G100: =+'4050'!G100+'4060'!G100+'4070'!G100+'4080'!G100+'40A0'!G100+'40B0'!G100+'40C0'!G100+'4000'!G99 -> 0 | H100: =+'4050'!H100+'4060'!H100+'4070'!H100+'4080'!H100+'40A0'!H100+'40B0'!H100+'40C0'!H100+'4000'!H99 -> 0 | I100: =+'4050'!I100+'4060'!I100+'4070'!I100+'4080'!I100+'40A0'!I100+'40B0'!I100+'40C0'!I100+'4000'!I99 -> 0 | J100: =+'4050'!J100+'4060'!J100+'4070'!J100+'4080'!J100+'40A0'!J100+'40B0'!J100+'40C0'!J100+'4000'!J99 -> 0 | K100: =+'4050'!K100+'4060'!K100+'4070'!K100+'4080'!K100+'40A0'!K100+'40B0'!K100+'40C0'!K100+'4000'!K99 -> 0 | L100: =+'4050'!L100+'4060'!L100+'4070'!L100+'4080'!L100+'40A0'!L100+'40B0'!L100+'40C0'!L100+'4000'!L99 -> 0 | ... P100: =+'4050'!P100+'4060'!P100+'4070'!P100+'4080'!P100+'40A0'!P100+'40B0'!P100+'40C0'!P100+'4000'!P99 -> 0 | Q100: =SUM(E100:P100) -> 0
A101: 8990-8501 | D101: Other G&A Expense | E101: =+'4050'!E101+'4060'!E101+'4070'!E101+'4080'!E101+'40A0'!E101+'40B0'!E101+'40C0'!E101+'4000'!E100 -> 154.5 | F101: =+'4050'!F101+'4060'!F101+'4070'!F101+'4080'!F101+'40A0'!F101+'40B0'!F101+'40C0'!F101+'4000'!F100 -> 154.5 | G101: =+'4050'!G101+'4060'!G101+'4070'!G101+'4080'!G101+'40A0'!G101+'40B0'!G101+'40C0'!G101+'4000'!G100 -> 154.5 | H101: =+'4050'!H101+'4060'!H101+'4070'!H101+'4080'!H101+'40A0'!H101+'40B0'!H101+'40C0'!H101+'4000'!H100 -> 154.5 | I101: =+'4050'!I101+'4060'!I101+'4070'!I101+'4080'!I101+'40A0'!I101+'40B0'!I101+'40C0'!I101+'4000'!I100 -> 154.5 | J101: =+'4050'!J101+'4060'!J101+'4070'!J101+'4080'!J101+'40A0'!J101+'40B0'!J101+'40C0'!J101+'4000'!J100 -> 154.5 | K101: =+'4050'!K101+'4060'!K101+'4070'!K101+'4080'!K101+'40A0'!K101+'40B0'!K101+'40C0'!K101+'4000'!K100 -> 154.5 | L101: =+'4050'!L101+'4060'!L101+'4070'!L101+'4080'!L101+'40A0'!L101+'40B0'!L101+'40C0'!L101+'4000'!L100 -> 154.5 | ... P101: =+'4050'!P101+'4060'!P101+'4070'!P101+'4080'!P101+'40A0'!P101+'40B0'!P101+'40C0'!P101+'4000'!P100 -> 154.5 | Q101: =SUM(E101:P101) -> 1854 | U101: 2025 Business Plan grown 3%
A102: 8990-9800 | D102: Other G&A-allocated from LIK | E102: =+'4050'!E102+'4060'!E102+'4070'!E102+'4080'!E102+'40A0'!E102+'40B0'!E102+'40C0'!E102+'4000'!E101 -> 7450 | F102: =+'4050'!F102+'4060'!F102+'4070'!F102+'4080'!F102+'40A0'!F102+'40B0'!F102+'40C0'!F102+'4000'!F101 -> 7450 | G102: =+'4050'!G102+'4060'!G102+'4070'!G102+'4080'!G102+'40A0'!G102+'40B0'!G102+'40C0'!G102+'4000'!G101 -> 7450 | H102: =+'4050'!H102+'4060'!H102+'4070'!H102+'4080'!H102+'40A0'!H102+'40B0'!H102+'40C0'!H102+'4000'!H101 -> 7450 | I102: =+'4050'!I102+'4060'!I102+'4070'!I102+'4080'!I102+'40A0'!I102+'40B0'!I102+'40C0'!I102+'4000'!I101 -> 7450 | J102: =+'4050'!J102+'4060'!J102+'4070'!J102+'4080'!J102+'40A0'!J102+'40B0'!J102+'40C0'!J102+'4000'!J101 -> 7450 | K102: =+'4050'!K102+'4060'!K102+'4070'!K102+'4080'!K102+'40A0'!K102+'40B0'!K102+'40C0'!K102+'4000'!K101 -> 7450 | L102: =+'4050'!L102+'4060'!L102+'4070'!L102+'4080'!L102+'40A0'!L102+'40B0'!L102+'40C0'!L102+'4000'!L101 -> 7450 | ... P102: =+'4050'!P102+'4060'!P102+'4070'!P102+'4080'!P102+'40A0'!P102+'40B0'!P102+'40C0'!P102+'4000'!P101 -> 7450 | Q102: =SUM(E102:P102) -> 89400 | U102: 2025 Business Plan grown 3%
C103: General & Administrative | E103: =SUM(E98:E102) -> 7764.15 | F103: =SUM(F98:F102) -> 7764.15 | G103: =SUM(G98:G102) -> 7764.15 | H103: =SUM(H98:H102) -> 7764.15 | I103: =SUM(I98:I102) -> 7764.15 | J103: =SUM(J98:J102) -> 7764.15 | K103: =SUM(K98:K102) -> 7764.15 | L103: =SUM(L98:L102) -> 7764.15 | ... Q103: =SUM(Q98:Q102) -> 93169.8 | R103: 98410 | S103: =Q103/R103-1 -> -0.053248654
C105: Total Non-Reimbursable Expenses | E105: =+E75+E79+E84+E88+E90+E92+E94+E96+E103 -> 35863.4 | F105: =+F75+F79+F84+F88+F90+F92+F94+F96+F103 -> 29498 | G105: =+G75+G79+G84+G88+G90+G92+G94+G96+G103 -> 29498 | H105: =+H75+H79+H84+H88+H90+H92+H94+H96+H103 -> 49684.501 | I105: =+I75+I79+I84+I88+I90+I92+I94+I96+I103 -> 29652.5 | J105: =+J75+J79+J84+J88+J90+J92+J94+J96+J103 -> 29498 | K105: =+K75+K79+K84+K88+K90+K92+K94+K96+K103 -> 35863.4 | L105: =+L75+L79+L84+L88+L90+L92+L94+L96+L103 -> 29498 | ... R105: =+R75+R79+R84+R88+R90+R92+R94+R96+R103 -> 342917 | S105: =Q105/R105-1 -> 0.14725488
Q106: =+'4050'!Q105+'4060'!Q105+'4070'!Q105+'4080'!Q105+'40A0'!Q105+'40B0'!Q105+'40C0'!Q105 -> 393413.2
Q107: =+Q105-Q106 -> 0
B108: TOTAL OPERATING EXPENSES | E108: =+E71+E105 -> 341534.16 | F108: =+F71+F105 -> 339027.93 | G108: =+G71+G105 -> 369419.34 | H108: =+H71+H105 -> 388366.47 | I108: =+I71+I105 -> 356565.72 | J108: =+J71+J105 -> 379541.11 | K108: =+K71+K105 -> 376725.32 | L108: =+L71+L105 -> 351105.2 | ... R108: =+R71+R105 -> 4292359 | S108: =Q108/R108-1 -> 0.0073947507
Q109: =+'4050'!Q107+'4060'!Q107+'4070'!Q107+'4080'!Q107+'40A0'!Q107+'40B0'!Q107+'40C0'!Q107 -> 4324099.9
B111: NET OPERATING INCOME | E111: =+E24-E108 -> 155113.02 | F111: =+F24-F108 -> 153157.16 | G111: =+G24-G108 -> 129097.19 | H111: =+H24-H108 -> 108722.89 | I111: =+I24-I108 -> 143390.14 | J111: =+J24-J108 -> 129494.55 | K111: =+K24-K108 -> 117219.29 | L111: =+L24-L108 -> 141342.52 | ... R111: =+R24-R108 -> 1695300 | S111: =Q111/R111-1 -> -0.05920311
Q112: =+'4000'!Q110+'4050'!Q109+'4060'!Q109+'4070'!Q109+'4080'!Q109+'40A0'!Q109+'40B0'!Q109+'40C0'!Q109 -> 1594933
A113: 1420-0000 | D113: Land Improvements | E113: =+'4050'!E111+'4060'!E111+'4070'!E111+'4080'!E111+'40A0'!E111+'40B0'!E111+'40C0'!E111+'4000'!E112 -> 0 | F113: =+'4050'!F111+'4060'!F111+'4070'!F111+'4080'!F111+'40A0'!F111+'40B0'!F111+'40C0'!F111+'4000'!F112 -> 0 | G113: =+'4050'!G111+'4060'!G111+'4070'!G111+'4080'!G111+'40A0'!G111+'40B0'!G111+'40C0'!G111+'4000'!G112 -> 0 | H113: =+'4050'!H111+'4060'!H111+'4070'!H111+'4080'!H111+'40A0'!H111+'40B0'!H111+'40C0'!H111+'4000'!H112 -> 0 | I113: =+'4050'!I111+'4060'!I111+'4070'!I111+'4080'!I111+'40A0'!I111+'40B0'!I111+'40C0'!I111+'4000'!I112 -> 0 | J113: =+'4050'!J111+'4060'!J111+'4070'!J111+'4080'!J111+'40A0'!J111+'40B0'!J111+'40C0'!J111+'4000'!J112 -> 0 | K113: =+'4050'!K111+'4060'!K111+'4070'!K111+'4080'!K111+'40A0'!K111+'40B0'!K111+'40C0'!K111+'4000'!K112 -> 0 | L113: =+'4050'!L111+'4060'!L111+'4070'!L111+'4080'!L111+'40A0'!L111+'40B0'!L111+'40C0'!L111+'4000'!L112 -> 0 | ... P113: =+'4050'!P111+'4060'!P111+'4070'!P111+'4080'!P111+'40A0'!P111+'40B0'!P111+'40C0'!P111+'4000'!P112 -> 0 | Q113: =SUM(E113:P113) -> 0
A114: 1430-0000 | D114: Buildings | E114: =+'4050'!E112+'4060'!E112+'4070'!E112+'4080'!E112+'40A0'!E112+'40B0'!E112+'40C0'!E112+'4000'!E113 -> 0 | F114: =+'4050'!F112+'4060'!F112+'4070'!F112+'4080'!F112+'40A0'!F112+'40B0'!F112+'40C0'!F112+'4000'!F113 -> 0 | G114: =+'4050'!G112+'4060'!G112+'4070'!G112+'4080'!G112+'40A0'!G112+'40B0'!G112+'40C0'!G112+'4000'!G113 -> 0 | H114: =+'4050'!H112+'4060'!H112+'4070'!H112+'4080'!H112+'40A0'!H112+'40B0'!H112+'40C0'!H112+'4000'!H113 -> 0 | I114: =+'4050'!I112+'4060'!I112+'4070'!I112+'4080'!I112+'40A0'!I112+'40B0'!I112+'40C0'!I112+'4000'!I113 -> 0 | J114: =+'4050'!J112+'4060'!J112+'4070'!J112+'4080'!J112+'40A0'!J112+'40B0'!J112+'40C0'!J112+'4000'!J113 -> 0 | K114: =+'4050'!K112+'4060'!K112+'4070'!K112+'4080'!K112+'40A0'!K112+'40B0'!K112+'40C0'!K112+'4000'!K113 -> 0 | L114: =+'4050'!L112+'4060'!L112+'4070'!L112+'4080'!L112+'40A0'!L112+'40B0'!L112+'40C0'!L112+'4000'!L113 -> 0 | ... P114: =+'4050'!P112+'4060'!P112+'4070'!P112+'4080'!P112+'40A0'!P112+'40B0'!P112+'40C0'!P112+'4000'!P113 -> 0 | Q114: =SUM(E114:P114) -> 0
A115: 1450-0000 | D115: Equipment | E115: =+'4050'!E113+'4060'!E113+'4070'!E113+'4080'!E113+'40A0'!E113+'40B0'!E113+'40C0'!E113+'4000'!E114 -> 0 | F115: =+'4050'!F113+'4060'!F113+'4070'!F113+'4080'!F113+'40A0'!F113+'40B0'!F113+'40C0'!F113+'4000'!F114 -> 0 | G115: =+'4050'!G113+'4060'!G113+'4070'!G113+'4080'!G113+'40A0'!G113+'40B0'!G113+'40C0'!G113+'4000'!G114 -> 0 | H115: =+'4050'!H113+'4060'!H113+'4070'!H113+'4080'!H113+'40A0'!H113+'40B0'!H113+'40C0'!H113+'4000'!H114 -> 0 | I115: =+'4050'!I113+'4060'!I113+'4070'!I113+'4080'!I113+'40A0'!I113+'40B0'!I113+'40C0'!I113+'4000'!I114 -> 0 | J115: =+'4050'!J113+'4060'!J113+'4070'!J113+'4080'!J113+'40A0'!J113+'40B0'!J113+'40C0'!J113+'4000'!J114 -> 0 | K115: =+'4050'!K113+'4060'!K113+'4070'!K113+'4080'!K113+'40A0'!K113+'40B0'!K113+'40C0'!K113+'4000'!K114 -> 0 | L115: =+'4050'!L113+'4060'!L113+'4070'!L113+'4080'!L113+'40A0'!L113+'40B0'!L113+'40C0'!L113+'4000'!L114 -> 0 | ... P115: =+'4050'!P113+'4060'!P113+'4070'!P113+'4080'!P113+'40A0'!P113+'40B0'!P113+'40C0'!P113+'4000'!P114 -> 0 | Q115: =SUM(E115:P115) -> 0
A116: 1980-8501 | D116: Capital Improvements | E116: =+'4050'!E114+'4060'!E114+'4070'!E114+'4080'!E114+'40A0'!E114+'40B0'!E114+'40C0'!E114+'4000'!E115 -> 0 | F116: =+'4050'!F114+'4060'!F114+'4070'!F114+'4080'!F114+'40A0'!F114+'40B0'!F114+'40C0'!F114+'4000'!F115 -> 0 | G116: =+'4050'!G114+'4060'!G114+'4070'!G114+'4080'!G114+'40A0'!G114+'40B0'!G114+'40C0'!G114+'4000'!G115 -> 0 | H116: =+'4050'!H114+'4060'!H114+'4070'!H114+'4080'!H114+'40A0'!H114+'40B0'!H114+'40C0'!H114+'4000'!H115 -> 0 | I116: =+'4050'!I114+'4060'!I114+'4070'!I114+'4080'!I114+'40A0'!I114+'40B0'!I114+'40C0'!I114+'4000'!I115 -> 0 | J116: =+'4050'!J114+'4060'!J114+'4070'!J114+'4080'!J114+'40A0'!J114+'40B0'!J114+'40C0'!J114+'4000'!J115 -> 0 | K116: =+'4050'!K114+'4060'!K114+'4070'!K114+'4080'!K114+'40A0'!K114+'40B0'!K114+'40C0'!K114+'4000'!K115 -> 0 | L116: =+'4050'!L114+'4060'!L114+'4070'!L114+'4080'!L114+'40A0'!L114+'40B0'!L114+'40C0'!L114+'4000'!L115 -> 0 | ... P116: =+'4050'!P114+'4060'!P114+'4070'!P114+'4080'!P114+'40A0'!P114+'40B0'!P114+'40C0'!P114+'4000'!P115 -> 0 | Q116: =SUM(E116:P116) -> 0
C117: Capital Improvements | E117: =SUM(E113:E116) -> 0 | F117: =SUM(F113:F116) -> 0 | G117: =SUM(G113:G116) -> 0 | H117: =SUM(H113:H116) -> 0 | I117: =SUM(I113:I116) -> 0 | J117: =SUM(J113:J116) -> 0 | K117: =SUM(K113:K116) -> 0 | L117: =SUM(L113:L116) -> 0 | ... Q117: =SUM(Q113:Q116) -> 0 | R117: 62000 | S117: =Q117/R117-1 -> -1
A119: 1440-0000 | C119: Tenant Improvements | E119: =+'4050'!E117+'4060'!E117+'4070'!E117+'4080'!E117+'40A0'!E117+'40B0'!E117+'40C0'!E117+'4000'!E118 -> 17804 | F119: =+'4050'!F117+'4060'!F117+'4070'!F117+'4080'!F117+'40A0'!F117+'40B0'!F117+'40C0'!F117+'4000'!F118 -> 639 | G119: =+'4050'!G117+'4060'!G117+'4070'!G117+'4080'!G117+'40A0'!G117+'40B0'!G117+'40C0'!G117+'4000'!G118 -> 0 | H119: =+'4050'!H117+'4060'!H117+'4070'!H117+'4080'!H117+'40A0'!H117+'40B0'!H117+'40C0'!H117+'4000'!H118 -> 32336 | I119: =+'4050'!I117+'4060'!I117+'4070'!I117+'4080'!I117+'40A0'!I117+'40B0'!I117+'40C0'!I117+'4000'!I118 -> 0 | J119: =+'4050'!J117+'4060'!J117+'4070'!J117+'4080'!J117+'40A0'!J117+'40B0'!J117+'40C0'!J117+'4000'!J118 -> 0 | K119: =+'4050'!K117+'4060'!K117+'4070'!K117+'4080'!K117+'40A0'!K117+'40B0'!K117+'40C0'!K117+'4000'!K118 -> 7226 | L119: =+'4050'!L117+'4060'!L117+'4070'!L117+'4080'!L117+'40A0'!L117+'40B0'!L117+'40C0'!L117+'4000'!L118 -> 3294 | ... P119: =+'4050'!P117+'4060'!P117+'4070'!P117+'4080'!P117+'40A0'!P117+'40B0'!P117+'40C0'!P117+'4000'!P118 -> 2622 | Q119: =SUM(E119:P119) -> 86157 | R119: 86764 | S119: =Q119/R119-1 -> -0.0069959891 | U119: Based on projected leasing assumptions
A121: 1940-8501 | D121: Deferred Marketing | E121: =+'4050'!E119+'4060'!E119+'4070'!E119+'4080'!E119+'40A0'!E119+'40B0'!E119+'40C0'!E119+'4000'!E120 -> 0 | F121: =+'4050'!F119+'4060'!F119+'4070'!F119+'4080'!F119+'40A0'!F119+'40B0'!F119+'40C0'!F119+'4000'!F120 -> 0 | G121: =+'4050'!G119+'4060'!G119+'4070'!G119+'4080'!G119+'40A0'!G119+'40B0'!G119+'40C0'!G119+'4000'!G120 -> 0 | H121: =+'4050'!H119+'4060'!H119+'4070'!H119+'4080'!H119+'40A0'!H119+'40B0'!H119+'40C0'!H119+'4000'!H120 -> 0 | I121: =+'4050'!I119+'4060'!I119+'4070'!I119+'4080'!I119+'40A0'!I119+'40B0'!I119+'40C0'!I119+'4000'!I120 -> 0 | J121: =+'4050'!J119+'4060'!J119+'4070'!J119+'4080'!J119+'40A0'!J119+'40B0'!J119+'40C0'!J119+'4000'!J120 -> 0 | K121: =+'4050'!K119+'4060'!K119+'4070'!K119+'4080'!K119+'40A0'!K119+'40B0'!K119+'40C0'!K119+'4000'!K120 -> 0 | L121: =+'4050'!L119+'4060'!L119+'4070'!L119+'4080'!L119+'40A0'!L119+'40B0'!L119+'40C0'!L119+'4000'!L120 -> 0 | ... P121: =+'4050'!P119+'4060'!P119+'4070'!P119+'4080'!P119+'40A0'!P119+'40B0'!P119+'40C0'!P119+'4000'!P120 -> 0 | Q121: =SUM(E121:P121) -> 0
A122: 1940-8501 | D122: Outside Leasing Commissions | E122: =+'4050'!E120+'4060'!E120+'4070'!E120+'4080'!E120+'40A0'!E120+'40B0'!E120+'40C0'!E120+'4000'!E121 -> 66037.71 | F122: =+'4050'!F120+'4060'!F120+'4070'!F120+'4080'!F120+'40A0'!F120+'40B0'!F120+'40C0'!F120+'4000'!F121 -> 670.95 | G122: =+'4050'!G120+'4060'!G120+'4070'!G120+'4080'!G120+'40A0'!G120+'40B0'!G120+'40C0'!G120+'4000'!G121 -> 0 | H122: =+'4050'!H120+'4060'!H120+'4070'!H120+'4080'!H120+'40A0'!H120+'40B0'!H120+'40C0'!H120+'4000'!H121 -> 11432.43 | I122: =+'4050'!I120+'4060'!I120+'4070'!I120+'4080'!I120+'40A0'!I120+'40B0'!I120+'40C0'!I120+'4000'!I121 -> 0 | J122: =+'4050'!J120+'4060'!J120+'4070'!J120+'4080'!J120+'40A0'!J120+'40B0'!J120+'40C0'!J120+'4000'!J121 -> 0 | K122: =+'4050'!K120+'4060'!K120+'4070'!K120+'4080'!K120+'40A0'!K120+'40B0'!K120+'40C0'!K120+'4000'!K121 -> 16694.88 | L122: =+'4050'!L120+'4060'!L120+'4070'!L120+'4080'!L120+'40A0'!L120+'40B0'!L120+'40C0'!L120+'4000'!L121 -> 0 | ... P122: =+'4050'!P120+'4060'!P120+'4070'!P120+'4080'!P120+'40A0'!P120+'40B0'!P120+'40C0'!P120+'4000'!P121 -> 0 | Q122: =SUM(E122:P122) -> 94835.97 | U122: Based on projected leasing assumptions
C123: Outside Leasing Commissions | E123: =SUM(E121:E122) -> 66037.71 | F123: =SUM(F121:F122) -> 670.95 | G123: =SUM(G121:G122) -> 0 | H123: =SUM(H121:H122) -> 11432.43 | I123: =SUM(I121:I122) -> 0 | J123: =SUM(J121:J122) -> 0 | K123: =SUM(K121:K122) -> 16694.88 | L123: =SUM(L121:L122) -> 0 | ... Q123: =SUM(Q121:Q122) -> 94835.97 | R123: 32280 | S123: =Q123/R123-1 -> 1.9379173
B125: CASH FLOW BEFORE DEBT SERVICE | E125: =+E111-E117-E119-E123 -> 71271.312 | F125: =+F111-F117-F119-F123 -> 151847.21 | G125: =+G111-G117-G119-G123 -> 129097.19 | H125: =+H111-H117-H119-H123 -> 64954.463 | I125: =+I111-I117-I119-I123 -> 143390.14 | J125: =+J111-J117-J119-J123 -> 129494.55 | K125: =+K111-K117-K119-K123 -> 93298.412 | L125: =+L111-L117-L119-L123 -> 138048.52 | ... R125: =+R111-R117-R119-R123 -> 1514256 | S125: =Q125/R125-1 -> -0.066247717
B127: Debt Service
A128: 9210-8501 | D128: Interest | E128: =+'4050'!E126+'4060'!E126+'4070'!E126+'4080'!E126+'40A0'!E126+'40B0'!E126+'40C0'!E126+'4000'!E127 -> 93058 | F128: =+'4050'!F126+'4060'!F126+'4070'!F126+'4080'!F126+'40A0'!F126+'40B0'!F126+'40C0'!F126+'4000'!F127 -> 93058 | G128: =+'4050'!G126+'4060'!G126+'4070'!G126+'4080'!G126+'40A0'!G126+'40B0'!G126+'40C0'!G126+'4000'!G127 -> 93058 | H128: =+'4050'!H126+'4060'!H126+'4070'!H126+'4080'!H126+'40A0'!H126+'40B0'!H126+'40C0'!H126+'4000'!H127 -> 93058 | I128: =+'4050'!I126+'4060'!I126+'4070'!I126+'4080'!I126+'40A0'!I126+'40B0'!I126+'40C0'!I126+'4000'!I127 -> 93058 | J128: =+'4050'!J126+'4060'!J126+'4070'!J126+'4080'!J126+'40A0'!J126+'40B0'!J126+'40C0'!J126+'4000'!J127 -> 93058 | K128: =+'4050'!K126+'4060'!K126+'4070'!K126+'4080'!K126+'40A0'!K126+'40B0'!K126+'40C0'!K126+'4000'!K127 -> 93058 | L128: =+'4050'!L126+'4060'!L126+'4070'!L126+'4080'!L126+'40A0'!L126+'40B0'!L126+'40C0'!L126+'4000'!L127 -> 93058 | ... P128: =+'4050'!P126+'4060'!P126+'4070'!P126+'4080'!P126+'40A0'!P126+'40B0'!P126+'40C0'!P126+'4000'!P127 -> 93058 | Q128: =SUM(E128:P128) -> 1116696 | R128: 1121261 | S128: =Q128/R128-1 -> -0.004071309
A129: 2740-8501 | D129: Mortgage Amortization | E129: =+'4050'!E127+'4060'!E127+'4070'!E127+'4080'!E127+'40A0'!E127+'40B0'!E127+'40C0'!E127+'4000'!E128 -> 0 | F129: =+'4050'!F127+'4060'!F127+'4070'!F127+'4080'!F127+'40A0'!F127+'40B0'!F127+'40C0'!F127+'4000'!F128 -> 0 | G129: =+'4050'!G127+'4060'!G127+'4070'!G127+'4080'!G127+'40A0'!G127+'40B0'!G127+'40C0'!G127+'4000'!G128 -> 0 | H129: =+'4050'!H127+'4060'!H127+'4070'!H127+'4080'!H127+'40A0'!H127+'40B0'!H127+'40C0'!H127+'4000'!H128 -> 0 | I129: =+'4050'!I127+'4060'!I127+'4070'!I127+'4080'!I127+'40A0'!I127+'40B0'!I127+'40C0'!I127+'4000'!I128 -> 0 | J129: =+'4050'!J127+'4060'!J127+'4070'!J127+'4080'!J127+'40A0'!J127+'40B0'!J127+'40C0'!J127+'4000'!J128 -> 0 | K129: =+'4050'!K127+'4060'!K127+'4070'!K127+'4080'!K127+'40A0'!K127+'40B0'!K127+'40C0'!K127+'4000'!K128 -> 0 | L129: =+'4050'!L127+'4060'!L127+'4070'!L127+'4080'!L127+'40A0'!L127+'40B0'!L127+'40C0'!L127+'4000'!L128 -> 0 | ... P129: =+'4050'!P127+'4060'!P127+'4070'!P127+'4080'!P127+'40A0'!P127+'40B0'!P127+'40C0'!P127+'4000'!P128 -> 0 | Q129: =SUM(E129:P129) -> 0 | R129: 119241 | S129: =Q129/R129-1 -> -1
A130: 2740-0000 | D130: Loan Proceeds | Q130: =SUM(E130:P130) -> 0
C131: Total Debt Service | E131: =SUM(E128:E130) -> 93058 | F131: =SUM(F128:F130) -> 93058 | G131: =SUM(G128:G130) -> 93058 | H131: =SUM(H128:H130) -> 93058 | I131: =SUM(I128:I130) -> 93058 | J131: =SUM(J128:J130) -> 93058 | K131: =SUM(K128:K130) -> 93058 | L131: =SUM(L128:L130) -> 93058 | ... R131: =SUM(R128:R130) -> 1240502 | S131: =Q131/R131-1 -> -0.099803144
B134: CASH FLOW AFTER DEBT SERVICE | E134: =+E125-E131 -> -21786.688 | F134: =+F125-F131 -> 58789.207 | G134: =+G125-G131 -> 36039.194 | H134: =+H125-H131 -> -28103.537 | I134: =+I125-I131 -> 50332.139 | J134: =+J125-J131 -> 36436.549 | K134: =+K125-K131 -> 240.41239 | L134: =+L125-L131 -> 44990.517 | ... R134: =+R125-R131 -> 273754 | S134: =Q134/R134-1 -> 0.085806957
A138: {1} | B138: Operating Cash 12/31/2025 (Projected using 2025.10 Reprojections) with $104,581.24 RET escrow overage refunded to NI LLC.
D139: =290537+104581.24 -> 395118.24 | Q139: =+D139 -> 395118.24 | U139: from June-25 Reprojection
...

Sheet 4000
B1: Unallocated Expenses-G&A, Interest | J1: =+'NI LLC-Consolidated'!J1 -> Operating Budget | Q1: ='NI LLC-Consolidated'!Q1 -> 46023
J2: ='NI LLC-Consolidated'!J2 -> Neshaminy Interplex LLC
Q3: =Q1 -> 46023
E4: Jan | F4: Feb | G4: Mar | H4: Apr | I4: May | J4: Jun | K4: Jul | L4: Aug | M4: Sep | N4: Oct | O4: Nov | P4: Dec | Q4: Total
D6: Occupancy %
B7: Revenues
A9: 4230-8501 | C9: Rental Income | Q9: =SUM(E9:P9) -> 0
A10: 4240-8501 | C10: Percentage Rents | Q10: =SUM(E10:P10) -> 0
A11: 4990-8501 | C11: Miscellaneous | Q11: =SUM(E11:P11) -> 0
A12: 9190-8501 | C12: Interest Income | Q12: =SUM(E12:P12) -> 0
C13: Total Rental and Other | E13: =SUM(E9:E12) -> 0 | F13: =SUM(F9:F12) -> 0 | G13: =SUM(G9:G12) -> 0 | H13: =SUM(H9:H12) -> 0 | I13: =SUM(I9:I12) -> 0 | J13: =SUM(J9:J12) -> 0 | K13: =SUM(K9:K12) -> 0 | L13: =SUM(L9:L12) -> 0 | ... Q13: =SUM(Q9:Q12) -> 0
B15: Reimbursements
A16: 4710-8502 | C16: Electric | Q16: =SUM(E16:P16) -> 0
A17: 4910-8502 | C17: Common Area Maintenance | Q17: =SUM(E17:P17) -> 0
A18: 4920-8502 | C18: Real Estate Taxes | Q18: =SUM(E18:P18) -> 0
A19: 4930-8502 | C19: Insurance | Q19: =SUM(E19:P19) -> 0
C21: Total Reimbursements | E21: =SUM(E16:E19) -> 0 | F21: =SUM(F16:F19) -> 0 | G21: =SUM(G16:G19) -> 0 | H21: =SUM(H16:H19) -> 0 | I21: =SUM(I16:I19) -> 0 | J21: =SUM(J16:J19) -> 0 | K21: =SUM(K16:K19) -> 0 | L21: =SUM(L16:L19) -> 0 | ... Q21: =SUM(Q16:Q19) -> 0
B23: TOTAL REVENUES | E23: =+E13+E21 -> 0 | F23: =+F13+F21 -> 0 | G23: =+G13+G21 -> 0 | H23: =+H13+H21 -> 0 | I23: =+I13+I21 -> 0 | J23: =+J13+J21 -> 0 | K23: =+K13+K21 -> 0 | L23: =+L13+L21 -> 0 | ... Q23: =+Q13+Q21 -> 0
B25: Reimbursable Expenses
A26: 6030-8502 | C26: Maintenance Salaries | Q26: =SUM(E26:P26) -> 0
A28: 6120-8502 | C28: Electric | Q28: =SUM(E28:P28) -> 0
A30: 6130-8502 | C30: Water & Sewer | Q30: =SUM(E30:P30) -> 0
D32: Building Maint.-Contractual | Q32: =SUM(E32:P32) -> 0
D33: Building Maint.-Recurring | Q33: =SUM(E33:P33) -> 0
D34: Building Maint.-Big Projects | Q34: =SUM(E34:P34) -> 0
A35: 6220-8502 | C35: Building Maintenance | E35: =SUM(E32:E34) -> 0 | F35: =SUM(F32:F34) -> 0 | G35: =SUM(G32:G34) -> 0 | H35: =SUM(H32:H34) -> 0 | I35: =SUM(I32:I34) -> 0 | J35: =SUM(J32:J34) -> 0 | K35: =SUM(K32:K34) -> 0 | L35: =SUM(L32:L34) -> 0 | ... Q35: =SUM(Q32:Q34) -> 0
A37: 6330-8502 | B37: (SC) | C37: Parking Lot Cleaning | Q37: =SUM(E37:P37) -> 0
D39: Parking Lot Maint.-Contractual | Q39: =SUM(E39:P39) -> 0
D40: Parking Lot Maint.-Recurring | Q40: =SUM(E40:P40) -> 0
D41: Parking Lot Maint.-Big Projects | Q41: =SUM(E41:P41) -> 0
A42: 6360-8502 | C42: Parking Lot Maintenance | E42: =SUM(E39:E41) -> 0 | F42: =SUM(F39:F41) -> 0 | G42: =SUM(G39:G41) -> 0 | H42: =SUM(H39:H41) -> 0 | I42: =SUM(I39:I41) -> 0 | J42: =SUM(J39:J41) -> 0 | K42: =SUM(K39:K41) -> 0 | L42: =SUM(L39:L41) -> 0 | ... Q42: =SUM(Q39:Q41) -> 0
A44: 6370-8502 | C44: Snow Removal | Q44: =SUM(E44:P44) -> 0
D46: Landscaping-Contractual | Q46: =SUM(E46:P46) -> 0
D47: Landscaping-Recurring | Q47: =SUM(E47:P47) -> 0
D48: Landscaping-Big Projects | Q48: =SUM(E48:P48) -> 0
A49: 6380-8502 | C49: Landscaping | E49: =SUM(E46:E48) -> 0 | F49: =SUM(F46:F48) -> 0 | G49: =SUM(G46:G48) -> 0 | H49: =SUM(H46:H48) -> 0 | I49: =SUM(I46:I48) -> 0 | J49: =SUM(J46:J48) -> 0 | K49: =SUM(K46:K48) -> 0 | L49: =SUM(L46:L48) -> 0 | ... Q49: =SUM(Q46:Q48) -> 0
A51: 6350-8502 | C51: Security | Q51: =SUM(E51:P51) -> 0
A53: 6610-8502 | B53: (BP) | C53: Management Fee | E53: =ROUND(E$23*0.04,0) -> 0 | F53: =ROUND(F$23*0.04,0) -> 0 | G53: =ROUND(G$23*0.04,0) -> 0 | H53: =ROUND(H$23*0.04,0) -> 0 | I53: =ROUND(I$23*0.04,0) -> 0 | J53: =ROUND(J$23*0.04,0) -> 0 | K53: =ROUND(K$23*0.04,0) -> 0 | L53: =ROUND(L$23*0.04,0) -> 0 | ... P53: =ROUND(P$23*0.04,0) -> 0 | Q53: =SUM(E53:P53) -> 0
A55: 6270-8502 | C55: Trash Removal | Q55: =SUM(E55:P55) -> 0
A57: 6410-8502 | C57: Real Estate Taxes | Q57: =SUM(E57:P57) -> 0
D59: Insurance-Liability | Q59: =SUM(E59:P59) -> 0
D60: Insurabce-Property | Q60: =SUM(E60:P60) -> 0
D61: Insurance-Other | Q61: =SUM(E61:P61) -> 0
A62: 6510-8502 | C62: Insurance | E62: =SUM(E59:E61) -> 0 | F62: =SUM(F59:F61) -> 0 | G62: =SUM(G59:G61) -> 0 | H62: =SUM(H59:H61) -> 0 | I62: =SUM(I59:I61) -> 0 | J62: =SUM(J59:J61) -> 0 | K62: =SUM(K59:K61) -> 0 | L62: =SUM(L59:L61) -> 0 | ... Q62: =SUM(Q59:Q61) -> 0
D64: Cleaning & Supplies | Q64: =SUM(E64:P64) -> 0
D65: Cleaning & Supplies-Vacancies | Q65: =SUM(E65:P65) -> 0
A66: 6250-8502 | B66: (BP) | C66: Cleaning & Supplies | E66: =SUM(E64:E65) -> 0 | F66: =SUM(F64:F65) -> 0 | G66: =SUM(G64:G65) -> 0 | H66: =SUM(H64:H65) -> 0 | I66: =SUM(I64:I65) -> 0 | J66: =SUM(J64:J65) -> 0 | K66: =SUM(K64:K65) -> 0 | L66: =SUM(L64:L65) -> 0 | ... Q66: =SUM(Q64:Q65) -> 0
B68: (SC) | C68: Other | E68: 0 | F68: 0 | G68: 0 | H68: 0 | I68: 0 | J68: 0 | K68: 0 | L68: 0 | M68: 0 | N68: 0 | O68: 0 | P68: 0 | Q68: =SUM(E68:P68) -> 0
C70: Total Reimbursable Expenses | E70: =+E26+E28+E30+E35+E37+E42+E44+E49+E51+E53+E55+E57+E62+E66+E68 -> 0 | F70: =+F26+F28+F30+F35+F37+F42+F44+F49+F51+F53+F55+F57+F62+F66+F68 -> 0 | G70: =+G26+G28+G30+G35+G37+G42+G44+G49+G51+G53+G55+G57+G62+G66+G68 -> 0 | H70: =+H26+H28+H30+H35+H37+H42+H44+H49+H51+H53+H55+H57+H62+H66+H68 -> 0 | I70: =+I26+I28+I30+I35+I37+I42+I44+I49+I51+I53+I55+I57+I62+I66+I68 -> 0 | J70: =+J26+J28+J30+J35+J37+J42+J44+J49+J51+J53+J55+J57+J62+J66+J68 -> 0 | K70: =+K26+K28+K30+K35+K37+K42+K44+K49+K51+K53+K55+K57+K62+K66+K68 -> 0 | L70: =+L26+L28+L30+L35+L37+L42+L44+L49+L51+L53+L55+L57+L62+L66+L68 -> 0 | ... Q70: =+Q26+Q28+Q30+Q35+Q37+Q42+Q44+Q49+Q51+Q53+Q55+Q57+Q62+Q66+Q68 -> 0
B72: Non-Reimbursable Expenses
A74: 5210-8501 | C74: Bad Debt | Q74: =SUM(E74:P74) -> 0
A76: 6010-8501 | D76: Salaries & Wages | Q76: =SUM(E76:P76) -> 0
A77: 6620-8501 | D77: Commissions-Internal Broker | Q77: =SUM(E77:P77) -> 0
C78: Leasing Salaries and Commissions | E78: =SUM(E76:E77) -> 0 | F78: =SUM(F76:F77) -> 0 | G78: =SUM(G76:G77) -> 0 | H78: =SUM(H76:H77) -> 0 | I78: =SUM(I76:I77) -> 0 | J78: =SUM(J76:J77) -> 0 | K78: =SUM(K76:K77) -> 0 | L78: =SUM(L76:L77) -> 0 | ... Q78: =SUM(Q76:Q77) -> 0
A80: 6110-8501 | D80: Gas | Q80: =SUM(E80:P80) -> 0
A81: 6120-8501 | D81: Electric | Q81: =SUM(E81:P81) -> 0
A82: 6130-8501 | D82: Water & Sewer | Q82: =SUM(E82:P82) -> 0
C83: Utilities | E83: =SUM(E80:E82) -> 0 | F83: =SUM(F80:F82) -> 0 | G83: =SUM(G80:G82) -> 0 | H83: =SUM(H80:H82) -> 0 | I83: =SUM(I80:I82) -> 0 | J83: =SUM(J80:J82) -> 0 | K83: =SUM(K80:K82) -> 0 | L83: =SUM(L80:L82) -> 0 | ... Q83: =SUM(Q80:Q82) -> 0
D85: Building Maint.-Recurring | Q85: =SUM(E85:P85) -> 0
D86: Building Maint.-Big Projects | Q86: =SUM(E86:P86) -> 0
A87: 6220-8501 | C87: Building Maintenance | E87: =SUM(E85:E86) -> 0 | F87: =SUM(F85:F86) -> 0 | G87: =SUM(G85:G86) -> 0 | H87: =SUM(H85:H86) -> 0 | I87: =SUM(I85:I86) -> 0 | J87: =SUM(J85:J86) -> 0 | K87: =SUM(K85:K86) -> 0 | L87: =SUM(L85:L86) -> 0 | ... Q87: =SUM(Q85:Q86) -> 0
A89: 6610-8501 | B89: (SC) | C89: Management fee | Q89: =SUM(E89:P89) -> 0
A91: 7110-8501 | C91: Marketing | Q91: =SUM(E91:P91) -> 0
A93: 8210-8501 | C93: Business Taxes | Q93: =SUM(E93:P93) -> 0
A95: 8310-8501 | C95: Legal & Accounting | Q95: =SUM(E95:P95) -> 0
A97: 8190-8501 | D97: Bank Fees | Q97: =SUM(E97:P97) -> 0
A98: 8930-8501 | D98: Office Supplies | Q98: =SUM(E98:P98) -> 0
A99: 8950-8501 | D99: Postage | Q99: =SUM(E99:P99) -> 0
A100: 8990-8501 | D100: Other G&A Expense | Q100: =SUM(E100:P100) -> 0
A101: 8990-9800 | D101: Other G&A-allocated from LIK | Q101: =SUM(E101:P101) -> 0
C102: General & Administrative | E102: =SUM(E97:E101) -> 0 | F102: =SUM(F97:F101) -> 0 | G102: =SUM(G97:G101) -> 0 | H102: =SUM(H97:H101) -> 0 | I102: =SUM(I97:I101) -> 0 | J102: =SUM(J97:J101) -> 0 | K102: =SUM(K97:K101) -> 0 | L102: =SUM(L97:L101) -> 0 | ... Q102: =SUM(Q97:Q101) -> 0
C104: Total Non-Reimbursable Expenses | E104: =+E74+E78+E83+E87+E89+E91+E93+E95+E102 -> 0 | F104: =+F74+F78+F83+F87+F89+F91+F93+F95+F102 -> 0 | G104: =+G74+G78+G83+G87+G89+G91+G93+G95+G102 -> 0 | H104: =+H74+H78+H83+H87+H89+H91+H93+H95+H102 -> 0 | I104: =+I74+I78+I83+I87+I89+I91+I93+I95+I102 -> 0 | J104: =+J74+J78+J83+J87+J89+J91+J93+J95+J102 -> 0 | K104: =+K74+K78+K83+K87+K89+K91+K93+K95+K102 -> 0 | L104: =+L74+L78+L83+L87+L89+L91+L93+L95+L102 -> 0 | ... Q104: =+Q74+Q78+Q83+Q87+Q89+Q91+Q93+Q95+Q102 -> 0
B107: TOTAL OPERATING EXPENSES | E107: =+E70+E104 -> 0 | F107: =+F70+F104 -> 0 | G107: =+G70+G104 -> 0 | H107: =+H70+H104 -> 0 | I107: =+I70+I104 -> 0 | J107: =+J70+J104 -> 0 | K107: =+K70+K104 -> 0 | L107: =+L70+L104 -> 0 | ... Q107: =+Q70+Q104 -> 0
B110: NET OPERATING INCOME | E110: =+E23-E107 -> 0 | F110: =+F23-F107 -> 0 | G110: =+G23-G107 -> 0 | H110: =+H23-H107 -> 0 | I110: =+I23-I107 -> 0 | J110: =+J23-J107 -> 0 | K110: =+K23-K107 -> 0 | L110: =+L23-L107 -> 0 | ... Q110: =+Q23-Q107 -> 0
A112: 1420-0000 | D112: Land Improvements | Q112: =SUM(E112:P112) -> 0
A113: 1430-0000 | D113: Buildings | Q113: =SUM(E113:P113) -> 0
A114: 1450-0000 | D114: Equipment | Q114: =SUM(E114:P114) -> 0
A115: 1980-8501 | D115: Capital Improvements | Q115: =SUM(E115:P115) -> 0
C116: Capital Improvements | E116: =SUM(E112:E115) -> 0 | F116: =SUM(F112:F115) -> 0 | G116: =SUM(G112:G115) -> 0 | H116: =SUM(H112:H115) -> 0 | I116: =SUM(I112:I115) -> 0 | J116: =SUM(J112:J115) -> 0 | K116: =SUM(K112:K115) -> 0 | L116: =SUM(L112:L115) -> 0 | ... Q116: =SUM(Q112:Q115) -> 0
A118: 1440-0000 | C118: Tenant Improvements | Q118: =SUM(E118:P118) -> 0
A120: 1940-8501 | D120: Deferred Marketing | Q120: =SUM(E120:P120) -> 0
A121: 1940-8501 | D121: Outside Leasing Commissions | Q121: =SUM(E121:P121) -> 0
C122: Outside Leasing Commissions | E122: =SUM(E120:E121) -> 0 | F122: =SUM(F120:F121) -> 0 | G122: =SUM(G120:G121) -> 0 | H122: =SUM(H120:H121) -> 0 | I122: =SUM(I120:I121) -> 0 | J122: =SUM(J120:J121) -> 0 | K122: =SUM(K120:K121) -> 0 | L122: =SUM(L120:L121) -> 0 | ... Q122: =SUM(Q120:Q121) -> 0
B124: CASH FLOW BEFORE DEBT SERVICE | E124: =+E110-E116-E118-E122 -> 0 | F124: =+F110-F116-F118-F122 -> 0 | G124: =+G110-G116-G118-G122 -> 0 | H124: =+H110-H116-H118-H122 -> 0 | I124: =+I110-I116-I118-I122 -> 0 | J124: =+J110-J116-J118-J122 -> 0 | K124: =+K110-K116-K118-K122 -> 0 | L124: =+L110-L116-L118-L122 -> 0 | ... Q124: =+Q110-Q116-Q118-Q122 -> 0
B126: Debt Service
A127: 9210-8501 | D127: Interest | Q127: =SUM(E127:P127) -> 0
A128: 2740-8501 | D128: Mortgage Amortization | Q128: =SUM(E128:P128) -> 0
A129: 2740-0000 | D129: Loan Proceeds | Q129: =SUM(E129:P129) -> 0
D130: Total Debt Service | E130: =SUM(E127:E129) -> 0 | F130: =SUM(F127:F129) -> 0 | G130: =SUM(G127:G129) -> 0 | H130: =SUM(H127:H129) -> 0 | I130: =SUM(I127:I129) -> 0 | J130: =SUM(J127:J129) -> 0 | K130: =SUM(K127:K129) -> 0 | L130: =SUM(L127:L129) -> 0 | ... Q130: =SUM(Q127:Q129) -> 0
B133: CASH FLOW AFTER DEBT SERVICE | E133: =+E124-E130 -> 0 | F133: =+F124-F130 -> 0 | G133: =+G124-G130 -> 0 | H133: =+H124-H130 -> 0 | I133: =+I124-I130 -> 0 | J133: =+J124-J130 -> 0 | K133: =+K124-K130 -> 0 | L133: =+L124-L130 -> 0 | ... Q133: =+Q124-Q130 -> 0
D141: ="Budget Import - "&B1 -> Budget Import - Unallocated Expenses-G&A, Interest
D142: Account | E142: 1 | F142: 2 | G142: 3 | H142: 4 | I142: 5 | J142: 6 | K142: 7 | L142: 8 | M142: 9 | N142: 10 | O142: 11 | P142: 12 | Q142: Total
D143: 8210-8501 | E143: =+E93 -> 0 | F143: =+F93 -> 0 | G143: =+G93 -> 0 | H143: =+H93 -> 0 | I143: =+I93 -> 0 | J143: =+J93 -> 0 | K143: =+K93 -> 0 | L143: =+L93 -> 0 | ... P143: =+P93 -> 0 | Q143: =SUM(E143:P143) -> 0
D144: 8310-8501 | E144: =+E95 -> 0 | F144: =+F95 -> 0 | G144: =+G95 -> 0 | H144: =+H95 -> 0 | I144: =+I95 -> 0 | J144: =+J95 -> 0 | K144: =+K95 -> 0 | L144: =+L95 -> 0 | ... P144: =+P95 -> 0 | Q144: =SUM(E144:P144) -> 0
D145: 8190-8501 | E145: =+E97 -> 0 | F145: =+F97 -> 0 | G145: =+G97 -> 0 | H145: =+H97 -> 0 | I145: =+I97 -> 0 | J145: =+J97 -> 0 | K145: =+K97 -> 0 | L145: =+L97 -> 0 | ... P145: =+P97 -> 0 | Q145: =SUM(E145:P145) -> 0
D146: 8990-8501 | E146: =+E100 -> 0 | F146: =+F100 -> 0 | G146: =+G100 -> 0 | H146: =+H100 -> 0 | I146: =+I100 -> 0 | J146: =+J100 -> 0 | K146: =+K100 -> 0 | L146: =+L100 -> 0 | ... P146: =+P100 -> 0 | Q146: =SUM(E146:P146) -> 0
D147: 9210-8501 | E147: =+E127 -> 0 | F147: =+F127 -> 0 | G147: =+G127 -> 0 | H147: =+H127 -> 0 | I147: =+I127 -> 0 | J147: =+J127 -> 0 | K147: =+K127 -> 0 | L147: =+L127 -> 0 | ... P147: =+P127 -> 0 | Q147: =SUM(E147:P147) -> 0
E148: =SUM(E143:E147) -> 0 | F148: =SUM(F143:F147) -> 0 | G148: =SUM(G143:G147) -> 0 | H148: =SUM(H143:H147) -> 0 | I148: =SUM(I143:I147) -> 0 | J148: =SUM(J143:J147) -> 0 | K148: =SUM(K143:K147) -> 0 | L148: =SUM(L143:L147) -> 0 | ... Q148: =SUM(Q143:Q147) -> 0

Sheet 4050
B1: 4050 | J1: =+'NI LLC-Consolidated'!J1 -> Operating Budget | Q1: ='NI LLC-Consolidated'!Q1 -> 46023
J2: ='NI LLC-Consolidated'!J2 -> Neshaminy Interplex LLC
Q3: =Q1 -> 46023 | S3: 7/2025 Reprojections
B4: 54008 | E4: Jan | F4: Feb | G4: Mar | H4: Apr | I4: May | J4: Jun | K4: Jul | L4: Aug | M4: Sep | N4: Oct | O4: Nov | P4: Dec | Q4: Total | R4: Total PSF | S4: Total | T4: Var. | U4: Input | V4: Notes
D6: Occupancy % | E6: ='Renew & Vac'!AJ9 -> 0.5858 | F6: ='Renew & Vac'!AK9 -> 0.5858 | G6: ='Renew & Vac'!AL9 -> 0.5858 | H6: ='Renew & Vac'!AM9 -> 0.5858 | I6: ='Renew & Vac'!AN9 -> 0.5858 | J6: ='Renew & Vac'!AO9 -> 0.5858 | K6: ='Renew & Vac'!AP9 -> 0.5858 | L6: ='Renew & Vac'!AQ9 -> 0.5858 | ... P6: ='Renew & Vac'!AU9 -> 0.5858
D7: Occupancy SF | E7: =$B$4*E6 -> 31637.886 | F7: =$B$4*F6 -> 31637.886 | G7: =$B$4*G6 -> 31637.886 | H7: =$B$4*H6 -> 31637.886 | I7: =$B$4*I6 -> 31637.886 | J7: =$B$4*J6 -> 31637.886 | K7: =$B$4*K6 -> 31637.886 | L7: =$B$4*L6 -> 31637.886 | ... P7: =$B$4*P6 -> 31637.886
B8: Revenues
A10: 4230-8501 | C10: Rental Income - In Place | E10: =SUMIFS('In Place Revenue'!$G:$G,'In Place Revenue'!$A:$A,"4050",'In Place Revenue'!$H:$H,1) -> 43151.75 | F10: =SUMIFS('In Place Revenue'!$G:$G,'In Place Revenue'!$A:$A,"4050",'In Place Revenue'!$H:$H,2) -> 43151.75 | G10: =SUMIFS('In Place Revenue'!$G:$G,'In Place Revenue'!$A:$A,"4050",'In Place Revenue'!$H:$H,3) -> 43151.75 | H10: =SUMIFS('In Place Revenue'!$G:$G,'In Place Revenue'!$A:$A,"4050",'In Place Revenue'!$H:$H,4) -> 37187.33 | I10: =SUMIFS('In Place Revenue'!$G:$G,'In Place Revenue'!$A:$A,"4050",'In Place Revenue'!$H:$H,5) -> 37187.33 | J10: =SUMIFS('In Place Revenue'!$G:$G,'In Place Revenue'!$A:$A,"4050",'In Place Revenue'!$H:$H,6) -> 37187.33 | K10: =SUMIFS('In Place Revenue'!$G:$G,'In Place Revenue'!$A:$A,"4050",'In Place Revenue'!$H:$H,7) -> 19840.96 | L10: =SUMIFS('In Place Revenue'!$G:$G,'In Place Revenue'!$A:$A,"4050",'In Place Revenue'!$H:$H,8) -> 19840.96 | M10: =SUMIFS('In Place Revenue'!$G:$G,'In Place Revenue'!$A:$A,"4050",'In Place Revenue'!$H:$H,9) -> 19840.96 | N10: =SUMIFS('In Place Revenue'!$G:$G,'In Place Revenue'!$A:$A,"4050",'In Place Revenue'!$H:$H,10) -> 11025.71 | O10: =SUMIFS('In Place Revenue'!$G:$G,'In Place Revenue'!$A:$A,"4050",'In Place Revenue'!$H:$H,11) -> 7562.42 | P10: =SUMIFS('In Place Revenue'!$G:$G,'In Place Revenue'!$A:$A,"4050",'In Place Revenue'!$H:$H,12) -> 7562.42 | Q10: =SUM(E10:P10) -> 326690.67 | R10: =Q10/$B$4 -> 6.0489311 | S10: 534079.37 | T10: =IFERROR(Q10/S10-1,"-") -> -0.38831064
A11: 4230-8501 | C11: Rental Income - New & Renewal | E11: ='Renew & Vac'!AJ10 -> 5483.7083 | F11: ='Renew & Vac'!AK10 -> 5483.7083 | G11: ='Renew & Vac'!AL10 -> 5483.7083 | H11: ='Renew & Vac'!AM10 -> 11448.125 | I11: ='Renew & Vac'!AN10 -> 11448.125 | J11: ='Renew & Vac'!AO10 -> 11448.125 | K11: ='Renew & Vac'!AP10 -> 28841.292 | L11: ='Renew & Vac'!AQ10 -> 28841.292 | ... P11: ='Renew & Vac'!AU10 -> 41119.833 | Q11: =SUM(E11:P11) -> 257215.58 | R11: =Q11/$B$4 -> 4.762546 | T11: =IFERROR(Q11/S11-1,"-") -> -
A12: 4240-8501 | C12: Percentage Rents | E12: 0 | F12: 0 | G12: 0 | H12: 0 | I12: 0 | J12: 0 | K12: 0 | L12: 0 | M12: 0 | N12: 0 | O12: 0 | P12: 0 | Q12: =SUM(E12:P12) -> 0 | R12: =Q12/$B$4 -> 0 | T12: =R12/S12-1 -> #DIV/0!
A13: 4990-8501 | C13: Miscellaneous | E13: 0 | F13: 0 | G13: 0 | H13: 0 | I13: 0 | J13: 0 | K13: 0 | L13: 0 | M13: 0 | N13: 0 | O13: 0 | P13: 0 | Q13: =SUM(E13:P13) -> 0 | R13: =Q13/$B$4 -> 0 | T13: =IFERROR(Q13/S13-1,"-") -> -
A14: 9190-8501 | C14: Interest Income | E14: 207 | F14: 207 | G14: 207 | H14: 207 | I14: 207 | J14: 207 | K14: 207 | L14: 207 | M14: 207 | N14: 207 | O14: 207 | P14: 207 | Q14: =SUM(E14:P14) -> 2484 | R14: =Q14/$B$4 -> 0.045993186 | T14: =IFERROR(Q14/S14-1,"-") -> - | U14: DW | V14: Annualized one month of interest from recent statement
C15: Total Rental and Other | E15: =SUM(E10:E14) -> 48842.458 | F15: =SUM(F10:F14) -> 48842.458 | G15: =SUM(G10:G14) -> 48842.458 | H15: =SUM(H10:H14) -> 48842.455 | I15: =SUM(I10:I14) -> 48842.455 | J15: =SUM(J10:J14) -> 48842.455 | K15: =SUM(K10:K14) -> 48889.252 | L15: =SUM(L10:L14) -> 48889.252 | ... Q15: =SUM(Q10:Q14) -> 586390.25 | R15: =Q15/$B$4 -> 10.85747 | S15: =SUM(S10:S14) -> 534079.37 | T15: =IFERROR(Q15/S15-1,"-") -> 0.097945898
B17: Reimbursements
A18: 4710-8502 | C18: Electric | E18: =E6*E29 -> 7434.3878 | F18: =F6*F29 -> 6089.391 | G18: =G6*G29 -> 5289.1882 | H18: =H6*H29 -> 5077.1286 | I18: =I6*I29 -> 4161.5232 | J18: =J6*J29 -> 4534.6778 | K18: =K6*K29 -> 5136.2944 | L18: =L6*L29 -> 5243.4958 | ... P18: =P6*P29 -> 6659.9602 | Q18: =SUM(E18:P18) -> 64091.792 | R18: =Q18/$B$4 -> 1.1867092 | S18: 61616.19 | T18: =IFERROR(Q18/S18-1,"-") -> 0.040177788 | U18: DW | V18: =Q18/Q29*100&"% Set to occupancy" -> 58.58% Set to occupancy
A19: 4910-8502 | C19: Common Area Maintenance | E19: =+'Tenant Recoveries'!F21 -> 3600 | F19: =+E19 -> 3600 | G19: =+F19 -> 3600 | H19: =+G19 -> 3600 | I19: =+H19 -> 3600 | J19: =+I19 -> 3600 | K19: =+J19 -> 3600 | L19: =+K19 -> 3600 | M19: =+L19 -> 3600 | ... P19: =+O19 -> 3600 | Q19: =SUM(E19:P19) -> 43200 | R19: =Q19/$B$4 -> 0.7998815 | S19: 33608 | T19: =IFERROR(Q19/S19-1,"-") -> 0.28540824 | V19: =Q19/(Q71-Q63-Q58-Q29) -> 0.1462202
A20: 4920-8502 | C20: Real Estate Taxes | E20: =+'Tenant Recoveries'!F22 -> 200 | F20: =+E20 -> 200 | G20: =+F20 -> 200 | H20: =+G20 -> 200 | I20: =+H20 -> 200 | J20: =+I20 -> 200 | K20: =+J20 -> 200 | L20: =+K20 -> 200 | M20: =+L20 -> 200 | ... P20: =+O20 -> 200 | Q20: =SUM(E20:P20) -> 2400 | R20: =Q20/$B$4 -> 0.044437861 | S20: 1302 | T20: =IFERROR(Q20/S20-1,"-") -> 0.84331797 | V20: =Q20/Q58 -> 0.053031006
A21: 4930-8502 | C21: Insurance | Q21: =SUM(E21:P21) -> 0 | R21: =Q21/$B$4 -> 0 | S21: 0 | T21: =IFERROR(Q21/S21-1,"-") -> -
C22: Total Reimbursements | E22: =SUM(E18:E21) -> 11234.388 | F22: =SUM(F18:F21) -> 9889.391 | G22: =SUM(G18:G21) -> 9089.1882 | H22: =SUM(H18:H21) -> 8877.1286 | I22: =SUM(I18:I21) -> 7961.5232 | J22: =SUM(J18:J21) -> 8334.6778 | K22: =SUM(K18:K21) -> 8936.2944 | L22: =SUM(L18:L21) -> 9043.4958 | ... Q22: =SUM(Q18:Q21) -> 109691.79 | R22: =Q22/$B$4 -> 2.0310286 | S22: =SUM(S18:S21) -> 96526.19 | T22: =IFERROR(Q22/S22-1,"-") -> 0.13639409
R23: =Q23/$B$4 -> 0
B24: TOTAL REVENUES | E24: =+E15+E22 -> 60076.846 | F24: =+F15+F22 -> 58731.849 | G24: =+G15+G22 -> 57931.647 | H24: =+H15+H22 -> 57719.584 | I24: =+I15+I22 -> 56803.978 | J24: =+J15+J22 -> 57177.133 | K24: =+K15+K22 -> 57825.546 | L24: =+L15+L22 -> 57932.747 | ... Q24: =+Q15+Q22 -> 696082.05 | R24: =Q24/$B$4 -> 12.888499 | S24: =+S15+S22 -> 630605.56 | T24: =IFERROR(Q24/S24-1,"-") -> 0.10383113
B26: Reimbursable Expenses
A27: 6030-8502 | C27: Maintenance Salaries | E27: ='Allocated Expenses'!F6 -> 1104.9382 | F27: ='Allocated Expenses'!G6 -> 1104.9382 | G27: ='Allocated Expenses'!H6 -> 1104.9382 | H27: ='Allocated Expenses'!I6 -> 1104.9382 | I27: ='Allocated Expenses'!J6 -> 1104.9382 | J27: ='Allocated Expenses'!K6 -> 1104.9382 | K27: ='Allocated Expenses'!L6 -> 1104.9382 | L27: ='Allocated Expenses'!M6 -> 1104.9382 | ... P27: ='Allocated Expenses'!Q6 -> 1104.9382 | Q27: =SUM(E27:P27) -> 13259.259 | R27: =Q27/$B$4 -> 0.24550546 | S27: 9312 | T27: =IFERROR(Q27/S27-1,"-") -> 0.42388946 | V27: Based on 2026 Payroll budget
A29: 6120-8502 | C29: Electric | E29: 12691 | F29: 10395 | G29: 9029 | H29: 8667 | I29: 7104 | J29: 7741 | K29: 8768 | L29: 8951 | M29: 7497 | N29: 8898 | O29: 8299 | P29: 11369 | Q29: =SUM(E29:P29) -> 109409 | R29: =Q29/$B$4 -> 2.0257925 | S29: 106977.43 | T29: =IFERROR(Q29/S29-1,"-") -> 0.022729748 | U29: DW | V29: Data\Shared\Properties\Business Plans - All Entities\2026\ISG Electric data
A31: 6130-8502 | C31: Water & Sewer | E31: ='Water Sewer'!D10 -> 903.31 | F31: ='Water Sewer'!E10 -> 919.79 | G31: ='Water Sewer'!F10 -> 962.02 | H31: ='Water Sewer'!G10 -> 946.57 | I31: ='Water Sewer'!H10 -> 1572.81 | J31: ='Water Sewer'!I10 -> 2022.92 | K31: ='Water Sewer'!J10 -> 2235.1 | L31: ='Water Sewer'!K10 -> 2706.84 | ... P31: ='Water Sewer'!O10 -> 975.41 | Q31: =SUM(E31:P31) -> 19406.23 | R31: =Q31/$B$4 -> 0.3593214 | S31: 11349.98 | T31: =IFERROR(Q31/S31-1,"-") -> 0.70980301 | U31: AK | V31: 2025 Business Plan grown 3%
D33: Building Maint.-Contractual | E33: ='Building Maint'!C17 -> 2737 | F33: ='Building Maint'!D17 -> 1037 | G33: ='Building Maint'!E17 -> 6671 | H33: ='Building Maint'!F17 -> 4383 | I33: ='Building Maint'!G17 -> 1037 | J33: ='Building Maint'!H17 -> 6653 | K33: ='Building Maint'!I17 -> 2737 | L33: ='Building Maint'!J17 -> 1037 | ... P33: ='Building Maint'!N17 -> 6653 | Q33: =SUM(E33:P33) -> 45018 | R33: =Q33/$B$4 -> 0.83354318 | U33: DW | V33: 2025 Business Plan grown 3%
D34: Building Maint.-Recurring | E34: ='Building Maint'!C6 -> 2350 | F34: ='Building Maint'!D6 -> 1100 | G34: ='Building Maint'!E6 -> 1300 | H34: ='Building Maint'!F6 -> 1725 | I34: ='Building Maint'!G6 -> 2940 | J34: ='Building Maint'!H6 -> 1475 | K34: ='Building Maint'!I6 -> 3845 | L34: ='Building Maint'!J6 -> 1100 | ... P34: ='Building Maint'!N6 -> 1100 | Q34: =SUM(E34:P34) -> 21535 | R34: =Q34/$B$4 -> 0.39873722 | U34: DW | V34: 2025 Business Plan grown 3%
D35: Building Maint.-Big Projects | G35: 10000 | N35: 10000 | Q35: =SUM(E35:P35) -> 20000 | R35: =Q35/$B$4 -> 0.37031551 | U35: AK | V35: Contingency for repairs
A36: 6220-8502 | C36: Building Maintenance | E36: =SUM(E33:E35) -> 5087 | F36: =SUM(F33:F35) -> 2137 | G36: =SUM(G33:G35) -> 17971 | H36: =SUM(H33:H35) -> 6108 | I36: =SUM(I33:I35) -> 3977 | J36: =SUM(J33:J35) -> 8128 | K36: =SUM(K33:K35) -> 6582 | L36: =SUM(L33:L35) -> 2137 | ... Q36: =SUM(Q33:Q35) -> 86553 | R36: =Q36/$B$4 -> 1.6025959 | S36: 86001.72 | T36: =IFERROR(Q36/S36-1,"-") -> 0.0064101044
A38: 6330-850 | B38: (SC) | C38: Parking Lot Cleaning | Q38: =SUM(E38:P38) -> 0 | R38: =Q38/$B$4 -> 0
D40: Parking Lot Maint.-Contractual | Q40: =SUM(E40:P40) -> 0 | R40: =Q40/$B$4 -> 0
D41: Parking Lot Maint.-Recurring | E41: ='Parking Lot Maint'!C6 -> 803.4 | F41: ='Parking Lot Maint'!D6 -> 803.4 | G41: ='Parking Lot Maint'!E6 -> 1323.55 | H41: ='Parking Lot Maint'!F6 -> 803.4 | I41: ='Parking Lot Maint'!G6 -> 803.4 | J41: ='Parking Lot Maint'!H6 -> 1323.55 | K41: ='Parking Lot Maint'!I6 -> 803.4 | L41: ='Parking Lot Maint'!J6 -> 803.4 | ... P41: ='Parking Lot Maint'!N6 -> 1323.55 | Q41: =SUM(E41:P41) -> 11721.4 | R41: =Q41/$B$4 -> 0.21703081 | U41: DW | V41: 2025 Business Plan grown 3%
D42: Parking Lot Maint.-Big Projects | H42: 6000 | M42: 6000 | Q42: =SUM(E42:P42) -> 12000 | R42: =Q42/$B$4 -> 0.22218931 | U42: AK | V42: Estimate for asphalt/pothole repairs
A43: 6330-8502 | C43: Parking Lot Maintenance | E43: =SUM(E40:E42) -> 803.4 | F43: =SUM(F40:F42) -> 803.4 | G43: =SUM(G40:G42) -> 1323.55 | H43: =SUM(H40:H42) -> 6803.4 | I43: =SUM(I40:I42) -> 803.4 | J43: =SUM(J40:J42) -> 1323.55 | K43: =SUM(K40:K42) -> 803.4 | L43: =SUM(L40:L42) -> 803.4 | ... Q43: =SUM(Q40:Q42) -> 23721.4 | R43: =Q43/$B$4 -> 0.43922012 | S43: 16795.6 | T43: =IFERROR(Q43/S43-1,"-") -> 0.412358
A45: 6370-8502 | C45: Snow Removal | E45: =1.03*3500 -> 3605 | F45: =1.03*3500 -> 3605 | G45: =1.03*3500 -> 3605 | O45: =1.03*1000 -> 1030 | P45: =1.03*3500 -> 3605 | Q45: =SUM(E45:P45) -> 15450 | R45: =Q45/$B$4 -> 0.28606873 | S45: 11247.51 | T45: =IFERROR(Q45/S45-1,"-") -> 0.37363737 | U45: DW | V45: 2025 Business Plan grown 3%
D47: Landscaping-Contractual | E47: ='Allocated Expenses'!F17 -> 0 | F47: ='Allocated Expenses'!G17 -> 0 | G47: ='Allocated Expenses'!H17 -> 922.69385 | H47: ='Allocated Expenses'!I17 -> 922.69385 | I47: ='Allocated Expenses'!J17 -> 922.69385 | J47: ='Allocated Expenses'!K17 -> 922.69385 | K47: ='Allocated Expenses'!L17 -> 922.69385 | L47: ='Allocated Expenses'!M17 -> 922.69385 | ... P47: ='Allocated Expenses'!Q17 -> 0 | Q47: =SUM(E47:P47) -> 8304.2446 | R47: =Q47/$B$4 -> 0.15375953 | U47: DW | V47: 2025 Business Plan grown 3%
D48: Landscaping-Recurring | E48: =Landscaping!C6 -> 0 | F48: =Landscaping!D6 -> 0 | G48: =Landscaping!E6 -> 463.5 | H48: =Landscaping!F6 -> 463.5 | I48: =Landscaping!G6 -> 2008.5 | J48: =Landscaping!H6 -> 463.5 | K48: =Landscaping!I6 -> 463.5 | L48: =Landscaping!J6 -> 463.5 | ... P48: =Landscaping!N6 -> 0 | Q48: =SUM(E48:P48) -> 7004 | R48: =Q48/$B$4 -> 0.12968449 | U48: DW | V48: 2025 Business Plan grown 3%
D49: Landscaping-Big Projects | E49: ='Allocated Expenses'!F28 -> 566.38519 | F49: ='Allocated Expenses'!G28 -> 566.38519 | G49: ='Allocated Expenses'!H28 -> 566.38519 | H49: ='Allocated Expenses'!I28 -> 566.38519 | I49: ='Allocated Expenses'!J28 -> 566.38519 | J49: ='Allocated Expenses'!K28 -> 566.38519 | K49: ='Allocated Expenses'!L28 -> 566.38519 | L49: ='Allocated Expenses'!M28 -> 566.38519 | ... P49: ='Allocated Expenses'!Q28 -> 566.38519 | Q49: =SUM(E49:P49) -> 6796.6223 | R49: =Q49/$B$4 -> 0.12584473 | U49: AK | V49: Fountain repairs
A50: 6380-8502 | C50: Landscaping | E50: =SUM(E47:E49) -> 566.38519 | F50: =SUM(F47:F49) -> 566.38519 | G50: =SUM(G47:G49) -> 1952.579 | H50: =SUM(H47:H49) -> 1952.579 | I50: =SUM(I47:I49) -> 3497.579 | J50: =SUM(J47:J49) -> 1952.579 | K50: =SUM(K47:K49) -> 1952.579 | L50: =SUM(L47:L49) -> 1952.579 | ... Q50: =SUM(Q47:Q49) -> 22104.867 | R50: =Q50/$B$4 -> 0.40928875 | S50: 14324.67 | T50: =IFERROR(Q50/S50-1,"-") -> 0.54313272
A52: 6350-8502 | C52: Security | E52: ='Allocated Expenses'!F39 -> 295.68 | F52: ='Allocated Expenses'!G39 -> 295.68 | G52: ='Allocated Expenses'!H39 -> 295.68 | H52: ='Allocated Expenses'!I39 -> 295.68 | I52: ='Allocated Expenses'!J39 -> 295.68 | J52: ='Allocated Expenses'!K39 -> 295.68 | K52: ='Allocated Expenses'!L39 -> 295.68 | L52: ='Allocated Expenses'!M39 -> 295.68 | ... P52: ='Allocated Expenses'!Q39 -> 295.68 | Q52: =SUM(E52:P52) -> 3548.16 | R52: =Q52/$B$4 -> 0.065696934 | S52: 3980.86 | T52: =IFERROR(Q52/S52-1,"-") -> -0.10869511 | U52: DW | V52: 2025 Business Plan grown 3%
A54: 6610-8502 | B54: (BP) | C54: Management Fee | E54: =ROUND(E$24*0.04,0) -> 2403 | F54: =ROUND(F$24*0.04,0) -> 2349 | G54: =ROUND(G$24*0.04,0) -> 2317 | H54: =ROUND(H$24*0.04,0) -> 2309 | I54: =ROUND(I$24*0.04,0) -> 2272 | J54: =ROUND(J$24*0.04,0) -> 2287 | K54: =ROUND(K$24*0.04,0) -> 2313 | L54: =ROUND(L$24*0.04,0) -> 2317 | ... P54: =ROUND(P$24*0.04,0) -> 2374 | Q54: =SUM(E54:P54) -> 27842 | R54: =Q54/$B$4 -> 0.51551622 | S54: 26023.92 | T54: =IFERROR(Q54/S54-1,"-") -> 0.069861881
A56: 6270-8502 | C56: Trash Removal | E56: =Trash!C6 -> 1751 | F56: =Trash!D6 -> 1751 | G56: =Trash!E6 -> 1751 | H56: =Trash!F6 -> 1751 | I56: =Trash!G6 -> 1751 | J56: =Trash!H6 -> 2251 | K56: =Trash!I6 -> 1751 | L56: =Trash!J6 -> 1751 | ... P56: =Trash!N6 -> 2251 | Q56: =SUM(E56:P56) -> 22012 | R56: =Q56/$B$4 -> 0.40756925 | S56: 23004.59 | T56: =IFERROR(Q56/S56-1,"-") -> -0.043147476 | U56: DW | V56: 2025 Business Plan grown 3% with semiannual bumps.
A58: 6410-8502 | C58: Real Estate Taxes | E58: =+'INS RET'!E59 -> 3771.3786 | F58: =+'INS RET'!F59 -> 3771.3786 | G58: =+'INS RET'!G59 -> 3771.3786 | H58: =+'INS RET'!H59 -> 3771.3786 | I58: =+'INS RET'!I59 -> 3771.3786 | J58: =+'INS RET'!J59 -> 3771.3786 | K58: =+'INS RET'!K59 -> 3771.3786 | L58: =+'INS RET'!L59 -> 3771.3786 | ... P58: =+'INS RET'!P59 -> 3771.3786 | Q58: =SUM(E58:P58) -> 45256.543 | R58: =Q58/$B$4 -> 0.83795999 | S58: 102397.79 | T58: =IFERROR(Q58/S58-1,"-") -> -0.55803203
D60: Insurance-Liability | E60: =+'INS RET'!E6+'INS RET'!E7 -> 1461 | F60: =+'INS RET'!F6+'INS RET'!F7 -> 1461 | G60: =+'INS RET'!G6+'INS RET'!G7 -> 1461 | H60: =+'INS RET'!H6+'INS RET'!H7 -> 1461 | I60: =+'INS RET'!I6+'INS RET'!I7 -> 1461 | J60: =+'INS RET'!J6+'INS RET'!J7 -> 1461 | K60: =+'INS RET'!K6+'INS RET'!K7 -> 1461 | L60: =+'INS RET'!L6+'INS RET'!L7 -> 1461 | ... P60: =+'INS RET'!P6+'INS RET'!P7 -> 1490.22 | Q60: =SUM(E60:P60) -> 17590.44 | R60: =Q60/$B$4 -> 0.32570064
D61: Insurabce-Property | E61: =+'INS RET'!E9 -> 1036 | F61: =+'INS RET'!F9 -> 1036 | G61: =+'INS RET'!G9 -> 1036 | H61: =+'INS RET'!H9 -> 1036 | I61: =+'INS RET'!I9 -> 1036 | J61: =+'INS RET'!J9 -> 1036 | K61: =+'INS RET'!K9 -> 1036 | L61: =+'INS RET'!L9 -> 1036 | ... P61: =+'INS RET'!P9 -> 1056.72 | Q61: =SUM(E61:P61) -> 12473.44 | R61: =Q61/$B$4 -> 0.23095541
D62: Insurance-Other | E62: =+'INS RET'!E10 -> 50 | F62: =+'INS RET'!F10 -> 50 | G62: =+'INS RET'!G10 -> 50 | H62: =+'INS RET'!H10 -> 50 | I62: =+'INS RET'!I10 -> 50 | J62: =+'INS RET'!J10 -> 50 | K62: =+'INS RET'!K10 -> 50 | L62: =+'INS RET'!L10 -> 50 | ... P62: =+'INS RET'!P10 -> 51 | Q62: =SUM(E62:P62) -> 602 | R62: =Q62/$B$4 -> 0.011146497
A63: 6510-8502 | C63: Insurance | E63: =SUM(E60:E62) -> 2547 | F63: =SUM(F60:F62) -> 2547 | G63: =SUM(G60:G62) -> 2547 | H63: =SUM(H60:H62) -> 2547 | I63: =SUM(I60:I62) -> 2547 | J63: =SUM(J60:J62) -> 2547 | K63: =SUM(K60:K62) -> 2547 | L63: =SUM(L60:L62) -> 2547 | ... Q63: =SUM(Q60:Q62) -> 30665.88 | R63: =Q63/$B$4 -> 0.56780255 | S63: 30392 | T63: =IFERROR(Q63/S63-1,"-") -> 0.009011582
D65: Cleaning & Supplies | E65: ='Allocated Expenses'!F50+'Allocated Expenses'!F61 -> 4956.1825 | F65: ='Allocated Expenses'!G50+'Allocated Expenses'!G61 -> 4956.1825 | G65: ='Allocated Expenses'!H50+'Allocated Expenses'!H61 -> 4956.1825 | H65: ='Allocated Expenses'!I50+'Allocated Expenses'!I61 -> 4956.1825 | I65: ='Allocated Expenses'!J50+'Allocated Expenses'!J61 -> 4956.1825 | J65: ='Allocated Expenses'!K50+'Allocated Expenses'!K61 -> 4956.1825 | K65: ='Allocated Expenses'!L50+'Allocated Expenses'!L61 -> 4956.1825 | L65: ='Allocated Expenses'!M50+'Allocated Expenses'!M61 -> 4956.1825 | ... P65: ='Allocated Expenses'!Q50+'Allocated Expenses'!Q61 -> 4956.1825 | Q65: =SUM(E65:P65) -> 59474.191 | R65: =Q65/$B$4 -> 1.1012108 | U65: DW | V65: Based on occupancy. Includes cleaning, supplies, and porter fee.
D66: Cleaning & Supplies-Vacancies | E66: ='Allocated Expenses'!F74 -> 172.80913 | F66: ='Allocated Expenses'!G74 -> 172.80913 | G66: ='Allocated Expenses'!H74 -> 172.80913 | H66: ='Allocated Expenses'!I74 -> 172.80913 | I66: ='Allocated Expenses'!J74 -> 172.80913 | J66: ='Allocated Expenses'!K74 -> 172.80913 | K66: ='Allocated Expenses'!L74 -> 172.80913 | L66: ='Allocated Expenses'!M74 -> 172.80913 | ... P66: ='Allocated Expenses'!Q74 -> 172.80913 | Q66: =SUM(E66:P66) -> 2073.7095 | R66: =Q66/$B$4 -> 0.03839634 | U66: DW | V66: Based on occupancy.
A67: 6250-8502 | B67: (BP) | C67: Cleaning & Supplies | E67: =SUM(E65:E66) -> 5128.9917 | F67: =SUM(F65:F66) -> 5128.9917 | G67: =SUM(G65:G66) -> 5128.9917 | H67: =SUM(H65:H66) -> 5128.9917 | I67: =SUM(I65:I66) -> 5128.9917 | J67: =SUM(J65:J66) -> 5128.9917 | K67: =SUM(K65:K66) -> 5128.9917 | L67: =SUM(L65:L66) -> 5128.9917 | ... Q67: =SUM(Q65:Q66) -> 61547.9 | R67: =Q67/$B$4 -> 1.1396071 | S67: 54794.66 | T67: =IFERROR(Q67/S67-1,"-") -> 0.12324632
B69: (SC) | C69: Other | E69: 0 | F69: 0 | G69: 0 | H69: 0 | I69: 0 | J69: 0 | K69: 0 | L69: 0 | M69: 0 | N69: 0 | O69: 0 | P69: 0 | Q69: =SUM(E69:P69) -> 0 | R69: =Q69/$B$4 -> 0 | T69: =IFERROR(Q69/S69-1,"-") -> -
C71: Total Reimbursable Expenses | E71: =+E27+E29+E31+E36+E38+E43+E45+E50+E52+E54+E56+E58+E63+E67+E69 -> 40658.084 | F71: =+F27+F29+F31+F36+F38+F43+F45+F50+F52+F54+F56+F58+F63+F67+F69 -> 35374.564 | G71: =+G27+G29+G31+G36+G38+G43+G45+G50+G52+G54+G56+G58+G63+G67+G69 -> 51759.138 | H71: =+H27+H29+H31+H36+H38+H43+H45+H50+H52+H54+H56+H58+H63+H67+H69 -> 41385.538 | I71: =+I27+I29+I31+I36+I38+I43+I45+I50+I52+I54+I56+I58+I63+I67+I69 -> 33825.778 | J71: =+J27+J29+J31+J36+J38+J43+J45+J50+J52+J54+J56+J58+J63+J67+J69 -> 38554.038 | K71: =+K27+K29+K31+K36+K38+K43+K45+K50+K52+K54+K56+K58+K63+K67+K69 -> 37253.068 | L71: =+L27+L29+L31+L36+L38+L43+L45+L50+L52+L54+L56+L58+L63+L67+L69 -> 33466.808 | ... Q71: =+Q27+Q29+Q31+Q36+Q38+Q43+Q45+Q50+Q52+Q54+Q56+Q58+Q63+Q67+Q69 -> 480776.24 | R71: =Q71/$B$4 -> 8.9019449 | S71: =+S27+S29+S31+S36+S38+S43+S45+S50+S52+S54+S56+S58+S63+S67+S69 -> 496602.73 | T71: =IFERROR(Q71/S71-1,"-") -> -0.031869521 | V71: =Q71-Q58-Q29 -> 326110.7
B73: Non-Reimbursable Expenses
A75: 5210-0000 | C75: Bad Debt | E75: 0 | F75: 0 | G75: 0 | H75: 0 | I75: 0 | J75: 0 | K75: 0 | L75: 0 | M75: 0 | N75: 0 | O75: 0 | P75: 0 | Q75: =SUM(E75:P75) -> 0 | R75: =Q75/$B$4 -> 0 | T75: =IFERROR(Q75/S75-1,"-") -> -
A77: 6010-8501 | D77: Salaries & Wages | E77: ='Allocated Expenses'!F85 -> 1368.919 | F77: ='Allocated Expenses'!G85 -> 1368.919 | G77: ='Allocated Expenses'!H85 -> 1368.919 | H77: ='Allocated Expenses'!I85 -> 1368.919 | I77: ='Allocated Expenses'!J85 -> 1368.919 | J77: ='Allocated Expenses'!K85 -> 1368.919 | K77: ='Allocated Expenses'!L85 -> 1368.919 | L77: ='Allocated Expenses'!M85 -> 1368.919 | ... P77: ='Allocated Expenses'!Q85 -> 1368.919 | Q77: =SUM(E77:P77) -> 16427.028 | R77: =Q77/$B$4 -> 0.30415917 | V77: Based on 2026 Payroll budget
A78: 6620-8501 | D78: Commissions-Internal Broker | E78: ='Allocated Expenses'!F96 -> 865.2644 | F78: ='Allocated Expenses'!G96 -> 0 | G78: ='Allocated Expenses'!H96 -> 0 | H78: ='Allocated Expenses'!I96 -> 865.2644 | I78: ='Allocated Expenses'!J96 -> 0 | J78: ='Allocated Expenses'!K96 -> 0 | K78: ='Allocated Expenses'!L96 -> 865.2644 | L78: ='Allocated Expenses'!M96 -> 0 | ... P78: ='Allocated Expenses'!Q96 -> 0 | Q78: =SUM(E78:P78) -> 3461.0576 | R78: =Q78/$B$4 -> 0.064084165
C79: Leasing Salaries and Commissions | E79: =SUM(E77:E78) -> 2234.1834 | F79: =SUM(F77:F78) -> 1368.919 | G79: =SUM(G77:G78) -> 1368.919 | H79: =SUM(H77:H78) -> 2234.1834 | I79: =SUM(I77:I78) -> 1368.919 | J79: =SUM(J77:J78) -> 1368.919 | K79: =SUM(K77:K78) -> 2234.1834 | L79: =SUM(L77:L78) -> 1368.919 | ... Q79: =SUM(Q77:Q78) -> 19888.086 | R79: =Q79/$B$4 -> 0.36824333 | S79: 16451.7 | T79: =IFERROR(Q79/S79-1,"-") -> 0.20887726
A81: 6110-8501 | D81: Gas | Q81: =SUM(E81:P81) -> 0 | R81: =Q81/$B$4 -> 0
A82: 6120-8501 | D82: Electric | Q82: =SUM(E82:P82) -> 0 | R82: =Q82/$B$4 -> 0
A83: 6130-8501 | D83: Water & Sewer | Q83: =SUM(E83:P83) -> 0 | R83: =Q83/$B$4 -> 0
C84: Utilities | E84: =SUM(E81:E83) -> 0 | F84: =SUM(F81:F83) -> 0 | G84: =SUM(G81:G83) -> 0 | H84: =SUM(H81:H83) -> 0 | I84: =SUM(I81:I83) -> 0 | J84: =SUM(J81:J83) -> 0 | K84: =SUM(K81:K83) -> 0 | L84: =SUM(L81:L83) -> 0 | ... Q84: =SUM(Q81:Q83) -> 0 | R84: =Q84/$B$4 -> 0 | S84: 278.52 | T84: =IFERROR(Q84/S84-1,"-") -> -1
D86: Building Maint.-Recurring | E86: =1.03*590 -> 607.7 | F86: =1.03*590 -> 607.7 | G86: =1.03*590 -> 607.7 | H86: =1.03*590 -> 607.7 | I86: =1.03*590 -> 607.7 | J86: =1.03*590 -> 607.7 | K86: =1.03*590 -> 607.7 | L86: =1.03*590 -> 607.7 | ... P86: =1.03*590 -> 607.7 | Q86: =SUM(E86:P86) -> 7292.4 | R86: =Q86/$B$4 -> 0.13502444 | U86: DW | V86: 2025 Business Plan grown 3%. New tenant costs/ Meter readings
D87: Building Maint.-Big Projects | Q87: =SUM(E87:P87) -> 0 | R87: =Q87/$B$4 -> 0
A88: 6220-8501 | C88: Building Maintenance | E88: =SUM(E86:E87) -> 607.7 | F88: =SUM(F86:F87) -> 607.7 | G88: =SUM(G86:G87) -> 607.7 | H88: =SUM(H86:H87) -> 607.7 | I88: =SUM(I86:I87) -> 607.7 | J88: =SUM(J86:J87) -> 607.7 | K88: =SUM(K86:K87) -> 607.7 | L88: =SUM(L86:L87) -> 607.7 | ... Q88: =SUM(Q86:Q87) -> 7292.4 | R88: =Q88/$B$4 -> 0.13502444 | S88: 5075.65 | T88: =IFERROR(Q88/S88-1,"-") -> 0.43674209
A90: 6610-8501 | B90: (SC) | C90: Management fee | Q90: =SUM(E90:P90) -> 0 | R90: =Q90/$B$4 -> 0 | T90: =R90/S90-1 -> #DIV/0!
T91: =R91/S91-1 -> #DIV/0!
A92: 7110-8501 | C92: Marketing | E92: ='Allocated Expenses'!F107+'Allocated Expenses'!F118 -> 525.14102 | F92: ='Allocated Expenses'!G107+'Allocated Expenses'!G118 -> 525.14102 | G92: ='Allocated Expenses'!H107+'Allocated Expenses'!H118 -> 525.14102 | H92: ='Allocated Expenses'!I107+'Allocated Expenses'!I118 -> 525.14102 | I92: ='Allocated Expenses'!J107+'Allocated Expenses'!J118 -> 525.14102 | J92: ='Allocated Expenses'!K107+'Allocated Expenses'!K118 -> 525.14102 | K92: ='Allocated Expenses'!L107+'Allocated Expenses'!L118 -> 525.14102 | L92: ='Allocated Expenses'!M107+'Allocated Expenses'!M118 -> 525.14102 | ... P92: ='Allocated Expenses'!Q107+'Allocated Expenses'!Q118 -> 525.14102 | Q92: =SUM(E92:P92) -> 6301.6923 | R92: =Q92/$B$4 -> 0.11668072 | S92: 6000 | T92: =IFERROR(Q92/S92-1,"-") -> 0.050282048
A94: 8210-8501 | C94: Business Taxes | E94: ='Allocated Expenses'!F129 -> 0 | F94: ='Allocated Expenses'!G129 -> 0 | G94: ='Allocated Expenses'!H129 -> 0 | H94: ='Allocated Expenses'!I129 -> 1619.1844 | I94: ='Allocated Expenses'!J129 -> 0 | J94: ='Allocated Expenses'!K129 -> 0 | K94: ='Allocated Expenses'!L129 -> 0 | L94: ='Allocated Expenses'!M129 -> 0 | ... P94: ='Allocated Expenses'!Q129 -> 0 | Q94: =SUM(E94:P94) -> 1619.1844 | R94: =Q94/$B$4 -> 0.029980456 | S94: 0 | T94: =IFERROR(Q94/S94-1,"-") -> -
A96: 8310-8501 | C96: Legal & Accounting | E96: ='Allocated Expenses'!F141 -> 479.93216 | F96: ='Allocated Expenses'!G141 -> 479.93216 | G96: ='Allocated Expenses'!H141 -> 479.93216 | H96: ='Allocated Expenses'!I141 -> 479.93216 | I96: ='Allocated Expenses'!J141 -> 479.93216 | J96: ='Allocated Expenses'!K141 -> 479.93216 | K96: ='Allocated Expenses'!L141 -> 479.93216 | L96: ='Allocated Expenses'!M141 -> 479.93216 | ... P96: ='Allocated Expenses'!Q141 -> 479.93216 | Q96: =SUM(E96:P96) -> 5759.1859 | R96: =Q96/$B$4 -> 0.10663579 | S96: 5821.26 | T96: =IFERROR(Q96/S96-1,"-") -> -0.010663345
A98: 8190-8501 | D98: Bank Fees | E98: ='Allocated Expenses'!F152 -> 21.701615 | F98: ='Allocated Expenses'!G152 -> 21.701615 | G98: ='Allocated Expenses'!H152 -> 21.701615 | H98: ='Allocated Expenses'!I152 -> 21.701615 | I98: ='Allocated Expenses'!J152 -> 21.701615 | J98: ='Allocated Expenses'!K152 -> 21.701615 | K98: ='Allocated Expenses'!L152 -> 21.701615 | L98: ='Allocated Expenses'!M152 -> 21.701615 | ... P98: ='Allocated Expenses'!Q152 -> 21.701615 | Q98: =SUM(E98:P98) -> 260.41938 | R98: =Q98/$B$4 -> 0.0048218668
A99: 8930-8501 | D99: Office Supplies | E99: ='Allocated Expenses'!F163 -> 0 | F99: ='Allocated Expenses'!G163 -> 0 | G99: ='Allocated Expenses'!H163 -> 0 | H99: ='Allocated Expenses'!I163 -> 0 | I99: ='Allocated Expenses'!J163 -> 0 | J99: ='Allocated Expenses'!K163 -> 0 | K99: ='Allocated Expenses'!L163 -> 0 | L99: ='Allocated Expenses'!M163 -> 0 | ... P99: ='Allocated Expenses'!Q163 -> 0 | Q99: =SUM(E99:P99) -> 0 | R99: =Q99/$B$4 -> 0
A100: 8950-8501 | D100: Postage | E100: ='Allocated Expenses'!F174 -> 0 | F100: ='Allocated Expenses'!G174 -> 0 | G100: ='Allocated Expenses'!H174 -> 0 | H100: ='Allocated Expenses'!I174 -> 0 | I100: ='Allocated Expenses'!J174 -> 0 | J100: ='Allocated Expenses'!K174 -> 0 | K100: ='Allocated Expenses'!L174 -> 0 | L100: ='Allocated Expenses'!M174 -> 0 | ... P100: ='Allocated Expenses'!Q174 -> 0 | Q100: =SUM(E100:P100) -> 0 | R100: =Q100/$B$4 -> 0
A101: 8990-8501 | D101: Other G&A Expense | E101: ='Allocated Expenses'!F185 -> 21.001563 | F101: ='Allocated Expenses'!G185 -> 21.001563 | G101: ='Allocated Expenses'!H185 -> 21.001563 | H101: ='Allocated Expenses'!I185 -> 21.001563 | I101: ='Allocated Expenses'!J185 -> 21.001563 | J101: ='Allocated Expenses'!K185 -> 21.001563 | K101: ='Allocated Expenses'!L185 -> 21.001563 | L101: ='Allocated Expenses'!M185 -> 21.001563 | ... P101: ='Allocated Expenses'!Q185 -> 21.001563 | Q101: =SUM(E101:P101) -> 252.01876 | R101: =Q101/$B$4 -> 0.0046663227
A102: 8990-9800 | D102: Other G&A-allocated from LIK | E102: ='Allocated Expenses'!F196 -> 650 | F102: ='Allocated Expenses'!G196 -> 650 | G102: ='Allocated Expenses'!H196 -> 650 | H102: ='Allocated Expenses'!I196 -> 650 | I102: ='Allocated Expenses'!J196 -> 650 | J102: ='Allocated Expenses'!K196 -> 650 | K102: ='Allocated Expenses'!L196 -> 650 | L102: ='Allocated Expenses'!M196 -> 650 | ... P102: ='Allocated Expenses'!Q196 -> 650 | Q102: =SUM(E102:P102) -> 7800 | R102: =Q102/$B$4 -> 0.14442305
C103: General & Administrative | E103: =SUM(E98:E102) -> 692.70318 | F103: =SUM(F98:F102) -> 692.70318 | G103: =SUM(G98:G102) -> 692.70318 | H103: =SUM(H98:H102) -> 692.70318 | I103: =SUM(I98:I102) -> 692.70318 | J103: =SUM(J98:J102) -> 692.70318 | K103: =SUM(K98:K102) -> 692.70318 | L103: =SUM(L98:L102) -> 692.70318 | ... Q103: =SUM(Q98:Q102) -> 8312.4381 | R103: =Q103/$B$4 -> 0.15391124 | S103: 8040 | T103: =IFERROR(Q103/S103-1,"-") -> 0.03388534
C105: Total Non-Reimbursable Expenses | E105: =+E75+E79+E84+E88+E90+E92+E94+E96+E103 -> 4539.6598 | F105: =+F75+F79+F84+F88+F90+F92+F94+F96+F103 -> 3674.3954 | G105: =+G75+G79+G84+G88+G90+G92+G94+G96+G103 -> 3674.3954 | H105: =+H75+H79+H84+H88+H90+H92+H94+H96+H103 -> 6158.8442 | I105: =+I75+I79+I84+I88+I90+I92+I94+I96+I103 -> 3674.3954 | J105: =+J75+J79+J84+J88+J90+J92+J94+J96+J103 -> 3674.3954 | K105: =+K75+K79+K84+K88+K90+K92+K94+K96+K103 -> 4539.6598 | L105: =+L75+L79+L84+L88+L90+L92+L94+L96+L103 -> 3674.3954 | ... Q105: =+Q75+Q79+Q84+Q88+Q90+Q92+Q94+Q96+Q103 -> 49172.987 | R105: =Q105/$B$4 -> 0.91047598 | S105: =+S75+S79+S84+S88+S90+S92+S94+S96+S103 -> 41667.13 | T105: =IFERROR(Q105/S105-1,"-") -> 0.18013856
B107: TOTAL OPERATING EXPENSES | E107: =+E71+E105 -> 45197.743 | F107: =+F71+F105 -> 39048.959 | G107: =+G71+G105 -> 55433.533 | H107: =+H71+H105 -> 47544.382 | I107: =+I71+I105 -> 37500.173 | J107: =+J71+J105 -> 42228.433 | K107: =+K71+K105 -> 41792.727 | L107: =+L71+L105 -> 37141.203 | ... Q107: =+Q71+Q105 -> 529949.23 | R107: =Q107/$B$4 -> 9.8124209 | S107: =+S71+S105 -> 538269.86 | T107: =IFERROR(Q107/S107-1,"-") -> -0.01545811
B109: NET OPERATING INCOME | E109: =+E24-E107 -> 14879.103 | F109: =+F24-F107 -> 19682.89 | G109: =+G24-G107 -> 2498.1136 | H109: =+H24-H107 -> 10175.202 | I109: =+I24-I107 -> 19303.805 | J109: =+J24-J107 -> 14948.7 | K109: =+K24-K107 -> 16032.819 | L109: =+L24-L107 -> 20791.545 | ... Q109: =+Q24-Q107 -> 166132.82 | R109: =Q109/$B$4 -> 3.076078 | S109: =+S24-S107 -> 92335.7 | T109: =IFERROR(Q109/S109-1,"-") -> 0.7992263
A111: 1420-0000 | D111: Land Improvements | Q111: =SUM(E111:P111) -> 0 | R111: =Q111/$B$4 -> 0
A112: 1430-0000 | D112: Buildings | Q112: =SUM(E112:P112) -> 0 | R112: =Q112/$B$4 -> 0
A113: 1450-0000 | D113: Equipment | Q113: =SUM(E113:P113) -> 0 | R113: =Q113/$B$4 -> 0
A114: 1980-0000 | D114: Capital Improvements | Q114: =SUM(E114:P114) -> 0 | R114: =Q114/$B$4 -> 0
C115: Capital Improvements | E115: =SUM(E111:E114) -> 0 | F115: =SUM(F111:F114) -> 0 | G115: =SUM(G111:G114) -> 0 | H115: =SUM(H111:H114) -> 0 | I115: =SUM(I111:I114) -> 0 | J115: =SUM(J111:J114) -> 0 | K115: =SUM(K111:K114) -> 0 | L115: =SUM(L111:L114) -> 0 | ... Q115: =SUM(Q111:Q114) -> 0 | R115: =Q115/$B$4 -> 0 | T115: =IFERROR(Q115/S115-1,"-") -> -
A117: 1440-0000 | C117: Tenant Improvements | E117: ='Renew & Vac'!AJ11 -> 0 | F117: ='Renew & Vac'!AK11 -> 0 | G117: ='Renew & Vac'!AL11 -> 0 | H117: ='Renew & Vac'!AM11 -> 11301 | I117: ='Renew & Vac'!AN11 -> 0 | J117: ='Renew & Vac'!AO11 -> 0 | K117: ='Renew & Vac'!AP11 -> 0 | L117: ='Renew & Vac'!AQ11 -> 0 | ... P117: ='Renew & Vac'!AU11 -> 0 | Q117: =SUM(E117:P117) -> 22737 | R117: =Q117/$B$4 -> 0.42099319 | S117: 3100 | T117: =IFERROR(Q117/S117-1,"-") -> 6.3345161
A119: 1940-8501 | D119: Deferred Marketing | Q119: =SUM(E119:P119) -> 0 | R119: =Q119/$B$4 -> 0
A120: 1940-8501 | D120: Outside Leasing Commissions | E120: ='Renew & Vac'!AJ12 -> 0 | F120: ='Renew & Vac'!AK12 -> 0 | G120: ='Renew & Vac'!AL12 -> 0 | H120: ='Renew & Vac'!AM12 -> 0 | I120: ='Renew & Vac'!AN12 -> 0 | J120: ='Renew & Vac'!AO12 -> 0 | K120: ='Renew & Vac'!AP12 -> 0 | L120: ='Renew & Vac'!AQ12 -> 0 | ... P120: ='Renew & Vac'!AU12 -> 0 | Q120: =SUM(E120:P120) -> 0 | R120: =Q120/$B$4 -> 0
C121: Outside Leasing Commissions | E121: =SUM(E119:E120) -> 0 | F121: =SUM(F119:F120) -> 0 | G121: =SUM(G119:G120) -> 0 | H121: =SUM(H119:H120) -> 0 | I121: =SUM(I119:I120) -> 0 | J121: =SUM(J119:J120) -> 0 | K121: =SUM(K119:K120) -> 0 | L121: =SUM(L119:L120) -> 0 | ... Q121: =SUM(Q119:Q120) -> 0 | R121: =Q121/$B$4 -> 0 | S121: 560 | T121: =IFERROR(Q121/S121-1,"-") -> -1 | V121: 7/25 Reproj. Is for Capitalized Lease Costs
B123: CASH FLOW BEFORE DEBT SERVICE | E123: =+E109-E115-E117-E121 -> 14879.103 | F123: =+F109-F115-F117-F121 -> 19682.89 | G123: =+G109-G115-G117-G121 -> 2498.1136 | H123: =+H109-H115-H117-H121 -> -1125.7982 | I123: =+I109-I115-I117-I121 -> 19303.805 | J123: =+J109-J115-J117-J121 -> 14948.7 | K123: =+K109-K115-K117-K121 -> 16032.819 | L123: =+L109-L115-L117-L121 -> 20791.545 | ... Q123: =+Q109-Q115-Q117-Q121 -> 143395.82 | R123: =Q123/$B$4 -> 2.6550848 | S123: =+S109-S115-S117-S121 -> 88675.7 | T123: =IFERROR(Q123/S123-1,"-") -> 0.61708134
B125: Debt Service
A126: 9210-8501 | D126: Interest | E126: =+'Allocated Expenses'!F208 -> 12649.602 | F126: =+'Allocated Expenses'!G208 -> 12649.602 | G126: =+'Allocated Expenses'!H208 -> 12649.602 | H126: =+'Allocated Expenses'!I208 -> 12649.602 | I126: =+'Allocated Expenses'!J208 -> 12649.602 | J126: =+'Allocated Expenses'!K208 -> 12649.602 | K126: =+'Allocated Expenses'!L208 -> 12649.602 | L126: =+'Allocated Expenses'!M208 -> 12649.602 | ... P126: =+'Allocated Expenses'!Q208 -> 12649.602 | Q126: =SUM(E126:P126) -> 151795.22 | R126: =Q126/$B$4 -> 2.8106062 | S126: 156974.39 | T126: =IFERROR(Q126/S126-1,"-") -> -0.03299373
A127: 2740-8501 | D127: Mortgage Amortization | E127: =+'Allocated Expenses'!E224 -> 0 | F127: =+'Allocated Expenses'!F224 -> 0 | G127: =+'Allocated Expenses'!G224 -> 0 | H127: =+'Allocated Expenses'!H224 -> 0 | I127: =+'Allocated Expenses'!I224 -> 0 | J127: =+'Allocated Expenses'!J224 -> 0 | K127: =+'Allocated Expenses'!K224 -> 0 | L127: =+'Allocated Expenses'!L224 -> 0 | ... P127: =+'Allocated Expenses'!P224 -> 0 | Q127: =SUM(E127:P127) -> 0 | R127: =Q127/$B$4 -> 0 | S127: 16694.65 | T127: =IFERROR(Q127/S127-1,"-") -> -1
A128: 2740-0000 | D128: Loan Proceeds | Q128: =SUM(E128:P128) -> 0 | R128: =Q128/$B$4 -> 0 | T128: =IFERROR(Q128/S128-1,"-") -> -
C129: Total Debt Service | E129: =SUM(E126:E128) -> 12649.602 | F129: =SUM(F126:F128) -> 12649.602 | G129: =SUM(G126:G128) -> 12649.602 | H129: =SUM(H126:H128) -> 12649.602 | I129: =SUM(I126:I128) -> 12649.602 | J129: =SUM(J126:J128) -> 12649.602 | K129: =SUM(K126:K128) -> 12649.602 | L129: =SUM(L126:L128) -> 12649.602 | ... Q129: =SUM(Q126:Q128) -> 151795.22 | R129: =Q129/$B$4 -> 2.8106062 | S129: =SUM(S126:S128) -> 173669.04 | T129: =Q129/S129-1 -> -0.12595118
B131: CASH FLOW AFTER DEBT SERVICE | E131: =+E123-E129 -> 2229.5011 | F131: =+F123-F129 -> 7033.2887 | G131: =+G123-G129 -> -10151.488 | H131: =+H123-H129 -> -13775.4 | I131: =+I123-I129 -> 6654.2037 | J131: =+J123-J129 -> 2299.0983 | K131: =+K123-K129 -> 3383.2171 | L131: =+L123-L129 -> 8141.9429 | ... Q131: =+Q123-Q129 -> -8399.3993 | R131: =Q131/$B$4 -> -0.15552139 | S131: =+S123-S129 -> -84993.34 | T131: =IFERROR(Q131/S131-1,"-") -> -0.90117579
B137: ="Rental Summary by Month "&C1 -> Rental Summary by Month
B138: Suite | D138: Tenant | E138: =E159 -> 46023 | F138: =F159 -> 46054 | G138: =G159 -> 46082 | H138: =H159 -> 46113 | I138: =I159 -> 46143 | J138: =J159 -> 46174 | K138: =K159 -> 46204 | L138: =L159 -> 46235 | ... P138: =P159 -> 46357 | Q138: Total
B139: =B160 -> 4050-101 | D139: =IF(D160="None",D180,D160) -> VACANT | E139: =SUMIF($B$160:$B$175,$B139,E$160:E$175)+SUMIF($B$181:$B$196,$B139,E$181:E$196) -> 0 | F139: =SUMIF($B$160:$B$175,$B139,F$160:F$175)+SUMIF($B$181:$B$196,$B139,F$181:F$196) -> 0 | G139: =SUMIF($B$160:$B$175,$B139,G$160:G$175)+SUMIF($B$181:$B$196,$B139,G$181:G$196) -> 0 | H139: =SUMIF($B$160:$B$175,$B139,H$160:H$175)+SUMIF($B$181:$B$196,$B139,H$181:H$196) -> 0 | I139: =SUMIF($B$160:$B$175,$B139,I$160:I$175)+SUMIF($B$181:$B$196,$B139,I$181:I$196) -> 0 | J139: =SUMIF($B$160:$B$175,$B139,J$160:J$175)+SUMIF($B$181:$B$196,$B139,J$181:J$196) -> 0 | K139: =SUMIF($B$160:$B$175,$B139,K$160:K$175)+SUMIF($B$181:$B$196,$B139,K$181:K$196) -> 0 | L139: =SUMIF($B$160:$B$175,$B139,L$160:L$175)+SUMIF($B$181:$B$196,$B139,L$181:L$196) -> 0 | ... P139: =SUMIF($B$160:$B$175,$B139,P$160:P$175)+SUMIF($B$181:$B$196,$B139,P$181:P$196) -> 0 | Q139: =SUM(E139:P139) -> 0
B140: =B161 -> 4050-113 | D140: =IF(D161="None",D181,D161) -> American Bread Company LLC | E140: =SUMIF($B$160:$B$175,$B140,E$160:E$175)+SUMIF($B$181:$B$196,$B140,E$181:E$196) -> 2601.63 | F140: =SUMIF($B$160:$B$175,$B140,F$160:F$175)+SUMIF($B$181:$B$196,$B140,F$181:F$196) -> 2601.63 | G140: =SUMIF($B$160:$B$175,$B140,G$160:G$175)+SUMIF($B$181:$B$196,$B140,G$181:G$196) -> 2601.63 | H140: =SUMIF($B$160:$B$175,$B140,H$160:H$175)+SUMIF($B$181:$B$196,$B140,H$181:H$196) -> 2601.63 | I140: =SUMIF($B$160:$B$175,$B140,I$160:I$175)+SUMIF($B$181:$B$196,$B140,I$181:I$196) -> 2601.63 | J140: =SUMIF($B$160:$B$175,$B140,J$160:J$175)+SUMIF($B$181:$B$196,$B140,J$181:J$196) -> 2601.63 | K140: =SUMIF($B$160:$B$175,$B140,K$160:K$175)+SUMIF($B$181:$B$196,$B140,K$181:K$196) -> 2601.63 | L140: =SUMIF($B$160:$B$175,$B140,L$160:L$175)+SUMIF($B$181:$B$196,$B140,L$181:L$196) -> 2601.63 | ... P140: =SUMIF($B$160:$B$175,$B140,P$160:P$175)+SUMIF($B$181:$B$196,$B140,P$181:P$196) -> 2601.63 | Q140: =SUM(E140:P140) -> 31219.56
B141: =B162 -> 4050-115 | D141: =IF(D162="None",D183,D162) -> SKH Abstract Agency Inc. | E141: =SUMIF($B$160:$B$175,$B141,E$160:E$175)+SUMIF($B$181:$B$196,$B141,E$181:E$196) -> 1046.79 | F141: =SUMIF($B$160:$B$175,$B141,F$160:F$175)+SUMIF($B$181:$B$196,$B141,F$181:F$196) -> 1046.79 | G141: =SUMIF($B$160:$B$175,$B141,G$160:G$175)+SUMIF($B$181:$B$196,$B141,G$181:G$196) -> 1046.79 | H141: =SUMIF($B$160:$B$175,$B141,H$160:H$175)+SUMIF($B$181:$B$196,$B141,H$181:H$196) -> 1046.79 | I141: =SUMIF($B$160:$B$175,$B141,I$160:I$175)+SUMIF($B$181:$B$196,$B141,I$181:I$196) -> 1046.79 | J141: =SUMIF($B$160:$B$175,$B141,J$160:J$175)+SUMIF($B$181:$B$196,$B141,J$181:J$196) -> 1046.79 | K141: =SUMIF($B$160:$B$175,$B141,K$160:K$175)+SUMIF($B$181:$B$196,$B141,K$181:K$196) -> 1046.79 | L141: =SUMIF($B$160:$B$175,$B141,L$160:L$175)+SUMIF($B$181:$B$196,$B141,L$181:L$196) -> 1046.79 | ... P141: =SUMIF($B$160:$B$175,$B141,P$160:P$175)+SUMIF($B$181:$B$196,$B141,P$181:P$196) -> 1046.79 | Q141: =SUM(E141:P141) -> 12561.48
B142: =B163 -> 4050-117 | D142: =IF(D163="None",D184,D163) -> VACANT | E142: =SUMIF($B$160:$B$175,$B142,E$160:E$175)+SUMIF($B$181:$B$196,$B142,E$181:E$196) -> 0 | F142: =SUMIF($B$160:$B$175,$B142,F$160:F$175)+SUMIF($B$181:$B$196,$B142,F$181:F$196) -> 0 | G142: =SUMIF($B$160:$B$175,$B142,G$160:G$175)+SUMIF($B$181:$B$196,$B142,G$181:G$196) -> 0 | H142: =SUMIF($B$160:$B$175,$B142,H$160:H$175)+SUMIF($B$181:$B$196,$B142,H$181:H$196) -> 0 | I142: =SUMIF($B$160:$B$175,$B142,I$160:I$175)+SUMIF($B$181:$B$196,$B142,I$181:I$196) -> 0 | J142: =SUMIF($B$160:$B$175,$B142,J$160:J$175)+SUMIF($B$181:$B$196,$B142,J$181:J$196) -> 0 | K142: =SUMIF($B$160:$B$175,$B142,K$160:K$175)+SUMIF($B$181:$B$196,$B142,K$181:K$196) -> 0 | L142: =SUMIF($B$160:$B$175,$B142,L$160:L$175)+SUMIF($B$181:$B$196,$B142,L$181:L$196) -> 0 | ... P142: =SUMIF($B$160:$B$175,$B142,P$160:P$175)+SUMIF($B$181:$B$196,$B142,P$181:P$196) -> 0 | Q142: =SUM(E142:P142) -> 0
...

Sheet 4060
B1: 4060 | J1: =+'NI LLC-Consolidated'!J1 -> Operating Budget | Q1: ='NI LLC-Consolidated'!Q1 -> 46023
J2: =+'NI LLC-Consolidated'!J2 -> Neshaminy Interplex LLC
Q3: =Q1 -> 46023 | S3: 7/2025 Reprojections
B4: 107890 | E4: Jan | F4: Feb | G4: Mar | H4: Apr | I4: May | J4: Jun | K4: Jul | L4: Aug | M4: Sep | N4: Oct | O4: Nov | P4: Dec | Q4: Total | R4: Total PSF | S4: Total | T4: Var. | U4: Input | V4: Notes
D6: Occupancy % | E6: ='Renew & Vac'!AJ31 -> 0.6534 | F6: ='Renew & Vac'!AK31 -> 0.6534 | G6: ='Renew & Vac'!AL31 -> 0.6534 | H6: ='Renew & Vac'!AM31 -> 0.6534 | I6: ='Renew & Vac'!AN31 -> 0.6534 | J6: ='Renew & Vac'!AO31 -> 0.6534 | K6: ='Renew & Vac'!AP31 -> 0.613 | L6: ='Renew & Vac'!AQ31 -> 0.613 | ... P6: ='Renew & Vac'!AU31 -> 0.5744
D7: Occupancy SF | E7: =$B$4*E6 -> 70495.326 | F7: =$B$4*F6 -> 70495.326 | G7: =$B$4*G6 -> 70495.326 | H7: =$B$4*H6 -> 70495.326 | I7: =$B$4*I6 -> 70495.326 | J7: =$B$4*J6 -> 70495.326 | K7: =$B$4*K6 -> 66136.57 | L7: =$B$4*L6 -> 66136.57 | ... P7: =$B$4*P6 -> 61972.016
B8: Revenues
A10: 4230-8501 | C10: Rental Income - In Place | E10: =SUMIFS('In Place Revenue'!$G:$G,'In Place Revenue'!$A:$A,"4060",'In Place Revenue'!$H:$H,1) -> 54229.9 | F10: =SUMIFS('In Place Revenue'!$G:$G,'In Place Revenue'!$A:$A,"4060",'In Place Revenue'!$H:$H,2) -> 54337.61 | G10: =SUMIFS('In Place Revenue'!$G:$G,'In Place Revenue'!$A:$A,"4060",'In Place Revenue'!$H:$H,3) -> 54337.61 | H10: =SUMIFS('In Place Revenue'!$G:$G,'In Place Revenue'!$A:$A,"4060",'In Place Revenue'!$H:$H,4) -> 52492.35 | I10: =SUMIFS('In Place Revenue'!$G:$G,'In Place Revenue'!$A:$A,"4060",'In Place Revenue'!$H:$H,5) -> 53299.93 | J10: =SUMIFS('In Place Revenue'!$G:$G,'In Place Revenue'!$A:$A,"4060",'In Place Revenue'!$H:$H,6) -> 53299.93 | K10: =SUMIFS('In Place Revenue'!$G:$G,'In Place Revenue'!$A:$A,"4060",'In Place Revenue'!$H:$H,7) -> 39646.43 | L10: =SUMIFS('In Place Revenue'!$G:$G,'In Place Revenue'!$A:$A,"4060",'In Place Revenue'!$H:$H,8) -> 37862.18 | M10: =SUMIFS('In Place Revenue'!$G:$G,'In Place Revenue'!$A:$A,"4060",'In Place Revenue'!$H:$H,9) -> 37862.18 | N10: =SUMIFS('In Place Revenue'!$G:$G,'In Place Revenue'!$A:$A,"4060",'In Place Revenue'!$H:$H,10) -> 37862.18 | O10: =SUMIFS('In Place Revenue'!$G:$G,'In Place Revenue'!$A:$A,"4060",'In Place Revenue'!$H:$H,11) -> 37924.89 | P10: =SUMIFS('In Place Revenue'!$G:$G,'In Place Revenue'!$A:$A,"4060",'In Place Revenue'!$H:$H,12) -> 37924.89 | Q10: =SUM(E10:P10) -> 551080.08 | R10: =Q10/$B$4 -> 5.1077957 | S10: 1653515 | T10: =IFERROR(Q10/S10-1,"-") -> -0.66672206
A11: 4230-8501 | C11: Rental Income - New & Renewal | E11: ='Renew & Vac'!AJ32 -> 47531.333 | F11: ='Renew & Vac'!AK32 -> 47531.333 | G11: ='Renew & Vac'!AL32 -> 47531.333 | H11: ='Renew & Vac'!AM32 -> 49531.5 | I11: ='Renew & Vac'!AN32 -> 49531.5 | J11: ='Renew & Vac'!AO32 -> 49531.5 | K11: ='Renew & Vac'!AP32 -> 57621.75 | L11: ='Renew & Vac'!AQ32 -> 59360.25 | ... P11: ='Renew & Vac'!AU32 -> 52963.875 | Q11: =SUM(E11:P11) -> 636428.12 | R11: =Q11/$B$4 -> 5.8988611 | T11: =IFERROR(Q11/S11-1,"-") -> -
A12: 4240-8501 | C12: Percentage Rent | E12: 0 | F12: 0 | G12: 0 | H12: 0 | I12: 0 | J12: 0 | K12: 0 | L12: 0 | M12: 0 | N12: 0 | O12: 0 | P12: 0 | Q12: =SUM(E12:P12) -> 0 | R12: =Q12/$B$4 -> 0 | T12: =R12/S12-1 -> #DIV/0!
A13: 4990-8501 | C13: Miscellaneous | E13: 0 | F13: 0 | G13: 0 | H13: 0 | I13: 0 | J13: 0 | K13: 0 | L13: 0 | M13: 0 | N13: 0 | O13: 0 | P13: 0 | Q13: =SUM(E13:P13) -> 0 | R13: =Q13/$B$4 -> 0 | S13: 467 | T13: =IFERROR(Q13/S13-1,"-") -> -1
A14: 9190-8501 | C14: Interest Income | E14: 0 | F14: 0 | G14: 0 | H14: 0 | I14: 0 | J14: 0 | K14: 0 | L14: 0 | M14: 0 | N14: 0 | O14: 0 | P14: 0 | Q14: =SUM(E14:P14) -> 0 | R14: =Q14/$B$4 -> 0 | S14: 0 | T14: =IFERROR(Q14/S14-1,"-") -> -
C15: Total Rental and Other | E15: =SUM(E10:E14) -> 101761.23 | F15: =SUM(F10:F14) -> 101868.94 | G15: =SUM(G10:G14) -> 101868.94 | H15: =SUM(H10:H14) -> 102023.85 | I15: =SUM(I10:I14) -> 102831.43 | J15: =SUM(J10:J14) -> 102831.43 | K15: =SUM(K10:K14) -> 97268.18 | L15: =SUM(L10:L14) -> 97222.43 | ... Q15: =SUM(Q10:Q14) -> 1187508.2 | R15: =Q15/$B$4 -> 11.006657 | S15: =SUM(S10:S14) -> 1653982 | T15: =IFERROR(Q15/S15-1,"-") -> -0.28203077
B17: Reimbursements
A18: 4710-8502 | C18: Electric | E18: =E6*E29 -> 19858.133 | F18: =F6*F29 -> 18738.205 | G18: =G6*G29 -> 18762.381 | H18: =H6*H29 -> 18778.063 | I18: =I6*I29 -> 19935.234 | J18: =J6*J29 -> 21802.651 | K18: =K6*K29 -> 22186.309 | L18: =L6*L29 -> 21530.399 | ... P18: =P6*P29 -> 18138.403 | Q18: =SUM(E18:P18) -> 235636.96 | R18: =Q18/$B$4 -> 2.1840482 | S18: 227260.63 | T18: =IFERROR(Q18/S18-1,"-") -> 0.036857831 | U18: DW | V18: =Q18/Q29*100&"% Set to occupancy" -> 62.8006854488372% Set to occupancy
A19: 4910-8502 | C19: Common Area Maintenance | E19: =+'Tenant Recoveries'!G21 -> 2000 | F19: =+E19 -> 2000 | G19: =+F19 -> 2000 | H19: =+G19 -> 2000 | I19: =+H19 -> 2000 | J19: =+I19 -> 2000 | K19: =+J19 -> 2000 | L19: =+K19 -> 2000 | M19: =+L19 -> 2000 | ... P19: =+O19 -> 2000 | Q19: =SUM(E19:P19) -> 24000 | R19: =Q19/$B$4 -> 0.22244879 | S19: 62160 | T19: =IFERROR(Q19/S19-1,"-") -> -0.61389961 | V19: =Q19/(Q71-Q63-Q58-Q29) -> 0.046449376
A20: 4920-8502 | C20: Real Estate Taxes | E20: =+'Tenant Recoveries'!G22 -> 0 | F20: =+E20 -> 0 | G20: =+F20 -> 0 | H20: =+G20 -> 0 | I20: =+H20 -> 0 | J20: =+I20 -> 0 | K20: =+J20 -> 0 | L20: =+K20 -> 0 | M20: =+L20 -> 0 | ... P20: =+O20 -> 0 | Q20: =SUM(E20:P20) -> 0 | R20: =Q20/$B$4 -> 0 | S20: 0 | T20: =IFERROR(Q20/S20-1,"-") -> - | V20: =Q20/Q58 -> 0
A21: 4930-8502 | C21: Insurance | Q21: =SUM(E21:P21) -> 0 | R21: =Q21/$B$4 -> 0 | S21: 0 | T21: =IFERROR(Q21/S21-1,"-") -> -
C22: Total Reimbursements | E22: =SUM(E18:E21) -> 21858.133 | F22: =SUM(F18:F21) -> 20738.205 | G22: =SUM(G18:G21) -> 20762.381 | H22: =SUM(H18:H21) -> 20778.063 | I22: =SUM(I18:I21) -> 21935.234 | J22: =SUM(J18:J21) -> 23802.651 | K22: =SUM(K18:K21) -> 24186.309 | L22: =SUM(L18:L21) -> 23530.399 | ... Q22: =SUM(Q18:Q21) -> 259636.96 | R22: =Q22/$B$4 -> 2.406497 | S22: =SUM(S18:S21) -> 289420.63 | T22: =IFERROR(Q22/S22-1,"-") -> -0.10290789
R23: =Q23/$B$4 -> 0
B24: TOTAL REVENUES | E24: =+E15+E22 -> 123619.37 | F24: =+F15+F22 -> 122607.15 | G24: =+G15+G22 -> 122631.32 | H24: =+H15+H22 -> 122801.91 | I24: =+I15+I22 -> 124766.66 | J24: =+J15+J22 -> 126634.08 | K24: =+K15+K22 -> 121454.49 | L24: =+L15+L22 -> 120752.83 | ... Q24: =+Q15+Q22 -> 1447145.2 | R24: =Q24/$B$4 -> 13.413154 | S24: =+S15+S22 -> 1943402.7 | T24: =IFERROR(Q24/S24-1,"-") -> -0.25535495
B26: Reimbursable Expenses
A27: 6030-8502 | C27: Maintenance Salaries | E27: ='Allocated Expenses'!F7 -> 2207.2986 | F27: ='Allocated Expenses'!G7 -> 2207.2986 | G27: ='Allocated Expenses'!H7 -> 2207.2986 | H27: ='Allocated Expenses'!I7 -> 2207.2986 | I27: ='Allocated Expenses'!J7 -> 2207.2986 | J27: ='Allocated Expenses'!K7 -> 2207.2986 | K27: ='Allocated Expenses'!L7 -> 2207.2986 | L27: ='Allocated Expenses'!M7 -> 2207.2986 | ... P27: ='Allocated Expenses'!Q7 -> 2207.2986 | Q27: =SUM(E27:P27) -> 26487.584 | R27: =Q27/$B$4 -> 0.24550546 | S27: 18600 | T27: =IFERROR(Q27/S27-1,"-") -> 0.42406363
A29: 6120-8502 | C29: Electric | E29: 30392 | F29: 28678 | G29: 28715 | H29: 28739 | I29: 30510 | J29: 33368 | K29: 36193 | L29: 35123 | M29: 32500 | N29: 31485 | O29: 27933 | P29: 31578 | Q29: =SUM(E29:P29) -> 375214 | R29: =Q29/$B$4 -> 3.4777459 | S29: 328077.74 | T29: =IFERROR(Q29/S29-1,"-") -> 0.14367406 | U29: DW | V29: Data\Shared\Properties\Business Plans - All Entities\2026\ISG Electric data
A31: 6130-8502 | C31: Water & Sewer | E31: ='Water Sewer'!D16 -> 1408.01 | F31: ='Water Sewer'!E16 -> 1529.55 | G31: ='Water Sewer'!F16 -> 1479.08 | H31: ='Water Sewer'!G16 -> 1526.46 | I31: ='Water Sewer'!H16 -> 3337.2 | J31: ='Water Sewer'!I16 -> 5896.75 | K31: ='Water Sewer'!J16 -> 6328.32 | L31: ='Water Sewer'!K16 -> 9496.6 | ... P31: ='Water Sewer'!O16 -> 1532.64 | Q31: =SUM(E31:P31) -> 42662.6 | R31: =Q31/$B$4 -> 0.39542682 | S31: 33314.35 | T31: =IFERROR(Q31/S31-1,"-") -> 0.28060731 | U31: AK | V31: 2025 Business Plan grown 3%
D33: Building Maint.-Contractual | E33: ='Building Maint'!C18 -> 1139 | F33: ='Building Maint'!D18 -> 4189 | G33: ='Building Maint'!E18 -> 7015 | H33: ='Building Maint'!F18 -> 8951 | I33: ='Building Maint'!G18 -> 4189 | J33: ='Building Maint'!H18 -> 7015 | K33: ='Building Maint'!I18 -> 1139 | L33: ='Building Maint'!J18 -> 4189 | ... P33: ='Building Maint'!N18 -> 310 | Q33: =SUM(E33:P33) -> 58291 | R33: =Q33/$B$4 -> 0.54028177 | U33: DW | V33: 2025 Business Plan grown 3%
D34: Building Maint.-Recurring | E34: ='Building Maint'!C7 -> 4205 | F34: ='Building Maint'!D7 -> 2700 | G34: ='Building Maint'!E7 -> 2900 | H34: ='Building Maint'!F7 -> 3325 | I34: ='Building Maint'!G7 -> 5590 | J34: ='Building Maint'!H7 -> 3225 | K34: ='Building Maint'!I7 -> 6160 | L34: ='Building Maint'!J7 -> 2700 | ... P34: ='Building Maint'!N7 -> 2700 | Q34: =SUM(E34:P34) -> 42905 | R34: =Q34/$B$4 -> 0.39767356 | U34: DW | V34: 2025 Business Plan grown 3%
D35: Building Maint.-Big Projects | G35: =1.03*5000 -> 5150 | J35: =1.03*5000 -> 5150 | M35: =1.03*5000 -> 5150 | Q35: =SUM(E35:P35) -> 15450 | R35: =Q35/$B$4 -> 0.14320141 | U35: DW | V35: Contingency for repairs
A36: 6220-8502 | C36: Building Maintenance | E36: =SUM(E33:E35) -> 5344 | F36: =SUM(F33:F35) -> 6889 | G36: =SUM(G33:G35) -> 15065 | H36: =SUM(H33:H35) -> 12276 | I36: =SUM(I33:I35) -> 9779 | J36: =SUM(J33:J35) -> 15390 | K36: =SUM(K33:K35) -> 7299 | L36: =SUM(L33:L35) -> 6889 | ... Q36: =SUM(Q33:Q35) -> 116646 | R36: =Q36/$B$4 -> 1.0811567 | S36: 143720.9 | T36: =IFERROR(Q36/S36-1,"-") -> -0.18838527
A38: 6330-850 | B38: (SC) | C38: Parking Lot Cleaning | Q38: =SUM(E38:P38) -> 0 | R38: =Q38/$B$4 -> 0
D40: Parking Lot Maint.-Contractual | Q40: =SUM(E40:P40) -> 0 | R40: =Q40/$B$4 -> 0
D41: Parking Lot Maint.-Recurring | E41: ='Parking Lot Maint'!C7 -> 1225.7 | F41: ='Parking Lot Maint'!D7 -> 1225.7 | G41: ='Parking Lot Maint'!E7 -> 2152.7 | H41: ='Parking Lot Maint'!F7 -> 1225.7 | I41: ='Parking Lot Maint'!G7 -> 1225.7 | J41: ='Parking Lot Maint'!H7 -> 2152.7 | K41: ='Parking Lot Maint'!I7 -> 1225.7 | L41: ='Parking Lot Maint'!J7 -> 1225.7 | ... P41: ='Parking Lot Maint'!N7 -> 2152.7 | Q41: =SUM(E41:P41) -> 18416.4 | R41: =Q41/$B$4 -> 0.17069608 | U41: DW | V41: 2025 Business Plan grown 3%
D42: Parking Lot Maint.-Big Projects | K42: =1.03*12000 -> 12360 | M42: =1.03*12000 -> 12360 | Q42: =SUM(E42:P42) -> 24720 | R42: =Q42/$B$4 -> 0.22912225 | U42: DW | V42: 2025 Business Plan grown 3%. Includes restriping and pothole repair
A43: 6330-8502 | C43: Parking Lot Maintenance | E43: =SUM(E40:E42) -> 1225.7 | F43: =SUM(F40:F42) -> 1225.7 | G43: =SUM(G40:G42) -> 2152.7 | H43: =SUM(H40:H42) -> 1225.7 | I43: =SUM(I40:I42) -> 1225.7 | J43: =SUM(J40:J42) -> 2152.7 | K43: =SUM(K40:K42) -> 13585.7 | L43: =SUM(L40:L42) -> 1225.7 | ... Q43: =SUM(Q40:Q42) -> 43136.4 | R43: =Q43/$B$4 -> 0.39981833 | S43: 32362.59 | T43: =IFERROR(Q43/S43-1,"-") -> 0.33290939
A45: 6370-8502 | C45: Snow Removal | E45: =1.03*6750 -> 6952.5 | F45: =1.03*6750 -> 6952.5 | G45: =1.03*6750 -> 6952.5 | O45: =1.03*1000 -> 1030 | P45: =1.03*6750 -> 6952.5 | Q45: =SUM(E45:P45) -> 28840 | R45: =Q45/$B$4 -> 0.2673093 | S45: 20763.12 | T45: =IFERROR(Q45/S45-1,"-") -> 0.38900127 | U45: DW | V45: 2025 Business Plan grown 3%
Q46: =SUM(E46:P46) -> 0
D47: Landscaping-Contractual | E47: ='Allocated Expenses'!F18 -> 0 | F47: ='Allocated Expenses'!G18 -> 0 | G47: ='Allocated Expenses'!H18 -> 2100.2168 | H47: ='Allocated Expenses'!I18 -> 2100.2168 | I47: ='Allocated Expenses'!J18 -> 2100.2168 | J47: ='Allocated Expenses'!K18 -> 2100.2168 | K47: ='Allocated Expenses'!L18 -> 2100.2168 | L47: ='Allocated Expenses'!M18 -> 2100.2168 | ... P47: ='Allocated Expenses'!Q18 -> 0 | Q47: =SUM(E47:P47) -> 18901.952 | R47: =Q47/$B$4 -> 0.17519651 | U47: DW | V47: 2025 Business Plan grown 3%
D48: Landscaping-Recurring | E48: =Landscaping!C7 -> 0 | F48: =Landscaping!D7 -> 0 | G48: =Landscaping!E7 -> 824 | H48: =Landscaping!F7 -> 824 | I48: =Landscaping!G7 -> 2369 | J48: =Landscaping!H7 -> 824 | K48: =Landscaping!I7 -> 824 | L48: =Landscaping!J7 -> 824 | ... P48: =Landscaping!N7 -> 0 | Q48: =SUM(E48:P48) -> 9939.5 | R48: =Q48/$B$4 -> 0.09212624 | U48: DW | V48: 2025 Business Plan grown 3%
D49: Landscaping-Big Projects | E49: ='Allocated Expenses'!F29 -> 1131.449 | F49: ='Allocated Expenses'!G29 -> 1131.449 | G49: ='Allocated Expenses'!H29 -> 1131.449 | H49: ='Allocated Expenses'!I29 -> 1131.449 | I49: ='Allocated Expenses'!J29 -> 1131.449 | J49: ='Allocated Expenses'!K29 -> 1131.449 | K49: ='Allocated Expenses'!L29 -> 1131.449 | L49: ='Allocated Expenses'!M29 -> 1131.449 | ... P49: ='Allocated Expenses'!Q29 -> 1131.449 | Q49: =SUM(E49:P49) -> 13577.388 | R49: =Q49/$B$4 -> 0.12584473 | U49: DW | V49: Fountain repairs
A50: 6380-8502 | C50: Landscaping | E50: =SUM(E47:E49) -> 1131.449 | F50: =SUM(F47:F49) -> 1131.449 | G50: =SUM(G47:G49) -> 4055.6659 | H50: =SUM(H47:H49) -> 4055.6659 | I50: =SUM(I47:I49) -> 5600.6659 | J50: =SUM(J47:J49) -> 4055.6659 | K50: =SUM(K47:K49) -> 4055.6659 | L50: =SUM(L47:L49) -> 4055.6659 | ... Q50: =SUM(Q47:Q49) -> 42418.84 | R50: =Q50/$B$4 -> 0.39316748 | S50: 28880.03 | T50: =IFERROR(Q50/S50-1,"-") -> 0.46879487
A52: 6350-8502 | C52: Security | E52: ='Allocated Expenses'!F40 -> 570.24 | F52: ='Allocated Expenses'!G40 -> 570.24 | G52: ='Allocated Expenses'!H40 -> 570.24 | H52: ='Allocated Expenses'!I40 -> 570.24 | I52: ='Allocated Expenses'!J40 -> 570.24 | J52: ='Allocated Expenses'!K40 -> 570.24 | K52: ='Allocated Expenses'!L40 -> 570.24 | L52: ='Allocated Expenses'!M40 -> 570.24 | ... P52: ='Allocated Expenses'!Q40 -> 570.24 | Q52: =SUM(E52:P52) -> 6842.88 | R52: =Q52/$B$4 -> 0.063424599 | S52: 7679.87 | T52: =IFERROR(Q52/S52-1,"-") -> -0.10898492 | U52: DW | V52: 2025 Business Plan grown 3%
A54: 6610-8502 | B54: (BP) | C54: Management Fee | E54: =ROUND(E$24*0.04,0) -> 4945 | F54: =ROUND(F$24*0.04,0) -> 4904 | G54: =ROUND(G$24*0.04,0) -> 4905 | H54: =ROUND(H$24*0.04,0) -> 4912 | I54: =ROUND(I$24*0.04,0) -> 4991 | J54: =ROUND(J$24*0.04,0) -> 5065 | K54: =ROUND(K$24*0.04,0) -> 4858 | L54: =ROUND(L$24*0.04,0) -> 4830 | ... P54: =ROUND(P$24*0.04,0) -> 4441 | Q54: =SUM(E54:P54) -> 57885 | R54: =Q54/$B$4 -> 0.53651868 | S54: 80205.56 | T54: =IFERROR(Q54/S54-1,"-") -> -0.27829193
A56: 6270-8502 | C56: Trash Removal | E56: =Trash!C7 -> 1648 | F56: =Trash!D7 -> 1648 | G56: =Trash!E7 -> 1648 | H56: =Trash!F7 -> 1648 | I56: =Trash!G7 -> 1648 | J56: =Trash!H7 -> 2248 | K56: =Trash!I7 -> 1648 | L56: =Trash!J7 -> 1648 | ... P56: =Trash!N7 -> 2248 | Q56: =SUM(E56:P56) -> 21576 | R56: =Q56/$B$4 -> 0.19998146 | S56: 26196.06 | T56: =IFERROR(Q56/S56-1,"-") -> -0.17636469 | U56: DW | V56: 2025 Business Plan grown 3%. Adjusted semiannual removals
A58: 6410-8502 | C58: Real Estate Taxes | E58: =+'INS RET'!E60 -> 9151.1392 | F58: =+'INS RET'!F60 -> 9151.1392 | G58: =+'INS RET'!G60 -> 9151.1392 | H58: =+'INS RET'!H60 -> 9151.1392 | I58: =+'INS RET'!I60 -> 9151.1392 | J58: =+'INS RET'!J60 -> 9151.1392 | K58: =+'INS RET'!K60 -> 9151.1392 | L58: =+'INS RET'!L60 -> 9151.1392 | ... P58: =+'INS RET'!P60 -> 9151.1392 | Q58: =SUM(E58:P58) -> 109813.67 | R58: =Q58/$B$4 -> 1.0178299 | S58: 210877.78 | T58: =IFERROR(Q58/S58-1,"-") -> -0.47925442 | V58: Based on 2025 tax bill
D60: Insurance-Liability | E60: =+'INS RET'!E13+'INS RET'!E14 -> 2935 | F60: =+'INS RET'!F13+'INS RET'!F14 -> 2935 | G60: =+'INS RET'!G13+'INS RET'!G14 -> 2935 | H60: =+'INS RET'!H13+'INS RET'!H14 -> 2935 | I60: =+'INS RET'!I13+'INS RET'!I14 -> 2935 | J60: =+'INS RET'!J13+'INS RET'!J14 -> 2935 | K60: =+'INS RET'!K13+'INS RET'!K14 -> 2935 | L60: =+'INS RET'!L13+'INS RET'!L14 -> 2935 | ... P60: =+'INS RET'!P13+'INS RET'!P14 -> 2993.7 | Q60: =SUM(E60:P60) -> 35337.4 | R60: =Q60/$B$4 -> 0.32753175
D61: Insurabce-Property | E61: =+'INS RET'!E16 -> 2140 | F61: =+'INS RET'!F16 -> 2140 | G61: =+'INS RET'!G16 -> 2140 | H61: =+'INS RET'!H16 -> 2140 | I61: =+'INS RET'!I16 -> 2140 | J61: =+'INS RET'!J16 -> 2140 | K61: =+'INS RET'!K16 -> 2140 | L61: =+'INS RET'!L16 -> 2140 | ... P61: =+'INS RET'!P16 -> 2182.8 | Q61: =SUM(E61:P61) -> 25765.6 | R61: =Q61/$B$4 -> 0.23881361
D62: Insurance-Other | E62: =+'INS RET'!E17 -> 0 | F62: =+'INS RET'!F17 -> 0 | G62: =+'INS RET'!G17 -> 0 | H62: =+'INS RET'!H17 -> 0 | I62: =+'INS RET'!I17 -> 0 | J62: =+'INS RET'!J17 -> 0 | K62: =+'INS RET'!K17 -> 0 | L62: =+'INS RET'!L17 -> 0 | ... P62: =+'INS RET'!P17 -> 0 | Q62: =SUM(E62:P62) -> 0 | R62: =Q62/$B$4 -> 0
A63: 6510-8502 | C63: Insurance | E63: =SUM(E60:E62) -> 5075 | F63: =SUM(F60:F62) -> 5075 | G63: =SUM(G60:G62) -> 5075 | H63: =SUM(H60:H62) -> 5075 | I63: =SUM(I60:I62) -> 5075 | J63: =SUM(J60:J62) -> 5075 | K63: =SUM(K60:K62) -> 5075 | L63: =SUM(L60:L62) -> 5075 | ... Q63: =SUM(Q60:Q62) -> 61103 | R63: =Q63/$B$4 -> 0.56634535 | S63: 61626 | T63: =IFERROR(Q63/S63-1,"-") -> -0.0084866777
D65: Cleaning & Supplies | E65: ='Allocated Expenses'!F51+'Allocated Expenses'!F62 -> 10908.935 | F65: ='Allocated Expenses'!G51+'Allocated Expenses'!G62 -> 10908.935 | G65: ='Allocated Expenses'!H51+'Allocated Expenses'!H62 -> 10908.935 | H65: ='Allocated Expenses'!I51+'Allocated Expenses'!I62 -> 10908.935 | I65: ='Allocated Expenses'!J51+'Allocated Expenses'!J62 -> 10908.935 | J65: ='Allocated Expenses'!K51+'Allocated Expenses'!K62 -> 10908.935 | K65: ='Allocated Expenses'!L51+'Allocated Expenses'!L62 -> 10306.441 | L65: ='Allocated Expenses'!M51+'Allocated Expenses'!M62 -> 10306.441 | ... P65: ='Allocated Expenses'!Q51+'Allocated Expenses'!Q62 -> 9730.7919 | Q65: =SUM(E65:P65) -> 126482.47 | R65: =Q65/$B$4 -> 1.172328 | U65: DW | V65: Based on occupancy. Includes cleaning, supplies, and porter fee.
D66: Cleaning & Supplies-Vacancies | E66: ='Allocated Expenses'!F75 -> 288.87386 | F66: ='Allocated Expenses'!G75 -> 288.87386 | G66: ='Allocated Expenses'!H75 -> 288.87386 | H66: ='Allocated Expenses'!I75 -> 288.87386 | I66: ='Allocated Expenses'!J75 -> 288.87386 | J66: ='Allocated Expenses'!K75 -> 288.87386 | K66: ='Allocated Expenses'!L75 -> 322.54525 | L66: ='Allocated Expenses'!M75 -> 322.54525 | ... P66: ='Allocated Expenses'!Q75 -> 354.71643 | Q66: =SUM(E66:P66) -> 3713.771 | R66: =Q66/$B$4 -> 0.034421827 | U66: DW | V66: Based on occupancy.
A67: 6250-8502 | B67: (BP) | C67: Cleaning & Supplies | E67: =SUM(E65:E66) -> 11197.809 | F67: =SUM(F65:F66) -> 11197.809 | G67: =SUM(G65:G66) -> 11197.809 | H67: =SUM(H65:H66) -> 11197.809 | I67: =SUM(I65:I66) -> 11197.809 | J67: =SUM(J65:J66) -> 11197.809 | K67: =SUM(K65:K66) -> 10628.987 | L67: =SUM(L65:L66) -> 10628.987 | ... Q67: =SUM(Q65:Q66) -> 130196.24 | R67: =Q67/$B$4 -> 1.2067499 | S67: 152553.69 | T67: =IFERROR(Q67/S67-1,"-") -> -0.14655462
B69: (SC) | C69: Other | E69: 0 | F69: 0 | G69: 0 | H69: 0 | I69: 0 | J69: 0 | K69: 0 | L69: 0 | M69: 0 | N69: 0 | O69: 0 | P69: 0 | Q69: =SUM(E69:P69) -> 0 | R69: =Q69/$B$4 -> 0 | S69: 335 | T69: =IFERROR(Q69/S69-1,"-") -> -1
C71: Total Reimbursable Expenses | E71: =+E27+E29+E31+E36+E38+E43+E45+E50+E52+E54+E56+E58+E63+E67+E69 -> 81248.146 | F71: =+F27+F29+F31+F36+F38+F43+F45+F50+F52+F54+F56+F58+F63+F67+F69 -> 81159.686 | G71: =+G27+G29+G31+G36+G38+G43+G45+G50+G52+G54+G56+G58+G63+G67+G69 -> 93174.432 | H71: =+H27+H29+H31+H36+H38+H43+H45+H50+H52+H54+H56+H58+H63+H67+H69 -> 82584.312 | I71: =+I27+I29+I31+I36+I38+I43+I45+I50+I52+I54+I56+I58+I63+I67+I69 -> 85293.052 | J71: =+J27+J29+J31+J36+J38+J43+J45+J50+J52+J54+J56+J58+J63+J67+J69 -> 96377.602 | K71: =+K27+K29+K31+K36+K38+K43+K45+K50+K52+K54+K56+K58+K63+K67+K69 -> 101600.35 | L71: =+L27+L29+L31+L36+L38+L43+L45+L50+L52+L54+L56+L58+L63+L67+L69 -> 90900.63 | ... Q71: =+Q27+Q29+Q31+Q36+Q38+Q43+Q45+Q50+Q52+Q54+Q56+Q58+Q63+Q67+Q69 -> 1062822.2 | R71: =Q71/$B$4 -> 9.8509799 | S71: =+S27+S29+S31+S36+S38+S43+S45+S50+S52+S54+S56+S58+S63+S67+S69 -> 1145192.7 | T71: =IFERROR(Q71/S71-1,"-") -> -0.071927174 | V71: =Q71-Q58-Q29 -> 577794.55
B73: Non-Reimbursable Expenses
A75: 5210-8501 | C75: Bad Debt | E75: 0 | F75: 0 | G75: 0 | H75: 0 | I75: 0 | J75: 0 | K75: 0 | L75: 0 | M75: 0 | N75: 0 | O75: 0 | P75: 0 | Q75: =SUM(E75:P75) -> 0 | R75: =Q75/$B$4 -> 0 | T75: =IFERROR(Q75/S75-1,"-") -> -
A77: 6010-8501 | D77: Salaries & Wages | E77: ='Allocated Expenses'!F86 -> 2734.6444 | F77: ='Allocated Expenses'!G86 -> 2734.6444 | G77: ='Allocated Expenses'!H86 -> 2734.6444 | H77: ='Allocated Expenses'!I86 -> 2734.6444 | I77: ='Allocated Expenses'!J86 -> 2734.6444 | J77: ='Allocated Expenses'!K86 -> 2734.6444 | K77: ='Allocated Expenses'!L86 -> 2734.6444 | L77: ='Allocated Expenses'!M86 -> 2734.6444 | ... P77: ='Allocated Expenses'!Q86 -> 2734.6444 | Q77: =SUM(E77:P77) -> 32815.733 | R77: =Q77/$B$4 -> 0.30415917
A78: 6620-8501 | D78: Commissions-Internal Broker | E78: ='Allocated Expenses'!F97 -> 1728.5101 | F78: ='Allocated Expenses'!G97 -> 0 | G78: ='Allocated Expenses'!H97 -> 0 | H78: ='Allocated Expenses'!I97 -> 1728.5101 | I78: ='Allocated Expenses'!J97 -> 0 | J78: ='Allocated Expenses'!K97 -> 0 | K78: ='Allocated Expenses'!L97 -> 1728.5101 | L78: ='Allocated Expenses'!M97 -> 0 | ... P78: ='Allocated Expenses'!Q97 -> 0 | Q78: =SUM(E78:P78) -> 6914.0406 | R78: =Q78/$B$4 -> 0.064084165
C79: Leasing Salaries and Commissions | E79: =SUM(E77:E78) -> 4463.1545 | F79: =SUM(F77:F78) -> 2734.6444 | G79: =SUM(G77:G78) -> 2734.6444 | H79: =SUM(H77:H78) -> 4463.1545 | I79: =SUM(I77:I78) -> 2734.6444 | J79: =SUM(J77:J78) -> 2734.6444 | K79: =SUM(K77:K78) -> 4463.1545 | L79: =SUM(L77:L78) -> 2734.6444 | ... Q79: =SUM(Q77:Q78) -> 39729.773 | R79: =Q79/$B$4 -> 0.36824333 | S79: 34389.64 | T79: =IFERROR(Q79/S79-1,"-") -> 0.1552832
A81: 6110-8501 | D81: Gas | Q81: =SUM(E81:P81) -> 0 | R81: =Q81/$B$4 -> 0
A82: 6120-8501 | D82: Electric | Q82: =SUM(E82:P82) -> 0 | R82: =Q82/$B$4 -> 0
A83: 6130-8501 | D83: Water & Sewer | Q83: =SUM(E83:P83) -> 0 | R83: =Q83/$B$4 -> 0
C84: Utilities | E84: =SUM(E81:E83) -> 0 | F84: =SUM(F81:F83) -> 0 | G84: =SUM(G81:G83) -> 0 | H84: =SUM(H81:H83) -> 0 | I84: =SUM(I81:I83) -> 0 | J84: =SUM(J81:J83) -> 0 | K84: =SUM(K81:K83) -> 0 | L84: =SUM(L81:L83) -> 0 | ... Q84: =SUM(Q81:Q83) -> 0 | R84: =Q84/$B$4 -> 0 | S84: 384.75 | T84: =IFERROR(Q84/S84-1,"-") -> -1
D86: Building Maint.-Recurring | E86: =1.03*1075 -> 1107.25 | F86: =1.03*1075 -> 1107.25 | G86: =1.03*1075 -> 1107.25 | H86: =1.03*1075 -> 1107.25 | I86: =1.03*1075 -> 1107.25 | J86: =1.03*1075 -> 1107.25 | K86: =1.03*1075 -> 1107.25 | L86: =1.03*1075 -> 1107.25 | ... P86: =1.03*1075 -> 1107.25 | Q86: =SUM(E86:P86) -> 13287 | R86: =Q86/$B$4 -> 0.12315321 | U86: DW | V86: 2025 Business Plan grown 3%. New tenant costs/ Meter readings
D87: Building Maint.-Big Projects | Q87: =SUM(E87:P87) -> 0 | R87: =Q87/$B$4 -> 0
A88: 6220-8501 | C88: Building Maintenance | E88: =SUM(E86:E87) -> 1107.25 | F88: =SUM(F86:F87) -> 1107.25 | G88: =SUM(G86:G87) -> 1107.25 | H88: =SUM(H86:H87) -> 1107.25 | I88: =SUM(I86:I87) -> 1107.25 | J88: =SUM(J86:J87) -> 1107.25 | K88: =SUM(K86:K87) -> 1107.25 | L88: =SUM(L86:L87) -> 1107.25 | ... Q88: =SUM(Q86:Q87) -> 13287 | R88: =Q88/$B$4 -> 0.12315321 | S88: 8795.91 | T88: =IFERROR(Q88/S88-1,"-") -> 0.51058844
A90: 6610-8501 | B90: (SC) | C90: Management fee | Q90: =SUM(E90:P90) -> 0 | R90: =Q90/$B$4 -> 0 | T90: =R90/S90-1 -> #DIV/0!
T91: =R91/S91-1 -> #DIV/0!
A92: 7110-8501 | C92: Marketing | E92: ='Allocated Expenses'!F108+'Allocated Expenses'!F119 -> 1049.0569 | F92: ='Allocated Expenses'!G108+'Allocated Expenses'!G119 -> 1049.0569 | G92: ='Allocated Expenses'!H108+'Allocated Expenses'!H119 -> 1049.0569 | H92: ='Allocated Expenses'!I108+'Allocated Expenses'!I119 -> 1049.0569 | I92: ='Allocated Expenses'!J108+'Allocated Expenses'!J119 -> 1049.0569 | J92: ='Allocated Expenses'!K108+'Allocated Expenses'!K119 -> 1049.0569 | K92: ='Allocated Expenses'!L108+'Allocated Expenses'!L119 -> 1049.0569 | L92: ='Allocated Expenses'!M108+'Allocated Expenses'!M119 -> 1049.0569 | ... P92: ='Allocated Expenses'!Q108+'Allocated Expenses'!Q119 -> 1049.0569 | Q92: =SUM(E92:P92) -> 12588.683 | R92: =Q92/$B$4 -> 0.11668072 | S92: 12829.2 | T92: =IFERROR(Q92/S92-1,"-") -> -0.018747638
A94: 8210-8501 | C94: Business Taxes | E94: ='Allocated Expenses'!F130 -> 0 | F94: ='Allocated Expenses'!G130 -> 0 | G94: ='Allocated Expenses'!H130 -> 0 | H94: ='Allocated Expenses'!I130 -> 3419.4117 | I94: ='Allocated Expenses'!J130 -> 0 | J94: ='Allocated Expenses'!K130 -> 0 | K94: ='Allocated Expenses'!L130 -> 0 | L94: ='Allocated Expenses'!M130 -> 0 | ... P94: ='Allocated Expenses'!Q130 -> 0 | Q94: =SUM(E94:P94) -> 3419.4117 | R94: =Q94/$B$4 -> 0.0316935 | S94: 0 | T94: =IFERROR(Q94/S94-1,"-") -> -
A96: 8310-8501 | C96: Legal & Accounting | E96: ='Allocated Expenses'!F142 -> 958.74464 | F96: ='Allocated Expenses'!G142 -> 958.74464 | G96: ='Allocated Expenses'!H142 -> 958.74464 | H96: ='Allocated Expenses'!I142 -> 958.74464 | I96: ='Allocated Expenses'!J142 -> 958.74464 | J96: ='Allocated Expenses'!K142 -> 958.74464 | K96: ='Allocated Expenses'!L142 -> 958.74464 | L96: ='Allocated Expenses'!M142 -> 958.74464 | ... P96: ='Allocated Expenses'!Q142 -> 958.74464 | Q96: =SUM(E96:P96) -> 11504.936 | R96: =Q96/$B$4 -> 0.10663579 | S96: 9995.22 | T96: =IFERROR(Q96/S96-1,"-") -> 0.15104377
A98: 8190-8501 | D98: Bank Fees | E98: ='Allocated Expenses'!F153 -> 43.352601 | F98: ='Allocated Expenses'!G153 -> 43.352601 | G98: ='Allocated Expenses'!H153 -> 43.352601 | H98: ='Allocated Expenses'!I153 -> 43.352601 | I98: ='Allocated Expenses'!J153 -> 43.352601 | J98: ='Allocated Expenses'!K153 -> 43.352601 | K98: ='Allocated Expenses'!L153 -> 43.352601 | L98: ='Allocated Expenses'!M153 -> 43.352601 | ... P98: ='Allocated Expenses'!Q153 -> 43.352601 | Q98: =SUM(E98:P98) -> 520.23121 | R98: =Q98/$B$4 -> 0.0048218668
A99: 8930-8501 | D99: Office Supplies | E99: ='Allocated Expenses'!F164 -> 0 | F99: ='Allocated Expenses'!G164 -> 0 | G99: ='Allocated Expenses'!H164 -> 0 | H99: ='Allocated Expenses'!I164 -> 0 | I99: ='Allocated Expenses'!J164 -> 0 | J99: ='Allocated Expenses'!K164 -> 0 | K99: ='Allocated Expenses'!L164 -> 0 | L99: ='Allocated Expenses'!M164 -> 0 | ... P99: ='Allocated Expenses'!Q164 -> 0 | Q99: =SUM(E99:P99) -> 0 | R99: =Q99/$B$4 -> 0
A100: 8950-8501 | D100: Postage | E100: ='Allocated Expenses'!F175 -> 0 | F100: ='Allocated Expenses'!G175 -> 0 | G100: ='Allocated Expenses'!H175 -> 0 | H100: ='Allocated Expenses'!I175 -> 0 | I100: ='Allocated Expenses'!J175 -> 0 | J100: ='Allocated Expenses'!K175 -> 0 | K100: ='Allocated Expenses'!L175 -> 0 | L100: ='Allocated Expenses'!M175 -> 0 | ... P100: ='Allocated Expenses'!Q175 -> 0 | Q100: =SUM(E100:P100) -> 0 | R100: =Q100/$B$4 -> 0
A101: 8990-8501 | D101: Other G&A Expense | E101: ='Allocated Expenses'!F186 -> 41.95413 | F101: ='Allocated Expenses'!G186 -> 41.95413 | G101: ='Allocated Expenses'!H186 -> 41.95413 | H101: ='Allocated Expenses'!I186 -> 41.95413 | I101: ='Allocated Expenses'!J186 -> 41.95413 | J101: ='Allocated Expenses'!K186 -> 41.95413 | K101: ='Allocated Expenses'!L186 -> 41.95413 | L101: ='Allocated Expenses'!M186 -> 41.95413 | ... P101: ='Allocated Expenses'!Q186 -> 41.95413 | Q101: =SUM(E101:P101) -> 503.44956 | R101: =Q101/$B$4 -> 0.0046663227
A102: 8990-9800 | D102: Other G&A-allocated from LIK | E102: ='Allocated Expenses'!F197 -> 1470 | F102: ='Allocated Expenses'!G197 -> 1470 | G102: ='Allocated Expenses'!H197 -> 1470 | H102: ='Allocated Expenses'!I197 -> 1470 | I102: ='Allocated Expenses'!J197 -> 1470 | J102: ='Allocated Expenses'!K197 -> 1470 | K102: ='Allocated Expenses'!L197 -> 1470 | L102: ='Allocated Expenses'!M197 -> 1470 | ... P102: ='Allocated Expenses'!Q197 -> 1470 | Q102: =SUM(E102:P102) -> 17640 | R102: =Q102/$B$4 -> 0.16349986
C103: General & Administrative | E103: =SUM(E98:E102) -> 1555.3067 | F103: =SUM(F98:F102) -> 1555.3067 | G103: =SUM(G98:G102) -> 1555.3067 | H103: =SUM(H98:H102) -> 1555.3067 | I103: =SUM(I98:I102) -> 1555.3067 | J103: =SUM(J98:J102) -> 1555.3067 | K103: =SUM(K98:K102) -> 1555.3067 | L103: =SUM(L98:L102) -> 1555.3067 | ... Q103: =SUM(Q98:Q102) -> 18663.681 | R103: =Q103/$B$4 -> 0.17298805 | S103: 18168 | T103: =IFERROR(Q103/S103-1,"-") -> 0.027283177
C105: Total Non-Reimbursable Expenses | E105: =+E75+E79+E84+E88+E90+E92+E94+E96+E103 -> 9133.5128 | F105: =+F75+F79+F84+F88+F90+F92+F94+F96+F103 -> 7405.0027 | G105: =+G75+G79+G84+G88+G90+G92+G94+G96+G103 -> 7405.0027 | H105: =+H75+H79+H84+H88+H90+H92+H94+H96+H103 -> 12552.925 | I105: =+I75+I79+I84+I88+I90+I92+I94+I96+I103 -> 7405.0027 | J105: =+J75+J79+J84+J88+J90+J92+J94+J96+J103 -> 7405.0027 | K105: =+K75+K79+K84+K88+K90+K92+K94+K96+K103 -> 9133.5128 | L105: =+L75+L79+L84+L88+L90+L92+L94+L96+L103 -> 7405.0027 | ... Q105: =+Q75+Q79+Q84+Q88+Q90+Q92+Q94+Q96+Q103 -> 99193.484 | R105: =Q105/$B$4 -> 0.91939461 | S105: =+S75+S79+S84+S88+S90+S92+S94+S96+S103 -> 84562.72 | T105: =IFERROR(Q105/S105-1,"-") -> 0.17301672
B107: TOTAL OPERATING EXPENSES | E107: =+E71+E105 -> 90381.658 | F107: =+F71+F105 -> 88564.688 | G107: =+G71+G105 -> 100579.44 | H107: =+H71+H105 -> 95137.237 | I107: =+I71+I105 -> 92698.055 | J107: =+J71+J105 -> 103782.61 | K107: =+K71+K105 -> 110733.86 | L107: =+L71+L105 -> 98305.633 | ... Q107: =+Q71+Q105 -> 1162015.7 | R107: =Q107/$B$4 -> 10.770374 | S107: =+S71+S105 -> 1229755.4 | T107: =IFERROR(Q107/S107-1,"-") -> -0.055083888
B109: NET OPERATING INCOME | E109: =+E24-E107 -> 33237.708 | F109: =+F24-F107 -> 34042.46 | G109: =+G24-G107 -> 22051.889 | H109: =+H24-H107 -> 27664.676 | I109: =+I24-I107 -> 32068.609 | J109: =+J24-J107 -> 22851.476 | K109: =+K24-K107 -> 10720.626 | L109: =+L24-L107 -> 22447.196 | ... Q109: =+Q24-Q107 -> 285129.47 | R109: =Q109/$B$4 -> 2.6427794 | S109: =+S24-S107 -> 713647.26 | T109: =IFERROR(Q109/S109-1,"-") -> -0.60046162
A111: 1420-0000 | D111: Land Improvements | Q111: =SUM(E111:P111) -> 0 | R111: =Q111/$B$4 -> 0
A112: 1430-0000 | D112: Buildings | Q112: =SUM(E112:P112) -> 0 | R112: =Q112/$B$4 -> 0
A113: 1450-0000 | D113: Equipment | Q113: =SUM(E113:P113) -> 0 | R113: =Q113/$B$4 -> 0
A114: 1980-8501 | D114: Capital Improvements | Q114: =SUM(E114:P114) -> 0 | R114: =Q114/$B$4 -> 0
C115: Capital Improvements | Q115: =SUM(Q111:Q114) -> 0 | R115: =Q115/$B$4 -> 0 | T115: =IFERROR(Q115/S115-1,"-") -> -
A117: 1440-0000 | C117: Tenant Improvements | E117: ='Renew & Vac'!AJ33 -> 0 | F117: ='Renew & Vac'!AK33 -> 0 | G117: ='Renew & Vac'!AL33 -> 0 | H117: ='Renew & Vac'!AM33 -> 0 | I117: ='Renew & Vac'!AN33 -> 0 | J117: ='Renew & Vac'!AO33 -> 0 | K117: ='Renew & Vac'!AP33 -> 0 | L117: ='Renew & Vac'!AQ33 -> 3294 | ... P117: ='Renew & Vac'!AU33 -> 0 | Q117: =SUM(E117:P117) -> 3294 | R117: =Q117/$B$4 -> 0.030531096 | S117: 29837.53 | T117: =IFERROR(Q117/S117-1,"-") -> -0.88960212
D119: Deferred Marketing | Q119: =SUM(E119:P119) -> 0 | R119: =Q119/$B$4 -> 0
D120: Outside Leasing Commissions | E120: ='Renew & Vac'!AJ34 -> 50687.25 | F120: ='Renew & Vac'!AK34 -> 0 | G120: ='Renew & Vac'!AL34 -> 0 | H120: ='Renew & Vac'!AM34 -> 2160.18 | I120: ='Renew & Vac'!AN34 -> 0 | J120: ='Renew & Vac'!AO34 -> 0 | K120: ='Renew & Vac'!AP34 -> 5266.35 | L120: ='Renew & Vac'!AQ34 -> 0 | ... P120: ='Renew & Vac'!AU34 -> 0 | Q120: =SUM(E120:P120) -> 58113.78 | R120: =Q120/$B$4 -> 0.53863917
A121: 1940-8501 | C121: Outside Leasing Commissions | E121: =SUM(E119:E120) -> 50687.25 | F121: =SUM(F119:F120) -> 0 | G121: =SUM(G119:G120) -> 0 | H121: =SUM(H119:H120) -> 2160.18 | I121: =SUM(I119:I120) -> 0 | J121: =SUM(J119:J120) -> 0 | K121: =SUM(K119:K120) -> 5266.35 | L121: =SUM(L119:L120) -> 0 | ... Q121: =SUM(Q119:Q120) -> 58113.78 | R121: =Q121/$B$4 -> 0.53863917 | S121: 17115.9 | T121: =IFERROR(Q121/S121-1,"-") -> 2.3953096 | V121: 7/25 Reproj. Is for Capitalized Lease Costs
B123: CASH FLOW BEFORE DEBT SERVICE | E123: =+E109-E115-E117-E121 -> -17449.542 | F123: =+F109-F115-F117-F121 -> 34042.46 | G123: =+G109-G115-G117-G121 -> 22051.889 | H123: =+H109-H115-H117-H121 -> 25504.496 | I123: =+I109-I115-I117-I121 -> 32068.609 | J123: =+J109-J115-J117-J121 -> 22851.476 | K123: =+K109-K115-K117-K121 -> 5454.2757 | L123: =+L109-L115-L117-L121 -> 19153.196 | ... Q123: =+Q109-Q115-Q117-Q121 -> 223721.69 | R123: =Q123/$B$4 -> 2.0736091 | S123: =+S109-S115-S117-S121 -> 666693.83 | T123: =IFERROR(Q123/S123-1,"-") -> -0.66443114
B125: Debt Service
A126: 9210-8501 | C126: Interest | E126: =+'Allocated Expenses'!F209 -> 25269.692 | F126: =+'Allocated Expenses'!G209 -> 25269.692 | G126: =+'Allocated Expenses'!H209 -> 25269.692 | H126: =+'Allocated Expenses'!I209 -> 25269.692 | I126: =+'Allocated Expenses'!J209 -> 25269.692 | J126: =+'Allocated Expenses'!K209 -> 25269.692 | K126: =+'Allocated Expenses'!L209 -> 25269.692 | L126: =+'Allocated Expenses'!M209 -> 25269.692 | ... P126: =+'Allocated Expenses'!Q209 -> 25269.692 | Q126: =SUM(E126:P126) -> 303236.3 | R126: =Q126/$B$4 -> 2.8106062 | S126: 302738.49 | T126: =IFERROR(Q126/S126-1,"-") -> 0.001644364
A127: 2740-8501 | C127: Mortgage Amortization | E127: =+'Allocated Expenses'!E225 -> 0 | F127: =+'Allocated Expenses'!F225 -> 0 | G127: =+'Allocated Expenses'!G225 -> 0 | H127: =+'Allocated Expenses'!H225 -> 0 | I127: =+'Allocated Expenses'!I225 -> 0 | J127: =+'Allocated Expenses'!J225 -> 0 | K127: =+'Allocated Expenses'!K225 -> 0 | L127: =+'Allocated Expenses'!L225 -> 0 | ... P127: =+'Allocated Expenses'!P225 -> 0 | Q127: =SUM(E127:P127) -> 0 | R127: =Q127/$B$4 -> 0 | S127: 32196.81 | T127: =IFERROR(Q127/S127-1,"-") -> -1
A128: 2740-0000 | C128: Loan Proceeds | Q128: =SUM(E128:P128) -> 0 | R128: =Q128/$B$4 -> 0 | T128: =IFERROR(Q128/S128-1,"-") -> -
C129: Total Debt Service | E129: =SUM(E126:E128) -> 25269.692 | F129: =SUM(F126:F128) -> 25269.692 | G129: =SUM(G126:G128) -> 25269.692 | H129: =SUM(H126:H128) -> 25269.692 | I129: =SUM(I126:I128) -> 25269.692 | J129: =SUM(J126:J128) -> 25269.692 | K129: =SUM(K126:K128) -> 25269.692 | L129: =SUM(L126:L128) -> 25269.692 | ... Q129: =SUM(Q126:Q128) -> 303236.3 | R129: =Q129/$B$4 -> 2.8106062 | S129: =SUM(S126:S128) -> 334935.3 | T129: =Q129/S129-1 -> -0.094642152
B132: CASH FLOW AFTER DEBT SERVICE | E132: =+E123-E129 -> -42719.234 | F132: =+F123-F129 -> 8772.7684 | G132: =+G123-G129 -> -3217.8027 | H132: =+H123-H129 -> 234.80372 | I132: =+I123-I129 -> 6798.917 | J132: =+J123-J129 -> -2418.2158 | K132: =+K123-K129 -> -19815.416 | L132: =+L123-L129 -> -6116.496 | ... Q132: =+Q123-Q129 -> -79514.614 | R132: =Q132/$B$4 -> -0.73699707 | S132: =+S123-S129 -> 331758.53 | T132: =IFERROR(Q132/S132-1,"-") -> -1.2396762
B138: ="Rental Summary by Month "&C2 -> Rental Summary by Month
B139: Suite | D139: Tenant | E139: =E169 -> 46023 | F139: =F169 -> 46054 | G139: =G169 -> 46082 | H139: =H169 -> 46113 | I139: =I169 -> 46143 | J139: =J169 -> 46174 | K139: =K169 -> 46204 | L139: =L169 -> 46235 | ... P139: =P169 -> 46357 | Q139: Total
B140: =B170 -> 4060-100 | D140: =IF(D170="None",D199,D170) -> Audiology Distribution, LLC | E140: =SUMIF($B$170:$B$194,$B140,E$170:E$194)+SUMIF($B$200:$B$224,$B140,E$200:E$224) -> 1846.17 | F140: =SUMIF($B$170:$B$194,$B140,F$170:F$194)+SUMIF($B$200:$B$224,$B140,F$200:F$224) -> 1846.17 | G140: =SUMIF($B$170:$B$194,$B140,G$170:G$194)+SUMIF($B$200:$B$224,$B140,G$200:G$224) -> 1846.17 | H140: =SUMIF($B$170:$B$194,$B140,H$170:H$194)+SUMIF($B$200:$B$224,$B140,H$200:H$224) -> 1894.75 | I140: =SUMIF($B$170:$B$194,$B140,I$170:I$194)+SUMIF($B$200:$B$224,$B140,I$200:I$224) -> 1894.75 | J140: =SUMIF($B$170:$B$194,$B140,J$170:J$194)+SUMIF($B$200:$B$224,$B140,J$200:J$224) -> 1894.75 | K140: =SUMIF($B$170:$B$194,$B140,K$170:K$194)+SUMIF($B$200:$B$224,$B140,K$200:K$224) -> 1894.75 | L140: =SUMIF($B$170:$B$194,$B140,L$170:L$194)+SUMIF($B$200:$B$224,$B140,L$200:L$224) -> 1894.75 | ... P140: =SUMIF($B$170:$B$194,$B140,P$170:P$194)+SUMIF($B$200:$B$224,$B140,P$200:P$224) -> 1894.75 | Q140: =SUM(E140:P140) -> 22591.26
B141: =B171 -> 4060-101 | D141: =IF(D171="None",D200,D171) -> VACANT | E141: =SUMIF($B$170:$B$194,$B141,E$170:E$194)+SUMIF($B$200:$B$224,$B141,E$200:E$224) -> 0 | F141: =SUMIF($B$170:$B$194,$B141,F$170:F$194)+SUMIF($B$200:$B$224,$B141,F$200:F$224) -> 0 | G141: =SUMIF($B$170:$B$194,$B141,G$170:G$194)+SUMIF($B$200:$B$224,$B141,G$200:G$224) -> 0 | H141: =SUMIF($B$170:$B$194,$B141,H$170:H$194)+SUMIF($B$200:$B$224,$B141,H$200:H$224) -> 0 | I141: =SUMIF($B$170:$B$194,$B141,I$170:I$194)+SUMIF($B$200:$B$224,$B141,I$200:I$224) -> 0 | J141: =SUMIF($B$170:$B$194,$B141,J$170:J$194)+SUMIF($B$200:$B$224,$B141,J$200:J$224) -> 0 | K141: =SUMIF($B$170:$B$194,$B141,K$170:K$194)+SUMIF($B$200:$B$224,$B141,K$200:K$224) -> 0 | L141: =SUMIF($B$170:$B$194,$B141,L$170:L$194)+SUMIF($B$200:$B$224,$B141,L$200:L$224) -> 0 | ... P141: =SUMIF($B$170:$B$194,$B141,P$170:P$194)+SUMIF($B$200:$B$224,$B141,P$200:P$224) -> 0 | Q141: =SUM(E141:P141) -> 0
B142: =B172 -> 4060-105 | D142: =IF(D172="None",D201,D172) -> NE Phila PA Caregiving LLC | E142: =SUMIF($B$170:$B$194,$B142,E$170:E$194)+SUMIF($B$200:$B$224,$B142,E$200:E$224) -> 2596.67 | F142: =SUMIF($B$170:$B$194,$B142,F$170:F$194)+SUMIF($B$200:$B$224,$B142,F$200:F$224) -> 2596.67 | G142: =SUMIF($B$170:$B$194,$B142,G$170:G$194)+SUMIF($B$200:$B$224,$B142,G$200:G$224) -> 2596.67 | H142: =SUMIF($B$170:$B$194,$B142,H$170:H$194)+SUMIF($B$200:$B$224,$B142,H$200:H$224) -> 2596.67 | I142: =SUMIF($B$170:$B$194,$B142,I$170:I$194)+SUMIF($B$200:$B$224,$B142,I$200:I$224) -> 2596.67 | J142: =SUMIF($B$170:$B$194,$B142,J$170:J$194)+SUMIF($B$200:$B$224,$B142,J$200:J$224) -> 2596.67 | K142: =SUMIF($B$170:$B$194,$B142,K$170:K$194)+SUMIF($B$200:$B$224,$B142,K$200:K$224) -> 2596.67 | L142: =SUMIF($B$170:$B$194,$B142,L$170:L$194)+SUMIF($B$200:$B$224,$B142,L$200:L$224) -> 2596.67 | ... P142: =SUMIF($B$170:$B$194,$B142,P$170:P$194)+SUMIF($B$200:$B$224,$B142,P$200:P$224) -> 2596.67 | Q142: =SUM(E142:P142) -> 31160.04
...

Sheet 4070
B1: 4070 | J1: =+'4060'!J1 -> Operating Budget | Q1: ='NI LLC-Consolidated'!Q1 -> 46023
J2: =+'4060'!J2 -> Neshaminy Interplex LLC
Q3: =Q1 -> 46023 | S3: 7/2025 Reprojections
B4: 61508 | E4: Jan | F4: Feb | G4: Mar | H4: Apr | I4: May | J4: Jun | K4: Jul | L4: Aug | M4: Sep | N4: Oct | O4: Nov | P4: Dec | Q4: Total | R4: Total PSF | S4: Total | T4: Var. | U4: Input | V4: Notes
D6: Occupancy % | E6: ='Renew & Vac'!AJ53 -> 0.6933 | F6: ='Renew & Vac'!AK53 -> 0.6933 | G6: ='Renew & Vac'!AL53 -> 0.6933 | H6: ='Renew & Vac'!AM53 -> 0.7449 | I6: ='Renew & Vac'!AN53 -> 0.7449 | J6: ='Renew & Vac'!AO53 -> 0.7449 | K6: ='Renew & Vac'!AP53 -> 0.7449 | L6: ='Renew & Vac'!AQ53 -> 0.7449 | ... P6: ='Renew & Vac'!AU53 -> 0.7173
D7: Occupancy SF | E7: =$B$4*E6 -> 42643.496 | F7: =$B$4*F6 -> 42643.496 | G7: =$B$4*G6 -> 42643.496 | H7: =$B$4*H6 -> 45817.309 | I7: =$B$4*I6 -> 45817.309 | J7: =$B$4*J6 -> 45817.309 | K7: =$B$4*K6 -> 45817.309 | L7: =$B$4*L6 -> 45817.309 | ... P7: =$B$4*P6 -> 44119.688
B8: Revenues
A10: 4230-8501 | C10: Rental Income - In Place | E10: =SUMIFS('In Place Revenue'!$G:$G,'In Place Revenue'!$A:$A,"4070",'In Place Revenue'!$H:$H,1) -> 62565.05 | F10: =SUMIFS('In Place Revenue'!$G:$G,'In Place Revenue'!$A:$A,"4070",'In Place Revenue'!$H:$H,2) -> 62565.05 | G10: =SUMIFS('In Place Revenue'!$G:$G,'In Place Revenue'!$A:$A,"4070",'In Place Revenue'!$H:$H,3) -> 62565.05 | H10: =SUMIFS('In Place Revenue'!$G:$G,'In Place Revenue'!$A:$A,"4070",'In Place Revenue'!$H:$H,4) -> 62565.05 | I10: =SUMIFS('In Place Revenue'!$G:$G,'In Place Revenue'!$A:$A,"4070",'In Place Revenue'!$H:$H,5) -> 62565.05 | J10: =SUMIFS('In Place Revenue'!$G:$G,'In Place Revenue'!$A:$A,"4070",'In Place Revenue'!$H:$H,6) -> 62702.89 | K10: =SUMIFS('In Place Revenue'!$G:$G,'In Place Revenue'!$A:$A,"4070",'In Place Revenue'!$H:$H,7) -> 62863.76 | L10: =SUMIFS('In Place Revenue'!$G:$G,'In Place Revenue'!$A:$A,"4070",'In Place Revenue'!$H:$H,8) -> 62937.55 | M10: =SUMIFS('In Place Revenue'!$G:$G,'In Place Revenue'!$A:$A,"4070",'In Place Revenue'!$H:$H,9) -> 62937.55 | N10: =SUMIFS('In Place Revenue'!$G:$G,'In Place Revenue'!$A:$A,"4070",'In Place Revenue'!$H:$H,10) -> 62937.55 | O10: =SUMIFS('In Place Revenue'!$G:$G,'In Place Revenue'!$A:$A,"4070",'In Place Revenue'!$H:$H,11) -> 63486.27 | P10: =SUMIFS('In Place Revenue'!$G:$G,'In Place Revenue'!$A:$A,"4070",'In Place Revenue'!$H:$H,12) -> 61246.64 | Q10: =SUM(E10:P10) -> 751937.46 | R10: =Q10/$B$4 -> 12.225035 | S10: 813875.07 | T10: =IFERROR((Q10+Q11)/S10-1,"-") -> 0.10879507
A11: 4230-8501 | C11: Rental Income - New & Renewal | E11: ='Renew & Vac'!AJ54 -> 8725.3333 | F11: ='Renew & Vac'!AK54 -> 8725.3333 | G11: ='Renew & Vac'!AL54 -> 8725.3333 | H11: ='Renew & Vac'!AM54 -> 13876.583 | I11: ='Renew & Vac'!AN54 -> 13876.583 | J11: ='Renew & Vac'!AO54 -> 13876.583 | K11: ='Renew & Vac'!AP54 -> 13876.583 | L11: ='Renew & Vac'!AQ54 -> 13876.583 | ... P11: ='Renew & Vac'!AU54 -> 13294.542 | Q11: =SUM(E11:P11) -> 150483.21 | R11: =Q11/$B$4 -> 2.4465632 | T11: =IFERROR(Q11/S11-1,"-") -> -
A12: 4240-8501 | C12: Percentage Rents | E12: 0 | F12: 0 | G12: 0 | H12: 0 | I12: 0 | J12: 0 | K12: 0 | L12: 0 | M12: 0 | N12: 0 | O12: 0 | P12: 0 | Q12: =SUM(E12:P12) -> 0 | R12: =Q12/$B$4 -> 0 | T12: =R12/S12-1 -> #DIV/0!
A13: 4990-8501 | C13: Miscellaneous | E13: 0 | F13: 0 | G13: 0 | H13: 0 | I13: 0 | J13: 0 | K13: 0 | L13: 0 | M13: 0 | N13: 0 | O13: 0 | P13: 0 | Q13: =SUM(E13:P13) -> 0 | R13: =Q13/$B$4 -> 0 | T13: =IFERROR(Q13/S13-1,"-") -> -
A14: 9190-8501 | C14: Interest Income | E14: 0 | F14: 0 | G14: 0 | H14: 0 | I14: 0 | J14: 0 | K14: 0 | L14: 0 | M14: 0 | N14: 0 | O14: 0 | P14: 0 | Q14: =SUM(E14:P14) -> 0 | R14: =Q14/$B$4 -> 0 | T14: =IFERROR(Q14/S14-1,"-") -> -
C15: Total Rental and Other | E15: =SUM(E10:E14) -> 71290.383 | F15: =SUM(F10:F14) -> 71290.383 | G15: =SUM(G10:G14) -> 71290.383 | H15: =SUM(H10:H14) -> 76441.633 | I15: =SUM(I10:I14) -> 76441.633 | J15: =SUM(J10:J14) -> 76579.473 | K15: =SUM(K10:K14) -> 76740.343 | L15: =SUM(L10:L14) -> 76814.133 | ... Q15: =SUM(Q10:Q14) -> 902420.67 | R15: =Q15/$B$4 -> 14.671598 | S15: =SUM(S10:S14) -> 813875.07 | T15: =IFERROR(Q15/S15-1,"-") -> 0.10879507
B17: Reimbursements
A18: 4710-8502 | C18: Electric | E18: =E6*E29 -> 10798.841 | F18: =F6*F29 -> 9799.7955 | G18: =G6*G29 -> 9063.5109 | H18: =H6*H29 -> 8579.0133 | I18: =I6*I29 -> 8549.9622 | J18: =J6*J29 -> 8678.085 | K18: =K6*K29 -> 9654.6489 | L18: =L6*L29 -> 8651.2686 | ... P18: =P6*P29 -> 10210.766 | Q18: =SUM(E18:P18) -> 108040.95 | R18: =Q18/$B$4 -> 1.7565349 | S18: 96851.9 | T18: =IFERROR(Q18/S18-1,"-") -> 0.11552738 | U18: DW | V18: =Q18/Q29*100&"% Set to occupancy" -> 72.7391716263162% Set to occupancy
A19: 4910-8502 | C19: Common Area Maintenance | E19: =+'Tenant Recoveries'!H21 -> 8500 | F19: =+E19 -> 8500 | G19: =+F19 -> 8500 | H19: =+G19 -> 8500 | I19: =+H19 -> 8500 | J19: =+I19 -> 8500 | K19: =+J19 -> 8500 | L19: =+K19 -> 8500 | M19: =+L19 -> 8500 | ... P19: =+O19 -> 8500 | Q19: =SUM(E19:P19) -> 102000 | R19: =Q19/$B$4 -> 1.6583209 | S19: 89300 | T19: =IFERROR(Q19/S19-1,"-") -> 0.14221725 | V19: =Q19/(Q71-Q63-Q58-Q29) -> 0.24989327
A20: 4920-8502 | C20: Real Estate Taxes | E20: =+'Tenant Recoveries'!H22 -> 400 | F20: =+E20 -> 400 | G20: =+F20 -> 400 | H20: =+G20 -> 400 | I20: =+H20 -> 400 | J20: =+I20 -> 400 | K20: =+J20 -> 400 | L20: =+K20 -> 400 | M20: =+L20 -> 400 | ... P20: =+O20 -> 400 | Q20: =SUM(E20:P20) -> 4800 | R20: =Q20/$B$4 -> 0.078038629 | S20: 5334 | T20: =IFERROR(Q20/S20-1,"-") -> -0.10011249 | V20: =Q20/Q58 -> 0.063542805
A21: 4930-8502 | C21: Insurance | Q21: =SUM(E21:P21) -> 0 | R21: =Q21/$B$4 -> 0 | S21: 0 | T21: =IFERROR(Q21/S21-1,"-") -> -
C22: Total Reimbursements | E22: =SUM(E18:E21) -> 19698.841 | F22: =SUM(F18:F21) -> 18699.796 | G22: =SUM(G18:G21) -> 17963.511 | H22: =SUM(H18:H21) -> 17479.013 | I22: =SUM(I18:I21) -> 17449.962 | J22: =SUM(J18:J21) -> 17578.085 | K22: =SUM(K18:K21) -> 18554.649 | L22: =SUM(L18:L21) -> 17551.269 | ... Q22: =SUM(Q18:Q21) -> 214840.95 | R22: =Q22/$B$4 -> 3.4928944 | S22: =SUM(S18:S21) -> 191485.9 | T22: =IFERROR(Q22/S22-1,"-") -> 0.12196745
R23: =Q23/$B$4 -> 0
B24: TOTAL REVENUES | E24: =+E15+E22 -> 90989.224 | F24: =+F15+F22 -> 89990.179 | G24: =+G15+G22 -> 89253.894 | H24: =+H15+H22 -> 93920.647 | I24: =+I15+I22 -> 93891.596 | J24: =+J15+J22 -> 94157.558 | K24: =+K15+K22 -> 95294.992 | L24: =+L15+L22 -> 94365.402 | ... Q24: =+Q15+Q22 -> 1117261.6 | R24: =Q24/$B$4 -> 18.164493 | S24: =+S15+S22 -> 1005361 | T24: =IFERROR(Q24/S24-1,"-") -> 0.11130395
B26: Reimbursable Expenses
A27: 6030-8502 | C27: Maintenance Salaries | E27: ='Allocated Expenses'!F8 -> 1258.3791 | F27: ='Allocated Expenses'!G8 -> 1258.3791 | G27: ='Allocated Expenses'!H8 -> 1258.3791 | H27: ='Allocated Expenses'!I8 -> 1258.3791 | I27: ='Allocated Expenses'!J8 -> 1258.3791 | J27: ='Allocated Expenses'!K8 -> 1258.3791 | K27: ='Allocated Expenses'!L8 -> 1258.3791 | L27: ='Allocated Expenses'!M8 -> 1258.3791 | ... P27: ='Allocated Expenses'!Q8 -> 1258.3791 | Q27: =SUM(E27:P27) -> 15100.55 | R27: =Q27/$B$4 -> 0.24550546 | S27: 10608 | T27: =IFERROR(Q27/S27-1,"-") -> 0.4235058
A29: 6120-8502 | C29: Electric | E29: 15576 | F29: 14135 | G29: 13073 | H29: 11517 | I29: 11478 | J29: 11650 | K29: 12961 | L29: 11614 | M29: 9990 | N29: 11652 | O29: 10651 | P29: 14235 | Q29: =SUM(E29:P29) -> 148532 | R29: =Q29/$B$4 -> 2.4148403 | S29: 138337.06 | T29: =IFERROR(Q29/S29-1,"-") -> 0.073696376 | U29: DW | V29: Data\Shared\Properties\Business Plans - All Entities\2026\ISG Electric data
A31: 6130-8502 | C31: Water & Sewer | E31: ='Water Sewer'!D22 -> 1319.43 | F31: ='Water Sewer'!E22 -> 1315.31 | G31: ='Water Sewer'!F22 -> 1319.43 | H31: ='Water Sewer'!G22 -> 1324.58 | I31: ='Water Sewer'!H22 -> 1855.03 | J31: ='Water Sewer'!I22 -> 1615.04 | K31: ='Water Sewer'!J22 -> 1808.68 | L31: ='Water Sewer'!K22 -> 2367.97 | ... P31: ='Water Sewer'!O22 -> 1334.88 | Q31: =SUM(E31:P31) -> 19175.51 | R31: =Q31/$B$4 -> 0.31175636 | S31: 18608.14 | T31: =IFERROR(Q31/S31-1,"-") -> 0.03049042 | U31: DW | V31: 2025 Business Plan grown 3%
D33: Building Maint.-Contractual | E33: ='Building Maint'!C19 -> 2612 | F33: ='Building Maint'!D19 -> 1092 | G33: ='Building Maint'!E19 -> 5980 | H33: ='Building Maint'!F19 -> 6099 | I33: ='Building Maint'!G19 -> 1092 | J33: ='Building Maint'!H19 -> 5980 | K33: ='Building Maint'!I19 -> 2612 | L33: ='Building Maint'!J19 -> 1092 | ... P33: ='Building Maint'!N19 -> 5980 | Q33: =SUM(E33:P33) -> 45710 | R33: =Q33/$B$4 -> 0.74315536 | U33: DW | V33: 2025 Business Plan grown 3%
D34: Building Maint.-Recurring | E34: ='Building Maint'!C8 -> 3175 | F34: ='Building Maint'!D8 -> 2350 | G34: ='Building Maint'!E8 -> 2200 | H34: ='Building Maint'!F8 -> 2375 | I34: ='Building Maint'!G8 -> 4295 | J34: ='Building Maint'!H8 -> 2350 | K34: ='Building Maint'!I8 -> 4550 | L34: ='Building Maint'!J8 -> 2350 | ... P34: ='Building Maint'!N8 -> 2000 | Q34: =SUM(E34:P34) -> 33045 | R34: =Q34/$B$4 -> 0.53724719 | U34: DW | V34: 2025 Business Plan grown 3%
D35: Building Maint.-Big Projects | I35: =1.03*10000 -> 10300 | K35: =1.03*15000 -> 15450 | L35: =1.03*10000 -> 10300 | Q35: =SUM(E35:P35) -> 36050 | R35: =Q35/$B$4 -> 0.58610262 | U35: DW | V35: Includes lobby planter stones
A36: 6220-8502 | C36: Building Maintenance | E36: =SUM(E33:E35) -> 5787 | F36: =SUM(F33:F35) -> 3442 | G36: =SUM(G33:G35) -> 8180 | H36: =SUM(H33:H35) -> 8474 | I36: =SUM(I33:I35) -> 15687 | J36: =SUM(J33:J35) -> 8330 | K36: =SUM(K33:K35) -> 22612 | L36: =SUM(L33:L35) -> 13742 | ... Q36: =SUM(Q33:Q35) -> 114805 | R36: =Q36/$B$4 -> 1.8665052 | S36: 102162.73 | T36: =IFERROR(Q36/S36-1,"-") -> 0.1237464
A38: 6330-850 | B38: (SC) | C38: Parking Lot Cleaning | Q38: =SUM(E38:P38) -> 0 | R38: =Q38/$B$4 -> 0
D40: Parking Lot Maint.-Contractual | Q40: =SUM(E40:P40) -> 0 | R40: =Q40/$B$4 -> 0
D41: Parking Lot Maint.-Recurring | E41: ='Parking Lot Maint'!C8 -> 1436.85 | F41: ='Parking Lot Maint'!D8 -> 1436.85 | G41: ='Parking Lot Maint'!E8 -> 2363.85 | H41: ='Parking Lot Maint'!F8 -> 1436.85 | I41: ='Parking Lot Maint'!G8 -> 1436.85 | J41: ='Parking Lot Maint'!H8 -> 2363.85 | K41: ='Parking Lot Maint'!I8 -> 1436.85 | L41: ='Parking Lot Maint'!J8 -> 1436.85 | ... P41: ='Parking Lot Maint'!N8 -> 2363.85 | Q41: =SUM(E41:P41) -> 20950.2 | R41: =Q41/$B$4 -> 0.34060935 | U41: DW | V41: 2025 Business Plan grown 3%
D42: Parking Lot Maint.-Big Projects | H42: =1.03*12000 -> 12360 | L42: =1.03*12000 -> 12360 | Q42: =SUM(E42:P42) -> 24720 | R42: =Q42/$B$4 -> 0.40189894 | U42: DW | V42: 2025 Business Plan grown 3%. Includes restriping and pothole repair
A43: 6330-8502 | C43: Parking Lot Maintenance | E43: =SUM(E40:E42) -> 1436.85 | F43: =SUM(F40:F42) -> 1436.85 | G43: =SUM(G40:G42) -> 2363.85 | H43: =SUM(H40:H42) -> 13796.85 | I43: =SUM(I40:I42) -> 1436.85 | J43: =SUM(J40:J42) -> 2363.85 | K43: =SUM(K40:K42) -> 1436.85 | L43: =SUM(L40:L42) -> 13796.85 | ... Q43: =SUM(Q40:Q42) -> 45670.2 | R43: =Q43/$B$4 -> 0.74250829 | S43: 27448.56 | T43: =IFERROR(Q43/S43-1,"-") -> 0.66384685
A45: 6370-8502 | C45: Snow Removal | E45: =1.03*3750 -> 3862.5 | F45: =1.03*3750 -> 3862.5 | G45: =1.03*3750 -> 3862.5 | O45: =1.03*1000 -> 1030 | P45: =1.03*3750 -> 3862.5 | Q45: =SUM(E45:P45) -> 16480 | R45: =Q45/$B$4 -> 0.26793263 | S45: 11979.46 | T45: =IFERROR(Q45/S45-1,"-") -> 0.37568805 | U45: DW | V45: 2025 Business Plan grown 3%
D47: Landscaping-Contractual | E47: ='Allocated Expenses'!F19 -> 0 | F47: ='Allocated Expenses'!G19 -> 0 | G47: ='Allocated Expenses'!H19 -> 2625.8019 | H47: ='Allocated Expenses'!I19 -> 2625.8019 | I47: ='Allocated Expenses'!J19 -> 2625.8019 | J47: ='Allocated Expenses'!K19 -> 2625.8019 | K47: ='Allocated Expenses'!L19 -> 2625.8019 | L47: ='Allocated Expenses'!M19 -> 2625.8019 | ... P47: ='Allocated Expenses'!Q19 -> 0 | Q47: =SUM(E47:P47) -> 23632.217 | R47: =Q47/$B$4 -> 0.38421372 | U47: DW | V47: 2025 Business Plan grown 3%
D48: Landscaping-Recurring | E48: =Landscaping!C8 -> 0 | F48: =Landscaping!D8 -> 0 | G48: =Landscaping!E8 -> 798.25 | H48: =Landscaping!F8 -> 798.25 | I48: =Landscaping!G8 -> 2343.25 | J48: =Landscaping!H8 -> 798.25 | K48: =Landscaping!I8 -> 798.25 | L48: =Landscaping!J8 -> 798.25 | ... P48: =Landscaping!N8 -> 0 | Q48: =SUM(E48:P48) -> 9682 | R48: =Q48/$B$4 -> 0.15741042 | U48: DW | V48: 2025 Business Plan grown 3%
D49: Landscaping-Big Projects | E49: ='Allocated Expenses'!F30 -> 645.03815 | F49: ='Allocated Expenses'!G30 -> 645.03815 | G49: ='Allocated Expenses'!H30 -> 645.03815 | H49: ='Allocated Expenses'!I30 -> 645.03815 | I49: ='Allocated Expenses'!J30 -> 645.03815 | J49: ='Allocated Expenses'!K30 -> 645.03815 | K49: ='Allocated Expenses'!L30 -> 645.03815 | L49: ='Allocated Expenses'!M30 -> 645.03815 | ... P49: ='Allocated Expenses'!Q30 -> 645.03815 | Q49: =SUM(E49:P49) -> 7740.4578 | R49: =Q49/$B$4 -> 0.12584473 | U49: DW | V49: Fountain repairs
A50: 6380-8502 | C50: Landscaping | E50: =SUM(E47:E49) -> 645.03815 | F50: =SUM(F47:F49) -> 645.03815 | G50: =SUM(G47:G49) -> 4069.0901 | H50: =SUM(H47:H49) -> 4069.0901 | I50: =SUM(I47:I49) -> 5614.0901 | J50: =SUM(J47:J49) -> 4069.0901 | K50: =SUM(K47:K49) -> 4069.0901 | L50: =SUM(L47:L49) -> 4069.0901 | ... Q50: =SUM(Q47:Q49) -> 41054.675 | R50: =Q50/$B$4 -> 0.66746887 | S50: 32641.03 | T50: =IFERROR(Q50/S50-1,"-") -> 0.25776286
A52: 6350-8502 | C52: Security | E52: ='Allocated Expenses'!F41 -> 316.8 | F52: ='Allocated Expenses'!G41 -> 316.8 | G52: ='Allocated Expenses'!H41 -> 316.8 | H52: ='Allocated Expenses'!I41 -> 316.8 | I52: ='Allocated Expenses'!J41 -> 316.8 | J52: ='Allocated Expenses'!K41 -> 316.8 | K52: ='Allocated Expenses'!L41 -> 316.8 | L52: ='Allocated Expenses'!M41 -> 316.8 | ... P52: ='Allocated Expenses'!Q41 -> 316.8 | Q52: =SUM(E52:P52) -> 3801.6 | R52: =Q52/$B$4 -> 0.061806594 | S52: 4267.71 | T52: =IFERROR(Q52/S52-1,"-") -> -0.10921782 | U52: DW | V52: 2025 Business Plan grown 3%
A54: 6610-8502 | B54: (BP) | C54: Management Fee | E54: =ROUND(E$24*0.04,0) -> 3640 | F54: =ROUND(F$24*0.04,0) -> 3600 | G54: =ROUND(G$24*0.04,0) -> 3570 | H54: =ROUND(H$24*0.04,0) -> 3757 | I54: =ROUND(I$24*0.04,0) -> 3756 | J54: =ROUND(J$24*0.04,0) -> 3766 | K54: =ROUND(K$24*0.04,0) -> 3812 | L54: =ROUND(L$24*0.04,0) -> 3775 | ... P54: =ROUND(P$24*0.04,0) -> 3746 | Q54: =SUM(E54:P54) -> 44692 | R54: =Q54/$B$4 -> 0.72660467 | S54: 40014.28 | T54: =IFERROR(Q54/S54-1,"-") -> 0.11690127
A56: 6270-8502 | C56: Trash Removal | E56: =Trash!C8 -> 1828.25 | F56: =Trash!D8 -> 1828.25 | G56: =Trash!E8 -> 1828.25 | H56: =Trash!F8 -> 1828.25 | I56: =Trash!G8 -> 1828.25 | J56: =Trash!H8 -> 2578.25 | K56: =Trash!I8 -> 1828.25 | L56: =Trash!J8 -> 1828.25 | ... P56: =Trash!N8 -> 2578.25 | Q56: =SUM(E56:P56) -> 23439 | R56: =Q56/$B$4 -> 0.38107238 | S56: 24943.65 | T56: =IFERROR(Q56/S56-1,"-") -> -0.060321966 | U56: DW | V56: 2025 Business Plan grown 3%
A58: 6410-8502 | C58: Real Estate Taxes | E58: =+'INS RET'!E61 -> 6294.9692 | F58: =+'INS RET'!F61 -> 6294.9692 | G58: =+'INS RET'!G61 -> 6294.9692 | H58: =+'INS RET'!H61 -> 6294.9692 | I58: =+'INS RET'!I61 -> 6294.9692 | J58: =+'INS RET'!J61 -> 6294.9692 | K58: =+'INS RET'!K61 -> 6294.9692 | L58: =+'INS RET'!L61 -> 6294.9692 | ... P58: =+'INS RET'!P61 -> 6294.9692 | Q58: =SUM(E58:P58) -> 75539.631 | R58: =Q58/$B$4 -> 1.2281269 | S58: 108929.3 | T58: =IFERROR(Q58/S58-1,"-") -> -0.30652606
D60: Insurance-Liability | E60: =+'INS RET'!E20+'INS RET'!E21 -> 1675 | F60: =+'INS RET'!F20+'INS RET'!F21 -> 1675 | G60: =+'INS RET'!G20+'INS RET'!G21 -> 1675 | H60: =+'INS RET'!H20+'INS RET'!H21 -> 1675 | I60: =+'INS RET'!I20+'INS RET'!I21 -> 1675 | J60: =+'INS RET'!J20+'INS RET'!J21 -> 1675 | K60: =+'INS RET'!K20+'INS RET'!K21 -> 1675 | L60: =+'INS RET'!L20+'INS RET'!L21 -> 1675 | ... P60: =+'INS RET'!P20+'INS RET'!P21 -> 1708.5 | Q60: =SUM(E60:P60) -> 20167 | R60: =Q60/$B$4 -> 0.32787605
D61: Insurance-Property | E61: =+'INS RET'!E23 -> 1216 | F61: =+'INS RET'!F23 -> 1216 | G61: =+'INS RET'!G23 -> 1216 | H61: =+'INS RET'!H23 -> 1216 | I61: =+'INS RET'!I23 -> 1216 | J61: =+'INS RET'!J23 -> 1216 | K61: =+'INS RET'!K23 -> 1216 | L61: =+'INS RET'!L23 -> 1216 | ... P61: =+'INS RET'!P23 -> 1240.32 | Q61: =SUM(E61:P61) -> 14640.64 | R61: =Q61/$B$4 -> 0.23802822
D62: Insurance-Other | E62: =+'INS RET'!E24 -> 95 | F62: =+'INS RET'!F24 -> 95 | G62: =+'INS RET'!G24 -> 95 | H62: =+'INS RET'!H24 -> 95 | I62: =+'INS RET'!I24 -> 95 | J62: =+'INS RET'!J24 -> 95 | K62: =+'INS RET'!K24 -> 95 | L62: =+'INS RET'!L24 -> 95 | ... P62: =+'INS RET'!P24 -> 96.9 | Q62: =SUM(E62:P62) -> 1143.8 | R62: =Q62/$B$4 -> 0.018595955
A63: 6510-8502 | C63: Insurance | E63: =SUM(E60:E62) -> 2986 | F63: =SUM(F60:F62) -> 2986 | G63: =SUM(G60:G62) -> 2986 | H63: =SUM(H60:H62) -> 2986 | I63: =SUM(I60:I62) -> 2986 | J63: =SUM(J60:J62) -> 2986 | K63: =SUM(K60:K62) -> 2986 | L63: =SUM(L60:L62) -> 2986 | ... Q63: =SUM(Q60:Q62) -> 35951.44 | R63: =Q63/$B$4 -> 0.58450023 | S63: 35094 | T63: =IFERROR(Q63/S63-1,"-") -> 0.024432667
D65: Cleaning & Supplies | E65: ='Allocated Expenses'!F52+'Allocated Expenses'!F63 -> 6558.4048 | F65: ='Allocated Expenses'!G52+'Allocated Expenses'!G63 -> 6558.4048 | G65: ='Allocated Expenses'!H52+'Allocated Expenses'!H63 -> 6558.4048 | H65: ='Allocated Expenses'!I52+'Allocated Expenses'!I63 -> 6997.1082 | I65: ='Allocated Expenses'!J52+'Allocated Expenses'!J63 -> 6997.1082 | J65: ='Allocated Expenses'!K52+'Allocated Expenses'!K63 -> 6997.1082 | K65: ='Allocated Expenses'!L52+'Allocated Expenses'!L63 -> 6997.1082 | L65: ='Allocated Expenses'!M52+'Allocated Expenses'!M63 -> 6997.1082 | ... P65: ='Allocated Expenses'!Q52+'Allocated Expenses'!Q63 -> 6762.4529 | Q65: =SUM(E65:P65) -> 82414.533 | R65: =Q65/$B$4 -> 1.3398994 | U65: DW | V65: Based on occupancy. Includes cleaning, supplies, and porter fee.
D66: Cleaning & Supplies-Vacancies | E66: ='Allocated Expenses'!F76 -> 145.72829 | F66: ='Allocated Expenses'!G76 -> 145.72829 | G66: ='Allocated Expenses'!H76 -> 145.72829 | H66: ='Allocated Expenses'!I76 -> 121.21059 | I66: ='Allocated Expenses'!J76 -> 121.21059 | J66: ='Allocated Expenses'!K76 -> 121.21059 | K66: ='Allocated Expenses'!L76 -> 121.21059 | L66: ='Allocated Expenses'!M76 -> 121.21059 | ... P66: ='Allocated Expenses'!Q76 -> 134.32471 | Q66: =SUM(E66:P66) -> 1541.1943 | R66: =Q66/$B$4 -> 0.02505681 | U66: DW | V66: Based on occupancy.
A67: 6250-8502 | B67: (BP) | C67: Cleaning & Supplies | E67: =SUM(E65:E66) -> 6704.1331 | F67: =SUM(F65:F66) -> 6704.1331 | G67: =SUM(G65:G66) -> 6704.1331 | H67: =SUM(H65:H66) -> 7118.3188 | I67: =SUM(I65:I66) -> 7118.3188 | J67: =SUM(J65:J66) -> 7118.3188 | K67: =SUM(K65:K66) -> 7118.3188 | L67: =SUM(L65:L66) -> 7118.3188 | ... P67: =SUM(P65:P66) -> 6896.7776 | Q67: =SUM(E67:P67) -> 83955.727 | R67: =Q67/$B$4 -> 1.3649562 | S67: 78197.41 | T67: =IFERROR(Q67/S67-1,"-") -> 0.073638211
B69: (SC) | C69: Other | E69: 0 | F69: 0 | G69: 0 | H69: 0 | I69: 0 | J69: 0 | K69: 0 | L69: 0 | M69: 0 | N69: 0 | O69: 0 | P69: 0 | Q69: =SUM(E69:P69) -> 0 | R69: =Q69/$B$4 -> 0 | T69: =IFERROR(Q69/S69-1,"-") -> -
C71: Total Reimbursable Expenses | E71: =+E27+E29+E31+E36+E38+E43+E45+E50+E52+E54+E56+E58+E63+E67+E69 -> 51655.35 | F71: =+F27+F29+F31+F36+F38+F43+F45+F50+F52+F54+F56+F58+F63+F67+F69 -> 47825.23 | G71: =+G27+G29+G31+G36+G38+G43+G45+G50+G52+G54+G56+G58+G63+G67+G69 -> 55826.402 | H71: =+H27+H29+H31+H36+H38+H43+H45+H50+H52+H54+H56+H58+H63+H67+H69 -> 62741.237 | I71: =+I27+I29+I31+I36+I38+I43+I45+I50+I52+I54+I56+I58+I63+I67+I69 -> 59629.687 | J71: =+J27+J29+J31+J36+J38+J43+J45+J50+J52+J54+J56+J58+J63+J67+J69 -> 52346.697 | K71: =+K27+K29+K31+K36+K38+K43+K45+K50+K52+K54+K56+K58+K63+K67+K69 -> 66502.337 | L71: =+L27+L29+L31+L36+L38+L43+L45+L50+L52+L54+L56+L58+L63+L67+L69 -> 69167.627 | ... Q71: =+Q27+Q29+Q31+Q36+Q38+Q43+Q45+Q50+Q52+Q54+Q56+Q58+Q63+Q67+Q69 -> 668197.33 | R71: =Q71/$B$4 -> 10.863584 | S71: =+S27+S29+S31+S36+S38+S43+S45+S50+S52+S54+S56+S58+S63+S67+S69 -> 633231.33 | T71: =IFERROR(Q71/S71-1,"-") -> 0.055218371 | V71: =Q71-Q58-Q29 -> 444125.7
B73: Non-Reimbursable Expenses | R73: =Q73/$B$4 -> 0
A75: 5210-8501 | C75: Bad Debt | E75: 0 | F75: 0 | G75: 0 | H75: 0 | I75: 0 | J75: 0 | K75: 0 | L75: 0 | M75: 0 | N75: 0 | O75: 0 | P75: 0 | Q75: =SUM(E75:P75) -> 0 | R75: =Q75/$B$4 -> 0 | T75: =IFERROR(Q75/S75-1,"-") -> -
A77: 6010-8501 | D77: Salaries & Wages | E77: ='Allocated Expenses'!F87 -> 1559.0185 | F77: ='Allocated Expenses'!G87 -> 1559.0185 | G77: ='Allocated Expenses'!H87 -> 1559.0185 | H77: ='Allocated Expenses'!I87 -> 1559.0185 | I77: ='Allocated Expenses'!J87 -> 1559.0185 | J77: ='Allocated Expenses'!K87 -> 1559.0185 | K77: ='Allocated Expenses'!L87 -> 1559.0185 | L77: ='Allocated Expenses'!M87 -> 1559.0185 | ... P77: ='Allocated Expenses'!Q87 -> 1559.0185 | Q77: =SUM(E77:P77) -> 18708.222 | R77: =Q77/$B$4 -> 0.30415917
A78: 6620-8501 | D78: Commissions-Internal Broker | E78: ='Allocated Expenses'!F98 -> 985.4222 | F78: ='Allocated Expenses'!G98 -> 0 | G78: ='Allocated Expenses'!H98 -> 0 | H78: ='Allocated Expenses'!I98 -> 985.4222 | I78: ='Allocated Expenses'!J98 -> 0 | J78: ='Allocated Expenses'!K98 -> 0 | K78: ='Allocated Expenses'!L98 -> 985.4222 | L78: ='Allocated Expenses'!M98 -> 0 | ... P78: ='Allocated Expenses'!Q98 -> 0 | Q78: =SUM(E78:P78) -> 3941.6888 | R78: =Q78/$B$4 -> 0.064084165
