Workbook
Name PaiementsParAn: 'INS RET DEBT'!$G$6
Name pmtType: 'INS RET DEBT'!$F$20
Name rate: 'INS RET DEBT'!$J$6
Name roundOpt: 'INS RET DEBT'!$F$24
Name TauxIntérêt: 'INS RET DEBT'!$G$3

Sheet Cover Sheet
A1: ='All Shopping Centers'!J1 -> Operating Budget
A2: ='All Shopping Centers'!J2 -> Shopping Centers
A3: ='All Shopping Centers'!Q1 -> 46023

Sheet All Shopping Centers
B1: All Shopping Centers | J1: Operating Budget | Q1: =DATE(2026,1,1) -> 46023
J2: Shopping Centers
B4: ='Renew & Vac '!A6+'Renew & Vac '!A28+'Renew & Vac '!A50+'Renew & Vac '!A72+'Renew & Vac '!A94+'Renew & Vac '!A116+'Renew & Vac '!A138+'7300'!B4+'8200'!B4+'9510'!B4 -> 296787 | E4: Jan | F4: Feb | G4: Mar | H4: Apr | I4: May | J4: Jun | K4: Jul | L4: Aug | M4: Sep | N4: Oct | O4: Nov | P4: Dec | Q4: Total
D6: Occupancy % | E6: =SUM('1100'!E7,'1500'!E7,'2300'!E7,'4500'!E7,'5600'!E7,'7010'!E7,'7200'!E7)/$B$4 -> 0.74016202 | F6: =SUM('1100'!F7,'1500'!F7,'2300'!F7,'4500'!F7,'5600'!F7,'7010'!F7,'7200'!F7)/$B$4 -> 0.74016202 | G6: =SUM('1100'!G7,'1500'!G7,'2300'!G7,'4500'!G7,'5600'!G7,'7010'!G7,'7200'!G7)/$B$4 -> 0.74016202 | H6: =SUM('1100'!H7,'1500'!H7,'2300'!H7,'4500'!H7,'5600'!H7,'7010'!H7,'7200'!H7)/$B$4 -> 0.74016202 | I6: =SUM('1100'!I7,'1500'!I7,'2300'!I7,'4500'!I7,'5600'!I7,'7010'!I7,'7200'!I7)/$B$4 -> 0.74825355 | J6: =SUM('1100'!J7,'1500'!J7,'2300'!J7,'4500'!J7,'5600'!J7,'7010'!J7,'7200'!J7)/$B$4 -> 0.75162378 | K6: =SUM('1100'!K7,'1500'!K7,'2300'!K7,'4500'!K7,'5600'!K7,'7010'!K7,'7200'!K7)/$B$4 -> 0.75162378 | L6: =SUM('1100'!L7,'1500'!L7,'2300'!L7,'4500'!L7,'5600'!L7,'7010'!L7,'7200'!L7)/$B$4 -> 0.75162378 | ... P6: =SUM('1100'!P7,'1500'!P7,'2300'!P7,'4500'!P7,'5600'!P7,'7010'!P7,'7200'!P7)/$B$4 -> 0.75162378
B8: Revenues
A10: 4230-8501 | C10: Rental Income - In Place | E10: =+'1100'!E10+'1500'!E10+'2300'!E10+'4500'!E10+'5600'!E10+'7010'!E10+'7200'!E10+'7300'!E10+'8200'!E10+'9510'!E10 -> 423443.68 | F10: =+'1100'!F10+'1500'!F10+'2300'!F10+'4500'!F10+'5600'!F10+'7010'!F10+'7200'!F10+'7300'!F10+'8200'!F10+'9510'!F10 -> 423473.68 | G10: =+'1100'!G10+'1500'!G10+'2300'!G10+'4500'!G10+'5600'!G10+'7010'!G10+'7200'!G10+'7300'!G10+'8200'!G10+'9510'!G10 -> 423923.68 | H10: =+'1100'!H10+'1500'!H10+'2300'!H10+'4500'!H10+'5600'!H10+'7010'!H10+'7200'!H10+'7300'!H10+'8200'!H10+'9510'!H10 -> 420610.35 | I10: =+'1100'!I10+'1500'!I10+'2300'!I10+'4500'!I10+'5600'!I10+'7010'!I10+'7200'!I10+'7300'!I10+'8200'!I10+'9510'!I10 -> 420717.18 | J10: =+'1100'!J10+'1500'!J10+'2300'!J10+'4500'!J10+'5600'!J10+'7010'!J10+'7200'!J10+'7300'!J10+'8200'!J10+'9510'!J10 -> 420911.26 | K10: =+'1100'!K10+'1500'!K10+'2300'!K10+'4500'!K10+'5600'!K10+'7010'!K10+'7200'!K10+'7300'!K10+'8200'!K10+'9510'!K10 -> 413746.55 | L10: =+'1100'!L10+'1500'!L10+'2300'!L10+'4500'!L10+'5600'!L10+'7010'!L10+'7200'!L10+'7300'!L10+'8200'!L10+'9510'!L10 -> 398617.55 | ... P10: =+'1100'!P10+'1500'!P10+'2300'!P10+'4500'!P10+'5600'!P10+'7010'!P10+'7200'!P10+'7300'!P10+'8200'!P10+'9510'!P10 -> 390617.53 | Q10: =SUM(E10:P10) -> 4894551.7
A11: 4230-8501 | C11: Rental Income - New & Renewal | E11: =+'1100'!E11+'1500'!E11+'2300'!E11+'4500'!E11+'5600'!E11+'7010'!E11+'7200'!E11+'7300'!E11+'8200'!E11+'9510'!E11 -> 11422.167 | F11: =+'1100'!F11+'1500'!F11+'2300'!F11+'4500'!F11+'5600'!F11+'7010'!F11+'7200'!F11+'7300'!F11+'8200'!F11+'9510'!F11 -> 11422.167 | G11: =+'1100'!G11+'1500'!G11+'2300'!G11+'4500'!G11+'5600'!G11+'7010'!G11+'7200'!G11+'7300'!G11+'8200'!G11+'9510'!G11 -> 8272.1667 | H11: =+'1100'!H11+'1500'!H11+'2300'!H11+'4500'!H11+'5600'!H11+'7010'!H11+'7200'!H11+'7300'!H11+'8200'!H11+'9510'!H11 -> 11401.61 | I11: =+'1100'!I11+'1500'!I11+'2300'!I11+'4500'!I11+'5600'!I11+'7010'!I11+'7200'!I11+'7300'!I11+'8200'!I11+'9510'!I11 -> 19801.61 | J11: =+'1100'!J11+'1500'!J11+'2300'!J11+'4500'!J11+'5600'!J11+'7010'!J11+'7200'!J11+'7300'!J11+'8200'!J11+'9510'!J11 -> 22851.61 | K11: =+'1100'!K11+'1500'!K11+'2300'!K11+'4500'!K11+'5600'!K11+'7010'!K11+'7200'!K11+'7300'!K11+'8200'!K11+'9510'!K11 -> 31300.426 | L11: =+'1100'!L11+'1500'!L11+'2300'!L11+'4500'!L11+'5600'!L11+'7010'!L11+'7200'!L11+'7300'!L11+'8200'!L11+'9510'!L11 -> 50652.876 | ... P11: =+'1100'!P11+'1500'!P11+'2300'!P11+'4500'!P11+'5600'!P11+'7010'!P11+'7200'!P11+'7300'!P11+'8200'!P11+'9510'!P11 -> 68777.312 | Q11: =SUM(E11:P11) -> 436977.21
A12: 4240-8501 | C12: Percentage Rents | E12: =+'1100'!E12+'1500'!E12+'2300'!E12+'4500'!E12+'5600'!E12+'7010'!E12+'7200'!E12+'7300'!E12+'8200'!E12+'9510'!E12 -> 0 | F12: =+'1100'!F12+'1500'!F12+'2300'!F12+'4500'!F12+'5600'!F12+'7010'!F12+'7200'!F12+'7300'!F12+'8200'!F12+'9510'!F12 -> 0 | G12: =+'1100'!G12+'1500'!G12+'2300'!G12+'4500'!G12+'5600'!G12+'7010'!G12+'7200'!G12+'7300'!G12+'8200'!G12+'9510'!G12 -> 0 | H12: =+'1100'!H12+'1500'!H12+'2300'!H12+'4500'!H12+'5600'!H12+'7010'!H12+'7200'!H12+'7300'!H12+'8200'!H12+'9510'!H12 -> 0 | I12: =+'1100'!I12+'1500'!I12+'2300'!I12+'4500'!I12+'5600'!I12+'7010'!I12+'7200'!I12+'7300'!I12+'8200'!I12+'9510'!I12 -> 0 | J12: =+'1100'!J12+'1500'!J12+'2300'!J12+'4500'!J12+'5600'!J12+'7010'!J12+'7200'!J12+'7300'!J12+'8200'!J12+'9510'!J12 -> 0 | K12: =+'1100'!K12+'1500'!K12+'2300'!K12+'4500'!K12+'5600'!K12+'7010'!K12+'7200'!K12+'7300'!K12+'8200'!K12+'9510'!K12 -> 0 | L12: =+'1100'!L12+'1500'!L12+'2300'!L12+'4500'!L12+'5600'!L12+'7010'!L12+'7200'!L12+'7300'!L12+'8200'!L12+'9510'!L12 -> 0 | ... P12: =+'1100'!P12+'1500'!P12+'2300'!P12+'4500'!P12+'5600'!P12+'7010'!P12+'7200'!P12+'7300'!P12+'8200'!P12+'9510'!P12 -> 33958.07 | Q12: =SUM(E12:P12) -> 33958.07
A13: 4990-8501 | C13: Miscellaneous | E13: =+'1100'!E13+'1500'!E13+'2300'!E13+'4500'!E13+'5600'!E13+'7010'!E13+'7200'!E13+'7300'!E13+'8200'!E13+'9510'!E13 -> 10530.967 | F13: =+'1100'!F13+'1500'!F13+'2300'!F13+'4500'!F13+'5600'!F13+'7010'!F13+'7200'!F13+'7300'!F13+'8200'!F13+'9510'!F13 -> 10530.967 | G13: =+'1100'!G13+'1500'!G13+'2300'!G13+'4500'!G13+'5600'!G13+'7010'!G13+'7200'!G13+'7300'!G13+'8200'!G13+'9510'!G13 -> 10530.967 | H13: =+'1100'!H13+'1500'!H13+'2300'!H13+'4500'!H13+'5600'!H13+'7010'!H13+'7200'!H13+'7300'!H13+'8200'!H13+'9510'!H13 -> 10530.967 | I13: =+'1100'!I13+'1500'!I13+'2300'!I13+'4500'!I13+'5600'!I13+'7010'!I13+'7200'!I13+'7300'!I13+'8200'!I13+'9510'!I13 -> 10530.967 | J13: =+'1100'!J13+'1500'!J13+'2300'!J13+'4500'!J13+'5600'!J13+'7010'!J13+'7200'!J13+'7300'!J13+'8200'!J13+'9510'!J13 -> 10530.967 | K13: =+'1100'!K13+'1500'!K13+'2300'!K13+'4500'!K13+'5600'!K13+'7010'!K13+'7200'!K13+'7300'!K13+'8200'!K13+'9510'!K13 -> 10530.967 | L13: =+'1100'!L13+'1500'!L13+'2300'!L13+'4500'!L13+'5600'!L13+'7010'!L13+'7200'!L13+'7300'!L13+'8200'!L13+'9510'!L13 -> 10530.967 | ... P13: =+'1100'!P13+'1500'!P13+'2300'!P13+'4500'!P13+'5600'!P13+'7010'!P13+'7200'!P13+'7300'!P13+'8200'!P13+'9510'!P13 -> 10530.967 | Q13: =SUM(E13:P13) -> 126371.61
A14: 9190-8501 | C14: Interest Income | E14: =+'1100'!E14+'1500'!E14+'2300'!E14+'4500'!E14+'5600'!E14+'7010'!E14+'7200'!E14+'7300'!E14+'8200'!E14+'9510'!E14 -> 243.08 | F14: =+'1100'!F14+'1500'!F14+'2300'!F14+'4500'!F14+'5600'!F14+'7010'!F14+'7200'!F14+'7300'!F14+'8200'!F14+'9510'!F14 -> 243.08 | G14: =+'1100'!G14+'1500'!G14+'2300'!G14+'4500'!G14+'5600'!G14+'7010'!G14+'7200'!G14+'7300'!G14+'8200'!G14+'9510'!G14 -> 243.08 | H14: =+'1100'!H14+'1500'!H14+'2300'!H14+'4500'!H14+'5600'!H14+'7010'!H14+'7200'!H14+'7300'!H14+'8200'!H14+'9510'!H14 -> 243.08 | I14: =+'1100'!I14+'1500'!I14+'2300'!I14+'4500'!I14+'5600'!I14+'7010'!I14+'7200'!I14+'7300'!I14+'8200'!I14+'9510'!I14 -> 243.08 | J14: =+'1100'!J14+'1500'!J14+'2300'!J14+'4500'!J14+'5600'!J14+'7010'!J14+'7200'!J14+'7300'!J14+'8200'!J14+'9510'!J14 -> 243.08 | K14: =+'1100'!K14+'1500'!K14+'2300'!K14+'4500'!K14+'5600'!K14+'7010'!K14+'7200'!K14+'7300'!K14+'8200'!K14+'9510'!K14 -> 243.08 | L14: =+'1100'!L14+'1500'!L14+'2300'!L14+'4500'!L14+'5600'!L14+'7010'!L14+'7200'!L14+'7300'!L14+'8200'!L14+'9510'!L14 -> 243.08 | ... P14: =+'1100'!P14+'1500'!P14+'2300'!P14+'4500'!P14+'5600'!P14+'7010'!P14+'7200'!P14+'7300'!P14+'8200'!P14+'9510'!P14 -> 243.08 | Q14: =SUM(E14:P14) -> 2916.96
D15: Total Rental and Other: | E15: =SUM(E10:E14) -> 445639.89 | F15: =SUM(F10:F14) -> 445669.89 | G15: =SUM(G10:G14) -> 442969.89 | H15: =SUM(H10:H14) -> 442786.01 | I15: =SUM(I10:I14) -> 451292.84 | J15: =SUM(J10:J14) -> 454536.92 | K15: =SUM(K10:K14) -> 455821.02 | L15: =SUM(L10:L14) -> 460044.47 | ... Q15: =SUM(Q10:Q14) -> 5494775.5
B17: Reimbursements
A18: 4710-8502 | C18: Electric | E18: =+'1100'!E18+'1500'!E18+'2300'!E18+'4500'!E18+'5600'!E18+'7010'!E18+'7200'!E18+'7300'!E18+'8200'!E18+'9510'!E18 -> 1978.2 | F18: =+'1100'!F18+'1500'!F18+'2300'!F18+'4500'!F18+'5600'!F18+'7010'!F18+'7200'!F18+'7300'!F18+'8200'!F18+'9510'!F18 -> 1802.85 | G18: =+'1100'!G18+'1500'!G18+'2300'!G18+'4500'!G18+'5600'!G18+'7010'!G18+'7200'!G18+'7300'!G18+'8200'!G18+'9510'!G18 -> 1659 | H18: =+'1100'!H18+'1500'!H18+'2300'!H18+'4500'!H18+'5600'!H18+'7010'!H18+'7200'!H18+'7300'!H18+'8200'!H18+'9510'!H18 -> 1174.95 | I18: =+'1100'!I18+'1500'!I18+'2300'!I18+'4500'!I18+'5600'!I18+'7010'!I18+'7200'!I18+'7300'!I18+'8200'!I18+'9510'!I18 -> 1174.95 | J18: =+'1100'!J18+'1500'!J18+'2300'!J18+'4500'!J18+'5600'!J18+'7010'!J18+'7200'!J18+'7300'!J18+'8200'!J18+'9510'!J18 -> 1191.75 | K18: =+'1100'!K18+'1500'!K18+'2300'!K18+'4500'!K18+'5600'!K18+'7010'!K18+'7200'!K18+'7300'!K18+'8200'!K18+'9510'!K18 -> 1503.6 | L18: =+'1100'!L18+'1500'!L18+'2300'!L18+'4500'!L18+'5600'!L18+'7010'!L18+'7200'!L18+'7300'!L18+'8200'!L18+'9510'!L18 -> 1451.1 | ... P18: =+'1100'!P18+'1500'!P18+'2300'!P18+'4500'!P18+'5600'!P18+'7010'!P18+'7200'!P18+'7300'!P18+'8200'!P18+'9510'!P18 -> 1978.2 | Q18: =SUM(E18:P18) -> 18551.4
A19: 4910-8502 | C19: Common Area Maintenance | E19: =+'1100'!E19+'1500'!E19+'2300'!E19+'4500'!E19+'5600'!E19+'7010'!E19+'7200'!E19+'7300'!E19+'8200'!E19+'9510'!E19 -> 90900 | F19: =+'1100'!F19+'1500'!F19+'2300'!F19+'4500'!F19+'5600'!F19+'7010'!F19+'7200'!F19+'7300'!F19+'8200'!F19+'9510'!F19 -> 90900 | G19: =+'1100'!G19+'1500'!G19+'2300'!G19+'4500'!G19+'5600'!G19+'7010'!G19+'7200'!G19+'7300'!G19+'8200'!G19+'9510'!G19 -> 90900 | H19: =+'1100'!H19+'1500'!H19+'2300'!H19+'4500'!H19+'5600'!H19+'7010'!H19+'7200'!H19+'7300'!H19+'8200'!H19+'9510'!H19 -> 96539.25 | I19: =+'1100'!I19+'1500'!I19+'2300'!I19+'4500'!I19+'5600'!I19+'7010'!I19+'7200'!I19+'7300'!I19+'8200'!I19+'9510'!I19 -> 90900 | J19: =+'1100'!J19+'1500'!J19+'2300'!J19+'4500'!J19+'5600'!J19+'7010'!J19+'7200'!J19+'7300'!J19+'8200'!J19+'9510'!J19 -> 90900 | K19: =+'1100'!K19+'1500'!K19+'2300'!K19+'4500'!K19+'5600'!K19+'7010'!K19+'7200'!K19+'7300'!K19+'8200'!K19+'9510'!K19 -> 96539.25 | L19: =+'1100'!L19+'1500'!L19+'2300'!L19+'4500'!L19+'5600'!L19+'7010'!L19+'7200'!L19+'7300'!L19+'8200'!L19+'9510'!L19 -> 90900 | ... P19: =+'1100'!P19+'1500'!P19+'2300'!P19+'4500'!P19+'5600'!P19+'7010'!P19+'7200'!P19+'7300'!P19+'8200'!P19+'9510'!P19 -> 96539.25 | Q19: =SUM(E19:P19) -> 1113357
A20: 4920-8502 | C20: Real Estate Taxes | E20: =+'1100'!E20+'1500'!E20+'2300'!E20+'4500'!E20+'5600'!E20+'7010'!E20+'7200'!E20+'7300'!E20+'8200'!E20+'9510'!E20 -> 36100 | F20: =+'1100'!F20+'1500'!F20+'2300'!F20+'4500'!F20+'5600'!F20+'7010'!F20+'7200'!F20+'7300'!F20+'8200'!F20+'9510'!F20 -> 36100 | G20: =+'1100'!G20+'1500'!G20+'2300'!G20+'4500'!G20+'5600'!G20+'7010'!G20+'7200'!G20+'7300'!G20+'8200'!G20+'9510'!G20 -> 36100 | H20: =+'1100'!H20+'1500'!H20+'2300'!H20+'4500'!H20+'5600'!H20+'7010'!H20+'7200'!H20+'7300'!H20+'8200'!H20+'9510'!H20 -> 37669 | I20: =+'1100'!I20+'1500'!I20+'2300'!I20+'4500'!I20+'5600'!I20+'7010'!I20+'7200'!I20+'7300'!I20+'8200'!I20+'9510'!I20 -> 36100 | J20: =+'1100'!J20+'1500'!J20+'2300'!J20+'4500'!J20+'5600'!J20+'7010'!J20+'7200'!J20+'7300'!J20+'8200'!J20+'9510'!J20 -> 36100 | K20: =+'1100'!K20+'1500'!K20+'2300'!K20+'4500'!K20+'5600'!K20+'7010'!K20+'7200'!K20+'7300'!K20+'8200'!K20+'9510'!K20 -> 37669 | L20: =+'1100'!L20+'1500'!L20+'2300'!L20+'4500'!L20+'5600'!L20+'7010'!L20+'7200'!L20+'7300'!L20+'8200'!L20+'9510'!L20 -> 36100 | ... P20: =+'1100'!P20+'1500'!P20+'2300'!P20+'4500'!P20+'5600'!P20+'7010'!P20+'7200'!P20+'7300'!P20+'8200'!P20+'9510'!P20 -> 37669 | Q20: =SUM(E20:P20) -> 439476
A21: 4930-8502 | C21: Insurance | E21: =+'1100'!E21+'1500'!E21+'2300'!E21+'4500'!E21+'5600'!E21+'7010'!E21+'7200'!E21+'7300'!E21+'8200'!E21+'9510'!E21 -> 10365 | F21: =+'1100'!F21+'1500'!F21+'2300'!F21+'4500'!F21+'5600'!F21+'7010'!F21+'7200'!F21+'7300'!F21+'8200'!F21+'9510'!F21 -> 0 | G21: =+'1100'!G21+'1500'!G21+'2300'!G21+'4500'!G21+'5600'!G21+'7010'!G21+'7200'!G21+'7300'!G21+'8200'!G21+'9510'!G21 -> 0 | H21: =+'1100'!H21+'1500'!H21+'2300'!H21+'4500'!H21+'5600'!H21+'7010'!H21+'7200'!H21+'7300'!H21+'8200'!H21+'9510'!H21 -> 0 | I21: =+'1100'!I21+'1500'!I21+'2300'!I21+'4500'!I21+'5600'!I21+'7010'!I21+'7200'!I21+'7300'!I21+'8200'!I21+'9510'!I21 -> 0 | J21: =+'1100'!J21+'1500'!J21+'2300'!J21+'4500'!J21+'5600'!J21+'7010'!J21+'7200'!J21+'7300'!J21+'8200'!J21+'9510'!J21 -> 0 | K21: =+'1100'!K21+'1500'!K21+'2300'!K21+'4500'!K21+'5600'!K21+'7010'!K21+'7200'!K21+'7300'!K21+'8200'!K21+'9510'!K21 -> 0 | L21: =+'1100'!L21+'1500'!L21+'2300'!L21+'4500'!L21+'5600'!L21+'7010'!L21+'7200'!L21+'7300'!L21+'8200'!L21+'9510'!L21 -> 0 | ... P21: =+'1100'!P21+'1500'!P21+'2300'!P21+'4500'!P21+'5600'!P21+'7010'!P21+'7200'!P21+'7300'!P21+'8200'!P21+'9510'!P21 -> 0 | Q21: =SUM(E21:P21) -> 10365
D22: Total Reimbursements: | E22: =SUM(E18:E21) -> 139343.2 | F22: =SUM(F18:F21) -> 128802.85 | G22: =SUM(G18:G21) -> 128659 | H22: =SUM(H18:H21) -> 135383.2 | I22: =SUM(I18:I21) -> 128174.95 | J22: =SUM(J18:J21) -> 128191.75 | K22: =SUM(K18:K21) -> 135711.85 | L22: =SUM(L18:L21) -> 128451.1 | ... Q22: =SUM(Q18:Q21) -> 1581749.4
B24: TOTAL REVENUES | E24: =+E15+E22 -> 584983.09 | F24: =+F15+F22 -> 574472.74 | G24: =+G15+G22 -> 571628.89 | H24: =+H15+H22 -> 578169.21 | I24: =+I15+I22 -> 579467.79 | J24: =+J15+J22 -> 582728.67 | K24: =+K15+K22 -> 591532.87 | L24: =+L15+L22 -> 588495.57 | ... Q24: =+Q15+Q22 -> 7076524.9
Q25: =+'1100'!Q24+'1500'!Q24+'2300'!Q24+'4500'!Q24+'5600'!Q24+'7010'!Q24+'7200'!Q24 -> 5700115.3
B26: Reimbursable Expenses
A27: 6030-8502 | C27: Maintenance Salaries | E27: =+'1100'!E27+'1500'!E27+'2300'!E27+'4500'!E27+'5600'!E27+'7010'!E27+'7200'!E27+'7300'!E27+'8200'!E27+'9510'!E27 -> 9139 | F27: =+'1100'!F27+'1500'!F27+'2300'!F27+'4500'!F27+'5600'!F27+'7010'!F27+'7200'!F27+'7300'!F27+'8200'!F27+'9510'!F27 -> 9139 | G27: =+'1100'!G27+'1500'!G27+'2300'!G27+'4500'!G27+'5600'!G27+'7010'!G27+'7200'!G27+'7300'!G27+'8200'!G27+'9510'!G27 -> 9139 | H27: =+'1100'!H27+'1500'!H27+'2300'!H27+'4500'!H27+'5600'!H27+'7010'!H27+'7200'!H27+'7300'!H27+'8200'!H27+'9510'!H27 -> 9139 | I27: =+'1100'!I27+'1500'!I27+'2300'!I27+'4500'!I27+'5600'!I27+'7010'!I27+'7200'!I27+'7300'!I27+'8200'!I27+'9510'!I27 -> 9139 | J27: =+'1100'!J27+'1500'!J27+'2300'!J27+'4500'!J27+'5600'!J27+'7010'!J27+'7200'!J27+'7300'!J27+'8200'!J27+'9510'!J27 -> 9139 | K27: =+'1100'!K27+'1500'!K27+'2300'!K27+'4500'!K27+'5600'!K27+'7010'!K27+'7200'!K27+'7300'!K27+'8200'!K27+'9510'!K27 -> 9139 | L27: =+'1100'!L27+'1500'!L27+'2300'!L27+'4500'!L27+'5600'!L27+'7010'!L27+'7200'!L27+'7300'!L27+'8200'!L27+'9510'!L27 -> 9139 | ... P27: =+'1100'!P27+'1500'!P27+'2300'!P27+'4500'!P27+'5600'!P27+'7010'!P27+'7200'!P27+'7300'!P27+'8200'!P27+'9510'!P27 -> 9139 | Q27: =SUM(E27:P27) -> 109668
A29: 6120-8502 | C29: Electric | E29: =+'1100'!E29+'1500'!E29+'2300'!E29+'4500'!E29+'5600'!E29+'7010'!E29+'7200'!E29+'7300'!E29+'8200'!E29+'9510'!E29+'7010'!E30+'7010'!E31 -> 5858.77 | F29: =+'1100'!F29+'1500'!F29+'2300'!F29+'4500'!F29+'5600'!F29+'7010'!F29+'7200'!F29+'7300'!F29+'8200'!F29+'9510'!F29+'7010'!F30+'7010'!F31 -> 5449.32 | G29: =+'1100'!G29+'1500'!G29+'2300'!G29+'4500'!G29+'5600'!G29+'7010'!G29+'7200'!G29+'7300'!G29+'8200'!G29+'9510'!G29+'7010'!G30+'7010'!G31 -> 5228.6 | H29: =+'1100'!H29+'1500'!H29+'2300'!H29+'4500'!H29+'5600'!H29+'7010'!H29+'7200'!H29+'7300'!H29+'8200'!H29+'9510'!H29+'7010'!H30+'7010'!H31 -> 4155.54 | I29: =+'1100'!I29+'1500'!I29+'2300'!I29+'4500'!I29+'5600'!I29+'7010'!I29+'7200'!I29+'7300'!I29+'8200'!I29+'9510'!I29+'7010'!I30+'7010'!I31 -> 3999.05 | J29: =+'1100'!J29+'1500'!J29+'2300'!J29+'4500'!J29+'5600'!J29+'7010'!J29+'7200'!J29+'7300'!J29+'8200'!J29+'9510'!J29+'7010'!J30+'7010'!J31 -> 3954.79 | K29: =+'1100'!K29+'1500'!K29+'2300'!K29+'4500'!K29+'5600'!K29+'7010'!K29+'7200'!K29+'7300'!K29+'8200'!K29+'9510'!K29+'7010'!K30+'7010'!K31 -> 4422.77 | L29: =+'1100'!L29+'1500'!L29+'2300'!L29+'4500'!L29+'5600'!L29+'7010'!L29+'7200'!L29+'7300'!L29+'8200'!L29+'9510'!L29+'7010'!L30+'7010'!L31 -> 4069.85 | ... P29: =+'1100'!P29+'1500'!P29+'2300'!P29+'4500'!P29+'5600'!P29+'7010'!P29+'7200'!P29+'7300'!P29+'8200'!P29+'9510'!P29+'7010'!P30+'7010'!P31 -> 6116.61 | Q29: =SUM(E29:P29) -> 57194.8
A31: 6130-8502 | C31: Water & Sewer | E31: =+'1100'!E31+'1500'!E31+'2300'!E31+'4500'!E31+'5600'!E31+'7010'!E33+'7200'!E31+'7300'!E31+'8200'!E31+'9510'!E31 -> 490.28 | F31: =+'1100'!F31+'1500'!F31+'2300'!F31+'4500'!F31+'5600'!F31+'7010'!F33+'7200'!F31+'7300'!F31+'8200'!F31+'9510'!F31 -> 717.91 | G31: =+'1100'!G31+'1500'!G31+'2300'!G31+'4500'!G31+'5600'!G31+'7010'!G33+'7200'!G31+'7300'!G31+'8200'!G31+'9510'!G31 -> 692.16 | H31: =+'1100'!H31+'1500'!H31+'2300'!H31+'4500'!H31+'5600'!H31+'7010'!H33+'7200'!H31+'7300'!H31+'8200'!H31+'9510'!H31 -> 621.09 | I31: =+'1100'!I31+'1500'!I31+'2300'!I31+'4500'!I31+'5600'!I31+'7010'!I33+'7200'!I31+'7300'!I31+'8200'!I31+'9510'!I31 -> 443.93 | J31: =+'1100'!J31+'1500'!J31+'2300'!J31+'4500'!J31+'5600'!J31+'7010'!J33+'7200'!J31+'7300'!J31+'8200'!J31+'9510'!J31 -> 459.38 | K31: =+'1100'!K31+'1500'!K31+'2300'!K31+'4500'!K31+'5600'!K31+'7010'!K33+'7200'!K31+'7300'!K31+'8200'!K31+'9510'!K31 -> 478.95 | L31: =+'1100'!L31+'1500'!L31+'2300'!L31+'4500'!L31+'5600'!L31+'7010'!L33+'7200'!L31+'7300'!L31+'8200'!L31+'9510'!L31 -> 468.65 | ... P31: =+'1100'!P31+'1500'!P31+'2300'!P31+'4500'!P31+'5600'!P31+'7010'!P33+'7200'!P31+'7300'!P31+'8200'!P31+'9510'!P31 -> 490.28 | Q31: =SUM(E31:P31) -> 6355.1
D33: Building Maint.-Contractual | E33: =+'1100'!E33+'1500'!E33+'2300'!E33+'4500'!E33+'5600'!E33+'7010'!E35+'7200'!E33+'7300'!E33+'8200'!E33+'9510'!E33 -> 3916 | F33: =+'1100'!F33+'1500'!F33+'2300'!F33+'4500'!F33+'5600'!F33+'7010'!F35+'7200'!F33+'7300'!F33+'8200'!F33+'9510'!F33 -> 850 | G33: =+'1100'!G33+'1500'!G33+'2300'!G33+'4500'!G33+'5600'!G33+'7010'!G35+'7200'!G33+'7300'!G33+'8200'!G33+'9510'!G33 -> 0 | H33: =+'1100'!H33+'1500'!H33+'2300'!H33+'4500'!H33+'5600'!H33+'7010'!H35+'7200'!H33+'7300'!H33+'8200'!H33+'9510'!H33 -> 4716 | I33: =+'1100'!I33+'1500'!I33+'2300'!I33+'4500'!I33+'5600'!I33+'7010'!I35+'7200'!I33+'7300'!I33+'8200'!I33+'9510'!I33 -> 4379.25 | J33: =+'1100'!J33+'1500'!J33+'2300'!J33+'4500'!J33+'5600'!J33+'7010'!J35+'7200'!J33+'7300'!J33+'8200'!J33+'9510'!J33 -> 0 | K33: =+'1100'!K33+'1500'!K33+'2300'!K33+'4500'!K33+'5600'!K33+'7010'!K35+'7200'!K33+'7300'!K33+'8200'!K33+'9510'!K33 -> 3916 | L33: =+'1100'!L33+'1500'!L33+'2300'!L33+'4500'!L33+'5600'!L33+'7010'!L35+'7200'!L33+'7300'!L33+'8200'!L33+'9510'!L33 -> 400 | ... P33: =+'1100'!P33+'1500'!P33+'2300'!P33+'4500'!P33+'5600'!P33+'7010'!P35+'7200'!P33+'7300'!P33+'8200'!P33+'9510'!P33 -> 0 | Q33: =SUM(E33:P33) -> 40557.5
D34: Building Maint.-Recurring | E34: =+'1100'!E34+'1500'!E34+'2300'!E34+'4500'!E34+'5600'!E34+'7010'!E36+'7200'!E34+'7300'!E34+'8200'!E34+'9510'!E34 -> 2835.15 | F34: =+'1100'!F34+'1500'!F34+'2300'!F34+'4500'!F34+'5600'!F34+'7010'!F36+'7200'!F34+'7300'!F34+'8200'!F34+'9510'!F34 -> 2835.15 | G34: =+'1100'!G34+'1500'!G34+'2300'!G34+'4500'!G34+'5600'!G34+'7010'!G36+'7200'!G34+'7300'!G34+'8200'!G34+'9510'!G34 -> 2835.15 | H34: =+'1100'!H34+'1500'!H34+'2300'!H34+'4500'!H34+'5600'!H34+'7010'!H36+'7200'!H34+'7300'!H34+'8200'!H34+'9510'!H34 -> 3135.15 | I34: =+'1100'!I34+'1500'!I34+'2300'!I34+'4500'!I34+'5600'!I34+'7010'!I36+'7200'!I34+'7300'!I34+'8200'!I34+'9510'!I34 -> 3460.15 | J34: =+'1100'!J34+'1500'!J34+'2300'!J34+'4500'!J34+'5600'!J34+'7010'!J36+'7200'!J34+'7300'!J34+'8200'!J34+'9510'!J34 -> 2835.15 | K34: =+'1100'!K34+'1500'!K34+'2300'!K34+'4500'!K34+'5600'!K34+'7010'!K36+'7200'!K34+'7300'!K34+'8200'!K34+'9510'!K34 -> 2835.15 | L34: =+'1100'!L34+'1500'!L34+'2300'!L34+'4500'!L34+'5600'!L34+'7010'!L36+'7200'!L34+'7300'!L34+'8200'!L34+'9510'!L34 -> 2835.15 | ... P34: =+'1100'!P34+'1500'!P34+'2300'!P34+'4500'!P34+'5600'!P34+'7010'!P36+'7200'!P34+'7300'!P34+'8200'!P34+'9510'!P34 -> 2835.15 | Q34: =SUM(E34:P34) -> 37998.8
D35: Building Maint.-7010 Office Center | E35: ='7010'!E37 -> 824 | F35: ='7010'!F37 -> 901.25 | G35: ='7010'!G37 -> 51.5 | H35: ='7010'!H37 -> 824 | I35: ='7010'!I37 -> 1364.75 | J35: ='7010'!J37 -> 51.5 | K35: ='7010'!K37 -> 824 | L35: ='7010'!L37 -> 901.25 | ... P35: ='7010'!P37 -> 51.5 | Q35: =SUM(E35:P35) -> 7570.5
D36: Building Maint.-Big Projects | E36: =+'1100'!E35+'1500'!E35+'2300'!E35+'4500'!E35+'5600'!E35+'7010'!E38+'7200'!E35+'7300'!E35+'8200'!E35+'9510'!E35 -> 0 | F36: =+'1100'!F35+'1500'!F35+'2300'!F35+'4500'!F35+'5600'!F35+'7010'!F38+'7200'!F35+'7300'!F35+'8200'!F35+'9510'!F35 -> 500 | G36: =+'1100'!G35+'1500'!G35+'2300'!G35+'4500'!G35+'5600'!G35+'7010'!G38+'7200'!G35+'7300'!G35+'8200'!G35+'9510'!G35 -> 23100 | H36: =+'1100'!H35+'1500'!H35+'2300'!H35+'4500'!H35+'5600'!H35+'7010'!H38+'7200'!H35+'7300'!H35+'8200'!H35+'9510'!H35 -> 24860 | I36: =+'1100'!I35+'1500'!I35+'2300'!I35+'4500'!I35+'5600'!I35+'7010'!I38+'7200'!I35+'7300'!I35+'8200'!I35+'9510'!I35 -> 500 | J36: =+'1100'!J35+'1500'!J35+'2300'!J35+'4500'!J35+'5600'!J35+'7010'!J38+'7200'!J35+'7300'!J35+'8200'!J35+'9510'!J35 -> 0 | K36: =+'1100'!K35+'1500'!K35+'2300'!K35+'4500'!K35+'5600'!K35+'7010'!K38+'7200'!K35+'7300'!K35+'8200'!K35+'9510'!K35 -> 0 | L36: =+'1100'!L35+'1500'!L35+'2300'!L35+'4500'!L35+'5600'!L35+'7010'!L38+'7200'!L35+'7300'!L35+'8200'!L35+'9510'!L35 -> 13000 | ... P36: =+'1100'!P35+'1500'!P35+'2300'!P35+'4500'!P35+'5600'!P35+'7010'!P38+'7200'!P35+'7300'!P35+'8200'!P35+'9510'!P35 -> 0 | Q36: =SUM(E36:P36) -> 97920
A37: 6220-8502 | C37: Building Maintenance | E37: =SUM(E33:E36) -> 7575.15 | F37: =SUM(F33:F36) -> 5086.4 | G37: =SUM(G33:G36) -> 25986.65 | H37: =SUM(H33:H36) -> 33535.15 | I37: =SUM(I33:I36) -> 9704.15 | J37: =SUM(J33:J36) -> 2886.65 | K37: =SUM(K33:K36) -> 7575.15 | L37: =SUM(L33:L36) -> 17136.4 | ... Q37: =SUM(Q33:Q36) -> 184046.8
A39: 6330-8502 | B39: (SC) | C39: Parking Lot Cleaning | E39: =+'1100'!E38+'1500'!E38+'2300'!E38+'4500'!E38+'5600'!E38+'7010'!E41+'7200'!E38+'7300'!E38+'8200'!E38+'9510'!E38 -> 11454.9 | F39: =+'1100'!F38+'1500'!F38+'2300'!F38+'4500'!F38+'5600'!F38+'7010'!F41+'7200'!F38+'7300'!F38+'8200'!F38+'9510'!F38 -> 12042 | G39: =+'1100'!G38+'1500'!G38+'2300'!G38+'4500'!G38+'5600'!G38+'7010'!G41+'7200'!G38+'7300'!G38+'8200'!G38+'9510'!G38 -> 11969.9 | H39: =+'1100'!H38+'1500'!H38+'2300'!H38+'4500'!H38+'5600'!H38+'7010'!H41+'7200'!H38+'7300'!H38+'8200'!H38+'9510'!H38 -> 11454.9 | I39: =+'1100'!I38+'1500'!I38+'2300'!I38+'4500'!I38+'5600'!I38+'7010'!I41+'7200'!I38+'7300'!I38+'8200'!I38+'9510'!I38 -> 12042 | J39: =+'1100'!J38+'1500'!J38+'2300'!J38+'4500'!J38+'5600'!J38+'7010'!J41+'7200'!J38+'7300'!J38+'8200'!J38+'9510'!J38 -> 11454.9 | K39: =+'1100'!K38+'1500'!K38+'2300'!K38+'4500'!K38+'5600'!K38+'7010'!K41+'7200'!K38+'7300'!K38+'8200'!K38+'9510'!K38 -> 11660.9 | L39: =+'1100'!L38+'1500'!L38+'2300'!L38+'4500'!L38+'5600'!L38+'7010'!L41+'7200'!L38+'7300'!L38+'8200'!L38+'9510'!L38 -> 12042 | ... P39: =+'1100'!P38+'1500'!P38+'2300'!P38+'4500'!P38+'5600'!P38+'7010'!P41+'7200'!P38+'7300'!P38+'8200'!P38+'9510'!P38 -> 11351.9 | Q39: =SUM(E39:P39) -> 140940.2
D41: Parking Lot Maint.-Contractual | E41: =+'1100'!E40+'1500'!E40+'2300'!E40+'4500'!E40+'5600'!E40+'7010'!E43+'7200'!E40+'7300'!E40+'8200'!E40+'9510'!E40 -> 0 | F41: =+'1100'!F40+'1500'!F40+'2300'!F40+'4500'!F40+'5600'!F40+'7010'!F43+'7200'!F40+'7300'!F40+'8200'!F40+'9510'!F40 -> 0 | G41: =+'1100'!G40+'1500'!G40+'2300'!G40+'4500'!G40+'5600'!G40+'7010'!G43+'7200'!G40+'7300'!G40+'8200'!G40+'9510'!G40 -> 0 | H41: =+'1100'!H40+'1500'!H40+'2300'!H40+'4500'!H40+'5600'!H40+'7010'!H43+'7200'!H40+'7300'!H40+'8200'!H40+'9510'!H40 -> 0 | I41: =+'1100'!I40+'1500'!I40+'2300'!I40+'4500'!I40+'5600'!I40+'7010'!I43+'7200'!I40+'7300'!I40+'8200'!I40+'9510'!I40 -> 0 | J41: =+'1100'!J40+'1500'!J40+'2300'!J40+'4500'!J40+'5600'!J40+'7010'!J43+'7200'!J40+'7300'!J40+'8200'!J40+'9510'!J40 -> 0 | K41: =+'1100'!K40+'1500'!K40+'2300'!K40+'4500'!K40+'5600'!K40+'7010'!K43+'7200'!K40+'7300'!K40+'8200'!K40+'9510'!K40 -> 0 | L41: =+'1100'!L40+'1500'!L40+'2300'!L40+'4500'!L40+'5600'!L40+'7010'!L43+'7200'!L40+'7300'!L40+'8200'!L40+'9510'!L40 -> 0 | ... P41: =+'1100'!P40+'1500'!P40+'2300'!P40+'4500'!P40+'5600'!P40+'7010'!P43+'7200'!P40+'7300'!P40+'8200'!P40+'9510'!P40 -> 0 | Q41: =SUM(E41:P41) -> 0
D42: Parking Lot Maint.-Recurring | E42: =+'1100'!E41+'1500'!E41+'2300'!E41+'4500'!E41+'5600'!E41+'7010'!E44+'7200'!E41+'7300'!E41+'8200'!E41+'9510'!E41 -> 2523.5 | F42: =+'1100'!F41+'1500'!F41+'2300'!F41+'4500'!F41+'5600'!F41+'7010'!F44+'7200'!F41+'7300'!F41+'8200'!F41+'9510'!F41 -> 2163 | G42: =+'1100'!G41+'1500'!G41+'2300'!G41+'4500'!G41+'5600'!G41+'7010'!G44+'7200'!G41+'7300'!G41+'8200'!G41+'9510'!G41 -> 7172.5 | H42: =+'1100'!H41+'1500'!H41+'2300'!H41+'4500'!H41+'5600'!H41+'7010'!H44+'7200'!H41+'7300'!H41+'8200'!H41+'9510'!H41 -> 5768 | I42: =+'1100'!I41+'1500'!I41+'2300'!I41+'4500'!I41+'5600'!I41+'7010'!I44+'7200'!I41+'7300'!I41+'8200'!I41+'9510'!I41 -> 2163 | J42: =+'1100'!J41+'1500'!J41+'2300'!J41+'4500'!J41+'5600'!J41+'7010'!J44+'7200'!J41+'7300'!J41+'8200'!J41+'9510'!J41 -> 7172.5 | K42: =+'1100'!K41+'1500'!K41+'2300'!K41+'4500'!K41+'5600'!K41+'7010'!K44+'7200'!K41+'7300'!K41+'8200'!K41+'9510'!K41 -> 2102.23 | L42: =+'1100'!L41+'1500'!L41+'2300'!L41+'4500'!L41+'5600'!L41+'7010'!L44+'7200'!L41+'7300'!L41+'8200'!L41+'9510'!L41 -> 2163 | ... P42: =+'1100'!P41+'1500'!P41+'2300'!P41+'4500'!P41+'5600'!P41+'7010'!P44+'7200'!P41+'7300'!P41+'8200'!P41+'9510'!P41 -> 7496.95 | Q42: =SUM(E42:P42) -> 54755.18
D43: Parking Lot Maint.-Big Projects | E43: =+'1100'!E42+'1500'!E42+'2300'!E42+'4500'!E42+'5600'!E42+'7010'!E45+'7200'!E42+'7300'!E42+'8200'!E42+'9510'!E42 -> 0 | F43: =+'1100'!F42+'1500'!F42+'2300'!F42+'4500'!F42+'5600'!F42+'7010'!F45+'7200'!F42+'7300'!F42+'8200'!F42+'9510'!F42 -> 0 | G43: =+'1100'!G42+'1500'!G42+'2300'!G42+'4500'!G42+'5600'!G42+'7010'!G45+'7200'!G42+'7300'!G42+'8200'!G42+'9510'!G42 -> 25750 | H43: =+'1100'!H42+'1500'!H42+'2300'!H42+'4500'!H42+'5600'!H42+'7010'!H45+'7200'!H42+'7300'!H42+'8200'!H42+'9510'!H42 -> 15150 | I43: =+'1100'!I42+'1500'!I42+'2300'!I42+'4500'!I42+'5600'!I42+'7010'!I45+'7200'!I42+'7300'!I42+'8200'!I42+'9510'!I42 -> 0 | J43: =+'1100'!J42+'1500'!J42+'2300'!J42+'4500'!J42+'5600'!J42+'7010'!J45+'7200'!J42+'7300'!J42+'8200'!J42+'9510'!J42 -> 15450 | K43: =+'1100'!K42+'1500'!K42+'2300'!K42+'4500'!K42+'5600'!K42+'7010'!K45+'7200'!K42+'7300'!K42+'8200'!K42+'9510'!K42 -> 0 | L43: =+'1100'!L42+'1500'!L42+'2300'!L42+'4500'!L42+'5600'!L42+'7010'!L45+'7200'!L42+'7300'!L42+'8200'!L42+'9510'!L42 -> 0 | ... P43: =+'1100'!P42+'1500'!P42+'2300'!P42+'4500'!P42+'5600'!P42+'7010'!P45+'7200'!P42+'7300'!P42+'8200'!P42+'9510'!P42 -> 0 | Q43: =SUM(E43:P43) -> 102400
A44: 6360-8502 | C44: Parking Lot Maintenance | E44: =SUM(E41:E43) -> 2523.5 | F44: =SUM(F41:F43) -> 2163 | G44: =SUM(G41:G43) -> 32922.5 | H44: =SUM(H41:H43) -> 20918 | I44: =SUM(I41:I43) -> 2163 | J44: =SUM(J41:J43) -> 22622.5 | K44: =SUM(K41:K43) -> 2102.23 | L44: =SUM(L41:L43) -> 2163 | ... Q44: =SUM(Q41:Q43) -> 157155.18
A46: 6370-8502 | C46: Snow Removal | E46: =+'1100'!E45+'1500'!E45+'2300'!E45+'4500'!E45+'5600'!E45+'7010'!E48+'7200'!E45+'7300'!E45+'8200'!E45+'9510'!E45 -> 47380 | F46: =+'1100'!F45+'1500'!F45+'2300'!F45+'4500'!F45+'5600'!F45+'7010'!F48+'7200'!F45+'7300'!F45+'8200'!F45+'9510'!F45 -> 47380 | G46: =+'1100'!G45+'1500'!G45+'2300'!G45+'4500'!G45+'5600'!G45+'7010'!G48+'7200'!G45+'7300'!G45+'8200'!G45+'9510'!G45 -> 14420 | H46: =+'1100'!H45+'1500'!H45+'2300'!H45+'4500'!H45+'5600'!H45+'7010'!H48+'7200'!H45+'7300'!H45+'8200'!H45+'9510'!H45 -> 0 | I46: =+'1100'!I45+'1500'!I45+'2300'!I45+'4500'!I45+'5600'!I45+'7010'!I48+'7200'!I45+'7300'!I45+'8200'!I45+'9510'!I45 -> 0 | J46: =+'1100'!J45+'1500'!J45+'2300'!J45+'4500'!J45+'5600'!J45+'7010'!J48+'7200'!J45+'7300'!J45+'8200'!J45+'9510'!J45 -> 0 | K46: =+'1100'!K45+'1500'!K45+'2300'!K45+'4500'!K45+'5600'!K45+'7010'!K48+'7200'!K45+'7300'!K45+'8200'!K45+'9510'!K45 -> 0 | L46: =+'1100'!L45+'1500'!L45+'2300'!L45+'4500'!L45+'5600'!L45+'7010'!L48+'7200'!L45+'7300'!L45+'8200'!L45+'9510'!L45 -> 0 | ... P46: =+'1100'!P45+'1500'!P45+'2300'!P45+'4500'!P45+'5600'!P45+'7010'!P48+'7200'!P45+'7300'!P45+'8200'!P45+'9510'!P45 -> 29355 | Q46: =SUM(E46:P46) -> 151410
D48: Landscaping-Contractual | E48: =+'1100'!E47+'1500'!E47+'2300'!E47+'4500'!E47+'5600'!E47+'7010'!E50+'7200'!E47+'7300'!E47+'8200'!E47+'9510'!E47 -> 0 | F48: =+'1100'!F47+'1500'!F47+'2300'!F47+'4500'!F47+'5600'!F47+'7010'!F50+'7200'!F47+'7300'!F47+'8200'!F47+'9510'!F47 -> 0 | G48: =+'1100'!G47+'1500'!G47+'2300'!G47+'4500'!G47+'5600'!G47+'7010'!G50+'7200'!G47+'7300'!G47+'8200'!G47+'9510'!G47 -> 1998.2 | H48: =+'1100'!H47+'1500'!H47+'2300'!H47+'4500'!H47+'5600'!H47+'7010'!H50+'7200'!H47+'7300'!H47+'8200'!H47+'9510'!H47 -> 5773.2 | I48: =+'1100'!I47+'1500'!I47+'2300'!I47+'4500'!I47+'5600'!I47+'7010'!I50+'7200'!I47+'7300'!I47+'8200'!I47+'9510'!I47 -> 5773.2 | J48: =+'1100'!J47+'1500'!J47+'2300'!J47+'4500'!J47+'5600'!J47+'7010'!J50+'7200'!J47+'7300'!J47+'8200'!J47+'9510'!J47 -> 5773.2 | K48: =+'1100'!K47+'1500'!K47+'2300'!K47+'4500'!K47+'5600'!K47+'7010'!K50+'7200'!K47+'7300'!K47+'8200'!K47+'9510'!K47 -> 5773.2 | L48: =+'1100'!L47+'1500'!L47+'2300'!L47+'4500'!L47+'5600'!L47+'7010'!L50+'7200'!L47+'7300'!L47+'8200'!L47+'9510'!L47 -> 5773.2 | ... P48: =+'1100'!P47+'1500'!P47+'2300'!P47+'4500'!P47+'5600'!P47+'7010'!P50+'7200'!P47+'7300'!P47+'8200'!P47+'9510'!P47 -> 0 | Q48: =SUM(E48:P48) -> 42410.6
D49: Landscaping-Recurring | E49: =+'1100'!E48+'1500'!E48+'2300'!E48+'4500'!E48+'5600'!E48+'7010'!E51+'7200'!E48+'7300'!E48+'8200'!E48+'9510'!E48 -> 0 | F49: =+'1100'!F48+'1500'!F48+'2300'!F48+'4500'!F48+'5600'!F48+'7010'!F51+'7200'!F48+'7300'!F48+'8200'!F48+'9510'!F48 -> 0 | G49: =+'1100'!G48+'1500'!G48+'2300'!G48+'4500'!G48+'5600'!G48+'7010'!G51+'7200'!G48+'7300'!G48+'8200'!G48+'9510'!G48 -> 206 | H49: =+'1100'!H48+'1500'!H48+'2300'!H48+'4500'!H48+'5600'!H48+'7010'!H51+'7200'!H48+'7300'!H48+'8200'!H48+'9510'!H48 -> 1030 | I49: =+'1100'!I48+'1500'!I48+'2300'!I48+'4500'!I48+'5600'!I48+'7010'!I51+'7200'!I48+'7300'!I48+'8200'!I48+'9510'!I48 -> 1030 | J49: =+'1100'!J48+'1500'!J48+'2300'!J48+'4500'!J48+'5600'!J48+'7010'!J51+'7200'!J48+'7300'!J48+'8200'!J48+'9510'!J48 -> 1030 | K49: =+'1100'!K48+'1500'!K48+'2300'!K48+'4500'!K48+'5600'!K48+'7010'!K51+'7200'!K48+'7300'!K48+'8200'!K48+'9510'!K48 -> 1030 | L49: =+'1100'!L48+'1500'!L48+'2300'!L48+'4500'!L48+'5600'!L48+'7010'!L51+'7200'!L48+'7300'!L48+'8200'!L48+'9510'!L48 -> 1030 | ... P49: =+'1100'!P48+'1500'!P48+'2300'!P48+'4500'!P48+'5600'!P48+'7010'!P51+'7200'!P48+'7300'!P48+'8200'!P48+'9510'!P48 -> 0 | Q49: =SUM(E49:P49) -> 7416
D50: Landscaping-Big Projects | E50: =+'1100'!E49+'1500'!E49+'2300'!E49+'4500'!E49+'5600'!E49+'7010'!E52+'7200'!E49+'7300'!E49+'8200'!E49+'9510'!E49 -> 0 | F50: =+'1100'!F49+'1500'!F49+'2300'!F49+'4500'!F49+'5600'!F49+'7010'!F52+'7200'!F49+'7300'!F49+'8200'!F49+'9510'!F49 -> 0 | G50: =+'1100'!G49+'1500'!G49+'2300'!G49+'4500'!G49+'5600'!G49+'7010'!G52+'7200'!G49+'7300'!G49+'8200'!G49+'9510'!G49 -> 0 | H50: =+'1100'!H49+'1500'!H49+'2300'!H49+'4500'!H49+'5600'!H49+'7010'!H52+'7200'!H49+'7300'!H49+'8200'!H49+'9510'!H49 -> 0 | I50: =+'1100'!I49+'1500'!I49+'2300'!I49+'4500'!I49+'5600'!I49+'7010'!I52+'7200'!I49+'7300'!I49+'8200'!I49+'9510'!I49 -> 31100 | J50: =+'1100'!J49+'1500'!J49+'2300'!J49+'4500'!J49+'5600'!J49+'7010'!J52+'7200'!J49+'7300'!J49+'8200'!J49+'9510'!J49 -> 0 | K50: =+'1100'!K49+'1500'!K49+'2300'!K49+'4500'!K49+'5600'!K49+'7010'!K52+'7200'!K49+'7300'!K49+'8200'!K49+'9510'!K49 -> 0 | L50: =+'1100'!L49+'1500'!L49+'2300'!L49+'4500'!L49+'5600'!L49+'7010'!L52+'7200'!L49+'7300'!L49+'8200'!L49+'9510'!L49 -> 10500 | ... P50: =+'1100'!P49+'1500'!P49+'2300'!P49+'4500'!P49+'5600'!P49+'7010'!P52+'7200'!P49+'7300'!P49+'8200'!P49+'9510'!P49 -> 0 | Q50: =SUM(E50:P50) -> 45720
A51: 6380-8502 | C51: Landscaping | E51: =SUM(E48:E50) -> 0 | F51: =SUM(F48:F50) -> 0 | G51: =SUM(G48:G50) -> 2204.2 | H51: =SUM(H48:H50) -> 6803.2 | I51: =SUM(I48:I50) -> 37903.2 | J51: =SUM(J48:J50) -> 6803.2 | K51: =SUM(K48:K50) -> 6803.2 | L51: =SUM(L48:L50) -> 17303.2 | ... Q51: =SUM(Q48:Q50) -> 95546.6
A53: 6350-8502 | C53: Security | E53: =+'1100'!E52+'1500'!E52+'2300'!E52+'4500'!E52+'5600'!E52+'7010'!E55+'7200'!E52+'7300'!E52+'8200'!E52+'9510'!E52 -> 25684.7 | F53: =+'1100'!F52+'1500'!F52+'2300'!F52+'4500'!F52+'5600'!F52+'7010'!F55+'7200'!F52+'7300'!F52+'8200'!F52+'9510'!F52 -> 25684.7 | G53: =+'1100'!G52+'1500'!G52+'2300'!G52+'4500'!G52+'5600'!G52+'7010'!G55+'7200'!G52+'7300'!G52+'8200'!G52+'9510'!G52 -> 26714.7 | H53: =+'1100'!H52+'1500'!H52+'2300'!H52+'4500'!H52+'5600'!H52+'7010'!H55+'7200'!H52+'7300'!H52+'8200'!H52+'9510'!H52 -> 25684.7 | I53: =+'1100'!I52+'1500'!I52+'2300'!I52+'4500'!I52+'5600'!I52+'7010'!I55+'7200'!I52+'7300'!I52+'8200'!I52+'9510'!I52 -> 28259.7 | J53: =+'1100'!J52+'1500'!J52+'2300'!J52+'4500'!J52+'5600'!J52+'7010'!J55+'7200'!J52+'7300'!J52+'8200'!J52+'9510'!J52 -> 25684.7 | K53: =+'1100'!K52+'1500'!K52+'2300'!K52+'4500'!K52+'5600'!K52+'7010'!K55+'7200'!K52+'7300'!K52+'8200'!K52+'9510'!K52 -> 25684.7 | L53: =+'1100'!L52+'1500'!L52+'2300'!L52+'4500'!L52+'5600'!L52+'7010'!L55+'7200'!L52+'7300'!L52+'8200'!L52+'9510'!L52 -> 25684.7 | ... P53: =+'1100'!P52+'1500'!P52+'2300'!P52+'4500'!P52+'5600'!P52+'7010'!P55+'7200'!P52+'7300'!P52+'8200'!P52+'9510'!P52 -> 25684.7 | Q53: =SUM(E53:P53) -> 315426.4
A55: 6610-8502 | B55: (BP) | C55: Management Fee | E55: ='1100'!E54+'1500'!E54+'2300'!E54+'4500'!E54+'5600'!E54+'7010'!E57+'7200'!E54+'7300'!E54+'8200'!E54+'9510'!E54 -> 0 | F55: ='1100'!F54+'1500'!F54+'2300'!F54+'4500'!F54+'5600'!F54+'7010'!F57+'7200'!F54+'7300'!F54+'8200'!F54+'9510'!F54 -> 0 | G55: ='1100'!G54+'1500'!G54+'2300'!G54+'4500'!G54+'5600'!G54+'7010'!G57+'7200'!G54+'7300'!G54+'8200'!G54+'9510'!G54 -> 0 | H55: ='1100'!H54+'1500'!H54+'2300'!H54+'4500'!H54+'5600'!H54+'7010'!H57+'7200'!H54+'7300'!H54+'8200'!H54+'9510'!H54 -> 0 | I55: ='1100'!I54+'1500'!I54+'2300'!I54+'4500'!I54+'5600'!I54+'7010'!I57+'7200'!I54+'7300'!I54+'8200'!I54+'9510'!I54 -> 0 | J55: ='1100'!J54+'1500'!J54+'2300'!J54+'4500'!J54+'5600'!J54+'7010'!J57+'7200'!J54+'7300'!J54+'8200'!J54+'9510'!J54 -> 0 | K55: ='1100'!K54+'1500'!K54+'2300'!K54+'4500'!K54+'5600'!K54+'7010'!K57+'7200'!K54+'7300'!K54+'8200'!K54+'9510'!K54 -> 0 | L55: ='1100'!L54+'1500'!L54+'2300'!L54+'4500'!L54+'5600'!L54+'7010'!L57+'7200'!L54+'7300'!L54+'8200'!L54+'9510'!L54 -> 0 | ... P55: ='1100'!P54+'1500'!P54+'2300'!P54+'4500'!P54+'5600'!P54+'7010'!P57+'7200'!P54+'7300'!P54+'8200'!P54+'9510'!P54 -> 0 | Q55: =SUM(E55:P55) -> 0
A57: 6270-8502 | C57: Trash Removal | E57: =+'1100'!E56+'1500'!E56+'2300'!E56+'4500'!E56+'5600'!E56+'7010'!E59+'7200'!E56+'7300'!E56+'8200'!E56+'9510'!E56 -> 5856.9 | F57: =+'1100'!F56+'1500'!F56+'2300'!F56+'4500'!F56+'5600'!F56+'7010'!F59+'7200'!F56+'7300'!F56+'8200'!F56+'9510'!F56 -> 4356.9 | G57: =+'1100'!G56+'1500'!G56+'2300'!G56+'4500'!G56+'5600'!G56+'7010'!G59+'7200'!G56+'7300'!G56+'8200'!G56+'9510'!G56 -> 4356.9 | H57: =+'1100'!H56+'1500'!H56+'2300'!H56+'4500'!H56+'5600'!H56+'7010'!H59+'7200'!H56+'7300'!H56+'8200'!H56+'9510'!H56 -> 5856.9 | I57: =+'1100'!I56+'1500'!I56+'2300'!I56+'4500'!I56+'5600'!I56+'7010'!I59+'7200'!I56+'7300'!I56+'8200'!I56+'9510'!I56 -> 4356.9 | J57: =+'1100'!J56+'1500'!J56+'2300'!J56+'4500'!J56+'5600'!J56+'7010'!J59+'7200'!J56+'7300'!J56+'8200'!J56+'9510'!J56 -> 4356.9 | K57: =+'1100'!K56+'1500'!K56+'2300'!K56+'4500'!K56+'5600'!K56+'7010'!K59+'7200'!K56+'7300'!K56+'8200'!K56+'9510'!K56 -> 5856.9 | L57: =+'1100'!L56+'1500'!L56+'2300'!L56+'4500'!L56+'5600'!L56+'7010'!L59+'7200'!L56+'7300'!L56+'8200'!L56+'9510'!L56 -> 4356.9 | ... P57: =+'1100'!P56+'1500'!P56+'2300'!P56+'4500'!P56+'5600'!P56+'7010'!P59+'7200'!P56+'7300'!P56+'8200'!P56+'9510'!P56 -> 4356.9 | Q57: =SUM(E57:P57) -> 58282.8
A59: 6410-8502 | C59: Real Estate Taxes | E59: =+'1100'!E58+'1500'!E58+'2300'!E58+'4500'!E58+'5600'!E58+'7010'!E61+'7200'!E58+'7300'!E58+'8200'!E58+'9510'!E58 -> 56590.558 | F59: =+'1100'!F58+'1500'!F58+'2300'!F58+'4500'!F58+'5600'!F58+'7010'!F61+'7200'!F58+'7300'!F58+'8200'!F58+'9510'!F58 -> 56590.558 | G59: =+'1100'!G58+'1500'!G58+'2300'!G58+'4500'!G58+'5600'!G58+'7010'!G61+'7200'!G58+'7300'!G58+'8200'!G58+'9510'!G58 -> 56590.558 | H59: =+'1100'!H58+'1500'!H58+'2300'!H58+'4500'!H58+'5600'!H58+'7010'!H61+'7200'!H58+'7300'!H58+'8200'!H58+'9510'!H58 -> 56590.558 | I59: =+'1100'!I58+'1500'!I58+'2300'!I58+'4500'!I58+'5600'!I58+'7010'!I61+'7200'!I58+'7300'!I58+'8200'!I58+'9510'!I58 -> 56590.558 | J59: =+'1100'!J58+'1500'!J58+'2300'!J58+'4500'!J58+'5600'!J58+'7010'!J61+'7200'!J58+'7300'!J58+'8200'!J58+'9510'!J58 -> 56590.558 | K59: =+'1100'!K58+'1500'!K58+'2300'!K58+'4500'!K58+'5600'!K58+'7010'!K61+'7200'!K58+'7300'!K58+'8200'!K58+'9510'!K58 -> 56590.558 | L59: =+'1100'!L58+'1500'!L58+'2300'!L58+'4500'!L58+'5600'!L58+'7010'!L61+'7200'!L58+'7300'!L58+'8200'!L58+'9510'!L58 -> 56590.558 | ... P59: =+'1100'!P58+'1500'!P58+'2300'!P58+'4500'!P58+'5600'!P58+'7010'!P61+'7200'!P58+'7300'!P58+'8200'!P58+'9510'!P58 -> 56590.558 | Q59: =SUM(E59:P59) -> 679086.7
D61: Insurance-Liability | E61: =+'1100'!E60+'1500'!E60+'2300'!E60+'4500'!E60+'5600'!E60+'7010'!E63+'7200'!E60+'7300'!E60+'8200'!E60+'9510'!E60 -> 15781 | F61: =+'1100'!F60+'1500'!F60+'2300'!F60+'4500'!F60+'5600'!F60+'7010'!F63+'7200'!F60+'7300'!F60+'8200'!F60+'9510'!F60 -> 15781 | G61: =+'1100'!G60+'1500'!G60+'2300'!G60+'4500'!G60+'5600'!G60+'7010'!G63+'7200'!G60+'7300'!G60+'8200'!G60+'9510'!G60 -> 15781 | H61: =+'1100'!H60+'1500'!H60+'2300'!H60+'4500'!H60+'5600'!H60+'7010'!H63+'7200'!H60+'7300'!H60+'8200'!H60+'9510'!H60 -> 15781 | I61: =+'1100'!I60+'1500'!I60+'2300'!I60+'4500'!I60+'5600'!I60+'7010'!I63+'7200'!I60+'7300'!I60+'8200'!I60+'9510'!I60 -> 15781 | J61: =+'1100'!J60+'1500'!J60+'2300'!J60+'4500'!J60+'5600'!J60+'7010'!J63+'7200'!J60+'7300'!J60+'8200'!J60+'9510'!J60 -> 15781 | K61: =+'1100'!K60+'1500'!K60+'2300'!K60+'4500'!K60+'5600'!K60+'7010'!K63+'7200'!K60+'7300'!K60+'8200'!K60+'9510'!K60 -> 15781 | L61: =+'1100'!L60+'1500'!L60+'2300'!L60+'4500'!L60+'5600'!L60+'7010'!L63+'7200'!L60+'7300'!L60+'8200'!L60+'9510'!L60 -> 15781 | ... P61: =+'1100'!P60+'1500'!P60+'2300'!P60+'4500'!P60+'5600'!P60+'7010'!P63+'7200'!P60+'7300'!P60+'8200'!P60+'9510'!P60 -> 16096.62 | Q61: =SUM(E61:P61) -> 190003.24
D62: Insurabce-Property | E62: =+'1100'!E61+'1500'!E61+'2300'!E61+'4500'!E61+'5600'!E61+'7010'!E64+'7200'!E61+'7300'!E61+'8200'!E61+'9510'!E61 -> 5697 | F62: =+'1100'!F61+'1500'!F61+'2300'!F61+'4500'!F61+'5600'!F61+'7010'!F64+'7200'!F61+'7300'!F61+'8200'!F61+'9510'!F61 -> 5697 | G62: =+'1100'!G61+'1500'!G61+'2300'!G61+'4500'!G61+'5600'!G61+'7010'!G64+'7200'!G61+'7300'!G61+'8200'!G61+'9510'!G61 -> 5697 | H62: =+'1100'!H61+'1500'!H61+'2300'!H61+'4500'!H61+'5600'!H61+'7010'!H64+'7200'!H61+'7300'!H61+'8200'!H61+'9510'!H61 -> 5697 | I62: =+'1100'!I61+'1500'!I61+'2300'!I61+'4500'!I61+'5600'!I61+'7010'!I64+'7200'!I61+'7300'!I61+'8200'!I61+'9510'!I61 -> 5697 | J62: =+'1100'!J61+'1500'!J61+'2300'!J61+'4500'!J61+'5600'!J61+'7010'!J64+'7200'!J61+'7300'!J61+'8200'!J61+'9510'!J61 -> 5697 | K62: =+'1100'!K61+'1500'!K61+'2300'!K61+'4500'!K61+'5600'!K61+'7010'!K64+'7200'!K61+'7300'!K61+'8200'!K61+'9510'!K61 -> 5697 | L62: =+'1100'!L61+'1500'!L61+'2300'!L61+'4500'!L61+'5600'!L61+'7010'!L64+'7200'!L61+'7300'!L61+'8200'!L61+'9510'!L61 -> 5697 | ... P62: =+'1100'!P61+'1500'!P61+'2300'!P61+'4500'!P61+'5600'!P61+'7010'!P64+'7200'!P61+'7300'!P61+'8200'!P61+'9510'!P61 -> 5810.94 | Q62: =SUM(E62:P62) -> 68591.88
D63: Insurance-Other | E63: =+'1100'!E62+'1500'!E62+'2300'!E62+'4500'!E62+'5600'!E62+'7010'!E65+'7200'!E62+'7300'!E62+'8200'!E62+'9510'!E62 -> 0 | F63: =+'1100'!F62+'1500'!F62+'2300'!F62+'4500'!F62+'5600'!F62+'7010'!F65+'7200'!F62+'7300'!F62+'8200'!F62+'9510'!F62 -> 0 | G63: =+'1100'!G62+'1500'!G62+'2300'!G62+'4500'!G62+'5600'!G62+'7010'!G65+'7200'!G62+'7300'!G62+'8200'!G62+'9510'!G62 -> 0 | H63: =+'1100'!H62+'1500'!H62+'2300'!H62+'4500'!H62+'5600'!H62+'7010'!H65+'7200'!H62+'7300'!H62+'8200'!H62+'9510'!H62 -> 0 | I63: =+'1100'!I62+'1500'!I62+'2300'!I62+'4500'!I62+'5600'!I62+'7010'!I65+'7200'!I62+'7300'!I62+'8200'!I62+'9510'!I62 -> 0 | J63: =+'1100'!J62+'1500'!J62+'2300'!J62+'4500'!J62+'5600'!J62+'7010'!J65+'7200'!J62+'7300'!J62+'8200'!J62+'9510'!J62 -> 0 | K63: =+'1100'!K62+'1500'!K62+'2300'!K62+'4500'!K62+'5600'!K62+'7010'!K65+'7200'!K62+'7300'!K62+'8200'!K62+'9510'!K62 -> 0 | L63: =+'1100'!L62+'1500'!L62+'2300'!L62+'4500'!L62+'5600'!L62+'7010'!L65+'7200'!L62+'7300'!L62+'8200'!L62+'9510'!L62 -> 0 | ... P63: =+'1100'!P62+'1500'!P62+'2300'!P62+'4500'!P62+'5600'!P62+'7010'!P65+'7200'!P62+'7300'!P62+'8200'!P62+'9510'!P62 -> 0 | Q63: =SUM(E63:P63) -> 0
A64: 6510-8502 | C64: Insurance | E64: =SUM(E61:E63) -> 21478 | F64: =SUM(F61:F63) -> 21478 | G64: =SUM(G61:G63) -> 21478 | H64: =SUM(H61:H63) -> 21478 | I64: =SUM(I61:I63) -> 21478 | J64: =SUM(J61:J63) -> 21478 | K64: =SUM(K61:K63) -> 21478 | L64: =SUM(L61:L63) -> 21478 | ... Q64: =SUM(Q61:Q63) -> 258595.12
D66: Cleaning & Supplies | E66: =+'1100'!E65+'1500'!E65+'2300'!E65+'4500'!E65+'5600'!E65+'7010'!E68+'7200'!E65+'7300'!E65+'8200'!E65+'9510'!E65 -> 0 | F66: =+'1100'!F65+'1500'!F65+'2300'!F65+'4500'!F65+'5600'!F65+'7010'!F68+'7200'!F65+'7300'!F65+'8200'!F65+'9510'!F65 -> 0 | G66: =+'1100'!G65+'1500'!G65+'2300'!G65+'4500'!G65+'5600'!G65+'7010'!G68+'7200'!G65+'7300'!G65+'8200'!G65+'9510'!G65 -> 0 | H66: =+'1100'!H65+'1500'!H65+'2300'!H65+'4500'!H65+'5600'!H65+'7010'!H68+'7200'!H65+'7300'!H65+'8200'!H65+'9510'!H65 -> 0 | I66: =+'1100'!I65+'1500'!I65+'2300'!I65+'4500'!I65+'5600'!I65+'7010'!I68+'7200'!I65+'7300'!I65+'8200'!I65+'9510'!I65 -> 0 | J66: =+'1100'!J65+'1500'!J65+'2300'!J65+'4500'!J65+'5600'!J65+'7010'!J68+'7200'!J65+'7300'!J65+'8200'!J65+'9510'!J65 -> 0 | K66: =+'1100'!K65+'1500'!K65+'2300'!K65+'4500'!K65+'5600'!K65+'7010'!K68+'7200'!K65+'7300'!K65+'8200'!K65+'9510'!K65 -> 0 | L66: =+'1100'!L65+'1500'!L65+'2300'!L65+'4500'!L65+'5600'!L65+'7010'!L68+'7200'!L65+'7300'!L65+'8200'!L65+'9510'!L65 -> 0 | ... P66: =+'1100'!P65+'1500'!P65+'2300'!P65+'4500'!P65+'5600'!P65+'7010'!P68+'7200'!P65+'7300'!P65+'8200'!P65+'9510'!P65 -> 0 | Q66: =SUM(E66:P66) -> 0
D67: Cleaning & Supplies-Vacancies | E67: =+'1100'!E66+'1500'!E66+'2300'!E66+'4500'!E66+'5600'!E66+'7010'!E69+'7200'!E66+'7300'!E66+'8200'!E66+'9510'!E66 -> 2163 | F67: =+'1100'!F66+'1500'!F66+'2300'!F66+'4500'!F66+'5600'!F66+'7010'!F69+'7200'!F66+'7300'!F66+'8200'!F66+'9510'!F66 -> 2163 | G67: =+'1100'!G66+'1500'!G66+'2300'!G66+'4500'!G66+'5600'!G66+'7010'!G69+'7200'!G66+'7300'!G66+'8200'!G66+'9510'!G66 -> 2163 | H67: =+'1100'!H66+'1500'!H66+'2300'!H66+'4500'!H66+'5600'!H66+'7010'!H69+'7200'!H66+'7300'!H66+'8200'!H66+'9510'!H66 -> 2163 | I67: =+'1100'!I66+'1500'!I66+'2300'!I66+'4500'!I66+'5600'!I66+'7010'!I69+'7200'!I66+'7300'!I66+'8200'!I66+'9510'!I66 -> 2163 | J67: =+'1100'!J66+'1500'!J66+'2300'!J66+'4500'!J66+'5600'!J66+'7010'!J69+'7200'!J66+'7300'!J66+'8200'!J66+'9510'!J66 -> 2163 | K67: =+'1100'!K66+'1500'!K66+'2300'!K66+'4500'!K66+'5600'!K66+'7010'!K69+'7200'!K66+'7300'!K66+'8200'!K66+'9510'!K66 -> 2163 | L67: =+'1100'!L66+'1500'!L66+'2300'!L66+'4500'!L66+'5600'!L66+'7010'!L69+'7200'!L66+'7300'!L66+'8200'!L66+'9510'!L66 -> 2163 | ... P67: =+'1100'!P66+'1500'!P66+'2300'!P66+'4500'!P66+'5600'!P66+'7010'!P69+'7200'!P66+'7300'!P66+'8200'!P66+'9510'!P66 -> 2163 | Q67: =SUM(E67:P67) -> 25956
A68: 6250-8502 | B68: (BP) | C68: Cleaning & Supplies | E68: =SUM(E66:E67) -> 2163 | F68: =SUM(F66:F67) -> 2163 | G68: =SUM(G66:G67) -> 2163 | H68: =SUM(H66:H67) -> 2163 | I68: =SUM(I66:I67) -> 2163 | J68: =SUM(J66:J67) -> 2163 | K68: =SUM(K66:K67) -> 2163 | L68: =SUM(L66:L67) -> 2163 | ... Q68: =SUM(Q66:Q67) -> 25956
B70: (SC) | C70: Other | E70: =+'1100'!E69+'1500'!E69+'2300'!E69+'4500'!E69+'5600'!E69+'7010'!E72+'7200'!E69+'7300'!E69+'8200'!E69+'9510'!E69 -> 0 | F70: =+'1100'!F69+'1500'!F69+'2300'!F69+'4500'!F69+'5600'!F69+'7010'!F72+'7200'!F69+'7300'!F69+'8200'!F69+'9510'!F69 -> 0 | G70: =+'1100'!G69+'1500'!G69+'2300'!G69+'4500'!G69+'5600'!G69+'7010'!G72+'7200'!G69+'7300'!G69+'8200'!G69+'9510'!G69 -> 0 | H70: =+'1100'!H69+'1500'!H69+'2300'!H69+'4500'!H69+'5600'!H69+'7010'!H72+'7200'!H69+'7300'!H69+'8200'!H69+'9510'!H69 -> 0 | I70: =+'1100'!I69+'1500'!I69+'2300'!I69+'4500'!I69+'5600'!I69+'7010'!I72+'7200'!I69+'7300'!I69+'8200'!I69+'9510'!I69 -> 0 | J70: =+'1100'!J69+'1500'!J69+'2300'!J69+'4500'!J69+'5600'!J69+'7010'!J72+'7200'!J69+'7300'!J69+'8200'!J69+'9510'!J69 -> 0 | K70: =+'1100'!K69+'1500'!K69+'2300'!K69+'4500'!K69+'5600'!K69+'7010'!K72+'7200'!K69+'7300'!K69+'8200'!K69+'9510'!K69 -> 0 | L70: =+'1100'!L69+'1500'!L69+'2300'!L69+'4500'!L69+'5600'!L69+'7010'!L72+'7200'!L69+'7300'!L69+'8200'!L69+'9510'!L69 -> 0 | ... P70: =+'1100'!P69+'1500'!P69+'2300'!P69+'4500'!P69+'5600'!P69+'7010'!P72+'7200'!P69+'7300'!P69+'8200'!P69+'9510'!P69 -> 0 | Q70: =SUM(E70:P70) -> 0
C72: Total Reimbursable Expenses | E72: =+E27+E29+E31+E37+E39+E44+E46+E51+E53+E55+E57+E59+E64+E68+E70 -> 196194.76 | F72: =+F27+F29+F31+F37+F39+F44+F46+F51+F53+F55+F57+F59+F64+F68+F70 -> 192250.79 | G72: =+G27+G29+G31+G37+G39+G44+G46+G51+G53+G55+G57+G59+G64+G68+G70 -> 213866.17 | H72: =+H27+H29+H31+H37+H39+H44+H46+H51+H53+H55+H57+H59+H64+H68+H70 -> 198400.04 | I72: =+I27+I29+I31+I37+I39+I44+I46+I51+I53+I55+I57+I59+I64+I68+I70 -> 188242.49 | J72: =+J27+J29+J31+J37+J39+J44+J46+J51+J53+J55+J57+J59+J64+J68+J70 -> 167593.58 | K72: =+K27+K29+K31+K37+K39+K44+K46+K51+K53+K55+K57+K59+K64+K68+K70 -> 153955.36 | L72: =+L27+L29+L31+L37+L39+L44+L46+L51+L53+L55+L57+L59+L64+L68+L70 -> 172595.26 | ... Q72: =+Q27+Q29+Q31+Q37+Q39+Q44+Q46+Q51+Q53+Q55+Q57+Q59+Q64+Q68+Q70 -> 2239663.7
Q73: =+#REF!+'1100'!Q71+'1500'!Q71+'2300'!Q71+'4500'!Q71+'5600'!Q71+'7010'!Q74+'7200'!Q71 -> #REF!
B74: Non-Reimbursable Expenses
A76: 5210-8501 | C76: Bad Debt | E76: =+'1100'!E75+'1500'!E75+'2300'!E75+'4500'!E75+'5600'!E75+'7010'!E78+'7200'!E75+'7300'!E75+'8200'!E75+'9510'!E75 -> 0 | F76: =+'1100'!F75+'1500'!F75+'2300'!F75+'4500'!F75+'5600'!F75+'7010'!F78+'7200'!F75+'7300'!F75+'8200'!F75+'9510'!F75 -> 0 | G76: =+'1100'!G75+'1500'!G75+'2300'!G75+'4500'!G75+'5600'!G75+'7010'!G78+'7200'!G75+'7300'!G75+'8200'!G75+'9510'!G75 -> 0 | H76: =+'1100'!H75+'1500'!H75+'2300'!H75+'4500'!H75+'5600'!H75+'7010'!H78+'7200'!H75+'7300'!H75+'8200'!H75+'9510'!H75 -> 0 | I76: =+'1100'!I75+'1500'!I75+'2300'!I75+'4500'!I75+'5600'!I75+'7010'!I78+'7200'!I75+'7300'!I75+'8200'!I75+'9510'!I75 -> 0 | J76: =+'1100'!J75+'1500'!J75+'2300'!J75+'4500'!J75+'5600'!J75+'7010'!J78+'7200'!J75+'7300'!J75+'8200'!J75+'9510'!J75 -> 0 | K76: =+'1100'!K75+'1500'!K75+'2300'!K75+'4500'!K75+'5600'!K75+'7010'!K78+'7200'!K75+'7300'!K75+'8200'!K75+'9510'!K75 -> 0 | L76: =+'1100'!L75+'1500'!L75+'2300'!L75+'4500'!L75+'5600'!L75+'7010'!L78+'7200'!L75+'7300'!L75+'8200'!L75+'9510'!L75 -> 0 | ... P76: =+'1100'!P75+'1500'!P75+'2300'!P75+'4500'!P75+'5600'!P75+'7010'!P78+'7200'!P75+'7300'!P75+'8200'!P75+'9510'!P75 -> 0 | Q76: =SUM(E76:P76) -> 0
A78: 6010-8501 | D78: Salaries & Wages | E78: =+'1100'!E77+'1500'!E77+'2300'!E77+'4500'!E77+'5600'!E77+'7010'!E80+'7200'!E77+'7300'!E77+'8200'!E77+'9510'!E77 -> 20584.833 | F78: =+'1100'!F77+'1500'!F77+'2300'!F77+'4500'!F77+'5600'!F77+'7010'!F80+'7200'!F77+'7300'!F77+'8200'!F77+'9510'!F77 -> 20584.833 | G78: =+'1100'!G77+'1500'!G77+'2300'!G77+'4500'!G77+'5600'!G77+'7010'!G80+'7200'!G77+'7300'!G77+'8200'!G77+'9510'!G77 -> 20584.833 | H78: =+'1100'!H77+'1500'!H77+'2300'!H77+'4500'!H77+'5600'!H77+'7010'!H80+'7200'!H77+'7300'!H77+'8200'!H77+'9510'!H77 -> 20584.833 | I78: =+'1100'!I77+'1500'!I77+'2300'!I77+'4500'!I77+'5600'!I77+'7010'!I80+'7200'!I77+'7300'!I77+'8200'!I77+'9510'!I77 -> 20584.833 | J78: =+'1100'!J77+'1500'!J77+'2300'!J77+'4500'!J77+'5600'!J77+'7010'!J80+'7200'!J77+'7300'!J77+'8200'!J77+'9510'!J77 -> 20584.833 | K78: =+'1100'!K77+'1500'!K77+'2300'!K77+'4500'!K77+'5600'!K77+'7010'!K80+'7200'!K77+'7300'!K77+'8200'!K77+'9510'!K77 -> 20584.833 | L78: =+'1100'!L77+'1500'!L77+'2300'!L77+'4500'!L77+'5600'!L77+'7010'!L80+'7200'!L77+'7300'!L77+'8200'!L77+'9510'!L77 -> 20584.833 | ... P78: =+'1100'!P77+'1500'!P77+'2300'!P77+'4500'!P77+'5600'!P77+'7010'!P80+'7200'!P77+'7300'!P77+'8200'!P77+'9510'!P77 -> 20584.833 | Q78: =SUM(E78:P78) -> 247018
A79: 6620-8501 | D79: Commissions-Internal Broker | E79: =+'1100'!E78+'1500'!E78+'2300'!E78+'4500'!E78+'5600'!E78+'7010'!E81+'7200'!E78+'7300'!E78+'8200'!E78+'9510'!E78 -> 0 | F79: =+'1100'!F78+'1500'!F78+'2300'!F78+'4500'!F78+'5600'!F78+'7010'!F81+'7200'!F78+'7300'!F78+'8200'!F78+'9510'!F78 -> 0 | G79: =+'1100'!G78+'1500'!G78+'2300'!G78+'4500'!G78+'5600'!G78+'7010'!G81+'7200'!G78+'7300'!G78+'8200'!G78+'9510'!G78 -> 0 | H79: =+'1100'!H78+'1500'!H78+'2300'!H78+'4500'!H78+'5600'!H78+'7010'!H81+'7200'!H78+'7300'!H78+'8200'!H78+'9510'!H78 -> 0 | I79: =+'1100'!I78+'1500'!I78+'2300'!I78+'4500'!I78+'5600'!I78+'7010'!I81+'7200'!I78+'7300'!I78+'8200'!I78+'9510'!I78 -> 0 | J79: =+'1100'!J78+'1500'!J78+'2300'!J78+'4500'!J78+'5600'!J78+'7010'!J81+'7200'!J78+'7300'!J78+'8200'!J78+'9510'!J78 -> 0 | K79: =+'1100'!K78+'1500'!K78+'2300'!K78+'4500'!K78+'5600'!K78+'7010'!K81+'7200'!K78+'7300'!K78+'8200'!K78+'9510'!K78 -> 0 | L79: =+'1100'!L78+'1500'!L78+'2300'!L78+'4500'!L78+'5600'!L78+'7010'!L81+'7200'!L78+'7300'!L78+'8200'!L78+'9510'!L78 -> 0 | ... P79: =+'1100'!P78+'1500'!P78+'2300'!P78+'4500'!P78+'5600'!P78+'7010'!P81+'7200'!P78+'7300'!P78+'8200'!P78+'9510'!P78 -> 0 | Q79: =SUM(E79:P79) -> 0
C80: Leasing Salaries and Commissions | E80: =SUM(E78:E79) -> 20584.833 | F80: =SUM(F78:F79) -> 20584.833 | G80: =SUM(G78:G79) -> 20584.833 | H80: =SUM(H78:H79) -> 20584.833 | I80: =SUM(I78:I79) -> 20584.833 | J80: =SUM(J78:J79) -> 20584.833 | K80: =SUM(K78:K79) -> 20584.833 | L80: =SUM(L78:L79) -> 20584.833 | ... Q80: =SUM(Q78:Q79) -> 247018
A82: 6110-8501 | D82: Gas | E82: =+'1100'!E81+'1500'!E81+'2300'!E81+'4500'!E81+'5600'!E81+'7010'!E84+'7200'!E81+'7300'!E81+'8200'!E81+'9510'!E81 -> 208.06 | F82: =+'1100'!F81+'1500'!F81+'2300'!F81+'4500'!F81+'5600'!F81+'7010'!F84+'7200'!F81+'7300'!F81+'8200'!F81+'9510'!F81 -> 208.06 | G82: =+'1100'!G81+'1500'!G81+'2300'!G81+'4500'!G81+'5600'!G81+'7010'!G84+'7200'!G81+'7300'!G81+'8200'!G81+'9510'!G81 -> 208.06 | H82: =+'1100'!H81+'1500'!H81+'2300'!H81+'4500'!H81+'5600'!H81+'7010'!H84+'7200'!H81+'7300'!H81+'8200'!H81+'9510'!H81 -> 104.03 | I82: =+'1100'!I81+'1500'!I81+'2300'!I81+'4500'!I81+'5600'!I81+'7010'!I84+'7200'!I81+'7300'!I81+'8200'!I81+'9510'!I81 -> 104.03 | J82: =+'1100'!J81+'1500'!J81+'2300'!J81+'4500'!J81+'5600'!J81+'7010'!J84+'7200'!J81+'7300'!J81+'8200'!J81+'9510'!J81 -> 104.03 | K82: =+'1100'!K81+'1500'!K81+'2300'!K81+'4500'!K81+'5600'!K81+'7010'!K84+'7200'!K81+'7300'!K81+'8200'!K81+'9510'!K81 -> 104.03 | L82: =+'1100'!L81+'1500'!L81+'2300'!L81+'4500'!L81+'5600'!L81+'7010'!L84+'7200'!L81+'7300'!L81+'8200'!L81+'9510'!L81 -> 104.03 | ... P82: =+'1100'!P81+'1500'!P81+'2300'!P81+'4500'!P81+'5600'!P81+'7010'!P84+'7200'!P81+'7300'!P81+'8200'!P81+'9510'!P81 -> 206 | Q82: =SUM(E82:P82) -> 1764.39
A83: 6120-8501 | D83: Electric | E83: =+'1100'!E82+'1500'!E82+'2300'!E82+'4500'!E82+'5600'!E82+'7010'!E85+'7200'!E82+'7300'!E82+'8200'!E82+'9510'!E82 -> 1123.8199 | F83: =+'1100'!F82+'1500'!F82+'2300'!F82+'4500'!F82+'5600'!F82+'7010'!F85+'7200'!F82+'7300'!F82+'8200'!F82+'9510'!F82 -> 1010.6781 | G83: =+'1100'!G82+'1500'!G82+'2300'!G82+'4500'!G82+'5600'!G82+'7010'!G85+'7200'!G82+'7300'!G82+'8200'!G82+'9510'!G82 -> 678.76634 | H83: =+'1100'!H82+'1500'!H82+'2300'!H82+'4500'!H82+'5600'!H82+'7010'!H85+'7200'!H82+'7300'!H82+'8200'!H82+'9510'!H82 -> 706.35306 | I83: =+'1100'!I82+'1500'!I82+'2300'!I82+'4500'!I82+'5600'!I82+'7010'!I85+'7200'!I82+'7300'!I82+'8200'!I82+'9510'!I82 -> 688.78548 | J83: =+'1100'!J82+'1500'!J82+'2300'!J82+'4500'!J82+'5600'!J82+'7010'!J85+'7200'!J82+'7300'!J82+'8200'!J82+'9510'!J82 -> 614.96392 | K83: =+'1100'!K82+'1500'!K82+'2300'!K82+'4500'!K82+'5600'!K82+'7010'!K85+'7200'!K82+'7300'!K82+'8200'!K82+'9510'!K82 -> 811.70203 | L83: =+'1100'!L82+'1500'!L82+'2300'!L82+'4500'!L82+'5600'!L82+'7010'!L85+'7200'!L82+'7300'!L82+'8200'!L82+'9510'!L82 -> 863.9668 | ... P83: =+'1100'!P82+'1500'!P82+'2300'!P82+'4500'!P82+'5600'!P82+'7010'!P85+'7200'!P82+'7300'!P82+'8200'!P82+'9510'!P82 -> 919.96542 | Q83: =SUM(E83:P83) -> 9796.3803
A84: 6130-8501 | D84: Water & Sewer | E84: =+'1100'!E83+'1500'!E83+'2300'!E83+'4500'!E83+'5600'!E83+'7010'!E86+'7200'!E83+'7300'!E83+'8200'!E83+'9510'!E83 -> 367.71 | F84: =+'1100'!F83+'1500'!F83+'2300'!F83+'4500'!F83+'5600'!F83+'7010'!F86+'7200'!F83+'7300'!F83+'8200'!F83+'9510'!F83 -> 341.96 | G84: =+'1100'!G83+'1500'!G83+'2300'!G83+'4500'!G83+'5600'!G83+'7010'!G86+'7200'!G83+'7300'!G83+'8200'!G83+'9510'!G83 -> 344.02 | H84: =+'1100'!H83+'1500'!H83+'2300'!H83+'4500'!H83+'5600'!H83+'7010'!H86+'7200'!H83+'7300'!H83+'8200'!H83+'9510'!H83 -> 347.11 | I84: =+'1100'!I83+'1500'!I83+'2300'!I83+'4500'!I83+'5600'!I83+'7010'!I86+'7200'!I83+'7300'!I83+'8200'!I83+'9510'!I83 -> 776.62 | J84: =+'1100'!J83+'1500'!J83+'2300'!J83+'4500'!J83+'5600'!J83+'7010'!J86+'7200'!J83+'7300'!J83+'8200'!J83+'9510'!J83 -> 333.72 | K84: =+'1100'!K83+'1500'!K83+'2300'!K83+'4500'!K83+'5600'!K83+'7010'!K86+'7200'!K83+'7300'!K83+'8200'!K83+'9510'!K83 -> 439.81 | L84: =+'1100'!L83+'1500'!L83+'2300'!L83+'4500'!L83+'5600'!L83+'7010'!L86+'7200'!L83+'7300'!L83+'8200'!L83+'9510'!L83 -> 585.04 | ... P84: =+'1100'!P83+'1500'!P83+'2300'!P83+'4500'!P83+'5600'!P83+'7010'!P86+'7200'!P83+'7300'!P83+'8200'!P83+'9510'!P83 -> 2230.98 | Q84: =SUM(E84:P84) -> 7811.52
C85: Utilities | E85: =SUM(E82:E84) -> 1699.5899 | F85: =SUM(F82:F84) -> 1560.6981 | G85: =SUM(G82:G84) -> 1230.8463 | H85: =SUM(H82:H84) -> 1157.4931 | I85: =SUM(I82:I84) -> 1569.4355 | J85: =SUM(J82:J84) -> 1052.7139 | K85: =SUM(K82:K84) -> 1355.542 | L85: =SUM(L82:L84) -> 1553.0368 | ... Q85: =SUM(Q82:Q84) -> 19372.29
D87: Building Maint.-Recurring | E87: =+'1100'!E86+'1500'!E86+'2300'!E86+'4500'!E86+'5600'!E86+'7010'!E89+'7200'!E86+'7300'!E86+'8200'!E86+'9510'!E86 -> 2199.5 | F87: =+'1100'!F86+'1500'!F86+'2300'!F86+'4500'!F86+'5600'!F86+'7010'!F89+'7200'!F86+'7300'!F86+'8200'!F86+'9510'!F86 -> 2199.5 | G87: =+'1100'!G86+'1500'!G86+'2300'!G86+'4500'!G86+'5600'!G86+'7010'!G89+'7200'!G86+'7300'!G86+'8200'!G86+'9510'!G86 -> 2199.5 | H87: =+'1100'!H86+'1500'!H86+'2300'!H86+'4500'!H86+'5600'!H86+'7010'!H89+'7200'!H86+'7300'!H86+'8200'!H86+'9510'!H86 -> 2199.5 | I87: =+'1100'!I86+'1500'!I86+'2300'!I86+'4500'!I86+'5600'!I86+'7010'!I89+'7200'!I86+'7300'!I86+'8200'!I86+'9510'!I86 -> 2199.5 | J87: =+'1100'!J86+'1500'!J86+'2300'!J86+'4500'!J86+'5600'!J86+'7010'!J89+'7200'!J86+'7300'!J86+'8200'!J86+'9510'!J86 -> 2199.5 | K87: =+'1100'!K86+'1500'!K86+'2300'!K86+'4500'!K86+'5600'!K86+'7010'!K89+'7200'!K86+'7300'!K86+'8200'!K86+'9510'!K86 -> 2199.5 | L87: =+'1100'!L86+'1500'!L86+'2300'!L86+'4500'!L86+'5600'!L86+'7010'!L89+'7200'!L86+'7300'!L86+'8200'!L86+'9510'!L86 -> 2199.5 | ... P87: =+'1100'!P86+'1500'!P86+'2300'!P86+'4500'!P86+'5600'!P86+'7010'!P89+'7200'!P86+'7300'!P86+'8200'!P86+'9510'!P86 -> 2199.5 | Q87: =SUM(E87:P87) -> 26394
D88: Building Maint.-Big Projects | E88: =+'1100'!E87+'1500'!E87+'2300'!E87+'4500'!E87+'5600'!E87+'7010'!E90+'7200'!E87+'7300'!E87+'8200'!E87+'9510'!E87 -> 0 | F88: =+'1100'!F87+'1500'!F87+'2300'!F87+'4500'!F87+'5600'!F87+'7010'!F90+'7200'!F87+'7300'!F87+'8200'!F87+'9510'!F87 -> 0 | G88: =+'1100'!G87+'1500'!G87+'2300'!G87+'4500'!G87+'5600'!G87+'7010'!G90+'7200'!G87+'7300'!G87+'8200'!G87+'9510'!G87 -> 0 | H88: =+'1100'!H87+'1500'!H87+'2300'!H87+'4500'!H87+'5600'!H87+'7010'!H90+'7200'!H87+'7300'!H87+'8200'!H87+'9510'!H87 -> 0 | I88: =+'1100'!I87+'1500'!I87+'2300'!I87+'4500'!I87+'5600'!I87+'7010'!I90+'7200'!I87+'7300'!I87+'8200'!I87+'9510'!I87 -> 0 | J88: =+'1100'!J87+'1500'!J87+'2300'!J87+'4500'!J87+'5600'!J87+'7010'!J90+'7200'!J87+'7300'!J87+'8200'!J87+'9510'!J87 -> 0 | K88: =+'1100'!K87+'1500'!K87+'2300'!K87+'4500'!K87+'5600'!K87+'7010'!K90+'7200'!K87+'7300'!K87+'8200'!K87+'9510'!K87 -> 0 | L88: =+'1100'!L87+'1500'!L87+'2300'!L87+'4500'!L87+'5600'!L87+'7010'!L90+'7200'!L87+'7300'!L87+'8200'!L87+'9510'!L87 -> 0 | ... P88: =+'1100'!P87+'1500'!P87+'2300'!P87+'4500'!P87+'5600'!P87+'7010'!P90+'7200'!P87+'7300'!P87+'8200'!P87+'9510'!P87 -> 0 | Q88: =SUM(E88:P88) -> 0
A89: 6220-8501 | C89: Building Maintenance | E89: =SUM(E87:E88) -> 2199.5 | F89: =SUM(F87:F88) -> 2199.5 | G89: =SUM(G87:G88) -> 2199.5 | H89: =SUM(H87:H88) -> 2199.5 | I89: =SUM(I87:I88) -> 2199.5 | J89: =SUM(J87:J88) -> 2199.5 | K89: =SUM(K87:K88) -> 2199.5 | L89: =SUM(L87:L88) -> 2199.5 | ... Q89: =SUM(Q87:Q88) -> 26394
A91: 6610-8501 | B91: (SC) | C91: Management fee | E91: ='1100'!E90+'1500'!E90+'2300'!E90+'4500'!E90+'5600'!E90+'7010'!E93+'7200'!E90+'7300'!E90+'8200'!E90+'9510'!E90 -> 35099 | F91: ='1100'!F90+'1500'!F90+'2300'!F90+'4500'!F90+'5600'!F90+'7010'!F93+'7200'!F90+'7300'!F90+'8200'!F90+'9510'!F90 -> 34468 | G91: ='1100'!G90+'1500'!G90+'2300'!G90+'4500'!G90+'5600'!G90+'7010'!G93+'7200'!G90+'7300'!G90+'8200'!G90+'9510'!G90 -> 34297 | H91: ='1100'!H90+'1500'!H90+'2300'!H90+'4500'!H90+'5600'!H90+'7010'!H93+'7200'!H90+'7300'!H90+'8200'!H90+'9510'!H90 -> 34690 | I91: ='1100'!I90+'1500'!I90+'2300'!I90+'4500'!I90+'5600'!I90+'7010'!I93+'7200'!I90+'7300'!I90+'8200'!I90+'9510'!I90 -> 34768 | J91: ='1100'!J90+'1500'!J90+'2300'!J90+'4500'!J90+'5600'!J90+'7010'!J93+'7200'!J90+'7300'!J90+'8200'!J90+'9510'!J90 -> 34963 | K91: ='1100'!K90+'1500'!K90+'2300'!K90+'4500'!K90+'5600'!K90+'7010'!K93+'7200'!K90+'7300'!K90+'8200'!K90+'9510'!K90 -> 35492 | L91: ='1100'!L90+'1500'!L90+'2300'!L90+'4500'!L90+'5600'!L90+'7010'!L93+'7200'!L90+'7300'!L90+'8200'!L90+'9510'!L90 -> 35309 | ... P91: ='1100'!P90+'1500'!P90+'2300'!P90+'4500'!P90+'5600'!P90+'7010'!P93+'7200'!P90+'7300'!P90+'8200'!P90+'9510'!P90 -> 38419 | Q91: =SUM(E91:P91) -> 424589
A93: 7110-8501 | C93: Marketing | E93: =+'1100'!E92+'1500'!E92+'2300'!E92+'4500'!E92+'5600'!E92+'7010'!E95+'7200'!E92+'7300'!E92+'8200'!E92+'9510'!E92 -> 6697.025 | F93: =+'1100'!F92+'1500'!F92+'2300'!F92+'4500'!F92+'5600'!F92+'7010'!F95+'7200'!F92+'7300'!F92+'8200'!F92+'9510'!F92 -> 6697.025 | G93: =+'1100'!G92+'1500'!G92+'2300'!G92+'4500'!G92+'5600'!G92+'7010'!G95+'7200'!G92+'7300'!G92+'8200'!G92+'9510'!G92 -> 6697.025 | H93: =+'1100'!H92+'1500'!H92+'2300'!H92+'4500'!H92+'5600'!H92+'7010'!H95+'7200'!H92+'7300'!H92+'8200'!H92+'9510'!H92 -> 6697.025 | I93: =+'1100'!I92+'1500'!I92+'2300'!I92+'4500'!I92+'5600'!I92+'7010'!I95+'7200'!I92+'7300'!I92+'8200'!I92+'9510'!I92 -> 6697.025 | J93: =+'1100'!J92+'1500'!J92+'2300'!J92+'4500'!J92+'5600'!J92+'7010'!J95+'7200'!J92+'7300'!J92+'8200'!J92+'9510'!J92 -> 6697.025 | K93: =+'1100'!K92+'1500'!K92+'2300'!K92+'4500'!K92+'5600'!K92+'7010'!K95+'7200'!K92+'7300'!K92+'8200'!K92+'9510'!K92 -> 6697.025 | L93: =+'1100'!L92+'1500'!L92+'2300'!L92+'4500'!L92+'5600'!L92+'7010'!L95+'7200'!L92+'7300'!L92+'8200'!L92+'9510'!L92 -> 6697.025 | ... P93: =+'1100'!P92+'1500'!P92+'2300'!P92+'4500'!P92+'5600'!P92+'7010'!P95+'7200'!P92+'7300'!P92+'8200'!P92+'9510'!P92 -> 6697.025 | Q93: =SUM(E93:P93) -> 80364.3
A95: 8210-8501 | C95: Business Taxes | E95: =+'1100'!E94+'1500'!E94+'2300'!E94+'4500'!E94+'5600'!E94+'7010'!E97+'7200'!E94+'7300'!E94+'8200'!E94+'9510'!E94 -> 0 | F95: =+'1100'!F94+'1500'!F94+'2300'!F94+'4500'!F94+'5600'!F94+'7010'!F97+'7200'!F94+'7300'!F94+'8200'!F94+'9510'!F94 -> 0 | G95: =+'1100'!G94+'1500'!G94+'2300'!G94+'4500'!G94+'5600'!G94+'7010'!G97+'7200'!G94+'7300'!G94+'8200'!G94+'9510'!G94 -> 0 | H95: =+'1100'!H94+'1500'!H94+'2300'!H94+'4500'!H94+'5600'!H94+'7010'!H97+'7200'!H94+'7300'!H94+'8200'!H94+'9510'!H94 -> 142717 | I95: =+'1100'!I94+'1500'!I94+'2300'!I94+'4500'!I94+'5600'!I94+'7010'!I97+'7200'!I94+'7300'!I94+'8200'!I94+'9510'!I94 -> 0 | J95: =+'1100'!J94+'1500'!J94+'2300'!J94+'4500'!J94+'5600'!J94+'7010'!J97+'7200'!J94+'7300'!J94+'8200'!J94+'9510'!J94 -> 0 | K95: =+'1100'!K94+'1500'!K94+'2300'!K94+'4500'!K94+'5600'!K94+'7010'!K97+'7200'!K94+'7300'!K94+'8200'!K94+'9510'!K94 -> 0 | L95: =+'1100'!L94+'1500'!L94+'2300'!L94+'4500'!L94+'5600'!L94+'7010'!L97+'7200'!L94+'7300'!L94+'8200'!L94+'9510'!L94 -> 0 | ... P95: =+'1100'!P94+'1500'!P94+'2300'!P94+'4500'!P94+'5600'!P94+'7010'!P97+'7200'!P94+'7300'!P94+'8200'!P94+'9510'!P94 -> 0 | Q95: =SUM(E95:P95) -> 142717
A97: 8310-8501 | C97: Legal & Accounting | E97: =+'1100'!E96+'1500'!E96+'2300'!E96+'4500'!E96+'5600'!E96+'7010'!E99+'7200'!E96+'7300'!E96+'8200'!E96+'9510'!E96 -> 4240.7675 | F97: =+'1100'!F96+'1500'!F96+'2300'!F96+'4500'!F96+'5600'!F96+'7010'!F99+'7200'!F96+'7300'!F96+'8200'!F96+'9510'!F96 -> 4240.7675 | G97: =+'1100'!G96+'1500'!G96+'2300'!G96+'4500'!G96+'5600'!G96+'7010'!G99+'7200'!G96+'7300'!G96+'8200'!G96+'9510'!G96 -> 4240.7675 | H97: =+'1100'!H96+'1500'!H96+'2300'!H96+'4500'!H96+'5600'!H96+'7010'!H99+'7200'!H96+'7300'!H96+'8200'!H96+'9510'!H96 -> 4240.7675 | I97: =+'1100'!I96+'1500'!I96+'2300'!I96+'4500'!I96+'5600'!I96+'7010'!I99+'7200'!I96+'7300'!I96+'8200'!I96+'9510'!I96 -> 4240.7675 | J97: =+'1100'!J96+'1500'!J96+'2300'!J96+'4500'!J96+'5600'!J96+'7010'!J99+'7200'!J96+'7300'!J96+'8200'!J96+'9510'!J96 -> 4240.7675 | K97: =+'1100'!K96+'1500'!K96+'2300'!K96+'4500'!K96+'5600'!K96+'7010'!K99+'7200'!K96+'7300'!K96+'8200'!K96+'9510'!K96 -> 4240.7675 | L97: =+'1100'!L96+'1500'!L96+'2300'!L96+'4500'!L96+'5600'!L96+'7010'!L99+'7200'!L96+'7300'!L96+'8200'!L96+'9510'!L96 -> 4240.7675 | ... P97: =+'1100'!P96+'1500'!P96+'2300'!P96+'4500'!P96+'5600'!P96+'7010'!P99+'7200'!P96+'7300'!P96+'8200'!P96+'9510'!P96 -> 4240.7675 | Q97: =SUM(E97:P97) -> 50889.21
A99: 8190-8501 | D99: Bank Fees | E99: ='1100'!E98+'1500'!E98+'2300'!E98+'4500'!E98+'5600'!E98+'7010'!E101+'7200'!E98+'7300'!E98+'8200'!E98+'9510'!E98 -> 370.8 | F99: ='1100'!F98+'1500'!F98+'2300'!F98+'4500'!F98+'5600'!F98+'7010'!F101+'7200'!F98+'7300'!F98+'8200'!F98+'9510'!F98 -> 370.8 | G99: ='1100'!G98+'1500'!G98+'2300'!G98+'4500'!G98+'5600'!G98+'7010'!G101+'7200'!G98+'7300'!G98+'8200'!G98+'9510'!G98 -> 370.8 | H99: ='1100'!H98+'1500'!H98+'2300'!H98+'4500'!H98+'5600'!H98+'7010'!H101+'7200'!H98+'7300'!H98+'8200'!H98+'9510'!H98 -> 370.8 | I99: ='1100'!I98+'1500'!I98+'2300'!I98+'4500'!I98+'5600'!I98+'7010'!I101+'7200'!I98+'7300'!I98+'8200'!I98+'9510'!I98 -> 370.8 | J99: ='1100'!J98+'1500'!J98+'2300'!J98+'4500'!J98+'5600'!J98+'7010'!J101+'7200'!J98+'7300'!J98+'8200'!J98+'9510'!J98 -> 370.8 | K99: ='1100'!K98+'1500'!K98+'2300'!K98+'4500'!K98+'5600'!K98+'7010'!K101+'7200'!K98+'7300'!K98+'8200'!K98+'9510'!K98 -> 370.8 | L99: ='1100'!L98+'1500'!L98+'2300'!L98+'4500'!L98+'5600'!L98+'7010'!L101+'7200'!L98+'7300'!L98+'8200'!L98+'9510'!L98 -> 370.8 | ... P99: ='1100'!P98+'1500'!P98+'2300'!P98+'4500'!P98+'5600'!P98+'7010'!P101+'7200'!P98+'7300'!P98+'8200'!P98+'9510'!P98 -> 370.8 | Q99: =SUM(E99:P99) -> 4449.6
A100: 8930-8501 | D100: Office Supplies | E100: ='1100'!E99+'1500'!E99+'2300'!E99+'4500'!E99+'5600'!E99+'7010'!E102+'7200'!E99+'7300'!E99+'8200'!E99+'9510'!E99 -> 0 | F100: ='1100'!F99+'1500'!F99+'2300'!F99+'4500'!F99+'5600'!F99+'7010'!F102+'7200'!F99+'7300'!F99+'8200'!F99+'9510'!F99 -> 0 | G100: ='1100'!G99+'1500'!G99+'2300'!G99+'4500'!G99+'5600'!G99+'7010'!G102+'7200'!G99+'7300'!G99+'8200'!G99+'9510'!G99 -> 0 | H100: ='1100'!H99+'1500'!H99+'2300'!H99+'4500'!H99+'5600'!H99+'7010'!H102+'7200'!H99+'7300'!H99+'8200'!H99+'9510'!H99 -> 0 | I100: ='1100'!I99+'1500'!I99+'2300'!I99+'4500'!I99+'5600'!I99+'7010'!I102+'7200'!I99+'7300'!I99+'8200'!I99+'9510'!I99 -> 0 | J100: ='1100'!J99+'1500'!J99+'2300'!J99+'4500'!J99+'5600'!J99+'7010'!J102+'7200'!J99+'7300'!J99+'8200'!J99+'9510'!J99 -> 0 | K100: ='1100'!K99+'1500'!K99+'2300'!K99+'4500'!K99+'5600'!K99+'7010'!K102+'7200'!K99+'7300'!K99+'8200'!K99+'9510'!K99 -> 0 | L100: ='1100'!L99+'1500'!L99+'2300'!L99+'4500'!L99+'5600'!L99+'7010'!L102+'7200'!L99+'7300'!L99+'8200'!L99+'9510'!L99 -> 0 | ... P100: ='1100'!P99+'1500'!P99+'2300'!P99+'4500'!P99+'5600'!P99+'7010'!P102+'7200'!P99+'7300'!P99+'8200'!P99+'9510'!P99 -> 0 | Q100: =SUM(E100:P100) -> 0
A101: 8950-8501 | D101: Postage | E101: ='1100'!E100+'1500'!E100+'2300'!E100+'4500'!E100+'5600'!E100+'7010'!E103+'7200'!E100+'7300'!E100+'8200'!E100+'9510'!E100 -> 0 | F101: ='1100'!F100+'1500'!F100+'2300'!F100+'4500'!F100+'5600'!F100+'7010'!F103+'7200'!F100+'7300'!F100+'8200'!F100+'9510'!F100 -> 0 | G101: ='1100'!G100+'1500'!G100+'2300'!G100+'4500'!G100+'5600'!G100+'7010'!G103+'7200'!G100+'7300'!G100+'8200'!G100+'9510'!G100 -> 0 | H101: ='1100'!H100+'1500'!H100+'2300'!H100+'4500'!H100+'5600'!H100+'7010'!H103+'7200'!H100+'7300'!H100+'8200'!H100+'9510'!H100 -> 0 | I101: ='1100'!I100+'1500'!I100+'2300'!I100+'4500'!I100+'5600'!I100+'7010'!I103+'7200'!I100+'7300'!I100+'8200'!I100+'9510'!I100 -> 0 | J101: ='1100'!J100+'1500'!J100+'2300'!J100+'4500'!J100+'5600'!J100+'7010'!J103+'7200'!J100+'7300'!J100+'8200'!J100+'9510'!J100 -> 0 | K101: ='1100'!K100+'1500'!K100+'2300'!K100+'4500'!K100+'5600'!K100+'7010'!K103+'7200'!K100+'7300'!K100+'8200'!K100+'9510'!K100 -> 0 | L101: ='1100'!L100+'1500'!L100+'2300'!L100+'4500'!L100+'5600'!L100+'7010'!L103+'7200'!L100+'7300'!L100+'8200'!L100+'9510'!L100 -> 0 | ... P101: ='1100'!P100+'1500'!P100+'2300'!P100+'4500'!P100+'5600'!P100+'7010'!P103+'7200'!P100+'7300'!P100+'8200'!P100+'9510'!P100 -> 0 | Q101: =SUM(E101:P101) -> 0
A102: 8990-8501 | D102: Other G&A Expense | E102: ='1100'!E101+'1500'!E101+'2300'!E101+'4500'!E101+'5600'!E101+'7010'!E104+'7200'!E101+'7300'!E101+'8200'!E101+'9510'!E101 -> 0 | F102: ='1100'!F101+'1500'!F101+'2300'!F101+'4500'!F101+'5600'!F101+'7010'!F104+'7200'!F101+'7300'!F101+'8200'!F101+'9510'!F101 -> 0 | G102: ='1100'!G101+'1500'!G101+'2300'!G101+'4500'!G101+'5600'!G101+'7010'!G104+'7200'!G101+'7300'!G101+'8200'!G101+'9510'!G101 -> 0 | H102: ='1100'!H101+'1500'!H101+'2300'!H101+'4500'!H101+'5600'!H101+'7010'!H104+'7200'!H101+'7300'!H101+'8200'!H101+'9510'!H101 -> 0 | I102: ='1100'!I101+'1500'!I101+'2300'!I101+'4500'!I101+'5600'!I101+'7010'!I104+'7200'!I101+'7300'!I101+'8200'!I101+'9510'!I101 -> 0 | J102: ='1100'!J101+'1500'!J101+'2300'!J101+'4500'!J101+'5600'!J101+'7010'!J104+'7200'!J101+'7300'!J101+'8200'!J101+'9510'!J101 -> 0 | K102: ='1100'!K101+'1500'!K101+'2300'!K101+'4500'!K101+'5600'!K101+'7010'!K104+'7200'!K101+'7300'!K101+'8200'!K101+'9510'!K101 -> 0 | L102: ='1100'!L101+'1500'!L101+'2300'!L101+'4500'!L101+'5600'!L101+'7010'!L104+'7200'!L101+'7300'!L101+'8200'!L101+'9510'!L101 -> 0 | ... P102: ='1100'!P101+'1500'!P101+'2300'!P101+'4500'!P101+'5600'!P101+'7010'!P104+'7200'!P101+'7300'!P101+'8200'!P101+'9510'!P101 -> 0 | Q102: =SUM(E102:P102) -> 0
A103: 8990-9800 | D103: Other G&A-allocated from LIK | E103: ='1100'!E102+'1500'!E102+'2300'!E102+'4500'!E102+'5600'!E102+'7010'!E105+'7200'!E102+'7300'!E102+'8200'!E102+'9510'!E102 -> 790.525 | F103: ='1100'!F102+'1500'!F102+'2300'!F102+'4500'!F102+'5600'!F102+'7010'!F105+'7200'!F102+'7300'!F102+'8200'!F102+'9510'!F102 -> 790.525 | G103: ='1100'!G102+'1500'!G102+'2300'!G102+'4500'!G102+'5600'!G102+'7010'!G105+'7200'!G102+'7300'!G102+'8200'!G102+'9510'!G102 -> 790.525 | H103: ='1100'!H102+'1500'!H102+'2300'!H102+'4500'!H102+'5600'!H102+'7010'!H105+'7200'!H102+'7300'!H102+'8200'!H102+'9510'!H102 -> 790.525 | I103: ='1100'!I102+'1500'!I102+'2300'!I102+'4500'!I102+'5600'!I102+'7010'!I105+'7200'!I102+'7300'!I102+'8200'!I102+'9510'!I102 -> 790.525 | J103: ='1100'!J102+'1500'!J102+'2300'!J102+'4500'!J102+'5600'!J102+'7010'!J105+'7200'!J102+'7300'!J102+'8200'!J102+'9510'!J102 -> 790.525 | K103: ='1100'!K102+'1500'!K102+'2300'!K102+'4500'!K102+'5600'!K102+'7010'!K105+'7200'!K102+'7300'!K102+'8200'!K102+'9510'!K102 -> 790.525 | L103: ='1100'!L102+'1500'!L102+'2300'!L102+'4500'!L102+'5600'!L102+'7010'!L105+'7200'!L102+'7300'!L102+'8200'!L102+'9510'!L102 -> 790.525 | ... P103: ='1100'!P102+'1500'!P102+'2300'!P102+'4500'!P102+'5600'!P102+'7010'!P105+'7200'!P102+'7300'!P102+'8200'!P102+'9510'!P102 -> 790.525 | Q103: =SUM(E103:P103) -> 9486.3
C104: General & Administrative | E104: =SUM(E99:E103) -> 1161.325 | F104: =SUM(F99:F103) -> 1161.325 | G104: =SUM(G99:G103) -> 1161.325 | H104: =SUM(H99:H103) -> 1161.325 | I104: =SUM(I99:I103) -> 1161.325 | J104: =SUM(J99:J103) -> 1161.325 | K104: =SUM(K99:K103) -> 1161.325 | L104: =SUM(L99:L103) -> 1161.325 | ... Q104: =SUM(Q99:Q103) -> 13935.9
C106: Total Non-Reimbursable Expenses | E106: =+E76+E80+E85+E89+E91+E93+E95+E97+E104 -> 71682.041 | F106: =+F76+F80+F85+F89+F91+F93+F95+F97+F104 -> 70912.149 | G106: =+G76+G80+G85+G89+G91+G93+G95+G97+G104 -> 70411.297 | H106: =+H76+H80+H85+H89+H91+H93+H95+H97+H104 -> 213447.94 | I106: =+I76+I80+I85+I89+I91+I93+I95+I97+I104 -> 71220.886 | J106: =+J76+J80+J85+J89+J91+J93+J95+J97+J104 -> 70899.165 | K106: =+K76+K80+K85+K89+K91+K93+K95+K97+K104 -> 71730.993 | L106: =+L76+L80+L85+L89+L91+L93+L95+L97+L104 -> 71745.488 | ... Q106: =+Q76+Q80+Q85+Q89+Q91+Q93+Q95+Q97+Q104 -> 1005279.7
Q107: =+'1100'!Q105+'1500'!Q105+'2300'!Q105+'4500'!Q105+'5600'!Q105+'7010'!Q108+'7200'!Q105 -> 831317.86
Q108: =+Q106-Q107 -> 173961.84
B109: TOTAL OPERATING EXPENSES | E109: =+E72+E106 -> 267876.8 | F109: =+F72+F106 -> 263162.94 | G109: =+G72+G106 -> 284277.47 | H109: =+H72+H106 -> 411847.98 | I109: =+I72+I106 -> 259463.37 | J109: =+J72+J106 -> 238492.74 | K109: =+K72+K106 -> 225686.35 | L109: =+L72+L106 -> 244340.75 | ... Q109: =+Q72+Q106 -> 3244943.4
Q110: =+'1100'!Q108+'1500'!Q108+'2300'!Q108+'4500'!Q108+'5600'!Q108+'7010'!Q111+'7200'!Q108 -> 2743582.6
B112: NET OPERATING INCOME | E112: =+E24-E109 -> 317106.29 | F112: =+F24-F109 -> 311309.81 | G112: =+G24-G109 -> 287351.43 | H112: =+H24-H109 -> 166321.22 | I112: =+I24-I109 -> 320004.41 | J112: =+J24-J109 -> 344235.92 | K112: =+K24-K109 -> 365846.52 | L112: =+L24-L109 -> 344154.83 | ... Q112: =+Q24-Q109 -> 3831581.5
A114: 1420-0000 | D114: Land Improvements | E114: =+'1100'!E113+'1500'!E113+'2300'!E113+'4500'!E113+'5600'!E113+'7010'!E116+'7200'!E113+'7300'!E113+'8200'!E113+'9510'!E113 -> 0 | F114: =+'1100'!F113+'1500'!F113+'2300'!F113+'4500'!F113+'5600'!F113+'7010'!F116+'7200'!F113+'7300'!F113+'8200'!F113+'9510'!F113 -> 0 | G114: =+'1100'!G113+'1500'!G113+'2300'!G113+'4500'!G113+'5600'!G113+'7010'!G116+'7200'!G113+'7300'!G113+'8200'!G113+'9510'!G113 -> 0 | H114: =+'1100'!H113+'1500'!H113+'2300'!H113+'4500'!H113+'5600'!H113+'7010'!H116+'7200'!H113+'7300'!H113+'8200'!H113+'9510'!H113 -> 0 | I114: =+'1100'!I113+'1500'!I113+'2300'!I113+'4500'!I113+'5600'!I113+'7010'!I116+'7200'!I113+'7300'!I113+'8200'!I113+'9510'!I113 -> 0 | J114: =+'1100'!J113+'1500'!J113+'2300'!J113+'4500'!J113+'5600'!J113+'7010'!J116+'7200'!J113+'7300'!J113+'8200'!J113+'9510'!J113 -> 0 | K114: =+'1100'!K113+'1500'!K113+'2300'!K113+'4500'!K113+'5600'!K113+'7010'!K116+'7200'!K113+'7300'!K113+'8200'!K113+'9510'!K113 -> 0 | L114: =+'1100'!L113+'1500'!L113+'2300'!L113+'4500'!L113+'5600'!L113+'7010'!L116+'7200'!L113+'7300'!L113+'8200'!L113+'9510'!L113 -> 0 | ... P114: =+'1100'!P113+'1500'!P113+'2300'!P113+'4500'!P113+'5600'!P113+'7010'!P116+'7200'!P113+'7300'!P113+'8200'!P113+'9510'!P113 -> 0 | Q114: =SUM(E114:P114) -> 0
A115: 1430-0000 | D115: Buildings | E115: =+'1100'!E114+'1500'!E114+'2300'!E114+'4500'!E114+'5600'!E114+'7010'!E117+'7200'!E114+'7300'!E114+'8200'!E114+'9510'!E114 -> 167200 | F115: =+'1100'!F114+'1500'!F114+'2300'!F114+'4500'!F114+'5600'!F114+'7010'!F117+'7200'!F114+'7300'!F114+'8200'!F114+'9510'!F114 -> 25000 | G115: =+'1100'!G114+'1500'!G114+'2300'!G114+'4500'!G114+'5600'!G114+'7010'!G117+'7200'!G114+'7300'!G114+'8200'!G114+'9510'!G114 -> 38500 | H115: =+'1100'!H114+'1500'!H114+'2300'!H114+'4500'!H114+'5600'!H114+'7010'!H117+'7200'!H114+'7300'!H114+'8200'!H114+'9510'!H114 -> 306219 | I115: =+'1100'!I114+'1500'!I114+'2300'!I114+'4500'!I114+'5600'!I114+'7010'!I117+'7200'!I114+'7300'!I114+'8200'!I114+'9510'!I114 -> 0 | J115: =+'1100'!J114+'1500'!J114+'2300'!J114+'4500'!J114+'5600'!J114+'7010'!J117+'7200'!J114+'7300'!J114+'8200'!J114+'9510'!J114 -> 0 | K115: =+'1100'!K114+'1500'!K114+'2300'!K114+'4500'!K114+'5600'!K114+'7010'!K117+'7200'!K114+'7300'!K114+'8200'!K114+'9510'!K114 -> 257500 | L115: =+'1100'!L114+'1500'!L114+'2300'!L114+'4500'!L114+'5600'!L114+'7010'!L117+'7200'!L114+'7300'!L114+'8200'!L114+'9510'!L114 -> 0 | ... P115: =+'1100'!P114+'1500'!P114+'2300'!P114+'4500'!P114+'5600'!P114+'7010'!P117+'7200'!P114+'7300'!P114+'8200'!P114+'9510'!P114 -> 0 | Q115: =SUM(E115:P115) -> 794419
A116: 1450-0000 | D116: Equipment | E116: =+'1100'!E115+'1500'!E115+'2300'!E115+'4500'!E115+'5600'!E115+'7010'!E118+'7200'!E115+'7300'!E115+'8200'!E115+'9510'!E115 -> 0 | F116: =+'1100'!F115+'1500'!F115+'2300'!F115+'4500'!F115+'5600'!F115+'7010'!F118+'7200'!F115+'7300'!F115+'8200'!F115+'9510'!F115 -> 0 | G116: =+'1100'!G115+'1500'!G115+'2300'!G115+'4500'!G115+'5600'!G115+'7010'!G118+'7200'!G115+'7300'!G115+'8200'!G115+'9510'!G115 -> 128000 | H116: =+'1100'!H115+'1500'!H115+'2300'!H115+'4500'!H115+'5600'!H115+'7010'!H118+'7200'!H115+'7300'!H115+'8200'!H115+'9510'!H115 -> 0 | I116: =+'1100'!I115+'1500'!I115+'2300'!I115+'4500'!I115+'5600'!I115+'7010'!I118+'7200'!I115+'7300'!I115+'8200'!I115+'9510'!I115 -> 0 | J116: =+'1100'!J115+'1500'!J115+'2300'!J115+'4500'!J115+'5600'!J115+'7010'!J118+'7200'!J115+'7300'!J115+'8200'!J115+'9510'!J115 -> 0 | K116: =+'1100'!K115+'1500'!K115+'2300'!K115+'4500'!K115+'5600'!K115+'7010'!K118+'7200'!K115+'7300'!K115+'8200'!K115+'9510'!K115 -> 0 | L116: =+'1100'!L115+'1500'!L115+'2300'!L115+'4500'!L115+'5600'!L115+'7010'!L118+'7200'!L115+'7300'!L115+'8200'!L115+'9510'!L115 -> 0 | ... P116: =+'1100'!P115+'1500'!P115+'2300'!P115+'4500'!P115+'5600'!P115+'7010'!P118+'7200'!P115+'7300'!P115+'8200'!P115+'9510'!P115 -> 0 | Q116: =SUM(E116:P116) -> 128000
A117: 1980-8501 | D117: Capital Improvements | E117: =+'1100'!E116+'1500'!E116+'2300'!E116+'4500'!E116+'5600'!E116+'7010'!E119+'7200'!E116+'7300'!E116+'8200'!E116+'9510'!E116 -> 0 | F117: =+'1100'!F116+'1500'!F116+'2300'!F116+'4500'!F116+'5600'!F116+'7010'!F119+'7200'!F116+'7300'!F116+'8200'!F116+'9510'!F116 -> 0 | G117: =+'1100'!G116+'1500'!G116+'2300'!G116+'4500'!G116+'5600'!G116+'7010'!G119+'7200'!G116+'7300'!G116+'8200'!G116+'9510'!G116 -> 0 | H117: =+'1100'!H116+'1500'!H116+'2300'!H116+'4500'!H116+'5600'!H116+'7010'!H119+'7200'!H116+'7300'!H116+'8200'!H116+'9510'!H116 -> 0 | I117: =+'1100'!I116+'1500'!I116+'2300'!I116+'4500'!I116+'5600'!I116+'7010'!I119+'7200'!I116+'7300'!I116+'8200'!I116+'9510'!I116 -> 0 | J117: =+'1100'!J116+'1500'!J116+'2300'!J116+'4500'!J116+'5600'!J116+'7010'!J119+'7200'!J116+'7300'!J116+'8200'!J116+'9510'!J116 -> 0 | K117: =+'1100'!K116+'1500'!K116+'2300'!K116+'4500'!K116+'5600'!K116+'7010'!K119+'7200'!K116+'7300'!K116+'8200'!K116+'9510'!K116 -> 0 | L117: =+'1100'!L116+'1500'!L116+'2300'!L116+'4500'!L116+'5600'!L116+'7010'!L119+'7200'!L116+'7300'!L116+'8200'!L116+'9510'!L116 -> 0 | ... P117: =+'1100'!P116+'1500'!P116+'2300'!P116+'4500'!P116+'5600'!P116+'7010'!P119+'7200'!P116+'7300'!P116+'8200'!P116+'9510'!P116 -> 0 | Q117: =SUM(E117:P117) -> 0
C118: Capital Improvements | E118: =SUM(E114:E117) -> 167200 | F118: =SUM(F114:F117) -> 25000 | G118: =SUM(G114:G117) -> 166500 | H118: =SUM(H114:H117) -> 306219 | I118: =SUM(I114:I117) -> 0 | J118: =SUM(J114:J117) -> 0 | K118: =SUM(K114:K117) -> 257500 | L118: =SUM(L114:L117) -> 0 | ... Q118: =SUM(Q114:Q117) -> 922419
A120: 1440-0000 | C120: Tenant Improvements | E120: =+'1100'!E119+'1500'!E119+'2300'!E119+'4500'!E119+'5600'!E119+'7010'!E122+'7200'!E119+'7300'!E119+'8200'!E119+'9510'!E119 -> 0 | F120: =+'1100'!F119+'1500'!F119+'2300'!F119+'4500'!F119+'5600'!F119+'7010'!F122+'7200'!F119+'7300'!F119+'8200'!F119+'9510'!F119 -> 0 | G120: =+'1100'!G119+'1500'!G119+'2300'!G119+'4500'!G119+'5600'!G119+'7010'!G122+'7200'!G119+'7300'!G119+'8200'!G119+'9510'!G119 -> 0 | H120: =+'1100'!H119+'1500'!H119+'2300'!H119+'4500'!H119+'5600'!H119+'7010'!H122+'7200'!H119+'7300'!H119+'8200'!H119+'9510'!H119 -> 0 | I120: =+'1100'!I119+'1500'!I119+'2300'!I119+'4500'!I119+'5600'!I119+'7010'!I122+'7200'!I119+'7300'!I119+'8200'!I119+'9510'!I119 -> 0 | J120: =+'1100'!J119+'1500'!J119+'2300'!J119+'4500'!J119+'5600'!J119+'7010'!J122+'7200'!J119+'7300'!J119+'8200'!J119+'9510'!J119 -> 15000 | K120: =+'1100'!K119+'1500'!K119+'2300'!K119+'4500'!K119+'5600'!K119+'7010'!K122+'7200'!K119+'7300'!K119+'8200'!K119+'9510'!K119 -> 0 | L120: =+'1100'!L119+'1500'!L119+'2300'!L119+'4500'!L119+'5600'!L119+'7010'!L122+'7200'!L119+'7300'!L119+'8200'!L119+'9510'!L119 -> 16560 | ... P120: =+'1100'!P119+'1500'!P119+'2300'!P119+'4500'!P119+'5600'!P119+'7010'!P122+'7200'!P119+'7300'!P119+'8200'!P119+'9510'!P119 -> 0 | Q120: =SUM(E120:P120) -> 31560
A122: 1940-8501 | D122: Deferred Marketing | E122: ='7300'!E121+'8200'!E121+'9510'!E121 -> 0 | F122: ='7300'!F121+'8200'!F121+'9510'!F121 -> 0 | G122: ='7300'!G121+'8200'!G121+'9510'!G121 -> 0 | H122: ='7300'!H121+'8200'!H121+'9510'!H121 -> 0 | I122: ='7300'!I121+'8200'!I121+'9510'!I121 -> 0 | J122: ='7300'!J121+'8200'!J121+'9510'!J121 -> 0 | K122: ='7300'!K121+'8200'!K121+'9510'!K121 -> 0 | L122: ='7300'!L121+'8200'!L121+'9510'!L121 -> 0 | ... P122: ='7300'!P121+'8200'!P121+'9510'!P121 -> 0 | Q122: =SUM(E122:P122) -> 0
A123: 1940-8501 | D123: Outside Leasing Commissions | E123: ='7300'!E122+'8200'!E122+'9510'!E122 -> 0 | F123: ='7300'!F122+'8200'!F122+'9510'!F122 -> 0 | G123: ='7300'!G122+'8200'!G122+'9510'!G122 -> 0 | H123: ='7300'!H122+'8200'!H122+'9510'!H122 -> 0 | I123: ='7300'!I122+'8200'!I122+'9510'!I122 -> 0 | J123: ='7300'!J122+'8200'!J122+'9510'!J122 -> 0 | K123: ='7300'!K122+'8200'!K122+'9510'!K122 -> 0 | L123: ='7300'!L122+'8200'!L122+'9510'!L122 -> 0 | ... P123: ='7300'!P122+'8200'!P122+'9510'!P122 -> 0 | Q123: =SUM(E123:P123) -> 0
C124: Outside Leasing Commissions | E124: =+'1100'!E123+'1500'!E123+'2300'!E123+'4500'!E122+'5600'!E123+'7010'!E126+'7200'!E123 -> 0 | F124: =+'1100'!F123+'1500'!F123+'2300'!F123+'4500'!F122+'5600'!F123+'7010'!F126+'7200'!F123 -> 0 | G124: =+'1100'!G123+'1500'!G123+'2300'!G123+'4500'!G122+'5600'!G123+'7010'!G126+'7200'!G123 -> 0 | H124: =+'1100'!H123+'1500'!H123+'2300'!H123+'4500'!H122+'5600'!H123+'7010'!H126+'7200'!H123 -> 0 | I124: =+'1100'!I123+'1500'!I123+'2300'!I123+'4500'!I122+'5600'!I123+'7010'!I126+'7200'!I123 -> 0 | J124: =+'1100'!J123+'1500'!J123+'2300'!J123+'4500'!J122+'5600'!J123+'7010'!J126+'7200'!J123 -> 0 | K124: =+'1100'!K123+'1500'!K123+'2300'!K123+'4500'!K122+'5600'!K123+'7010'!K126+'7200'!K123 -> 0 | L124: =+'1100'!L123+'1500'!L123+'2300'!L123+'4500'!L122+'5600'!L123+'7010'!L126+'7200'!L123 -> 0 | ... P124: =+'1100'!P123+'1500'!P123+'2300'!P123+'4500'!P122+'5600'!P123+'7010'!P126+'7200'!P123 -> 0 | Q124: =SUM(Q122:Q123) -> 0
B126: CASH FLOW BEFORE DEBT SERVICE | E126: =+E112-E118 -> 149906.29 | F126: =+F112-F118 -> 286309.81 | G126: =+G112-G118 -> 120851.43 | H126: =+H112-H118 -> -139897.78 | I126: =+I112-I118 -> 320004.41 | J126: =+J112-J118 -> 344235.92 | K126: =+K112-K118 -> 108346.52 | L126: =+L112-L118 -> 344154.83 | ... Q126: =+Q112-Q118 -> 2909162.5
B128: Debt Service
A129: 9210-8501 | D129: Interest | E129: =+'1100'!E128+'1500'!E128+'2300'!E128+'4500'!E128+'5600'!E128+'7010'!E131+'7200'!E128+'7300'!E128+'8200'!E128+'9510'!E128 -> 47987.415 | F129: =+'1100'!F128+'1500'!F128+'2300'!F128+'4500'!F128+'5600'!F128+'7010'!F131+'7200'!F128+'7300'!F128+'8200'!F128+'9510'!F128 -> 47851.993 | G129: =+'1100'!G128+'1500'!G128+'2300'!G128+'4500'!G128+'5600'!G128+'7010'!G131+'7200'!G128+'7300'!G128+'8200'!G128+'9510'!G128 -> 47716.173 | H129: =+'1100'!H128+'1500'!H128+'2300'!H128+'4500'!H128+'5600'!H128+'7010'!H131+'7200'!H128+'7300'!H128+'8200'!H128+'9510'!H128 -> 47579.955 | I129: =+'1100'!I128+'1500'!I128+'2300'!I128+'4500'!I128+'5600'!I128+'7010'!I131+'7200'!I128+'7300'!I128+'8200'!I128+'9510'!I128 -> 47443.336 | J129: =+'1100'!J128+'1500'!J128+'2300'!J128+'4500'!J128+'5600'!J128+'7010'!J131+'7200'!J128+'7300'!J128+'8200'!J128+'9510'!J128 -> 47306.317 | K129: =+'1100'!K128+'1500'!K128+'2300'!K128+'4500'!K128+'5600'!K128+'7010'!K131+'7200'!K128+'7300'!K128+'8200'!K128+'9510'!K128 -> 47168.895 | L129: =+'1100'!L128+'1500'!L128+'2300'!L128+'4500'!L128+'5600'!L128+'7010'!L131+'7200'!L128+'7300'!L128+'8200'!L128+'9510'!L128 -> 47031.069 | ... P129: =+'1100'!P128+'1500'!P128+'2300'!P128+'4500'!P128+'5600'!P128+'7010'!P131+'7200'!P128+'7300'!P128+'8200'!P128+'9510'!P128 -> 46475.708 | Q129: =SUM(E129:P129) -> 566823.06
A130: 2740-8501 | D130: Mortgage Amortization | E130: =+'1100'!E129+'1500'!E129+'2300'!E129+'4500'!E129+'5600'!E129+'7010'!E132+'7200'!E129+'7300'!E129+'8200'!E129+'9510'!E129 -> 46121.206 | F130: =+'1100'!F129+'1500'!F129+'2300'!F129+'4500'!F129+'5600'!F129+'7010'!F132+'7200'!F129+'7300'!F129+'8200'!F129+'9510'!F129 -> 46256.628 | G130: =+'1100'!G129+'1500'!G129+'2300'!G129+'4500'!G129+'5600'!G129+'7010'!G132+'7200'!G129+'7300'!G129+'8200'!G129+'9510'!G129 -> 46392.448 | H130: =+'1100'!H129+'1500'!H129+'2300'!H129+'4500'!H129+'5600'!H129+'7010'!H132+'7200'!H129+'7300'!H129+'8200'!H129+'9510'!H129 -> 46528.666 | I130: =+'1100'!I129+'1500'!I129+'2300'!I129+'4500'!I129+'5600'!I129+'7010'!I132+'7200'!I129+'7300'!I129+'8200'!I129+'9510'!I129 -> 46665.285 | J130: =+'1100'!J129+'1500'!J129+'2300'!J129+'4500'!J129+'5600'!J129+'7010'!J132+'7200'!J129+'7300'!J129+'8200'!J129+'9510'!J129 -> 46802.305 | K130: =+'1100'!K129+'1500'!K129+'2300'!K129+'4500'!K129+'5600'!K129+'7010'!K132+'7200'!K129+'7300'!K129+'8200'!K129+'9510'!K129 -> 46939.727 | L130: =+'1100'!L129+'1500'!L129+'2300'!L129+'4500'!L129+'5600'!L129+'7010'!L132+'7200'!L129+'7300'!L129+'8200'!L129+'9510'!L129 -> 47077.552 | ... P130: =+'1100'!P129+'1500'!P129+'2300'!P129+'4500'!P129+'5600'!P129+'7010'!P132+'7200'!P129+'7300'!P129+'8200'!P129+'9510'!P129 -> 47632.913 | Q130: =SUM(E130:P130) -> 562480.39
A131: 2740-0000 | D131: Loan Proceeds | Q131: =SUM(E131:P131) -> 0
C132: Total Debt Service | E132: =SUM(E129:E131) -> 94108.621 | F132: =SUM(F129:F131) -> 94108.621 | G132: =SUM(G129:G131) -> 94108.621 | H132: =SUM(H129:H131) -> 94108.621 | I132: =SUM(I129:I131) -> 94108.621 | J132: =SUM(J129:J131) -> 94108.621 | K132: =SUM(K129:K131) -> 94108.621 | L132: =SUM(L129:L131) -> 94108.621 | ... Q132: =SUM(Q129:Q131) -> 1129303.5
B135: CASH FLOW AFTER DEBT SERVICE | E135: =+E126-E132 -> 55797.674 | F135: =+F126-F132 -> 192201.19 | G135: =+G126-G132 -> 26742.807 | H135: =+H126-H132 -> -234006.4 | I135: =+I126-I132 -> 225895.79 | J135: =+J126-J132 -> 250127.3 | K135: =+K126-K132 -> 14237.901 | L135: =+L126-L132 -> 250046.21 | ... Q135: =+Q126-Q132 -> 1779859.1
D256: Other New Leases | F256: -2803 | G256: =+F256 -> -2803 | H256: =-5293+G256 -> -8096 | I256: =-3237+H256 -> -11333 | J256: =-5607+I256 -> -16940 | K256: =+J256 -> -16940 | L256: =-4951+K256 -> -21891 | M256: =+L256 -> -21891 | N256: =+M256 -> -21891 | O256: =+N256 -> -21891 | P256: =+O256 -> -21891 | Q256: =SUM(E256:P256) -> -168370
E258: =+#REF!+#REF!+E256 -> #REF! | F258: =+E258+#REF!+F256 -> #REF! | G258: =+F258+#REF!+G256 -> #REF! | H258: =+G258+#REF!+H256 -> #REF! | I258: =+H258+#REF!+I256 -> #REF! | J258: =+I258+#REF!+J256 -> #REF! | K258: =+J258+#REF!+K256 -> #REF! | L258: =+K258+#REF!+L256 -> #REF! | M258: =+L258+#REF!+M256 -> #REF! | ... O258: =+N258+#REF!+O256 -> #REF!
D261: Debt Service - Consolidated
D263: Liberty Bank
...

Sheet 1100
B1: 1100 | C1: - Parkwood Professional Building | J1: =+'All Shopping Centers'!J1 -> Operating Budget | Q1: ='All Shopping Centers'!Q1 -> 46023
J2: ='All Shopping Centers'!J2&" - "&B1 -> Shopping Centers - 1100
B4: 8287 | E4: Jan | F4: Feb | G4: Mar | H4: Apr | I4: May | J4: Jun | K4: Jul | L4: Aug | M4: Sep | N4: Oct | O4: Nov | P4: Dec | Q4: Total | R4: Total PSF | S4: Input | T4: Notes
D6: Occupancy % | E6: ='Renew & Vac '!AJ9 -> 0.5143 | F6: ='Renew & Vac '!AK9 -> 0.5143 | G6: ='Renew & Vac '!AL9 -> 0.5143 | H6: ='Renew & Vac '!AM9 -> 0.5143 | I6: ='Renew & Vac '!AN9 -> 0.5143 | J6: ='Renew & Vac '!AO9 -> 0.635 | K6: ='Renew & Vac '!AP9 -> 0.635 | L6: ='Renew & Vac '!AQ9 -> 0.635 | ... P6: ='Renew & Vac '!AU9 -> 0.635
D7: Occupancy SF | E7: =$B$4*E6 -> 4262.0041 | F7: =$B$4*F6 -> 4262.0041 | G7: =$B$4*G6 -> 4262.0041 | H7: =$B$4*H6 -> 4262.0041 | I7: =$B$4*I6 -> 4262.0041 | J7: =$B$4*J6 -> 5262.245 | K7: =$B$4*K6 -> 5262.245 | L7: =$B$4*L6 -> 5262.245 | ... P7: =$B$4*P6 -> 5262.245
B8: Revenues
A10: 4230-8501 | C10: Rental Income - In Place | E10: =SUMIFS('In Place Revenue'!$G:$G,'In Place Revenue'!$A:$A,$B$1,'In Place Revenue'!$H:$H,1) -> 0 | F10: =SUMIFS('In Place Revenue'!$G:$G,'In Place Revenue'!$A:$A,$B$1,'In Place Revenue'!$H:$H,2) -> 0 | G10: =SUMIFS('In Place Revenue'!$G:$G,'In Place Revenue'!$A:$A,$B$1,'In Place Revenue'!$H:$H,3) -> 0 | H10: =SUMIFS('In Place Revenue'!$G:$G,'In Place Revenue'!$A:$A,$B$1,'In Place Revenue'!$H:$H,4) -> 0 | I10: =SUMIFS('In Place Revenue'!$G:$G,'In Place Revenue'!$A:$A,$B$1,'In Place Revenue'!$H:$H,5) -> 0 | J10: =SUMIFS('In Place Revenue'!$G:$G,'In Place Revenue'!$A:$A,$B$1,'In Place Revenue'!$H:$H,6) -> 0 | K10: =SUMIFS('In Place Revenue'!$G:$G,'In Place Revenue'!$A:$A,$B$1,'In Place Revenue'!$H:$H,7) -> 0 | L10: =SUMIFS('In Place Revenue'!$G:$G,'In Place Revenue'!$A:$A,$B$1,'In Place Revenue'!$H:$H,8) -> 0 | M10: =SUMIFS('In Place Revenue'!$G:$G,'In Place Revenue'!$A:$A,$B$1,'In Place Revenue'!$H:$H,9) -> 0 | N10: =SUMIFS('In Place Revenue'!$G:$G,'In Place Revenue'!$A:$A,$B$1,'In Place Revenue'!$H:$H,10) -> 0 | O10: =SUMIFS('In Place Revenue'!$G:$G,'In Place Revenue'!$A:$A,$B$1,'In Place Revenue'!$H:$H,11) -> 0 | P10: =SUMIFS('In Place Revenue'!$G:$G,'In Place Revenue'!$A:$A,$B$1,'In Place Revenue'!$H:$H,12) -> 0 | Q10: =SUM(E10:P10) -> 0 | R10: =Q10/$B$4 -> 0
A11: 4230-8501 | C11: Rental Income - New & Renewal | E11: ='Renew & Vac '!AJ10 -> 3056.1667 | F11: ='Renew & Vac '!AK10 -> 3056.1667 | G11: ='Renew & Vac '!AL10 -> 3056.1667 | H11: ='Renew & Vac '!AM10 -> 3056.1667 | I11: ='Renew & Vac '!AN10 -> 3056.1667 | J11: ='Renew & Vac '!AO10 -> 4306.1667 | K11: ='Renew & Vac '!AP10 -> 4306.1667 | L11: ='Renew & Vac '!AQ10 -> 4306.1667 | ... P11: ='Renew & Vac '!AU10 -> 4306.1667 | Q11: =SUM(E11:P11) -> 45424 | R11: =Q11/$B$4 -> 5.4813563
A12: 4240-8501 | C12: Percentage Rents | E12: 0 | F12: 0 | G12: 0 | H12: 0 | I12: 0 | J12: 0 | K12: 0 | L12: 0 | M12: 0 | N12: 0 | O12: 0 | P12: 0 | Q12: =SUM(E12:P12) -> 0 | R12: =Q12/$B$4 -> 0
A13: 4990-8501 | C13: Miscellaneous | E13: 0 | F13: 0 | G13: 0 | H13: 0 | I13: 0 | J13: 0 | K13: 0 | L13: 0 | M13: 0 | N13: 0 | O13: 0 | P13: 0 | Q13: =SUM(E13:P13) -> 0 | R13: =Q13/$B$4 -> 0
A14: 9190-8501 | C14: Interest Income | E14: =1.03*3 -> 3.09 | F14: =1.03*3 -> 3.09 | G14: =1.03*3 -> 3.09 | H14: =1.03*3 -> 3.09 | I14: =1.03*3 -> 3.09 | J14: =1.03*3 -> 3.09 | K14: =1.03*3 -> 3.09 | L14: =1.03*3 -> 3.09 | ... P14: =1.03*3 -> 3.09 | Q14: =SUM(E14:P14) -> 37.08 | R14: =Q14/$B$4 -> 0.0044744781 | S14: DW | T14: 2025 Business Plan grown 3%
C15: Total Rental and Other | E15: =SUM(E10:E14) -> 3059.2567 | F15: =SUM(F10:F14) -> 3059.2567 | G15: =SUM(G10:G14) -> 3059.2567 | H15: =SUM(H10:H14) -> 3059.2567 | I15: =SUM(I10:I14) -> 3059.2567 | J15: =SUM(J10:J14) -> 4309.2567 | K15: =SUM(K10:K14) -> 4309.2567 | L15: =SUM(L10:L14) -> 4309.2567 | ... Q15: =SUM(Q10:Q14) -> 45461.08 | R15: =Q15/$B$4 -> 5.4858308
B17: Reimbursements
A18: 4710-8502 | C18: Electric | Q18: =SUM(E18:P18) -> 0 | R18: =Q18/$B$4 -> 0
A19: 4910-8502 | C19: Common Area Maintenance | E19: =+'Tenant Recoveries'!E26 -> 2600 | F19: =+E19 -> 2600 | G19: =+F19 -> 2600 | H19: =+G19 -> 2600 | I19: =+H19 -> 2600 | J19: =+I19 -> 2600 | K19: =+J19 -> 2600 | L19: =+K19 -> 2600 | M19: =+L19 -> 2600 | ... P19: =+O19 -> 2600 | Q19: =SUM(E19:P19) -> 31200 | R19: =Q19/$B$4 -> 3.764933
A20: 4920-8502 | C20: Real Estate Taxes | E20: =+'Tenant Recoveries'!E27 -> 600 | F20: =+E20 -> 600 | G20: =+F20 -> 600 | H20: =+G20 -> 600 | I20: =+H20 -> 600 | J20: =+I20 -> 600 | K20: =+J20 -> 600 | L20: =+K20 -> 600 | M20: =+L20 -> 600 | ... P20: =+O20 -> 600 | Q20: =SUM(E20:P20) -> 7200 | R20: =Q20/$B$4 -> 0.8688307
A21: 4930-8502 | C21: Insurance | Q21: =SUM(E21:P21) -> 0 | R21: =Q21/$B$4 -> 0
C22: Total Reimbursements | E22: =SUM(E18:E21) -> 3200 | F22: =SUM(F18:F21) -> 3200 | G22: =SUM(G18:G21) -> 3200 | H22: =SUM(H18:H21) -> 3200 | I22: =SUM(I18:I21) -> 3200 | J22: =SUM(J18:J21) -> 3200 | K22: =SUM(K18:K21) -> 3200 | L22: =SUM(L18:L21) -> 3200 | ... Q22: =SUM(Q18:Q21) -> 38400 | R22: =Q22/$B$4 -> 4.6337637
R23: =Q23/$B$4 -> 0
B24: TOTAL REVENUES | E24: =+E15+E22 -> 6259.2567 | F24: =+F15+F22 -> 6259.2567 | G24: =+G15+G22 -> 6259.2567 | H24: =+H15+H22 -> 6259.2567 | I24: =+I15+I22 -> 6259.2567 | J24: =+J15+J22 -> 7509.2567 | K24: =+K15+K22 -> 7509.2567 | L24: =+L15+L22 -> 7509.2567 | ... Q24: =+Q15+Q22 -> 83861.08 | R24: =Q24/$B$4 -> 10.119595
B26: Reimbursable Expenses
A27: 6030-8502 | C27: Maintenance Salaries | E27: =VLOOKUP($B$1,'Allocated Expenses'!$B$6:$P$15,4,FALSE) -> 255.18265 | F27: =VLOOKUP($B$1,'Allocated Expenses'!$B$6:$P$15,5,FALSE) -> 255.18265 | G27: =VLOOKUP($B$1,'Allocated Expenses'!$B$6:$P$15,6,FALSE) -> 255.18265 | H27: =VLOOKUP($B$1,'Allocated Expenses'!$B$6:$P$15,7,FALSE) -> 255.18265 | I27: =VLOOKUP($B$1,'Allocated Expenses'!$B$6:$P$15,8,FALSE) -> 255.18265 | J27: =VLOOKUP($B$1,'Allocated Expenses'!$B$6:$P$15,9,FALSE) -> 255.18265 | K27: =VLOOKUP($B$1,'Allocated Expenses'!$B$6:$P$15,10,FALSE) -> 255.18265 | L27: =VLOOKUP($B$1,'Allocated Expenses'!$B$6:$P$15,11,FALSE) -> 255.18265 | M27: =VLOOKUP($B$1,'Allocated Expenses'!$B$6:$P$15,12,FALSE) -> 255.18265 | N27: =VLOOKUP($B$1,'Allocated Expenses'!$B$6:$P$15,13,FALSE) -> 255.18265 | O27: =VLOOKUP($B$1,'Allocated Expenses'!$B$6:$P$15,14,FALSE) -> 255.18265 | P27: =VLOOKUP($B$1,'Allocated Expenses'!$B$6:$P$15,15,FALSE) -> 255.18265 | Q27: =SUM(E27:P27) -> 3062.1918 | R27: =Q27/$B$4 -> 0.36951753
A29: 6120-8502 | C29: Electric | E29: =1.03*641 -> 660.23 | F29: =1.03*622 -> 640.66 | G29: =1.03*712 -> 733.36 | H29: =1.03*651 -> 670.53 | I29: =1.03*616 -> 634.48 | J29: =1.03*527 -> 542.81 | K29: =1.03*192 -> 197.76 | L29: =1.03*171 -> 176.13 | M29: =1.03*176 -> 181.28 | N29: =1.03*170 -> 175.1 | O29: =1.03*581 -> 598.43 | P29: =1.03*774 -> 797.22 | Q29: =SUM(E29:P29) -> 6007.99 | R29: =Q29/$B$4 -> 0.72498974 | S29: DW | T29: 2025 Business Plan grown 3%
A31: 6130-8502 | C31: Water & Sewer | Q31: =SUM(E31:P31) -> 0 | R31: =Q31/$B$4 -> 0
D33: Building Maint.-Contractual | E33: ='Building Maint'!C20 -> 0 | F33: ='Building Maint'!D20 -> 0 | G33: ='Building Maint'!E20 -> 0 | H33: ='Building Maint'!F20 -> 0 | I33: ='Building Maint'!G20 -> 400 | J33: ='Building Maint'!H20 -> 0 | K33: ='Building Maint'!I20 -> 0 | L33: ='Building Maint'!J20 -> 0 | ... P33: ='Building Maint'!N20 -> 0 | Q33: =SUM(E33:P33) -> 1100 | R33: =Q33/$B$4 -> 0.13273802 | S33: DW | T33: 2025 Business Plan grown 3%
D34: Building Maint.-Recurring | E34: ='Building Maint'!C6 -> 200 | F34: ='Building Maint'!D6 -> 200 | G34: ='Building Maint'!E6 -> 200 | H34: ='Building Maint'!F6 -> 500 | I34: ='Building Maint'!G6 -> 200 | J34: ='Building Maint'!H6 -> 200 | K34: ='Building Maint'!I6 -> 200 | L34: ='Building Maint'!J6 -> 200 | ... P34: ='Building Maint'!N6 -> 200 | Q34: =SUM(E34:P34) -> 3150 | R34: =Q34/$B$4 -> 0.38011343 | S34: DW | T34: 2025 Business Plan grown 3%
D35: Building Maint.-Big Projects | F35: 500 | I35: 500 | L35: 500 | O35: 500 | Q35: =SUM(E35:P35) -> 2000 | R35: =Q35/$B$4 -> 0.24134186 | S35: GM | T35: Roof maintenance
A36: 6220-8502 | C36: Building Maintenance | E36: =SUM(E33:E35) -> 200 | F36: =SUM(F33:F35) -> 700 | G36: =SUM(G33:G35) -> 200 | H36: =SUM(H33:H35) -> 500 | I36: =SUM(I33:I35) -> 1100 | J36: =SUM(J33:J35) -> 200 | K36: =SUM(K33:K35) -> 200 | L36: =SUM(L33:L35) -> 700 | ... Q36: =SUM(Q33:Q35) -> 6250 | R36: =Q36/$B$4 -> 0.75419331
A38: 6330-8502 | B38: (SC) | C38: Parking Lot Cleaning | E38: 300 | F38: 300 | G38: 300 | H38: 300 | I38: 300 | J38: 300 | K38: 300 | L38: 300 | M38: 300 | N38: 300 | O38: 300 | P38: 300 | Q38: =SUM(E38:P38) -> 3600 | R38: =Q38/$B$4 -> 0.43441535 | S38: DW | T38: 2025 Business Plan grown 3%
D40: Parking Lot Maint.-Contractual | Q40: =SUM(E40:P40) -> 0 | R40: =Q40/$B$4 -> 0
D41: Parking Lot Maint.-Recurring | G41: 1250 | J41: 1250 | M41: 1250 | P41: 1250 | Q41: =SUM(E41:P41) -> 5000 | R41: =Q41/$B$4 -> 0.60335465 | S41: DW | T41: Est Misc. Repairs
D42: Parking Lot Maint.-Big Projects | Q42: =SUM(E42:P42) -> 0 | R42: =Q42/$B$4 -> 0 | S42: GM
A43: 6360-8502 | C43: Parking Lot Maintenance | E43: =SUM(E40:E42) -> 0 | F43: =SUM(F40:F42) -> 0 | G43: =SUM(G40:G42) -> 1250 | H43: =SUM(H40:H42) -> 0 | I43: =SUM(I40:I42) -> 0 | J43: =SUM(J40:J42) -> 1250 | K43: =SUM(K40:K42) -> 0 | L43: =SUM(L40:L42) -> 0 | ... Q43: =SUM(Q40:Q42) -> 5000 | R43: =Q43/$B$4 -> 0.60335465
A45: 6370-8502 | C45: Snow Removal | E45: =1.03*3500 -> 3605 | F45: =1.03*3500 -> 3605 | G45: =1.03*1000 -> 1030 | O45: =1.03*1000 -> 1030 | P45: =1.03*2000 -> 2060 | Q45: =SUM(E45:P45) -> 11330 | R45: =Q45/$B$4 -> 1.3672016 | S45: DW | T45: 2025 Business Plan grown 3%
D47: Landscaping-Contractual | H47: 376 | I47: 376 | J47: 376 | K47: 376 | L47: 376 | M47: 376 | N47: 376 | Q47: =SUM(E47:P47) -> 2632 | R47: =Q47/$B$4 -> 0.31760589 | S47: DW | T47: For mowing SC area only
D48: Landscaping-Recurring | H48: =1.03*100 -> 103 | I48: =1.03*100 -> 103 | J48: =1.03*100 -> 103 | K48: =1.03*100 -> 103 | L48: =1.03*100 -> 103 | M48: =1.03*100 -> 103 | N48: =1.03*100 -> 103 | Q48: =SUM(E48:P48) -> 721 | R48: =Q48/$B$4 -> 0.087003741 | S48: DW | T48: 2025 Business Plan grown 3%
D49: Landscaping-Big Projects | I49: 500 | L49: 500 | Q49: =SUM(G49:P49) -> 1000 | R49: =Q49/$B$4 -> 0.12067093 | S49: DW
A50: 6380-8502 | C50: Landscaping | E50: =SUM(E47:E49) -> 0 | F50: =SUM(F47:F49) -> 0 | G50: =SUM(G47:G49) -> 0 | H50: =SUM(H47:H49) -> 479 | I50: =SUM(I47:I49) -> 979 | J50: =SUM(J47:J49) -> 479 | K50: =SUM(K47:K49) -> 479 | L50: =SUM(L47:L49) -> 979 | ... Q50: =SUM(Q47:Q49) -> 4353 | R50: =Q50/$B$4 -> 0.52528056
A52: 6350-8502 | C52: Security | E52: =1.03*1300 -> 1339 | F52: =1.03*1300 -> 1339 | G52: =1.03*1300 -> 1339 | H52: =1.03*1300 -> 1339 | I52: =1.03*1300 -> 1339 | J52: =1.03*1300 -> 1339 | K52: =1.03*1300 -> 1339 | L52: =1.03*1300 -> 1339 | ... P52: =1.03*1300 -> 1339 | Q52: =SUM(E52:P52) -> 16068 | R52: =Q52/$B$4 -> 1.9389405 | S52: DW | T52: 2025 Business Plan grown 3%
A54: 6610-8502 | B54: (BP) | C54: Management Fee | Q54: =SUM(E54:P54) -> 0 | R54: =Q54/$B$4 -> 0
A56: 6270-8502 | C56: Trash Removal | Q56: =SUM(E56:P56) -> 0 | R56: =Q56/$B$4 -> 0
A58: 6410-8502 | C58: Real Estate Taxes | E58: =+'INS RET DEBT'!E81 -> 1391.0508 | F58: =+'INS RET DEBT'!F81 -> 1391.0508 | G58: =+'INS RET DEBT'!G81 -> 1391.0508 | H58: =+'INS RET DEBT'!H81 -> 1391.0508 | I58: =+'INS RET DEBT'!I81 -> 1391.0508 | J58: =+'INS RET DEBT'!J81 -> 1391.0508 | K58: =+'INS RET DEBT'!K81 -> 1391.0508 | L58: =+'INS RET DEBT'!L81 -> 1391.0508 | ... P58: =+'INS RET DEBT'!P81 -> 1391.0508 | Q58: =SUM(E58:P58) -> 16692.61 | R58: =Q58/$B$4 -> 2.0143128
D60: Insurance-Liability | E60: =+'INS RET DEBT'!E6+'INS RET DEBT'!E7 -> 560 | F60: =+'INS RET DEBT'!F6+'INS RET DEBT'!F7 -> 560 | G60: =+'INS RET DEBT'!G6+'INS RET DEBT'!G7 -> 560 | H60: =+'INS RET DEBT'!H6+'INS RET DEBT'!H7 -> 560 | I60: =+'INS RET DEBT'!I6+'INS RET DEBT'!I7 -> 560 | J60: =+'INS RET DEBT'!J6+'INS RET DEBT'!J7 -> 560 | K60: =+'INS RET DEBT'!K6+'INS RET DEBT'!K7 -> 560 | L60: =+'INS RET DEBT'!L6+'INS RET DEBT'!L7 -> 560 | ... P60: =+'INS RET DEBT'!P6+'INS RET DEBT'!P7 -> 571.2 | Q60: =SUM(E60:P60) -> 6742.4 | R60: =Q60/$B$4 -> 0.81361168
D61: Insurance-Property | E61: =+'INS RET DEBT'!E9 -> 93 | F61: =+'INS RET DEBT'!F9 -> 93 | G61: =+'INS RET DEBT'!G9 -> 93 | H61: =+'INS RET DEBT'!H9 -> 93 | I61: =+'INS RET DEBT'!I9 -> 93 | J61: =+'INS RET DEBT'!J9 -> 93 | K61: =+'INS RET DEBT'!K9 -> 93 | L61: =+'INS RET DEBT'!L9 -> 93 | ... P61: =+'INS RET DEBT'!P9 -> 94.86 | Q61: =SUM(E61:P61) -> 1119.72 | R61: =Q61/$B$4 -> 0.13511765
D62: Insurance-Other | E62: =+'INS RET DEBT'!E10 -> 0 | F62: =+'INS RET DEBT'!F10 -> 0 | G62: =+'INS RET DEBT'!G10 -> 0 | H62: =+'INS RET DEBT'!H10 -> 0 | I62: =+'INS RET DEBT'!I10 -> 0 | J62: =+'INS RET DEBT'!J10 -> 0 | K62: =+'INS RET DEBT'!K10 -> 0 | L62: =+'INS RET DEBT'!L10 -> 0 | ... P62: =+'INS RET DEBT'!P10 -> 0 | Q62: =SUM(E62:P62) -> 0 | R62: =Q62/$B$4 -> 0
A63: 6510-8502 | C63: Insurance | E63: =SUM(E60:E62) -> 653 | F63: =SUM(F60:F62) -> 653 | G63: =SUM(G60:G62) -> 653 | H63: =SUM(H60:H62) -> 653 | I63: =SUM(I60:I62) -> 653 | J63: =SUM(J60:J62) -> 653 | K63: =SUM(K60:K62) -> 653 | L63: =SUM(L60:L62) -> 653 | ... Q63: =SUM(Q60:Q62) -> 7862.12 | R63: =Q63/$B$4 -> 0.94872934
D65: Cleaning & Supplies | Q65: =SUM(E65:P65) -> 0 | R65: =Q65/$B$4 -> 0
D66: Cleaning & Supplies-Vacancies | Q66: =SUM(E66:P66) -> 0 | R66: =Q66/$B$4 -> 0
A67: 6250-8502 | B67: (BP) | C67: Cleaning & Supplies | E67: =SUM(E65:E66) -> 0 | F67: =SUM(F65:F66) -> 0 | G67: =SUM(G65:G66) -> 0 | H67: =SUM(H65:H66) -> 0 | I67: =SUM(I65:I66) -> 0 | J67: =SUM(J65:J66) -> 0 | K67: =SUM(K65:K66) -> 0 | L67: =SUM(L65:L66) -> 0 | ... Q67: =SUM(Q65:Q66) -> 0 | R67: =Q67/$B$4 -> 0
B69: (SC) | C69: Other | E69: 0 | F69: 0 | G69: 0 | H69: 0 | I69: 0 | J69: 0 | K69: 0 | L69: 0 | M69: 0 | N69: 0 | O69: 0 | P69: 0 | Q69: =SUM(E69:P69) -> 0 | R69: =Q69/$B$4 -> 0
C71: Total Reimbursable Expenses | E71: =+E27+E29+E31+E36+E38+E43+E45+E50+E52+E54+E56+E58+E63+E67+E69 -> 8403.4635 | F71: =+F27+F29+F31+F36+F38+F43+F45+F50+F52+F54+F56+F58+F63+F67+F69 -> 8883.8935 | G71: =+G27+G29+G31+G36+G38+G43+G45+G50+G52+G54+G56+G58+G63+G67+G69 -> 7151.5935 | H71: =+H27+H29+H31+H36+H38+H43+H45+H50+H52+H54+H56+H58+H63+H67+H69 -> 5587.7635 | I71: =+I27+I29+I31+I36+I38+I43+I45+I50+I52+I54+I56+I58+I63+I67+I69 -> 6651.7135 | J71: =+J27+J29+J31+J36+J38+J43+J45+J50+J52+J54+J56+J58+J63+J67+J69 -> 6410.0435 | K71: =+K27+K29+K31+K36+K38+K43+K45+K50+K52+K54+K56+K58+K63+K67+K69 -> 4814.9935 | L71: =+L27+L29+L31+L36+L38+L43+L45+L50+L52+L54+L56+L58+L63+L67+L69 -> 5793.3635 | ... Q71: =+Q27+Q29+Q31+Q36+Q38+Q43+Q45+Q50+Q52+Q54+Q56+Q58+Q63+Q67+Q69 -> 80225.912 | R71: =Q71/$B$4 -> 9.6809354 | T71: =+(Q71-Q58-Q61)/B4 -> 7.531505
T72: =+Q58/B4 -> 2.0143128
B73: Non-Reimbursable Expenses | R73: =Q73/$B$4 -> 0 | T73: =+Q61/B4 -> 0.13511765
A75: 5210-0000 | C75: Bad Debt | E75: 0 | F75: 0 | G75: 0 | H75: 0 | I75: 0 | J75: 0 | K75: 0 | L75: 0 | M75: 0 | N75: 0 | O75: 0 | P75: 0 | Q75: =SUM(E75:P75) -> 0 | R75: =Q75/$B$4 -> 0
A77: 6010-8501 | D77: Salaries & Wages | E77: =VLOOKUP($B$1,'Allocated Expenses'!$B$20:$P$29,4,FALSE) -> 616.27185 | F77: =VLOOKUP($B$1,'Allocated Expenses'!$B$20:$P$29,5,FALSE) -> 616.27185 | G77: =VLOOKUP($B$1,'Allocated Expenses'!$B$20:$P$29,6,FALSE) -> 616.27185 | H77: =VLOOKUP($B$1,'Allocated Expenses'!$B$20:$P$29,7,FALSE) -> 616.27185 | I77: =VLOOKUP($B$1,'Allocated Expenses'!$B$20:$P$29,8,FALSE) -> 616.27185 | J77: =VLOOKUP($B$1,'Allocated Expenses'!$B$20:$P$29,9,FALSE) -> 616.27185 | K77: =VLOOKUP($B$1,'Allocated Expenses'!$B$20:$P$29,10,FALSE) -> 616.27185 | L77: =VLOOKUP($B$1,'Allocated Expenses'!$B$20:$P$29,11,FALSE) -> 616.27185 | M77: =VLOOKUP($B$1,'Allocated Expenses'!$B$20:$P$29,12,FALSE) -> 616.27185 | N77: =VLOOKUP($B$1,'Allocated Expenses'!$B$20:$P$29,13,FALSE) -> 616.27185 | O77: =VLOOKUP($B$1,'Allocated Expenses'!$B$20:$P$29,14,FALSE) -> 616.27185 | P77: =VLOOKUP($B$1,'Allocated Expenses'!$B$20:$P$29,15,FALSE) -> 616.27185 | Q77: =SUM(E77:P77) -> 7395.2622 | R77: =Q77/$B$4 -> 0.89239317
A78: 6620-8501 | D78: Commissions-Internal Broker | E78: =VLOOKUP($B$1,'Allocated Expenses'!$B$132:$P$141,4,FALSE) -> 0 | F78: =VLOOKUP($B$1,'Allocated Expenses'!$B$132:$P$141,5,FALSE) -> 0 | G78: =VLOOKUP($B$1,'Allocated Expenses'!$B$132:$P$141,6,FALSE) -> 0 | H78: =VLOOKUP($B$1,'Allocated Expenses'!$B$132:$P$141,7,FALSE) -> 0 | I78: =VLOOKUP($B$1,'Allocated Expenses'!$B$132:$P$141,8,FALSE) -> 0 | J78: =VLOOKUP($B$1,'Allocated Expenses'!$B$132:$P$141,9,FALSE) -> 0 | K78: =VLOOKUP($B$1,'Allocated Expenses'!$B$132:$P$141,10,FALSE) -> 0 | L78: =VLOOKUP($B$1,'Allocated Expenses'!$B$132:$P$141,11,FALSE) -> 0 | M78: =VLOOKUP($B$1,'Allocated Expenses'!$B$132:$P$141,12,FALSE) -> 0 | N78: =VLOOKUP($B$1,'Allocated Expenses'!$B$132:$P$141,13,FALSE) -> 0 | O78: =VLOOKUP($B$1,'Allocated Expenses'!$B$132:$P$141,14,FALSE) -> 0 | P78: =VLOOKUP($B$1,'Allocated Expenses'!$B$132:$P$141,15,FALSE) -> 0 | Q78: =SUM(E78:P78) -> 0 | R78: =Q78/$B$4 -> 0
C79: Leasing Salaries and Commissions | E79: =SUM(E77:E78) -> 616.27185 | F79: =SUM(F77:F78) -> 616.27185 | G79: =SUM(G77:G78) -> 616.27185 | H79: =SUM(H77:H78) -> 616.27185 | I79: =SUM(I77:I78) -> 616.27185 | J79: =SUM(J77:J78) -> 616.27185 | K79: =SUM(K77:K78) -> 616.27185 | L79: =SUM(L77:L78) -> 616.27185 | ... Q79: =SUM(Q77:Q78) -> 7395.2622 | R79: =Q79/$B$4 -> 0.89239317
A81: 6110-8501 | D81: Gas | Q81: =SUM(E81:P81) -> 0 | R81: =Q81/$B$4 -> 0 | S81: DW | T81: 2025 Business Plan grown 3%
A82: 6120-8501 | D82: Electric | Q82: =SUM(E82:P82) -> 0 | R82: =Q82/$B$4 -> 0 | S82: DW | T82: 2025 Business Plan grown 3%
A83: 6130-8501 | D83: Water & Sewer | Q83: =SUM(E83:P83) -> 0 | R83: =Q83/$B$4 -> 0
C84: Utilities | E84: =SUM(E81:E83) -> 0 | F84: =SUM(F81:F83) -> 0 | G84: =SUM(G81:G83) -> 0 | H84: =SUM(H81:H83) -> 0 | I84: =SUM(I81:I83) -> 0 | J84: =SUM(J81:J83) -> 0 | K84: =SUM(K81:K83) -> 0 | L84: =SUM(L81:L83) -> 0 | ... Q84: =SUM(Q81:Q83) -> 0 | R84: =Q84/$B$4 -> 0
D86: Building Maint.-Recurring | E86: =1.03*150+500 -> 654.5 | F86: =1.03*150+500 -> 654.5 | G86: =1.03*150+500 -> 654.5 | H86: =1.03*150+500 -> 654.5 | I86: =1.03*150+500 -> 654.5 | J86: =1.03*150+500 -> 654.5 | K86: =1.03*150+500 -> 654.5 | L86: =1.03*150+500 -> 654.5 | ... P86: =1.03*150+500 -> 654.5 | Q86: =SUM(E86:P86) -> 7854 | R86: =Q86/$B$4 -> 0.94774949 | S86: DW | T86: Includes $500/mo to mow empty field
D87: Building Maint.-Big Projects | Q87: =SUM(E87:P87) -> 0 | R87: =Q87/$B$4 -> 0
A88: 6220-8501 | C88: Building Maintenance | E88: =SUM(E86:E87) -> 654.5 | F88: =SUM(F86:F87) -> 654.5 | G88: =SUM(G86:G87) -> 654.5 | H88: =SUM(H86:H87) -> 654.5 | I88: =SUM(I86:I87) -> 654.5 | J88: =SUM(J86:J87) -> 654.5 | K88: =SUM(K86:K87) -> 654.5 | L88: =SUM(L86:L87) -> 654.5 | ... Q88: =SUM(Q86:Q87) -> 7854 | R88: =Q88/$B$4 -> 0.94774949
A90: 6610-8501 | B90: (SC) | C90: Management fee | E90: =ROUND(E$24*0.06,0) -> 376 | F90: =ROUND(F$24*0.06,0) -> 376 | G90: =ROUND(G$24*0.06,0) -> 376 | H90: =ROUND(H$24*0.06,0) -> 376 | I90: =ROUND(I$24*0.06,0) -> 376 | J90: =ROUND(J$24*0.06,0) -> 451 | K90: =ROUND(K$24*0.06,0) -> 451 | L90: =ROUND(L$24*0.06,0) -> 451 | ... P90: =ROUND(P$24*0.06,0) -> 451 | Q90: =SUM(E90:P90) -> 5037 | R90: =Q90/$B$4 -> 0.60781948
A92: 7110-8501 | C92: Marketing | E92: =VLOOKUP($B$1,'Allocated Expenses'!$B$34:$P$43,4,FALSE)+VLOOKUP($B$1,'Allocated Expenses'!$B$48:$P$57,4,FALSE) -> 241.13352 | F92: =VLOOKUP($B$1,'Allocated Expenses'!$B$34:$P$43,5,FALSE)+VLOOKUP($B$1,'Allocated Expenses'!$B$48:$P$57,5,FALSE) -> 241.13352 | G92: =VLOOKUP($B$1,'Allocated Expenses'!$B$34:$P$43,6,FALSE)+VLOOKUP($B$1,'Allocated Expenses'!$B$48:$P$57,6,FALSE) -> 241.13352 | H92: =VLOOKUP($B$1,'Allocated Expenses'!$B$34:$P$43,7,FALSE)+VLOOKUP($B$1,'Allocated Expenses'!$B$48:$P$57,7,FALSE) -> 241.13352 | I92: =VLOOKUP($B$1,'Allocated Expenses'!$B$34:$P$43,8,FALSE)+VLOOKUP($B$1,'Allocated Expenses'!$B$48:$P$57,8,FALSE) -> 241.13352 | J92: =VLOOKUP($B$1,'Allocated Expenses'!$B$34:$P$43,9,FALSE)+VLOOKUP($B$1,'Allocated Expenses'!$B$48:$P$57,9,FALSE) -> 241.13352 | K92: =VLOOKUP($B$1,'Allocated Expenses'!$B$34:$P$43,10,FALSE)+VLOOKUP($B$1,'Allocated Expenses'!$B$48:$P$57,10,FALSE) -> 241.13352 | L92: =VLOOKUP($B$1,'Allocated Expenses'!$B$34:$P$43,11,FALSE)+VLOOKUP($B$1,'Allocated Expenses'!$B$48:$P$57,11,FALSE) -> 241.13352 | M92: =VLOOKUP($B$1,'Allocated Expenses'!$B$34:$P$43,12,FALSE)+VLOOKUP($B$1,'Allocated Expenses'!$B$48:$P$57,12,FALSE) -> 241.13352 | N92: =VLOOKUP($B$1,'Allocated Expenses'!$B$34:$P$43,13,FALSE)+VLOOKUP($B$1,'Allocated Expenses'!$B$48:$P$57,13,FALSE) -> 241.13352 | O92: =VLOOKUP($B$1,'Allocated Expenses'!$B$34:$P$43,14,FALSE)+VLOOKUP($B$1,'Allocated Expenses'!$B$48:$P$57,14,FALSE) -> 241.13352 | P92: =VLOOKUP($B$1,'Allocated Expenses'!$B$34:$P$43,15,FALSE)+VLOOKUP($B$1,'Allocated Expenses'!$B$48:$P$57,15,FALSE) -> 241.13352 | Q92: =SUM(E92:P92) -> 2893.6023 | R92: =Q92/$B$4 -> 0.34917368
A94: 8210-8501 | C94: Business Taxes | E94: 0 | F94: 0 | G94: 0 | H94: =1.03*4200 -> 4326 | I94: 0 | J94: 0 | K94: 0 | L94: 0 | M94: 0 | N94: 0 | O94: 0 | P94: 0 | Q94: =SUM(E94:P94) -> 4326 | R94: =Q94/$B$4 -> 0.52202244 | S94: DW | T94: 2025 Business Plan grown 3%
A96: 8310-8501 | C96: Legal & Accounting | E96: =VLOOKUP($B$1,'Allocated Expenses'!$B$62:$P$71,4,FALSE) -> 578.25917 | F96: =VLOOKUP($B$1,'Allocated Expenses'!$B$62:$P$71,5,FALSE) -> 578.25917 | G96: =VLOOKUP($B$1,'Allocated Expenses'!$B$62:$P$71,6,FALSE) -> 578.25917 | H96: =VLOOKUP($B$1,'Allocated Expenses'!$B$62:$P$71,7,FALSE) -> 578.25917 | I96: =VLOOKUP($B$1,'Allocated Expenses'!$B$62:$P$71,8,FALSE) -> 578.25917 | J96: =VLOOKUP($B$1,'Allocated Expenses'!$B$62:$P$71,9,FALSE) -> 578.25917 | K96: =VLOOKUP($B$1,'Allocated Expenses'!$B$62:$P$71,10,FALSE) -> 578.25917 | L96: =VLOOKUP($B$1,'Allocated Expenses'!$B$62:$P$71,11,FALSE) -> 578.25917 | M96: =VLOOKUP($B$1,'Allocated Expenses'!$B$62:$P$71,12,FALSE) -> 578.25917 | N96: =VLOOKUP($B$1,'Allocated Expenses'!$B$62:$P$71,13,FALSE) -> 578.25917 | O96: =VLOOKUP($B$1,'Allocated Expenses'!$B$62:$P$71,14,FALSE) -> 578.25917 | P96: =VLOOKUP($B$1,'Allocated Expenses'!$B$62:$P$71,15,FALSE) -> 578.25917 | Q96: =SUM(E96:P96) -> 6939.11 | R96: =Q96/$B$4 -> 0.83734886
A98: 8190-8501 | D98: Bank Fees | E98: =VLOOKUP($B$1,'Allocated Expenses'!$B$76:$P$85,4,FALSE) -> 0 | F98: =VLOOKUP($B$1,'Allocated Expenses'!$B$76:$P$85,5,FALSE) -> 0 | G98: =VLOOKUP($B$1,'Allocated Expenses'!$B$76:$P$85,6,FALSE) -> 0 | H98: =VLOOKUP($B$1,'Allocated Expenses'!$B$76:$P$85,7,FALSE) -> 0 | I98: =VLOOKUP($B$1,'Allocated Expenses'!$B$76:$P$85,8,FALSE) -> 0 | J98: =VLOOKUP($B$1,'Allocated Expenses'!$B$76:$P$85,9,FALSE) -> 0 | K98: =VLOOKUP($B$1,'Allocated Expenses'!$B$76:$P$85,10,FALSE) -> 0 | L98: =VLOOKUP($B$1,'Allocated Expenses'!$B$76:$P$85,11,FALSE) -> 0 | M98: =VLOOKUP($B$1,'Allocated Expenses'!$B$76:$P$85,12,FALSE) -> 0 | N98: =VLOOKUP($B$1,'Allocated Expenses'!$B$76:$P$85,13,FALSE) -> 0 | O98: =VLOOKUP($B$1,'Allocated Expenses'!$B$76:$P$85,14,FALSE) -> 0 | P98: =VLOOKUP($B$1,'Allocated Expenses'!$B$76:$P$85,15,FALSE) -> 0 | Q98: =SUM(E98:P98) -> 0 | R98: =Q98/$B$4 -> 0
A99: 8930-8501 | D99: Office Supplies | E99: =VLOOKUP($B$1,'Allocated Expenses'!$B$104:$P$113,4,FALSE) -> 0 | F99: =VLOOKUP($B$1,'Allocated Expenses'!$B$104:$P$113,5,FALSE) -> 0 | G99: =VLOOKUP($B$1,'Allocated Expenses'!$B$104:$P$113,6,FALSE) -> 0 | H99: =VLOOKUP($B$1,'Allocated Expenses'!$B$104:$P$113,7,FALSE) -> 0 | I99: =VLOOKUP($B$1,'Allocated Expenses'!$B$104:$P$113,8,FALSE) -> 0 | J99: =VLOOKUP($B$1,'Allocated Expenses'!$B$104:$P$113,9,FALSE) -> 0 | K99: =VLOOKUP($B$1,'Allocated Expenses'!$B$104:$P$113,10,FALSE) -> 0 | L99: =VLOOKUP($B$1,'Allocated Expenses'!$B$104:$P$113,11,FALSE) -> 0 | M99: =VLOOKUP($B$1,'Allocated Expenses'!$B$104:$P$113,12,FALSE) -> 0 | N99: =VLOOKUP($B$1,'Allocated Expenses'!$B$104:$P$113,13,FALSE) -> 0 | O99: =VLOOKUP($B$1,'Allocated Expenses'!$B$104:$P$113,14,FALSE) -> 0 | P99: =VLOOKUP($B$1,'Allocated Expenses'!$B$104:$P$113,15,FALSE) -> 0 | Q99: =SUM(E99:P99) -> 0 | R99: =Q99/$B$4 -> 0
A100: 8950-8501 | D100: Postage | E100: =VLOOKUP($B$1,'Allocated Expenses'!$B$90:$P$99,4,FALSE) -> 0 | F100: =VLOOKUP($B$1,'Allocated Expenses'!$B$90:$P$99,5,FALSE) -> 0 | G100: =VLOOKUP($B$1,'Allocated Expenses'!$B$90:$P$99,6,FALSE) -> 0 | H100: =VLOOKUP($B$1,'Allocated Expenses'!$B$90:$P$99,7,FALSE) -> 0 | I100: =VLOOKUP($B$1,'Allocated Expenses'!$B$90:$P$99,8,FALSE) -> 0 | J100: =VLOOKUP($B$1,'Allocated Expenses'!$B$90:$P$99,9,FALSE) -> 0 | K100: =VLOOKUP($B$1,'Allocated Expenses'!$B$90:$P$99,10,FALSE) -> 0 | L100: =VLOOKUP($B$1,'Allocated Expenses'!$B$90:$P$99,11,FALSE) -> 0 | M100: =VLOOKUP($B$1,'Allocated Expenses'!$B$90:$P$99,12,FALSE) -> 0 | N100: =VLOOKUP($B$1,'Allocated Expenses'!$B$90:$P$99,13,FALSE) -> 0 | O100: =VLOOKUP($B$1,'Allocated Expenses'!$B$90:$P$99,14,FALSE) -> 0 | P100: =VLOOKUP($B$1,'Allocated Expenses'!$B$90:$P$99,15,FALSE) -> 0 | Q100: =SUM(E100:P100) -> 0 | R100: =Q100/$B$4 -> 0
A101: 8990-8501 | D101: Other G&A Expense | Q101: =SUM(E101:P101) -> 0 | R101: =Q101/$B$4 -> 0
A102: 8990-9800 | D102: Other G&A-allocated from LIK | E102: =VLOOKUP($B$1,'Allocated Expenses'!$B$118:$P$127,4,FALSE) -> 24.033333 | F102: =VLOOKUP($B$1,'Allocated Expenses'!$B$118:$P$127,5,FALSE) -> 24.033333 | G102: =VLOOKUP($B$1,'Allocated Expenses'!$B$118:$P$127,6,FALSE) -> 24.033333 | H102: =VLOOKUP($B$1,'Allocated Expenses'!$B$118:$P$127,7,FALSE) -> 24.033333 | I102: =VLOOKUP($B$1,'Allocated Expenses'!$B$118:$P$127,8,FALSE) -> 24.033333 | J102: =VLOOKUP($B$1,'Allocated Expenses'!$B$118:$P$127,9,FALSE) -> 24.033333 | K102: =VLOOKUP($B$1,'Allocated Expenses'!$B$118:$P$127,10,FALSE) -> 24.033333 | L102: =VLOOKUP($B$1,'Allocated Expenses'!$B$118:$P$127,11,FALSE) -> 24.033333 | M102: =VLOOKUP($B$1,'Allocated Expenses'!$B$118:$P$127,12,FALSE) -> 24.033333 | N102: =VLOOKUP($B$1,'Allocated Expenses'!$B$118:$P$127,13,FALSE) -> 24.033333 | O102: =VLOOKUP($B$1,'Allocated Expenses'!$B$118:$P$127,14,FALSE) -> 24.033333 | P102: =VLOOKUP($B$1,'Allocated Expenses'!$B$118:$P$127,15,FALSE) -> 24.033333 | Q102: =SUM(E102:P102) -> 288.4 | R102: =Q102/$B$4 -> 0.034801496
C103: General & Administrative | E103: =SUM(E98:E102) -> 24.033333 | F103: =SUM(F98:F102) -> 24.033333 | G103: =SUM(G98:G102) -> 24.033333 | H103: =SUM(H98:H102) -> 24.033333 | I103: =SUM(I98:I102) -> 24.033333 | J103: =SUM(J98:J102) -> 24.033333 | K103: =SUM(K98:K102) -> 24.033333 | L103: =SUM(L98:L102) -> 24.033333 | ... Q103: =SUM(Q98:Q102) -> 288.4 | R103: =Q103/$B$4 -> 0.034801496
C105: Total Non-Reimbursable Expenses | E105: =+E75+E79+E84+E88+E90+E92+E94+E96+E103 -> 2490.1979 | F105: =+F75+F79+F84+F88+F90+F92+F94+F96+F103 -> 2490.1979 | G105: =+G75+G79+G84+G88+G90+G92+G94+G96+G103 -> 2490.1979 | H105: =+H75+H79+H84+H88+H90+H92+H94+H96+H103 -> 6816.1979 | I105: =+I75+I79+I84+I88+I90+I92+I94+I96+I103 -> 2490.1979 | J105: =+J75+J79+J84+J88+J90+J92+J94+J96+J103 -> 2565.1979 | K105: =+K75+K79+K84+K88+K90+K92+K94+K96+K103 -> 2565.1979 | L105: =+L75+L79+L84+L88+L90+L92+L94+L96+L103 -> 2565.1979 | ... Q105: =+Q75+Q79+Q84+Q88+Q90+Q92+Q94+Q96+Q103 -> 34733.375 | R105: =Q105/$B$4 -> 4.1913086
B108: TOTAL OPERATING EXPENSES | E108: =+E71+E105 -> 10893.661 | F108: =+F71+F105 -> 11374.091 | G108: =+G71+G105 -> 9641.7914 | H108: =+H71+H105 -> 12403.961 | I108: =+I71+I105 -> 9141.9114 | J108: =+J71+J105 -> 8975.2414 | K108: =+K71+K105 -> 7380.1914 | L108: =+L71+L105 -> 8358.5614 | ... Q108: =+Q71+Q105 -> 114959.29 | R108: =Q108/$B$4 -> 13.872244
B111: NET OPERATING INCOME | E111: =+E24-E108 -> -4634.4047 | F111: =+F24-F108 -> -5114.8347 | G111: =+G24-G108 -> -3382.5347 | H111: =+H24-H108 -> -6144.7047 | I111: =+I24-I108 -> -2882.6547 | J111: =+J24-J108 -> -1465.9847 | K111: =+K24-K108 -> 129.06531 | L111: =+L24-L108 -> -849.30469 | ... Q111: =+Q24-Q108 -> -31098.206 | R111: =Q111/$B$4 -> -3.7526495
A113: 1420-0000 | D113: Land Improvements | Q113: =SUM(E113:P113) -> 0 | R113: =Q113/$B$4 -> 0
A114: 1430-0000 | D114: Buildings | H114: =1.03*8500 -> 8755 | Q114: =SUM(E114:P114) -> 8755 | R114: =Q114/$B$4 -> 1.056474 | S114: DW | T114: 2025 Business Plan grown 3%
A115: 1450-0000 | D115: Equipment | Q115: =SUM(E115:P115) -> 0 | R115: =Q115/$B$4 -> 0
A116: 1980-0000 | D116: Capital Improvements | Q116: =SUM(E116:P116) -> 0 | R116: =Q116/$B$4 -> 0
C117: Capital Improvements | E117: =SUM(E113:E116) -> 0 | F117: =SUM(F113:F116) -> 0 | G117: =SUM(G113:G116) -> 0 | H117: =SUM(H113:H116) -> 8755 | I117: =SUM(I113:I116) -> 0 | J117: =SUM(J113:J116) -> 0 | K117: =SUM(K113:K116) -> 0 | L117: =SUM(L113:L116) -> 0 | ... Q117: =SUM(Q113:Q116) -> 8755 | R117: =Q117/$B$4 -> 1.056474
A119: 1440-0000 | C119: Tenant Improvements | E119: ='Renew & Vac '!AJ11 -> 0 | F119: ='Renew & Vac '!AK11 -> 0 | G119: ='Renew & Vac '!AL11 -> 0 | H119: ='Renew & Vac '!AM11 -> 0 | I119: ='Renew & Vac '!AN11 -> 0 | J119: ='Renew & Vac '!AO11 -> 15000 | K119: ='Renew & Vac '!AP11 -> 0 | L119: ='Renew & Vac '!AQ11 -> 0 | ... P119: ='Renew & Vac '!AU11 -> 0 | Q119: =SUM(E119:P119) -> 15000 | R119: =Q119/$B$4 -> 1.810064
A121: 1940-8501 | D121: Deferred Marketing | Q121: =SUM(E121:P121) -> 0 | R121: =Q121/$B$4 -> 0
A122: 1940-8501 | D122: Outside Leasing Commissions | E122: ='Renew & Vac '!AJ12 -> 0 | F122: ='Renew & Vac '!AK12 -> 0 | G122: ='Renew & Vac '!AL12 -> 0 | H122: ='Renew & Vac '!AM12 -> 0 | I122: ='Renew & Vac '!AN12 -> 0 | J122: ='Renew & Vac '!AO12 -> 0 | K122: ='Renew & Vac '!AP12 -> 0 | L122: ='Renew & Vac '!AQ12 -> 0 | ... P122: ='Renew & Vac '!AU12 -> 0 | Q122: =SUM(E122:P122) -> 0 | R122: =Q122/$B$4 -> 0
C123: Outside Leasing Commissions | E123: =SUM(E121:E122) -> 0 | F123: =SUM(F121:F122) -> 0 | G123: =SUM(G121:G122) -> 0 | H123: =SUM(H121:H122) -> 0 | I123: =SUM(I121:I122) -> 0 | J123: =SUM(J121:J122) -> 0 | K123: =SUM(K121:K122) -> 0 | L123: =SUM(L121:L122) -> 0 | ... Q123: =SUM(Q121:Q122) -> 0 | R123: =Q123/$B$4 -> 0
B125: CASH FLOW BEFORE DEBT SERVICE | E125: =+E111-E117-E119-E123 -> -4634.4047 | F125: =+F111-F117-F119-F123 -> -5114.8347 | G125: =+G111-G117-G119-G123 -> -3382.5347 | H125: =+H111-H117-H119-H123 -> -14899.705 | I125: =+I111-I117-I119-I123 -> -2882.6547 | J125: =+J111-J117-J119-J123 -> -16465.985 | K125: =+K111-K117-K119-K123 -> 129.06531 | L125: =+L111-L117-L119-L123 -> -849.30469 | ... Q125: =+Q111-Q117-Q119-Q123 -> -54853.206 | R125: =Q125/$B$4 -> -6.6191874
B127: Debt Service
A128: 9210-8501 | C128: Interest | E128: =VLOOKUP($B$1,'INS RET DEBT'!$C$98:$Q$107,3,FALSE) -> 0 | F128: =VLOOKUP($B$1,'INS RET DEBT'!$C$98:$Q$107,4,FALSE) -> 0 | G128: =VLOOKUP($B$1,'INS RET DEBT'!$C$98:$Q$107,5,FALSE) -> 0 | H128: =VLOOKUP($B$1,'INS RET DEBT'!$C$98:$Q$107,6,FALSE) -> 0 | I128: =VLOOKUP($B$1,'INS RET DEBT'!$C$98:$Q$107,7,FALSE) -> 0 | J128: =VLOOKUP($B$1,'INS RET DEBT'!$C$98:$Q$107,8,FALSE) -> 0 | K128: =VLOOKUP($B$1,'INS RET DEBT'!$C$98:$Q$107,9,FALSE) -> 0 | L128: =VLOOKUP($B$1,'INS RET DEBT'!$C$98:$Q$107,10,FALSE) -> 0 | M128: =VLOOKUP($B$1,'INS RET DEBT'!$C$98:$Q$107,11,FALSE) -> 0 | N128: =VLOOKUP($B$1,'INS RET DEBT'!$C$98:$Q$107,12,FALSE) -> 0 | O128: =VLOOKUP($B$1,'INS RET DEBT'!$C$98:$Q$107,13,FALSE) -> 0 | P128: =VLOOKUP($B$1,'INS RET DEBT'!$C$98:$Q$107,14,FALSE) -> 0 | Q128: =SUM(E128:P128) -> 0 | R128: =Q128/$B$4 -> 0
A129: 2740-8501 | C129: Mortgage Amortization | E129: =VLOOKUP($B$1,'INS RET DEBT'!$C$113:$Q$122,3,FALSE) -> 0 | F129: =VLOOKUP($B$1,'INS RET DEBT'!$C$113:$Q$122,4,FALSE) -> 0 | G129: =VLOOKUP($B$1,'INS RET DEBT'!$C$113:$Q$122,5,FALSE) -> 0 | H129: =VLOOKUP($B$1,'INS RET DEBT'!$C$113:$Q$122,6,FALSE) -> 0 | I129: =VLOOKUP($B$1,'INS RET DEBT'!$C$113:$Q$122,7,FALSE) -> 0 | J129: =VLOOKUP($B$1,'INS RET DEBT'!$C$113:$Q$122,8,FALSE) -> 0 | K129: =VLOOKUP($B$1,'INS RET DEBT'!$C$113:$Q$122,9,FALSE) -> 0 | L129: =VLOOKUP($B$1,'INS RET DEBT'!$C$113:$Q$122,10,FALSE) -> 0 | M129: =VLOOKUP($B$1,'INS RET DEBT'!$C$113:$Q$122,11,FALSE) -> 0 | N129: =VLOOKUP($B$1,'INS RET DEBT'!$C$113:$Q$122,12,FALSE) -> 0 | O129: =VLOOKUP($B$1,'INS RET DEBT'!$C$113:$Q$122,13,FALSE) -> 0 | P129: =VLOOKUP($B$1,'INS RET DEBT'!$C$113:$Q$122,14,FALSE) -> 0 | Q129: =SUM(E129:P129) -> 0 | R129: =Q129/$B$4 -> 0
A130: 2740-0000 | C130: Loan Proceeds | Q130: =SUM(E130:P130) -> 0 | R130: =Q130/$B$4 -> 0
C131: Total Debt Service | E131: =SUM(E128:E130) -> 0 | F131: =SUM(F128:F130) -> 0 | G131: =SUM(G128:G130) -> 0 | H131: =SUM(H128:H130) -> 0 | I131: =SUM(I128:I130) -> 0 | J131: =SUM(J128:J130) -> 0 | K131: =SUM(K128:K130) -> 0 | L131: =SUM(L128:L130) -> 0 | ... Q131: =SUM(Q128:Q130) -> 0 | R131: =Q131/$B$4 -> 0
B134: CASH FLOW AFTER DEBT SERVICE | E134: =+E125-E131 -> -4634.4047 | F134: =+F125-F131 -> -5114.8347 | G134: =+G125-G131 -> -3382.5347 | H134: =+H125-H131 -> -14899.705 | I134: =+I125-I131 -> -2882.6547 | J134: =+J125-J131 -> -16465.985 | K134: =+K125-K131 -> 129.06531 | L134: =+L125-L131 -> -849.30469 | ... Q134: =+Q125-Q131 -> -54853.206 | R134: =Q134/$B$4 -> -6.6191874
B140: Rental Summary by Month
B141: Suite | D141: Tenant | E141: =E161 -> 46023 | F141: =F161 -> 46054 | G141: =G161 -> 46082 | H141: =H161 -> 46113 | I141: =I161 -> 46143 | J141: =J161 -> 46174 | K141: =K161 -> 46204 | L141: =L161 -> 46235 | ... P141: =P161 -> 46357 | Q141: Total
B142: =B162 -> 1100-30 | D142: =IF(D152="None",D162,D152) -> VACANT | E142: =SUMIF($B$152:$B$156,$B142,E$152:E$156)+SUMIF($B$162:$B$166,$B142,E$162:E$166) -> 0 | F142: =SUMIF($B$152:$B$156,$B142,F$152:F$156)+SUMIF($B$162:$B$166,$B142,F$162:F$166) -> 0 | G142: =SUMIF($B$152:$B$156,$B142,G$152:G$156)+SUMIF($B$162:$B$166,$B142,G$162:G$166) -> 0 | H142: =SUMIF($B$152:$B$156,$B142,H$152:H$156)+SUMIF($B$162:$B$166,$B142,H$162:H$166) -> 0 | I142: =SUMIF($B$152:$B$156,$B142,I$152:I$156)+SUMIF($B$162:$B$166,$B142,I$162:I$166) -> 0 | J142: =SUMIF($B$152:$B$156,$B142,J$152:J$156)+SUMIF($B$162:$B$166,$B142,J$162:J$166) -> 0 | K142: =SUMIF($B$152:$B$156,$B142,K$152:K$156)+SUMIF($B$162:$B$166,$B142,K$162:K$166) -> 0 | L142: =SUMIF($B$152:$B$156,$B142,L$152:L$156)+SUMIF($B$162:$B$166,$B142,L$162:L$166) -> 0 | ... P142: =SUMIF($B$152:$B$156,$B142,P$152:P$156)+SUMIF($B$162:$B$166,$B142,P$162:P$166) -> 0 | Q142: =SUM(E142:P142) -> 0
B143: =B163 -> 1100-32 | D143: =IF(D153="None",D163,D153) -> VACANT | E143: =SUMIF($B$152:$B$156,$B143,E$152:E$156)+SUMIF($B$162:$B$166,$B143,E$162:E$166) -> 0 | F143: =SUMIF($B$152:$B$156,$B143,F$152:F$156)+SUMIF($B$162:$B$166,$B143,F$162:F$166) -> 0 | G143: =SUMIF($B$152:$B$156,$B143,G$152:G$156)+SUMIF($B$162:$B$166,$B143,G$162:G$166) -> 0 | H143: =SUMIF($B$152:$B$156,$B143,H$152:H$156)+SUMIF($B$162:$B$166,$B143,H$162:H$166) -> 0 | I143: =SUMIF($B$152:$B$156,$B143,I$152:I$156)+SUMIF($B$162:$B$166,$B143,I$162:I$166) -> 0 | J143: =SUMIF($B$152:$B$156,$B143,J$152:J$156)+SUMIF($B$162:$B$166,$B143,J$162:J$166) -> 1250 | K143: =SUMIF($B$152:$B$156,$B143,K$152:K$156)+SUMIF($B$162:$B$166,$B143,K$162:K$166) -> 1250 | L143: =SUMIF($B$152:$B$156,$B143,L$152:L$156)+SUMIF($B$162:$B$166,$B143,L$162:L$166) -> 1250 | ... P143: =SUMIF($B$152:$B$156,$B143,P$152:P$156)+SUMIF($B$162:$B$166,$B143,P$162:P$166) -> 1250 | Q143: =SUM(E143:P143) -> 8750
B144: =B164 -> 1100-34 | D144: =IF(D154="None",D164,D154) -> Shear Sensation | E144: =SUMIF($B$152:$B$156,$B144,E$152:E$156)+SUMIF($B$162:$B$166,$B144,E$162:E$166) -> 1772.8333 | F144: =SUMIF($B$152:$B$156,$B144,F$152:F$156)+SUMIF($B$162:$B$166,$B144,F$162:F$166) -> 1772.8333 | G144: =SUMIF($B$152:$B$156,$B144,G$152:G$156)+SUMIF($B$162:$B$166,$B144,G$162:G$166) -> 1772.8333 | H144: =SUMIF($B$152:$B$156,$B144,H$152:H$156)+SUMIF($B$162:$B$166,$B144,H$162:H$166) -> 1772.8333 | I144: =SUMIF($B$152:$B$156,$B144,I$152:I$156)+SUMIF($B$162:$B$166,$B144,I$162:I$166) -> 1772.8333 | J144: =SUMIF($B$152:$B$156,$B144,J$152:J$156)+SUMIF($B$162:$B$166,$B144,J$162:J$166) -> 1772.8333 | K144: =SUMIF($B$152:$B$156,$B144,K$152:K$156)+SUMIF($B$162:$B$166,$B144,K$162:K$166) -> 1772.8333 | L144: =SUMIF($B$152:$B$156,$B144,L$152:L$156)+SUMIF($B$162:$B$166,$B144,L$162:L$166) -> 1772.8333 | ... P144: =SUMIF($B$152:$B$156,$B144,P$152:P$156)+SUMIF($B$162:$B$166,$B144,P$162:P$166) -> 1772.8333 | Q144: =SUM(E144:P144) -> 21274
B145: =B165 -> 1100-36 | D145: =IF(D155="None",D165,D155) -> Honest Real Estate | E145: =SUMIF($B$152:$B$156,$B145,E$152:E$156)+SUMIF($B$162:$B$166,$B145,E$162:E$166) -> 1283.3333 | F145: =SUMIF($B$152:$B$156,$B145,F$152:F$156)+SUMIF($B$162:$B$166,$B145,F$162:F$166) -> 1283.3333 | G145: =SUMIF($B$152:$B$156,$B145,G$152:G$156)+SUMIF($B$162:$B$166,$B145,G$162:G$166) -> 1283.3333 | H145: =SUMIF($B$152:$B$156,$B145,H$152:H$156)+SUMIF($B$162:$B$166,$B145,H$162:H$166) -> 1283.3333 | I145: =SUMIF($B$152:$B$156,$B145,I$152:I$156)+SUMIF($B$162:$B$166,$B145,I$162:I$166) -> 1283.3333 | J145: =SUMIF($B$152:$B$156,$B145,J$152:J$156)+SUMIF($B$162:$B$166,$B145,J$162:J$166) -> 1283.3333 | K145: =SUMIF($B$152:$B$156,$B145,K$152:K$156)+SUMIF($B$162:$B$166,$B145,K$162:K$166) -> 1283.3333 | L145: =SUMIF($B$152:$B$156,$B145,L$152:L$156)+SUMIF($B$162:$B$166,$B145,L$162:L$166) -> 1283.3333 | ... P145: =SUMIF($B$152:$B$156,$B145,P$152:P$156)+SUMIF($B$162:$B$166,$B145,P$162:P$166) -> 1283.3333 | Q145: =SUM(E145:P145) -> 15400
B146: =B166 -> 1100-12330 | D146: =IF(D156="None",D166,D156) -> None | E146: =SUMIF($B$152:$B$156,$B146,E$152:E$156)+SUMIF($B$162:$B$166,$B146,E$162:E$166) -> 0 | F146: =SUMIF($B$152:$B$156,$B146,F$152:F$156)+SUMIF($B$162:$B$166,$B146,F$162:F$166) -> 0 | G146: =SUMIF($B$152:$B$156,$B146,G$152:G$156)+SUMIF($B$162:$B$166,$B146,G$162:G$166) -> 0 | H146: =SUMIF($B$152:$B$156,$B146,H$152:H$156)+SUMIF($B$162:$B$166,$B146,H$162:H$166) -> 0 | I146: =SUMIF($B$152:$B$156,$B146,I$152:I$156)+SUMIF($B$162:$B$166,$B146,I$162:I$166) -> 0 | J146: =SUMIF($B$152:$B$156,$B146,J$152:J$156)+SUMIF($B$162:$B$166,$B146,J$162:J$166) -> 0 | K146: =SUMIF($B$152:$B$156,$B146,K$152:K$156)+SUMIF($B$162:$B$166,$B146,K$162:K$166) -> 0 | L146: =SUMIF($B$152:$B$156,$B146,L$152:L$156)+SUMIF($B$162:$B$166,$B146,L$162:L$166) -> 0 | ... P146: =SUMIF($B$152:$B$156,$B146,P$152:P$156)+SUMIF($B$162:$B$166,$B146,P$162:P$166) -> 0 | Q146: =SUM(E146:P146) -> 0
...

Sheet 1500
B1: 1500 | C1: - Eastwick JV I | J1: =+'All Shopping Centers'!J1 -> Operating Budget | Q1: ='All Shopping Centers'!Q1 -> 46023
J2: ='All Shopping Centers'!J2&" - "&B1 -> Shopping Centers - 1500
B4: 2280 | E4: Jan | F4: Feb | G4: Mar | H4: Apr | I4: May | J4: Jun | K4: Jul | L4: Aug | M4: Sep | N4: Oct | O4: Nov | P4: Dec | Q4: Total | R4: Total PSF | S4: Input | T4: Notes
D6: Occupancy % | E6: ='Renew & Vac '!AJ31 -> 1 | F6: ='Renew & Vac '!AK31 -> 1 | G6: ='Renew & Vac '!AL31 -> 1 | H6: ='Renew & Vac '!AM31 -> 1 | I6: ='Renew & Vac '!AN31 -> 1 | J6: ='Renew & Vac '!AO31 -> 1 | K6: ='Renew & Vac '!AP31 -> 1 | L6: ='Renew & Vac '!AQ31 -> 1 | ... P6: ='Renew & Vac '!AU31 -> 1
D7: Occupancy SF | E7: =$B$4*E6 -> 2280 | F7: =$B$4*F6 -> 2280 | G7: =$B$4*G6 -> 2280 | H7: =$B$4*H6 -> 2280 | I7: =$B$4*I6 -> 2280 | J7: =$B$4*J6 -> 2280 | K7: =$B$4*K6 -> 2280 | L7: =$B$4*L6 -> 2280 | ... P7: =$B$4*P6 -> 2280
B8: Revenues
A10: 4230-8501 | C10: Rental Income - In Place | E10: =SUMIFS('In Place Revenue'!$G:$G,'In Place Revenue'!$A:$A,$B$1,'In Place Revenue'!$H:$H,1) -> 0 | F10: =SUMIFS('In Place Revenue'!$G:$G,'In Place Revenue'!$A:$A,$B$1,'In Place Revenue'!$H:$H,2) -> 0 | G10: =SUMIFS('In Place Revenue'!$G:$G,'In Place Revenue'!$A:$A,$B$1,'In Place Revenue'!$H:$H,3) -> 0 | H10: =SUMIFS('In Place Revenue'!$G:$G,'In Place Revenue'!$A:$A,$B$1,'In Place Revenue'!$H:$H,4) -> 0 | I10: =SUMIFS('In Place Revenue'!$G:$G,'In Place Revenue'!$A:$A,$B$1,'In Place Revenue'!$H:$H,5) -> 0 | J10: =SUMIFS('In Place Revenue'!$G:$G,'In Place Revenue'!$A:$A,$B$1,'In Place Revenue'!$H:$H,6) -> 0 | K10: =SUMIFS('In Place Revenue'!$G:$G,'In Place Revenue'!$A:$A,$B$1,'In Place Revenue'!$H:$H,7) -> 0 | L10: =SUMIFS('In Place Revenue'!$G:$G,'In Place Revenue'!$A:$A,$B$1,'In Place Revenue'!$H:$H,8) -> 0 | M10: =SUMIFS('In Place Revenue'!$G:$G,'In Place Revenue'!$A:$A,$B$1,'In Place Revenue'!$H:$H,9) -> 0 | N10: =SUMIFS('In Place Revenue'!$G:$G,'In Place Revenue'!$A:$A,$B$1,'In Place Revenue'!$H:$H,10) -> 0 | O10: =SUMIFS('In Place Revenue'!$G:$G,'In Place Revenue'!$A:$A,$B$1,'In Place Revenue'!$H:$H,11) -> 0 | P10: =SUMIFS('In Place Revenue'!$G:$G,'In Place Revenue'!$A:$A,$B$1,'In Place Revenue'!$H:$H,12) -> 0 | Q10: =SUM(E10:P10) -> 0 | R10: =Q10/$B$4 -> 0
A11: 4230-8501 | C11: Rental Income - New & Renewal | E11: ='Renew & Vac '!AJ32 -> 0 | F11: ='Renew & Vac '!AK32 -> 0 | G11: ='Renew & Vac '!AL32 -> 0 | H11: ='Renew & Vac '!AM32 -> 0 | I11: ='Renew & Vac '!AN32 -> 0 | J11: ='Renew & Vac '!AO32 -> 0 | K11: ='Renew & Vac '!AP32 -> 0 | L11: ='Renew & Vac '!AQ32 -> 0 | ... P11: ='Renew & Vac '!AU32 -> 0 | Q11: =SUM(E11:P11) -> 0 | R11: =Q11/$B$4 -> 0
A12: 4240-8501 | C12: Percentage Rent | Q12: =SUM(E12:P12) -> 0 | R12: =Q12/$B$4 -> 0
A13: 4990-8501 | C13: Miscellaneous | Q13: =SUM(E13:P13) -> 0 | R13: =Q13/$B$4 -> 0
A14: 9190-8501 | C14: Interest Income | Q14: =SUM(E14:P14) -> 0 | R14: =Q14/$B$4 -> 0
C15: Total Rental and Other | E15: =SUM(E10:E14) -> 0 | F15: =SUM(F10:F14) -> 0 | G15: =SUM(G10:G14) -> 0 | H15: =SUM(H10:H14) -> 0 | I15: =SUM(I10:I14) -> 0 | J15: =SUM(J10:J14) -> 0 | K15: =SUM(K10:K14) -> 0 | L15: =SUM(L10:L14) -> 0 | ... Q15: =SUM(Q10:Q14) -> 0 | R15: =Q15/$B$4 -> 0
B17: Reimbursements
A18: 4710-8502 | C18: Electric | Q18: =SUM(E18:P18) -> 0 | R18: =Q18/$B$4 -> 0
A19: 4910-8502 | C19: Common Area Maintenance | E19: =+'Tenant Recoveries'!F26 -> 0 | F19: =+E19 -> 0 | G19: =+F19 -> 0 | H19: =+G19 -> 0 | I19: =+H19 -> 0 | J19: =+I19 -> 0 | K19: =+J19 -> 0 | L19: =+K19 -> 0 | M19: =+L19 -> 0 | ... P19: =+O19 -> 0 | Q19: =SUM(E19:P19) -> 0 | R19: =Q19/$B$4 -> 0
A20: 4920-8502 | C20: Real Estate Taxes | E20: =+'Tenant Recoveries'!F27 -> 0 | F20: =+E20 -> 0 | G20: =+F20 -> 0 | H20: =+G20 -> 0 | I20: =+H20 -> 0 | J20: =+I20 -> 0 | K20: =+J20 -> 0 | L20: =+K20 -> 0 | M20: =+L20 -> 0 | ... P20: =+O20 -> 0 | Q20: =SUM(E20:P20) -> 0 | R20: =Q20/$B$4 -> 0
A21: 4930-8502 | C21: Insurance | Q21: =SUM(E21:P21) -> 0 | R21: =Q21/$B$4 -> 0
C22: Total Reimbursements | E22: =SUM(E18:E21) -> 0 | F22: =SUM(F18:F21) -> 0 | G22: =SUM(G18:G21) -> 0 | H22: =SUM(H18:H21) -> 0 | I22: =SUM(I18:I21) -> 0 | J22: =SUM(J18:J21) -> 0 | K22: =SUM(K18:K21) -> 0 | L22: =SUM(L18:L21) -> 0 | ... Q22: =SUM(Q18:Q21) -> 0 | R22: =Q22/$B$4 -> 0
R23: =Q23/$B$4 -> 0
B24: TOTAL REVENUES | E24: =+E15+E22 -> 0 | F24: =+F15+F22 -> 0 | G24: =+G15+G22 -> 0 | H24: =+H15+H22 -> 0 | I24: =+I15+I22 -> 0 | J24: =+J15+J22 -> 0 | K24: =+K15+K22 -> 0 | L24: =+L15+L22 -> 0 | ... Q24: =+Q15+Q22 -> 0 | R24: =Q24/$B$4 -> 0
B26: Reimbursable Expenses
A27: 6030-8502 | C27: Maintenance Salaries | E27: =VLOOKUP($B$1,'Allocated Expenses'!$B$6:$P$15,4,FALSE) -> 70.208331 | F27: =VLOOKUP($B$1,'Allocated Expenses'!$B$6:$P$15,5,FALSE) -> 70.208331 | G27: =VLOOKUP($B$1,'Allocated Expenses'!$B$6:$P$15,6,FALSE) -> 70.208331 | H27: =VLOOKUP($B$1,'Allocated Expenses'!$B$6:$P$15,7,FALSE) -> 70.208331 | I27: =VLOOKUP($B$1,'Allocated Expenses'!$B$6:$P$15,8,FALSE) -> 70.208331 | J27: =VLOOKUP($B$1,'Allocated Expenses'!$B$6:$P$15,9,FALSE) -> 70.208331 | K27: =VLOOKUP($B$1,'Allocated Expenses'!$B$6:$P$15,10,FALSE) -> 70.208331 | L27: =VLOOKUP($B$1,'Allocated Expenses'!$B$6:$P$15,11,FALSE) -> 70.208331 | M27: =VLOOKUP($B$1,'Allocated Expenses'!$B$6:$P$15,12,FALSE) -> 70.208331 | N27: =VLOOKUP($B$1,'Allocated Expenses'!$B$6:$P$15,13,FALSE) -> 70.208331 | O27: =VLOOKUP($B$1,'Allocated Expenses'!$B$6:$P$15,14,FALSE) -> 70.208331 | P27: =VLOOKUP($B$1,'Allocated Expenses'!$B$6:$P$15,15,FALSE) -> 70.208331 | Q27: =SUM(E27:P27) -> 842.49997 | R27: =Q27/$B$4 -> 0.36951753
A29: 6120-8502 | C29: Electric | Q29: =SUM(E29:P29) -> 0 | R29: =Q29/$B$4 -> 0
A31: 6130-8502 | C31: Water & Sewer | Q31: =SUM(E31:P31) -> 0 | R31: =Q31/$B$4 -> 0
D33: Building Maint.-Contractual | E33: ='Building Maint'!C21 -> 0 | F33: ='Building Maint'!D21 -> 0 | G33: ='Building Maint'!E21 -> 0 | H33: ='Building Maint'!F21 -> 0 | I33: ='Building Maint'!G21 -> 0 | J33: ='Building Maint'!H21 -> 0 | K33: ='Building Maint'!I21 -> 0 | L33: ='Building Maint'!J21 -> 0 | ... P33: ='Building Maint'!N21 -> 0 | Q33: =SUM(E33:P33) -> 0 | R33: =Q33/$B$4 -> 0
D34: Building Maint.-Recurring | E34: ='Building Maint'!C7 -> 0 | F34: ='Building Maint'!D7 -> 0 | G34: ='Building Maint'!E7 -> 0 | H34: ='Building Maint'!F7 -> 0 | I34: ='Building Maint'!G7 -> 0 | J34: ='Building Maint'!H7 -> 0 | K34: ='Building Maint'!I7 -> 0 | L34: ='Building Maint'!J7 -> 0 | ... P34: ='Building Maint'!N7 -> 0 | Q34: =SUM(E34:P34) -> 0 | R34: =Q34/$B$4 -> 0
D35: Building Maint.-Big Projects | Q35: =SUM(E35:P35) -> 0 | R35: =Q35/$B$4 -> 0
A36: 6220-8502 | C36: Building Maintenance | E36: =SUM(E33:E35) -> 0 | F36: =SUM(F33:F35) -> 0 | G36: =SUM(G33:G35) -> 0 | H36: =SUM(H33:H35) -> 0 | I36: =SUM(I33:I35) -> 0 | J36: =SUM(J33:J35) -> 0 | K36: =SUM(K33:K35) -> 0 | L36: =SUM(L33:L35) -> 0 | ... Q36: =SUM(Q33:Q35) -> 0 | R36: =Q36/$B$4 -> 0
A38: 6330-8502 | B38: (SC) | C38: Parking Lot Cleaning | Q38: =SUM(E38:P38) -> 0 | R38: =Q38/$B$4 -> 0
D40: Parking Lot Maint.-Contractual | Q40: =SUM(E40:P40) -> 0 | R40: =Q40/$B$4 -> 0
D41: Parking Lot Maint.-Recurring | Q41: =SUM(E41:P41) -> 0 | R41: =Q41/$B$4 -> 0
D42: Parking Lot Maint.-Big Projects | Q42: =SUM(E42:P42) -> 0 | R42: =Q42/$B$4 -> 0
A43: 6360-8502 | C43: Parking Lot Maintenance | E43: =SUM(E40:E42) -> 0 | F43: =SUM(F40:F42) -> 0 | G43: =SUM(G40:G42) -> 0 | H43: =SUM(H40:H42) -> 0 | I43: =SUM(I40:I42) -> 0 | J43: =SUM(J40:J42) -> 0 | K43: =SUM(K40:K42) -> 0 | L43: =SUM(L40:L42) -> 0 | ... Q43: =SUM(Q40:Q42) -> 0 | R43: =Q43/$B$4 -> 0
A45: 6370-8502 | C45: Snow Removal | Q45: =SUM(E45:P45) -> 0 | R45: =Q45/$B$4 -> 0
Q46: =SUM(E46:P46) -> 0
D47: Landscaping-Contractual | Q47: =SUM(E47:P47) -> 0 | R47: =Q47/$B$4 -> 0
D48: Landscaping-Recurring | Q48: =SUM(E48:P48) -> 0 | R48: =Q48/$B$4 -> 0
D49: Landscaping-Big Projects | Q49: =SUM(E49:P49) -> 0 | R49: =Q49/$B$4 -> 0
A50: 6380-8502 | C50: Landscaping | E50: =SUM(E47:E49) -> 0 | F50: =SUM(F47:F49) -> 0 | G50: =SUM(G47:G49) -> 0 | H50: =SUM(H47:H49) -> 0 | I50: =SUM(I47:I49) -> 0 | J50: =SUM(J47:J49) -> 0 | K50: =SUM(K47:K49) -> 0 | L50: =SUM(L47:L49) -> 0 | ... Q50: =SUM(Q47:Q49) -> 0 | R50: =Q50/$B$4 -> 0
A52: 6350-8502 | C52: Security | Q52: =SUM(E52:P52) -> 0 | R52: =Q52/$B$4 -> 0
A54: 6610-8502 | B54: (BP) | C54: Management Fee | Q54: =SUM(E54:P54) -> 0 | R54: =Q54/$B$4 -> 0
A56: 6270-8502 | C56: Trash Removal | Q56: =SUM(E56:P56) -> 0 | R56: =Q56/$B$4 -> 0
A58: 6410-8502 | C58: Real Estate Taxes | E58: =+'INS RET DEBT'!E82 -> 721.618 | F58: =+'INS RET DEBT'!F82 -> 721.618 | G58: =+'INS RET DEBT'!G82 -> 721.618 | H58: =+'INS RET DEBT'!H82 -> 721.618 | I58: =+'INS RET DEBT'!I82 -> 721.618 | J58: =+'INS RET DEBT'!J82 -> 721.618 | K58: =+'INS RET DEBT'!K82 -> 721.618 | L58: =+'INS RET DEBT'!L82 -> 721.618 | ... P58: =+'INS RET DEBT'!P82 -> 721.618 | Q58: =SUM(E58:P58) -> 8659.416 | R58: =Q58/$B$4 -> 3.7979895
D60: Insurance-Liability | E60: =+'INS RET DEBT'!E13+'INS RET DEBT'!E14 -> 52 | F60: =+'INS RET DEBT'!F13+'INS RET DEBT'!F14 -> 52 | G60: =+'INS RET DEBT'!G13+'INS RET DEBT'!G14 -> 52 | H60: =+'INS RET DEBT'!H13+'INS RET DEBT'!H14 -> 52 | I60: =+'INS RET DEBT'!I13+'INS RET DEBT'!I14 -> 52 | J60: =+'INS RET DEBT'!J13+'INS RET DEBT'!J14 -> 52 | K60: =+'INS RET DEBT'!K13+'INS RET DEBT'!K14 -> 52 | L60: =+'INS RET DEBT'!L13+'INS RET DEBT'!L14 -> 52 | ... P60: =+'INS RET DEBT'!P13+'INS RET DEBT'!P14 -> 53.04 | Q60: =SUM(E60:P60) -> 626.08 | R60: =Q60/$B$4 -> 0.27459649
D61: Insurance-Property | E61: =+'INS RET DEBT'!E16 -> 28 | F61: =+'INS RET DEBT'!F16 -> 28 | G61: =+'INS RET DEBT'!G16 -> 28 | H61: =+'INS RET DEBT'!H16 -> 28 | I61: =+'INS RET DEBT'!I16 -> 28 | J61: =+'INS RET DEBT'!J16 -> 28 | K61: =+'INS RET DEBT'!K16 -> 28 | L61: =+'INS RET DEBT'!L16 -> 28 | ... P61: =+'INS RET DEBT'!P16 -> 28.56 | Q61: =SUM(E61:P61) -> 337.12 | R61: =Q61/$B$4 -> 0.14785965
D62: Insurance-Other | E62: =+'INS RET DEBT'!E17 -> 0 | F62: =+'INS RET DEBT'!F17 -> 0 | G62: =+'INS RET DEBT'!G17 -> 0 | H62: =+'INS RET DEBT'!H17 -> 0 | I62: =+'INS RET DEBT'!I17 -> 0 | J62: =+'INS RET DEBT'!J17 -> 0 | K62: =+'INS RET DEBT'!K17 -> 0 | L62: =+'INS RET DEBT'!L17 -> 0 | ... P62: =+'INS RET DEBT'!P17 -> 0 | Q62: =SUM(E62:P62) -> 0 | R62: =Q62/$B$4 -> 0
A63: 6510-8502 | C63: Insurance | E63: =SUM(E60:E62) -> 80 | F63: =SUM(F60:F62) -> 80 | G63: =SUM(G60:G62) -> 80 | H63: =SUM(H60:H62) -> 80 | I63: =SUM(I60:I62) -> 80 | J63: =SUM(J60:J62) -> 80 | K63: =SUM(K60:K62) -> 80 | L63: =SUM(L60:L62) -> 80 | ... Q63: =SUM(Q60:Q62) -> 963.2 | R63: =Q63/$B$4 -> 0.42245614
D65: Cleaning & Supplies | Q65: =SUM(E65:P65) -> 0 | R65: =Q65/$B$4 -> 0
D66: Cleaning & Supplies-Vacancies | Q66: =SUM(E66:P66) -> 0 | R66: =Q66/$B$4 -> 0
A67: 6250-8502 | B67: (BP) | C67: Cleaning & Supplies | E67: =SUM(E65:E66) -> 0 | F67: =SUM(F65:F66) -> 0 | G67: =SUM(G65:G66) -> 0 | H67: =SUM(H65:H66) -> 0 | I67: =SUM(I65:I66) -> 0 | J67: =SUM(J65:J66) -> 0 | K67: =SUM(K65:K66) -> 0 | L67: =SUM(L65:L66) -> 0 | ... Q67: =SUM(Q65:Q66) -> 0 | R67: =Q67/$B$4 -> 0
B69: (SC) | C69: Other | Q69: =SUM(E69:P69) -> 0 | R69: =Q69/$B$4 -> 0
C71: Total Reimbursable Expenses | E71: =+E27+E29+E31+E36+E38+E43+E45+E50+E52+E54+E56+E58+E63+E67+E69 -> 871.82633 | F71: =+F27+F29+F31+F36+F38+F43+F45+F50+F52+F54+F56+F58+F63+F67+F69 -> 871.82633 | G71: =+G27+G29+G31+G36+G38+G43+G45+G50+G52+G54+G56+G58+G63+G67+G69 -> 871.82633 | H71: =+H27+H29+H31+H36+H38+H43+H45+H50+H52+H54+H56+H58+H63+H67+H69 -> 871.82633 | I71: =+I27+I29+I31+I36+I38+I43+I45+I50+I52+I54+I56+I58+I63+I67+I69 -> 871.82633 | J71: =+J27+J29+J31+J36+J38+J43+J45+J50+J52+J54+J56+J58+J63+J67+J69 -> 871.82633 | K71: =+K27+K29+K31+K36+K38+K43+K45+K50+K52+K54+K56+K58+K63+K67+K69 -> 871.82633 | L71: =+L27+L29+L31+L36+L38+L43+L45+L50+L52+L54+L56+L58+L63+L67+L69 -> 871.82633 | ... Q71: =+Q27+Q29+Q31+Q36+Q38+Q43+Q45+Q50+Q52+Q54+Q56+Q58+Q63+Q67+Q69 -> 10465.116 | R71: =Q71/$B$4 -> 4.5899631
B73: Non-Reimbursable Expenses | R73: =Q73/$B$4 -> 0
A75: 5210-8501 | C75: Bad Debt | Q75: =SUM(E75:P75) -> 0 | R75: =Q75/$B$4 -> 0
A77: 6010-8501 | D77: Salaries & Wages | E77: =VLOOKUP($B$1,'Allocated Expenses'!$B$20:$P$29,4,FALSE) -> 169.5547 | F77: =VLOOKUP($B$1,'Allocated Expenses'!$B$20:$P$29,5,FALSE) -> 169.5547 | G77: =VLOOKUP($B$1,'Allocated Expenses'!$B$20:$P$29,6,FALSE) -> 169.5547 | H77: =VLOOKUP($B$1,'Allocated Expenses'!$B$20:$P$29,7,FALSE) -> 169.5547 | I77: =VLOOKUP($B$1,'Allocated Expenses'!$B$20:$P$29,8,FALSE) -> 169.5547 | J77: =VLOOKUP($B$1,'Allocated Expenses'!$B$20:$P$29,9,FALSE) -> 169.5547 | K77: =VLOOKUP($B$1,'Allocated Expenses'!$B$20:$P$29,10,FALSE) -> 169.5547 | L77: =VLOOKUP($B$1,'Allocated Expenses'!$B$20:$P$29,11,FALSE) -> 169.5547 | M77: =VLOOKUP($B$1,'Allocated Expenses'!$B$20:$P$29,12,FALSE) -> 169.5547 | N77: =VLOOKUP($B$1,'Allocated Expenses'!$B$20:$P$29,13,FALSE) -> 169.5547 | O77: =VLOOKUP($B$1,'Allocated Expenses'!$B$20:$P$29,14,FALSE) -> 169.5547 | P77: =VLOOKUP($B$1,'Allocated Expenses'!$B$20:$P$29,15,FALSE) -> 169.5547 | Q77: =SUM(E77:P77) -> 2034.6564 | R77: =Q77/$B$4 -> 0.89239317
A78: 6620-8501 | D78: Commissions-Internal Broker | E78: =VLOOKUP($B$1,'Allocated Expenses'!$B$132:$P$141,4,FALSE) -> 0 | F78: =VLOOKUP($B$1,'Allocated Expenses'!$B$132:$P$141,5,FALSE) -> 0 | G78: =VLOOKUP($B$1,'Allocated Expenses'!$B$132:$P$141,6,FALSE) -> 0 | H78: =VLOOKUP($B$1,'Allocated Expenses'!$B$132:$P$141,7,FALSE) -> 0 | I78: =VLOOKUP($B$1,'Allocated Expenses'!$B$132:$P$141,8,FALSE) -> 0 | J78: =VLOOKUP($B$1,'Allocated Expenses'!$B$132:$P$141,9,FALSE) -> 0 | K78: =VLOOKUP($B$1,'Allocated Expenses'!$B$132:$P$141,10,FALSE) -> 0 | L78: =VLOOKUP($B$1,'Allocated Expenses'!$B$132:$P$141,11,FALSE) -> 0 | M78: =VLOOKUP($B$1,'Allocated Expenses'!$B$132:$P$141,12,FALSE) -> 0 | N78: =VLOOKUP($B$1,'Allocated Expenses'!$B$132:$P$141,13,FALSE) -> 0 | O78: =VLOOKUP($B$1,'Allocated Expenses'!$B$132:$P$141,14,FALSE) -> 0 | P78: =VLOOKUP($B$1,'Allocated Expenses'!$B$132:$P$141,15,FALSE) -> 0 | Q78: =SUM(E78:P78) -> 0 | R78: =Q78/$B$4 -> 0
C79: Leasing Salaries and Commissions | E79: =SUM(E77:E78) -> 169.5547 | F79: =SUM(F77:F78) -> 169.5547 | G79: =SUM(G77:G78) -> 169.5547 | H79: =SUM(H77:H78) -> 169.5547 | I79: =SUM(I77:I78) -> 169.5547 | J79: =SUM(J77:J78) -> 169.5547 | K79: =SUM(K77:K78) -> 169.5547 | L79: =SUM(L77:L78) -> 169.5547 | ... Q79: =SUM(Q77:Q78) -> 2034.6564 | R79: =Q79/$B$4 -> 0.89239317
A81: 6110-8501 | D81: Gas | Q81: =SUM(E81:P81) -> 0 | R81: =Q81/$B$4 -> 0
A82: 6120-8501 | D82: Electric | E82: =1.03*300 -> 309 | F82: =1.03*300 -> 309 | Q82: =SUM(E82:P82) -> 618 | R82: =Q82/$B$4 -> 0.27105263 | S82: DW | T82: 2025 Business Plan grown 3%
A83: 6130-8501 | D83: Water & Sewer | Q83: =SUM(E83:P83) -> 0 | R83: =Q83/$B$4 -> 0
C84: Utilities | E84: =SUM(E81:E83) -> 309 | F84: =SUM(F81:F83) -> 309 | G84: =SUM(G81:G83) -> 0 | H84: =SUM(H81:H83) -> 0 | I84: =SUM(I81:I83) -> 0 | J84: =SUM(J81:J83) -> 0 | K84: =SUM(K81:K83) -> 0 | L84: =SUM(L81:L83) -> 0 | ... Q84: =SUM(Q81:Q83) -> 618 | R84: =Q84/$B$4 -> 0.27105263
D86: Building Maint.-Recurring | Q86: =SUM(E86:P86) -> 0 | R86: =Q86/$B$4 -> 0
D87: Building Maint.-Big Projects | Q87: =SUM(E87:P87) -> 0 | R87: =Q87/$B$4 -> 0
A88: 6220-8501 | C88: Building Maintenance | E88: =SUM(E86:E87) -> 0 | F88: =SUM(F86:F87) -> 0 | G88: =SUM(G86:G87) -> 0 | H88: =SUM(H86:H87) -> 0 | I88: =SUM(I86:I87) -> 0 | J88: =SUM(J86:J87) -> 0 | K88: =SUM(K86:K87) -> 0 | L88: =SUM(L86:L87) -> 0 | ... Q88: =SUM(Q86:Q87) -> 0 | R88: =Q88/$B$4 -> 0
A90: 6610-8501 | B90: (SC) | C90: Management fee | E90: =ROUND(E$24*0.06,0) -> 0 | F90: =ROUND(F$24*0.06,0) -> 0 | G90: =ROUND(G$24*0.06,0) -> 0 | H90: =ROUND(H$24*0.06,0) -> 0 | I90: =ROUND(I$24*0.06,0) -> 0 | J90: =ROUND(J$24*0.06,0) -> 0 | K90: =ROUND(K$24*0.06,0) -> 0 | L90: =ROUND(L$24*0.06,0) -> 0 | ... P90: =ROUND(P$24*0.06,0) -> 0 | Q90: =SUM(E90:P90) -> 0 | R90: =Q90/$B$4 -> 0
A92: 7110-8501 | C92: Marketing | E92: =VLOOKUP($B$1,'Allocated Expenses'!$B$34:$P$43,4,FALSE)+VLOOKUP($B$1,'Allocated Expenses'!$B$48:$P$57,4,FALSE) -> 54.735458 | F92: =VLOOKUP($B$1,'Allocated Expenses'!$B$34:$P$43,5,FALSE)+VLOOKUP($B$1,'Allocated Expenses'!$B$48:$P$57,5,FALSE) -> 54.735458 | G92: =VLOOKUP($B$1,'Allocated Expenses'!$B$34:$P$43,6,FALSE)+VLOOKUP($B$1,'Allocated Expenses'!$B$48:$P$57,6,FALSE) -> 54.735458 | H92: =VLOOKUP($B$1,'Allocated Expenses'!$B$34:$P$43,7,FALSE)+VLOOKUP($B$1,'Allocated Expenses'!$B$48:$P$57,7,FALSE) -> 54.735458 | I92: =VLOOKUP($B$1,'Allocated Expenses'!$B$34:$P$43,8,FALSE)+VLOOKUP($B$1,'Allocated Expenses'!$B$48:$P$57,8,FALSE) -> 54.735458 | J92: =VLOOKUP($B$1,'Allocated Expenses'!$B$34:$P$43,9,FALSE)+VLOOKUP($B$1,'Allocated Expenses'!$B$48:$P$57,9,FALSE) -> 54.735458 | K92: =VLOOKUP($B$1,'Allocated Expenses'!$B$34:$P$43,10,FALSE)+VLOOKUP($B$1,'Allocated Expenses'!$B$48:$P$57,10,FALSE) -> 54.735458 | L92: =VLOOKUP($B$1,'Allocated Expenses'!$B$34:$P$43,11,FALSE)+VLOOKUP($B$1,'Allocated Expenses'!$B$48:$P$57,11,FALSE) -> 54.735458 | M92: =VLOOKUP($B$1,'Allocated Expenses'!$B$34:$P$43,12,FALSE)+VLOOKUP($B$1,'Allocated Expenses'!$B$48:$P$57,12,FALSE) -> 54.735458 | N92: =VLOOKUP($B$1,'Allocated Expenses'!$B$34:$P$43,13,FALSE)+VLOOKUP($B$1,'Allocated Expenses'!$B$48:$P$57,13,FALSE) -> 54.735458 | O92: =VLOOKUP($B$1,'Allocated Expenses'!$B$34:$P$43,14,FALSE)+VLOOKUP($B$1,'Allocated Expenses'!$B$48:$P$57,14,FALSE) -> 54.735458 | P92: =VLOOKUP($B$1,'Allocated Expenses'!$B$34:$P$43,15,FALSE)+VLOOKUP($B$1,'Allocated Expenses'!$B$48:$P$57,15,FALSE) -> 54.735458 | Q92: =SUM(E92:P92) -> 656.82549 | R92: =Q92/$B$4 -> 0.28808136
A94: 8210-8501 | C94: Business Taxes | E94: 0 | F94: 0 | G94: 0 | H94: =1.03*1500 -> 1545 | I94: 0 | J94: 0 | K94: 0 | L94: 0 | M94: 0 | N94: 0 | O94: 0 | P94: 0 | Q94: =SUM(E94:P94) -> 1545 | R94: =Q94/$B$4 -> 0.67763158 | S94: DW | T94: 2025 Business Plan grown 3%
A96: 8310-8501 | C96: Legal & Accounting | E96: =VLOOKUP($B$1,'Allocated Expenses'!$B$62:$P$71,4,FALSE) -> 229.175 | F96: =VLOOKUP($B$1,'Allocated Expenses'!$B$62:$P$71,5,FALSE) -> 229.175 | G96: =VLOOKUP($B$1,'Allocated Expenses'!$B$62:$P$71,6,FALSE) -> 229.175 | H96: =VLOOKUP($B$1,'Allocated Expenses'!$B$62:$P$71,7,FALSE) -> 229.175 | I96: =VLOOKUP($B$1,'Allocated Expenses'!$B$62:$P$71,8,FALSE) -> 229.175 | J96: =VLOOKUP($B$1,'Allocated Expenses'!$B$62:$P$71,9,FALSE) -> 229.175 | K96: =VLOOKUP($B$1,'Allocated Expenses'!$B$62:$P$71,10,FALSE) -> 229.175 | L96: =VLOOKUP($B$1,'Allocated Expenses'!$B$62:$P$71,11,FALSE) -> 229.175 | M96: =VLOOKUP($B$1,'Allocated Expenses'!$B$62:$P$71,12,FALSE) -> 229.175 | N96: =VLOOKUP($B$1,'Allocated Expenses'!$B$62:$P$71,13,FALSE) -> 229.175 | O96: =VLOOKUP($B$1,'Allocated Expenses'!$B$62:$P$71,14,FALSE) -> 229.175 | P96: =VLOOKUP($B$1,'Allocated Expenses'!$B$62:$P$71,15,FALSE) -> 229.175 | Q96: =SUM(E96:P96) -> 2750.1 | R96: =Q96/$B$4 -> 1.2061842
A98: 8190-8501 | D98: Bank Fees | E98: =VLOOKUP($B$1,'Allocated Expenses'!$B$76:$P$85,4,FALSE) -> 0 | F98: =VLOOKUP($B$1,'Allocated Expenses'!$B$76:$P$85,5,FALSE) -> 0 | G98: =VLOOKUP($B$1,'Allocated Expenses'!$B$76:$P$85,6,FALSE) -> 0 | H98: =VLOOKUP($B$1,'Allocated Expenses'!$B$76:$P$85,7,FALSE) -> 0 | I98: =VLOOKUP($B$1,'Allocated Expenses'!$B$76:$P$85,8,FALSE) -> 0 | J98: =VLOOKUP($B$1,'Allocated Expenses'!$B$76:$P$85,9,FALSE) -> 0 | K98: =VLOOKUP($B$1,'Allocated Expenses'!$B$76:$P$85,10,FALSE) -> 0 | L98: =VLOOKUP($B$1,'Allocated Expenses'!$B$76:$P$85,11,FALSE) -> 0 | M98: =VLOOKUP($B$1,'Allocated Expenses'!$B$76:$P$85,12,FALSE) -> 0 | N98: =VLOOKUP($B$1,'Allocated Expenses'!$B$76:$P$85,13,FALSE) -> 0 | O98: =VLOOKUP($B$1,'Allocated Expenses'!$B$76:$P$85,14,FALSE) -> 0 | P98: =VLOOKUP($B$1,'Allocated Expenses'!$B$76:$P$85,15,FALSE) -> 0 | Q98: =SUM(E98:P98) -> 0 | R98: =Q98/$B$4 -> 0
A99: 8930-8501 | D99: Office Supplies | E99: =VLOOKUP($B$1,'Allocated Expenses'!$B$104:$P$113,4,FALSE) -> 0 | F99: =VLOOKUP($B$1,'Allocated Expenses'!$B$104:$P$113,5,FALSE) -> 0 | G99: =VLOOKUP($B$1,'Allocated Expenses'!$B$104:$P$113,6,FALSE) -> 0 | H99: =VLOOKUP($B$1,'Allocated Expenses'!$B$104:$P$113,7,FALSE) -> 0 | I99: =VLOOKUP($B$1,'Allocated Expenses'!$B$104:$P$113,8,FALSE) -> 0 | J99: =VLOOKUP($B$1,'Allocated Expenses'!$B$104:$P$113,9,FALSE) -> 0 | K99: =VLOOKUP($B$1,'Allocated Expenses'!$B$104:$P$113,10,FALSE) -> 0 | L99: =VLOOKUP($B$1,'Allocated Expenses'!$B$104:$P$113,11,FALSE) -> 0 | M99: =VLOOKUP($B$1,'Allocated Expenses'!$B$104:$P$113,12,FALSE) -> 0 | N99: =VLOOKUP($B$1,'Allocated Expenses'!$B$104:$P$113,13,FALSE) -> 0 | O99: =VLOOKUP($B$1,'Allocated Expenses'!$B$104:$P$113,14,FALSE) -> 0 | P99: =VLOOKUP($B$1,'Allocated Expenses'!$B$104:$P$113,15,FALSE) -> 0 | Q99: =SUM(E99:P99) -> 0 | R99: =Q99/$B$4 -> 0
A100: 8950-8501 | D100: Postage | E100: =VLOOKUP($B$1,'Allocated Expenses'!$B$90:$P$99,4,FALSE) -> 0 | F100: =VLOOKUP($B$1,'Allocated Expenses'!$B$90:$P$99,5,FALSE) -> 0 | G100: =VLOOKUP($B$1,'Allocated Expenses'!$B$90:$P$99,6,FALSE) -> 0 | H100: =VLOOKUP($B$1,'Allocated Expenses'!$B$90:$P$99,7,FALSE) -> 0 | I100: =VLOOKUP($B$1,'Allocated Expenses'!$B$90:$P$99,8,FALSE) -> 0 | J100: =VLOOKUP($B$1,'Allocated Expenses'!$B$90:$P$99,9,FALSE) -> 0 | K100: =VLOOKUP($B$1,'Allocated Expenses'!$B$90:$P$99,10,FALSE) -> 0 | L100: =VLOOKUP($B$1,'Allocated Expenses'!$B$90:$P$99,11,FALSE) -> 0 | M100: =VLOOKUP($B$1,'Allocated Expenses'!$B$90:$P$99,12,FALSE) -> 0 | N100: =VLOOKUP($B$1,'Allocated Expenses'!$B$90:$P$99,13,FALSE) -> 0 | O100: =VLOOKUP($B$1,'Allocated Expenses'!$B$90:$P$99,14,FALSE) -> 0 | P100: =VLOOKUP($B$1,'Allocated Expenses'!$B$90:$P$99,15,FALSE) -> 0 | Q100: =SUM(E100:P100) -> 0 | R100: =Q100/$B$4 -> 0
A101: 8990-8501 | D101: Other G&A Expense | Q101: =SUM(E101:P101) -> 0 | R101: =Q101/$B$4 -> 0
A102: 8990-9800 | D102: Other G&A-allocated from LIK | E102: =VLOOKUP($B$1,'Allocated Expenses'!$B$118:$P$127,4,FALSE) -> 6.8666667 | F102: =VLOOKUP($B$1,'Allocated Expenses'!$B$118:$P$127,5,FALSE) -> 6.8666667 | G102: =VLOOKUP($B$1,'Allocated Expenses'!$B$118:$P$127,6,FALSE) -> 6.8666667 | H102: =VLOOKUP($B$1,'Allocated Expenses'!$B$118:$P$127,7,FALSE) -> 6.8666667 | I102: =VLOOKUP($B$1,'Allocated Expenses'!$B$118:$P$127,8,FALSE) -> 6.8666667 | J102: =VLOOKUP($B$1,'Allocated Expenses'!$B$118:$P$127,9,FALSE) -> 6.8666667 | K102: =VLOOKUP($B$1,'Allocated Expenses'!$B$118:$P$127,10,FALSE) -> 6.8666667 | L102: =VLOOKUP($B$1,'Allocated Expenses'!$B$118:$P$127,11,FALSE) -> 6.8666667 | M102: =VLOOKUP($B$1,'Allocated Expenses'!$B$118:$P$127,12,FALSE) -> 6.8666667 | N102: =VLOOKUP($B$1,'Allocated Expenses'!$B$118:$P$127,13,FALSE) -> 6.8666667 | O102: =VLOOKUP($B$1,'Allocated Expenses'!$B$118:$P$127,14,FALSE) -> 6.8666667 | P102: =VLOOKUP($B$1,'Allocated Expenses'!$B$118:$P$127,15,FALSE) -> 6.8666667 | Q102: =SUM(E102:P102) -> 82.4 | R102: =Q102/$B$4 -> 0.036140351
C103: General & Administrative | E103: =SUM(E98:E102) -> 6.8666667 | F103: =SUM(F98:F102) -> 6.8666667 | G103: =SUM(G98:G102) -> 6.8666667 | H103: =SUM(H98:H102) -> 6.8666667 | I103: =SUM(I98:I102) -> 6.8666667 | J103: =SUM(J98:J102) -> 6.8666667 | K103: =SUM(K98:K102) -> 6.8666667 | L103: =SUM(L98:L102) -> 6.8666667 | ... Q103: =SUM(Q98:Q102) -> 82.4 | R103: =Q103/$B$4 -> 0.036140351
C105: Total Non-Reimbursable Expenses | E105: =+E75+E79+E84+E88+E90+E92+E94+E96+E103 -> 769.33183 | F105: =+F75+F79+F84+F88+F90+F92+F94+F96+F103 -> 769.33183 | G105: =+G75+G79+G84+G88+G90+G92+G94+G96+G103 -> 460.33183 | H105: =+H75+H79+H84+H88+H90+H92+H94+H96+H103 -> 2005.3318 | I105: =+I75+I79+I84+I88+I90+I92+I94+I96+I103 -> 460.33183 | J105: =+J75+J79+J84+J88+J90+J92+J94+J96+J103 -> 460.33183 | K105: =+K75+K79+K84+K88+K90+K92+K94+K96+K103 -> 460.33183 | L105: =+L75+L79+L84+L88+L90+L92+L94+L96+L103 -> 460.33183 | ... Q105: =+Q75+Q79+Q84+Q88+Q90+Q92+Q94+Q96+Q103 -> 7686.9819 | R105: =Q105/$B$4 -> 3.3714833
B108: TOTAL OPERATING EXPENSES | E108: =+E71+E105 -> 1641.1582 | F108: =+F71+F105 -> 1641.1582 | G108: =+G71+G105 -> 1332.1582 | H108: =+H71+H105 -> 2877.1582 | I108: =+I71+I105 -> 1332.1582 | J108: =+J71+J105 -> 1332.1582 | K108: =+K71+K105 -> 1332.1582 | L108: =+L71+L105 -> 1332.1582 | ... Q108: =+Q71+Q105 -> 18152.098 | R108: =Q108/$B$4 -> 7.9614464
B111: NET OPERATING INCOME | E111: =+E24-E108 -> -1641.1582 | F111: =+F24-F108 -> -1641.1582 | G111: =+G24-G108 -> -1332.1582 | H111: =+H24-H108 -> -2877.1582 | I111: =+I24-I108 -> -1332.1582 | J111: =+J24-J108 -> -1332.1582 | K111: =+K24-K108 -> -1332.1582 | L111: =+L24-L108 -> -1332.1582 | ... Q111: =+Q24-Q108 -> -18152.098 | R111: =Q111/$B$4 -> -7.9614464
A113: 1420-0000 | D113: Land Improvements | Q113: =SUM(E113:P113) -> 0 | R113: =Q113/$B$4 -> 0
A114: 1430-0000 | D114: Buildings | Q114: =SUM(E114:P114) -> 0 | R114: =Q114/$B$4 -> 0
A115: 1450-0000 | D115: Equipment | Q115: =SUM(E115:P115) -> 0 | R115: =Q115/$B$4 -> 0
A116: 1980-8501 | D116: Capital Improvements | Q116: =SUM(E116:P116) -> 0 | R116: =Q116/$B$4 -> 0
C117: Capital Improvements | Q117: =SUM(Q113:Q116) -> 0 | R117: =Q117/$B$4 -> 0
A119: 1440-0000 | C119: Tenant Improvements | E119: ='Renew & Vac '!AJ33 -> 0 | F119: ='Renew & Vac '!AK33 -> 0 | G119: ='Renew & Vac '!AL33 -> 0 | H119: ='Renew & Vac '!AM33 -> 0 | I119: ='Renew & Vac '!AN33 -> 0 | J119: ='Renew & Vac '!AO33 -> 0 | K119: ='Renew & Vac '!AP33 -> 0 | L119: ='Renew & Vac '!AQ33 -> 0 | ... P119: ='Renew & Vac '!AU33 -> 0 | Q119: =SUM(E119:P119) -> 0 | R119: =Q119/$B$4 -> 0
A121: 1940-8501 | D121: Deferred Marketing | Q121: =SUM(E121:P121) -> 0 | R121: =Q121/$B$4 -> 0
A122: 1940-8501 | D122: Outside Leasing Commissions | E122: ='Renew & Vac '!AJ34 -> 0 | F122: ='Renew & Vac '!AK34 -> 0 | G122: ='Renew & Vac '!AL34 -> 0 | H122: ='Renew & Vac '!AM34 -> 0 | I122: ='Renew & Vac '!AN34 -> 0 | J122: ='Renew & Vac '!AO34 -> 0 | K122: ='Renew & Vac '!AP34 -> 0 | L122: ='Renew & Vac '!AQ34 -> 0 | ... P122: ='Renew & Vac '!AU34 -> 0 | Q122: =SUM(E122:P122) -> 0 | R122: =Q122/$B$4 -> 0
C123: Outside Leasing Commissions | E123: =SUM(E121:E122) -> 0 | F123: =SUM(F121:F122) -> 0 | G123: =SUM(G121:G122) -> 0 | H123: =SUM(H121:H122) -> 0 | I123: =SUM(I121:I122) -> 0 | J123: =SUM(J121:J122) -> 0 | K123: =SUM(K121:K122) -> 0 | L123: =SUM(L121:L122) -> 0 | ... Q123: =SUM(Q121:Q122) -> 0 | R123: =Q123/$B$4 -> 0
B125: CASH FLOW BEFORE DEBT SERVICE | E125: =+E111-E117-E119-E123 -> -1641.1582 | F125: =+F111-F117-F119-F123 -> -1641.1582 | G125: =+G111-G117-G119-G123 -> -1332.1582 | H125: =+H111-H117-H119-H123 -> -2877.1582 | I125: =+I111-I117-I119-I123 -> -1332.1582 | J125: =+J111-J117-J119-J123 -> -1332.1582 | K125: =+K111-K117-K119-K123 -> -1332.1582 | L125: =+L111-L117-L119-L123 -> -1332.1582 | ... Q125: =+Q111-Q117-Q119-Q123 -> -18152.098 | R125: =Q125/$B$4 -> -7.9614464
B127: Debt Service
A128: 9210-8501 | C128: Interest | E128: =VLOOKUP($B$1,'INS RET DEBT'!$C$98:$Q$107,3,FALSE) -> 0 | F128: =VLOOKUP($B$1,'INS RET DEBT'!$C$98:$Q$107,4,FALSE) -> 0 | G128: =VLOOKUP($B$1,'INS RET DEBT'!$C$98:$Q$107,5,FALSE) -> 0 | H128: =VLOOKUP($B$1,'INS RET DEBT'!$C$98:$Q$107,6,FALSE) -> 0 | I128: =VLOOKUP($B$1,'INS RET DEBT'!$C$98:$Q$107,7,FALSE) -> 0 | J128: =VLOOKUP($B$1,'INS RET DEBT'!$C$98:$Q$107,8,FALSE) -> 0 | K128: =VLOOKUP($B$1,'INS RET DEBT'!$C$98:$Q$107,9,FALSE) -> 0 | L128: =VLOOKUP($B$1,'INS RET DEBT'!$C$98:$Q$107,10,FALSE) -> 0 | M128: =VLOOKUP($B$1,'INS RET DEBT'!$C$98:$Q$107,11,FALSE) -> 0 | N128: =VLOOKUP($B$1,'INS RET DEBT'!$C$98:$Q$107,12,FALSE) -> 0 | O128: =VLOOKUP($B$1,'INS RET DEBT'!$C$98:$Q$107,13,FALSE) -> 0 | P128: =VLOOKUP($B$1,'INS RET DEBT'!$C$98:$Q$107,14,FALSE) -> 0 | Q128: =SUM(E128:P128) -> 0 | R128: =Q128/$B$4 -> 0
A129: 2740-8501 | C129: Mortgage Amortization | E129: =VLOOKUP($B$1,'INS RET DEBT'!$C$113:$Q$122,3,FALSE) -> 0 | F129: =VLOOKUP($B$1,'INS RET DEBT'!$C$113:$Q$122,4,FALSE) -> 0 | G129: =VLOOKUP($B$1,'INS RET DEBT'!$C$113:$Q$122,5,FALSE) -> 0 | H129: =VLOOKUP($B$1,'INS RET DEBT'!$C$113:$Q$122,6,FALSE) -> 0 | I129: =VLOOKUP($B$1,'INS RET DEBT'!$C$113:$Q$122,7,FALSE) -> 0 | J129: =VLOOKUP($B$1,'INS RET DEBT'!$C$113:$Q$122,8,FALSE) -> 0 | K129: =VLOOKUP($B$1,'INS RET DEBT'!$C$113:$Q$122,9,FALSE) -> 0 | L129: =VLOOKUP($B$1,'INS RET DEBT'!$C$113:$Q$122,10,FALSE) -> 0 | M129: =VLOOKUP($B$1,'INS RET DEBT'!$C$113:$Q$122,11,FALSE) -> 0 | N129: =VLOOKUP($B$1,'INS RET DEBT'!$C$113:$Q$122,12,FALSE) -> 0 | O129: =VLOOKUP($B$1,'INS RET DEBT'!$C$113:$Q$122,13,FALSE) -> 0 | P129: =VLOOKUP($B$1,'INS RET DEBT'!$C$113:$Q$122,14,FALSE) -> 0 | Q129: =SUM(E129:P129) -> 0 | R129: =Q129/$B$4 -> 0
A130: 2740-0000 | C130: Loan Proceeds | Q130: =SUM(E130:P130) -> 0 | R130: =Q130/$B$4 -> 0
C131: Total Debt Service | E131: =SUM(E128:E130) -> 0 | F131: =SUM(F128:F130) -> 0 | G131: =SUM(G128:G130) -> 0 | H131: =SUM(H128:H130) -> 0 | I131: =SUM(I128:I130) -> 0 | J131: =SUM(J128:J130) -> 0 | K131: =SUM(K128:K130) -> 0 | L131: =SUM(L128:L130) -> 0 | ... Q131: =SUM(Q128:Q130) -> 0 | R131: =Q131/$B$4 -> 0
B134: CASH FLOW AFTER DEBT SERVICE | E134: =+E125-E131 -> -1641.1582 | F134: =+F125-F131 -> -1641.1582 | G134: =+G125-G131 -> -1332.1582 | H134: =+H125-H131 -> -2877.1582 | I134: =+I125-I131 -> -1332.1582 | J134: =+J125-J131 -> -1332.1582 | K134: =+K125-K131 -> -1332.1582 | L134: =+L125-L131 -> -1332.1582 | ... Q134: =+Q125-Q131 -> -18152.098 | R134: =Q134/$B$4 -> -7.9614464
D135: Cash Balance 12/31/205
D136: Cumulative Cash Flow
D145: ="Budget Import - "&B1 -> Budget Import - 1500 | E145: 5 | F145: =E145+1 -> 6 | G145: =F145+1 -> 7 | H145: =G145+1 -> 8 | I145: =H145+1 -> 9 | J145: =I145+1 -> 10 | K145: =J145+1 -> 11 | L145: =K145+1 -> 12 | M145: =L145+1 -> 13 | ... P145: =O145+1 -> 16 | Q145: <- Lookup Column
D146: Account | E146: 1 | F146: 2 | G146: 3 | H146: 4 | I146: 5 | J146: 6 | K146: 7 | L146: 8 | M146: 9 | N146: 10 | O146: 11 | P146: 12 | Q146: Total
A147: =VLOOKUP($D147,$A$10:$D$130,3,FALSE) -> Rental Income - In Place | D147: 4230-8501 | E147: =-(VLOOKUP($D147,$A$10:$P$134,E$145,FALSE)+E11) -> 0 | F147: =-(VLOOKUP($D147,$A$10:$P$134,F$145,FALSE)+F11) -> 0 | G147: =-(VLOOKUP($D147,$A$10:$P$134,G$145,FALSE)+G11) -> 0 | H147: =-(VLOOKUP($D147,$A$10:$P$134,H$145,FALSE)+H11) -> 0 | I147: =-(VLOOKUP($D147,$A$10:$P$134,I$145,FALSE)+I11) -> 0 | J147: =-(VLOOKUP($D147,$A$10:$P$134,J$145,FALSE)+J11) -> 0 | K147: =-(VLOOKUP($D147,$A$10:$P$134,K$145,FALSE)+K11) -> 0 | L147: =-(VLOOKUP($D147,$A$10:$P$134,L$145,FALSE)+L11) -> 0 | ... P147: =-(VLOOKUP($D147,$A$10:$P$134,P$145,FALSE)+P11) -> 0 | Q147: =SUM(E147:P147) -> 0
A148: =VLOOKUP($D148,$A$10:$D$130,3,FALSE) -> Electric | D148: 4710-8502 | E148: =-VLOOKUP($D148,$A$10:$P$134,E$145,FALSE) -> 0 | F148: =-VLOOKUP($D148,$A$10:$P$134,F$145,FALSE) -> 0 | G148: =-VLOOKUP($D148,$A$10:$P$134,G$145,FALSE) -> 0 | H148: =-VLOOKUP($D148,$A$10:$P$134,H$145,FALSE) -> 0 | I148: =-VLOOKUP($D148,$A$10:$P$134,I$145,FALSE) -> 0 | J148: =-VLOOKUP($D148,$A$10:$P$134,J$145,FALSE) -> 0 | K148: =-VLOOKUP($D148,$A$10:$P$134,K$145,FALSE) -> 0 | L148: =-VLOOKUP($D148,$A$10:$P$134,L$145,FALSE) -> 0 | ... P148: =-VLOOKUP($D148,$A$10:$P$134,P$145,FALSE) -> 0 | Q148: =SUM(E148:P148) -> 0
A149: =VLOOKUP($D149,$A$10:$D$130,3,FALSE) -> Common Area Maintenance | D149: 4910-8502 | E149: =-VLOOKUP($D149,$A$10:$P$134,E$145,FALSE) -> 0 | F149: =-VLOOKUP($D149,$A$10:$P$134,F$145,FALSE) -> 0 | G149: =-VLOOKUP($D149,$A$10:$P$134,G$145,FALSE) -> 0 | H149: =-VLOOKUP($D149,$A$10:$P$134,H$145,FALSE) -> 0 | I149: =-VLOOKUP($D149,$A$10:$P$134,I$145,FALSE) -> 0 | J149: =-VLOOKUP($D149,$A$10:$P$134,J$145,FALSE) -> 0 | K149: =-VLOOKUP($D149,$A$10:$P$134,K$145,FALSE) -> 0 | L149: =-VLOOKUP($D149,$A$10:$P$134,L$145,FALSE) -> 0 | ... P149: =-VLOOKUP($D149,$A$10:$P$134,P$145,FALSE) -> 0 | Q149: =SUM(E149:P149) -> 0
...

Sheet 2300
B1: 2300 | C1: - Brookwood Shopping Center | J1: =+'1500'!J1 -> Operating Budget | Q1: ='All Shopping Centers'!Q1 -> 46023
J2: ='All Shopping Centers'!J2&" - "&B1 -> Shopping Centers - 2300
S3: 9/2025 Reprojections
B4: 61572 | E4: Jan | F4: Feb | G4: Mar | H4: Apr | I4: May | J4: Jun | K4: Jul | L4: Aug | M4: Sep | N4: Oct | O4: Nov | P4: Dec | Q4: Total | R4: Total PSF | S4: Total | T4: Var. | U4: Input | V4: Notes
D6: Occupancy % | E6: ='Renew & Vac '!AJ53 -> 1 | F6: ='Renew & Vac '!AK53 -> 1 | G6: ='Renew & Vac '!AL53 -> 1 | H6: ='Renew & Vac '!AM53 -> 1 | I6: ='Renew & Vac '!AN53 -> 1 | J6: ='Renew & Vac '!AO53 -> 1 | K6: ='Renew & Vac '!AP53 -> 1 | L6: ='Renew & Vac '!AQ53 -> 1 | ... P6: ='Renew & Vac '!AU53 -> 1
D7: Occupancy SF | E7: =$B$4*E6 -> 61572 | F7: =$B$4*F6 -> 61572 | G7: =$B$4*G6 -> 61572 | H7: =$B$4*H6 -> 61572 | I7: =$B$4*I6 -> 61572 | J7: =$B$4*J6 -> 61572 | K7: =$B$4*K6 -> 61572 | L7: =$B$4*L6 -> 61572 | ... P7: =$B$4*P6 -> 61572
B8: Revenues
A10: 4230-8501 | C10: Rental Income - In Place | E10: =SUMIFS('In Place Revenue'!$G:$G,'In Place Revenue'!$A:$A,$B$1,'In Place Revenue'!$H:$H,1) -> 96896.61 | F10: =SUMIFS('In Place Revenue'!$G:$G,'In Place Revenue'!$A:$A,$B$1,'In Place Revenue'!$H:$H,2) -> 96896.61 | G10: =SUMIFS('In Place Revenue'!$G:$G,'In Place Revenue'!$A:$A,$B$1,'In Place Revenue'!$H:$H,3) -> 97346.61 | H10: =SUMIFS('In Place Revenue'!$G:$G,'In Place Revenue'!$A:$A,$B$1,'In Place Revenue'!$H:$H,4) -> 97346.61 | I10: =SUMIFS('In Place Revenue'!$G:$G,'In Place Revenue'!$A:$A,$B$1,'In Place Revenue'!$H:$H,5) -> 97346.61 | J10: =SUMIFS('In Place Revenue'!$G:$G,'In Place Revenue'!$A:$A,$B$1,'In Place Revenue'!$H:$H,6) -> 97479.94 | K10: =SUMIFS('In Place Revenue'!$G:$G,'In Place Revenue'!$A:$A,$B$1,'In Place Revenue'!$H:$H,7) -> 94386.36 | L10: =SUMIFS('In Place Revenue'!$G:$G,'In Place Revenue'!$A:$A,$B$1,'In Place Revenue'!$H:$H,8) -> 94386.36 | M10: =SUMIFS('In Place Revenue'!$G:$G,'In Place Revenue'!$A:$A,$B$1,'In Place Revenue'!$H:$H,9) -> 94386.36 | N10: =SUMIFS('In Place Revenue'!$G:$G,'In Place Revenue'!$A:$A,$B$1,'In Place Revenue'!$H:$H,10) -> 94386.36 | O10: =SUMIFS('In Place Revenue'!$G:$G,'In Place Revenue'!$A:$A,$B$1,'In Place Revenue'!$H:$H,11) -> 94386.36 | P10: =SUMIFS('In Place Revenue'!$G:$G,'In Place Revenue'!$A:$A,$B$1,'In Place Revenue'!$H:$H,12) -> 94386.36 | Q10: =SUM(E10:P10) -> 1149631.2 | R10: =Q10/$B$4 -> 18.67133 | S10: 1157263 | T10: =(Q10+Q11)/S10-1 -> 0.0099961288
A11: 4230-8501 | C11: Rental Income - New & Renewal | E11: ='Renew & Vac '!AJ54 -> 0 | F11: ='Renew & Vac '!AK54 -> 0 | G11: ='Renew & Vac '!AL54 -> 0 | H11: ='Renew & Vac '!AM54 -> 0 | I11: ='Renew & Vac '!AN54 -> 0 | J11: ='Renew & Vac '!AO54 -> 0 | K11: ='Renew & Vac '!AP54 -> 3200 | L11: ='Renew & Vac '!AQ54 -> 3200 | ... P11: ='Renew & Vac '!AU54 -> 3200 | Q11: =SUM(E11:P11) -> 19200 | R11: =Q11/$B$4 -> 0.31183005
A12: 4240-8501 | C12: Percentage Rents | Q12: =SUM(E12:P12) -> 0 | R12: =Q12/$B$4 -> 0 | S12: 0 | T12: =IFERROR(Q12/S12-1,"")
A13: 4990-8501 | C13: Miscellaneous | Q13: =SUM(E13:P13) -> 0 | R13: =Q13/$B$4 -> 0 | S13: 0 | T13: =IFERROR(Q13/S13-1,"")
A14: 9190-8501 | C14: Interest Income | Q14: =SUM(E14:P14) -> 0 | R14: =Q14/$B$4 -> 0 | S14: 31900 | T14: =IFERROR(Q14/S14-1,"") -> -1
C15: Total Rental and Other | E15: =SUM(E10:E14) -> 96896.61 | F15: =SUM(F10:F14) -> 96896.61 | G15: =SUM(G10:G14) -> 97346.61 | H15: =SUM(H10:H14) -> 97346.61 | I15: =SUM(I10:I14) -> 97346.61 | J15: =SUM(J10:J14) -> 97479.94 | K15: =SUM(K10:K14) -> 97586.36 | L15: =SUM(L10:L14) -> 97586.36 | ... Q15: =SUM(Q10:Q14) -> 1168831.2 | R15: =Q15/$B$4 -> 18.98316 | S15: =SUM(S10:S14) -> 1189163 | T15: =Q15/S15-1 -> -0.017097614
B17: Reimbursements
A18: 4710-8502 | C18: Electric | Q18: =SUM(E18:P18) -> 0 | R18: =Q18/$B$4 -> 0 | S18: 0 | T18: =IFERROR(Q18/S18-1,"")
A19: 4910-8502 | C19: Common Area Maintenance | E19: =+'Tenant Recoveries'!G26 -> 21100 | F19: =+E19 -> 21100 | G19: =+F19 -> 21100 | H19: =+G19 -> 21100 | I19: =+H19 -> 21100 | J19: =+I19 -> 21100 | K19: =+J19 -> 21100 | L19: =+K19 -> 21100 | M19: =+L19 -> 21100 | ... P19: =+O19 -> 21100 | Q19: =SUM(E19:P19) -> 253200 | R19: =Q19/$B$4 -> 4.1122588 | S19: 267960 | T19: =IFERROR(Q19/S19-1,"") -> -0.055082848
A20: 4920-8502 | C20: Real Estate Taxes | E20: =+'Tenant Recoveries'!G27 -> 11200 | F20: =+E20 -> 11200 | G20: =+F20 -> 11200 | H20: =+G20 -> 11200 | I20: =+H20 -> 11200 | J20: =+I20 -> 11200 | K20: =+J20 -> 11200 | L20: =+K20 -> 11200 | M20: =+L20 -> 11200 | ... P20: =+O20 -> 11200 | Q20: =SUM(E20:P20) -> 134400 | R20: =Q20/$B$4 -> 2.1828104 | S20: 140724 | T20: =IFERROR(Q20/S20-1,"") -> -0.04493903
A21: 4930-8502 | C21: Insurance | Q21: =SUM(E21:P21) -> 0 | R21: =Q21/$B$4 -> 0 | S21: 13468 | T21: =IFERROR(Q21/S21-1,"") -> -1
C22: Total Reimbursements | E22: =SUM(E18:E21) -> 32300 | F22: =SUM(F18:F21) -> 32300 | G22: =SUM(G18:G21) -> 32300 | H22: =SUM(H18:H21) -> 32300 | I22: =SUM(I18:I21) -> 32300 | J22: =SUM(J18:J21) -> 32300 | K22: =SUM(K18:K21) -> 32300 | L22: =SUM(L18:L21) -> 32300 | ... Q22: =SUM(Q18:Q21) -> 387600 | R22: =Q22/$B$4 -> 6.2950692 | S22: =SUM(S18:S21) -> 422152 | T22: =Q22/S22-1 -> -0.081847297
R23: =Q23/$B$4 -> 0
B24: TOTAL REVENUES | E24: =+E15+E22 -> 129196.61 | F24: =+F15+F22 -> 129196.61 | G24: =+G15+G22 -> 129646.61 | H24: =+H15+H22 -> 129646.61 | I24: =+I15+I22 -> 129646.61 | J24: =+J15+J22 -> 129779.94 | K24: =+K15+K22 -> 129886.36 | L24: =+L15+L22 -> 129886.36 | ... Q24: =+Q15+Q22 -> 1556431.2 | R24: =Q24/$B$4 -> 25.27823 | S24: =+S15+S22 -> 1611315 | T24: =Q24/S24-1 -> -0.034061527
B26: Reimbursable Expenses
A27: 6030-8502 | C27: Maintenance Salaries | E27: =VLOOKUP($B$1,'Allocated Expenses'!$B$6:$P$15,4,FALSE) -> 1895.9945 | F27: =VLOOKUP($B$1,'Allocated Expenses'!$B$6:$P$15,5,FALSE) -> 1895.9945 | G27: =VLOOKUP($B$1,'Allocated Expenses'!$B$6:$P$15,6,FALSE) -> 1895.9945 | H27: =VLOOKUP($B$1,'Allocated Expenses'!$B$6:$P$15,7,FALSE) -> 1895.9945 | I27: =VLOOKUP($B$1,'Allocated Expenses'!$B$6:$P$15,8,FALSE) -> 1895.9945 | J27: =VLOOKUP($B$1,'Allocated Expenses'!$B$6:$P$15,9,FALSE) -> 1895.9945 | K27: =VLOOKUP($B$1,'Allocated Expenses'!$B$6:$P$15,10,FALSE) -> 1895.9945 | L27: =VLOOKUP($B$1,'Allocated Expenses'!$B$6:$P$15,11,FALSE) -> 1895.9945 | M27: =VLOOKUP($B$1,'Allocated Expenses'!$B$6:$P$15,12,FALSE) -> 1895.9945 | N27: =VLOOKUP($B$1,'Allocated Expenses'!$B$6:$P$15,13,FALSE) -> 1895.9945 | O27: =VLOOKUP($B$1,'Allocated Expenses'!$B$6:$P$15,14,FALSE) -> 1895.9945 | P27: =VLOOKUP($B$1,'Allocated Expenses'!$B$6:$P$15,15,FALSE) -> 1895.9945 | Q27: =SUM(E27:P27) -> 22751.934 | R27: =Q27/$B$4 -> 0.36951753 | S27: 23520 | T27: =IFERROR(Q27/S27-1,"") -> -0.032655887
A29: 6120-8502 | C29: Electric | E29: =1.03*752 -> 774.56 | F29: =1.03*606 -> 624.18 | G29: =1.03*770 -> 793.1 | H29: =1.03*568 -> 585.04 | I29: =1.03*536 -> 552.08 | J29: =1.03*495 -> 509.85 | K29: =1.03*493 -> 507.79 | L29: =1.03*609 -> 627.27 | M29: =1.03*682 -> 702.46 | N29: =1.03*830 -> 854.9 | O29: =1.03*727 -> 748.81 | P29: =1.03*775 -> 798.25 | Q29: =SUM(E29:P29) -> 8078.29 | R29: =Q29/$B$4 -> 0.13120071 | S29: 7474 | T29: =IFERROR(Q29/S29-1,"") -> 0.080852288 | U29: DW | V29: 2025 Business Plan grown 3%
A31: 6130-8502 | C31: Water & Sewer | Q31: =SUM(E31:P31) -> 0 | R31: =Q31/$B$4 -> 0 | S31: 0 | T31: =IFERROR(Q31/S31-1,"")
D33: Building Maint.-Contractual | E33: ='Building Maint'!C22 -> 750 | F33: ='Building Maint'!D22 -> 0 | G33: ='Building Maint'!E22 -> 0 | H33: ='Building Maint'!F22 -> 750 | I33: ='Building Maint'!G22 -> 1275 | J33: ='Building Maint'!H22 -> 0 | K33: ='Building Maint'!I22 -> 750 | L33: ='Building Maint'!J22 -> 0 | ... P33: ='Building Maint'!N22 -> 0 | Q33: =SUM(E33:P33) -> 7550 | R33: =Q33/$B$4 -> 0.12262067 | U33: DW | V33: 2025 Business Plan grown 3%
D34: Building Maint.-Recurring | E34: ='Building Maint'!C8 -> 200 | F34: ='Building Maint'!D8 -> 200 | G34: ='Building Maint'!E8 -> 200 | H34: ='Building Maint'!F8 -> 200 | I34: ='Building Maint'!G8 -> 200 | J34: ='Building Maint'!H8 -> 200 | K34: ='Building Maint'!I8 -> 200 | L34: ='Building Maint'!J8 -> 200 | ... P34: ='Building Maint'!N8 -> 200 | Q34: =SUM(E34:P34) -> 2800 | R34: =Q34/$B$4 -> 0.045475216 | U34: DW | V34: 2025 Business Plan grown 3%
D35: Building Maint.-Big Projects | H35: 12500 | L35: 12500 | Q35: =SUM(E35:P35) -> 25000 | R35: =Q35/$B$4 -> 0.40602871 | U35: GM | V35: Pointing/EFIS repairs/Painting/HVAC/Roof Repairs
A36: 6220-8502 | C36: Building Maintenance | E36: =SUM(E33:E35) -> 950 | F36: =SUM(F33:F35) -> 200 | G36: =SUM(G33:G35) -> 200 | H36: =SUM(H33:H35) -> 13450 | I36: =SUM(I33:I35) -> 1475 | J36: =SUM(J33:J35) -> 200 | K36: =SUM(K33:K35) -> 950 | L36: =SUM(L33:L35) -> 12700 | ... Q36: =SUM(Q33:Q35) -> 35350 | R36: =Q36/$B$4 -> 0.5741246 | S36: 32516 | T36: =IFERROR(Q36/S36-1,"") -> 0.087157092
A38: 6330-8502 | B38: (SC) | C38: Parking Lot Cleaning | E38: =1.03*2750 -> 2832.5 | F38: =1.03*2750 -> 2832.5 | G38: =1.03*3050 -> 3141.5 | H38: =1.03*2750 -> 2832.5 | I38: =1.03*2750 -> 2832.5 | J38: =1.03*2750 -> 2832.5 | K38: =1.03*2750 -> 2832.5 | L38: =1.03*2750 -> 2832.5 | M38: =1.03*3050 -> 3141.5 | N38: =1.03*2750 -> 2832.5 | O38: =1.03*2750 -> 2832.5 | P38: =1.03*2750 -> 2832.5 | Q38: =SUM(E38:P38) -> 34608 | R38: =Q38/$B$4 -> 0.56207367 | S38: 20417 | T38: =IFERROR(Q38/S38-1,"") -> 0.69505804 | U38: DW | V38: 2025 Business Plan grown 3%
D40: Parking Lot Maint.-Contractual | Q40: =SUM(E40:P40) -> 0 | R40: =Q40/$B$4 -> 0
D41: Parking Lot Maint.-Recurring | E41: =1.03*250 -> 257.5 | F41: =1.03*250 -> 257.5 | G41: =1.03*1395 -> 1436.85 | H41: =1.03*1750 -> 1802.5 | I41: =1.03*250 -> 257.5 | J41: =1.03*1395 -> 1436.85 | K41: =1.03*250 -> 257.5 | L41: =1.03*250 -> 257.5 | M41: =1.03*1395 -> 1436.85 | N41: =1.03*1750 -> 1802.5 | O41: =1.03*250 -> 257.5 | P41: =1.03*1495 -> 1539.85 | Q41: =SUM(E41:P41) -> 11000.4 | R41: =Q41/$B$4 -> 0.17865913 | U41: DW | V41: 2025 Business Plan grown 3%
D42: Parking Lot Maint.-Big Projects | G42: =1.03*10000 -> 10300 | M42: =1.03*10000 -> 10300 | Q42: =SUM(E42:P42) -> 20600 | R42: =Q42/$B$4 -> 0.33456766 | U42: DW | V42: 2025 Business Plan grown 3%. Sidewalk repairs
A43: 6360-8502 | C43: Parking Lot Maintenance | E43: =SUM(E40:E42) -> 257.5 | F43: =SUM(F40:F42) -> 257.5 | G43: =SUM(G40:G42) -> 11736.85 | H43: =SUM(H40:H42) -> 1802.5 | I43: =SUM(I40:I42) -> 257.5 | J43: =SUM(J40:J42) -> 1436.85 | K43: =SUM(K40:K42) -> 257.5 | L43: =SUM(L40:L42) -> 257.5 | ... Q43: =SUM(Q40:Q42) -> 31600.4 | R43: =Q43/$B$4 -> 0.51322679 | S43: 18739 | T43: =IFERROR(Q43/S43-1,"") -> 0.68634399
A45: 6370-8502 | C45: Snow Removal | E45: =1.03*13000 -> 13390 | F45: =1.03*13000 -> 13390 | G45: =1.03*2000 -> 2060 | H45: 0 | I45: 0 | J45: 0 | K45: 0 | L45: 0 | M45: 0 | N45: 0 | O45: =1.03*2000 -> 2060 | P45: =1.03*13000 -> 13390 | Q45: =SUM(E45:P45) -> 44290 | R45: =Q45/$B$4 -> 0.71932047 | S45: 62294 | T45: =IFERROR(Q45/S45-1,"") -> -0.2890166 | U45: DW | V45: 2025 Business Plan grown 3%
D47: Landscaping-Contractual | E47: 0 | F47: 0 | G47: 0 | H47: =1.03*1750 -> 1802.5 | I47: =1.03*1750 -> 1802.5 | J47: =1.03*1750 -> 1802.5 | K47: =1.03*1750 -> 1802.5 | L47: =1.03*1750 -> 1802.5 | M47: =1.03*1750 -> 1802.5 | N47: =1.03*1750 -> 1802.5 | O47: 0 | P47: 0 | Q47: =SUM(E47:P47) -> 12617.5 | R47: =Q47/$B$4 -> 0.20492269 | U47: DW | V47: 2025 Business Plan grown 3%
D48: Landscaping-Recurring | E48: 0 | F48: 0 | G48: 0 | H48: =1.03*100 -> 103 | I48: =1.03*100 -> 103 | J48: =1.03*100 -> 103 | K48: =1.03*100 -> 103 | L48: =1.03*100 -> 103 | M48: =1.03*100 -> 103 | N48: =1.03*100 -> 103 | O48: 0 | P48: 0 | Q48: =SUM(E48:P48) -> 721 | R48: =Q48/$B$4 -> 0.011709868 | U48: DW | V48: 2025 Business Plan grown 3%
D49: Landscaping-Big Projects | E49: 0 | G49: 0 | H49: 0 | I49: 10000 | J49: 0 | K49: 0 | L49: 10000 | M49: 0 | N49: 0 | O49: 0 | P49: 0 | Q49: =SUM(E49:P49) -> 20000 | R49: =Q49/$B$4 -> 0.32482297 | U49: AK
A50: 6380-8502 | C50: Landscaping | E50: =SUM(E47:E49) -> 0 | F50: =SUM(F47:F49) -> 0 | G50: =SUM(G47:G49) -> 0 | H50: =SUM(H47:H49) -> 1905.5 | I50: =SUM(I47:I49) -> 11905.5 | J50: =SUM(J47:J49) -> 1905.5 | K50: =SUM(K47:K49) -> 1905.5 | L50: =SUM(L47:L49) -> 11905.5 | ... Q50: =SUM(Q47:Q49) -> 33338.5 | R50: =Q50/$B$4 -> 0.54145553 | S50: 13849 | T50: =IFERROR(Q50/S50-1,"") -> 1.4072857
A52: 6350-8502 | C52: Security | E52: =1200 -> 1200 | F52: =1200 -> 1200 | G52: =1200 -> 1200 | H52: =1200 -> 1200 | I52: =1200 -> 1200 | J52: =1200 -> 1200 | K52: =1200 -> 1200 | L52: =1200 -> 1200 | ... P52: =1200 -> 1200 | Q52: =SUM(E52:P52) -> 14400 | R52: =Q52/$B$4 -> 0.23387254 | S52: 22847 | T52: =IFERROR(Q52/S52-1,"") -> -0.36972031 | U52: GM | V52: Monthly camera fee
A54: 6610-8502 | B54: (BP) | C54: Management Fee | Q54: =SUM(E54:P54) -> 0 | R54: =Q54/$B$4 -> 0 | T54: =R54/S54-1 -> #DIV/0!
A56: 6270-8502 | C56: Trash Removal | E56: =1.03*100 -> 103 | F56: =1.03*100 -> 103 | G56: =1.03*100 -> 103 | H56: =1.03*100 -> 103 | I56: =1.03*100 -> 103 | J56: =1.03*100 -> 103 | K56: =1.03*100 -> 103 | L56: =1.03*100 -> 103 | ... P56: =1.03*100 -> 103 | Q56: =SUM(E56:P56) -> 1236 | R56: =Q56/$B$4 -> 0.02007406 | S56: 12576 | T56: =IFERROR(Q56/S56-1,"") -> -0.90171756 | U56: DW | V56: 2025 Business Plan grown 3%
A58: 6410-8502 | C58: Real Estate Taxes | E58: =+'INS RET DEBT'!E83 -> 13547.23 | F58: =+'INS RET DEBT'!F83 -> 13547.23 | G58: =+'INS RET DEBT'!G83 -> 13547.23 | H58: =+'INS RET DEBT'!H83 -> 13547.23 | I58: =+'INS RET DEBT'!I83 -> 13547.23 | J58: =+'INS RET DEBT'!J83 -> 13547.23 | K58: =+'INS RET DEBT'!K83 -> 13547.23 | L58: =+'INS RET DEBT'!L83 -> 13547.23 | ... P58: =+'INS RET DEBT'!P83 -> 13547.23 | Q58: =SUM(E58:P58) -> 162566.76 | R58: =Q58/$B$4 -> 2.6402709 | S58: 160970 | T58: =IFERROR(Q58/S58-1,"") -> 0.0099196124 | U58: DW | V58: Flat from 2025
D60: Insurance-Liability | E60: =+'INS RET DEBT'!E20+'INS RET DEBT'!E21 -> 3279 | F60: =+'INS RET DEBT'!F20+'INS RET DEBT'!F21 -> 3279 | G60: =+'INS RET DEBT'!G20+'INS RET DEBT'!G21 -> 3279 | H60: =+'INS RET DEBT'!H20+'INS RET DEBT'!H21 -> 3279 | I60: =+'INS RET DEBT'!I20+'INS RET DEBT'!I21 -> 3279 | J60: =+'INS RET DEBT'!J20+'INS RET DEBT'!J21 -> 3279 | K60: =+'INS RET DEBT'!K20+'INS RET DEBT'!K21 -> 3279 | L60: =+'INS RET DEBT'!L20+'INS RET DEBT'!L21 -> 3279 | ... P60: =+'INS RET DEBT'!P20+'INS RET DEBT'!P21 -> 3344.58 | Q60: =SUM(E60:P60) -> 39479.16 | R60: =Q60/$B$4 -> 0.6411869
D61: Insurance-Property | E61: =+'INS RET DEBT'!E23 -> 788 | F61: =+'INS RET DEBT'!F23 -> 788 | G61: =+'INS RET DEBT'!G23 -> 788 | H61: =+'INS RET DEBT'!H23 -> 788 | I61: =+'INS RET DEBT'!I23 -> 788 | J61: =+'INS RET DEBT'!J23 -> 788 | K61: =+'INS RET DEBT'!K23 -> 788 | L61: =+'INS RET DEBT'!L23 -> 788 | ... P61: =+'INS RET DEBT'!P23 -> 803.76 | Q61: =SUM(E61:P61) -> 9487.52 | R61: =Q61/$B$4 -> 0.15408822
D62: Insurance-Other | E62: =+'INS RET DEBT'!E24 -> 0 | F62: =+'INS RET DEBT'!F24 -> 0 | G62: =+'INS RET DEBT'!G24 -> 0 | H62: =+'INS RET DEBT'!H24 -> 0 | I62: =+'INS RET DEBT'!I24 -> 0 | J62: =+'INS RET DEBT'!J24 -> 0 | K62: =+'INS RET DEBT'!K24 -> 0 | L62: =+'INS RET DEBT'!L24 -> 0 | ... P62: =+'INS RET DEBT'!P24 -> 0 | Q62: =SUM(E62:P62) -> 0 | R62: =Q62/$B$4 -> 0
A63: 6510-8502 | C63: Insurance | E63: =SUM(E60:E62) -> 4067 | F63: =SUM(F60:F62) -> 4067 | G63: =SUM(G60:G62) -> 4067 | H63: =SUM(H60:H62) -> 4067 | I63: =SUM(I60:I62) -> 4067 | J63: =SUM(J60:J62) -> 4067 | K63: =SUM(K60:K62) -> 4067 | L63: =SUM(L60:L62) -> 4067 | ... Q63: =SUM(Q60:Q62) -> 48966.68 | R63: =Q63/$B$4 -> 0.79527513 | S63: 49234 | T63: =IFERROR(Q63/S63-1,"") -> -0.0054295812
D65: Cleaning & Supplies | Q65: =SUM(E65:P65) -> 0 | R65: =Q65/$B$4 -> 0
D66: Cleaning & Supplies-Vacancies | Q66: =SUM(E66:P66) -> 0 | R66: =Q66/$B$4 -> 0
A67: 6250-8502 | B67: (BP) | C67: Cleaning & Supplies | E67: =SUM(E65:E66) -> 0 | F67: =SUM(F65:F66) -> 0 | G67: =SUM(G65:G66) -> 0 | H67: =SUM(H65:H66) -> 0 | I67: =SUM(I65:I66) -> 0 | J67: =SUM(J65:J66) -> 0 | K67: =SUM(K65:K66) -> 0 | L67: =SUM(L65:L66) -> 0 | ... P67: =SUM(P65:P66) -> 0 | Q67: =SUM(E67:P67) -> 0 | R67: =Q67/$B$4 -> 0 | S67: 0 | T67: =IFERROR(Q67/S67-1,"")
B69: (SC) | C69: Other | E69: 0 | F69: 0 | G69: 0 | H69: 0 | I69: 0 | J69: 0 | K69: 0 | L69: 0 | M69: 0 | N69: 0 | O69: 0 | P69: 0 | Q69: =SUM(E69:P69) -> 0 | R69: =Q69/$B$4 -> 0 | T69: =IFERROR(Q69/S69-1,"")
C71: Total Reimbursable Expenses | E71: =+E27+E29+E31+E36+E38+E43+E45+E50+E52+E54+E56+E58+E63+E67+E69 -> 39017.784 | F71: =+F27+F29+F31+F36+F38+F43+F45+F50+F52+F54+F56+F58+F63+F67+F69 -> 38117.404 | G71: =+G27+G29+G31+G36+G38+G43+G45+G50+G52+G54+G56+G58+G63+G67+G69 -> 38744.674 | H71: =+H27+H29+H31+H36+H38+H43+H45+H50+H52+H54+H56+H58+H63+H67+H69 -> 41388.764 | I71: =+I27+I29+I31+I36+I38+I43+I45+I50+I52+I54+I56+I58+I63+I67+I69 -> 37835.804 | J71: =+J27+J29+J31+J36+J38+J43+J45+J50+J52+J54+J56+J58+J63+J67+J69 -> 27697.924 | K71: =+K27+K29+K31+K36+K38+K43+K45+K50+K52+K54+K56+K58+K63+K67+K69 -> 27266.514 | L71: =+L27+L29+L31+L36+L38+L43+L45+L50+L52+L54+L56+L58+L63+L67+L69 -> 49135.994 | ... Q71: =+Q27+Q29+Q31+Q36+Q38+Q43+Q45+Q50+Q52+Q54+Q56+Q58+Q63+Q67+Q69 -> 437186.56 | R71: =Q71/$B$4 -> 7.1004119 | S71: =+S27+S29+S31+S36+S38+S43+S45+S50+S52+S54+S56+S58+S63+S67+S69 -> 424436 | T71: =Q71/S71-1 -> 0.030041192
B73: Non-Reimbursable Expenses
A75: 5210-8501 | C75: Bad Debt | E75: 0 | F75: 0 | G75: 0 | H75: 0 | I75: 0 | J75: 0 | K75: 0 | L75: 0 | M75: 0 | N75: 0 | O75: 0 | P75: 0 | Q75: =SUM(E75:P75) -> 0 | R75: =Q75/$B$4 -> 0 | S75: 0 | T75: =IFERROR(Q75/S75-1,"")
A77: 6010-8501 | D77: Salaries & Wages | E77: =VLOOKUP($B$1,'Allocated Expenses'!$B$20:$P$29,4,FALSE) -> 4578.8694 | F77: =VLOOKUP($B$1,'Allocated Expenses'!$B$20:$P$29,5,FALSE) -> 4578.8694 | G77: =VLOOKUP($B$1,'Allocated Expenses'!$B$20:$P$29,6,FALSE) -> 4578.8694 | H77: =VLOOKUP($B$1,'Allocated Expenses'!$B$20:$P$29,7,FALSE) -> 4578.8694 | I77: =VLOOKUP($B$1,'Allocated Expenses'!$B$20:$P$29,8,FALSE) -> 4578.8694 | J77: =VLOOKUP($B$1,'Allocated Expenses'!$B$20:$P$29,9,FALSE) -> 4578.8694 | K77: =VLOOKUP($B$1,'Allocated Expenses'!$B$20:$P$29,10,FALSE) -> 4578.8694 | L77: =VLOOKUP($B$1,'Allocated Expenses'!$B$20:$P$29,11,FALSE) -> 4578.8694 | M77: =VLOOKUP($B$1,'Allocated Expenses'!$B$20:$P$29,12,FALSE) -> 4578.8694 | N77: =VLOOKUP($B$1,'Allocated Expenses'!$B$20:$P$29,13,FALSE) -> 4578.8694 | O77: =VLOOKUP($B$1,'Allocated Expenses'!$B$20:$P$29,14,FALSE) -> 4578.8694 | P77: =VLOOKUP($B$1,'Allocated Expenses'!$B$20:$P$29,15,FALSE) -> 4578.8694 | Q77: =SUM(E77:P77) -> 54946.432 | R77: =Q77/$B$4 -> 0.89239317
A78: 6620-8501 | D78: Commissions-Internal Broker | E78: =VLOOKUP($B$1,'Allocated Expenses'!$B$132:$P$141,4,FALSE) -> 0 | F78: =VLOOKUP($B$1,'Allocated Expenses'!$B$132:$P$141,5,FALSE) -> 0 | G78: =VLOOKUP($B$1,'Allocated Expenses'!$B$132:$P$141,6,FALSE) -> 0 | H78: =VLOOKUP($B$1,'Allocated Expenses'!$B$132:$P$141,7,FALSE) -> 0 | I78: =VLOOKUP($B$1,'Allocated Expenses'!$B$132:$P$141,8,FALSE) -> 0 | J78: =VLOOKUP($B$1,'Allocated Expenses'!$B$132:$P$141,9,FALSE) -> 0 | K78: =VLOOKUP($B$1,'Allocated Expenses'!$B$132:$P$141,10,FALSE) -> 0 | L78: =VLOOKUP($B$1,'Allocated Expenses'!$B$132:$P$141,11,FALSE) -> 0 | M78: =VLOOKUP($B$1,'Allocated Expenses'!$B$132:$P$141,12,FALSE) -> 0 | N78: =VLOOKUP($B$1,'Allocated Expenses'!$B$132:$P$141,13,FALSE) -> 0 | O78: =VLOOKUP($B$1,'Allocated Expenses'!$B$132:$P$141,14,FALSE) -> 0 | P78: =VLOOKUP($B$1,'Allocated Expenses'!$B$132:$P$141,15,FALSE) -> 0 | Q78: =SUM(E78:P78) -> 0 | R78: =Q78/$B$4 -> 0
C79: Leasing Salaries and Commissions | E79: =SUM(E77:E78) -> 4578.8694 | F79: =SUM(F77:F78) -> 4578.8694 | G79: =SUM(G77:G78) -> 4578.8694 | H79: =SUM(H77:H78) -> 4578.8694 | I79: =SUM(I77:I78) -> 4578.8694 | J79: =SUM(J77:J78) -> 4578.8694 | K79: =SUM(K77:K78) -> 4578.8694 | L79: =SUM(L77:L78) -> 4578.8694 | ... Q79: =SUM(Q77:Q78) -> 54946.432 | R79: =Q79/$B$4 -> 0.89239317 | S79: 64560 | T79: =IFERROR(Q79/S79-1,"") -> -0.14890904
A81: 6110-8501 | D81: Gas | Q81: =SUM(E81:P81) -> 0 | R81: =Q81/$B$4 -> 0
A82: 6120-8501 | D82: Electric | Q82: =SUM(E82:P82) -> 0 | R82: =Q82/$B$4 -> 0
A83: 6130-8501 | D83: Water & Sewer | Q83: =SUM(E83:P83) -> 0 | R83: =Q83/$B$4 -> 0
C84: Utilities | E84: =SUM(E81:E83) -> 0 | F84: =SUM(F81:F83) -> 0 | G84: =SUM(G81:G83) -> 0 | H84: =SUM(H81:H83) -> 0 | I84: =SUM(I81:I83) -> 0 | J84: =SUM(J81:J83) -> 0 | K84: =SUM(K81:K83) -> 0 | L84: =SUM(L81:L83) -> 0 | ... Q84: =SUM(Q81:Q83) -> 0 | R84: =Q84/$B$4 -> 0 | S84: 18 | T84: =IFERROR(Q84/S84-1,"") -> -1
D86: Building Maint.-Recurring | E86: =1.03*150 -> 154.5 | F86: =1.03*150 -> 154.5 | G86: =1.03*150 -> 154.5 | H86: =1.03*150 -> 154.5 | I86: =1.03*150 -> 154.5 | J86: =1.03*150 -> 154.5 | K86: =1.03*150 -> 154.5 | L86: =1.03*150 -> 154.5 | ... P86: =1.03*150 -> 154.5 | Q86: =SUM(E86:P86) -> 1854 | R86: =Q86/$B$4 -> 0.030111089 | U86: DW | V86: 2025 Business Plan grown 3%
D87: Building Maint.-Big Projects | Q87: =SUM(E87:P87) -> 0 | R87: =Q87/$B$4 -> 0
A88: 6220-8501 | C88: Building Maintenance | E88: =SUM(E86:E87) -> 154.5 | F88: =SUM(F86:F87) -> 154.5 | G88: =SUM(G86:G87) -> 154.5 | H88: =SUM(H86:H87) -> 154.5 | I88: =SUM(I86:I87) -> 154.5 | J88: =SUM(J86:J87) -> 154.5 | K88: =SUM(K86:K87) -> 154.5 | L88: =SUM(L86:L87) -> 154.5 | ... Q88: =SUM(Q86:Q87) -> 1854 | R88: =Q88/$B$4 -> 0.030111089 | S88: 1837 | T88: =IFERROR(Q88/S88-1,"") -> 0.0092542188
A90: 6610-8501 | B90: (SC) | C90: Management fee | E90: =ROUND(E$24*0.06,0) -> 7752 | F90: =ROUND(F$24*0.06,0) -> 7752 | G90: =ROUND(G$24*0.06,0) -> 7779 | H90: =ROUND(H$24*0.06,0) -> 7779 | I90: =ROUND(I$24*0.06,0) -> 7779 | J90: =ROUND(J$24*0.06,0) -> 7787 | K90: =ROUND(K$24*0.06,0) -> 7793 | L90: =ROUND(L$24*0.06,0) -> 7793 | ... P90: =ROUND(P$24*0.06,0) -> 7793 | Q90: =SUM(E90:P90) -> 93386 | R90: =Q90/$B$4 -> 1.5166959 | S90: 88291 | T90: =IFERROR(Q90/S90-1,"") -> 0.057706901
T91: =IFERROR(Q91/S91-1,"")
A92: 7110-8501 | C92: Marketing | E92: =VLOOKUP($B$1,'Allocated Expenses'!$B$34:$P$43,4,FALSE)+VLOOKUP($B$1,'Allocated Expenses'!$B$48:$P$57,4,FALSE) -> 1364.6828 | F92: =VLOOKUP($B$1,'Allocated Expenses'!$B$34:$P$43,5,FALSE)+VLOOKUP($B$1,'Allocated Expenses'!$B$48:$P$57,5,FALSE) -> 1364.6828 | G92: =VLOOKUP($B$1,'Allocated Expenses'!$B$34:$P$43,6,FALSE)+VLOOKUP($B$1,'Allocated Expenses'!$B$48:$P$57,6,FALSE) -> 1364.6828 | H92: =VLOOKUP($B$1,'Allocated Expenses'!$B$34:$P$43,7,FALSE)+VLOOKUP($B$1,'Allocated Expenses'!$B$48:$P$57,7,FALSE) -> 1364.6828 | I92: =VLOOKUP($B$1,'Allocated Expenses'!$B$34:$P$43,8,FALSE)+VLOOKUP($B$1,'Allocated Expenses'!$B$48:$P$57,8,FALSE) -> 1364.6828 | J92: =VLOOKUP($B$1,'Allocated Expenses'!$B$34:$P$43,9,FALSE)+VLOOKUP($B$1,'Allocated Expenses'!$B$48:$P$57,9,FALSE) -> 1364.6828 | K92: =VLOOKUP($B$1,'Allocated Expenses'!$B$34:$P$43,10,FALSE)+VLOOKUP($B$1,'Allocated Expenses'!$B$48:$P$57,10,FALSE) -> 1364.6828 | L92: =VLOOKUP($B$1,'Allocated Expenses'!$B$34:$P$43,11,FALSE)+VLOOKUP($B$1,'Allocated Expenses'!$B$48:$P$57,11,FALSE) -> 1364.6828 | M92: =VLOOKUP($B$1,'Allocated Expenses'!$B$34:$P$43,12,FALSE)+VLOOKUP($B$1,'Allocated Expenses'!$B$48:$P$57,12,FALSE) -> 1364.6828 | N92: =VLOOKUP($B$1,'Allocated Expenses'!$B$34:$P$43,13,FALSE)+VLOOKUP($B$1,'Allocated Expenses'!$B$48:$P$57,13,FALSE) -> 1364.6828 | O92: =VLOOKUP($B$1,'Allocated Expenses'!$B$34:$P$43,14,FALSE)+VLOOKUP($B$1,'Allocated Expenses'!$B$48:$P$57,14,FALSE) -> 1364.6828 | P92: =VLOOKUP($B$1,'Allocated Expenses'!$B$34:$P$43,15,FALSE)+VLOOKUP($B$1,'Allocated Expenses'!$B$48:$P$57,15,FALSE) -> 1364.6828 | Q92: =SUM(E92:P92) -> 16376.194 | R92: =Q92/$B$4 -> 0.26596819 | S92: 7200 | T92: =IFERROR(Q92/S92-1,"") -> 1.2744713
A94: 8210-8501 | C94: Business Taxes | E94: 0 | F94: 0 | G94: 0 | H94: =1.03*3600 -> 3708 | I94: 0 | J94: 0 | K94: 0 | L94: 0 | M94: 0 | N94: 0 | O94: 0 | P94: 0 | Q94: =SUM(E94:P94) -> 3708 | R94: =Q94/$B$4 -> 0.060222179 | S94: 3656 | T94: =IFERROR(Q94/S94-1,"") -> 0.014223195 | U94: DW | V94: 2025 Business Plan grown 3%
A96: 8310-8501 | C96: Legal & Accounting | E96: =VLOOKUP($B$1,'Allocated Expenses'!$B$62:$P$71,4,FALSE) -> 386.25 | F96: =VLOOKUP($B$1,'Allocated Expenses'!$B$62:$P$71,5,FALSE) -> 386.25 | G96: =VLOOKUP($B$1,'Allocated Expenses'!$B$62:$P$71,6,FALSE) -> 386.25 | H96: =VLOOKUP($B$1,'Allocated Expenses'!$B$62:$P$71,7,FALSE) -> 386.25 | I96: =VLOOKUP($B$1,'Allocated Expenses'!$B$62:$P$71,8,FALSE) -> 386.25 | J96: =VLOOKUP($B$1,'Allocated Expenses'!$B$62:$P$71,9,FALSE) -> 386.25 | K96: =VLOOKUP($B$1,'Allocated Expenses'!$B$62:$P$71,10,FALSE) -> 386.25 | L96: =VLOOKUP($B$1,'Allocated Expenses'!$B$62:$P$71,11,FALSE) -> 386.25 | M96: =VLOOKUP($B$1,'Allocated Expenses'!$B$62:$P$71,12,FALSE) -> 386.25 | N96: =VLOOKUP($B$1,'Allocated Expenses'!$B$62:$P$71,13,FALSE) -> 386.25 | O96: =VLOOKUP($B$1,'Allocated Expenses'!$B$62:$P$71,14,FALSE) -> 386.25 | P96: =VLOOKUP($B$1,'Allocated Expenses'!$B$62:$P$71,15,FALSE) -> 386.25 | Q96: =SUM(E96:P96) -> 4635 | R96: =Q96/$B$4 -> 0.075277724 | S96: 5289 | T96: =IFERROR(Q96/S96-1,"") -> -0.12365286
A98: 8190-8501 | D98: Bank Fees | E98: =VLOOKUP($B$1,'Allocated Expenses'!$B$76:$P$85,4,FALSE) -> 159.65 | F98: =VLOOKUP($B$1,'Allocated Expenses'!$B$76:$P$85,5,FALSE) -> 159.65 | G98: =VLOOKUP($B$1,'Allocated Expenses'!$B$76:$P$85,6,FALSE) -> 159.65 | H98: =VLOOKUP($B$1,'Allocated Expenses'!$B$76:$P$85,7,FALSE) -> 159.65 | I98: =VLOOKUP($B$1,'Allocated Expenses'!$B$76:$P$85,8,FALSE) -> 159.65 | J98: =VLOOKUP($B$1,'Allocated Expenses'!$B$76:$P$85,9,FALSE) -> 159.65 | K98: =VLOOKUP($B$1,'Allocated Expenses'!$B$76:$P$85,10,FALSE) -> 159.65 | L98: =VLOOKUP($B$1,'Allocated Expenses'!$B$76:$P$85,11,FALSE) -> 159.65 | M98: =VLOOKUP($B$1,'Allocated Expenses'!$B$76:$P$85,12,FALSE) -> 159.65 | N98: =VLOOKUP($B$1,'Allocated Expenses'!$B$76:$P$85,13,FALSE) -> 159.65 | O98: =VLOOKUP($B$1,'Allocated Expenses'!$B$76:$P$85,14,FALSE) -> 159.65 | P98: =VLOOKUP($B$1,'Allocated Expenses'!$B$76:$P$85,15,FALSE) -> 159.65 | Q98: =SUM(E98:P98) -> 1915.8 | R98: =Q98/$B$4 -> 0.031114792
A99: 8930-8501 | D99: Office Supplies | E99: =VLOOKUP($B$1,'Allocated Expenses'!$B$104:$P$113,4,FALSE) -> 0 | F99: =VLOOKUP($B$1,'Allocated Expenses'!$B$104:$P$113,5,FALSE) -> 0 | G99: =VLOOKUP($B$1,'Allocated Expenses'!$B$104:$P$113,6,FALSE) -> 0 | H99: =VLOOKUP($B$1,'Allocated Expenses'!$B$104:$P$113,7,FALSE) -> 0 | I99: =VLOOKUP($B$1,'Allocated Expenses'!$B$104:$P$113,8,FALSE) -> 0 | J99: =VLOOKUP($B$1,'Allocated Expenses'!$B$104:$P$113,9,FALSE) -> 0 | K99: =VLOOKUP($B$1,'Allocated Expenses'!$B$104:$P$113,10,FALSE) -> 0 | L99: =VLOOKUP($B$1,'Allocated Expenses'!$B$104:$P$113,11,FALSE) -> 0 | M99: =VLOOKUP($B$1,'Allocated Expenses'!$B$104:$P$113,12,FALSE) -> 0 | N99: =VLOOKUP($B$1,'Allocated Expenses'!$B$104:$P$113,13,FALSE) -> 0 | O99: =VLOOKUP($B$1,'Allocated Expenses'!$B$104:$P$113,14,FALSE) -> 0 | P99: =VLOOKUP($B$1,'Allocated Expenses'!$B$104:$P$113,15,FALSE) -> 0 | Q99: =SUM(E99:P99) -> 0 | R99: =Q99/$B$4 -> 0
A100: 8950-8501 | D100: Postage | E100: =VLOOKUP($B$1,'Allocated Expenses'!$B$90:$P$99,4,FALSE) -> 0 | F100: =VLOOKUP($B$1,'Allocated Expenses'!$B$90:$P$99,5,FALSE) -> 0 | G100: =VLOOKUP($B$1,'Allocated Expenses'!$B$90:$P$99,6,FALSE) -> 0 | H100: =VLOOKUP($B$1,'Allocated Expenses'!$B$90:$P$99,7,FALSE) -> 0 | I100: =VLOOKUP($B$1,'Allocated Expenses'!$B$90:$P$99,8,FALSE) -> 0 | J100: =VLOOKUP($B$1,'Allocated Expenses'!$B$90:$P$99,9,FALSE) -> 0 | K100: =VLOOKUP($B$1,'Allocated Expenses'!$B$90:$P$99,10,FALSE) -> 0 | L100: =VLOOKUP($B$1,'Allocated Expenses'!$B$90:$P$99,11,FALSE) -> 0 | M100: =VLOOKUP($B$1,'Allocated Expenses'!$B$90:$P$99,12,FALSE) -> 0 | N100: =VLOOKUP($B$1,'Allocated Expenses'!$B$90:$P$99,13,FALSE) -> 0 | O100: =VLOOKUP($B$1,'Allocated Expenses'!$B$90:$P$99,14,FALSE) -> 0 | P100: =VLOOKUP($B$1,'Allocated Expenses'!$B$90:$P$99,15,FALSE) -> 0 | Q100: =SUM(E100:P100) -> 0 | R100: =Q100/$B$4 -> 0
A101: 8990-8501 | D101: Other G&A Expense | Q101: =SUM(E101:P101) -> 0 | R101: =Q101/$B$4 -> 0
A102: 8990-9800 | D102: Other G&A-allocated from LIK | E102: =VLOOKUP($B$1,'Allocated Expenses'!$B$118:$P$127,4,FALSE) -> 175.95833 | F102: =VLOOKUP($B$1,'Allocated Expenses'!$B$118:$P$127,5,FALSE) -> 175.95833 | G102: =VLOOKUP($B$1,'Allocated Expenses'!$B$118:$P$127,6,FALSE) -> 175.95833 | H102: =VLOOKUP($B$1,'Allocated Expenses'!$B$118:$P$127,7,FALSE) -> 175.95833 | I102: =VLOOKUP($B$1,'Allocated Expenses'!$B$118:$P$127,8,FALSE) -> 175.95833 | J102: =VLOOKUP($B$1,'Allocated Expenses'!$B$118:$P$127,9,FALSE) -> 175.95833 | K102: =VLOOKUP($B$1,'Allocated Expenses'!$B$118:$P$127,10,FALSE) -> 175.95833 | L102: =VLOOKUP($B$1,'Allocated Expenses'!$B$118:$P$127,11,FALSE) -> 175.95833 | M102: =VLOOKUP($B$1,'Allocated Expenses'!$B$118:$P$127,12,FALSE) -> 175.95833 | N102: =VLOOKUP($B$1,'Allocated Expenses'!$B$118:$P$127,13,FALSE) -> 175.95833 | O102: =VLOOKUP($B$1,'Allocated Expenses'!$B$118:$P$127,14,FALSE) -> 175.95833 | P102: =VLOOKUP($B$1,'Allocated Expenses'!$B$118:$P$127,15,FALSE) -> 175.95833 | Q102: =SUM(E102:P102) -> 2111.5 | R102: =Q102/$B$4 -> 0.034293185
C103: General & Administrative | E103: =SUM(E98:E102) -> 335.60833 | F103: =SUM(F98:F102) -> 335.60833 | G103: =SUM(G98:G102) -> 335.60833 | H103: =SUM(H98:H102) -> 335.60833 | I103: =SUM(I98:I102) -> 335.60833 | J103: =SUM(J98:J102) -> 335.60833 | K103: =SUM(K98:K102) -> 335.60833 | L103: =SUM(L98:L102) -> 335.60833 | ... Q103: =SUM(Q98:Q102) -> 4027.3 | R103: =Q103/$B$4 -> 0.065407978 | S103: 26305 | T103: =IFERROR(Q103/S103-1,"") -> -0.84689983
C105: Total Non-Reimbursable Expenses | E105: =+E75+E79+E84+E88+E90+E92+E94+E96+E103 -> 14571.911 | F105: =+F75+F79+F84+F88+F90+F92+F94+F96+F103 -> 14571.911 | G105: =+G75+G79+G84+G88+G90+G92+G94+G96+G103 -> 14598.911 | H105: =+H75+H79+H84+H88+H90+H92+H94+H96+H103 -> 18306.911 | I105: =+I75+I79+I84+I88+I90+I92+I94+I96+I103 -> 14598.911 | J105: =+J75+J79+J84+J88+J90+J92+J94+J96+J103 -> 14606.911 | K105: =+K75+K79+K84+K88+K90+K92+K94+K96+K103 -> 14612.911 | L105: =+L75+L79+L84+L88+L90+L92+L94+L96+L103 -> 14612.911 | ... Q105: =+Q75+Q79+Q84+Q88+Q90+Q92+Q94+Q96+Q103 -> 178932.93 | R105: =Q105/$B$4 -> 2.9060762 | S105: =+S75+S79+S84+S88+S90+S92+S94+S96+S103 -> 197156 | T105: =IFERROR(Q105/S105-1,"") -> -0.09242972
B108: TOTAL OPERATING EXPENSES | E108: =+E71+E105 -> 53589.695 | F108: =+F71+F105 -> 52689.315 | G108: =+G71+G105 -> 53343.585 | H108: =+H71+H105 -> 59695.675 | I108: =+I71+I105 -> 52434.715 | J108: =+J71+J105 -> 42304.835 | K108: =+K71+K105 -> 41879.425 | L108: =+L71+L105 -> 63748.905 | ... Q108: =+Q71+Q105 -> 616119.49 | R108: =Q108/$B$4 -> 10.006488 | S108: =+S71+S105 -> 621592 | T108: =Q108/S108-1 -> -0.0088040231
B111: NET OPERATING INCOME | E111: =+E24-E108 -> 75606.915 | F111: =+F24-F108 -> 76507.295 | G111: =+G24-G108 -> 76303.025 | H111: =+H24-H108 -> 69950.935 | I111: =+I24-I108 -> 77211.895 | J111: =+J24-J108 -> 87475.105 | K111: =+K24-K108 -> 88006.935 | L111: =+L24-L108 -> 66137.455 | ... Q111: =+Q24-Q108 -> 940311.66 | R111: =Q111/$B$4 -> 15.271741 | S111: =+S24-S108 -> 989723 | T111: =Q111/S111-1 -> -0.049924413
A113: 1420-0000 | D113: Land Improvements | Q113: =SUM(E113:P113) -> 0 | R113: =Q113/$B$4 -> 0
A114: 1430-0000 | D114: Buildings | Q114: =SUM(E114:P114) -> 0 | R114: =Q114/$B$4 -> 0
A115: 1450-0000 | D115: Equipment | Q115: =SUM(E115:P115) -> 0 | R115: =Q115/$B$4 -> 0
A116: 1980-8501 | D116: Capital Improvements | Q116: =SUM(E116:P116) -> 0 | R116: =Q116/$B$4 -> 0
C117: Capital Improvements | E117: =SUM(E113:E116) -> 0 | F117: =SUM(F113:F116) -> 0 | G117: =SUM(G113:G116) -> 0 | H117: =SUM(H113:H116) -> 0 | I117: =SUM(I113:I116) -> 0 | J117: =SUM(J113:J116) -> 0 | K117: =SUM(K113:K116) -> 0 | L117: =SUM(L113:L116) -> 0 | ... Q117: =SUM(Q113:Q116) -> 0 | R117: =Q117/$B$4 -> 0 | S117: 25376 | T117: =IFERROR(Q117/S117-1,"") -> -1
A119: 1440-0000 | C119: Tenant Improvements | E119: ='Renew & Vac '!AJ55 -> 0 | F119: ='Renew & Vac '!AK55 -> 0 | G119: ='Renew & Vac '!AL55 -> 0 | H119: ='Renew & Vac '!AM55 -> 0 | I119: ='Renew & Vac '!AN55 -> 0 | J119: ='Renew & Vac '!AO55 -> 0 | K119: ='Renew & Vac '!AP55 -> 0 | L119: ='Renew & Vac '!AQ55 -> 0 | ... P119: ='Renew & Vac '!AU55 -> 0 | Q119: =SUM(E119:P119) -> 0 | R119: =Q119/$B$4 -> 0 | T119: =IFERROR(Q119/S119-1,"")
A121: 1940-8501 | D121: Deferred Marketing | Q121: =SUM(E121:P121) -> 0 | R121: =Q121/$B$4 -> 0
A122: 1940-8501 | D122: Outside Leasing Commissions | E122: ='Renew & Vac '!AJ56 -> 0 | F122: ='Renew & Vac '!AK56 -> 0 | G122: ='Renew & Vac '!AL56 -> 0 | H122: ='Renew & Vac '!AM56 -> 0 | I122: ='Renew & Vac '!AN56 -> 0 | J122: ='Renew & Vac '!AO56 -> 0 | K122: ='Renew & Vac '!AP56 -> 0 | L122: ='Renew & Vac '!AQ56 -> 0 | ... P122: ='Renew & Vac '!AU56 -> 0 | Q122: =SUM(E122:P122) -> 0 | R122: =Q122/$B$4 -> 0
C123: Outside Leasing Commissions | E123: =SUM(E121:E122) -> 0 | F123: =SUM(F121:F122) -> 0 | G123: =SUM(G121:G122) -> 0 | H123: =SUM(H121:H122) -> 0 | I123: =SUM(I121:I122) -> 0 | J123: =SUM(J121:J122) -> 0 | K123: =SUM(K121:K122) -> 0 | L123: =SUM(L121:L122) -> 0 | ... Q123: =SUM(Q121:Q122) -> 0 | R123: =Q123/$B$4 -> 0 | T123: =IFERROR(Q123/S123-1,"")
B125: CASH FLOW BEFORE DEBT SERVICE | E125: =+E111-E117-E119-E123 -> 75606.915 | F125: =+F111-F117-F119-F123 -> 76507.295 | G125: =+G111-G117-G119-G123 -> 76303.025 | H125: =+H111-H117-H119-H123 -> 69950.935 | I125: =+I111-I117-I119-I123 -> 77211.895 | J125: =+J111-J117-J119-J123 -> 87475.105 | K125: =+K111-K117-K119-K123 -> 88006.935 | L125: =+L111-L117-L119-L123 -> 66137.455 | ... Q125: =+Q111-Q117-Q119-Q123 -> 940311.66 | R125: =Q125/$B$4 -> 15.271741 | S125: =+S111-S117-S119-S123 -> 964347 | T125: =Q125/S125-1 -> -0.024923953
B127: Debt Service
A128: 9210-8501 | C128: Interest | E128: =VLOOKUP($B$1,'INS RET DEBT'!$C$98:$Q$107,3,FALSE) -> 12479.2 | F128: =VLOOKUP($B$1,'INS RET DEBT'!$C$98:$Q$107,4,FALSE) -> 12442.59 | G128: =VLOOKUP($B$1,'INS RET DEBT'!$C$98:$Q$107,5,FALSE) -> 12405.873 | H128: =VLOOKUP($B$1,'INS RET DEBT'!$C$98:$Q$107,6,FALSE) -> 12369.05 | I128: =VLOOKUP($B$1,'INS RET DEBT'!$C$98:$Q$107,7,FALSE) -> 12332.118 | J128: =VLOOKUP($B$1,'INS RET DEBT'!$C$98:$Q$107,8,FALSE) -> 12295.079 | K128: =VLOOKUP($B$1,'INS RET DEBT'!$C$98:$Q$107,9,FALSE) -> 12257.932 | L128: =VLOOKUP($B$1,'INS RET DEBT'!$C$98:$Q$107,10,FALSE) -> 12220.677 | M128: =VLOOKUP($B$1,'INS RET DEBT'!$C$98:$Q$107,11,FALSE) -> 12183.313 | N128: =VLOOKUP($B$1,'INS RET DEBT'!$C$98:$Q$107,12,FALSE) -> 12145.84 | O128: =VLOOKUP($B$1,'INS RET DEBT'!$C$98:$Q$107,13,FALSE) -> 12108.258 | P128: =VLOOKUP($B$1,'INS RET DEBT'!$C$98:$Q$107,14,FALSE) -> 12070.566 | Q128: =SUM(E128:P128) -> 147310.5 | R128: =Q128/$B$4 -> 2.3924917 | S128: 139511 | T128: =IFERROR(Q128/S128-1,"") -> 0.055905969
A129: 2740-8501 | C129: Mortgage Amortization | E129: =VLOOKUP($B$1,'INS RET DEBT'!$C$113:$Q$122,3,FALSE) -> 12551.979 | F129: =VLOOKUP($B$1,'INS RET DEBT'!$C$113:$Q$122,4,FALSE) -> 12588.588 | G129: =VLOOKUP($B$1,'INS RET DEBT'!$C$113:$Q$122,5,FALSE) -> 12625.305 | H129: =VLOOKUP($B$1,'INS RET DEBT'!$C$113:$Q$122,6,FALSE) -> 12662.129 | I129: =VLOOKUP($B$1,'INS RET DEBT'!$C$113:$Q$122,7,FALSE) -> 12699.06 | J129: =VLOOKUP($B$1,'INS RET DEBT'!$C$113:$Q$122,8,FALSE) -> 12736.099 | K129: =VLOOKUP($B$1,'INS RET DEBT'!$C$113:$Q$122,9,FALSE) -> 12773.246 | L129: =VLOOKUP($B$1,'INS RET DEBT'!$C$113:$Q$122,10,FALSE) -> 12810.501 | M129: =VLOOKUP($B$1,'INS RET DEBT'!$C$113:$Q$122,11,FALSE) -> 12847.865 | N129: =VLOOKUP($B$1,'INS RET DEBT'!$C$113:$Q$122,12,FALSE) -> 12885.338 | O129: =VLOOKUP($B$1,'INS RET DEBT'!$C$113:$Q$122,13,FALSE) -> 12922.921 | P129: =VLOOKUP($B$1,'INS RET DEBT'!$C$113:$Q$122,14,FALSE) -> 12960.612 | Q129: =SUM(E129:P129) -> 153063.64 | R129: =Q129/$B$4 -> 2.4859294 | S129: 135831 | T129: =IFERROR(Q129/S129-1,"") -> 0.12686827
A130: 2740-0000 | C130: Loan Proceeds | Q130: =SUM(E130:P130) -> 0 | R130: =Q130/$B$4 -> 0
C131: Total Debt Service | E131: =SUM(E128:E130) -> 25031.179 | F131: =SUM(F128:F130) -> 25031.179 | G131: =SUM(G128:G130) -> 25031.179 | H131: =SUM(H128:H130) -> 25031.179 | I131: =SUM(I128:I130) -> 25031.179 | J131: =SUM(J128:J130) -> 25031.179 | K131: =SUM(K128:K130) -> 25031.179 | L131: =SUM(L128:L130) -> 25031.179 | ... Q131: =SUM(Q128:Q130) -> 300374.14 | R131: =Q131/$B$4 -> 4.8784211 | S131: =SUM(S128:S129) -> 275342 | T131: =IFERROR(Q131/S131-1,"") -> 0.090912909
B134: CASH FLOW AFTER DEBT SERVICE | E134: =+E125-E131 -> 50575.737 | F134: =+F125-F131 -> 51476.117 | G134: =+G125-G131 -> 51271.847 | H134: =+H125-H131 -> 44919.757 | I134: =+I125-I131 -> 52180.717 | J134: =+J125-J131 -> 62443.927 | K134: =+K125-K131 -> 62975.757 | L134: =+L125-L131 -> 41106.277 | ... Q134: =+Q125-Q131 -> 639937.52 | R134: =Q134/$B$4 -> 10.39332 | S134: =+S125-S131 -> 689005 | T134: =Q134/S134-1 -> -0.071214987
B140: Rental Summary by Month
B141: Suite | D141: Tenant | E141: =E177 -> 46023 | F141: =F177 -> 46054 | G141: =G177 -> 46082 | H141: =H177 -> 46113 | I141: =I177 -> 46143 | J141: =J177 -> 46174 | K141: =K177 -> 46204 | L141: =L177 -> 46235 | ... P141: =P177 -> 46357 | Q141: Total
B142: =B160 -> 2300-1817 | D142: =IF(D160="None",D178,D160) -> M & T Bank | E142: =SUMIF($B$160:$B$172,$B142,E$160:E$172)+SUMIF($B$178:$B$190,$B142,E$178:E$190) -> 11458.33 | F142: =SUMIF($B$160:$B$172,$B142,F$160:F$172)+SUMIF($B$178:$B$190,$B142,F$178:F$190) -> 11458.33 | G142: =SUMIF($B$160:$B$172,$B142,G$160:G$172)+SUMIF($B$178:$B$190,$B142,G$178:G$190) -> 11458.33 | H142: =SUMIF($B$160:$B$172,$B142,H$160:H$172)+SUMIF($B$178:$B$190,$B142,H$178:H$190) -> 11458.33 | I142: =SUMIF($B$160:$B$172,$B142,I$160:I$172)+SUMIF($B$178:$B$190,$B142,I$178:I$190) -> 11458.33 | J142: =SUMIF($B$160:$B$172,$B142,J$160:J$172)+SUMIF($B$178:$B$190,$B142,J$178:J$190) -> 11458.33 | K142: =SUMIF($B$160:$B$172,$B142,K$160:K$172)+SUMIF($B$178:$B$190,$B142,K$178:K$190) -> 11458.08 | L142: =SUMIF($B$160:$B$172,$B142,L$160:L$172)+SUMIF($B$178:$B$190,$B142,L$178:L$190) -> 11458.08 | ... P142: =SUMIF($B$160:$B$172,$B142,P$160:P$172)+SUMIF($B$178:$B$190,$B142,P$178:P$190) -> 11458.08 | Q142: =SUM(E142:P142) -> 137498.46
B143: =B161 -> 2300-1847 | D143: =IF(D161="None",D179,D161) -> Crafty Crab | E143: =SUMIF($B$160:$B$172,$B143,E$160:E$172)+SUMIF($B$178:$B$190,$B143,E$178:E$190) -> 12759 | F143: =SUMIF($B$160:$B$172,$B143,F$160:F$172)+SUMIF($B$178:$B$190,$B143,F$178:F$190) -> 12759 | G143: =SUMIF($B$160:$B$172,$B143,G$160:G$172)+SUMIF($B$178:$B$190,$B143,G$178:G$190) -> 12759 | H143: =SUMIF($B$160:$B$172,$B143,H$160:H$172)+SUMIF($B$178:$B$190,$B143,H$178:H$190) -> 12759 | I143: =SUMIF($B$160:$B$172,$B143,I$160:I$172)+SUMIF($B$178:$B$190,$B143,I$178:I$190) -> 12759 | J143: =SUMIF($B$160:$B$172,$B143,J$160:J$172)+SUMIF($B$178:$B$190,$B143,J$178:J$190) -> 12759 | K143: =SUMIF($B$160:$B$172,$B143,K$160:K$172)+SUMIF($B$178:$B$190,$B143,K$178:K$190) -> 12759 | L143: =SUMIF($B$160:$B$172,$B143,L$160:L$172)+SUMIF($B$178:$B$190,$B143,L$178:L$190) -> 12759 | ... P143: =SUMIF($B$160:$B$172,$B143,P$160:P$172)+SUMIF($B$178:$B$190,$B143,P$178:P$190) -> 12759 | Q143: =SUM(E143:P143) -> 153108
B144: =B162 -> 2300-1851 | D144: =IF(D162="None",D180,D162) -> National Fitness Partners | E144: =SUMIF($B$160:$B$172,$B144,E$160:E$172)+SUMIF($B$178:$B$190,$B144,E$178:E$190) -> 20603.28 | F144: =SUMIF($B$160:$B$172,$B144,F$160:F$172)+SUMIF($B$178:$B$190,$B144,F$178:F$190) -> 20603.28 | G144: =SUMIF($B$160:$B$172,$B144,G$160:G$172)+SUMIF($B$178:$B$190,$B144,G$178:G$190) -> 20603.28 | H144: =SUMIF($B$160:$B$172,$B144,H$160:H$172)+SUMIF($B$178:$B$190,$B144,H$178:H$190) -> 20603.28 | I144: =SUMIF($B$160:$B$172,$B144,I$160:I$172)+SUMIF($B$178:$B$190,$B144,I$178:I$190) -> 20603.28 | J144: =SUMIF($B$160:$B$172,$B144,J$160:J$172)+SUMIF($B$178:$B$190,$B144,J$178:J$190) -> 20603.28 | K144: =SUMIF($B$160:$B$172,$B144,K$160:K$172)+SUMIF($B$178:$B$190,$B144,K$178:K$190) -> 20603.28 | L144: =SUMIF($B$160:$B$172,$B144,L$160:L$172)+SUMIF($B$178:$B$190,$B144,L$178:L$190) -> 20603.28 | ... P144: =SUMIF($B$160:$B$172,$B144,P$160:P$172)+SUMIF($B$178:$B$190,$B144,P$178:P$190) -> 20603.28 | Q144: =SUM(E144:P144) -> 247239.36
B145: =B163 -> 2300-1861 | D145: =IF(D163="None",D181,D163) -> Edible Arrangements | E145: =SUMIF($B$160:$B$172,$B145,E$160:E$172)+SUMIF($B$178:$B$190,$B145,E$178:E$190) -> 4583 | F145: =SUMIF($B$160:$B$172,$B145,F$160:F$172)+SUMIF($B$178:$B$190,$B145,F$178:F$190) -> 4583 | G145: =SUMIF($B$160:$B$172,$B145,G$160:G$172)+SUMIF($B$178:$B$190,$B145,G$178:G$190) -> 4833 | H145: =SUMIF($B$160:$B$172,$B145,H$160:H$172)+SUMIF($B$178:$B$190,$B145,H$178:H$190) -> 4833 | I145: =SUMIF($B$160:$B$172,$B145,I$160:I$172)+SUMIF($B$178:$B$190,$B145,I$178:I$190) -> 4833 | J145: =SUMIF($B$160:$B$172,$B145,J$160:J$172)+SUMIF($B$178:$B$190,$B145,J$178:J$190) -> 4833 | K145: =SUMIF($B$160:$B$172,$B145,K$160:K$172)+SUMIF($B$178:$B$190,$B145,K$178:K$190) -> 4833 | L145: =SUMIF($B$160:$B$172,$B145,L$160:L$172)+SUMIF($B$178:$B$190,$B145,L$178:L$190) -> 4833 | ... P145: =SUMIF($B$160:$B$172,$B145,P$160:P$172)+SUMIF($B$178:$B$190,$B145,P$178:P$190) -> 4833 | Q145: =SUM(E145:P145) -> 57496
...

Sheet 4500
B1: 4500 | C1: - Gray's Ferry Shopping Center | J1: =+'2300'!J1 -> Operating Budget | Q1: ='All Shopping Centers'!Q1 -> 46023
J2: ='All Shopping Centers'!J2&" - "&B1 -> Shopping Centers - 4500
S3: 9/2025 Reprojections
B4: 82809 | E4: Jan | F4: Feb | G4: Mar | H4: Apr | I4: May | J4: Jun | K4: Jul | L4: Aug | M4: Sep | N4: Oct | O4: Nov | P4: Dec | Q4: Total | R4: Total PSF | S4: Total | T4: Var. | U4: Input | V4: Notes
D6: Occupancy % | E6: ='Renew & Vac '!AJ75 -> 0.971 | F6: ='Renew & Vac '!AK75 -> 0.971 | G6: ='Renew & Vac '!AL75 -> 0.971 | H6: ='Renew & Vac '!AM75 -> 0.971 | I6: ='Renew & Vac '!AN75 -> 1 | J6: ='Renew & Vac '!AO75 -> 1 | K6: ='Renew & Vac '!AP75 -> 1 | L6: ='Renew & Vac '!AQ75 -> 1 | ... P6: ='Renew & Vac '!AU75 -> 1
D7: Occupancy SF | E7: =$B$4*E6 -> 80407.539 | F7: =$B$4*F6 -> 80407.539 | G7: =$B$4*G6 -> 80407.539 | H7: =$B$4*H6 -> 80407.539 | I7: =$B$4*I6 -> 82809 | J7: =$B$4*J6 -> 82809 | K7: =$B$4*K6 -> 82809 | L7: =$B$4*L6 -> 82809 | ... P7: =$B$4*P6 -> 82809
B8: Revenues
A10: 4230-8501 | C10: Rental Income - In Place | E10: =SUMIFS('In Place Revenue'!$G:$G,'In Place Revenue'!$A:$A,$B$1,'In Place Revenue'!$H:$H,1) -> 123600.01 | F10: =SUMIFS('In Place Revenue'!$G:$G,'In Place Revenue'!$A:$A,$B$1,'In Place Revenue'!$H:$H,2) -> 123600.01 | G10: =SUMIFS('In Place Revenue'!$G:$G,'In Place Revenue'!$A:$A,$B$1,'In Place Revenue'!$H:$H,3) -> 123600.01 | H10: =SUMIFS('In Place Revenue'!$G:$G,'In Place Revenue'!$A:$A,$B$1,'In Place Revenue'!$H:$H,4) -> 123600.01 | I10: =SUMIFS('In Place Revenue'!$G:$G,'In Place Revenue'!$A:$A,$B$1,'In Place Revenue'!$H:$H,5) -> 123600.01 | J10: =SUMIFS('In Place Revenue'!$G:$G,'In Place Revenue'!$A:$A,$B$1,'In Place Revenue'!$H:$H,6) -> 123600.01 | K10: =SUMIFS('In Place Revenue'!$G:$G,'In Place Revenue'!$A:$A,$B$1,'In Place Revenue'!$H:$H,7) -> 123600.01 | L10: =SUMIFS('In Place Revenue'!$G:$G,'In Place Revenue'!$A:$A,$B$1,'In Place Revenue'!$H:$H,8) -> 123600.01 | M10: =SUMIFS('In Place Revenue'!$G:$G,'In Place Revenue'!$A:$A,$B$1,'In Place Revenue'!$H:$H,9) -> 123600.01 | N10: =SUMIFS('In Place Revenue'!$G:$G,'In Place Revenue'!$A:$A,$B$1,'In Place Revenue'!$H:$H,10) -> 123600.01 | O10: =SUMIFS('In Place Revenue'!$G:$G,'In Place Revenue'!$A:$A,$B$1,'In Place Revenue'!$H:$H,11) -> 133286.67 | P10: =SUMIFS('In Place Revenue'!$G:$G,'In Place Revenue'!$A:$A,$B$1,'In Place Revenue'!$H:$H,12) -> 133286.67 | Q10: =SUM(E10:P10) -> 1502573.4 | R10: =Q10/$B$4 -> 18.14505 | S10: 1439251 | T10: =(Q10+Q11)/S10-1 -> 0.072900724
A11: 4230-8501 | C11: Rental Income - New & Renewal | E11: ='Renew & Vac '!AJ76 -> 0 | F11: ='Renew & Vac '!AK76 -> 0 | G11: ='Renew & Vac '!AL76 -> 0 | H11: ='Renew & Vac '!AM76 -> 0 | I11: ='Renew & Vac '!AN76 -> 5200 | J11: ='Renew & Vac '!AO76 -> 5200 | K11: ='Renew & Vac '!AP76 -> 5200 | L11: ='Renew & Vac '!AQ76 -> 5200 | ... P11: ='Renew & Vac '!AU76 -> 5200 | Q11: =SUM(E11:P11) -> 41600 | R11: =Q11/$B$4 -> 0.50236085
A12: 4240-8501 | C12: Percentage Rents | Q12: =SUM(E12:P12) -> 0 | R12: =Q12/$B$4 -> 0 | S12: 0 | T12: =IFERROR(Q12/S12-1,"")
A13: 4990-8501 | C13: Miscellaneous | E13: =1.03*10224.24 -> 10530.967 | F13: =1.03*10224.24 -> 10530.967 | G13: =1.03*10224.24 -> 10530.967 | H13: =1.03*10224.24 -> 10530.967 | I13: =1.03*10224.24 -> 10530.967 | J13: =1.03*10224.24 -> 10530.967 | K13: =1.03*10224.24 -> 10530.967 | L13: =1.03*10224.24 -> 10530.967 | ... P13: =1.03*10224.24 -> 10530.967 | Q13: =SUM(E13:P13) -> 126371.61 | R13: =Q13/$B$4 -> 1.5260613 | S13: 125144 | T13: =IFERROR(Q13/S13-1,"") -> 0.0098095506 | U13: DW | V13: 2025 Business Plan grown 3%
A14: 9190-8501 | C14: Interest Income | E14: =1.03*89 -> 91.67 | F14: =1.03*89 -> 91.67 | G14: =1.03*89 -> 91.67 | H14: =1.03*89 -> 91.67 | I14: =1.03*89 -> 91.67 | J14: =1.03*89 -> 91.67 | K14: =1.03*89 -> 91.67 | L14: =1.03*89 -> 91.67 | ... P14: =1.03*89 -> 91.67 | Q14: =SUM(E14:P14) -> 1100.04 | R14: =Q14/$B$4 -> 0.013284063 | S14: 16693 | T14: =IFERROR(Q14/S14-1,"") -> -0.93410172 | U14: DW | V14: 2025 Business Plan grown 3%
C15: Total Rental and Other | E15: =SUM(E10:E14) -> 134222.65 | F15: =SUM(F10:F14) -> 134222.65 | G15: =SUM(G10:G14) -> 134222.65 | H15: =SUM(H10:H14) -> 134222.65 | I15: =SUM(I10:I14) -> 139422.65 | J15: =SUM(J10:J14) -> 139422.65 | K15: =SUM(K10:K14) -> 139422.65 | L15: =SUM(L10:L14) -> 139422.65 | ... Q15: =SUM(Q10:Q14) -> 1671645.1 | R15: =Q15/$B$4 -> 20.186756 | S15: =SUM(S10:S14) -> 1581088 | T15: =Q15/S15-1 -> 0.057275172
B17: Reimbursements
A18: 4710-8502 | C18: Electric | Q18: =SUM(E18:P18) -> 0 | R18: =Q18/$B$4 -> 0 | S18: 0 | T18: =IFERROR(Q18/S18-1,"")
A19: 4910-8502 | C19: Common Area Maintenance | E19: =+'Tenant Recoveries'!H26 -> 30500 | F19: =+E19 -> 30500 | G19: =+F19 -> 30500 | H19: =+G19 -> 30500 | I19: =+H19 -> 30500 | J19: =+I19 -> 30500 | K19: =+J19 -> 30500 | L19: =+K19 -> 30500 | M19: =+L19 -> 30500 | ... P19: =+O19 -> 30500 | Q19: =SUM(E19:P19) -> 366000 | R19: =Q19/$B$4 -> 4.4198094 | S19: 341379 | T19: =IFERROR(Q19/S19-1,"") -> 0.072122187
A20: 4920-8502 | C20: Real Estate Taxes | E20: =+'Tenant Recoveries'!H27 -> 15100 | F20: =+E20 -> 15100 | G20: =+F20 -> 15100 | H20: =+G20 -> 15100 | I20: =+H20 -> 15100 | J20: =+I20 -> 15100 | K20: =+J20 -> 15100 | L20: =+K20 -> 15100 | M20: =+L20 -> 15100 | ... P20: =+O20 -> 15100 | Q20: =SUM(E20:P20) -> 181200 | R20: =Q20/$B$4 -> 2.188168 | S20: 127932 | T20: =IFERROR(Q20/S20-1,"") -> 0.41637745
A21: 4930-8502 | C21: Insurance | E21: ='Tenant Recoveries'!H24 -> 10365 | Q21: =SUM(E21:P21) -> 10365 | R21: =Q21/$B$4 -> 0.12516755 | S21: 9004 | T21: =IFERROR(Q21/S21-1,"") -> 0.15115504
C22: Total Reimbursements | E22: =SUM(E18:E21) -> 55965 | F22: =SUM(F18:F21) -> 45600 | G22: =SUM(G18:G21) -> 45600 | H22: =SUM(H18:H21) -> 45600 | I22: =SUM(I18:I21) -> 45600 | J22: =SUM(J18:J21) -> 45600 | K22: =SUM(K18:K21) -> 45600 | L22: =SUM(L18:L21) -> 45600 | ... Q22: =SUM(Q18:Q21) -> 557565 | R22: =Q22/$B$4 -> 6.7331449 | S22: =SUM(S18:S21) -> 478315 | T22: =Q22/S22-1 -> 0.16568579
R23: =Q23/$B$4 -> 0
